{
  "type": "Feature",
  "properties": {
    "gn:admin1_code":"15.0",
    "gn:asciiname":"Ban Vangduanha",
    "gn:country_code":"LA",
    "gn:dem":191,
    "gn:feature_class":"P",
    "gn:feature_code":"PPL",
    "gn:name":"Ban Vangduanha",
    "gn:population":0,
    "gn:timezone":"Asia/Vientiane",
    "iso:country":"LA",
    "name:und_x_variant":[
        "Ban Vangduongha",
        "Ban Vangduanha"
    ],
    "wof:name":"Ban Vangduanha",
    "wof:placetype":"locality"
},
  "geometry": {"coordinates":[105.31837,17.16702],"type":"Point"}
}