{
  "type": "Feature",
  "properties": {
    "gn:admin1_code":"23.0",
    "gn:asciiname":"Ban Kokfuang",
    "gn:country_code":"LA",
    "gn:dem":437,
    "gn:feature_class":"P",
    "gn:feature_code":"PPL",
    "gn:name":"Ban K\u00f4kfuang",
    "gn:population":0,
    "gn:timezone":"Asia/Vientiane",
    "iso:country":"LA",
    "name:und_x_variant":[
        "Ban Coc Phuong",
        "Ban K\u00f4kfuang"
    ],
    "wof:name":"Ban Kokfuang",
    "wof:placetype":"locality"
},
  "geometry": {"coordinates":[104.73182,18.38341],"type":"Point"}
}