{
  "type": "Feature",
  "properties": {
    "gn:admin1_code":"17.0",
    "gn:asciiname":"Ban Houay Sek",
    "gn:cc2":"LA",
    "gn:country_code":"LA",
    "gn:dem":595,
    "gn:feature_class":"P",
    "gn:feature_code":"PPL",
    "gn:name":"Ban Houay S\u00e8k",
    "gn:population":0,
    "gn:timezone":"Asia/Vientiane",
    "iso:country":"LA",
    "name:und_x_variant":[
        "Ban S\u00e8n Kam",
        "Ban Houe\u00ef S\u00e9k",
        "Ban Houay S\u00e8k"
    ],
    "wof:name":"Ban Houay Sek",
    "wof:placetype":"locality"
},
  "geometry": {"coordinates":[102.51667,19.93333],"type":"Point"}
}