{
  "type": "Feature",
  "properties": {
    "gn:admin1_code":"2.0",
    "gn:asciiname":"Ban Muangsen-Tai",
    "gn:country_code":"LA",
    "gn:dem":91,
    "gn:feature_class":"P",
    "gn:feature_code":"PPL",
    "gn:name":"Ban Muangs\u00e8n-Tai",
    "gn:population":0,
    "gn:timezone":"Asia/Vientiane",
    "iso:country":"LA",
    "name:lao_x_preferred":[
        "Ban Muangs\u00e8n-Tai"
    ],
    "wof:name":"Ban Muangsen-Tai",
    "wof:placetype":"locality"
},
  "geometry": {"coordinates":[105.79591000000001,14.09255],"type":"Point"}
}