{
  "type": "Feature",
  "properties": {
    "gn:admin1_code":"17.0",
    "gn:asciiname":"Ban Phon",
    "gn:country_code":"LA",
    "gn:dem":325,
    "gn:feature_class":"P",
    "gn:feature_code":"PPL",
    "gn:name":"Ban Ph\u00f4n",
    "gn:population":0,
    "gn:timezone":"Asia/Vientiane",
    "iso:country":"LA",
    "name:lao_x_preferred":[
        "Ban Ph\u00f4n"
    ],
    "wof:name":"Ban Phon",
    "wof:placetype":"locality"
},
  "geometry": {"coordinates":[101.86211,19.49495],"type":"Point"}
}