{
  "type": "Feature",
  "properties": {
    "gn:admin1_code":"17.0",
    "gn:asciiname":"Ban Thapho",
    "gn:country_code":"LA",
    "gn:dem":379,
    "gn:feature_class":"P",
    "gn:feature_code":"PPL",
    "gn:name":"Ban Thaph\u00f4",
    "gn:population":0,
    "gn:timezone":"Asia/Vientiane",
    "iso:country":"LA",
    "name:lao_x_preferred":[
        "Ban Thaph\u00f4"
    ],
    "wof:name":"Ban Thapho",
    "wof:placetype":"locality"
},
  "geometry": {"coordinates":[102.44875,19.94401],"type":"Point"}
}