{
  "type": "Feature",
  "properties": {
    "gn:admin1_code":"20.0",
    "gn:asciiname":"Ban Dongkhamkhen",
    "gn:country_code":"LA",
    "gn:dem":167,
    "gn:feature_class":"P",
    "gn:feature_code":"PPL",
    "gn:name":"Ban D\u00f4ngkhamkh\u00e8n",
    "gn:population":0,
    "gn:timezone":"Asia/Vientiane",
    "iso:country":"LA",
    "name:und_x_variant":[
        "Ban Kham Kheme",
        "Ban D\u00f4ngkhamkh\u00e8n"
    ],
    "wof:name":"Ban Dongkhamkhen",
    "wof:placetype":"locality"
},
  "geometry": {"coordinates":[105.10413,16.56861],"type":"Point"}
}