{
  "type": "Feature",
  "properties": {
    "gn:admin1_code":"28.0",
    "gn:asciiname":"Ban Muangphoun",
    "gn:country_code":"LA",
    "gn:dem":1114,
    "gn:feature_class":"P",
    "gn:feature_code":"PPL",
    "gn:name":"Ban Muangphoun",
    "gn:population":0,
    "gn:timezone":"Asia/Vientiane",
    "iso:country":"LA",
    "name:und_x_variant":[
        "Muong Poun",
        "Muang Phoun",
        "Ban Muangphoun"
    ],
    "wof:name":"Ban Muangphoun",
    "wof:placetype":"locality"
},
  "geometry": {"coordinates":[102.71424,19.09843],"type":"Point"}
}