{
  "type": "Feature",
  "properties": {
    "gn:admin1_code":"7.0",
    "gn:asciiname":"Ban Chomphou",
    "gn:country_code":"LA",
    "gn:dem":762,
    "gn:feature_class":"P",
    "gn:feature_code":"PPL",
    "gn:name":"Ban Chomphou",
    "gn:population":0,
    "gn:timezone":"Asia/Vientiane",
    "iso:country":"LA",
    "name:lao_x_preferred":[
        "Ban Chomphou"
    ],
    "wof:name":"Ban Chomphou",
    "wof:placetype":"locality"
},
  "geometry": {"coordinates":[101.08922,19.95544],"type":"Point"}
}