{
  "type": "Feature",
  "properties": {
    "gn:admin1_code":"26.0",
    "gn:asciiname":"Ban Tanglou",
    "gn:country_code":"LA",
    "gn:dem":408,
    "gn:feature_class":"P",
    "gn:feature_code":"PPL",
    "gn:name":"Ban Tanglou",
    "gn:population":0,
    "gn:timezone":"Asia/Vientiane",
    "iso:country":"LA",
    "name:und_x_variant":[
        "Ban Tang",
        "Ban Tanglou"
    ],
    "wof:name":"Ban Tanglou",
    "wof:placetype":"locality"
},
  "geometry": {"coordinates":[106.82262,15.77744],"type":"Point"}
}