{
  "type": "Feature",
  "properties": {
    "gn:admin1_code":"19.0",
    "gn:asciiname":"Ban Paxingpaloy",
    "gn:country_code":"LA",
    "gn:dem":579,
    "gn:feature_class":"P",
    "gn:feature_code":"PPL",
    "gn:name":"Ban Paxingpaloy",
    "gn:population":0,
    "gn:timezone":"Asia/Vientiane",
    "iso:country":"LA",
    "name:lao_x_preferred":[
        "Ban Paxingpaloy"
    ],
    "wof:name":"Ban Paxingpaloy",
    "wof:placetype":"locality"
},
  "geometry": {"coordinates":[106.51085,16.05284],"type":"Point"}
}