{
  "type": "Feature",
  "properties": {
    "gn:admin1_code":"15.0",
    "gn:asciiname":"Ban Chakouan",
    "gn:country_code":"LA",
    "gn:dem":169,
    "gn:feature_class":"P",
    "gn:feature_code":"PPL",
    "gn:name":"Ban Chakouan",
    "gn:population":0,
    "gn:timezone":"Asia/Vientiane",
    "iso:country":"LA",
    "name:und_x_variant":[
        "Ban Chakhouane",
        "Ban Chakouan"
    ],
    "wof:name":"Ban Chakouan",
    "wof:placetype":"locality"
},
  "geometry": {"coordinates":[105.53538,17.47392],"type":"Point"}
}