{
  "type": "Feature",
  "properties": {
    "gn:admin1_code":"7.0",
    "gn:asciiname":"Ban Xianglek",
    "gn:country_code":"LA",
    "gn:dem":1571,
    "gn:feature_class":"P",
    "gn:feature_code":"PPL",
    "gn:name":"Ban Xiangl\u00e8k",
    "gn:population":0,
    "gn:timezone":"Asia/Vientiane",
    "iso:country":"LA",
    "name:lao_x_preferred":[
        "Ban Xiangl\u00e8k"
    ],
    "name:und_x_variant":[
        "Ban Xiangt\u00e8k"
    ],
    "wof:name":"Ban Xianglek",
    "wof:placetype":"locality"
},
  "geometry": {"coordinates":[101.42383,19.92817],"type":"Point"}
}