{
  "type": "Feature",
  "properties": {
    "gn:admin1_code":"20.0",
    "gn:asciiname":"Ban Salai",
    "gn:country_code":"LA",
    "gn:dem":185,
    "gn:feature_class":"P",
    "gn:feature_code":"PPL",
    "gn:name":"Ban Salai",
    "gn:population":0,
    "gn:timezone":"Asia/Vientiane",
    "iso:country":"LA",
    "name:und_x_variant":[
        "Ban Sea Raye",
        "Ban Salai"
    ],
    "wof:name":"Ban Salai",
    "wof:placetype":"locality"
},
  "geometry": {"coordinates":[106.17276,16.43308],"type":"Point"}
}