{
  "type": "Feature",
  "properties": {
    "gn:admin1_code":"19.0",
    "gn:asciiname":"Ban Dondou",
    "gn:country_code":"LA",
    "gn:dem":673,
    "gn:feature_class":"P",
    "gn:feature_code":"PPL",
    "gn:name":"Ban Dondou",
    "gn:population":0,
    "gn:timezone":"Asia/Vientiane",
    "iso:country":"LA",
    "name:lao_x_preferred":[
        "Ban Dondou"
    ],
    "wof:name":"Ban Dondou",
    "wof:placetype":"locality"
},
  "geometry": {"coordinates":[106.23733,15.44564],"type":"Point"}
}