{
  "type": "Feature",
  "properties": {
    "gn:admin1_code":"2.0",
    "gn:asciiname":"Ban Campi",
    "gn:country_code":"LA",
    "gn:dem":110,
    "gn:feature_class":"P",
    "gn:feature_code":"PPL",
    "gn:name":"Ban Campi",
    "gn:population":0,
    "gn:timezone":"Asia/Vientiane",
    "iso:country":"LA",
    "name:lao_x_preferred":[
        "Ban Campi"
    ],
    "name:und_x_variant":[
        "Ban Champi"
    ],
    "wof:name":"Ban Campi",
    "wof:placetype":"locality"
},
  "geometry": {"coordinates":[105.81786,15.26667],"type":"Point"}
}