{
  "type": "Feature",
  "properties": {
    "gn:admin1_code":"28.0",
    "gn:asciiname":"Phiali",
    "gn:country_code":"LA",
    "gn:dem":1173,
    "gn:feature_class":"P",
    "gn:feature_code":"PPL",
    "gn:name":"Phiali",
    "gn:population":0,
    "gn:timezone":"Asia/Vientiane",
    "iso:country":"LA",
    "name:und_x_variant":[
        "Pie Li",
        "Phiali"
    ],
    "wof:name":"Phiali",
    "wof:placetype":"locality"
},
  "geometry": {"coordinates":[102.75,19.26667],"type":"Point"}
}