{
  "type": "Feature",
  "properties": {
    "gn:admin1_code":"16.0",
    "gn:asciiname":"Ban Tavan-Tai",
    "gn:country_code":"LA",
    "gn:dem":602,
    "gn:feature_class":"P",
    "gn:feature_code":"PPL",
    "gn:name":"Ban Tavan-Tai",
    "gn:population":0,
    "gn:timezone":"Asia/Vientiane",
    "iso:country":"LA",
    "name:lao_x_preferred":[
        "Ban Tavan-Tai"
    ],
    "wof:name":"Ban Tavan-Tai",
    "wof:placetype":"locality"
},
  "geometry": {"coordinates":[101.47548999999999,20.97727],"type":"Point"}
}