{
  "type": "Feature",
  "properties": {
    "gn:admin1_code":"17.0",
    "gn:asciiname":"Ban Mokpalou",
    "gn:country_code":"LA",
    "gn:dem":892,
    "gn:feature_class":"P",
    "gn:feature_code":"PPL",
    "gn:name":"Ban M\u00f4kpalou",
    "gn:population":0,
    "gn:timezone":"Asia/Vientiane",
    "iso:country":"LA",
    "name:lao_x_preferred":[
        "Ban M\u00f4kpalou"
    ],
    "wof:name":"Ban Mokpalou",
    "wof:placetype":"locality"
},
  "geometry": {"coordinates":[102.27422,20.4996],"type":"Point"}
}