{
  "type": "Feature",
  "properties": {
    "gn:admin1_code":"1.0",
    "gn:asciiname":"Ban Hinlat-Tai",
    "gn:country_code":"LA",
    "gn:dem":87,
    "gn:feature_class":"P",
    "gn:feature_code":"PPL",
    "gn:name":"Ban Hinlat-Tai",
    "gn:population":0,
    "gn:timezone":"Asia/Vientiane",
    "iso:country":"LA",
    "name:lao_x_preferred":[
        "Ban Hinlat-Tai"
    ],
    "wof:name":"Ban Hinlat-Tai",
    "wof:placetype":"locality"
},
  "geometry": {"coordinates":[106.48642,14.7209],"type":"Point"}
}