{
  "type": "Feature",
  "properties": {
    "gn:admin1_code":"17.0",
    "gn:asciiname":"Ban Houay-En",
    "gn:country_code":"LA",
    "gn:dem":347,
    "gn:feature_class":"P",
    "gn:feature_code":"PPL",
    "gn:name":"Ban Houay-En",
    "gn:population":0,
    "gn:timezone":"Asia/Vientiane",
    "iso:country":"LA",
    "name:lao_x_preferred":[
        "Ban Houay-En"
    ],
    "wof:name":"Ban Houay-En",
    "wof:placetype":"locality"
},
  "geometry": {"coordinates":[102.58723999999999,20.47022],"type":"Point"}
}