{
  "type": "Feature",
  "properties": {
    "gn:admin1_code":"3.0",
    "gn:asciiname":"Ban Sengket",
    "gn:country_code":"LA",
    "gn:dem":1137,
    "gn:feature_class":"P",
    "gn:feature_code":"PPL",
    "gn:name":"Ban S\u00eangk\u00e9t",
    "gn:population":0,
    "gn:timezone":"Asia/Vientiane",
    "iso:country":"LA",
    "name:lao_x_preferred":[
        "Ban S\u00eangk\u00e9t"
    ],
    "wof:name":"Ban Sengket",
    "wof:placetype":"locality"
},
  "geometry": {"coordinates":[103.9473,19.99547],"type":"Point"}
}