{
  "type": "Feature",
  "properties": {
    "gn:admin1_code":"17.0",
    "gn:asciiname":"Ban Senlat",
    "gn:country_code":"LA",
    "gn:dem":846,
    "gn:feature_class":"P",
    "gn:feature_code":"PPL",
    "gn:name":"Ban S\u00e8nlat",
    "gn:population":0,
    "gn:timezone":"Asia/Vientiane",
    "iso:country":"LA",
    "name:und_x_variant":[
        "Ban Hoi Len",
        "Ban S\u00e8nlat"
    ],
    "wof:name":"Ban Senlat",
    "wof:placetype":"locality"
},
  "geometry": {"coordinates":[102.44974000000001,19.89372],"type":"Point"}
}