{
  "type": "Feature",
  "properties": {
    "gn:admin1_code":"19.0",
    "gn:asciiname":"Ban Tagneuk",
    "gn:country_code":"LA",
    "gn:dem":325,
    "gn:feature_class":"P",
    "gn:feature_code":"PPL",
    "gn:name":"Ban Tagneuk",
    "gn:population":0,
    "gn:timezone":"Asia/Vientiane",
    "iso:country":"LA",
    "name:lao_x_preferred":[
        "Ban Tagneuk"
    ],
    "wof:name":"Ban Tagneuk",
    "wof:placetype":"locality"
},
  "geometry": {"coordinates":[106.26007,16.13722000000001],"type":"Point"}
}