{
  "type": "Feature",
  "properties": {
    "gn:admin1_code":"1.0",
    "gn:asciiname":"Ban Cheng-Gnai",
    "gn:country_code":"LA",
    "gn:dem":96,
    "gn:feature_class":"P",
    "gn:feature_code":"PPL",
    "gn:name":"Ban Cheng-Gnai",
    "gn:population":0,
    "gn:timezone":"Asia/Vientiane",
    "iso:country":"LA",
    "name:lao_x_preferred":[
        "Ban Cheng-Gnai"
    ],
    "name:und_x_variant":[
        "Ban Cheng Tay",
        "Ban Ch\u00e9ng Tai"
    ],
    "wof:name":"Ban Cheng-Gnai",
    "wof:placetype":"locality"
},
  "geometry": {"coordinates":[106.64012,14.73181],"type":"Point"}
}