{
  "type": "Feature",
  "properties": {
    "gn:admin1_code":"22.0",
    "gn:asciiname":"Ban Lakha",
    "gn:country_code":"LA",
    "gn:dem":769,
    "gn:feature_class":"P",
    "gn:feature_code":"PPL",
    "gn:name":"Ban Lakha",
    "gn:population":0,
    "gn:timezone":"Asia/Vientiane",
    "iso:country":"LA",
    "name:lao_x_preferred":[
        "Ban Lakha"
    ],
    "wof:name":"Ban Lakha",
    "wof:placetype":"locality"
},
  "geometry": {"coordinates":[101.1923,20.23709],"type":"Point"}
}