{
  "type": "Feature",
  "properties": {
    "gn:admin1_code":"14.0",
    "gn:asciiname":"Ban Phonhom",
    "gn:country_code":"LA",
    "gn:dem":750,
    "gn:feature_class":"P",
    "gn:feature_code":"PPL",
    "gn:name":"Ban Ph\u00f4nh\u00f4m",
    "gn:population":0,
    "gn:timezone":"Asia/Vientiane",
    "iso:country":"LA",
    "name:lao_x_preferred":[
        "Ban Ph\u00f4nh\u00f4m"
    ],
    "wof:name":"Ban Phonhom",
    "wof:placetype":"locality"
},
  "geometry": {"coordinates":[103.51221,19.53243],"type":"Point"}
}