{
  "type": "Feature",
  "properties": {
    "gn:admin1_code":"20.0",
    "gn:asciiname":"Ban Soplouan",
    "gn:country_code":"LA",
    "gn:dem":284,
    "gn:feature_class":"P",
    "gn:feature_code":"PPL",
    "gn:name":"Ban S\u00f4plouan",
    "gn:population":0,
    "gn:timezone":"Asia/Vientiane",
    "iso:country":"LA",
    "name:lao_x_preferred":[
        "Ban S\u00f4plouan"
    ],
    "wof:name":"Ban Soplouan",
    "wof:placetype":"locality"
},
  "geometry": {"coordinates":[106.45786,16.89587],"type":"Point"}
}