{
  "type": "Feature",
  "properties": {
    "gn:admin1_code":"17.0",
    "gn:asciiname":"Ban Laosao",
    "gn:country_code":"LA",
    "gn:dem":1267,
    "gn:feature_class":"P",
    "gn:feature_code":"PPL",
    "gn:name":"Ban Laosao",
    "gn:population":0,
    "gn:timezone":"Asia/Vientiane",
    "iso:country":"LA",
    "name:lao_x_preferred":[
        "Ban Laosao"
    ],
    "wof:name":"Ban Laosao",
    "wof:placetype":"locality"
},
  "geometry": {"coordinates":[102.74736,20.45465],"type":"Point"}
}