{
  "type": "Feature",
  "properties": {
    "gn:admin1_code":"2.0",
    "gn:asciiname":"Ban Khansouanmon",
    "gn:country_code":"LA",
    "gn:dem":112,
    "gn:feature_class":"P",
    "gn:feature_code":"PPL",
    "gn:name":"Ban Khansouanmon",
    "gn:population":0,
    "gn:timezone":"Asia/Vientiane",
    "iso:country":"LA",
    "name:lao_x_preferred":[
        "Ban Khansouanmon"
    ],
    "name:und_x_variant":[
        "Ban K\u00e8ngsan\u00f4m"
    ],
    "wof:name":"Ban Khansouanmon",
    "wof:placetype":"locality"
},
  "geometry": {"coordinates":[105.80668,15.25162],"type":"Point"}
}