{
  "type": "Feature",
  "properties": {
    "gn:admin1_code":"17.0",
    "gn:asciiname":"Ban Hat-Ong",
    "gn:country_code":"LA",
    "gn:dem":528,
    "gn:feature_class":"P",
    "gn:feature_code":"PPL",
    "gn:name":"Ban Hat-Ong",
    "gn:population":0,
    "gn:timezone":"Asia/Vientiane",
    "iso:country":"LA",
    "name:lao_x_preferred":[
        "Ban Hat-Ong"
    ],
    "wof:name":"Ban Hat-Ong",
    "wof:placetype":"locality"
},
  "geometry": {"coordinates":[103.02933,20.6588],"type":"Point"}
}