{
  "type": "Feature",
  "properties": {
    "gn:admin1_code":"2.0",
    "gn:asciiname":"Ban Saman",
    "gn:country_code":"LA",
    "gn:dem":107,
    "gn:feature_class":"P",
    "gn:feature_code":"PPL",
    "gn:name":"Ban Saman",
    "gn:population":0,
    "gn:timezone":"Asia/Vientiane",
    "iso:country":"LA",
    "name:und_x_variant":[
        "Ban Samanh",
        "Ban Saman"
    ],
    "wof:name":"Ban Saman",
    "wof:placetype":"locality"
},
  "geometry": {"coordinates":[105.69347,15.18184],"type":"Point"}
}