{
  "type": "Feature",
  "properties": {
    "gn:admin1_code":"13.0",
    "gn:asciiname":"Ban Namlouak",
    "gn:country_code":"LA",
    "gn:dem":356,
    "gn:feature_class":"P",
    "gn:feature_code":"PPL",
    "gn:name":"Ban Namlouak",
    "gn:population":0,
    "gn:timezone":"Asia/Vientiane",
    "iso:country":"LA",
    "name:lao_x_preferred":[
        "Ban Namlouak"
    ],
    "wof:name":"Ban Namlouak",
    "wof:placetype":"locality"
},
  "geometry": {"coordinates":[101.49216,18.96426],"type":"Point"}
}