{
  "type": "Feature",
  "properties": {
    "gn:admin1_code":"2.0",
    "gn:asciiname":"Ban Phoudon",
    "gn:country_code":"LA",
    "gn:dem":95,
    "gn:feature_class":"P",
    "gn:feature_code":"PPL",
    "gn:name":"Ban Phoud\u00f4n",
    "gn:population":0,
    "gn:timezone":"Asia/Vientiane",
    "iso:country":"LA",
    "name:und_x_variant":[
        "Ban Phou Done",
        "Ban Pho Done",
        "Ban Phoud\u00f4n"
    ],
    "wof:name":"Ban Phoudon",
    "wof:placetype":"locality"
},
  "geometry": {"coordinates":[105.88333,14.15],"type":"Point"}
}