{
  "type": "Feature",
  "properties": {
    "gn:admin1_code":"7.0",
    "gn:asciiname":"Ban Yang",
    "gn:country_code":"LA",
    "gn:dem":761,
    "gn:feature_class":"P",
    "gn:feature_code":"PPL",
    "gn:name":"Ban Yang",
    "gn:population":0,
    "gn:timezone":"Asia/Vientiane",
    "iso:country":"LA",
    "name:ceb_x_preferred":[
        "Ban Yang"
    ],
    "name:und_x_variant":[
        "Houay Yang"
    ],
    "wof:name":"Ban Yang",
    "wof:placetype":"locality"
},
  "geometry": {"coordinates":[101.96831,20.79371],"type":"Point"}
}