{
  "type": "Feature",
  "properties": {
    "gn:admin1_code":"20.0",
    "gn:asciiname":"Ban Kenghouapa",
    "gn:country_code":"LA",
    "gn:dem":187,
    "gn:feature_class":"P",
    "gn:feature_code":"PPL",
    "gn:name":"Ban K\u00e8nghouapa",
    "gn:population":0,
    "gn:timezone":"Asia/Vientiane",
    "iso:country":"LA",
    "name:und_x_variant":[
        "Ban Keng Hoapa",
        "Ban K\u00e8nghouapa"
    ],
    "wof:name":"Ban Kenghouapa",
    "wof:placetype":"locality"
},
  "geometry": {"coordinates":[106.19692000000001,16.67126],"type":"Point"}
}