{
  "type": "Feature",
  "properties": {
    "gn:admin1_code":"19.0",
    "gn:asciiname":"Ban Natabeng",
    "gn:country_code":"LA",
    "gn:dem":139,
    "gn:feature_class":"P",
    "gn:feature_code":"PPL",
    "gn:name":"Ban Natab\u00e8ng",
    "gn:population":0,
    "gn:timezone":"Asia/Vientiane",
    "iso:country":"LA",
    "name:lao_x_preferred":[
        "Ban Natab\u00e8ng"
    ],
    "wof:name":"Ban Natabeng",
    "wof:placetype":"locality"
},
  "geometry": {"coordinates":[105.72359,15.51483],"type":"Point"}
}