{
  "type": "Feature",
  "properties": {
    "gn:admin1_code":"3.0",
    "gn:asciiname":"Ban Leuy",
    "gn:country_code":"LA",
    "gn:dem":418,
    "gn:feature_class":"P",
    "gn:feature_code":"PPL",
    "gn:name":"Ban Leuy",
    "gn:population":0,
    "gn:timezone":"Asia/Vientiane",
    "iso:country":"LA",
    "name:lao_x_preferred":[
        "Ban Leuy"
    ],
    "wof:name":"Ban Leuy",
    "wof:placetype":"locality"
},
  "geometry": {"coordinates":[104.54922000000001,20.31304],"type":"Point"}
}