{
  "type": "Feature",
  "properties": {
    "gn:admin1_code":"14.0",
    "gn:asciiname":"Ban Tinphalen Noy",
    "gn:country_code":"LA",
    "gn:dem":1487,
    "gn:feature_class":"P",
    "gn:feature_code":"PPL",
    "gn:name":"Ban Tinphal\u00e9n Noy",
    "gn:population":0,
    "gn:timezone":"Asia/Vientiane",
    "iso:country":"LA",
    "wof:name":"Ban Tinphalen Noy",
    "wof:placetype":"locality"
},
  "geometry": {"coordinates":[103.91667,19.55],"type":"Point"}
}