{
  "type": "Feature",
  "properties": {
    "gn:admin1_code":"3.0",
    "gn:asciiname":"Ban Sampakha",
    "gn:country_code":"LA",
    "gn:dem":851,
    "gn:feature_class":"P",
    "gn:feature_code":"PPL",
    "gn:name":"Ban Sampakha",
    "gn:population":0,
    "gn:timezone":"Asia/Vientiane",
    "iso:country":"LA",
    "name:lao_x_preferred":[
        "Ban Sampakha"
    ],
    "wof:name":"Ban Sampakha",
    "wof:placetype":"locality"
},
  "geometry": {"coordinates":[103.4036,20.15614],"type":"Point"}
}