{
  "type": "Feature",
  "properties": {
    "gn:admin1_code":"26.0",
    "gn:asciiname":"Ban Tahit-Tai",
    "gn:country_code":"LA",
    "gn:dem":578,
    "gn:feature_class":"P",
    "gn:feature_code":"PPL",
    "gn:name":"Ban Tahit-Tai",
    "gn:population":0,
    "gn:timezone":"Asia/Vientiane",
    "iso:country":"LA",
    "name:lao_x_preferred":[
        "Ban Tahit-Tai"
    ],
    "wof:name":"Ban Tahit-Tai",
    "wof:placetype":"locality"
},
  "geometry": {"coordinates":[107.08099,15.84575],"type":"Point"}
}