{
  "type": "Feature",
  "properties": {
    "gn:admin1_code":"7.0",
    "gn:asciiname":"Ban Chomleng",
    "gn:country_code":"LA",
    "gn:dem":900,
    "gn:feature_class":"P",
    "gn:feature_code":"PPL",
    "gn:name":"Ban Choml\u00e8ng",
    "gn:population":0,
    "gn:timezone":"Asia/Vientiane",
    "iso:country":"LA",
    "wof:name":"Ban Chomleng",
    "wof:placetype":"locality"
},
  "geometry": {"coordinates":[101.54917,20.01667],"type":"Point"}
}