{
  "type": "Feature",
  "properties": {
    "gn:admin1_code":"15.0",
    "gn:asciiname":"Ban Kabong",
    "gn:country_code":"LA",
    "gn:dem":199,
    "gn:feature_class":"P",
    "gn:feature_code":"PPL",
    "gn:name":"Ban Kab\u00f4ng",
    "gn:population":0,
    "gn:timezone":"Asia/Vientiane",
    "iso:country":"LA",
    "name:lao_x_preferred":[
        "Ban Kab\u00f4ng"
    ],
    "wof:name":"Ban Kabong",
    "wof:placetype":"locality"
},
  "geometry": {"coordinates":[105.52188999999998,17.19938],"type":"Point"}
}