{
  "type": "Feature",
  "properties": {
    "gn:admin1_code":"13.0",
    "gn:asciiname":"Ban Muangpa",
    "gn:country_code":"LA",
    "gn:dem":299,
    "gn:feature_class":"P",
    "gn:feature_code":"PPL",
    "gn:name":"Ban Muangpa",
    "gn:population":0,
    "gn:timezone":"Asia/Vientiane",
    "iso:country":"LA",
    "name:lao_x_preferred":[
        "Ban Muangpa"
    ],
    "name:und_x_variant":[
        "Muong Pa",
        "Muang Pa"
    ],
    "wof:name":"Ban Muangpa",
    "wof:placetype":"locality"
},
  "geometry": {"coordinates":[101.59999999999999,18.55],"type":"Point"}
}