{
  "type": "Feature",
  "properties": {
    "gn:admin1_code":"3.0",
    "gn:asciiname":"Ban Kenpha",
    "gn:country_code":"LA",
    "gn:dem":819,
    "gn:feature_class":"P",
    "gn:feature_code":"PPL",
    "gn:name":"Ban K\u00e8npha",
    "gn:population":0,
    "gn:timezone":"Asia/Vientiane",
    "iso:country":"LA",
    "name:dan_x_preferred":[
        "Ban Kenpha"
    ],
    "name:und_x_variant":[
        "Ban K\u00e8npha"
    ],
    "wof:name":"Ban Kenpha",
    "wof:placetype":"locality"
},
  "geometry": {"coordinates":[103.28570999999999,20.53288],"type":"Point"}
}