{
  "type": "Feature",
  "properties": {
    "gn:admin1_code":"18.0",
    "gn:asciiname":"Ban Xioulixou",
    "gn:country_code":"LA",
    "gn:dem":857,
    "gn:feature_class":"P",
    "gn:feature_code":"PPL",
    "gn:name":"Ban Xioulixou",
    "gn:population":0,
    "gn:timezone":"Asia/Vientiane",
    "iso:country":"LA",
    "name:lao_x_preferred":[
        "Ban Xioulixou"
    ],
    "wof:name":"Ban Xioulixou",
    "wof:placetype":"locality"
},
  "geometry": {"coordinates":[102.01201,22.17849],"type":"Point"}
}