{
  "type": "Feature",
  "properties": {
    "gn:admin1_code":"17.0",
    "gn:asciiname":"Ban Houay-En",
    "gn:country_code":"LA",
    "gn:dem":937,
    "gn:feature_class":"P",
    "gn:feature_code":"PPL",
    "gn:name":"Ban Houay-En",
    "gn:population":0,
    "gn:timezone":"Asia/Vientiane",
    "iso:country":"LA",
    "name:und_x_variant":[
        "Ban Houay Va",
        "Ban Houei Va",
        "Ban Houay-En"
    ],
    "wof:name":"Ban Houay-En",
    "wof:placetype":"locality"
},
  "geometry": {"coordinates":[102.75664,20.26273],"type":"Point"}
}