{
  "type": "Feature",
  "properties": {
    "gn:admin1_code":"2.0",
    "gn:asciiname":"Ban Houayvay",
    "gn:country_code":"LA",
    "gn:dem":1085,
    "gn:feature_class":"P",
    "gn:feature_code":"PPL",
    "gn:name":"Ban Houayvay",
    "gn:population":0,
    "gn:timezone":"Asia/Vientiane",
    "iso:country":"LA",
    "name:lao_x_preferred":[
        "Ban Houayvay"
    ],
    "wof:name":"Ban Houayvay",
    "wof:placetype":"locality"
},
  "geometry": {"coordinates":[106.32074,15.31323],"type":"Point"}
}