{
  "type": "Feature",
  "properties": {
    "gn:admin1_code":"27.0",
    "gn:asciiname":"Ban Houaysing",
    "gn:country_code":"LA",
    "gn:dem":371,
    "gn:feature_class":"P",
    "gn:feature_code":"PPL",
    "gn:name":"Ban Houaysing",
    "gn:population":0,
    "gn:timezone":"Asia/Vientiane",
    "iso:country":"LA",
    "name:lao_x_preferred":[
        "Ban Houaysing"
    ],
    "wof:name":"Ban Houaysing",
    "wof:placetype":"locality"
},
  "geometry": {"coordinates":[102.58228,18.88057],"type":"Point"}
}