{
  "type": "Feature",
  "properties": {
    "gn:admin1_code":"2.0",
    "gn:asciiname":"Ban Koutchik",
    "gn:country_code":"LA",
    "gn:dem":127,
    "gn:feature_class":"P",
    "gn:feature_code":"PPL",
    "gn:name":"Ban Koutchik",
    "gn:population":0,
    "gn:timezone":"Asia/Vientiane",
    "iso:country":"LA",
    "wof:name":"Ban Koutchik",
    "wof:placetype":"locality"
},
  "geometry": {"coordinates":[105.71145,14.97698],"type":"Point"}
}