{
  "type": "Feature",
  "properties": {
    "gn:admin1_code":"18.0",
    "gn:asciiname":"Ban Pangkhai-Nua",
    "gn:country_code":"LA",
    "gn:dem":778,
    "gn:feature_class":"P",
    "gn:feature_code":"PPL",
    "gn:name":"Ban Pangkhai-Nua",
    "gn:population":0,
    "gn:timezone":"Asia/Vientiane",
    "iso:country":"LA",
    "name:lao_x_preferred":[
        "Ban Pangkhai-Nua"
    ],
    "wof:name":"Ban Pangkhai-Nua",
    "wof:placetype":"locality"
},
  "geometry": {"coordinates":[101.91027,21.23306],"type":"Point"}
}