{
  "type": "Feature",
  "properties": {
    "gn:admin1_code":"1.0",
    "gn:asciiname":"Ban Namkong",
    "gn:country_code":"LA",
    "gn:dem":91,
    "gn:feature_class":"P",
    "gn:feature_code":"PPL",
    "gn:name":"Ban Namk\u00f4ng",
    "gn:population":0,
    "gn:timezone":"Asia/Vientiane",
    "iso:country":"LA",
    "name:und_x_variant":[
        "Nam Kong",
        "Ban Namk\u00f4ng"
    ],
    "wof:name":"Ban Namkong",
    "wof:placetype":"locality"
},
  "geometry": {"coordinates":[106.58277,14.63452],"type":"Point"}
}