{
  "type": "Feature",
  "properties": {
    "gn:admin1_code":"20.0",
    "gn:asciiname":"Ban Kabao-Nua",
    "gn:country_code":"LA",
    "gn:dem":156,
    "gn:feature_class":"P",
    "gn:feature_code":"PPL",
    "gn:name":"Ban Kabao-Nua",
    "gn:population":0,
    "gn:timezone":"Asia/Vientiane",
    "iso:country":"LA",
    "name:lao_x_preferred":[
        "Ban Kabao-Nua"
    ],
    "name:und_x_variant":[
        "Ban Kabao"
    ],
    "wof:name":"Ban Kabao-Nua",
    "wof:placetype":"locality"
},
  "geometry": {"coordinates":[105.39933000000001,16.46264],"type":"Point"}
}