{
  "type": "Feature",
  "properties": {
    "gn:admin1_code":"20.0",
    "gn:asciiname":"Ban Khilek",
    "gn:country_code":"LA",
    "gn:dem":139,
    "gn:feature_class":"P",
    "gn:feature_code":"PPL",
    "gn:name":"Ban Khil\u00e9k",
    "gn:population":0,
    "gn:timezone":"Asia/Vientiane",
    "iso:country":"LA",
    "name:lao_x_preferred":[
        "Ban Khil\u00e9k"
    ],
    "wof:name":"Ban Khilek",
    "wof:placetype":"locality"
},
  "geometry": {"coordinates":[105.30500000000001,16.0437],"type":"Point"}
}