{
  "type": "Feature",
  "properties": {
    "gn:admin1_code":"22.0",
    "gn:asciiname":"Ban Dan",
    "gn:country_code":"LA",
    "gn:dem":357,
    "gn:feature_class":"P",
    "gn:feature_code":"PPL",
    "gn:name":"Ban Dan",
    "gn:population":0,
    "gn:timezone":"Asia/Vientiane",
    "iso:country":"LA",
    "name:lao_x_preferred":[
        "Ban Dan"
    ],
    "wof:name":"Ban Dan",
    "wof:placetype":"locality"
},
  "geometry": {"coordinates":[100.50557000000001,20.16166],"type":"Point"}
}