{
  "type": "Feature",
  "properties": {
    "gn:admin1_code":"18.0",
    "gn:asciiname":"Ban Nagnao",
    "gn:country_code":"LA",
    "gn:dem":812,
    "gn:feature_class":"P",
    "gn:feature_code":"PPL",
    "gn:name":"Ban Nagnao",
    "gn:population":0,
    "gn:timezone":"Asia/Vientiane",
    "iso:country":"LA",
    "name:lao_x_preferred":[
        "Ban Nagnao"
    ],
    "wof:name":"Ban Nagnao",
    "wof:placetype":"locality"
},
  "geometry": {"coordinates":[101.81453,22.20912],"type":"Point"}
}