{
  "type": "Feature",
  "properties": {
    "gn:admin1_code":"16.0",
    "gn:asciiname":"Ban Konsalay",
    "gn:country_code":"LA",
    "gn:dem":1035,
    "gn:feature_class":"P",
    "gn:feature_code":"PPL",
    "gn:name":"Ban Konsalay",
    "gn:population":0,
    "gn:timezone":"Asia/Vientiane",
    "iso:country":"LA",
    "name:lao_x_preferred":[
        "Ban Konsalay"
    ],
    "wof:name":"Ban Konsalay",
    "wof:placetype":"locality"
},
  "geometry": {"coordinates":[101.25494999999999,20.51644],"type":"Point"}
}