{
  "type": "Feature",
  "properties": {
    "gn:admin1_code":"15.0",
    "gn:asciiname":"Ban Mouanglatkhoay",
    "gn:country_code":"LA",
    "gn:dem":150,
    "gn:feature_class":"P",
    "gn:feature_code":"PPL",
    "gn:name":"Ban Mouanglatkhoay",
    "gn:population":0,
    "gn:timezone":"Asia/Vientiane",
    "iso:country":"LA",
    "name:und_x_variant":[
        "Ban Mouang Lat Khouei",
        "Ban Mouanglatkhoay"
    ],
    "wof:name":"Ban Mouanglatkhoay",
    "wof:placetype":"locality"
},
  "geometry": {"coordinates":[104.90072000000001,17.2896],"type":"Point"}
}