{
  "type": "Feature",
  "properties": {
    "gn:admin1_code":"20.0",
    "gn:asciiname":"Ban Lak Sam Sip Ha",
    "gn:country_code":"LA",
    "gn:dem":199,
    "gn:feature_class":"P",
    "gn:feature_code":"PPL",
    "gn:name":"Ban Lak Sam Sip Ha",
    "gn:population":0,
    "gn:timezone":"Asia/Vientiane",
    "iso:country":"LA",
    "name:lao_x_preferred":[
        "Ban Lak Sam Sip Ha"
    ],
    "wof:name":"Ban Lak Sam Sip Ha",
    "wof:placetype":"locality"
},
  "geometry": {"coordinates":[105.03557000000001,16.48962],"type":"Point"}
}