{
  "type": "Feature",
  "properties": {
    "gn:admin1_code":"20.0",
    "gn:asciiname":"Ban Nongkom",
    "gn:country_code":"LA",
    "gn:dem":178,
    "gn:feature_class":"P",
    "gn:feature_code":"PPL",
    "gn:name":"Ban Nongk\u00f4m",
    "gn:population":0,
    "gn:timezone":"Asia/Vientiane",
    "iso:country":"LA",
    "name:lao_x_preferred":[
        "Ban Nongk\u00f4m"
    ],
    "wof:name":"Ban Nongkom",
    "wof:placetype":"locality"
},
  "geometry": {"coordinates":[104.88505000000001,16.66299],"type":"Point"}
}