{
  "type": "Feature",
  "properties": {
    "gn:admin1_code":"24.0",
    "gn:asciiname":"Ban Peuk",
    "gn:country_code":"LA",
    "gn:dem":173,
    "gn:feature_class":"P",
    "gn:feature_code":"PPL",
    "gn:name":"Ban Peuk",
    "gn:population":0,
    "gn:timezone":"Asia/Vientiane",
    "iso:country":"LA",
    "name:lao_x_preferred":[
        "Ban Peuk"
    ],
    "wof:name":"Ban Peuk",
    "wof:placetype":"locality"
},
  "geometry": {"coordinates":[102.5138,18.17622],"type":"Point"}
}