{
  "type": "Feature",
  "properties": {
    "gn:admin1_code":"14.0",
    "gn:asciiname":"Ban Gnotkha Noy",
    "gn:country_code":"LA",
    "gn:dem":1158,
    "gn:feature_class":"P",
    "gn:feature_code":"PPL",
    "gn:name":"Ban Gnotkha Noy",
    "gn:population":0,
    "gn:timezone":"Asia/Vientiane",
    "iso:country":"LA",
    "wof:name":"Ban Gnotkha Noy",
    "wof:placetype":"locality"
},
  "geometry": {"coordinates":[103.81667,19.51667],"type":"Point"}
}