{
  "type": "Feature",
  "properties": {
    "gn:admin1_code":"20.0",
    "gn:asciiname":"Ban Nongdeun",
    "gn:country_code":"LA",
    "gn:dem":137,
    "gn:feature_class":"P",
    "gn:feature_code":"PPL",
    "gn:name":"Ban Nongdeun",
    "gn:population":0,
    "gn:timezone":"Asia/Vientiane",
    "iso:country":"LA",
    "name:lao_x_preferred":[
        "Ban Nongdeun"
    ],
    "wof:name":"Ban Nongdeun",
    "wof:placetype":"locality"
},
  "geometry": {"coordinates":[105.19275,16.06287],"type":"Point"}
}