{
  "type": "Feature",
  "properties": {
    "gn:admin1_code":"7.0",
    "gn:asciiname":"Ban Mokkho-Gnai",
    "gn:country_code":"LA",
    "gn:dem":1528,
    "gn:feature_class":"P",
    "gn:feature_code":"PPL",
    "gn:name":"Ban M\u00f4kkh\u00f4-Gnai",
    "gn:population":0,
    "gn:timezone":"Asia/Vientiane",
    "iso:country":"LA",
    "name:lao_x_preferred":[
        "Ban M\u00f4kkh\u00f4-Gnai"
    ],
    "wof:name":"Ban Mokkho-Gnai",
    "wof:placetype":"locality"
},
  "geometry": {"coordinates":[101.08823,20.03451],"type":"Point"}
}