{
  "type": "Feature",
  "properties": {
    "gn:admin1_code":"14.0",
    "gn:asciiname":"Ban Keokoang",
    "gn:cc2":"LA",
    "gn:country_code":"LA",
    "gn:dem":1267,
    "gn:feature_class":"P",
    "gn:feature_code":"PPL",
    "gn:name":"Ban K\u00e8okoang",
    "gn:population":0,
    "gn:timezone":"Asia/Vientiane",
    "iso:country":"LA",
    "name:und_x_variant":[
        "Kheo Khoang",
        "Ban K\u00e8okoang"
    ],
    "wof:name":"Ban Keokoang",
    "wof:placetype":"locality"
},
  "geometry": {"coordinates":[103.09999999999999,19.23333],"type":"Point"}
}