{
  "type": "Feature",
  "properties": {
    "gn:admin1_code":"24.0",
    "gn:asciiname":"Ban Thakhek",
    "gn:country_code":"LA",
    "gn:dem":174,
    "gn:feature_class":"P",
    "gn:feature_code":"PPL",
    "gn:name":"Ban Thakh\u00e8k",
    "gn:population":0,
    "gn:timezone":"Asia/Vientiane",
    "iso:country":"LA",
    "name:lao_x_preferred":[
        "Ban Thakh\u00e8k"
    ],
    "name:und_x_variant":[
        "Ban Tha Khok"
    ],
    "wof:name":"Ban Thakhek",
    "wof:placetype":"locality"
},
  "geometry": {"coordinates":[102.66506,17.81546],"type":"Point"}
}