{
  "type": "Feature",
  "properties": {
    "gn:admin1_code":"18.0",
    "gn:asciiname":"Ban Senkang-Mai",
    "gn:country_code":"LA",
    "gn:dem":1203,
    "gn:feature_class":"P",
    "gn:feature_code":"PPL",
    "gn:name":"Ban S\u00e8nkang-Mai",
    "gn:population":0,
    "gn:timezone":"Asia/Vientiane",
    "iso:country":"LA",
    "name:und_x_variant":[
        "Sen May",
        "P\u2019anha Sum Pu",
        "Ban S\u00e8nkang-Mai"
    ],
    "wof:name":"Ban Senkang-Mai",
    "wof:placetype":"locality"
},
  "geometry": {"coordinates":[102.16052000000001,21.44762],"type":"Point"}
}