{
  "type": "Feature",
  "properties": {
    "gn:admin1_code":"14.0",
    "gn:asciiname":"Ban Natheng",
    "gn:country_code":"LA",
    "gn:dem":1139,
    "gn:feature_class":"P",
    "gn:feature_code":"PPL",
    "gn:name":"Ban Nath\u00e8ng",
    "gn:population":0,
    "gn:timezone":"Asia/Vientiane",
    "iso:country":"LA",
    "name:lao_x_preferred":[
        "Ban Nath\u00e8ng"
    ],
    "wof:name":"Ban Natheng",
    "wof:placetype":"locality"
},
  "geometry": {"coordinates":[103.10554999999999,19.27802],"type":"Point"}
}