{
  "type": "Feature",
  "properties": {
    "gn:admin1_code":"22.0",
    "gn:asciiname":"Ban Thaikhan",
    "gn:country_code":"LA",
    "gn:dem":368,
    "gn:feature_class":"P",
    "gn:feature_code":"PPL",
    "gn:name":"Ban Thaikhan",
    "gn:population":0,
    "gn:timezone":"Asia/Vientiane",
    "iso:country":"LA",
    "name:lao_x_preferred":[
        "Ban Thaikhan"
    ],
    "name:und_x_variant":[
        "Ban Thalkhan"
    ],
    "wof:name":"Ban Thaikhan",
    "wof:placetype":"locality"
},
  "geometry": {"coordinates":[100.23457999999999,20.41412],"type":"Point"}
}