{
  "type": "Feature",
  "properties": {
    "gn:admin1_code":"17.0",
    "gn:asciiname":"Ban Mout",
    "gn:country_code":"LA",
    "gn:dem":320,
    "gn:feature_class":"P",
    "gn:feature_code":"PPL",
    "gn:name":"Ban Mout",
    "gn:population":0,
    "gn:timezone":"Asia/Vientiane",
    "iso:country":"LA",
    "name:und_x_variant":[
        "Ban Mat",
        "Ban Mout"
    ],
    "wof:name":"Ban Mout",
    "wof:placetype":"locality"
},
  "geometry": {"coordinates":[102.18731,19.78966],"type":"Point"}
}