{
  "type": "Feature",
  "properties": {
    "gn:admin1_code":"24.0",
    "gn:asciiname":"Ban Nong Veng",
    "gn:country_code":"LA",
    "gn:dem":179,
    "gn:feature_class":"P",
    "gn:feature_code":"PPL",
    "gn:name":"Ban Nong V\u00e8ng",
    "gn:population":0,
    "gn:timezone":"Asia/Vientiane",
    "iso:country":"LA",
    "name:und_x_variant":[
        "Ban Nong V\u00e8ng",
        "Ban Nong Veng"
    ],
    "wof:name":"Ban Nong Veng",
    "wof:placetype":"locality"
},
  "geometry": {"coordinates":[102.64077,17.88239],"type":"Point"}
}