{
  "type": "Feature",
  "properties": {
    "gn:admin1_code":"15.0",
    "gn:asciiname":"Ban Muangsek",
    "gn:country_code":"LA",
    "gn:dem":175,
    "gn:feature_class":"P",
    "gn:feature_code":"PPL",
    "gn:name":"Ban Muangs\u00e8k",
    "gn:population":0,
    "gn:timezone":"Asia/Vientiane",
    "iso:country":"LA",
    "name:und_x_variant":[
        "Ban Moung Siek",
        "Ban Muong S\u00e8k",
        "Ban Muangs\u00e8k"
    ],
    "wof:name":"Ban Muangsek",
    "wof:placetype":"locality"
},
  "geometry": {"coordinates":[105.19893999999999,17.6138],"type":"Point"}
}