{
  "type": "Feature",
  "properties": {
    "gn:admin1_code":"15.0",
    "gn:asciiname":"Ban Khamkhiao-Nua",
    "gn:country_code":"LA",
    "gn:dem":174,
    "gn:feature_class":"P",
    "gn:feature_code":"PPL",
    "gn:name":"Ban Khamkhiao-Nua",
    "gn:population":0,
    "gn:timezone":"Asia/Vientiane",
    "iso:country":"LA",
    "name:lao_x_preferred":[
        "Ban Khamkhiao-Nua"
    ],
    "name:und_x_variant":[
        "Ban Kham Houei Neua",
        "Ban Kham Kieo"
    ],
    "wof:name":"Ban Khamkhiao-Nua",
    "wof:placetype":"locality"
},
  "geometry": {"coordinates":[105.33584,17.07215],"type":"Point"}
}