{
  "type": "Feature",
  "properties": {
    "gn:admin1_code":"2.0",
    "gn:asciiname":"Ban Nonghouakhoay",
    "gn:country_code":"LA",
    "gn:dem":204,
    "gn:feature_class":"P",
    "gn:feature_code":"PPL",
    "gn:name":"Ban Nonghouakhoay",
    "gn:population":0,
    "gn:timezone":"Asia/Vientiane",
    "iso:country":"LA",
    "name:und_x_variant":[
        "Ban Nong Houa Khouai",
        "Ban Nonghouakhoay"
    ],
    "wof:name":"Ban Nonghouakhoay",
    "wof:placetype":"locality"
},
  "geometry": {"coordinates":[105.90281,15.26876],"type":"Point"}
}