{
  "type": "Feature",
  "properties": {
    "gn:admin1_code":"3.0",
    "gn:asciiname":"Ban Xianglouang",
    "gn:country_code":"LA",
    "gn:dem":692,
    "gn:feature_class":"P",
    "gn:feature_code":"PPL",
    "gn:name":"Ban Xianglouang",
    "gn:population":0,
    "gn:timezone":"Asia/Vientiane",
    "iso:country":"LA",
    "name:und_x_variant":[
        "Xieng Luong",
        "Xieng Louang",
        "Xiangluang",
        "Ban Xiangluang",
        "Ban Xianglouang"
    ],
    "wof:name":"Ban Xianglouang",
    "wof:placetype":"locality"
},
  "geometry": {"coordinates":[104.28932,20.36699],"type":"Point"}
}