{
  "type": "Feature",
  "properties": {
    "gn:admin1_code":"18.0",
    "gn:asciiname":"Ban Longthang-Mai",
    "gn:country_code":"LA",
    "gn:dem":1159,
    "gn:feature_class":"P",
    "gn:feature_code":"PPL",
    "gn:name":"Ban L\u00f4ngthang-Mai",
    "gn:population":0,
    "gn:timezone":"Asia/Vientiane",
    "iso:country":"LA",
    "name:lao_x_preferred":[
        "Ban L\u00f4ngthang-Mai"
    ],
    "wof:name":"Ban Longthang-Mai",
    "wof:placetype":"locality"
},
  "geometry": {"coordinates":[102.23206999999999,21.55839],"type":"Point"}
}