{
  "type": "Feature",
  "properties": {
    "gn:admin1_code":"24.0",
    "gn:asciiname":"Ban Pamai",
    "gn:country_code":"LA",
    "gn:dem":174,
    "gn:feature_class":"P",
    "gn:feature_code":"PPL",
    "gn:name":"Ban Pamai",
    "gn:population":0,
    "gn:timezone":"Asia/Vientiane",
    "iso:country":"LA",
    "name:lao_x_preferred":[
        "Ban Pamai"
    ],
    "wof:name":"Ban Pamai",
    "wof:placetype":"locality"
},
  "geometry": {"coordinates":[102.62452999999999,17.92696],"type":"Point"}
}