{
  "type": "Feature",
  "properties": {
    "gn:admin1_code":"3.0",
    "gn:asciiname":"Ban Houaylong",
    "gn:country_code":"LA",
    "gn:dem":557,
    "gn:feature_class":"P",
    "gn:feature_code":"PPL",
    "gn:name":"Ban Houaylong",
    "gn:population":0,
    "gn:timezone":"Asia/Vientiane",
    "iso:country":"LA",
    "name:und_x_variant":[
        "Ban Luong",
        "Ban Houaylong"
    ],
    "wof:name":"Ban Houaylong",
    "wof:placetype":"locality"
},
  "geometry": {"coordinates":[104.07773,20.78038],"type":"Point"}
}