{
  "type": "Feature",
  "properties": {
    "gn:admin1_code":"22.0",
    "gn:asciiname":"Ban Mokkachok",
    "gn:country_code":"LA",
    "gn:dem":363,
    "gn:feature_class":"P",
    "gn:feature_code":"PPL",
    "gn:name":"Ban M\u00f4kkachok",
    "gn:population":0,
    "gn:timezone":"Asia/Vientiane",
    "iso:country":"LA",
    "name:lao_x_preferred":[
        "Ban M\u00f4kkachok"
    ],
    "wof:name":"Ban Mokkachok",
    "wof:placetype":"locality"
},
  "geometry": {"coordinates":[100.44946,20.25392],"type":"Point"}
}