{
  "type": "Feature",
  "properties": {
    "gn:admin1_code":"7.0",
    "gn:asciiname":"Ban Nathoua",
    "gn:country_code":"LA",
    "gn:dem":744,
    "gn:feature_class":"P",
    "gn:feature_code":"PPL",
    "gn:name":"Ban Nathoua",
    "gn:population":0,
    "gn:timezone":"Asia/Vientiane",
    "iso:country":"LA",
    "name:lao_x_preferred":[
        "Ban Nathoua"
    ],
    "wof:name":"Ban Nathoua",
    "wof:placetype":"locality"
},
  "geometry": {"coordinates":[101.80022,20.83819],"type":"Point"}
}