{
  "type": "Feature",
  "properties": {
    "gn:admin1_code":"14.0",
    "gn:asciiname":"Ban Houay-Mai",
    "gn:country_code":"LA",
    "gn:dem":782,
    "gn:feature_class":"P",
    "gn:feature_code":"PPL",
    "gn:name":"Ban Houay-Mai",
    "gn:population":0,
    "gn:timezone":"Asia/Vientiane",
    "iso:country":"LA",
    "name:lao_x_preferred":[
        "Ban Houay-Mai"
    ],
    "wof:name":"Ban Houay-Mai",
    "wof:placetype":"locality"
},
  "geometry": {"coordinates":[103.80228,20.02723],"type":"Point"}
}