{
  "type": "Feature",
  "properties": {
    "gn:admin1_code":"13.0",
    "gn:asciiname":"Ban Houay-Eum",
    "gn:country_code":"LA",
    "gn:dem":554,
    "gn:feature_class":"P",
    "gn:feature_code":"PPL",
    "gn:name":"Ban Houay-Eum",
    "gn:population":0,
    "gn:timezone":"Asia/Vientiane",
    "iso:country":"LA",
    "name:lao_x_preferred":[
        "Ban Houay-Eum"
    ],
    "wof:name":"Ban Houay-Eum",
    "wof:placetype":"locality"
},
  "geometry": {"coordinates":[101.55707,18.61536],"type":"Point"}
}