{
  "type": "Feature",
  "properties": {
    "gn:admin1_code":"20.0",
    "gn:asciiname":"Ban Nakasin",
    "gn:country_code":"LA",
    "gn:dem":225,
    "gn:feature_class":"P",
    "gn:feature_code":"PPL",
    "gn:name":"Ban Nakasin",
    "gn:population":0,
    "gn:timezone":"Asia/Vientiane",
    "iso:country":"LA",
    "name:und_x_variant":[
        "Ban Na Kasine",
        "Ban Nakasin"
    ],
    "wof:name":"Ban Nakasin",
    "wof:placetype":"locality"
},
  "geometry": {"coordinates":[105.99097999999999,16.99185],"type":"Point"}
}