{
  "type": "Feature",
  "properties": {
    "gn:admin1_code":"2.0",
    "gn:asciiname":"Ban Houayset",
    "gn:country_code":"LA",
    "gn:dem":183,
    "gn:feature_class":"P",
    "gn:feature_code":"PPL",
    "gn:name":"Ban Houays\u00e9t",
    "gn:population":0,
    "gn:timezone":"Asia/Vientiane",
    "iso:country":"LA",
    "name:lao_x_preferred":[
        "Ban Houays\u00e9t"
    ],
    "wof:name":"Ban Houayset",
    "wof:placetype":"locality"
},
  "geometry": {"coordinates":[105.88821000000002,15.09651],"type":"Point"}
}