{
  "type": "Feature",
  "properties": {
    "gn:admin1_code":"27.0",
    "gn:asciiname":"Ban Non",
    "gn:country_code":"LA",
    "gn:dem":233,
    "gn:feature_class":"P",
    "gn:feature_code":"PPL",
    "gn:name":"Ban N\u00f4n",
    "gn:population":0,
    "gn:timezone":"Asia/Vientiane",
    "iso:country":"LA",
    "name:lao_x_preferred":[
        "Ban N\u00f4n"
    ],
    "wof:name":"Ban Non",
    "wof:placetype":"locality"
},
  "geometry": {"coordinates":[102.27666000000001,18.49127],"type":"Point"}
}