{
  "type": "Feature",
  "properties": {
    "gn:admin1_code":"19.0",
    "gn:asciiname":"Ban Donvay",
    "gn:country_code":"LA",
    "gn:dem":153,
    "gn:feature_class":"P",
    "gn:feature_code":"PPL",
    "gn:name":"Ban Donvay",
    "gn:population":0,
    "gn:timezone":"Asia/Vientiane",
    "iso:country":"LA",
    "name:lao_x_preferred":[
        "Ban Donvay"
    ],
    "wof:name":"Ban Donvay",
    "wof:placetype":"locality"
},
  "geometry": {"coordinates":[105.53946000000001,15.90872],"type":"Point"}
}