{
  "type": "Feature",
  "properties": {
    "gn:admin1_code":"14.0",
    "gn:asciiname":"Ban Houat",
    "gn:country_code":"LA",
    "gn:dem":558,
    "gn:feature_class":"P",
    "gn:feature_code":"PPL",
    "gn:name":"Ban Houat",
    "gn:population":0,
    "gn:timezone":"Asia/Vientiane",
    "iso:country":"LA",
    "name:und_x_variant":[
        "Ban Huot",
        "Ban Houat"
    ],
    "wof:name":"Ban Houat",
    "wof:placetype":"locality"
},
  "geometry": {"coordinates":[103.65637,19.56926],"type":"Point"}
}