{
  "type": "Feature",
  "properties": {
    "gn:admin1_code":"14.0",
    "gn:asciiname":"Ban Xiangie",
    "gn:country_code":"LA",
    "gn:dem":1127,
    "gn:feature_class":"P",
    "gn:feature_code":"PPL",
    "gn:name":"Ban Xiangie",
    "gn:population":0,
    "gn:timezone":"Asia/Vientiane",
    "iso:country":"LA",
    "name:lao_x_preferred":[
        "Ban Xiangie"
    ],
    "name:und_x_variant":[
        "Xieng Le"
    ],
    "wof:name":"Ban Xiangie",
    "wof:placetype":"locality"
},
  "geometry": {"coordinates":[103.9802,18.89656],"type":"Point"}
}