{
  "type": "Feature",
  "properties": {
    "gn:admin1_code":"26.0",
    "gn:asciiname":"Ban Mun-Kang",
    "gn:country_code":"LA",
    "gn:dem":770,
    "gn:feature_class":"P",
    "gn:feature_code":"PPL",
    "gn:name":"Ban Mun-Kang",
    "gn:population":0,
    "gn:timezone":"Asia/Vientiane",
    "iso:country":"LA",
    "name:lao_x_preferred":[
        "Ban Mun-Kang"
    ],
    "wof:name":"Ban Mun-Kang",
    "wof:placetype":"locality"
},
  "geometry": {"coordinates":[106.38997000000001,15.47918],"type":"Point"}
}