{
  "type": "Feature",
  "properties": {
    "gn:admin1_code":"7.0",
    "gn:asciiname":"Ban Houa Namveun",
    "gn:country_code":"LA",
    "gn:dem":890,
    "gn:feature_class":"P",
    "gn:feature_code":"PPL",
    "gn:name":"Ban Houa Namveun",
    "gn:population":0,
    "gn:timezone":"Asia/Vientiane",
    "iso:country":"LA",
    "wof:name":"Ban Houa Namveun",
    "wof:placetype":"locality"
},
  "geometry": {"coordinates":[101.88333,20.83333],"type":"Point"}
}