{
  "type": "Feature",
  "properties": {
    "gn:admin1_code":"27.0",
    "gn:asciiname":"Ban Mai-Phonsi",
    "gn:country_code":"LA",
    "gn:dem":227,
    "gn:feature_class":"P",
    "gn:feature_code":"PPL",
    "gn:name":"Ban Mai-Ph\u00f4nsi",
    "gn:population":0,
    "gn:timezone":"Asia/Vientiane",
    "iso:country":"LA",
    "name:lao_x_preferred":[
        "Ban Mai-Ph\u00f4nsi"
    ],
    "wof:name":"Ban Mai-Phonsi",
    "wof:placetype":"locality"
},
  "geometry": {"coordinates":[102.12488,18.69400000000001],"type":"Point"}
}