{
  "type": "Feature",
  "properties": {
    "gn:admin1_code":"20.0",
    "gn:asciiname":"Ban Nonghai",
    "gn:country_code":"LA",
    "gn:dem":196,
    "gn:feature_class":"P",
    "gn:feature_code":"PPL",
    "gn:name":"Ban Nonghai",
    "gn:population":0,
    "gn:timezone":"Asia/Vientiane",
    "iso:country":"LA",
    "name:und_x_variant":[
        "Ban Kadop",
        "Ban Nonghai"
    ],
    "wof:name":"Ban Nonghai",
    "wof:placetype":"locality"
},
  "geometry": {"coordinates":[105.68301,17.02577],"type":"Point"}
}