{
  "type": "Feature",
  "properties": {
    "gn:admin1_code":"7.0",
    "gn:asciiname":"Ban Phouli",
    "gn:country_code":"LA",
    "gn:dem":802,
    "gn:feature_class":"P",
    "gn:feature_code":"PPL",
    "gn:name":"Ban Phouli",
    "gn:population":0,
    "gn:timezone":"Asia/Vientiane",
    "iso:country":"LA",
    "name:lao_x_preferred":[
        "Ban Phouli"
    ],
    "wof:name":"Ban Phouli",
    "wof:placetype":"locality"
},
  "geometry": {"coordinates":[101.82141,21.00219],"type":"Point"}
}