{
  "type": "Feature",
  "properties": {
    "gn:admin1_code":"20.0",
    "gn:asciiname":"Ban Kengkhanthagnat",
    "gn:country_code":"LA",
    "gn:dem":139,
    "gn:feature_class":"P",
    "gn:feature_code":"PPL",
    "gn:name":"Ban K\u00e8ngkhanthagnat",
    "gn:population":0,
    "gn:timezone":"Asia/Vientiane",
    "iso:country":"LA",
    "name:und_x_variant":[
        "Ban Keng Taniat",
        "Ban Kong Taniat",
        "Ban K\u00e8ngkhanthagnat"
    ],
    "wof:name":"Ban Kengkhanthagnat",
    "wof:placetype":"locality"
},
  "geometry": {"coordinates":[105.36104,16.14881],"type":"Point"}
}