{
  "type": "Feature",
  "properties": {
    "gn:admin1_code":"18.0",
    "gn:asciiname":"Ban Lon",
    "gn:country_code":"LA",
    "gn:dem":494,
    "gn:feature_class":"P",
    "gn:feature_code":"PPL",
    "gn:name":"Ban L\u00f4n",
    "gn:population":0,
    "gn:timezone":"Asia/Vientiane",
    "iso:country":"LA",
    "wof:name":"Ban Lon",
    "wof:placetype":"locality"
},
  "geometry": {"coordinates":[102.84721999999999,21.52278],"type":"Point"}
}