{
  "type": "Feature",
  "properties": {
    "gn:admin1_code":"17.0",
    "gn:asciiname":"Ban Houayhoy",
    "gn:country_code":"LA",
    "gn:dem":339,
    "gn:feature_class":"P",
    "gn:feature_code":"PPL",
    "gn:name":"Ban Houayhoy",
    "gn:population":0,
    "gn:timezone":"Asia/Vientiane",
    "iso:country":"LA",
    "name:und_x_variant":[
        "Ban Houay Hoi",
        "Ban Houei Hoi",
        "Ban Houayhoy"
    ],
    "wof:name":"Ban Houayhoy",
    "wof:placetype":"locality"
},
  "geometry": {"coordinates":[102.65712000000001,20.64285],"type":"Point"}
}