{
  "type": "Feature",
  "properties": {
    "gn:admin1_code":"19.0",
    "gn:asciiname":"Ban Tam",
    "gn:country_code":"LA",
    "gn:dem":366,
    "gn:feature_class":"P",
    "gn:feature_code":"PPL",
    "gn:name":"Ban Tam",
    "gn:population":0,
    "gn:timezone":"Asia/Vientiane",
    "iso:country":"LA",
    "name:lao_x_preferred":[
        "Ban Tam"
    ],
    "wof:name":"Ban Tam",
    "wof:placetype":"locality"
},
  "geometry": {"coordinates":[106.45157,16.11657],"type":"Point"}
}