{
  "type": "Feature",
  "properties": {
    "gn:admin1_code":"7.0",
    "gn:asciiname":"Ban Houayxin-Tai",
    "gn:country_code":"LA",
    "gn:dem":887,
    "gn:feature_class":"P",
    "gn:feature_code":"PPL",
    "gn:name":"Ban Houayxin-Tai",
    "gn:population":0,
    "gn:timezone":"Asia/Vientiane",
    "iso:country":"LA",
    "name:lao_x_preferred":[
        "Ban Houayxin-Tai"
    ],
    "wof:name":"Ban Houayxin-Tai",
    "wof:placetype":"locality"
},
  "geometry": {"coordinates":[102.06576,20.30203],"type":"Point"}
}