{
  "type": "Feature",
  "properties": {
    "gn:admin1_code":"17.0",
    "gn:asciiname":"Ban Phadao",
    "gn:country_code":"LA",
    "gn:dem":655,
    "gn:feature_class":"P",
    "gn:feature_code":"PPL",
    "gn:name":"Ban Phadao",
    "gn:population":0,
    "gn:timezone":"Asia/Vientiane",
    "iso:country":"LA",
    "name:lao_x_preferred":[
        "Ban Phadao"
    ],
    "wof:name":"Ban Phadao",
    "wof:placetype":"locality"
},
  "geometry": {"coordinates":[101.94602999999999,19.85522000000001],"type":"Point"}
}