{
  "type": "Feature",
  "properties": {
    "gn:admin1_code":"17.0",
    "gn:asciiname":"Ban Nounsavat",
    "gn:country_code":"LA",
    "gn:dem":310,
    "gn:feature_class":"P",
    "gn:feature_code":"PPL",
    "gn:name":"Ban Nounsavat",
    "gn:population":0,
    "gn:timezone":"Asia/Vientiane",
    "iso:country":"LA",
    "name:lao_x_preferred":[
        "Ban Nounsavat"
    ],
    "name:und_x_variant":[
        "Ban Noun"
    ],
    "wof:name":"Ban Nounsavat",
    "wof:placetype":"locality"
},
  "geometry": {"coordinates":[102.19962,19.88119],"type":"Point"}
}