{
  "type": "Feature",
  "properties": {
    "gn:admin1_code":"19.0",
    "gn:asciiname":"Ban Xapon",
    "gn:country_code":"LA",
    "gn:dem":257,
    "gn:feature_class":"P",
    "gn:feature_code":"PPL",
    "gn:name":"Ban Xap\u00f4n",
    "gn:population":0,
    "gn:timezone":"Asia/Vientiane",
    "iso:country":"LA",
    "name:und_x_variant":[
        "Ban Sapone",
        "Ban Xap\u00f4n"
    ],
    "wof:name":"Ban Xapon",
    "wof:placetype":"locality"
},
  "geometry": {"coordinates":[106.30293,15.6159],"type":"Point"}
}