{
  "type": "Feature",
  "properties": {
    "gn:admin1_code":"20.0",
    "gn:asciiname":"Ban Nakhanay",
    "gn:country_code":"LA",
    "gn:dem":160,
    "gn:feature_class":"P",
    "gn:feature_code":"PPL",
    "gn:name":"Ban Nakhanay",
    "gn:population":0,
    "gn:timezone":"Asia/Vientiane",
    "iso:country":"LA",
    "name:und_x_variant":[
        "Ban Nakhanai",
        "Ban Nakhanay"
    ],
    "wof:name":"Ban Nakhanay",
    "wof:placetype":"locality"
},
  "geometry": {"coordinates":[104.87596000000001,16.95501],"type":"Point"}
}