{
  "type": "Feature",
  "properties": {
    "gn:admin1_code":"7.0",
    "gn:asciiname":"Ban Houayliang-Nua",
    "gn:country_code":"LA",
    "gn:dem":599,
    "gn:feature_class":"P",
    "gn:feature_code":"PPL",
    "gn:name":"Ban Houayliang-Nua",
    "gn:population":0,
    "gn:timezone":"Asia/Vientiane",
    "iso:country":"LA",
    "name:lao_x_preferred":[
        "Ban Houayliang-Nua"
    ],
    "wof:name":"Ban Houayliang-Nua",
    "wof:placetype":"locality"
},
  "geometry": {"coordinates":[102.01393,20.38232],"type":"Point"}
}