{
  "type": "Feature",
  "properties": {
    "gn:admin1_code":"17.0",
    "gn:asciiname":"Ban Longkang",
    "gn:country_code":"LA",
    "gn:dem":832,
    "gn:feature_class":"P",
    "gn:feature_code":"PPL",
    "gn:name":"Ban Longkang",
    "gn:population":0,
    "gn:timezone":"Asia/Vientiane",
    "iso:country":"LA",
    "name:lao_x_preferred":[
        "Ban Longkang"
    ],
    "wof:name":"Ban Longkang",
    "wof:placetype":"locality"
},
  "geometry": {"coordinates":[102.28549,19.70257],"type":"Point"}
}