{
  "type": "Feature",
  "properties": {
    "gn:admin1_code":"19.0",
    "gn:asciiname":"Ban Oung",
    "gn:country_code":"LA",
    "gn:dem":239,
    "gn:feature_class":"P",
    "gn:feature_code":"PPL",
    "gn:name":"Ban Oung",
    "gn:population":0,
    "gn:timezone":"Asia/Vientiane",
    "iso:country":"LA",
    "name:lao_x_preferred":[
        "Ban Oung"
    ],
    "wof:name":"Ban Oung",
    "wof:placetype":"locality"
},
  "geometry": {"coordinates":[106.45860999999999,15.94925],"type":"Point"}
}