{
  "type": "Feature",
  "properties": {
    "gn:admin1_code":"23.0",
    "gn:asciiname":"Ban Nahen",
    "gn:country_code":"LA",
    "gn:dem":158,
    "gn:feature_class":"P",
    "gn:feature_code":"PPL",
    "gn:name":"Ban Nah\u00e8n",
    "gn:population":0,
    "gn:timezone":"Asia/Vientiane",
    "iso:country":"LA",
    "name:und_x_variant":[
        "Ban Na He",
        "Ban Nah\u00e8n"
    ],
    "wof:name":"Ban Nahen",
    "wof:placetype":"locality"
},
  "geometry": {"coordinates":[103.42919999999999,18.44815],"type":"Point"}
}