{
  "type": "Feature",
  "properties": {
    "gn:admin1_code":"2.0",
    "gn:asciiname":"Ban Thadua",
    "gn:country_code":"LA",
    "gn:dem":96,
    "gn:feature_class":"P",
    "gn:feature_code":"PPL",
    "gn:name":"Ban Thadua",
    "gn:population":0,
    "gn:timezone":"Asia/Vientiane",
    "iso:country":"LA",
    "name:und_x_variant":[
        "Thadeua",
        "Ban Thadeua",
        "Ban Thadua"
    ],
    "wof:name":"Ban Thadua",
    "wof:placetype":"locality"
},
  "geometry": {"coordinates":[105.76766000000001,14.20031],"type":"Point"}
}