{
  "type": "Feature",
  "properties": {
    "gn:admin1_code":"1.0",
    "gn:asciiname":"Ban Ho",
    "gn:country_code":"LA",
    "gn:dem":98,
    "gn:feature_class":"P",
    "gn:feature_code":"PPL",
    "gn:name":"Ban Ho",
    "gn:population":0,
    "gn:timezone":"Asia/Vientiane",
    "iso:country":"LA",
    "name:lao_x_preferred":[
        "Ban Ho"
    ],
    "wof:name":"Ban Ho",
    "wof:placetype":"locality"
},
  "geometry": {"coordinates":[106.61845,14.71417],"type":"Point"}
}