{
  "type": "Feature",
  "properties": {
    "gn:admin1_code":"18.0",
    "gn:asciiname":"Ban Monsavan",
    "gn:country_code":"LA",
    "gn:dem":394,
    "gn:feature_class":"P",
    "gn:feature_code":"PPL",
    "gn:name":"Ban Monsavan",
    "gn:population":0,
    "gn:timezone":"Asia/Vientiane",
    "iso:country":"LA",
    "name:und_x_variant":[
        "Ban Monsavani"
    ],
    "wof:name":"Ban Monsavan",
    "wof:placetype":"locality"
},
  "geometry": {"coordinates":[102.34104000000001,21.09352],"type":"Point"}
}