{
  "type": "Feature",
  "properties": {
    "gn:admin1_code":"14.0",
    "gn:asciiname":"Ban Lathouang",
    "gn:country_code":"LA",
    "gn:dem":1111,
    "gn:feature_class":"P",
    "gn:feature_code":"PPL",
    "gn:name":"Ban Lathouang",
    "gn:population":0,
    "gn:timezone":"Asia/Vientiane",
    "iso:country":"LA",
    "name:lao_x_preferred":[
        "Ban Lathouang"
    ],
    "wof:name":"Ban Lathouang",
    "wof:placetype":"locality"
},
  "geometry": {"coordinates":[103.18940000000001,19.39365],"type":"Point"}
}