{
  "type": "Feature",
  "properties": {
    "gn:admin1_code":"7.0",
    "gn:asciiname":"Ban Houayyang",
    "gn:country_code":"LA",
    "gn:dem":671,
    "gn:feature_class":"P",
    "gn:feature_code":"PPL",
    "gn:name":"Ban Houayyang",
    "gn:population":0,
    "gn:timezone":"Asia/Vientiane",
    "iso:country":"LA",
    "name:und_x_variant":[
        "Ban Houei Yang",
        "Ban Houayy\u00e8",
        "Ban Houayyang"
    ],
    "wof:name":"Ban Houayyang",
    "wof:placetype":"locality"
},
  "geometry": {"coordinates":[101.9504,20.75635],"type":"Point"}
}