{
  "type": "Feature",
  "properties": {
    "gn:admin1_code":"15.0",
    "gn:asciiname":"Ban Phadeng",
    "gn:country_code":"LA",
    "gn:dem":155,
    "gn:feature_class":"P",
    "gn:feature_code":"PPL",
    "gn:name":"Ban Phad\u00e8ng",
    "gn:population":0,
    "gn:timezone":"Asia/Vientiane",
    "iso:country":"LA",
    "name:lao_x_preferred":[
        "Ban Phad\u00e8ng"
    ],
    "wof:name":"Ban Phadeng",
    "wof:placetype":"locality"
},
  "geometry": {"coordinates":[104.70432,17.64304],"type":"Point"}
}