{
  "type": "Feature",
  "properties": {
    "gn:admin1_code":"26.0",
    "gn:asciiname":"Ban Takiao",
    "gn:country_code":"LA",
    "gn:dem":772,
    "gn:feature_class":"P",
    "gn:feature_code":"PPL",
    "gn:name":"Ban Takiao",
    "gn:population":0,
    "gn:timezone":"Asia/Vientiane",
    "iso:country":"LA",
    "name:und_x_variant":[
        "Ban Taki\u00e8o",
        "Ban Takiao"
    ],
    "wof:name":"Ban Takiao",
    "wof:placetype":"locality"
},
  "geometry": {"coordinates":[106.37560000000001,15.48253],"type":"Point"}
}