{
  "type": "Feature",
  "properties": {
    "gn:admin1_code":"13.0",
    "gn:asciiname":"Ban Houayleuk",
    "gn:country_code":"LA",
    "gn:dem":462,
    "gn:feature_class":"P",
    "gn:feature_code":"PPL",
    "gn:name":"Ban Houayleuk",
    "gn:population":0,
    "gn:timezone":"Asia/Vientiane",
    "iso:country":"LA",
    "name:und_x_variant":[
        "Ban Huai Leuk",
        "Ban Houayleuk"
    ],
    "wof:name":"Ban Houayleuk",
    "wof:placetype":"locality"
},
  "geometry": {"coordinates":[101.21923,17.87692000000001],"type":"Point"}
}