{
  "type": "Feature",
  "properties": {
    "gn:admin1_code":"3.0",
    "gn:asciiname":"Ban Namyat",
    "gn:country_code":"LA",
    "gn:dem":1061,
    "gn:feature_class":"P",
    "gn:feature_code":"PPL",
    "gn:name":"Ban Namyat",
    "gn:population":0,
    "gn:timezone":"Asia/Vientiane",
    "iso:country":"LA",
    "name:und_x_variant":[
        "Ban Namyai",
        "Ban Namyat"
    ],
    "wof:name":"Ban Namyat",
    "wof:placetype":"locality"
},
  "geometry": {"coordinates":[104.09202999999999,20.39569],"type":"Point"}
}