{
  "type": "Feature",
  "properties": {
    "gn:admin1_code":"22.0",
    "gn:asciiname":"Ban Phouvan",
    "gn:country_code":"LA",
    "gn:dem":432,
    "gn:feature_class":"P",
    "gn:feature_code":"PPL",
    "gn:name":"Ban Phouvan",
    "gn:population":0,
    "gn:timezone":"Asia/Vientiane",
    "iso:country":"LA",
    "name:lao_x_preferred":[
        "Ban Phouvan"
    ],
    "wof:name":"Ban Phouvan",
    "wof:placetype":"locality"
},
  "geometry": {"coordinates":[100.56458000000001,20.41708],"type":"Point"}
}