{
  "type": "Feature",
  "properties": {
    "gn:admin1_code":"17.0",
    "gn:asciiname":"Ban Thao Khing",
    "gn:country_code":"LA",
    "gn:dem":856,
    "gn:feature_class":"P",
    "gn:feature_code":"PPL",
    "gn:name":"Ban Thao Khing",
    "gn:population":0,
    "gn:timezone":"Asia/Vientiane",
    "iso:country":"LA",
    "wof:name":"Ban Thao Khing",
    "wof:placetype":"locality"
},
  "geometry": {"coordinates":[102.53333000000001,19.65],"type":"Point"}
}