{
  "type": "Feature",
  "properties": {
    "gn:admin1_code":"15.0",
    "gn:asciiname":"Ban Kouk",
    "gn:country_code":"LA",
    "gn:dem":396,
    "gn:feature_class":"P",
    "gn:feature_code":"PPL",
    "gn:name":"Ban Kouk",
    "gn:population":0,
    "gn:timezone":"Asia/Vientiane",
    "iso:country":"LA",
    "name:und_x_variant":[
        "Hon Cuc",
        "Hon Couc",
        "Ban Kouk"
    ],
    "wof:name":"Ban Kouk",
    "wof:placetype":"locality"
},
  "geometry": {"coordinates":[106.22113,17.16062],"type":"Point"}
}