{
  "type": "Feature",
  "properties": {
    "gn:admin1_code":"17.0",
    "gn:asciiname":"Ban Gnotxeuk",
    "gn:country_code":"LA",
    "gn:dem":893,
    "gn:feature_class":"P",
    "gn:feature_code":"PPL",
    "gn:name":"Ban Gnotxeuk",
    "gn:population":0,
    "gn:timezone":"Asia/Vientiane",
    "iso:country":"LA",
    "name:lao_x_preferred":[
        "Ban Gnotxeuk"
    ],
    "wof:name":"Ban Gnotxeuk",
    "wof:placetype":"locality"
},
  "geometry": {"coordinates":[103.01402,20.42576],"type":"Point"}
}