{
  "type": "Feature",
  "properties": {
    "gn:admin1_code":"13.0",
    "gn:asciiname":"Ban Pauy Khou Lao",
    "gn:country_code":"LA",
    "gn:dem":418,
    "gn:feature_class":"P",
    "gn:feature_code":"PPL",
    "gn:name":"Ban Pauy Khou Lao",
    "gn:population":0,
    "gn:timezone":"Asia/Vientiane",
    "iso:country":"LA",
    "wof:name":"Ban Pauy Khou Lao",
    "wof:placetype":"locality"
},
  "geometry": {"coordinates":[101.41667,18.38333],"type":"Point"}
}