{
  "type": "Feature",
  "properties": {
    "gn:admin1_code":"16.0",
    "gn:asciiname":"Ban Khonthou",
    "gn:country_code":"LA",
    "gn:dem":1231,
    "gn:feature_class":"P",
    "gn:feature_code":"PPL",
    "gn:name":"Ban Khonthou",
    "gn:population":0,
    "gn:timezone":"Asia/Vientiane",
    "iso:country":"LA",
    "name:lao_x_preferred":[
        "Ban Khonthou"
    ],
    "wof:name":"Ban Khonthou",
    "wof:placetype":"locality"
},
  "geometry": {"coordinates":[101.18518,20.51766],"type":"Point"}
}