{
  "type": "Feature",
  "properties": {
    "gn:admin1_code":"14.0",
    "gn:asciiname":"Ban Muan",
    "gn:country_code":"LA",
    "gn:dem":692,
    "gn:feature_class":"P",
    "gn:feature_code":"PPL",
    "gn:name":"Ban Muan",
    "gn:population":0,
    "gn:timezone":"Asia/Vientiane",
    "iso:country":"LA",
    "name:lao_x_preferred":[
        "Ban Muan"
    ],
    "wof:name":"Ban Muan",
    "wof:placetype":"locality"
},
  "geometry": {"coordinates":[103.25494,19.82635],"type":"Point"}
}