{
  "type": "Feature",
  "properties": {
    "gn:admin1_code":"15.0",
    "gn:asciiname":"Ban Thakhe",
    "gn:country_code":"LA",
    "gn:dem":153,
    "gn:feature_class":"P",
    "gn:feature_code":"PPL",
    "gn:name":"Ban Thakh\u00e8",
    "gn:population":0,
    "gn:timezone":"Asia/Vientiane",
    "iso:country":"LA",
    "name:lao_x_preferred":[
        "Ban Thakh\u00e8"
    ],
    "wof:name":"Ban Thakhe",
    "wof:placetype":"locality"
},
  "geometry": {"coordinates":[104.8442,17.44393],"type":"Point"}
}