{
  "type": "Feature",
  "properties": {
    "gn:admin1_code":"3.0",
    "gn:asciiname":"Ban Houayxay",
    "gn:country_code":"LA",
    "gn:dem":1005,
    "gn:feature_class":"P",
    "gn:feature_code":"PPL",
    "gn:name":"Ban Houayxay",
    "gn:population":0,
    "gn:timezone":"Asia/Vientiane",
    "iso:country":"LA",
    "name:lao_x_preferred":[
        "Ban Houayxay"
    ],
    "wof:name":"Ban Houayxay",
    "wof:placetype":"locality"
},
  "geometry": {"coordinates":[104.13968,20.51115],"type":"Point"}
}