{
  "type": "Feature",
  "properties": {
    "gn:admin1_code":"17.0",
    "gn:asciiname":"Ban Pakkam",
    "gn:country_code":"LA",
    "gn:dem":510,
    "gn:feature_class":"P",
    "gn:feature_code":"PPL",
    "gn:name":"Ban Pakkam",
    "gn:population":0,
    "gn:timezone":"Asia/Vientiane",
    "iso:country":"LA",
    "name:lao_x_preferred":[
        "Ban Pakkam"
    ],
    "wof:name":"Ban Pakkam",
    "wof:placetype":"locality"
},
  "geometry": {"coordinates":[102.53225999999999,20.83298],"type":"Point"}
}