{
  "type": "Feature",
  "properties": {
    "gn:admin1_code":"17.0",
    "gn:asciiname":"Ban Longchok",
    "gn:country_code":"LA",
    "gn:dem":1100,
    "gn:feature_class":"P",
    "gn:feature_code":"PPL",
    "gn:name":"Ban Longch\u00f4k",
    "gn:population":0,
    "gn:timezone":"Asia/Vientiane",
    "iso:country":"LA",
    "name:lao_x_preferred":[
        "Ban Longch\u00f4k"
    ],
    "wof:name":"Ban Longchok",
    "wof:placetype":"locality"
},
  "geometry": {"coordinates":[102.22898000000001,20.48475],"type":"Point"}
}