{
  "type": "Feature",
  "properties": {
    "gn:admin1_code":"17.0",
    "gn:asciiname":"Ban Houaykaxang",
    "gn:country_code":"LA",
    "gn:dem":1054,
    "gn:feature_class":"P",
    "gn:feature_code":"PPL",
    "gn:name":"Ban Houaykaxang",
    "gn:population":0,
    "gn:timezone":"Asia/Vientiane",
    "iso:country":"LA",
    "name:lao_x_preferred":[
        "Ban Houaykaxang"
    ],
    "wof:name":"Ban Houaykaxang",
    "wof:placetype":"locality"
},
  "geometry": {"coordinates":[102.51646,20.23169],"type":"Point"}
}