{
  "type": "Feature",
  "properties": {
    "gn:admin1_code":"20.0",
    "gn:asciiname":"Ban Saleo",
    "gn:country_code":"LA",
    "gn:dem":206,
    "gn:feature_class":"P",
    "gn:feature_code":"PPL",
    "gn:name":"Ban Sal\u00e8o",
    "gn:population":0,
    "gn:timezone":"Asia/Vientiane",
    "iso:country":"LA",
    "name:lao_x_preferred":[
        "Ban Sal\u00e8o"
    ],
    "wof:name":"Ban Saleo",
    "wof:placetype":"locality"
},
  "geometry": {"coordinates":[106.44001000000002,16.63338],"type":"Point"}
}