{
  "type": "Feature",
  "properties": {
    "gn:admin1_code":"15.0",
    "gn:asciiname":"Ban Pakouay-Tai",
    "gn:country_code":"LA",
    "gn:dem":182,
    "gn:feature_class":"P",
    "gn:feature_code":"PPL",
    "gn:name":"Ban Pakouay-Tai",
    "gn:population":0,
    "gn:timezone":"Asia/Vientiane",
    "iso:country":"LA",
    "name:lao_x_preferred":[
        "Ban Pakouay-Tai"
    ],
    "wof:name":"Ban Pakouay-Tai",
    "wof:placetype":"locality"
},
  "geometry": {"coordinates":[105.37375,17.21036],"type":"Point"}
}