{
  "type": "Feature",
  "properties": {
    "gn:admin1_code":"18.0",
    "gn:asciiname":"Ban Namma",
    "gn:country_code":"LA",
    "gn:dem":1221,
    "gn:feature_class":"P",
    "gn:feature_code":"PPL",
    "gn:name":"Ban Namma",
    "gn:population":0,
    "gn:timezone":"Asia/Vientiane",
    "iso:country":"LA",
    "name:lao_x_preferred":[
        "Ban Namma"
    ],
    "wof:name":"Ban Namma",
    "wof:placetype":"locality"
},
  "geometry": {"coordinates":[101.62246,22.0335],"type":"Point"}
}