{
  "type": "Feature",
  "properties": {
    "gn:admin1_code":"23.0",
    "gn:asciiname":"Ban Houayxay",
    "gn:country_code":"LA",
    "gn:dem":158,
    "gn:feature_class":"P",
    "gn:feature_code":"PPL",
    "gn:name":"Ban Houayxay",
    "gn:population":0,
    "gn:timezone":"Asia/Vientiane",
    "iso:country":"LA",
    "name:ara_x_preferred":[
        "\u0628\u0627\u0646 \u0647\u0648\u0643\u0633\u0649"
    ],
    "name:ben_x_preferred":[
        "\u09ac\u09be\u09a8 \u09b9\u09cc\u09df\u09be\u0995\u09cd\u09b8\u09c7"
    ],
    "name:ces_x_preferred":[
        "Huay Xai"
    ],
    "name:deu_x_preferred":[
        "Ban Houayxay"
    ],
    "name:ell_x_preferred":[
        "\u039c\u03c0\u03b1\u03bd \u03a7\u03bf\u03c5\u03b1\u03ca\u03be\u03ac\u03b9"
    ],
    "name:epo_x_preferred":[
        "Ban Huajsai"
    ],
    "name:fas_x_preferred":[
        "\u0628\u0627\u0646 \u0647\u0648\u0627\u06cc\u0634\u0627\u06cc"
    ],
    "name:fra_x_preferred":[
        "Houei Sai"
    ],
    "name:heb_x_preferred":[
        "\u05d1\u05d0\u05df \u05d4\u05d5\u05d0\u05e7\u05e1\u05d0\u05d9"
    ],
    "name:hin_x_preferred":[
        "\u092c\u0948\u0928 \u0939\u094d\u092f\u093e\u0915\u094d\u0938\u0947"
    ],
    "name:hun_x_preferred":[
        "Ban Houayxay"
    ],
    "name:ind_x_preferred":[
        "Ban Houayxay"
    ],
    "name:ita_x_preferred":[
        "Ban Houayxay"
    ],
    "name:jpn_x_preferred":[
        "\u30d5\u30a2\u30a4\u30b5\u30fc\u30a4\u90e1"
    ],
    "name:kat_x_preferred":[
        "\u10f0\u10e3\u10d0\u10d8\u10e1\u10d0\u10d8"
    ],
    "name:lao_x_preferred":[
        "Ban Houayxay"
    ],
    "name:lao_x_variant":[
        "\u0eab\u0ec9\u0ea7\u0e8d\u0e8a\u0eb2\u0e8d"
    ],
    "name:nld_x_preferred":[
        "Ban Houayxay"
    ],
    "name:pol_x_preferred":[
        "Ban Houayxay"
    ],
    "name:por_x_preferred":[
        "Ban Houayxay"
    ],
    "name:rus_x_preferred":[
        "\u0425\u0443\u0430\u0439\u0441\u0430\u0439"
    ],
    "name:spa_x_preferred":[
        "Ban Houayxay"
    ],
    "name:swe_x_preferred":[
        "Ban Houayxay"
    ],
    "name:tha_x_preferred":[
        "\u0e2b\u0e49\u0e27\u0e22\u0e17\u0e23\u0e32\u0e22"
    ],
    "name:tur_x_preferred":[
        "Ban Houayxay"
    ],
    "name:ukr_x_preferred":[
        "\u0411\u0430\u043d \u0425\u0443\u0430\u0439\u0441\u0430\u0439"
    ],
    "name:urd_x_preferred":[
        "\u0628\u0627\u0646 \u06c1\u0648\u0648\u0627\u06d2 \u0633\u0627\u0626\u06d2"
    ],
    "name:vie_x_preferred":[
        "Huoixai"
    ],
    "name:war_x_preferred":[
        "Ban Houayxay"
    ],
    "wof:name":"Ban Houayxay",
    "wof:placetype":"locality"
},
  "geometry": {"coordinates":[103.90022,18.33518],"type":"Point"}
}