{
  "type": "Feature",
  "properties": {
    "gn:admin1_code":"20.0",
    "gn:asciiname":"Ban Nongkadok",
    "gn:country_code":"LA",
    "gn:dem":154,
    "gn:feature_class":"P",
    "gn:feature_code":"PPL",
    "gn:name":"Ban Nongkad\u00f4k",
    "gn:population":0,
    "gn:timezone":"Asia/Vientiane",
    "iso:country":"LA",
    "name:lao_x_preferred":[
        "Ban Nongkad\u00f4k"
    ],
    "wof:name":"Ban Nongkadok",
    "wof:placetype":"locality"
},
  "geometry": {"coordinates":[105.26833999999999,16.50984],"type":"Point"}
}