{
  "type": "Feature",
  "properties": {
    "gn:admin1_code":"2.0",
    "gn:asciiname":"Ban Khan-Gnang",
    "gn:country_code":"LA",
    "gn:dem":113,
    "gn:feature_class":"P",
    "gn:feature_code":"PPL",
    "gn:name":"Ban Khan-Gnang",
    "gn:population":0,
    "gn:timezone":"Asia/Vientiane",
    "iso:country":"LA",
    "name:lao_x_preferred":[
        "Ban Khan-Gnang"
    ],
    "name:und_x_variant":[
        "Ban Ha Khan Nhang",
        "Ban Na Khan Nhang",
        "Ban Nakhan-Gnang"
    ],
    "wof:name":"Ban Khan-Gnang",
    "wof:placetype":"locality"
},
  "geometry": {"coordinates":[105.61836,15.31373],"type":"Point"}
}