{
  "type": "Feature",
  "properties": {
    "gn:admin1_code":"27.0",
    "gn:asciiname":"Ban Daomouang",
    "gn:country_code":"LA",
    "gn:dem":206,
    "gn:feature_class":"P",
    "gn:feature_code":"PPL",
    "gn:name":"Ban Daomouang",
    "gn:population":0,
    "gn:timezone":"Asia/Vientiane",
    "iso:country":"LA",
    "name:lao_x_preferred":[
        "Ban Daomouang"
    ],
    "wof:name":"Ban Daomouang",
    "wof:placetype":"locality"
},
  "geometry": {"coordinates":[102.41059,18.31097],"type":"Point"}
}