{
  "type": "Feature",
  "properties": {
    "gn:admin1_code":"20.0",
    "gn:asciiname":"Ban Natang-Nua",
    "gn:country_code":"LA",
    "gn:dem":164,
    "gn:feature_class":"P",
    "gn:feature_code":"PPL",
    "gn:name":"Ban Natang-Nua",
    "gn:population":0,
    "gn:timezone":"Asia/Vientiane",
    "iso:country":"LA",
    "name:lao_x_preferred":[
        "Ban Natang-Nua"
    ],
    "wof:name":"Ban Natang-Nua",
    "wof:placetype":"locality"
},
  "geometry": {"coordinates":[105.5836,16.19983],"type":"Point"}
}