{
  "type": "Feature",
  "properties": {
    "gn:admin1_code":"15.0",
    "gn:asciiname":"Ban Tonphao",
    "gn:country_code":"LA",
    "gn:dem":180,
    "gn:feature_class":"P",
    "gn:feature_code":"PPL",
    "gn:name":"Ban T\u00f4nphao",
    "gn:population":0,
    "gn:timezone":"Asia/Vientiane",
    "iso:country":"LA",
    "name:lao_x_preferred":[
        "Ban T\u00f4nphao"
    ],
    "wof:name":"Ban Tonphao",
    "wof:placetype":"locality"
},
  "geometry": {"coordinates":[105.71209,17.43625],"type":"Point"}
}