{
  "type": "Feature",
  "properties": {
    "gn:admin1_code":"26.0",
    "gn:asciiname":"Ban Tanglou",
    "gn:country_code":"LA",
    "gn:dem":1228,
    "gn:feature_class":"P",
    "gn:feature_code":"PPL",
    "gn:name":"Ban Tanglou",
    "gn:population":0,
    "gn:timezone":"Asia/Vientiane",
    "iso:country":"LA",
    "name:lao_x_preferred":[
        "Ban Tanglou"
    ],
    "wof:name":"Ban Tanglou",
    "wof:placetype":"locality"
},
  "geometry": {"coordinates":[107.12179,15.51351],"type":"Point"}
}