{
  "type": "Feature",
  "properties": {
    "gn:admin1_code":"13.0",
    "gn:asciiname":"Ban Namxong",
    "gn:country_code":"LA",
    "gn:dem":443,
    "gn:feature_class":"P",
    "gn:feature_code":"PPL",
    "gn:name":"Ban Namxong",
    "gn:population":0,
    "gn:timezone":"Asia/Vientiane",
    "iso:country":"LA",
    "name:lao_x_preferred":[
        "Ban Namxong"
    ],
    "wof:name":"Ban Namxong",
    "wof:placetype":"locality"
},
  "geometry": {"coordinates":[101.4268,18.89659],"type":"Point"}
}