{
  "type": "Feature",
  "properties": {
    "gn:admin1_code":"18.0",
    "gn:asciiname":"Ban Changtuan",
    "gn:country_code":"LA",
    "gn:dem":1113,
    "gn:feature_class":"P",
    "gn:feature_code":"PPL",
    "gn:name":"Ban Changtuan",
    "gn:population":0,
    "gn:timezone":"Asia/Vientiane",
    "iso:country":"LA",
    "name:lao_x_preferred":[
        "Ban Changtuan"
    ],
    "wof:name":"Ban Changtuan",
    "wof:placetype":"locality"
},
  "geometry": {"coordinates":[102.06440000000001,21.79266],"type":"Point"}
}