{
  "type": "Feature",
  "properties": {
    "gn:admin1_code":"23.0",
    "gn:asciiname":"Ban Xay Ing",
    "gn:country_code":"LA",
    "gn:dem":160,
    "gn:feature_class":"P",
    "gn:feature_code":"PPL",
    "gn:name":"Ban Xay Ing",
    "gn:population":0,
    "gn:timezone":"Asia/Vientiane",
    "iso:country":"LA",
    "name:und_x_variant":[
        "Ban Sai Ing",
        "Ban Xay Ing"
    ],
    "wof:name":"Ban Xay Ing",
    "wof:placetype":"locality"
},
  "geometry": {"coordinates":[103.48294,18.43583],"type":"Point"}
}