{
  "type": "Feature",
  "properties": {
    "gn:admin1_code":"20.0",
    "gn:asciiname":"Ban Alan",
    "gn:country_code":"LA",
    "gn:dem":256,
    "gn:feature_class":"P",
    "gn:feature_code":"PPL",
    "gn:name":"Ban Alan",
    "gn:population":0,
    "gn:timezone":"Asia/Vientiane",
    "iso:country":"LA",
    "name:und_x_variant":[
        "Ban Arao",
        "Ban Alao",
        "Ban Alan"
    ],
    "wof:name":"Ban Alan",
    "wof:placetype":"locality"
},
  "geometry": {"coordinates":[106.31582,16.54637],"type":"Point"}
}