{
  "type": "Feature",
  "properties": {
    "gn:admin1_code":"20.0",
    "gn:asciiname":"Ban Sisavang",
    "gn:country_code":"LA",
    "gn:dem":155,
    "gn:feature_class":"P",
    "gn:feature_code":"PPL",
    "gn:name":"Ban Sisavang",
    "gn:population":0,
    "gn:timezone":"Asia/Vientiane",
    "iso:country":"LA",
    "name:und_x_variant":[
        "Ban Sisavang (1)",
        "Ban Sisayang"
    ],
    "wof:name":"Ban Sisavang",
    "wof:placetype":"locality"
},
  "geometry": {"coordinates":[105.08101000000001,16.22632999999999],"type":"Point"}
}