{
  "type": "Feature",
  "properties": {
    "gn:admin1_code":"27.0",
    "gn:asciiname":"Ban Phontong",
    "gn:country_code":"LA",
    "gn:dem":209,
    "gn:feature_class":"P",
    "gn:feature_code":"PPL",
    "gn:name":"Ban Ph\u00f4ntong",
    "gn:population":0,
    "gn:timezone":"Asia/Vientiane",
    "iso:country":"LA",
    "name:lao_x_preferred":[
        "Ban Ph\u00f4ntong"
    ],
    "wof:name":"Ban Phontong",
    "wof:placetype":"locality"
},
  "geometry": {"coordinates":[102.41880999999999,18.42312],"type":"Point"}
}