{
  "type": "Feature",
  "properties": {
    "gn:admin1_code":"3.0",
    "gn:asciiname":"Ban Xiangxu",
    "gn:country_code":"LA",
    "gn:dem":761,
    "gn:feature_class":"P",
    "gn:feature_code":"PPL",
    "gn:name":"Ban Xiangxu",
    "gn:population":0,
    "gn:timezone":"Asia/Vientiane",
    "iso:country":"LA",
    "name:und_x_variant":[
        "Xiangxu",
        "Xieng Su",
        "Ban Xiangxu"
    ],
    "wof:name":"Ban Xiangxu",
    "wof:placetype":"locality"
},
  "geometry": {"coordinates":[104.22168000000001,20.37523],"type":"Point"}
}