{
  "type": "Feature",
  "properties": {
    "gn:admin1_code":"26.0",
    "gn:asciiname":"Ban Katup",
    "gn:country_code":"LA",
    "gn:dem":268,
    "gn:feature_class":"P",
    "gn:feature_code":"PPL",
    "gn:name":"Ban Katup",
    "gn:population":0,
    "gn:timezone":"Asia/Vientiane",
    "iso:country":"LA",
    "name:lao_x_preferred":[
        "Ban Katup"
    ],
    "wof:name":"Ban Katup",
    "wof:placetype":"locality"
},
  "geometry": {"coordinates":[106.68985000000001,15.7506],"type":"Point"}
}