{
  "type": "Feature",
  "properties": {
    "gn:admin1_code":"3.0",
    "gn:asciiname":"Ban Houayphong",
    "gn:country_code":"LA",
    "gn:dem":439,
    "gn:feature_class":"P",
    "gn:feature_code":"PPL",
    "gn:name":"Ban Houayph\u00f4ng",
    "gn:population":0,
    "gn:timezone":"Asia/Vientiane",
    "iso:country":"LA",
    "name:lao_x_preferred":[
        "Ban Houayph\u00f4ng"
    ],
    "wof:name":"Ban Houayphong",
    "wof:placetype":"locality"
},
  "geometry": {"coordinates":[104.49296,20.26779],"type":"Point"}
}