{
  "type": "Feature",
  "properties": {
    "gn:admin1_code":"17.0",
    "gn:asciiname":"Ban Sen Vong",
    "gn:cc2":"LA",
    "gn:country_code":"LA",
    "gn:dem":1035,
    "gn:feature_class":"P",
    "gn:feature_code":"PPL",
    "gn:name":"Ban S\u00e8n Vong",
    "gn:population":0,
    "gn:timezone":"Asia/Vientiane",
    "iso:country":"LA",
    "name:und_x_variant":[
        "Ban Sen Vang",
        "Ban S\u00e8n Vong"
    ],
    "wof:name":"Ban Sen Vong",
    "wof:placetype":"locality"
},
  "geometry": {"coordinates":[102.58333,19.91667],"type":"Point"}
}