{
  "type": "Feature",
  "properties": {
    "gn:admin1_code":"17.0",
    "gn:asciiname":"Ban Pagnakha",
    "gn:country_code":"LA",
    "gn:dem":1410,
    "gn:feature_class":"P",
    "gn:feature_code":"PPL",
    "gn:name":"Ban Pagnakha",
    "gn:population":0,
    "gn:timezone":"Asia/Vientiane",
    "iso:country":"LA",
    "name:lao_x_preferred":[
        "Ban Pagnakha"
    ],
    "wof:name":"Ban Pagnakha",
    "wof:placetype":"locality"
},
  "geometry": {"coordinates":[102.22485,19.56788],"type":"Point"}
}