{
  "type": "Feature",
  "properties": {
    "gn:admin1_code":"22.0",
    "gn:asciiname":"Ban Namnge",
    "gn:cc2":"LA",
    "gn:country_code":"LA",
    "gn:dem":429,
    "gn:feature_class":"P",
    "gn:feature_code":"PPL",
    "gn:name":"Ban Namng\u00e8",
    "gn:population":0,
    "gn:timezone":"Asia/Vientiane",
    "iso:country":"LA",
    "name:lao_x_preferred":[
        "Ban Namng\u00e8"
    ],
    "name:und_x_variant":[
        "Ban Ye",
        "Ban Namy\u00e8"
    ],
    "wof:name":"Ban Namnge",
    "wof:placetype":"locality"
},
  "geometry": {"coordinates":[100.56457,20.36452],"type":"Point"}
}