{
  "type": "Feature",
  "properties": {
    "gn:admin1_code":"19.0",
    "gn:asciiname":"Ban Lakhonpheng-Noy",
    "gn:country_code":"LA",
    "gn:dem":155,
    "gn:feature_class":"P",
    "gn:feature_code":"PPL",
    "gn:name":"Ban Lakhonph\u00e9ng-N\u00f4y",
    "gn:population":0,
    "gn:timezone":"Asia/Vientiane",
    "iso:country":"LA",
    "name:lao_x_preferred":[
        "Ban Lakhonph\u00e9ng-N\u00f4y"
    ],
    "wof:name":"Ban Lakhonpheng-Noy",
    "wof:placetype":"locality"
},
  "geometry": {"coordinates":[105.57125000000001,15.90316],"type":"Point"}
}