{
  "type": "Feature",
  "properties": {
    "gn:admin1_code":"14.0",
    "gn:asciiname":"Ban Nangoy",
    "gn:country_code":"LA",
    "gn:dem":1167,
    "gn:feature_class":"P",
    "gn:feature_code":"PPL",
    "gn:name":"Ban Nangoy",
    "gn:population":0,
    "gn:timezone":"Asia/Vientiane",
    "iso:country":"LA",
    "name:und_x_variant":[
        "Ban Nghao",
        "Ban Nangoy"
    ],
    "wof:name":"Ban Nangoy",
    "wof:placetype":"locality"
},
  "geometry": {"coordinates":[103.50261,19.3107],"type":"Point"}
}