{
  "type": "Feature",
  "properties": {
    "gn:admin1_code":"22.0",
    "gn:asciiname":"Ban Chako",
    "gn:country_code":"LA",
    "gn:dem":678,
    "gn:feature_class":"P",
    "gn:feature_code":"PPL",
    "gn:name":"Ban Chako",
    "gn:population":0,
    "gn:timezone":"Asia/Vientiane",
    "iso:country":"LA",
    "name:lao_x_preferred":[
        "Ban Chako"
    ],
    "wof:name":"Ban Chako",
    "wof:placetype":"locality"
},
  "geometry": {"coordinates":[100.68098999999999,20.73095],"type":"Point"}
}