{
  "type": "Feature",
  "properties": {
    "gn:admin1_code":"22.0",
    "gn:asciiname":"Ban Namhoy",
    "gn:country_code":"LA",
    "gn:dem":685,
    "gn:feature_class":"P",
    "gn:feature_code":"PPL",
    "gn:name":"Ban Namhoy",
    "gn:population":0,
    "gn:timezone":"Asia/Vientiane",
    "iso:country":"LA",
    "name:lao_x_preferred":[
        "Ban Namhoy"
    ],
    "wof:name":"Ban Namhoy",
    "wof:placetype":"locality"
},
  "geometry": {"coordinates":[100.3927,20.66666],"type":"Point"}
}