{
  "type": "Feature",
  "properties": {
    "gn:admin1_code":"20.0",
    "gn:asciiname":"Ban Namalou",
    "gn:country_code":"LA",
    "gn:dem":236,
    "gn:feature_class":"P",
    "gn:feature_code":"PPL",
    "gn:name":"Ban Namalou",
    "gn:population":0,
    "gn:timezone":"Asia/Vientiane",
    "iso:country":"LA",
    "name:lao_x_preferred":[
        "Ban Namalou"
    ],
    "wof:name":"Ban Namalou",
    "wof:placetype":"locality"
},
  "geometry": {"coordinates":[105.89418000000001,16.91147],"type":"Point"}
}