{
  "type": "Feature",
  "properties": {
    "gn:admin1_code":"18.0",
    "gn:asciiname":"Ban Laosen",
    "gn:country_code":"LA",
    "gn:dem":1085,
    "gn:feature_class":"P",
    "gn:feature_code":"PPL",
    "gn:name":"Ban Laos\u00e8n",
    "gn:population":0,
    "gn:timezone":"Asia/Vientiane",
    "iso:country":"LA",
    "name:lao_x_preferred":[
        "Ban Laos\u00e8n"
    ],
    "wof:name":"Ban Laosen",
    "wof:placetype":"locality"
},
  "geometry": {"coordinates":[102.04797000000001,21.26449],"type":"Point"}
}