{
  "type": "Feature",
  "properties": {
    "gn:admin1_code":"1.0",
    "gn:asciiname":"Ban Dakpala",
    "gn:country_code":"LA",
    "gn:dem":807,
    "gn:feature_class":"P",
    "gn:feature_code":"PPL",
    "gn:name":"Ban Dakpala",
    "gn:population":0,
    "gn:timezone":"Asia/Vientiane",
    "iso:country":"LA",
    "name:lao_x_preferred":[
        "Ban Dakpala"
    ],
    "wof:name":"Ban Dakpala",
    "wof:placetype":"locality"
},
  "geometry": {"coordinates":[107.40336000000001,14.94175],"type":"Point"}
}