{
  "type": "Feature",
  "properties": {
    "gn:admin1_code":"17.0",
    "gn:asciiname":"Ban Moklak",
    "gn:country_code":"LA",
    "gn:dem":400,
    "gn:feature_class":"P",
    "gn:feature_code":"PPL",
    "gn:name":"Ban M\u00f4klak",
    "gn:population":0,
    "gn:timezone":"Asia/Vientiane",
    "iso:country":"LA",
    "name:lao_x_preferred":[
        "Ban M\u00f4klak"
    ],
    "wof:name":"Ban Moklak",
    "wof:placetype":"locality"
},
  "geometry": {"coordinates":[102.52889,20.5447],"type":"Point"}
}