{
  "type": "Feature",
  "properties": {
    "gn:admin1_code":"2.0",
    "gn:asciiname":"Ban Nachampa",
    "gn:country_code":"LA",
    "gn:dem":77,
    "gn:feature_class":"P",
    "gn:feature_code":"PPL",
    "gn:name":"Ban Nachampa",
    "gn:population":0,
    "gn:timezone":"Asia/Vientiane",
    "iso:country":"LA",
    "name:lao_x_preferred":[
        "Ban Nachampa"
    ],
    "wof:name":"Ban Nachampa",
    "wof:placetype":"locality"
},
  "geometry": {"coordinates":[106.14861999999999,14.02365],"type":"Point"}
}