{
  "type": "Feature",
  "properties": {
    "gn:admin1_code":"20.0",
    "gn:asciiname":"Ban Laen-Dong",
    "gn:country_code":"LA",
    "gn:dem":183,
    "gn:feature_class":"P",
    "gn:feature_code":"PPL",
    "gn:name":"Ban La\u00e8n-D\u00f4ng",
    "gn:population":0,
    "gn:timezone":"Asia/Vientiane",
    "iso:country":"LA",
    "name:lao_x_preferred":[
        "Ban La\u00e8n-D\u00f4ng"
    ],
    "name:und_x_variant":[
        "Ban La Ene"
    ],
    "wof:name":"Ban Laen-Dong",
    "wof:placetype":"locality"
},
  "geometry": {"coordinates":[105.70735000000001,16.59745],"type":"Point"}
}