{
  "type": "Feature",
  "properties": {
    "gn:admin1_code":"19.0",
    "gn:asciiname":"Ban Nonglao-Loum",
    "gn:country_code":"LA",
    "gn:dem":348,
    "gn:feature_class":"P",
    "gn:feature_code":"PPL",
    "gn:name":"Ban Nonglao-Loum",
    "gn:population":0,
    "gn:timezone":"Asia/Vientiane",
    "iso:country":"LA",
    "name:lao_x_preferred":[
        "Ban Nonglao-Loum"
    ],
    "wof:name":"Ban Nonglao-Loum",
    "wof:placetype":"locality"
},
  "geometry": {"coordinates":[106.02739,15.48536],"type":"Point"}
}