{
  "type": "Feature",
  "properties": {
    "gn:admin1_code":"20.0",
    "gn:asciiname":"Peroi",
    "gn:cc2":"LA",
    "gn:country_code":"LA",
    "gn:dem":347,
    "gn:feature_class":"P",
    "gn:feature_code":"PPL",
    "gn:name":"P\u00e9roi",
    "gn:population":0,
    "gn:timezone":"Asia/Vientiane",
    "iso:country":"LA",
    "name:und_x_variant":[
        "P\u00e9noi",
        "P\u00e9roi"
    ],
    "wof:name":"Peroi",
    "wof:placetype":"locality"
},
  "geometry": {"coordinates":[106.55,16.31667],"type":"Point"}
}