{
  "type": "Feature",
  "properties": {
    "gn:admin1_code":"22.0",
    "gn:asciiname":"Ban Langkay",
    "gn:country_code":"LA",
    "gn:dem":416,
    "gn:feature_class":"P",
    "gn:feature_code":"PPL",
    "gn:name":"Ban Langkay",
    "gn:population":0,
    "gn:timezone":"Asia/Vientiane",
    "iso:country":"LA",
    "name:und_x_variant":[
        "Ban Lam Kai",
        "Ban Langkay"
    ],
    "wof:name":"Ban Langkay",
    "wof:placetype":"locality"
},
  "geometry": {"coordinates":[100.83333,20.08333],"type":"Point"}
}