{
  "type": "Feature",
  "properties": {
    "gn:admin1_code":"27.0",
    "gn:asciiname":"Ban Lak-Hasipsong",
    "gn:country_code":"LA",
    "gn:dem":189,
    "gn:feature_class":"P",
    "gn:feature_code":"PPL",
    "gn:name":"Ban Lak-Hasipsong",
    "gn:population":0,
    "gn:timezone":"Asia/Vientiane",
    "iso:country":"LA",
    "name:lao_x_preferred":[
        "Ban Lak-Hasipsong"
    ],
    "wof:name":"Ban Lak-Hasipsong",
    "wof:placetype":"locality"
},
  "geometry": {"coordinates":[102.42610999999999,18.34823],"type":"Point"}
}