{
  "type": "Feature",
  "properties": {
    "gn:admin1_code":"17.0",
    "gn:asciiname":"Ban Phokang",
    "gn:country_code":"LA",
    "gn:dem":1149,
    "gn:feature_class":"P",
    "gn:feature_code":"PPL",
    "gn:name":"Ban Phokang",
    "gn:population":0,
    "gn:timezone":"Asia/Vientiane",
    "iso:country":"LA",
    "name:lao_x_preferred":[
        "Ban Phokang"
    ],
    "wof:name":"Ban Phokang",
    "wof:placetype":"locality"
},
  "geometry": {"coordinates":[102.29197000000001,19.57634],"type":"Point"}
}