{
  "type": "Feature",
  "properties": {
    "gn:admin1_code":"3.0",
    "gn:asciiname":"Ban Taniat",
    "gn:country_code":"LA",
    "gn:dem":830,
    "gn:feature_class":"P",
    "gn:feature_code":"PPL",
    "gn:name":"Ban Taniat",
    "gn:population":0,
    "gn:timezone":"Asia/Vientiane",
    "iso:country":"LA",
    "name:und_x_variant":[
        "Ban Tari\u00eat",
        "Ban Taniet",
        "Ban Taniat"
    ],
    "wof:name":"Ban Taniat",
    "wof:placetype":"locality"
},
  "geometry": {"coordinates":[103.96124,20.0127],"type":"Point"}
}