{
  "type": "Feature",
  "properties": {
    "gn:admin1_code":"18.0",
    "gn:asciiname":"Ban Khasela",
    "gn:country_code":"LA",
    "gn:dem":1468,
    "gn:feature_class":"P",
    "gn:feature_code":"PPL",
    "gn:name":"Ban Khasela",
    "gn:population":0,
    "gn:timezone":"Asia/Vientiane",
    "iso:country":"LA",
    "wof:name":"Ban Khasela",
    "wof:placetype":"locality"
},
  "geometry": {"coordinates":[101.73333,22.28333],"type":"Point"}
}