{
  "type": "Feature",
  "properties": {
    "gn:admin1_code":"15.0",
    "gn:asciiname":"Ban Phonsavan",
    "gn:country_code":"LA",
    "gn:dem":168,
    "gn:feature_class":"P",
    "gn:feature_code":"PPL",
    "gn:name":"Ban Ph\u00f4nsavan",
    "gn:population":0,
    "gn:timezone":"Asia/Vientiane",
    "iso:country":"LA",
    "name:lao_x_preferred":[
        "Ban Ph\u00f4nsavan"
    ],
    "wof:name":"Ban Phonsavan",
    "wof:placetype":"locality"
},
  "geometry": {"coordinates":[105.06113999999999,17.45171],"type":"Point"}
}