{
  "type": "Feature",
  "properties": {
    "gn:admin1_code":"23.0",
    "gn:asciiname":"Ban Pak Kap",
    "gn:country_code":"LA",
    "gn:dem":161,
    "gn:feature_class":"P",
    "gn:feature_code":"PPL",
    "gn:name":"Ban Pak Kap",
    "gn:population":0,
    "gn:timezone":"Asia/Vientiane",
    "iso:country":"LA",
    "name:und_x_variant":[
        "Ban Pak Kab",
        "Ban Pak Kap"
    ],
    "wof:name":"Ban Pak Kap",
    "wof:placetype":"locality"
},
  "geometry": {"coordinates":[103.91701999999999,18.33658],"type":"Point"}
}