{
  "type": "Feature",
  "properties": {
    "gn:admin1_code":"7.0",
    "gn:asciiname":"Ban Chomxang",
    "gn:country_code":"LA",
    "gn:dem":1193,
    "gn:feature_class":"P",
    "gn:feature_code":"PPL",
    "gn:name":"Ban Chomxang",
    "gn:population":0,
    "gn:timezone":"Asia/Vientiane",
    "iso:country":"LA",
    "name:lao_x_preferred":[
        "Ban Chomxang"
    ],
    "wof:name":"Ban Chomxang",
    "wof:placetype":"locality"
},
  "geometry": {"coordinates":[101.06881,19.97659],"type":"Point"}
}