{
  "type": "Feature",
  "properties": {
    "gn:admin1_code":"26.0",
    "gn:asciiname":"Ban Bu-Ang",
    "gn:country_code":"LA",
    "gn:dem":998,
    "gn:feature_class":"P",
    "gn:feature_code":"PPL",
    "gn:name":"Ban Bu-Ang",
    "gn:population":0,
    "gn:timezone":"Asia/Vientiane",
    "iso:country":"LA",
    "name:lao_x_preferred":[
        "Ban Bu-Ang"
    ],
    "wof:name":"Ban Bu-Ang",
    "wof:placetype":"locality"
},
  "geometry": {"coordinates":[107.3339,15.51322],"type":"Point"}
}