{
  "type": "Feature",
  "properties": {
    "gn:admin1_code":"27.0",
    "gn:asciiname":"Ban Kokkiang",
    "gn:country_code":"LA",
    "gn:dem":184,
    "gn:feature_class":"P",
    "gn:feature_code":"PPL",
    "gn:name":"Ban K\u00f4kkiang",
    "gn:population":0,
    "gn:timezone":"Asia/Vientiane",
    "iso:country":"LA",
    "name:lao_x_preferred":[
        "Ban K\u00f4kkiang"
    ],
    "name:und_x_variant":[
        "Kokhieng",
        "Ban Kok Kieng"
    ],
    "wof:name":"Ban Kokkiang",
    "wof:placetype":"locality"
},
  "geometry": {"coordinates":[102.46498,18.56031],"type":"Point"}
}