{
  "type": "Feature",
  "properties": {
    "gn:admin1_code":"20.0",
    "gn:asciiname":"Ban Nalam",
    "gn:country_code":"LA",
    "gn:dem":138,
    "gn:feature_class":"P",
    "gn:feature_code":"PPL",
    "gn:name":"Ban Nalam",
    "gn:population":0,
    "gn:timezone":"Asia/Vientiane",
    "iso:country":"LA",
    "name:lao_x_preferred":[
        "Ban Nalam"
    ],
    "wof:name":"Ban Nalam",
    "wof:placetype":"locality"
},
  "geometry": {"coordinates":[105.27543,16.10927],"type":"Point"}
}