{
  "type": "Feature",
  "properties": {
    "gn:admin1_code":"27.0",
    "gn:asciiname":"Ban Donsantiphap",
    "gn:country_code":"LA",
    "gn:dem":208,
    "gn:feature_class":"P",
    "gn:feature_code":"PPL",
    "gn:name":"Ban Donsantiphap",
    "gn:population":0,
    "gn:timezone":"Asia/Vientiane",
    "iso:country":"LA",
    "name:lao_x_preferred":[
        "Ban Donsantiphap"
    ],
    "wof:name":"Ban Donsantiphap",
    "wof:placetype":"locality"
},
  "geometry": {"coordinates":[102.59103,18.55587],"type":"Point"}
}