{
  "type": "Feature",
  "properties": {
    "gn:admin1_code":"7.0",
    "gn:asciiname":"Ban Namphak",
    "gn:country_code":"LA",
    "gn:dem":1176,
    "gn:feature_class":"P",
    "gn:feature_code":"PPL",
    "gn:name":"Ban Namphak",
    "gn:population":0,
    "gn:timezone":"Asia/Vientiane",
    "iso:country":"LA",
    "wof:name":"Ban Namphak",
    "wof:placetype":"locality"
},
  "geometry": {"coordinates":[101.26833000000001,20.08722],"type":"Point"}
}