{
  "type": "Feature",
  "properties": {
    "gn:admin1_code":"15.0",
    "gn:asciiname":"Ban Phakphua",
    "gn:country_code":"LA",
    "gn:dem":136,
    "gn:feature_class":"P",
    "gn:feature_code":"PPL",
    "gn:name":"Ban Phakphua",
    "gn:population":0,
    "gn:timezone":"Asia/Vientiane",
    "iso:country":"LA",
    "name:lao_x_preferred":[
        "Ban Phakphua"
    ],
    "wof:name":"Ban Phakphua",
    "wof:placetype":"locality"
},
  "geometry": {"coordinates":[104.80938999999999,16.99507],"type":"Point"}
}