{
  "type": "Feature",
  "properties": {
    "gn:admin1_code":"26.0",
    "gn:asciiname":"Ban Amouan",
    "gn:country_code":"LA",
    "gn:dem":668,
    "gn:feature_class":"P",
    "gn:feature_code":"PPL",
    "gn:name":"Ban Amouan",
    "gn:population":0,
    "gn:timezone":"Asia/Vientiane",
    "iso:country":"LA",
    "wof:name":"Ban Amouan",
    "wof:placetype":"locality"
},
  "geometry": {"coordinates":[107.03333000000001,15.91667],"type":"Point"}
}