{
  "type": "Feature",
  "properties": {
    "gn:admin1_code":"2.0",
    "gn:asciiname":"Ban Nalak",
    "gn:country_code":"LA",
    "gn:dem":118,
    "gn:feature_class":"P",
    "gn:feature_code":"PPL",
    "gn:name":"Ban Nalak",
    "gn:population":0,
    "gn:timezone":"Asia/Vientiane",
    "iso:country":"LA",
    "name:lao_x_preferred":[
        "Ban Nalak"
    ],
    "wof:name":"Ban Nalak",
    "wof:placetype":"locality"
},
  "geometry": {"coordinates":[105.74366000000001,15.27035],"type":"Point"}
}