{
  "type": "Feature",
  "properties": {
    "gn:admin1_code":"1.0",
    "gn:asciiname":"Ban Phouhom-Tai",
    "gn:country_code":"LA",
    "gn:dem":112,
    "gn:feature_class":"P",
    "gn:feature_code":"PPL",
    "gn:name":"Ban Phouh\u00f4m-Tai",
    "gn:population":0,
    "gn:timezone":"Asia/Vientiane",
    "iso:country":"LA",
    "name:lao_x_preferred":[
        "Ban Phouh\u00f4m-Tai"
    ],
    "wof:name":"Ban Phouhom-Tai",
    "wof:placetype":"locality"
},
  "geometry": {"coordinates":[106.77491999999999,14.86385],"type":"Point"}
}