{
  "type": "Feature",
  "properties": {
    "gn:admin1_code":"14.0",
    "gn:asciiname":"Ban Xiangdi",
    "gn:country_code":"LA",
    "gn:dem":1101,
    "gn:feature_class":"P",
    "gn:feature_code":"PPL",
    "gn:name":"Ban Xiangdi",
    "gn:population":0,
    "gn:timezone":"Asia/Vientiane",
    "iso:country":"LA",
    "name:lao_x_preferred":[
        "Ban Xiangdi"
    ],
    "wof:name":"Ban Xiangdi",
    "wof:placetype":"locality"
},
  "geometry": {"coordinates":[103.14628,19.29682],"type":"Point"}
}