{
  "type": "Feature",
  "properties": {
    "gn:admin1_code":"2.0",
    "gn:asciiname":"Ban Thongphao",
    "gn:country_code":"LA",
    "gn:dem":781,
    "gn:feature_class":"P",
    "gn:feature_code":"PPL",
    "gn:name":"Ban Th\u00f4ngphao",
    "gn:population":0,
    "gn:timezone":"Asia/Vientiane",
    "iso:country":"LA",
    "name:lao_x_preferred":[
        "Ban Th\u00f4ngphao"
    ],
    "wof:name":"Ban Thongphao",
    "wof:placetype":"locality"
},
  "geometry": {"coordinates":[106.6687,15.1036],"type":"Point"}
}