{
  "type": "Feature",
  "properties": {
    "gn:admin1_code":"2.0",
    "gn:asciiname":"Ban Boungbao",
    "gn:country_code":"LA",
    "gn:dem":95,
    "gn:feature_class":"P",
    "gn:feature_code":"PPL",
    "gn:name":"Ban Boungbao",
    "gn:population":0,
    "gn:timezone":"Asia/Vientiane",
    "iso:country":"LA",
    "name:lao_x_preferred":[
        "Ban Boungbao"
    ],
    "name:und_x_variant":[
        "Ban Boung Bao",
        "Ban Bounghao"
    ],
    "wof:name":"Ban Boungbao",
    "wof:placetype":"locality"
},
  "geometry": {"coordinates":[105.85203,14.49471],"type":"Point"}
}