{
  "type": "Feature",
  "properties": {
    "gn:admin1_code":"27.0",
    "gn:asciiname":"Ban Kham Xang",
    "gn:country_code":"LA",
    "gn:dem":183,
    "gn:feature_class":"P",
    "gn:feature_code":"PPL",
    "gn:name":"Ban Kham Xang",
    "gn:population":0,
    "gn:timezone":"Asia/Vientiane",
    "iso:country":"LA",
    "wof:name":"Ban Kham Xang",
    "wof:placetype":"locality"
},
  "geometry": {"coordinates":[102.50139,18.55667],"type":"Point"}
}