{
  "type": "Feature",
  "properties": {
    "gn:admin1_code":"7.0",
    "gn:asciiname":"Ban Donkeo",
    "gn:country_code":"LA",
    "gn:dem":657,
    "gn:feature_class":"P",
    "gn:feature_code":"PPL",
    "gn:name":"Ban Donk\u00e8o",
    "gn:population":0,
    "gn:timezone":"Asia/Vientiane",
    "iso:country":"LA",
    "name:lao_x_preferred":[
        "Ban Donk\u00e8o"
    ],
    "wof:name":"Ban Donkeo",
    "wof:placetype":"locality"
},
  "geometry": {"coordinates":[102.00369000000001,20.69462],"type":"Point"}
}