{
  "type": "Feature",
  "properties": {
    "gn:admin1_code":"27.0",
    "gn:asciiname":"Ban Phonthon",
    "gn:country_code":"LA",
    "gn:dem":242,
    "gn:feature_class":"P",
    "gn:feature_code":"PPL",
    "gn:name":"Ban Ph\u00f4nthon",
    "gn:population":0,
    "gn:timezone":"Asia/Vientiane",
    "iso:country":"LA",
    "name:lao_x_preferred":[
        "Ban Ph\u00f4nthon"
    ],
    "wof:name":"Ban Phonthon",
    "wof:placetype":"locality"
},
  "geometry": {"coordinates":[102.06255,18.62719],"type":"Point"}
}