{
  "type": "Feature",
  "properties": {
    "gn:admin1_code":"20.0",
    "gn:asciiname":"Ban Pasia",
    "gn:country_code":"LA",
    "gn:dem":251,
    "gn:feature_class":"P",
    "gn:feature_code":"PPL",
    "gn:name":"Ban Pasia",
    "gn:population":0,
    "gn:timezone":"Asia/Vientiane",
    "iso:country":"LA",
    "name:lao_x_preferred":[
        "Ban Pasia"
    ],
    "wof:name":"Ban Pasia",
    "wof:placetype":"locality"
},
  "geometry": {"coordinates":[106.41630000000001,16.44054],"type":"Point"}
}