{
  "type": "Feature",
  "properties": {
    "gn:admin1_code":"18.0",
    "gn:asciiname":"Ban Phia",
    "gn:country_code":"LA",
    "gn:dem":396,
    "gn:feature_class":"P",
    "gn:feature_code":"PPL",
    "gn:name":"Ban Phia",
    "gn:population":0,
    "gn:timezone":"Asia/Vientiane",
    "iso:country":"LA",
    "name:lao_x_preferred":[
        "Ban Phia"
    ],
    "wof:name":"Ban Phia",
    "wof:placetype":"locality"
},
  "geometry": {"coordinates":[102.32449,21.09511],"type":"Point"}
}