{
  "type": "Feature",
  "properties": {
    "gn:admin1_code":"13.0",
    "gn:asciiname":"Ban Nampe-Nua",
    "gn:country_code":"LA",
    "gn:dem":567,
    "gn:feature_class":"P",
    "gn:feature_code":"PPL",
    "gn:name":"Ban Namp\u00e9-Nua",
    "gn:population":0,
    "gn:timezone":"Asia/Vientiane",
    "iso:country":"LA",
    "name:lao_x_preferred":[
        "Ban Namp\u00e9-Nua"
    ],
    "wof:name":"Ban Nampe-Nua",
    "wof:placetype":"locality"
},
  "geometry": {"coordinates":[100.90131,19.72762],"type":"Point"}
}