{
  "type": "Feature",
  "properties": {
    "gn:admin1_code":"13.0",
    "gn:asciiname":"Ban Pakloun",
    "gn:country_code":"LA",
    "gn:dem":376,
    "gn:feature_class":"P",
    "gn:feature_code":"PPL",
    "gn:name":"Ban Pakloun",
    "gn:population":0,
    "gn:timezone":"Asia/Vientiane",
    "iso:country":"LA",
    "name:lao_x_preferred":[
        "Ban Pakloun"
    ],
    "wof:name":"Ban Pakloun",
    "wof:placetype":"locality"
},
  "geometry": {"coordinates":[101.61017,19.39977],"type":"Point"}
}