{
  "type": "Feature",
  "properties": {
    "gn:admin1_code":"20.0",
    "gn:asciiname":"Ban Xouang-Noy",
    "gn:country_code":"LA",
    "gn:dem":258,
    "gn:feature_class":"P",
    "gn:feature_code":"PPL",
    "gn:name":"Ban Xouang-Noy",
    "gn:population":0,
    "gn:timezone":"Asia/Vientiane",
    "iso:country":"LA",
    "name:lao_x_preferred":[
        "Ban Xouang-Noy"
    ],
    "wof:name":"Ban Xouang-Noy",
    "wof:placetype":"locality"
},
  "geometry": {"coordinates":[106.44297,16.44829],"type":"Point"}
}