{
  "type": "Feature",
  "properties": {
    "gn:admin1_code":"1.0",
    "gn:asciiname":"Ban Dakdouan",
    "gn:country_code":"LA",
    "gn:dem":1021,
    "gn:feature_class":"P",
    "gn:feature_code":"PPL",
    "gn:name":"Ban Dakdouan",
    "gn:population":0,
    "gn:timezone":"Asia/Vientiane",
    "iso:country":"LA",
    "name:und_x_variant":[
        "Dak Deuan",
        "Ban Dakdouan"
    ],
    "wof:name":"Ban Dakdouan",
    "wof:placetype":"locality"
},
  "geometry": {"coordinates":[107.18089000000001,15.20816],"type":"Point"}
}