{
  "type": "Feature",
  "properties": {
    "gn:admin1_code":"2.0",
    "gn:asciiname":"Ban Houaymouang",
    "gn:country_code":"LA",
    "gn:dem":497,
    "gn:feature_class":"P",
    "gn:feature_code":"PPL",
    "gn:name":"Ban Houaymouang",
    "gn:population":0,
    "gn:timezone":"Asia/Vientiane",
    "iso:country":"LA",
    "name:lao_x_preferred":[
        "Ban Houaymouang"
    ],
    "wof:name":"Ban Houaymouang",
    "wof:placetype":"locality"
},
  "geometry": {"coordinates":[105.99258,15.17158],"type":"Point"}
}