{
  "type": "Feature",
  "properties": {
    "gn:admin1_code":"3.0",
    "gn:asciiname":"Ban Sopvek",
    "gn:country_code":"LA",
    "gn:dem":353,
    "gn:feature_class":"P",
    "gn:feature_code":"PPL",
    "gn:name":"Ban S\u00f4pv\u00e8k",
    "gn:population":0,
    "gn:timezone":"Asia/Vientiane",
    "iso:country":"LA",
    "name:lao_x_preferred":[
        "Ban S\u00f4pv\u00e8k"
    ],
    "name:und_x_variant":[
        "Sop V\u00e8te"
    ],
    "wof:name":"Ban Sopvek",
    "wof:placetype":"locality"
},
  "geometry": {"coordinates":[103.87902,20.67222000000001],"type":"Point"}
}