{
  "type": "Feature",
  "properties": {
    "gn:admin1_code":"17.0",
    "gn:asciiname":"Ban Chang-Uan",
    "gn:country_code":"LA",
    "gn:dem":841,
    "gn:feature_class":"P",
    "gn:feature_code":"PPL",
    "gn:name":"Ban Chang-Uan",
    "gn:population":0,
    "gn:timezone":"Asia/Vientiane",
    "iso:country":"LA",
    "name:lao_x_preferred":[
        "Ban Chang-Uan"
    ],
    "wof:name":"Ban Chang-Uan",
    "wof:placetype":"locality"
},
  "geometry": {"coordinates":[102.3916,19.50025],"type":"Point"}
}