{
  "type": "Feature",
  "properties": {
    "gn:admin1_code":"7.0",
    "gn:asciiname":"Ban Donghankong",
    "gn:country_code":"LA",
    "gn:dem":1342,
    "gn:feature_class":"P",
    "gn:feature_code":"PPL",
    "gn:name":"Ban D\u00f4nghankong",
    "gn:population":0,
    "gn:timezone":"Asia/Vientiane",
    "iso:country":"LA",
    "name:lao_x_preferred":[
        "Ban D\u00f4nghankong"
    ],
    "wof:name":"Ban Donghankong",
    "wof:placetype":"locality"
},
  "geometry": {"coordinates":[101.72342999999999,20.18913],"type":"Point"}
}