{
  "type": "Feature",
  "properties": {
    "gn:admin1_code":"14.0",
    "gn:asciiname":"Ban Nagnong",
    "gn:country_code":"LA",
    "gn:dem":530,
    "gn:feature_class":"P",
    "gn:feature_code":"PPL",
    "gn:name":"Ban Nagnong",
    "gn:population":0,
    "gn:timezone":"Asia/Vientiane",
    "iso:country":"LA",
    "name:und_x_variant":[
        "Ban Nhong",
        "Ban Nagnong"
    ],
    "wof:name":"Ban Nagnong",
    "wof:placetype":"locality"
},
  "geometry": {"coordinates":[103.67142,19.59164],"type":"Point"}
}