{
  "type": "Feature",
  "properties": {
    "gn:admin1_code":"20.0",
    "gn:asciiname":"Ban Patoy-Gnai",
    "gn:country_code":"LA",
    "gn:dem":372,
    "gn:feature_class":"P",
    "gn:feature_code":"PPL",
    "gn:name":"Ban Patoy-Gnai",
    "gn:population":0,
    "gn:timezone":"Asia/Vientiane",
    "iso:country":"LA",
    "name:lao_x_preferred":[
        "Ban Patoy-Gnai"
    ],
    "name:und_x_variant":[
        "Ban Patoi"
    ],
    "wof:name":"Ban Patoy-Gnai",
    "wof:placetype":"locality"
},
  "geometry": {"coordinates":[106.54937,16.29762],"type":"Point"}
}