{
  "type": "Feature",
  "properties": {
    "gn:admin1_code":"15.0",
    "gn:asciiname":"Ban Sopmaxong",
    "gn:country_code":"LA",
    "gn:dem":588,
    "gn:feature_class":"P",
    "gn:feature_code":"PPL",
    "gn:name":"Ban S\u00f4pmaxong",
    "gn:population":0,
    "gn:timezone":"Asia/Vientiane",
    "iso:country":"LA",
    "name:lao_x_preferred":[
        "Ban S\u00f4pmaxong"
    ],
    "wof:name":"Ban Sopmaxong",
    "wof:placetype":"locality"
},
  "geometry": {"coordinates":[105.22993,17.9435],"type":"Point"}
}