{
  "type": "Feature",
  "properties": {
    "gn:admin1_code":"7.0",
    "gn:asciiname":"Latxang",
    "gn:country_code":"LA",
    "gn:dem":1303,
    "gn:feature_class":"P",
    "gn:feature_code":"PPL",
    "gn:name":"Latxang",
    "gn:population":0,
    "gn:timezone":"Asia/Vientiane",
    "iso:country":"LA",
    "name:und_x_variant":[
        "Ban Latsa",
        "Latxang"
    ],
    "wof:name":"Latxang",
    "wof:placetype":"locality"
},
  "geometry": {"coordinates":[102.09999999999999,21.03333],"type":"Point"}
}