{
  "type": "Feature",
  "properties": {
    "gn:admin1_code":"20.0",
    "gn:asciiname":"Ban Dongkhagnang",
    "gn:country_code":"LA",
    "gn:dem":194,
    "gn:feature_class":"P",
    "gn:feature_code":"PPL",
    "gn:name":"Ban D\u00f4ngkhagnang",
    "gn:population":0,
    "gn:timezone":"Asia/Vientiane",
    "iso:country":"LA",
    "name:lao_x_preferred":[
        "Ban D\u00f4ngkhagnang"
    ],
    "wof:name":"Ban Dongkhagnang",
    "wof:placetype":"locality"
},
  "geometry": {"coordinates":[105.09795,16.3517],"type":"Point"}
}