{
  "type": "Feature",
  "properties": {
    "gn:admin1_code":"20.0",
    "gn:asciiname":"Ban Donmouang",
    "gn:country_code":"LA",
    "gn:dem":156,
    "gn:feature_class":"P",
    "gn:feature_code":"PPL",
    "gn:name":"Ban Donmouang",
    "gn:population":0,
    "gn:timezone":"Asia/Vientiane",
    "iso:country":"LA",
    "name:lao_x_preferred":[
        "Ban Donmouang"
    ],
    "wof:name":"Ban Donmouang",
    "wof:placetype":"locality"
},
  "geometry": {"coordinates":[105.27618,16.13916],"type":"Point"}
}