{
  "type": "Feature",
  "properties": {
    "gn:admin1_code":"7.0",
    "gn:asciiname":"Ban Houayxan",
    "gn:country_code":"LA",
    "gn:dem":450,
    "gn:feature_class":"P",
    "gn:feature_code":"PPL",
    "gn:name":"Ban Houayxan",
    "gn:population":0,
    "gn:timezone":"Asia/Vientiane",
    "iso:country":"LA",
    "wof:name":"Ban Houayxan",
    "wof:placetype":"locality"
},
  "geometry": {"coordinates":[101.75888999999999,20.00194],"type":"Point"}
}