{
  "type": "Feature",
  "properties": {
    "gn:admin1_code":"27.0",
    "gn:asciiname":"Ban Namden",
    "gn:country_code":"LA",
    "gn:dem":288,
    "gn:feature_class":"P",
    "gn:feature_code":"PPL",
    "gn:name":"Ban Namd\u00e8n",
    "gn:population":0,
    "gn:timezone":"Asia/Vientiane",
    "iso:country":"LA",
    "name:lao_x_preferred":[
        "Ban Namd\u00e8n"
    ],
    "wof:name":"Ban Namden",
    "wof:placetype":"locality"
},
  "geometry": {"coordinates":[102.44265,19.10942],"type":"Point"}
}