{
  "type": "Feature",
  "properties": {
    "gn:admin1_code":"20.0",
    "gn:asciiname":"Ban Soung",
    "gn:country_code":"LA",
    "gn:dem":211,
    "gn:feature_class":"P",
    "gn:feature_code":"PPL",
    "gn:name":"Ban Soung",
    "gn:population":0,
    "gn:timezone":"Asia/Vientiane",
    "iso:country":"LA",
    "name:lao_x_preferred":[
        "Ban Soung"
    ],
    "wof:name":"Ban Soung",
    "wof:placetype":"locality"
},
  "geometry": {"coordinates":[106.50449999999999,16.57532],"type":"Point"}
}