{
  "type": "Feature",
  "properties": {
    "gn:admin1_code":"15.0",
    "gn:asciiname":"Ban Saeum",
    "gn:country_code":"LA",
    "gn:dem":244,
    "gn:feature_class":"P",
    "gn:feature_code":"PPL",
    "gn:name":"Ban Saeum",
    "gn:population":0,
    "gn:timezone":"Asia/Vientiane",
    "iso:country":"LA",
    "name:und_x_variant":[
        "Ban Sa Um",
        "Ban Sa Umo",
        "Ban Saeum"
    ],
    "wof:name":"Ban Saeum",
    "wof:placetype":"locality"
},
  "geometry": {"coordinates":[105.94186000000001,17.19736],"type":"Point"}
}