{
  "type": "Feature",
  "properties": {
    "gn:admin1_code":"28.0",
    "gn:asciiname":"Ban Khet-Sam",
    "gn:country_code":"LA",
    "gn:dem":223,
    "gn:feature_class":"P",
    "gn:feature_code":"PPL",
    "gn:name":"Ban Khet-Sam",
    "gn:population":0,
    "gn:timezone":"Asia/Vientiane",
    "iso:country":"LA",
    "name:lao_x_preferred":[
        "Ban Khet-Sam"
    ],
    "wof:name":"Ban Khet-Sam",
    "wof:placetype":"locality"
},
  "geometry": {"coordinates":[102.74817,18.52425],"type":"Point"}
}