{
  "type": "Feature",
  "properties": {
    "gn:admin1_code":"26.0",
    "gn:asciiname":"Ban Alam-Tam",
    "gn:country_code":"LA",
    "gn:dem":800,
    "gn:feature_class":"P",
    "gn:feature_code":"PPL",
    "gn:name":"Ban Alam-Tam",
    "gn:population":0,
    "gn:timezone":"Asia/Vientiane",
    "iso:country":"LA",
    "name:lao_x_preferred":[
        "Ban Alam-Tam"
    ],
    "wof:name":"Ban Alam-Tam",
    "wof:placetype":"locality"
},
  "geometry": {"coordinates":[107.10235,16.01986],"type":"Point"}
}