{
  "type": "Feature",
  "properties": {
    "gn:admin1_code":"17.0",
    "gn:asciiname":"Ban Houayving",
    "gn:country_code":"LA",
    "gn:dem":518,
    "gn:feature_class":"P",
    "gn:feature_code":"PPL",
    "gn:name":"Ban Houayving",
    "gn:population":0,
    "gn:timezone":"Asia/Vientiane",
    "iso:country":"LA",
    "name:lao_x_preferred":[
        "Ban Houayving"
    ],
    "wof:name":"Ban Houayving",
    "wof:placetype":"locality"
},
  "geometry": {"coordinates":[102.01438,19.99543],"type":"Point"}
}