{
  "type": "Feature",
  "properties": {
    "gn:admin1_code":"28.0",
    "gn:asciiname":"Ban Leu",
    "gn:country_code":"LA",
    "gn:dem":308,
    "gn:feature_class":"P",
    "gn:feature_code":"PPL",
    "gn:name":"Ban Leu",
    "gn:population":0,
    "gn:timezone":"Asia/Vientiane",
    "iso:country":"LA",
    "name:und_x_variant":[
        "Ban Lau",
        "Ban Leu"
    ],
    "wof:name":"Ban Leu",
    "wof:placetype":"locality"
},
  "geometry": {"coordinates":[103.4902,18.9809],"type":"Point"}
}