{
  "type": "Feature",
  "properties": {
    "gn:admin1_code":"16.0",
    "gn:asciiname":"Ban Houaytat",
    "gn:country_code":"LA",
    "gn:dem":895,
    "gn:feature_class":"P",
    "gn:feature_code":"PPL",
    "gn:name":"Ban Houaytat",
    "gn:population":0,
    "gn:timezone":"Asia/Vientiane",
    "iso:country":"LA",
    "name:lao_x_preferred":[
        "Ban Houaytat"
    ],
    "wof:name":"Ban Houaytat",
    "wof:placetype":"locality"
},
  "geometry": {"coordinates":[101.1472,21.4312],"type":"Point"}
}