{
  "type": "Feature",
  "properties": {
    "gn:admin1_code":"18.0",
    "gn:asciiname":"Ban Gnakha",
    "gn:country_code":"LA",
    "gn:dem":856,
    "gn:feature_class":"P",
    "gn:feature_code":"PPL",
    "gn:name":"Ban Gnakha",
    "gn:population":0,
    "gn:timezone":"Asia/Vientiane",
    "iso:country":"LA",
    "name:und_x_variant":[
        "Na Kha",
        "Mok Son Luang",
        "Ban Gnakha"
    ],
    "wof:name":"Ban Gnakha",
    "wof:placetype":"locality"
},
  "geometry": {"coordinates":[102.61385,21.09684],"type":"Point"}
}