{
  "type": "Feature",
  "properties": {
    "gn:admin1_code":"28.0",
    "gn:asciiname":"Ban Xiangtan",
    "gn:country_code":"LA",
    "gn:dem":232,
    "gn:feature_class":"P",
    "gn:feature_code":"PPL",
    "gn:name":"Ban Xiangtan",
    "gn:population":0,
    "gn:timezone":"Asia/Vientiane",
    "iso:country":"LA",
    "name:und_x_variant":[
        "Ban Xieng Than",
        "Ban Xiangtan"
    ],
    "wof:name":"Ban Xiangtan",
    "wof:placetype":"locality"
},
  "geometry": {"coordinates":[103.62397,18.97216],"type":"Point"}
}