{
  "type": "Feature",
  "properties": {
    "gn:admin1_code":"7.0",
    "gn:asciiname":"Ban Nalai",
    "gn:country_code":"LA",
    "gn:dem":541,
    "gn:feature_class":"P",
    "gn:feature_code":"PPL",
    "gn:name":"Ban Nalai",
    "gn:population":0,
    "gn:timezone":"Asia/Vientiane",
    "iso:country":"LA",
    "name:lao_x_preferred":[
        "Ban Nalai"
    ],
    "wof:name":"Ban Nalai",
    "wof:placetype":"locality"
},
  "geometry": {"coordinates":[101.67456,20.33932],"type":"Point"}
}