{
  "type": "Feature",
  "properties": {
    "gn:admin1_code":"23.0",
    "gn:asciiname":"Ban Mouan-Noy",
    "gn:country_code":"LA",
    "gn:dem":366,
    "gn:feature_class":"P",
    "gn:feature_code":"PPL",
    "gn:name":"Ban Mouan-Noy",
    "gn:population":0,
    "gn:timezone":"Asia/Vientiane",
    "iso:country":"LA",
    "name:lao_x_preferred":[
        "Ban Mouan-Noy"
    ],
    "name:und_x_variant":[
        "Mon Noy",
        "Ban Mone Noi"
    ],
    "wof:name":"Ban Mouan-Noy",
    "wof:placetype":"locality"
},
  "geometry": {"coordinates":[104.29012,18.65746],"type":"Point"}
}