{
  "type": "Feature",
  "properties": {
    "gn:admin1_code":"16.0",
    "gn:asciiname":"Ban Mounglot",
    "gn:country_code":"LA",
    "gn:dem":1212,
    "gn:feature_class":"P",
    "gn:feature_code":"PPL",
    "gn:name":"Ban Mounglot",
    "gn:population":0,
    "gn:timezone":"Asia/Vientiane",
    "iso:country":"LA",
    "name:lao_x_preferred":[
        "Ban Mounglot"
    ],
    "wof:name":"Ban Mounglot",
    "wof:placetype":"locality"
},
  "geometry": {"coordinates":[101.22223,20.49136],"type":"Point"}
}