{
  "type": "Feature",
  "properties": {
    "gn:admin1_code":"13.0",
    "gn:asciiname":"Ban Pakngou",
    "gn:country_code":"LA",
    "gn:dem":832,
    "gn:feature_class":"P",
    "gn:feature_code":"PPL",
    "gn:name":"Ban Pakngou",
    "gn:population":0,
    "gn:timezone":"Asia/Vientiane",
    "iso:country":"LA",
    "name:lao_x_preferred":[
        "Ban Pakngou"
    ],
    "wof:name":"Ban Pakngou",
    "wof:placetype":"locality"
},
  "geometry": {"coordinates":[101.28335,19.6214],"type":"Point"}
}