{
  "type": "Feature",
  "properties": {
    "gn:admin1_code":"7.0",
    "gn:asciiname":"Ban Napang",
    "gn:country_code":"LA",
    "gn:dem":475,
    "gn:feature_class":"P",
    "gn:feature_code":"PPL",
    "gn:name":"Ban Napang",
    "gn:population":0,
    "gn:timezone":"Asia/Vientiane",
    "iso:country":"LA",
    "name:lao_x_preferred":[
        "Ban Napang"
    ],
    "wof:name":"Ban Napang",
    "wof:placetype":"locality"
},
  "geometry": {"coordinates":[101.4639,20.14129],"type":"Point"}
}