{
  "type": "Feature",
  "properties": {
    "gn:admin1_code":"20.0",
    "gn:asciiname":"Ban Dongkhankhou",
    "gn:country_code":"LA",
    "gn:dem":172,
    "gn:feature_class":"P",
    "gn:feature_code":"PPL",
    "gn:name":"Ban D\u00f4ngkhankhou",
    "gn:population":0,
    "gn:timezone":"Asia/Vientiane",
    "iso:country":"LA",
    "name:und_x_variant":[
        "Ban Dong Nhien",
        "Ban D\u00f4ngkhankhou"
    ],
    "wof:name":"Ban Dongkhankhou",
    "wof:placetype":"locality"
},
  "geometry": {"coordinates":[105.09667,16.53821],"type":"Point"}
}