{
  "type": "Feature",
  "properties": {
    "gn:admin1_code":"24.0",
    "gn:asciiname":"Ban Hatsento",
    "gn:country_code":"LA",
    "gn:dem":172,
    "gn:feature_class":"P",
    "gn:feature_code":"PPL",
    "gn:name":"Ban Hats\u00e8nto",
    "gn:population":0,
    "gn:timezone":"Asia/Vientiane",
    "iso:country":"LA",
    "wof:name":"Ban Hatsento",
    "wof:placetype":"locality"
},
  "geometry": {"coordinates":[102.55,18.23333],"type":"Point"}
}