{
  "type": "Feature",
  "properties": {
    "gn:admin1_code":"2.0",
    "gn:asciiname":"Ban Sichantho",
    "gn:country_code":"LA",
    "gn:dem":105,
    "gn:feature_class":"P",
    "gn:feature_code":"PPL",
    "gn:name":"Ban Sichanth\u00f4",
    "gn:population":0,
    "gn:timezone":"Asia/Vientiane",
    "iso:country":"LA",
    "name:lao_x_preferred":[
        "Ban Sichanth\u00f4"
    ],
    "name:und_x_variant":[
        "Ban Sichantho Nhai",
        "Ban Sichanth\u00f4 Gnai"
    ],
    "wof:name":"Ban Sichantho",
    "wof:placetype":"locality"
},
  "geometry": {"coordinates":[105.9119,14.89089],"type":"Point"}
}