{
  "type": "Feature",
  "properties": {
    "gn:admin1_code":"20.0",
    "gn:asciiname":"Ban Sopnam",
    "gn:country_code":"LA",
    "gn:dem":189,
    "gn:feature_class":"P",
    "gn:feature_code":"PPL",
    "gn:name":"Ban S\u00f4pnam",
    "gn:population":0,
    "gn:timezone":"Asia/Vientiane",
    "iso:country":"LA",
    "name:lao_x_preferred":[
        "Ban S\u00f4pnam"
    ],
    "wof:name":"Ban Sopnam",
    "wof:placetype":"locality"
},
  "geometry": {"coordinates":[106.21482,16.68792],"type":"Point"}
}