{
  "type": "Feature",
  "properties": {
    "gn:admin1_code":"19.0",
    "gn:asciiname":"Ban Ango",
    "gn:country_code":"LA",
    "gn:dem":423,
    "gn:feature_class":"P",
    "gn:feature_code":"PPL",
    "gn:name":"Ban Ango",
    "gn:population":0,
    "gn:timezone":"Asia/Vientiane",
    "iso:country":"LA",
    "name:lao_x_preferred":[
        "Ban Ango"
    ],
    "wof:name":"Ban Ango",
    "wof:placetype":"locality"
},
  "geometry": {"coordinates":[106.82015,16.23239],"type":"Point"}
}