{
  "type": "Feature",
  "properties": {
    "gn:admin1_code":"2.0",
    "gn:asciiname":"Ban Phonpheung",
    "gn:country_code":"LA",
    "gn:dem":99,
    "gn:feature_class":"P",
    "gn:feature_code":"PPL",
    "gn:name":"Ban Ph\u00f4npheung",
    "gn:population":0,
    "gn:timezone":"Asia/Vientiane",
    "iso:country":"LA",
    "name:lao_x_preferred":[
        "Ban Ph\u00f4npheung"
    ],
    "name:und_x_variant":[
        "Ban None Pheung",
        "Ban N\u00f4pheung"
    ],
    "wof:name":"Ban Phonpheung",
    "wof:placetype":"locality"
},
  "geometry": {"coordinates":[105.77889999999999,14.64696],"type":"Point"}
}