{
  "type": "Feature",
  "properties": {
    "gn:admin1_code":"15.0",
    "gn:asciiname":"Ban Donglatling",
    "gn:country_code":"LA",
    "gn:dem":146,
    "gn:feature_class":"P",
    "gn:feature_code":"PPL",
    "gn:name":"Ban D\u00f4nglatling",
    "gn:population":0,
    "gn:timezone":"Asia/Vientiane",
    "iso:country":"LA",
    "name:lao_x_preferred":[
        "Ban D\u00f4nglatling"
    ],
    "wof:name":"Ban Donglatling",
    "wof:placetype":"locality"
},
  "geometry": {"coordinates":[105.06832,17.17457000000001],"type":"Point"}
}