{
  "type": "Feature",
  "properties": {
    "gn:admin1_code":"7.0",
    "gn:asciiname":"Ban Takouan",
    "gn:country_code":"LA",
    "gn:dem":1088,
    "gn:feature_class":"P",
    "gn:feature_code":"PPL",
    "gn:name":"Ban Takouan",
    "gn:population":0,
    "gn:timezone":"Asia/Vientiane",
    "iso:country":"LA",
    "name:lao_x_preferred":[
        "Ban Takouan"
    ],
    "wof:name":"Ban Takouan",
    "wof:placetype":"locality"
},
  "geometry": {"coordinates":[101.52489,20.31377],"type":"Point"}
}