{
  "type": "Feature",
  "properties": {
    "gn:admin1_code":"20.0",
    "gn:asciiname":"Ban Latbok",
    "gn:country_code":"LA",
    "gn:dem":174,
    "gn:feature_class":"P",
    "gn:feature_code":"PPL",
    "gn:name":"Ban Latb\u00f4k",
    "gn:population":0,
    "gn:timezone":"Asia/Vientiane",
    "iso:country":"LA",
    "name:lao_x_preferred":[
        "Ban Latb\u00f4k"
    ],
    "wof:name":"Ban Latbok",
    "wof:placetype":"locality"
},
  "geometry": {"coordinates":[105.22342,16.15083],"type":"Point"}
}