{
  "type": "Feature",
  "properties": {
    "gn:admin1_code":"24.0",
    "gn:asciiname":"Ban Sangveuy",
    "gn:country_code":"LA",
    "gn:dem":176,
    "gn:feature_class":"P",
    "gn:feature_code":"PPL",
    "gn:name":"Ban Sangveuy",
    "gn:population":0,
    "gn:timezone":"Asia/Vientiane",
    "iso:country":"LA",
    "name:lao_x_preferred":[
        "Ban Sangveuy"
    ],
    "wof:name":"Ban Sangveuy",
    "wof:placetype":"locality"
},
  "geometry": {"coordinates":[102.63417,17.91917999999999],"type":"Point"}
}