{
  "type": "Feature",
  "properties": {
    "gn:admin1_code":"13.0",
    "gn:asciiname":"Ban Laocha",
    "gn:country_code":"LA",
    "gn:dem":1266,
    "gn:feature_class":"P",
    "gn:feature_code":"PPL",
    "gn:name":"Ban Laocha",
    "gn:population":0,
    "gn:timezone":"Asia/Vientiane",
    "iso:country":"LA",
    "name:lao_x_preferred":[
        "Ban Laocha"
    ],
    "wof:name":"Ban Laocha",
    "wof:placetype":"locality"
},
  "geometry": {"coordinates":[100.92052,19.83037],"type":"Point"}
}