{
  "type": "Feature",
  "properties": {
    "gn:admin1_code":"26.0",
    "gn:asciiname":"Ban Het",
    "gn:country_code":"LA",
    "gn:dem":829,
    "gn:feature_class":"P",
    "gn:feature_code":"PPL",
    "gn:name":"Ban H\u00e8t",
    "gn:population":0,
    "gn:timezone":"Asia/Vientiane",
    "iso:country":"LA",
    "name:lao_x_preferred":[
        "Ban H\u00e8t"
    ],
    "wof:name":"Ban Het",
    "wof:placetype":"locality"
},
  "geometry": {"coordinates":[107.0684,15.38176],"type":"Point"}
}