{
  "type": "Feature",
  "properties": {
    "gn:admin1_code":"17.0",
    "gn:asciiname":"Ban Khole",
    "gn:country_code":"LA",
    "gn:dem":284,
    "gn:feature_class":"P",
    "gn:feature_code":"PPL",
    "gn:name":"Ban Khol\u00e9",
    "gn:population":0,
    "gn:timezone":"Asia/Vientiane",
    "iso:country":"LA",
    "wof:name":"Ban Khole",
    "wof:placetype":"locality"
},
  "geometry": {"coordinates":[101.80444,19.60472],"type":"Point"}
}