{
  "type": "Feature",
  "properties": {
    "gn:admin1_code":"13.0",
    "gn:asciiname":"Ban Naven",
    "gn:country_code":"LA",
    "gn:dem":456,
    "gn:feature_class":"P",
    "gn:feature_code":"PPL",
    "gn:name":"Ban Nav\u00e8n",
    "gn:population":0,
    "gn:timezone":"Asia/Vientiane",
    "iso:country":"LA",
    "name:lao_x_preferred":[
        "Ban Nav\u00e8n"
    ],
    "wof:name":"Ban Naven",
    "wof:placetype":"locality"
},
  "geometry": {"coordinates":[101.38961,18.81288],"type":"Point"}
}