{
  "type": "Feature",
  "properties": {
    "gn:admin1_code":"22.0",
    "gn:asciiname":"Ban Houaykengphak",
    "gn:cc2":"LA",
    "gn:country_code":"LA",
    "gn:dem":357,
    "gn:feature_class":"P",
    "gn:feature_code":"PPL",
    "gn:name":"Ban Houayk\u00e8ngphak",
    "gn:population":0,
    "gn:timezone":"Asia/Vientiane",
    "iso:country":"LA",
    "name:und_x_variant":[
        "Ban Phua Geang Phak",
        "Ban Houa Kong Phak",
        "Ban Houe Kong Phak",
        "Ban Houayk\u00e8ngphak"
    ],
    "wof:name":"Ban Houaykengphak",
    "wof:placetype":"locality"
},
  "geometry": {"coordinates":[100.58,19.87361],"type":"Point"}
}