{
  "type": "Feature",
  "properties": {
    "gn:admin1_code":"2.0",
    "gn:asciiname":"Ban Lak Si Sip Pet",
    "gn:country_code":"LA",
    "gn:dem":1261,
    "gn:feature_class":"P",
    "gn:feature_code":"PPL",
    "gn:name":"Ban Lak Si Sip P\u00e8t",
    "gn:population":0,
    "gn:timezone":"Asia/Vientiane",
    "iso:country":"LA",
    "name:lao_x_preferred":[
        "Ban Lak Si Sip P\u00e8t"
    ],
    "wof:name":"Ban Lak Si Sip Pet",
    "wof:placetype":"locality"
},
  "geometry": {"coordinates":[106.20968000000001,15.18732],"type":"Point"}
}