{
  "type": "Feature",
  "properties": {
    "gn:admin1_code":"22.0",
    "gn:asciiname":"Ban Namsen",
    "gn:country_code":"LA",
    "gn:dem":384,
    "gn:feature_class":"P",
    "gn:feature_code":"PPL",
    "gn:name":"Ban Nams\u00e8n",
    "gn:population":0,
    "gn:timezone":"Asia/Vientiane",
    "iso:country":"LA",
    "name:lao_x_preferred":[
        "Ban Nams\u00e8n"
    ],
    "wof:name":"Ban Namsen",
    "wof:placetype":"locality"
},
  "geometry": {"coordinates":[100.43886999999999,20.38881],"type":"Point"}
}