{
  "type": "Feature",
  "properties": {
    "gn:admin1_code":"13.0",
    "gn:asciiname":"Ban Hatdong",
    "gn:country_code":"LA",
    "gn:dem":241,
    "gn:feature_class":"P",
    "gn:feature_code":"PPL",
    "gn:name":"Ban Hatd\u00f4ng",
    "gn:population":0,
    "gn:timezone":"Asia/Vientiane",
    "iso:country":"LA",
    "name:und_x_variant":[
        "Ban Hat Deng",
        "Ban Hatd\u00f4ng",
        "Ban Hatdong"
    ],
    "wof:name":"Ban Hatdong",
    "wof:placetype":"locality"
},
  "geometry": {"coordinates":[101.41970000000001,17.73497],"type":"Point"}
}