{
  "type": "Feature",
  "properties": {
    "gn:admin1_code":"20.0",
    "gn:asciiname":"Ban Donggnay",
    "gn:country_code":"LA",
    "gn:dem":145,
    "gn:feature_class":"P",
    "gn:feature_code":"PPL",
    "gn:name":"Ban D\u00f4nggnay",
    "gn:population":0,
    "gn:timezone":"Asia/Vientiane",
    "iso:country":"LA",
    "name:lao_x_preferred":[
        "Ban D\u00f4nggnay"
    ],
    "name:und_x_variant":[
        "D. Dong Chan"
    ],
    "wof:name":"Ban Donggnay",
    "wof:placetype":"locality"
},
  "geometry": {"coordinates":[104.85812,17.00953],"type":"Point"}
}