{
  "type": "Feature",
  "properties": {
    "gn:admin1_code":"18.0",
    "gn:asciiname":"Ban Sensoukkha",
    "gn:country_code":"LA",
    "gn:dem":901,
    "gn:feature_class":"P",
    "gn:feature_code":"PPL",
    "gn:name":"Ban S\u00e8nsoukkha",
    "gn:population":0,
    "gn:timezone":"Asia/Vientiane",
    "iso:country":"LA",
    "name:und_x_variant":[
        "Sen Su Kha",
        "Sen Su Khu",
        "Ban S\u00e8nsoukkha"
    ],
    "wof:name":"Ban Sensoukkha",
    "wof:placetype":"locality"
},
  "geometry": {"coordinates":[102.27229,21.70485],"type":"Point"}
}