{
  "type": "Feature",
  "properties": {
    "gn:admin1_code":"14.0",
    "gn:asciiname":"Ban Houaydou",
    "gn:cc2":"LA",
    "gn:country_code":"LA",
    "gn:dem":1111,
    "gn:feature_class":"P",
    "gn:feature_code":"PPL",
    "gn:name":"Ban Houaydou",
    "gn:population":0,
    "gn:timezone":"Asia/Vientiane",
    "iso:country":"LA",
    "name:und_x_variant":[
        "Ban Houei Kho",
        "Ban Houei Dou",
        "Ban Houaydou"
    ],
    "wof:name":"Ban Houaydou",
    "wof:placetype":"locality"
},
  "geometry": {"coordinates":[104.05,19.45],"type":"Point"}
}