{
  "type": "Feature",
  "properties": {
    "gn:admin1_code":"14.0",
    "gn:asciiname":"Ban Muangmian",
    "gn:country_code":"LA",
    "gn:dem":772,
    "gn:feature_class":"P",
    "gn:feature_code":"PPL",
    "gn:name":"Ban Muangmian",
    "gn:population":0,
    "gn:timezone":"Asia/Vientiane",
    "iso:country":"LA",
    "name:und_x_variant":[
        "Muang Mian",
        "Muong Mian",
        "Ban Muangmian"
    ],
    "wof:name":"Ban Muangmian",
    "wof:placetype":"locality"
},
  "geometry": {"coordinates":[103.02921000000001,19.70604],"type":"Point"}
}