{
  "type": "Feature",
  "properties": {
    "gn:admin1_code":"17.0",
    "gn:asciiname":"Ban Xiangmen",
    "gn:country_code":"LA",
    "gn:dem":311,
    "gn:feature_class":"P",
    "gn:feature_code":"PPL",
    "gn:name":"Ban Xiangm\u00e8n",
    "gn:population":0,
    "gn:timezone":"Asia/Vientiane",
    "iso:country":"LA",
    "name:und_x_variant":[
        "Xieng Men",
        "Xien Men",
        "Ban Xiangm\u00e8n"
    ],
    "wof:name":"Ban Xiangmen",
    "wof:placetype":"locality"
},
  "geometry": {"coordinates":[102.12844,19.89625],"type":"Point"}
}