{
  "type": "Feature",
  "properties": {
    "gn:admin1_code":"2.0",
    "gn:asciiname":"Ban Mouang",
    "gn:country_code":"LA",
    "gn:dem":91,
    "gn:feature_class":"P",
    "gn:feature_code":"PPL",
    "gn:name":"Ban Mouang",
    "gn:population":0,
    "gn:timezone":"Asia/Vientiane",
    "iso:country":"LA",
    "name:lao_x_preferred":[
        "Ban Mouang"
    ],
    "wof:name":"Ban Mouang",
    "wof:placetype":"locality"
},
  "geometry": {"coordinates":[105.88028,14.0601],"type":"Point"}
}