{
  "type": "Feature",
  "properties": {
    "gn:admin1_code":"19.0",
    "gn:asciiname":"Ban Lukdong",
    "gn:country_code":"LA",
    "gn:dem":707,
    "gn:feature_class":"P",
    "gn:feature_code":"PPL",
    "gn:name":"Ban Lukd\u00f4ng",
    "gn:population":0,
    "gn:timezone":"Asia/Vientiane",
    "iso:country":"LA",
    "name:lao_x_preferred":[
        "Ban Lukd\u00f4ng"
    ],
    "wof:name":"Ban Lukdong",
    "wof:placetype":"locality"
},
  "geometry": {"coordinates":[106.6977,15.88153],"type":"Point"}
}