{
  "type": "Feature",
  "properties": {
    "gn:admin1_code":"22.0",
    "gn:asciiname":"Ban Had Tcha",
    "gn:country_code":"LA",
    "gn:dem":385,
    "gn:feature_class":"P",
    "gn:feature_code":"PPL",
    "gn:name":"Ban Had Tcha",
    "gn:population":0,
    "gn:timezone":"Asia/Vientiane",
    "iso:country":"LA",
    "wof:name":"Ban Had Tcha",
    "wof:placetype":"locality"
},
  "geometry": {"coordinates":[100.73333,20.16667],"type":"Point"}
}