{
  "type": "Feature",
  "properties": {
    "gn:admin1_code":"17.0",
    "gn:asciiname":"Ban Navang",
    "gn:country_code":"LA",
    "gn:dem":1032,
    "gn:feature_class":"P",
    "gn:feature_code":"PPL",
    "gn:name":"Ban Navang",
    "gn:population":0,
    "gn:timezone":"Asia/Vientiane",
    "iso:country":"LA",
    "name:lao_x_preferred":[
        "Ban Navang"
    ],
    "wof:name":"Ban Navang",
    "wof:placetype":"locality"
},
  "geometry": {"coordinates":[101.9849,19.95641],"type":"Point"}
}