{
  "type": "Feature",
  "properties": {
    "gn:admin1_code":"26.0",
    "gn:asciiname":"Ban Dakpaha",
    "gn:country_code":"LA",
    "gn:dem":938,
    "gn:feature_class":"P",
    "gn:feature_code":"PPL",
    "gn:name":"Ban Dakpaha",
    "gn:population":0,
    "gn:timezone":"Asia/Vientiane",
    "iso:country":"LA",
    "name:lao_x_preferred":[
        "Ban Dakpaha"
    ],
    "name:und_x_variant":[
        "Dak Raha",
        "Dak Paha"
    ],
    "wof:name":"Ban Dakpaha",
    "wof:placetype":"locality"
},
  "geometry": {"coordinates":[107.52049,15.33392],"type":"Point"}
}