{
  "type": "Feature",
  "properties": {
    "gn:admin1_code":"19.0",
    "gn:asciiname":"Ban Sanam",
    "gn:country_code":"LA",
    "gn:dem":195,
    "gn:feature_class":"P",
    "gn:feature_code":"PPL",
    "gn:name":"Ban Sanam",
    "gn:population":0,
    "gn:timezone":"Asia/Vientiane",
    "iso:country":"LA",
    "name:lao_x_preferred":[
        "Ban Sanam"
    ],
    "wof:name":"Ban Sanam",
    "wof:placetype":"locality"
},
  "geometry": {"coordinates":[106.25539000000001,15.99559],"type":"Point"}
}