{
  "type": "Feature",
  "properties": {
    "gn:admin1_code":"17.0",
    "gn:asciiname":"Ban Houaymuang",
    "gn:country_code":"LA",
    "gn:dem":1187,
    "gn:feature_class":"P",
    "gn:feature_code":"PPL",
    "gn:name":"Ban Houaymuang",
    "gn:population":0,
    "gn:timezone":"Asia/Vientiane",
    "iso:country":"LA",
    "name:und_x_variant":[
        "Ban Houei Muong",
        "Ban Houaymuang"
    ],
    "wof:name":"Ban Houaymuang",
    "wof:placetype":"locality"
},
  "geometry": {"coordinates":[102.85742999999999,20.03977],"type":"Point"}
}