{
  "type": "Feature",
  "properties": {
    "gn:admin1_code":"2.0",
    "gn:asciiname":"Ban Xekatam",
    "gn:country_code":"LA",
    "gn:dem":953,
    "gn:feature_class":"P",
    "gn:feature_code":"PPL",
    "gn:name":"Ban X\u00e9katam",
    "gn:population":0,
    "gn:timezone":"Asia/Vientiane",
    "iso:country":"LA",
    "name:lao_x_preferred":[
        "Ban X\u00e9katam"
    ],
    "wof:name":"Ban Xekatam",
    "wof:placetype":"locality"
},
  "geometry": {"coordinates":[106.52208,15.20922],"type":"Point"}
}