{
  "type": "Feature",
  "properties": {
    "gn:admin1_code":"7.0",
    "gn:asciiname":"Ban Konching",
    "gn:country_code":"LA",
    "gn:dem":1212,
    "gn:feature_class":"P",
    "gn:feature_code":"PPL",
    "gn:name":"Ban Konching",
    "gn:population":0,
    "gn:timezone":"Asia/Vientiane",
    "iso:country":"LA",
    "name:lao_x_preferred":[
        "Ban Konching"
    ],
    "wof:name":"Ban Konching",
    "wof:placetype":"locality"
},
  "geometry": {"coordinates":[101.46559000000001,20.31261],"type":"Point"}
}