{
  "type": "Feature",
  "properties": {
    "gn:admin1_code":"14.0",
    "gn:asciiname":"Ban Namteng",
    "gn:country_code":"LA",
    "gn:dem":967,
    "gn:feature_class":"P",
    "gn:feature_code":"PPL",
    "gn:name":"Ban Namt\u00e8ng",
    "gn:population":0,
    "gn:timezone":"Asia/Vientiane",
    "iso:country":"LA",
    "name:lao_x_preferred":[
        "Ban Namt\u00e8ng"
    ],
    "wof:name":"Ban Namteng",
    "wof:placetype":"locality"
},
  "geometry": {"coordinates":[103.90076000000001,19.02392],"type":"Point"}
}