{
  "type": "Feature",
  "properties": {
    "gn:admin1_code":"2.0",
    "gn:asciiname":"Ban Nafang-Noy",
    "gn:country_code":"LA",
    "gn:dem":97,
    "gn:feature_class":"P",
    "gn:feature_code":"PPL",
    "gn:name":"Ban Nafang-Noy",
    "gn:population":0,
    "gn:timezone":"Asia/Vientiane",
    "iso:country":"LA",
    "name:lao_x_preferred":[
        "Ban Nafang-Noy"
    ],
    "name:und_x_variant":[
        "Ban Nafang No\u00ef"
    ],
    "wof:name":"Ban Nafang-Noy",
    "wof:placetype":"locality"
},
  "geometry": {"coordinates":[105.86375,14.46432],"type":"Point"}
}