{
  "type": "Feature",
  "properties": {
    "gn:admin1_code":"27.0",
    "gn:asciiname":"Ban Phonsi-Tai",
    "gn:country_code":"LA",
    "gn:dem":184,
    "gn:feature_class":"P",
    "gn:feature_code":"PPL",
    "gn:name":"Ban Ph\u00f4nsi-Tai",
    "gn:population":0,
    "gn:timezone":"Asia/Vientiane",
    "iso:country":"LA",
    "name:lao_x_preferred":[
        "Ban Ph\u00f4nsi-Tai"
    ],
    "wof:name":"Ban Phonsi-Tai",
    "wof:placetype":"locality"
},
  "geometry": {"coordinates":[102.41247,18.4844],"type":"Point"}
}