{
  "type": "Feature",
  "properties": {
    "gn:admin1_code":"13.0",
    "gn:asciiname":"Ban Houayxoay",
    "gn:country_code":"LA",
    "gn:dem":640,
    "gn:feature_class":"P",
    "gn:feature_code":"PPL",
    "gn:name":"Ban Houayxoay",
    "gn:population":0,
    "gn:timezone":"Asia/Vientiane",
    "iso:country":"LA",
    "name:lao_x_preferred":[
        "Ban Houayxoay"
    ],
    "wof:name":"Ban Houayxoay",
    "wof:placetype":"locality"
},
  "geometry": {"coordinates":[100.73724,19.72992],"type":"Point"}
}