{
  "type": "Feature",
  "properties": {
    "gn:admin1_code":"14.0",
    "gn:asciiname":"Muang Phang",
    "gn:cc2":"LA",
    "gn:country_code":"LA",
    "gn:dem":1264,
    "gn:feature_class":"P",
    "gn:feature_code":"PPL",
    "gn:name":"Muang Phang",
    "gn:population":0,
    "gn:timezone":"Asia/Vientiane",
    "iso:country":"LA",
    "name:und_x_variant":[
        "Muong Phan",
        "Muang Phang"
    ],
    "wof:name":"Muang Phang",
    "wof:placetype":"locality"
},
  "geometry": {"coordinates":[103.61667,19.25],"type":"Point"}
}