{
  "type": "Feature",
  "properties": {
    "gn:admin1_code":"13.0",
    "gn:asciiname":"Houaydua",
    "gn:country_code":"LA",
    "gn:dem":403,
    "gn:feature_class":"P",
    "gn:feature_code":"PPL",
    "gn:name":"Houaydua",
    "gn:population":0,
    "gn:timezone":"Asia/Vientiane",
    "iso:country":"LA",
    "name:lao_x_preferred":[
        "Houaydua"
    ],
    "wof:name":"Houaydua",
    "wof:placetype":"locality"
},
  "geometry": {"coordinates":[101.64812000000001,19.13829],"type":"Point"}
}