{
  "type": "Feature",
  "properties": {
    "gn:admin1_code":"13.0",
    "gn:asciiname":"Ban Houaykhai-Nua",
    "gn:country_code":"LA",
    "gn:dem":856,
    "gn:feature_class":"P",
    "gn:feature_code":"PPL",
    "gn:name":"Ban Houaykhai-Nua",
    "gn:population":0,
    "gn:timezone":"Asia/Vientiane",
    "iso:country":"LA",
    "wof:name":"Ban Houaykhai-Nua",
    "wof:placetype":"locality"
},
  "geometry": {"coordinates":[101.26027999999999,19.75167],"type":"Point"}
}