{
  "type": "Feature",
  "properties": {
    "gn:admin1_code":"24.0",
    "gn:asciiname":"Ban Phakokhai",
    "gn:country_code":"LA",
    "gn:dem":169,
    "gn:feature_class":"P",
    "gn:feature_code":"PPL",
    "gn:name":"Ban Phak\u00f4khai",
    "gn:population":0,
    "gn:timezone":"Asia/Vientiane",
    "iso:country":"LA",
    "name:lao_x_preferred":[
        "Ban Phak\u00f4khai"
    ],
    "wof:name":"Ban Phakokhai",
    "wof:placetype":"locality"
},
  "geometry": {"coordinates":[102.88115000000001,18.18274],"type":"Point"}
}