{
  "type": "Feature",
  "properties": {
    "gn:admin1_code":"18.0",
    "gn:asciiname":"Ban Palan-Nua",
    "gn:country_code":"LA",
    "gn:dem":1054,
    "gn:feature_class":"P",
    "gn:feature_code":"PPL",
    "gn:name":"Ban Palan-Nua",
    "gn:population":0,
    "gn:timezone":"Asia/Vientiane",
    "iso:country":"LA",
    "name:lao_x_preferred":[
        "Ban Palan-Nua"
    ],
    "wof:name":"Ban Palan-Nua",
    "wof:placetype":"locality"
},
  "geometry": {"coordinates":[101.99379999999999,21.2451],"type":"Point"}
}