{
  "type": "Feature",
  "properties": {
    "gn:admin1_code":"17.0",
    "gn:asciiname":"Ban Naxang",
    "gn:country_code":"LA",
    "gn:dem":321,
    "gn:feature_class":"P",
    "gn:feature_code":"PPL",
    "gn:name":"Ban Naxang",
    "gn:population":0,
    "gn:timezone":"Asia/Vientiane",
    "iso:country":"LA",
    "name:lao_x_preferred":[
        "Ban Naxang"
    ],
    "wof:name":"Ban Naxang",
    "wof:placetype":"locality"
},
  "geometry": {"coordinates":[102.13363,19.86762],"type":"Point"}
}