{
  "type": "Feature",
  "properties": {
    "gn:admin1_code":"22.0",
    "gn:asciiname":"Ban Mokso",
    "gn:country_code":"LA",
    "gn:dem":431,
    "gn:feature_class":"P",
    "gn:feature_code":"PPL",
    "gn:name":"Ban M\u00f4ks\u00f4",
    "gn:population":0,
    "gn:timezone":"Asia/Vientiane",
    "iso:country":"LA",
    "name:lao_x_preferred":[
        "Ban M\u00f4ks\u00f4"
    ],
    "wof:name":"Ban Mokso",
    "wof:placetype":"locality"
},
  "geometry": {"coordinates":[100.79004999999999,20.03617],"type":"Point"}
}