{
  "type": "Feature",
  "properties": {
    "gn:admin1_code":"20.0",
    "gn:asciiname":"Ban Nong-Ahong",
    "gn:country_code":"LA",
    "gn:dem":173,
    "gn:feature_class":"P",
    "gn:feature_code":"PPL",
    "gn:name":"Ban Nong-Ahong",
    "gn:population":0,
    "gn:timezone":"Asia/Vientiane",
    "iso:country":"LA",
    "name:lao_x_preferred":[
        "Ban Nong-Ahong"
    ],
    "name:und_x_variant":[
        "Ban Nong A Nong"
    ],
    "wof:name":"Ban Nong-Ahong",
    "wof:placetype":"locality"
},
  "geometry": {"coordinates":[105.13294,16.68141],"type":"Point"}
}