{
  "type": "Feature",
  "properties": {
    "gn:admin1_code":"7.0",
    "gn:asciiname":"Ban Houayxeng",
    "gn:country_code":"LA",
    "gn:dem":351,
    "gn:feature_class":"P",
    "gn:feature_code":"PPL",
    "gn:name":"Ban Houayx\u00e8ng",
    "gn:population":0,
    "gn:timezone":"Asia/Vientiane",
    "iso:country":"LA",
    "name:lao_x_preferred":[
        "Ban Houayx\u00e8ng"
    ],
    "wof:name":"Ban Houayxeng",
    "wof:placetype":"locality"
},
  "geometry": {"coordinates":[101.0857,19.88712],"type":"Point"}
}