{
  "type": "Feature",
  "properties": {
    "gn:admin1_code":"26.0",
    "gn:asciiname":"Dak Lat",
    "gn:country_code":"LA",
    "gn:dem":1118,
    "gn:feature_class":"P",
    "gn:feature_code":"PPL",
    "gn:name":"Dak Lat",
    "gn:population":0,
    "gn:timezone":"Asia/Vientiane",
    "iso:country":"LA",
    "wof:name":"Dak Lat",
    "wof:placetype":"locality"
},
  "geometry": {"coordinates":[107.61667,15.33333],"type":"Point"}
}