{
  "type": "Feature",
  "properties": {
    "gn:admin1_code":"16.0",
    "gn:asciiname":"Ban Chakhamlu",
    "gn:country_code":"LA",
    "gn:dem":1039,
    "gn:feature_class":"P",
    "gn:feature_code":"PPL",
    "gn:name":"Ban Chakhamlu",
    "gn:population":0,
    "gn:timezone":"Asia/Vientiane",
    "iso:country":"LA",
    "name:lao_x_preferred":[
        "Ban Chakhamlu"
    ],
    "wof:name":"Ban Chakhamlu",
    "wof:placetype":"locality"
},
  "geometry": {"coordinates":[100.84681999999999,21.2663],"type":"Point"}
}