{
  "type": "Feature",
  "properties": {
    "gn:admin1_code":"20.0",
    "gn:asciiname":"Ban Lo",
    "gn:country_code":"LA",
    "gn:dem":255,
    "gn:feature_class":"P",
    "gn:feature_code":"PPL",
    "gn:name":"Ban L\u00f4",
    "gn:population":0,
    "gn:timezone":"Asia/Vientiane",
    "iso:country":"LA",
    "name:lao_x_preferred":[
        "Ban L\u00f4"
    ],
    "wof:name":"Ban Lo",
    "wof:placetype":"locality"
},
  "geometry": {"coordinates":[106.43385000000001,16.38606],"type":"Point"}
}