{
  "type": "Feature",
  "properties": {
    "gn:admin1_code":"17.0",
    "gn:asciiname":"Ban Cheng-Tai",
    "gn:country_code":"LA",
    "gn:dem":656,
    "gn:feature_class":"P",
    "gn:feature_code":"PPL",
    "gn:name":"Ban Ch\u00e8ng-Tai",
    "gn:population":0,
    "gn:timezone":"Asia/Vientiane",
    "iso:country":"LA",
    "name:lao_x_preferred":[
        "Ban Ch\u00e8ng-Tai"
    ],
    "wof:name":"Ban Cheng-Tai",
    "wof:placetype":"locality"
},
  "geometry": {"coordinates":[102.76548,20.96897],"type":"Point"}
}