{
  "type": "Feature",
  "properties": {
    "gn:admin1_code":"20.0",
    "gn:asciiname":"Ban Vangkhon-Nua",
    "gn:country_code":"LA",
    "gn:dem":152,
    "gn:feature_class":"P",
    "gn:feature_code":"PPL",
    "gn:name":"Ban Vangkhon-Nua",
    "gn:population":0,
    "gn:timezone":"Asia/Vientiane",
    "iso:country":"LA",
    "name:lao_x_preferred":[
        "Ban Vangkhon-Nua"
    ],
    "wof:name":"Ban Vangkhon-Nua",
    "wof:placetype":"locality"
},
  "geometry": {"coordinates":[105.41121,16.43577],"type":"Point"}
}