{
  "type": "Feature",
  "properties": {
    "gn:admin1_code":"18.0",
    "gn:asciiname":"Ban Phianglouang",
    "gn:country_code":"LA",
    "gn:dem":883,
    "gn:feature_class":"P",
    "gn:feature_code":"PPL",
    "gn:name":"Ban Phianglouang",
    "gn:population":0,
    "gn:timezone":"Asia/Vientiane",
    "iso:country":"LA",
    "name:lao_x_preferred":[
        "Ban Phianglouang"
    ],
    "name:und_x_variant":[
        "Sen Nam Sen Quang",
        "Ban Phlanglouang"
    ],
    "wof:name":"Ban Phianglouang",
    "wof:placetype":"locality"
},
  "geometry": {"coordinates":[102.22577,21.20958],"type":"Point"}
}