{
  "type": "Feature",
  "properties": {
    "gn:admin1_code":"15.0",
    "gn:asciiname":"Ban Pakthuk",
    "gn:country_code":"LA",
    "gn:dem":151,
    "gn:feature_class":"P",
    "gn:feature_code":"PPL",
    "gn:name":"Ban Pakthuk",
    "gn:population":0,
    "gn:timezone":"Asia/Vientiane",
    "iso:country":"LA",
    "name:lao_x_preferred":[
        "Ban Pakthuk"
    ],
    "wof:name":"Ban Pakthuk",
    "wof:placetype":"locality"
},
  "geometry": {"coordinates":[104.50548999999999,17.84153],"type":"Point"}
}