{
  "type": "Feature",
  "properties": {
    "gn:admin1_code":"18.0",
    "gn:asciiname":"Ban Mokkoang",
    "gn:country_code":"LA",
    "gn:dem":1015,
    "gn:feature_class":"P",
    "gn:feature_code":"PPL",
    "gn:name":"Ban M\u00f4kkoang",
    "gn:population":0,
    "gn:timezone":"Asia/Vientiane",
    "iso:country":"LA",
    "name:und_x_variant":[
        "Moc Quang",
        "Ban Moc Quang",
        "Ban M\u00f4kkoang"
    ],
    "wof:name":"Ban Mokkoang",
    "wof:placetype":"locality"
},
  "geometry": {"coordinates":[102.14851,21.19268],"type":"Point"}
}