{
  "type": "Feature",
  "properties": {
    "gn:admin1_code":"3.0",
    "gn:asciiname":"Ban Nakham",
    "gn:country_code":"LA",
    "gn:dem":278,
    "gn:feature_class":"P",
    "gn:feature_code":"PPL",
    "gn:name":"Ban Nakham",
    "gn:population":0,
    "gn:timezone":"Asia/Vientiane",
    "iso:country":"LA",
    "name:und_x_variant":[
        "Ban Na Kam",
        "Ban Nakham"
    ],
    "wof:name":"Ban Nakham",
    "wof:placetype":"locality"
},
  "geometry": {"coordinates":[104.00191,20.77951],"type":"Point"}
}