{
  "type": "Feature",
  "properties": {
    "gn:admin1_code":"7.0",
    "gn:asciiname":"Ban Senboun-Gnai",
    "gn:country_code":"LA",
    "gn:dem":1228,
    "gn:feature_class":"P",
    "gn:feature_code":"PPL",
    "gn:name":"Ban S\u00e9nboun-Gnai",
    "gn:population":0,
    "gn:timezone":"Asia/Vientiane",
    "iso:country":"LA",
    "name:lao_x_preferred":[
        "Ban S\u00e9nboun-Gnai"
    ],
    "wof:name":"Ban Senboun-Gnai",
    "wof:placetype":"locality"
},
  "geometry": {"coordinates":[101.85559000000001,20.19592],"type":"Point"}
}