{
  "type": "Feature",
  "properties": {
    "gn:admin1_code":"7.0",
    "gn:asciiname":"Ban Hay-Tai",
    "gn:country_code":"LA",
    "gn:dem":707,
    "gn:feature_class":"P",
    "gn:feature_code":"PPL",
    "gn:name":"Ban Hay-Tai",
    "gn:population":0,
    "gn:timezone":"Asia/Vientiane",
    "iso:country":"LA",
    "name:lao_x_preferred":[
        "Ban Hay-Tai"
    ],
    "wof:name":"Ban Hay-Tai",
    "wof:placetype":"locality"
},
  "geometry": {"coordinates":[101.30182000000001,20.19333],"type":"Point"}
}