{
  "type": "Feature",
  "properties": {
    "gn:admin1_code":"17.0",
    "gn:asciiname":"Ban Senchan",
    "gn:country_code":"LA",
    "gn:dem":1107,
    "gn:feature_class":"P",
    "gn:feature_code":"PPL",
    "gn:name":"Ban S\u00e8nchan",
    "gn:population":0,
    "gn:timezone":"Asia/Vientiane",
    "iso:country":"LA",
    "name:lao_x_preferred":[
        "Ban S\u00e8nchan"
    ],
    "wof:name":"Ban Senchan",
    "wof:placetype":"locality"
},
  "geometry": {"coordinates":[103.10098000000001,20.56434],"type":"Point"}
}