{
  "type": "Feature",
  "properties": {
    "gn:admin1_code":"26.0",
    "gn:asciiname":"Ban Don",
    "gn:country_code":"LA",
    "gn:dem":232,
    "gn:feature_class":"P",
    "gn:feature_code":"PPL",
    "gn:name":"Ban D\u00f4n",
    "gn:population":0,
    "gn:timezone":"Asia/Vientiane",
    "iso:country":"LA",
    "name:lao_x_preferred":[
        "Ban D\u00f4n"
    ],
    "wof:name":"Ban Don",
    "wof:placetype":"locality"
},
  "geometry": {"coordinates":[106.75721,15.80151],"type":"Point"}
}