{
  "type": "Feature",
  "properties": {
    "gn:admin1_code":"19.0",
    "gn:asciiname":"Ban Pangandao",
    "gn:country_code":"LA",
    "gn:dem":364,
    "gn:feature_class":"P",
    "gn:feature_code":"PPL",
    "gn:name":"Ban Pangandao",
    "gn:population":0,
    "gn:timezone":"Asia/Vientiane",
    "iso:country":"LA",
    "name:lao_x_preferred":[
        "Ban Pangandao"
    ],
    "name:und_x_variant":[
        "Po Teul",
        "Pa Gnham (3)",
        "Pa Gnham"
    ],
    "wof:name":"Ban Pangandao",
    "wof:placetype":"locality"
},
  "geometry": {"coordinates":[106.68312,16.22632999999999],"type":"Point"}
}