{
  "type": "Feature",
  "properties": {
    "gn:admin1_code":"16.0",
    "gn:asciiname":"Ban Konlang",
    "gn:country_code":"LA",
    "gn:dem":975,
    "gn:feature_class":"P",
    "gn:feature_code":"PPL",
    "gn:name":"Ban Konlang",
    "gn:population":0,
    "gn:timezone":"Asia/Vientiane",
    "iso:country":"LA",
    "name:lao_x_preferred":[
        "Ban Konlang"
    ],
    "wof:name":"Ban Konlang",
    "wof:placetype":"locality"
},
  "geometry": {"coordinates":[101.49486,20.48757],"type":"Point"}
}