{
  "type": "Feature",
  "properties": {
    "gn:admin1_code":"18.0",
    "gn:asciiname":"Ban Chomxon",
    "gn:country_code":"LA",
    "gn:dem":1141,
    "gn:feature_class":"P",
    "gn:feature_code":"PPL",
    "gn:name":"Ban Chomx\u00f4n",
    "gn:population":0,
    "gn:timezone":"Asia/Vientiane",
    "iso:country":"LA",
    "name:lao_x_preferred":[
        "Ban Chomx\u00f4n"
    ],
    "wof:name":"Ban Chomxon",
    "wof:placetype":"locality"
},
  "geometry": {"coordinates":[102.52638,21.1519],"type":"Point"}
}