{
  "type": "Feature",
  "properties": {
    "gn:admin1_code":"20.0",
    "gn:asciiname":"Ban Thadua-Gnai",
    "gn:country_code":"LA",
    "gn:dem":140,
    "gn:feature_class":"P",
    "gn:feature_code":"PPL",
    "gn:name":"Ban Thadua-Gnai",
    "gn:population":0,
    "gn:timezone":"Asia/Vientiane",
    "iso:country":"LA",
    "name:lao_x_preferred":[
        "Ban Thadua-Gnai"
    ],
    "name:und_x_variant":[
        "Ban Thadua"
    ],
    "wof:name":"Ban Thadua-Gnai",
    "wof:placetype":"locality"
},
  "geometry": {"coordinates":[105.1742,16.07215],"type":"Point"}
}