{
  "type": "Feature",
  "properties": {
    "gn:admin1_code":"18.0",
    "gn:asciiname":"Ban Yapoung",
    "gn:country_code":"LA",
    "gn:dem":1118,
    "gn:feature_class":"P",
    "gn:feature_code":"PPL",
    "gn:name":"Ban Yapoung",
    "gn:population":0,
    "gn:timezone":"Asia/Vientiane",
    "iso:country":"LA",
    "name:lao_x_preferred":[
        "Ban Yapoung"
    ],
    "wof:name":"Ban Yapoung",
    "wof:placetype":"locality"
},
  "geometry": {"coordinates":[102.05242,21.64448],"type":"Point"}
}