{
  "type": "Feature",
  "properties": {
    "gn:admin1_code":"14.0",
    "gn:asciiname":"Ban Lalkhouay",
    "gn:country_code":"LA",
    "gn:dem":1440,
    "gn:feature_class":"P",
    "gn:feature_code":"PPL",
    "gn:name":"Ban Lalkhouay",
    "gn:population":0,
    "gn:timezone":"Asia/Vientiane",
    "iso:country":"LA",
    "name:lao_x_preferred":[
        "Ban Lalkhouay"
    ],
    "wof:name":"Ban Lalkhouay",
    "wof:placetype":"locality"
},
  "geometry": {"coordinates":[104.05383,19.11644],"type":"Point"}
}