{
  "type": "Feature",
  "properties": {
    "gn:admin1_code":"15.0",
    "gn:asciiname":"Ban Vangyiam",
    "gn:country_code":"LA",
    "gn:dem":208,
    "gn:feature_class":"P",
    "gn:feature_code":"PPL",
    "gn:name":"Ban Vangyiam",
    "gn:population":0,
    "gn:timezone":"Asia/Vientiane",
    "iso:country":"LA",
    "name:lao_x_preferred":[
        "Ban Vangyiam"
    ],
    "name:und_x_variant":[
        "Ban Van Yeng",
        "Ban Van Veng",
        "Ban Vang Yiam"
    ],
    "wof:name":"Ban Vangyiam",
    "wof:placetype":"locality"
},
  "geometry": {"coordinates":[105.06319999999999,17.65505],"type":"Point"}
}