{
  "type": "Feature",
  "properties": {
    "gn:admin1_code":"1.0",
    "gn:asciiname":"Ban Nongping",
    "gn:country_code":"LA",
    "gn:dem":312,
    "gn:feature_class":"P",
    "gn:feature_code":"PPL",
    "gn:name":"Ban Nongping",
    "gn:population":0,
    "gn:timezone":"Asia/Vientiane",
    "iso:country":"LA",
    "name:lao_x_preferred":[
        "Ban Nongping"
    ],
    "wof:name":"Ban Nongping",
    "wof:placetype":"locality"
},
  "geometry": {"coordinates":[106.27002,14.87475],"type":"Point"}
}