{
  "type": "Feature",
  "properties": {
    "gn:admin1_code":"19.0",
    "gn:asciiname":"Ban Okat-Noy",
    "gn:country_code":"LA",
    "gn:dem":138,
    "gn:feature_class":"P",
    "gn:feature_code":"PPL",
    "gn:name":"Ban \u00d4kat-Noy",
    "gn:population":0,
    "gn:timezone":"Asia/Vientiane",
    "iso:country":"LA",
    "name:lao_x_preferred":[
        "Ban \u00d4kat-Noy"
    ],
    "wof:name":"Ban Okat-Noy",
    "wof:placetype":"locality"
},
  "geometry": {"coordinates":[105.77328,15.49515],"type":"Point"}
}