{
  "type": "Feature",
  "properties": {
    "gn:admin1_code":"7.0",
    "gn:asciiname":"Ban Houayhai",
    "gn:country_code":"LA",
    "gn:dem":355,
    "gn:feature_class":"P",
    "gn:feature_code":"PPL",
    "gn:name":"Ban Houayhai",
    "gn:population":0,
    "gn:timezone":"Asia/Vientiane",
    "iso:country":"LA",
    "name:und_x_variant":[
        "Ban Houei Hai",
        "Ban Houayhai"
    ],
    "wof:name":"Ban Houayhai",
    "wof:placetype":"locality"
},
  "geometry": {"coordinates":[102.01667,20.06667],"type":"Point"}
}