{
  "type": "Feature",
  "properties": {
    "gn:admin1_code":"27.0",
    "gn:asciiname":"Ban Gnouat",
    "gn:country_code":"LA",
    "gn:dem":193,
    "gn:feature_class":"P",
    "gn:feature_code":"PPL",
    "gn:name":"Ban Gnouat",
    "gn:population":0,
    "gn:timezone":"Asia/Vientiane",
    "iso:country":"LA",
    "name:und_x_variant":[
        "Ban Nhouat"
    ],
    "wof:name":"Ban Gnouat",
    "wof:placetype":"locality"
},
  "geometry": {"coordinates":[102.39673999999999,18.57405],"type":"Point"}
}