{
  "type": "Feature",
  "properties": {
    "gn:admin1_code":"2.0",
    "gn:asciiname":"Ban Nake",
    "gn:country_code":"LA",
    "gn:dem":116,
    "gn:feature_class":"P",
    "gn:feature_code":"PPL",
    "gn:name":"Ban Nak\u00e8",
    "gn:population":0,
    "gn:timezone":"Asia/Vientiane",
    "iso:country":"LA",
    "name:lao_x_preferred":[
        "Ban Nak\u00e8"
    ],
    "name:und_x_variant":[
        "Ban Nak\u00ea"
    ],
    "wof:name":"Ban Nake",
    "wof:placetype":"locality"
},
  "geometry": {"coordinates":[105.84701,15.26927],"type":"Point"}
}