{
  "type": "Feature",
  "properties": {
    "gn:admin1_code":"24.0",
    "gn:asciiname":"Ban Nongviangkham",
    "gn:country_code":"LA",
    "gn:dem":184,
    "gn:feature_class":"P",
    "gn:feature_code":"PPL",
    "gn:name":"Ban Nongviangkham",
    "gn:population":0,
    "gn:timezone":"Asia/Vientiane",
    "iso:country":"LA",
    "name:lao_x_preferred":[
        "Ban Nongviangkham"
    ],
    "wof:name":"Ban Nongviangkham",
    "wof:placetype":"locality"
},
  "geometry": {"coordinates":[102.63088,18.0542],"type":"Point"}
}