{
  "type": "Feature",
  "properties": {
    "gn:admin1_code":"20.0",
    "gn:asciiname":"Ban Phonmoung",
    "gn:country_code":"LA",
    "gn:dem":199,
    "gn:feature_class":"P",
    "gn:feature_code":"PPL",
    "gn:name":"Ban Ph\u00f4nmoung",
    "gn:population":0,
    "gn:timezone":"Asia/Vientiane",
    "iso:country":"LA",
    "name:lao_x_preferred":[
        "Ban Ph\u00f4nmoung"
    ],
    "wof:name":"Ban Phonmoung",
    "wof:placetype":"locality"
},
  "geometry": {"coordinates":[106.19342,16.70479],"type":"Point"}
}