{
  "type": "Feature",
  "properties": {
    "gn:admin1_code":"20.0",
    "gn:asciiname":"Ban Plouan",
    "gn:country_code":"LA",
    "gn:dem":512,
    "gn:feature_class":"P",
    "gn:feature_code":"PPL",
    "gn:name":"Ban Plouan",
    "gn:population":0,
    "gn:timezone":"Asia/Vientiane",
    "iso:country":"LA",
    "name:lao_x_preferred":[
        "Ban Plouan"
    ],
    "wof:name":"Ban Plouan",
    "wof:placetype":"locality"
},
  "geometry": {"coordinates":[106.36654,16.59514],"type":"Point"}
}