{
  "type": "Feature",
  "properties": {
    "gn:admin1_code":"2.0",
    "gn:asciiname":"Ban He",
    "gn:country_code":"LA",
    "gn:dem":105,
    "gn:feature_class":"P",
    "gn:feature_code":"PPL",
    "gn:name":"Ban H\u00e8",
    "gn:population":0,
    "gn:timezone":"Asia/Vientiane",
    "iso:country":"LA",
    "name:lao_x_preferred":[
        "Ban H\u00e8"
    ],
    "wof:name":"Ban He",
    "wof:placetype":"locality"
},
  "geometry": {"coordinates":[105.80311,15.14159],"type":"Point"}
}