{
  "type": "Feature",
  "properties": {
    "gn:admin1_code":"16.0",
    "gn:asciiname":"Ban Oon-Noy",
    "gn:country_code":"LA",
    "gn:dem":743,
    "gn:feature_class":"P",
    "gn:feature_code":"PPL",
    "gn:name":"Ban \u00d4on-Noy",
    "gn:population":0,
    "gn:timezone":"Asia/Vientiane",
    "iso:country":"LA",
    "name:lao_x_preferred":[
        "Ban \u00d4on-Noy"
    ],
    "wof:name":"Ban Oon-Noy",
    "wof:placetype":"locality"
},
  "geometry": {"coordinates":[101.61505,21.05426],"type":"Point"}
}