{
  "type": "Feature",
  "properties": {
    "gn:admin1_code":"14.0",
    "gn:asciiname":"Ban Phalouang",
    "gn:cc2":"LA",
    "gn:country_code":"LA",
    "gn:dem":1447,
    "gn:feature_class":"P",
    "gn:feature_code":"PPL",
    "gn:name":"Ban Phalouang",
    "gn:population":0,
    "gn:timezone":"Asia/Vientiane",
    "iso:country":"LA",
    "name:und_x_variant":[
        "Ban Pha Luong",
        "Ban Phalouang"
    ],
    "wof:name":"Ban Phalouang",
    "wof:placetype":"locality"
},
  "geometry": {"coordinates":[103.73333,19.48333],"type":"Point"}
}