{
  "type": "Feature",
  "properties": {
    "gn:admin1_code":"2.0",
    "gn:asciiname":"Ban Nongphanouan",
    "gn:country_code":"LA",
    "gn:dem":781,
    "gn:feature_class":"P",
    "gn:feature_code":"PPL",
    "gn:name":"Ban Nongphanouan",
    "gn:population":0,
    "gn:timezone":"Asia/Vientiane",
    "iso:country":"LA",
    "name:lao_x_preferred":[
        "Ban Nongphanouan"
    ],
    "wof:name":"Ban Nongphanouan",
    "wof:placetype":"locality"
},
  "geometry": {"coordinates":[106.52639000000001,15.04235],"type":"Point"}
}