{
  "type": "Feature",
  "properties": {
    "gn:admin1_code":"27.0",
    "gn:asciiname":"Ban Natao",
    "gn:country_code":"LA",
    "gn:dem":268,
    "gn:feature_class":"P",
    "gn:feature_code":"PPL",
    "gn:name":"Ban Natao",
    "gn:population":0,
    "gn:timezone":"Asia/Vientiane",
    "iso:country":"LA",
    "name:lao_x_preferred":[
        "Ban Natao"
    ],
    "wof:name":"Ban Natao",
    "wof:placetype":"locality"
},
  "geometry": {"coordinates":[101.90357,18.82533],"type":"Point"}
}