{
  "type": "Feature",
  "properties": {
    "gn:admin1_code":"19.0",
    "gn:asciiname":"Pril Riong",
    "gn:country_code":"LA",
    "gn:dem":702,
    "gn:feature_class":"P",
    "gn:feature_code":"PPL",
    "gn:name":"Pril Ri\u00f4ng",
    "gn:population":0,
    "gn:timezone":"Asia/Vientiane",
    "iso:country":"LA",
    "wof:name":"Pril Riong",
    "wof:placetype":"locality"
},
  "geometry": {"coordinates":[106.88333,16.36667000000001],"type":"Point"}
}