{
  "type": "Feature",
  "properties": {
    "gn:admin1_code":"18.0",
    "gn:asciiname":"Ban Taliao-Noy",
    "gn:country_code":"LA",
    "gn:dem":643,
    "gn:feature_class":"P",
    "gn:feature_code":"PPL",
    "gn:name":"Ban Taliao-Noy",
    "gn:population":0,
    "gn:timezone":"Asia/Vientiane",
    "iso:country":"LA",
    "name:lao_x_preferred":[
        "Ban Taliao-Noy"
    ],
    "wof:name":"Ban Taliao-Noy",
    "wof:placetype":"locality"
},
  "geometry": {"coordinates":[102.74414,21.45733],"type":"Point"}
}