{
  "type": "Feature",
  "properties": {
    "gn:admin1_code":"16.0",
    "gn:asciiname":"Ban Phoukhang",
    "gn:country_code":"LA",
    "gn:dem":932,
    "gn:feature_class":"P",
    "gn:feature_code":"PPL",
    "gn:name":"Ban Phoukhang",
    "gn:population":0,
    "gn:timezone":"Asia/Vientiane",
    "iso:country":"LA",
    "name:lao_x_preferred":[
        "Ban Phoukhang"
    ],
    "wof:name":"Ban Phoukhang",
    "wof:placetype":"locality"
},
  "geometry": {"coordinates":[101.28928000000001,20.45613],"type":"Point"}
}