{
  "type": "Feature",
  "properties": {
    "gn:admin1_code":"20.0",
    "gn:asciiname":"Ban Naxeng-Nua",
    "gn:country_code":"LA",
    "gn:dem":152,
    "gn:feature_class":"P",
    "gn:feature_code":"PPL",
    "gn:name":"Ban Nax\u00e8ng-Nua",
    "gn:population":0,
    "gn:timezone":"Asia/Vientiane",
    "iso:country":"LA",
    "name:lao_x_preferred":[
        "Ban Nax\u00e8ng-Nua"
    ],
    "wof:name":"Ban Naxeng-Nua",
    "wof:placetype":"locality"
},
  "geometry": {"coordinates":[105.59596999999999,16.22983],"type":"Point"}
}