{
  "type": "Feature",
  "properties": {
    "gn:admin1_code":"2.0",
    "gn:asciiname":"Ban Nakham-Noy",
    "gn:country_code":"LA",
    "gn:dem":114,
    "gn:feature_class":"P",
    "gn:feature_code":"PPL",
    "gn:name":"Ban Nakham-Noy",
    "gn:population":0,
    "gn:timezone":"Asia/Vientiane",
    "iso:country":"LA",
    "name:lao_x_preferred":[
        "Ban Nakham-Noy"
    ],
    "wof:name":"Ban Nakham-Noy",
    "wof:placetype":"locality"
},
  "geometry": {"coordinates":[105.96971000000001,14.81647],"type":"Point"}
}