{
  "type": "Feature",
  "properties": {
    "gn:admin1_code":"3.0",
    "gn:asciiname":"Ban Na Bone",
    "gn:country_code":"LA",
    "gn:dem":271,
    "gn:feature_class":"P",
    "gn:feature_code":"PPL",
    "gn:name":"Ban Na Bone",
    "gn:population":0,
    "gn:timezone":"Asia/Vientiane",
    "iso:country":"LA",
    "wof:name":"Ban Na Bone",
    "wof:placetype":"locality"
},
  "geometry": {"coordinates":[103.98333,20.83333],"type":"Point"}
}