{
  "type": "Feature",
  "properties": {
    "gn:admin1_code":"22.0",
    "gn:asciiname":"Ban Taphou",
    "gn:country_code":"LA",
    "gn:dem":732,
    "gn:feature_class":"P",
    "gn:feature_code":"PPL",
    "gn:name":"Ban Taphou",
    "gn:population":0,
    "gn:timezone":"Asia/Vientiane",
    "iso:country":"LA",
    "name:lao_x_preferred":[
        "Ban Taphou"
    ],
    "wof:name":"Ban Taphou",
    "wof:placetype":"locality"
},
  "geometry": {"coordinates":[101.14917,20.23667],"type":"Point"}
}