{
  "type": "Feature",
  "properties": {
    "gn:admin1_code":"7.0",
    "gn:asciiname":"Ban Chap-Lata",
    "gn:country_code":"LA",
    "gn:dem":344,
    "gn:feature_class":"P",
    "gn:feature_code":"PPL",
    "gn:name":"Ban Chap-Lata",
    "gn:population":0,
    "gn:timezone":"Asia/Vientiane",
    "iso:country":"LA",
    "name:lao_x_preferred":[
        "Ban Chap-Lata"
    ],
    "wof:name":"Ban Chap-Lata",
    "wof:placetype":"locality"
},
  "geometry": {"coordinates":[100.94542,19.87125],"type":"Point"}
}