{
  "type": "Feature",
  "properties": {
    "gn:admin1_code":"1.0",
    "gn:asciiname":"Ban Gnakou",
    "gn:country_code":"LA",
    "gn:dem":101,
    "gn:feature_class":"P",
    "gn:feature_code":"PPL",
    "gn:name":"Ban Gnakou",
    "gn:population":0,
    "gn:timezone":"Asia/Vientiane",
    "iso:country":"LA",
    "name:lao_x_preferred":[
        "Ban Gnakou"
    ],
    "wof:name":"Ban Gnakou",
    "wof:placetype":"locality"
},
  "geometry": {"coordinates":[106.71809,14.6441],"type":"Point"}
}