{
  "type": "Feature",
  "properties": {
    "gn:admin1_code":"15.0",
    "gn:asciiname":"Ban Phasanum",
    "gn:country_code":"LA",
    "gn:dem":161,
    "gn:feature_class":"P",
    "gn:feature_code":"PPL",
    "gn:name":"Ban Phasanum",
    "gn:population":0,
    "gn:timezone":"Asia/Vientiane",
    "iso:country":"LA",
    "name:lao_x_preferred":[
        "Ban Phasanum"
    ],
    "wof:name":"Ban Phasanum",
    "wof:placetype":"locality"
},
  "geometry": {"coordinates":[105.29581,17.31663],"type":"Point"}
}