{
  "type": "Feature",
  "properties": {
    "gn:admin1_code":"23.0",
    "gn:asciiname":"Ban Phonxai",
    "gn:country_code":"LA",
    "gn:dem":500,
    "gn:feature_class":"P",
    "gn:feature_code":"PPL",
    "gn:name":"Ban Phonxai",
    "gn:population":0,
    "gn:timezone":"Asia/Vientiane",
    "iso:country":"LA",
    "name:lao_x_preferred":[
        "Ban Phonxai"
    ],
    "wof:name":"Ban Phonxai",
    "wof:placetype":"locality"
},
  "geometry": {"coordinates":[105.02979999999999,18.10692],"type":"Point"}
}