{
  "type": "Feature",
  "properties": {
    "gn:admin1_code":"18.0",
    "gn:asciiname":"Sen Kham",
    "gn:country_code":"LA",
    "gn:dem":542,
    "gn:feature_class":"P",
    "gn:feature_code":"PPL",
    "gn:name":"Sen Kham",
    "gn:population":0,
    "gn:timezone":"Asia/Vientiane",
    "iso:country":"LA",
    "wof:name":"Sen Kham",
    "wof:placetype":"locality"
},
  "geometry": {"coordinates":[102.53333000000001,21.28333],"type":"Point"}
}