{
  "type": "Feature",
  "properties": {
    "gn:admin1_code":"24.0",
    "gn:asciiname":"Ban Oudom-Phon",
    "gn:country_code":"LA",
    "gn:dem":180,
    "gn:feature_class":"P",
    "gn:feature_code":"PPL",
    "gn:name":"Ban Oud\u00f4m-Ph\u00f4n",
    "gn:population":0,
    "gn:timezone":"Asia/Vientiane",
    "iso:country":"LA",
    "name:lao_x_preferred":[
        "Ban Oud\u00f4m-Ph\u00f4n"
    ],
    "wof:name":"Ban Oudom-Phon",
    "wof:placetype":"locality"
},
  "geometry": {"coordinates":[102.68256,18.1303],"type":"Point"}
}