{
  "type": "Feature",
  "properties": {
    "gn:admin1_code":"27.0",
    "gn:asciiname":"Ban Souanmon",
    "gn:country_code":"LA",
    "gn:dem":216,
    "gn:feature_class":"P",
    "gn:feature_code":"PPL",
    "gn:name":"Ban Souanmon",
    "gn:population":0,
    "gn:timezone":"Asia/Vientiane",
    "iso:country":"LA",
    "name:lao_x_preferred":[
        "Ban Souanmon"
    ],
    "wof:name":"Ban Souanmon",
    "wof:placetype":"locality"
},
  "geometry": {"coordinates":[102.20077000000001,18.44041],"type":"Point"}
}