{
  "type": "Feature",
  "properties": {
    "gn:admin1_code":"2.0",
    "gn:asciiname":"Ban Dondou",
    "gn:cc2":"LA",
    "gn:country_code":"LA",
    "gn:dem":87,
    "gn:feature_class":"P",
    "gn:feature_code":"PPL",
    "gn:name":"Ban Dondou",
    "gn:population":0,
    "gn:timezone":"Asia/Vientiane",
    "iso:country":"LA",
    "name:und_x_variant":[
        "Ban Done Dou",
        "Ban Dondou"
    ],
    "wof:name":"Ban Dondou",
    "wof:placetype":"locality"
},
  "geometry": {"coordinates":[105.90000000000001,14.91667],"type":"Point"}
}