{
  "type": "Feature",
  "properties": {
    "gn:admin1_code":"20.0",
    "gn:asciiname":"Ban Xe",
    "gn:country_code":"LA",
    "gn:dem":146,
    "gn:feature_class":"P",
    "gn:feature_code":"PPL",
    "gn:name":"Ban X\u00e9",
    "gn:population":0,
    "gn:timezone":"Asia/Vientiane",
    "iso:country":"LA",
    "name:und_x_variant":[
        "Ban S\u00e9",
        "Ban X\u00e9"
    ],
    "wof:name":"Ban Xe",
    "wof:placetype":"locality"
},
  "geometry": {"coordinates":[105.26528999999999,16.54749],"type":"Point"}
}