{
  "type": "Feature",
  "properties": {
    "gn:admin1_code":"20.0",
    "gn:asciiname":"Ban Thoun",
    "gn:country_code":"LA",
    "gn:dem":179,
    "gn:feature_class":"P",
    "gn:feature_code":"PPL",
    "gn:name":"Ban Thoun",
    "gn:population":0,
    "gn:timezone":"Asia/Vientiane",
    "iso:country":"LA",
    "name:und_x_variant":[
        "Veung",
        "Ban Thoun",
        "Ban Thoun Kham",
        "Ban Thoun (2)"
    ],
    "wof:name":"Ban Thoun",
    "wof:placetype":"locality"
},
  "geometry": {"coordinates":[106.17198999999999,16.36652999999999],"type":"Point"}
}