{
  "type": "Feature",
  "properties": {
    "gn:admin1_code":"20.0",
    "gn:asciiname":"Ban Nathongtoun",
    "gn:country_code":"LA",
    "gn:dem":196,
    "gn:feature_class":"P",
    "gn:feature_code":"PPL",
    "gn:name":"Ban Nath\u00f4ngtoun",
    "gn:population":0,
    "gn:timezone":"Asia/Vientiane",
    "iso:country":"LA",
    "name:und_x_variant":[
        "Ban Na Thong Taun",
        "Ban Na Thong Toun",
        "Ban Nath\u00f4ngtoun"
    ],
    "wof:name":"Ban Nathongtoun",
    "wof:placetype":"locality"
},
  "geometry": {"coordinates":[105.7608,17.06647],"type":"Point"}
}