{
  "type": "Feature",
  "properties": {
    "gn:admin1_code":"16.0",
    "gn:asciiname":"Ban Phochan",
    "gn:country_code":"LA",
    "gn:dem":1121,
    "gn:feature_class":"P",
    "gn:feature_code":"PPL",
    "gn:name":"Ban Phochan",
    "gn:population":0,
    "gn:timezone":"Asia/Vientiane",
    "iso:country":"LA",
    "name:lao_x_preferred":[
        "Ban Phochan"
    ],
    "wof:name":"Ban Phochan",
    "wof:placetype":"locality"
},
  "geometry": {"coordinates":[100.82557,21.05346],"type":"Point"}
}