{
  "type": "Feature",
  "properties": {
    "gn:admin1_code":"20.0",
    "gn:asciiname":"Ban Khokkong",
    "gn:country_code":"LA",
    "gn:dem":180,
    "gn:feature_class":"P",
    "gn:feature_code":"PPL",
    "gn:name":"Ban Kh\u00f4kkong",
    "gn:population":0,
    "gn:timezone":"Asia/Vientiane",
    "iso:country":"LA",
    "name:und_x_variant":[
        "Ban Na Khok Kong",
        "Ban Kh\u00f4kkong"
    ],
    "wof:name":"Ban Khokkong",
    "wof:placetype":"locality"
},
  "geometry": {"coordinates":[105.21238999999998,16.81488],"type":"Point"}
}