{
  "type": "Feature",
  "properties": {
    "gn:admin1_code":"22.0",
    "gn:asciiname":"Ban Mai-Muangkhon",
    "gn:country_code":"LA",
    "gn:dem":807,
    "gn:feature_class":"P",
    "gn:feature_code":"PPL",
    "gn:name":"Ban Mai-Muangkhon",
    "gn:population":0,
    "gn:timezone":"Asia/Vientiane",
    "iso:country":"LA",
    "name:lao_x_preferred":[
        "Ban Mai-Muangkhon"
    ],
    "wof:name":"Ban Mai-Muangkhon",
    "wof:placetype":"locality"
},
  "geometry": {"coordinates":[100.38889,20.76889],"type":"Point"}
}