{
  "type": "Feature",
  "properties": {
    "gn:admin1_code":"19.0",
    "gn:asciiname":"Ban Soungkalang",
    "gn:country_code":"LA",
    "gn:dem":222,
    "gn:feature_class":"P",
    "gn:feature_code":"PPL",
    "gn:name":"Ban Soungkalang",
    "gn:population":0,
    "gn:timezone":"Asia/Vientiane",
    "iso:country":"LA",
    "wof:name":"Ban Soungkalang",
    "wof:placetype":"locality"
},
  "geometry": {"coordinates":[106.33333,15.61667],"type":"Point"}
}