{
  "type": "Feature",
  "properties": {
    "gn:admin1_code":"7.0",
    "gn:asciiname":"Ban Dongbang",
    "gn:country_code":"LA",
    "gn:dem":1086,
    "gn:feature_class":"P",
    "gn:feature_code":"PPL",
    "gn:name":"Ban D\u00f4ngbang",
    "gn:population":0,
    "gn:timezone":"Asia/Vientiane",
    "iso:country":"LA",
    "name:lao_x_preferred":[
        "Ban D\u00f4ngbang"
    ],
    "wof:name":"Ban Dongbang",
    "wof:placetype":"locality"
},
  "geometry": {"coordinates":[101.36411,20.25518],"type":"Point"}
}