{
  "type": "Feature",
  "properties": {
    "gn:admin1_code":"19.0",
    "gn:asciiname":"Ban Nathan",
    "gn:country_code":"LA",
    "gn:dem":210,
    "gn:feature_class":"P",
    "gn:feature_code":"PPL",
    "gn:name":"Ban Nathan",
    "gn:population":0,
    "gn:timezone":"Asia/Vientiane",
    "iso:country":"LA",
    "name:und_x_variant":[
        "Ban Nathon",
        "Ban Nathan"
    ],
    "wof:name":"Ban Nathan",
    "wof:placetype":"locality"
},
  "geometry": {"coordinates":[106.37179,15.66583],"type":"Point"}
}