{
  "type": "Feature",
  "properties": {
    "gn:admin1_code":"3.0",
    "gn:asciiname":"Ban Houayhai",
    "gn:country_code":"LA",
    "gn:dem":875,
    "gn:feature_class":"P",
    "gn:feature_code":"PPL",
    "gn:name":"Ban Houayhai",
    "gn:population":0,
    "gn:timezone":"Asia/Vientiane",
    "iso:country":"LA",
    "name:und_x_variant":[
        "Ban Houe\u00ef Ha\u00ef",
        "Ban Houayhai"
    ],
    "wof:name":"Ban Houayhai",
    "wof:placetype":"locality"
},
  "geometry": {"coordinates":[103.92574999999999,19.99758],"type":"Point"}
}