{
  "type": "Feature",
  "properties": {
    "gn:admin1_code":"3.0",
    "gn:asciiname":"Ban Poung",
    "gn:country_code":"LA",
    "gn:dem":623,
    "gn:feature_class":"P",
    "gn:feature_code":"PPL",
    "gn:name":"Ban Poung",
    "gn:population":0,
    "gn:timezone":"Asia/Vientiane",
    "iso:country":"LA",
    "name:und_x_variant":[
        "Ban Poung (2)",
        "Ban Poung"
    ],
    "wof:name":"Ban Poung",
    "wof:placetype":"locality"
},
  "geometry": {"coordinates":[104.28563,20.47682],"type":"Point"}
}