{
  "type": "Feature",
  "properties": {
    "gn:admin1_code":"27.0",
    "gn:asciiname":"Ban Bouakmeo",
    "gn:country_code":"LA",
    "gn:dem":1110,
    "gn:feature_class":"P",
    "gn:feature_code":"PPL",
    "gn:name":"Ban Bouakm\u00e8o",
    "gn:population":0,
    "gn:timezone":"Asia/Vientiane",
    "iso:country":"LA",
    "name:lao_x_preferred":[
        "Ban Bouakm\u00e8o"
    ],
    "wof:name":"Ban Bouakmeo",
    "wof:placetype":"locality"
},
  "geometry": {"coordinates":[102.45650999999999,19.26396],"type":"Point"}
}