{
  "type": "Feature",
  "properties": {
    "gn:admin1_code":"13.0",
    "gn:asciiname":"Ban Nagnai",
    "gn:country_code":"LA",
    "gn:dem":360,
    "gn:feature_class":"P",
    "gn:feature_code":"PPL",
    "gn:name":"Ban Nagnai",
    "gn:population":0,
    "gn:timezone":"Asia/Vientiane",
    "iso:country":"LA",
    "name:lao_x_preferred":[
        "Ban Nagnai"
    ],
    "wof:name":"Ban Nagnai",
    "wof:placetype":"locality"
},
  "geometry": {"coordinates":[101.32205999999999,18.30224],"type":"Point"}
}