{
  "type": "Feature",
  "properties": {
    "gn:admin1_code":"19.0",
    "gn:asciiname":"Ban Houayhoun-Nua",
    "gn:country_code":"LA",
    "gn:dem":668,
    "gn:feature_class":"P",
    "gn:feature_code":"PPL",
    "gn:name":"Ban Houayhoun-Nua",
    "gn:population":0,
    "gn:timezone":"Asia/Vientiane",
    "iso:country":"LA",
    "name:lao_x_preferred":[
        "Ban Houayhoun-Nua"
    ],
    "wof:name":"Ban Houayhoun-Nua",
    "wof:placetype":"locality"
},
  "geometry": {"coordinates":[106.151,15.39879],"type":"Point"}
}