{
  "type": "Feature",
  "properties": {
    "gn:admin1_code":"3.0",
    "gn:asciiname":"Ban Kohai",
    "gn:country_code":"LA",
    "gn:dem":1037,
    "gn:feature_class":"P",
    "gn:feature_code":"PPL",
    "gn:name":"Ban Kohai",
    "gn:population":0,
    "gn:timezone":"Asia/Vientiane",
    "iso:country":"LA",
    "name:lao_x_preferred":[
        "Ban Kohai"
    ],
    "wof:name":"Ban Kohai",
    "wof:placetype":"locality"
},
  "geometry": {"coordinates":[104.24791,20.89247],"type":"Point"}
}