{
  "type": "Feature",
  "properties": {
    "gn:admin1_code":"15.0",
    "gn:asciiname":"Ban Naxong",
    "gn:country_code":"LA",
    "gn:dem":196,
    "gn:feature_class":"P",
    "gn:feature_code":"PPL",
    "gn:name":"Ban Nax\u00f4ng",
    "gn:population":0,
    "gn:timezone":"Asia/Vientiane",
    "iso:country":"LA",
    "name:und_x_variant":[
        "Ban Na Song",
        "Ban Nax\u00f4ng"
    ],
    "wof:name":"Ban Naxong",
    "wof:placetype":"locality"
},
  "geometry": {"coordinates":[105.55064,17.19426],"type":"Point"}
}