{
  "type": "Feature",
  "properties": {
    "gn:admin1_code":"18.0",
    "gn:asciiname":"Ban Mokkong-Kao",
    "gn:country_code":"LA",
    "gn:dem":1005,
    "gn:feature_class":"P",
    "gn:feature_code":"PPL",
    "gn:name":"Ban M\u00f4kk\u00f4ng-Kao",
    "gn:population":0,
    "gn:timezone":"Asia/Vientiane",
    "iso:country":"LA",
    "name:lao_x_preferred":[
        "Ban M\u00f4kk\u00f4ng-Kao"
    ],
    "wof:name":"Ban Mokkong-Kao",
    "wof:placetype":"locality"
},
  "geometry": {"coordinates":[102.15366,21.20492],"type":"Point"}
}