{
  "type": "Feature",
  "properties": {
    "gn:admin1_code":"22.0",
    "gn:asciiname":"Ban Phamon",
    "gn:country_code":"LA",
    "gn:dem":948,
    "gn:feature_class":"P",
    "gn:feature_code":"PPL",
    "gn:name":"Ban Pham\u00f4n",
    "gn:population":0,
    "gn:timezone":"Asia/Vientiane",
    "iso:country":"LA",
    "name:lao_x_preferred":[
        "Ban Pham\u00f4n"
    ],
    "wof:name":"Ban Phamon",
    "wof:placetype":"locality"
},
  "geometry": {"coordinates":[100.53364999999999,19.9106],"type":"Point"}
}