{
  "type": "Feature",
  "properties": {
    "gn:admin1_code":"22.0",
    "gn:asciiname":"Ban Namtin",
    "gn:country_code":"LA",
    "gn:dem":392,
    "gn:feature_class":"P",
    "gn:feature_code":"PPL",
    "gn:name":"Ban Namtin",
    "gn:population":0,
    "gn:timezone":"Asia/Vientiane",
    "iso:country":"LA",
    "name:lao_x_preferred":[
        "Ban Namtin"
    ],
    "wof:name":"Ban Namtin",
    "wof:placetype":"locality"
},
  "geometry": {"coordinates":[100.57111,20.3175],"type":"Point"}
}