{
  "type": "Feature",
  "properties": {
    "gn:admin1_code":"16.0",
    "gn:asciiname":"Ban Chavang-Kao",
    "gn:country_code":"LA",
    "gn:dem":886,
    "gn:feature_class":"P",
    "gn:feature_code":"PPL",
    "gn:name":"Ban Chavang-Kao",
    "gn:population":0,
    "gn:timezone":"Asia/Vientiane",
    "iso:country":"LA",
    "name:lao_x_preferred":[
        "Ban Chavang-Kao"
    ],
    "wof:name":"Ban Chavang-Kao",
    "wof:placetype":"locality"
},
  "geometry": {"coordinates":[101.07445,21.39788],"type":"Point"}
}