{
  "type": "Feature",
  "properties": {
    "gn:admin1_code":"14.0",
    "gn:asciiname":"Ban Tattong",
    "gn:country_code":"LA",
    "gn:dem":1063,
    "gn:feature_class":"P",
    "gn:feature_code":"PPL",
    "gn:name":"Ban Tattong",
    "gn:population":0,
    "gn:timezone":"Asia/Vientiane",
    "iso:country":"LA",
    "name:lao_x_preferred":[
        "Ban Tattong"
    ],
    "wof:name":"Ban Tattong",
    "wof:placetype":"locality"
},
  "geometry": {"coordinates":[103.56671,19.51811],"type":"Point"}
}