{
  "type": "Feature",
  "properties": {
    "gn:admin1_code":"15.0",
    "gn:asciiname":"Ban Nathon",
    "gn:country_code":"LA",
    "gn:dem":176,
    "gn:feature_class":"P",
    "gn:feature_code":"PPL",
    "gn:name":"Ban Nathon",
    "gn:population":0,
    "gn:timezone":"Asia/Vientiane",
    "iso:country":"LA",
    "name:und_x_variant":[
        "Ban Na Th\u00f4ne",
        "Ban Nathon"
    ],
    "wof:name":"Ban Nathon",
    "wof:placetype":"locality"
},
  "geometry": {"coordinates":[105.26617,17.27746],"type":"Point"}
}