{
  "type": "Feature",
  "properties": {
    "gn:admin1_code":"27.0",
    "gn:asciiname":"Ban Phousan",
    "gn:country_code":"LA",
    "gn:dem":191,
    "gn:feature_class":"P",
    "gn:feature_code":"PPL",
    "gn:name":"Ban Phousan",
    "gn:population":0,
    "gn:timezone":"Asia/Vientiane",
    "iso:country":"LA",
    "name:lao_x_preferred":[
        "Ban Phousan"
    ],
    "wof:name":"Ban Phousan",
    "wof:placetype":"locality"
},
  "geometry": {"coordinates":[102.41204,18.35221],"type":"Point"}
}