{
  "type": "Feature",
  "properties": {
    "gn:admin1_code":"20.0",
    "gn:asciiname":"Ban Chakeng",
    "gn:country_code":"LA",
    "gn:dem":198,
    "gn:feature_class":"P",
    "gn:feature_code":"PPL",
    "gn:name":"Ban Chak\u00e8ng",
    "gn:population":0,
    "gn:timezone":"Asia/Vientiane",
    "iso:country":"LA",
    "name:lao_x_preferred":[
        "Ban Chak\u00e8ng"
    ],
    "wof:name":"Ban Chakeng",
    "wof:placetype":"locality"
},
  "geometry": {"coordinates":[106.1802,16.73897],"type":"Point"}
}