{
  "type": "Feature",
  "properties": {
    "gn:admin1_code":"3.0",
    "gn:asciiname":"Ban Xianggnot",
    "gn:country_code":"LA",
    "gn:dem":1302,
    "gn:feature_class":"P",
    "gn:feature_code":"PPL",
    "gn:name":"Ban Xianggnot",
    "gn:population":0,
    "gn:timezone":"Asia/Vientiane",
    "iso:country":"LA",
    "name:und_x_variant":[
        "Ban Xianggnet"
    ],
    "wof:name":"Ban Xianggnot",
    "wof:placetype":"locality"
},
  "geometry": {"coordinates":[104.14252,20.00606],"type":"Point"}
}