{
  "type": "Feature",
  "properties": {
    "gn:admin1_code":"7.0",
    "gn:asciiname":"Ban Khonken",
    "gn:country_code":"LA",
    "gn:dem":784,
    "gn:feature_class":"P",
    "gn:feature_code":"PPL",
    "gn:name":"Ban Khonk\u00e8n",
    "gn:population":0,
    "gn:timezone":"Asia/Vientiane",
    "iso:country":"LA",
    "name:lao_x_preferred":[
        "Ban Khonk\u00e8n"
    ],
    "wof:name":"Ban Khonken",
    "wof:placetype":"locality"
},
  "geometry": {"coordinates":[101.93792000000001,20.59333],"type":"Point"}
}