{
  "type": "Feature",
  "properties": {
    "gn:admin1_code":"20.0",
    "gn:asciiname":"Ban Nongsaphan",
    "gn:country_code":"LA",
    "gn:dem":184,
    "gn:feature_class":"P",
    "gn:feature_code":"PPL",
    "gn:name":"Ban Nongsaphan",
    "gn:population":0,
    "gn:timezone":"Asia/Vientiane",
    "iso:country":"LA",
    "name:lao_x_preferred":[
        "Ban Nongsaphan"
    ],
    "wof:name":"Ban Nongsaphan",
    "wof:placetype":"locality"
},
  "geometry": {"coordinates":[104.86006,16.76471],"type":"Point"}
}