{
  "type": "Feature",
  "properties": {
    "gn:admin1_code":"20.0",
    "gn:asciiname":"Ban Koutbon-Tai",
    "gn:country_code":"LA",
    "gn:dem":150,
    "gn:feature_class":"P",
    "gn:feature_code":"PPL",
    "gn:name":"Ban Koutbon-Tai",
    "gn:population":0,
    "gn:timezone":"Asia/Vientiane",
    "iso:country":"LA",
    "name:lao_x_preferred":[
        "Ban Koutbon-Tai"
    ],
    "name:und_x_variant":[
        "Ban Kout Done"
    ],
    "wof:name":"Ban Koutbon-Tai",
    "wof:placetype":"locality"
},
  "geometry": {"coordinates":[105.19605,16.62052000000001],"type":"Point"}
}