{
  "type": "Feature",
  "properties": {
    "gn:admin1_code":"24.0",
    "gn:asciiname":"Ban Dongphosi",
    "gn:country_code":"LA",
    "gn:dem":164,
    "gn:feature_class":"P",
    "gn:feature_code":"PPL",
    "gn:name":"Ban D\u00f4ngph\u00f4si",
    "gn:population":0,
    "gn:timezone":"Asia/Vientiane",
    "iso:country":"LA",
    "name:lao_x_preferred":[
        "Ban D\u00f4ngph\u00f4si"
    ],
    "wof:name":"Ban Dongphosi",
    "wof:placetype":"locality"
},
  "geometry": {"coordinates":[102.72071,17.89125],"type":"Point"}
}