{
  "type": "Feature",
  "properties": {
    "gn:admin1_code":"14.0",
    "gn:asciiname":"Ban Ngoua-Nua",
    "gn:country_code":"LA",
    "gn:dem":1111,
    "gn:feature_class":"P",
    "gn:feature_code":"PPL",
    "gn:name":"Ban Ngoua-Nua",
    "gn:population":0,
    "gn:timezone":"Asia/Vientiane",
    "iso:country":"LA",
    "name:und_x_variant":[
        "Ban Ngoua",
        "Ban Ngoua-Nua"
    ],
    "wof:name":"Ban Ngoua-Nua",
    "wof:placetype":"locality"
},
  "geometry": {"coordinates":[103.16209000000001,19.34973],"type":"Point"}
}