{
  "type": "Feature",
  "properties": {
    "gn:admin1_code":"13.0",
    "gn:asciiname":"Ban Naphoun",
    "gn:country_code":"LA",
    "gn:dem":395,
    "gn:feature_class":"P",
    "gn:feature_code":"PPL",
    "gn:name":"Ban Naphoun",
    "gn:population":0,
    "gn:timezone":"Asia/Vientiane",
    "iso:country":"LA",
    "name:lao_x_preferred":[
        "Ban Naphoun"
    ],
    "wof:name":"Ban Naphoun",
    "wof:placetype":"locality"
},
  "geometry": {"coordinates":[101.55991,18.66725],"type":"Point"}
}