{
  "type": "Feature",
  "properties": {
    "gn:admin1_code":"14.0",
    "gn:asciiname":"Ban Thak",
    "gn:country_code":"LA",
    "gn:dem":1154,
    "gn:feature_class":"P",
    "gn:feature_code":"PPL",
    "gn:name":"Ban Thak",
    "gn:population":0,
    "gn:timezone":"Asia/Vientiane",
    "iso:country":"LA",
    "name:und_x_variant":[
        "Ban Thau",
        "Ban Thak"
    ],
    "wof:name":"Ban Thak",
    "wof:placetype":"locality"
},
  "geometry": {"coordinates":[103.47915999999999,19.31329],"type":"Point"}
}