{
  "type": "Feature",
  "properties": {
    "gn:admin1_code":"17.0",
    "gn:asciiname":"Ban Houaytou",
    "gn:country_code":"LA",
    "gn:dem":1229,
    "gn:feature_class":"P",
    "gn:feature_code":"PPL",
    "gn:name":"Ban Houaytou",
    "gn:population":0,
    "gn:timezone":"Asia/Vientiane",
    "iso:country":"LA",
    "name:lao_x_preferred":[
        "Ban Houaytou"
    ],
    "wof:name":"Ban Houaytou",
    "wof:placetype":"locality"
},
  "geometry": {"coordinates":[102.83916000000001,20.25877],"type":"Point"}
}