{
  "type": "Feature",
  "properties": {
    "gn:admin1_code":"20.0",
    "gn:asciiname":"Ban Vangpha",
    "gn:country_code":"LA",
    "gn:dem":238,
    "gn:feature_class":"P",
    "gn:feature_code":"PPL",
    "gn:name":"Ban Vangpha",
    "gn:population":0,
    "gn:timezone":"Asia/Vientiane",
    "iso:country":"LA",
    "name:lao_x_preferred":[
        "Ban Vangpha"
    ],
    "wof:name":"Ban Vangpha",
    "wof:placetype":"locality"
},
  "geometry": {"coordinates":[106.26954000000001,16.77558],"type":"Point"}
}