{
  "type": "Feature",
  "properties": {
    "gn:admin1_code":"20.0",
    "gn:asciiname":"Ban Malai-Thong",
    "gn:country_code":"LA",
    "gn:dem":166,
    "gn:feature_class":"P",
    "gn:feature_code":"PPL",
    "gn:name":"Ban Malai-Th\u00f4ng",
    "gn:population":0,
    "gn:timezone":"Asia/Vientiane",
    "iso:country":"LA",
    "name:lao_x_preferred":[
        "Ban Malai-Th\u00f4ng"
    ],
    "wof:name":"Ban Malai-Thong",
    "wof:placetype":"locality"
},
  "geometry": {"coordinates":[105.23851999999999,16.22707],"type":"Point"}
}