{
  "type": "Feature",
  "properties": {
    "gn:admin1_code":"18.0",
    "gn:asciiname":"Ban Muang-Ou-Nua",
    "gn:country_code":"LA",
    "gn:dem":795,
    "gn:feature_class":"P",
    "gn:feature_code":"PPL",
    "gn:name":"Ban Muang-Ou-Nua",
    "gn:population":0,
    "gn:timezone":"Asia/Vientiane",
    "iso:country":"LA",
    "name:und_x_variant":[
        "Unua",
        "Ho Nua",
        "Ounua",
        "Houn-neua",
        "Muang Ou Nua",
        "Ou Neua",
        "Muong Hou Neua",
        "Muong Hu",
        "Muong Hou Nua",
        "Muong Ou Neua",
        "Muong Ou Neva",
        "Muang Ou Neua",
        "Muong Hou Neva",
        "Muongkhoua",
        "Ban Muang-Ou-Nua"
    ],
    "wof:name":"Ban Muang-Ou-Nua",
    "wof:placetype":"locality"
},
  "geometry": {"coordinates":[101.79430000000001,22.29772],"type":"Point"}
}