{
  "type": "Feature",
  "properties": {
    "gn:admin1_code":"17.0",
    "gn:asciiname":"Ban Xaythong",
    "gn:country_code":"LA",
    "gn:dem":1120,
    "gn:feature_class":"P",
    "gn:feature_code":"PPL",
    "gn:name":"Ban Xaythong",
    "gn:population":0,
    "gn:timezone":"Asia/Vientiane",
    "iso:country":"LA",
    "name:lao_x_preferred":[
        "Ban Xaythong"
    ],
    "wof:name":"Ban Xaythong",
    "wof:placetype":"locality"
},
  "geometry": {"coordinates":[102.39613,19.5069],"type":"Point"}
}