{
  "type": "Feature",
  "properties": {
    "gn:admin1_code":"17.0",
    "gn:asciiname":"Ban Houaygna",
    "gn:country_code":"LA",
    "gn:dem":435,
    "gn:feature_class":"P",
    "gn:feature_code":"PPL",
    "gn:name":"Ban Houaygna",
    "gn:population":0,
    "gn:timezone":"Asia/Vientiane",
    "iso:country":"LA",
    "name:lao_x_preferred":[
        "Ban Houaygna"
    ],
    "wof:name":"Ban Houaygna",
    "wof:placetype":"locality"
},
  "geometry": {"coordinates":[102.87227,20.12147],"type":"Point"}
}