{
  "type": "Feature",
  "properties": {
    "gn:admin1_code":"18.0",
    "gn:asciiname":"Ban Nakham",
    "gn:country_code":"LA",
    "gn:dem":424,
    "gn:feature_class":"P",
    "gn:feature_code":"PPL",
    "gn:name":"Ban Nakham",
    "gn:population":0,
    "gn:timezone":"Asia/Vientiane",
    "iso:country":"LA",
    "name:lao_x_preferred":[
        "Ban Nakham"
    ],
    "wof:name":"Ban Nakham",
    "wof:placetype":"locality"
},
  "geometry": {"coordinates":[102.70757,21.17858],"type":"Point"}
}