{
  "type": "Feature",
  "properties": {
    "gn:admin1_code":"7.0",
    "gn:asciiname":"Ban Panghouayhok",
    "gn:country_code":"LA",
    "gn:dem":963,
    "gn:feature_class":"P",
    "gn:feature_code":"PPL",
    "gn:name":"Ban Panghouayhok",
    "gn:population":0,
    "gn:timezone":"Asia/Vientiane",
    "iso:country":"LA",
    "name:lao_x_preferred":[
        "Ban Panghouayhok"
    ],
    "wof:name":"Ban Panghouayhok",
    "wof:placetype":"locality"
},
  "geometry": {"coordinates":[101.56085,20.43136],"type":"Point"}
}