{
  "type": "Feature",
  "properties": {
    "gn:admin1_code":"24.0",
    "gn:asciiname":"Ban Thaxang",
    "gn:country_code":"LA",
    "gn:dem":168,
    "gn:feature_class":"P",
    "gn:feature_code":"PPL",
    "gn:name":"Ban Thaxang",
    "gn:population":0,
    "gn:timezone":"Asia/Vientiane",
    "iso:country":"LA",
    "name:lao_x_preferred":[
        "Ban Thaxang"
    ],
    "wof:name":"Ban Thaxang",
    "wof:placetype":"locality"
},
  "geometry": {"coordinates":[102.92045,18.20271],"type":"Point"}
}