{
  "type": "Feature",
  "properties": {
    "gn:admin1_code":"14.0",
    "gn:asciiname":"Ban Nahang",
    "gn:country_code":"LA",
    "gn:dem":633,
    "gn:feature_class":"P",
    "gn:feature_code":"PPL",
    "gn:name":"Ban Nahang",
    "gn:population":0,
    "gn:timezone":"Asia/Vientiane",
    "iso:country":"LA",
    "name:und_x_variant":[
        "Ban Nahat",
        "Ban Nahang"
    ],
    "wof:name":"Ban Nahang",
    "wof:placetype":"locality"
},
  "geometry": {"coordinates":[103.54111,19.65064],"type":"Point"}
}