{
  "type": "Feature",
  "properties": {
    "gn:admin1_code":"20.0",
    "gn:asciiname":"Ban Koutkhe",
    "gn:country_code":"LA",
    "gn:dem":169,
    "gn:feature_class":"P",
    "gn:feature_code":"PPL",
    "gn:name":"Ban Koutkh\u00e8",
    "gn:population":0,
    "gn:timezone":"Asia/Vientiane",
    "iso:country":"LA",
    "name:lao_x_preferred":[
        "Ban Koutkh\u00e8"
    ],
    "name:und_x_variant":[
        "Kuut Kh\u00e9",
        "Kout Kh\u00e8"
    ],
    "wof:name":"Ban Koutkhe",
    "wof:placetype":"locality"
},
  "geometry": {"coordinates":[105.08651,16.63871],"type":"Point"}
}