{
  "type": "Feature",
  "properties": {
    "gn:admin1_code":"13.0",
    "gn:asciiname":"Ban Houayxong",
    "gn:country_code":"LA",
    "gn:dem":349,
    "gn:feature_class":"P",
    "gn:feature_code":"PPL",
    "gn:name":"Ban Houayxong",
    "gn:population":0,
    "gn:timezone":"Asia/Vientiane",
    "iso:country":"LA",
    "name:lao_x_preferred":[
        "Ban Houayxong"
    ],
    "wof:name":"Ban Houayxong",
    "wof:placetype":"locality"
},
  "geometry": {"coordinates":[101.29473,19.83],"type":"Point"}
}