{
  "type": "Feature",
  "properties": {
    "gn:admin1_code":"22.0",
    "gn:asciiname":"Ban Namgnon-Kao",
    "gn:country_code":"LA",
    "gn:dem":373,
    "gn:feature_class":"P",
    "gn:feature_code":"PPL",
    "gn:name":"Ban Namgnon-Kao",
    "gn:population":0,
    "gn:timezone":"Asia/Vientiane",
    "iso:country":"LA",
    "name:und_x_variant":[
        "Ban Nam Nhion",
        "Ban Namgnon",
        "Ban Namgnon-Kao"
    ],
    "wof:name":"Ban Namgnon-Kao",
    "wof:placetype":"locality"
},
  "geometry": {"coordinates":[100.32319,20.40315],"type":"Point"}
}