{
  "type": "Feature",
  "properties": {
    "gn:admin1_code":"17.0",
    "gn:asciiname":"Ban Houaytham",
    "gn:country_code":"LA",
    "gn:dem":1073,
    "gn:feature_class":"P",
    "gn:feature_code":"PPL",
    "gn:name":"Ban Houaytham",
    "gn:population":0,
    "gn:timezone":"Asia/Vientiane",
    "iso:country":"LA",
    "name:lao_x_preferred":[
        "Ban Houaytham"
    ],
    "wof:name":"Ban Houaytham",
    "wof:placetype":"locality"
},
  "geometry": {"coordinates":[102.90772,20.16418],"type":"Point"}
}