{
  "type": "Feature",
  "properties": {
    "gn:admin1_code":"2.0",
    "gn:asciiname":"Ban Naveng",
    "gn:country_code":"LA",
    "gn:dem":112,
    "gn:feature_class":"P",
    "gn:feature_code":"PPL",
    "gn:name":"Ban Nav\u00e8ng",
    "gn:population":0,
    "gn:timezone":"Asia/Vientiane",
    "iso:country":"LA",
    "name:und_x_variant":[
        "Phum Naveng",
        "Ban Nav\u00e8ng"
    ],
    "wof:name":"Ban Naveng",
    "wof:placetype":"locality"
},
  "geometry": {"coordinates":[105.93255000000001,14.24047],"type":"Point"}
}