{
  "type": "Feature",
  "properties": {
    "gn:admin1_code":"15.0",
    "gn:asciiname":"Ban Nathet",
    "gn:country_code":"LA",
    "gn:dem":183,
    "gn:feature_class":"P",
    "gn:feature_code":"PPL",
    "gn:name":"Ban Nath\u00e9t",
    "gn:population":0,
    "gn:timezone":"Asia/Vientiane",
    "iso:country":"LA",
    "name:lao_x_preferred":[
        "Ban Nath\u00e9t"
    ],
    "name:und_x_variant":[
        "Ban Natheut"
    ],
    "wof:name":"Ban Nathet",
    "wof:placetype":"locality"
},
  "geometry": {"coordinates":[105.26358999999999,17.59858],"type":"Point"}
}