{
  "type": "Feature",
  "properties": {
    "gn:admin1_code":"26.0",
    "gn:asciiname":"Ban Palai",
    "gn:country_code":"LA",
    "gn:dem":504,
    "gn:feature_class":"P",
    "gn:feature_code":"PPL",
    "gn:name":"Ban Palai",
    "gn:population":0,
    "gn:timezone":"Asia/Vientiane",
    "iso:country":"LA",
    "name:lao_x_preferred":[
        "Ban Palai"
    ],
    "wof:name":"Ban Palai",
    "wof:placetype":"locality"
},
  "geometry": {"coordinates":[106.52506,15.46133],"type":"Point"}
}