{
  "type": "Feature",
  "properties": {
    "gn:admin1_code":"14.0",
    "gn:asciiname":"Ban Nongphu",
    "gn:country_code":"LA",
    "gn:dem":1130,
    "gn:feature_class":"P",
    "gn:feature_code":"PPL",
    "gn:name":"Ban Nongphu",
    "gn:population":0,
    "gn:timezone":"Asia/Vientiane",
    "iso:country":"LA",
    "name:lao_x_preferred":[
        "Ban Nongphu"
    ],
    "wof:name":"Ban Nongphu",
    "wof:placetype":"locality"
},
  "geometry": {"coordinates":[103.31196,19.3674],"type":"Point"}
}