{
  "type": "Feature",
  "properties": {
    "gn:admin1_code":"1.0",
    "gn:asciiname":"Ban Chom",
    "gn:country_code":"LA",
    "gn:dem":595,
    "gn:feature_class":"P",
    "gn:feature_code":"PPL",
    "gn:name":"Ban Chom",
    "gn:population":0,
    "gn:timezone":"Asia/Vientiane",
    "iso:country":"LA",
    "name:epo_x_preferred":[
        "Ban Chom"
    ],
    "name:pol_x_preferred":[
        "Ban Chom"
    ],
    "wof:name":"Ban Chom",
    "wof:placetype":"locality"
},
  "geometry": {"coordinates":[107.05,14.55],"type":"Point"}
}