{
  "type": "Feature",
  "properties": {
    "gn:admin1_code":"2.0",
    "gn:asciiname":"Ban Phonngam",
    "gn:country_code":"LA",
    "gn:dem":162,
    "gn:feature_class":"P",
    "gn:feature_code":"PPL",
    "gn:name":"Ban Ph\u00f4nngam",
    "gn:population":0,
    "gn:timezone":"Asia/Vientiane",
    "iso:country":"LA",
    "name:lao_x_preferred":[
        "Ban Ph\u00f4nngam"
    ],
    "name:und_x_variant":[
        "Ban Phon Ngam",
        "Ban Phoungam"
    ],
    "wof:name":"Ban Phonngam",
    "wof:placetype":"locality"
},
  "geometry": {"coordinates":[106.07986,14.71659],"type":"Point"}
}