{
  "type": "Feature",
  "properties": {
    "gn:admin1_code":"2.0",
    "gn:asciiname":"Ban Phokeo",
    "gn:country_code":"LA",
    "gn:dem":106,
    "gn:feature_class":"P",
    "gn:feature_code":"PPL",
    "gn:name":"Ban Ph\u00f4k\u00e8o",
    "gn:population":0,
    "gn:timezone":"Asia/Vientiane",
    "iso:country":"LA",
    "name:lao_x_preferred":[
        "Ban Ph\u00f4k\u00e8o"
    ],
    "wof:name":"Ban Phokeo",
    "wof:placetype":"locality"
},
  "geometry": {"coordinates":[105.72535000000001,15.18574],"type":"Point"}
}