{
  "type": "Feature",
  "properties": {
    "gn:admin1_code":"20.0",
    "gn:asciiname":"Ban Pakpongdeng",
    "gn:country_code":"LA",
    "gn:dem":166,
    "gn:feature_class":"P",
    "gn:feature_code":"PPL",
    "gn:name":"Ban Pakpongd\u00e8ng",
    "gn:population":0,
    "gn:timezone":"Asia/Vientiane",
    "iso:country":"LA",
    "name:lao_x_preferred":[
        "Ban Pakpongd\u00e8ng"
    ],
    "wof:name":"Ban Pakpongdeng",
    "wof:placetype":"locality"
},
  "geometry": {"coordinates":[105.52824,16.64007],"type":"Point"}
}