{
  "type": "Feature",
  "properties": {
    "gn:admin1_code":"20.0",
    "gn:asciiname":"Ban Khamkop",
    "gn:country_code":"LA",
    "gn:dem":181,
    "gn:feature_class":"P",
    "gn:feature_code":"PPL",
    "gn:name":"Ban Khamkop",
    "gn:population":0,
    "gn:timezone":"Asia/Vientiane",
    "iso:country":"LA",
    "name:lao_x_preferred":[
        "Ban Khamkop"
    ],
    "wof:name":"Ban Khamkop",
    "wof:placetype":"locality"
},
  "geometry": {"coordinates":[104.87929,16.84031],"type":"Point"}
}