{
  "type": "Feature",
  "properties": {
    "gn:admin1_code":"26.0",
    "gn:asciiname":"Ban Nong-Nok",
    "gn:country_code":"LA",
    "gn:dem":724,
    "gn:feature_class":"P",
    "gn:feature_code":"PPL",
    "gn:name":"Ban Nong-N\u00f4k",
    "gn:population":0,
    "gn:timezone":"Asia/Vientiane",
    "iso:country":"LA",
    "name:lao_x_preferred":[
        "Ban Nong-N\u00f4k"
    ],
    "wof:name":"Ban Nong-Nok",
    "wof:placetype":"locality"
},
  "geometry": {"coordinates":[106.4419,15.46536],"type":"Point"}
}