{
  "type": "Feature",
  "properties": {
    "gn:admin1_code":"2.0",
    "gn:asciiname":"Ban Houayko",
    "gn:country_code":"LA",
    "gn:dem":98,
    "gn:feature_class":"P",
    "gn:feature_code":"PPL",
    "gn:name":"Ban Houayk\u00f4",
    "gn:population":0,
    "gn:timezone":"Asia/Vientiane",
    "iso:country":"LA",
    "name:lao_x_preferred":[
        "Ban Houayk\u00f4"
    ],
    "name:und_x_variant":[
        "Ban Houei Ko"
    ],
    "wof:name":"Ban Houayko",
    "wof:placetype":"locality"
},
  "geometry": {"coordinates":[105.73684,14.18532],"type":"Point"}
}