{
  "type": "Feature",
  "properties": {
    "gn:admin1_code":"7.0",
    "gn:asciiname":"Seneke",
    "gn:country_code":"LA",
    "gn:dem":1216,
    "gn:feature_class":"P",
    "gn:feature_code":"PPL",
    "gn:name":"Seneke",
    "gn:population":0,
    "gn:timezone":"Asia/Vientiane",
    "iso:country":"LA",
    "wof:name":"Seneke",
    "wof:placetype":"locality"
},
  "geometry": {"coordinates":[102.25,20.83333],"type":"Point"}
}