{
  "type": "Feature",
  "properties": {
    "gn:admin1_code":"7.0",
    "gn:asciiname":"Ban Tongsaluang",
    "gn:country_code":"LA",
    "gn:dem":825,
    "gn:feature_class":"P",
    "gn:feature_code":"PPL",
    "gn:name":"Ban Tongsaluang",
    "gn:population":0,
    "gn:timezone":"Asia/Vientiane",
    "iso:country":"LA",
    "name:lao_x_preferred":[
        "Ban Tongsaluang"
    ],
    "wof:name":"Ban Tongsaluang",
    "wof:placetype":"locality"
},
  "geometry": {"coordinates":[101.73599,20.48855],"type":"Point"}
}