{
  "type": "Feature",
  "properties": {
    "gn:admin1_code":"13.0",
    "gn:asciiname":"Ban Sopmang",
    "gn:country_code":"LA",
    "gn:dem":564,
    "gn:feature_class":"P",
    "gn:feature_code":"PPL",
    "gn:name":"Ban S\u00f4pmang",
    "gn:population":0,
    "gn:timezone":"Asia/Vientiane",
    "iso:country":"LA",
    "name:lao_x_preferred":[
        "Ban S\u00f4pmang"
    ],
    "wof:name":"Ban Sopmang",
    "wof:placetype":"locality"
},
  "geometry": {"coordinates":[100.94567000000001,19.67297],"type":"Point"}
}