{
  "type": "Feature",
  "properties": {
    "gn:admin1_code":"2.0",
    "gn:asciiname":"Ban Khanat",
    "gn:country_code":"LA",
    "gn:dem":108,
    "gn:feature_class":"P",
    "gn:feature_code":"PPL",
    "gn:name":"Ban Khanat",
    "gn:population":0,
    "gn:timezone":"Asia/Vientiane",
    "iso:country":"LA",
    "name:lao_x_preferred":[
        "Ban Khanat"
    ],
    "wof:name":"Ban Khanat",
    "wof:placetype":"locality"
},
  "geometry": {"coordinates":[105.64915000000001,15.22989],"type":"Point"}
}