{
  "type": "Feature",
  "properties": {
    "gn:admin1_code":"3.0",
    "gn:asciiname":"Ban Nakhoun",
    "gn:country_code":"LA",
    "gn:dem":493,
    "gn:feature_class":"P",
    "gn:feature_code":"PPL",
    "gn:name":"Ban Nakhoun",
    "gn:population":0,
    "gn:timezone":"Asia/Vientiane",
    "iso:country":"LA",
    "name:lao_x_preferred":[
        "Ban Nakhoun"
    ],
    "wof:name":"Ban Nakhoun",
    "wof:placetype":"locality"
},
  "geometry": {"coordinates":[104.33163999999999,20.61213],"type":"Point"}
}