{
  "type": "Feature",
  "properties": {
    "gn:admin1_code":"19.0",
    "gn:asciiname":"Ban Talouaydup",
    "gn:country_code":"LA",
    "gn:dem":597,
    "gn:feature_class":"P",
    "gn:feature_code":"PPL",
    "gn:name":"Ban Talouaydup",
    "gn:population":0,
    "gn:timezone":"Asia/Vientiane",
    "iso:country":"LA",
    "name:lao_x_preferred":[
        "Ban Talouaydup"
    ],
    "name:und_x_variant":[
        "Ta Lol Dup",
        "Ta Lo I Dup",
        "Talouaydup"
    ],
    "wof:name":"Ban Talouaydup",
    "wof:placetype":"locality"
},
  "geometry": {"coordinates":[106.94736,16.21947999999999],"type":"Point"}
}