{
  "type": "Feature",
  "properties": {
    "gn:admin1_code":"17.0",
    "gn:asciiname":"Ban Houayngao",
    "gn:country_code":"LA",
    "gn:dem":669,
    "gn:feature_class":"P",
    "gn:feature_code":"PPL",
    "gn:name":"Ban Houayngao",
    "gn:population":0,
    "gn:timezone":"Asia/Vientiane",
    "iso:country":"LA",
    "name:lao_x_preferred":[
        "Ban Houayngao"
    ],
    "wof:name":"Ban Houayngao",
    "wof:placetype":"locality"
},
  "geometry": {"coordinates":[102.04646,19.499],"type":"Point"}
}