{
  "type": "Feature",
  "properties": {
    "gn:admin1_code":"2.0",
    "gn:asciiname":"Ban Don-Gnang",
    "gn:country_code":"LA",
    "gn:dem":96,
    "gn:feature_class":"P",
    "gn:feature_code":"PPL",
    "gn:name":"Ban Don-Gnang",
    "gn:population":0,
    "gn:timezone":"Asia/Vientiane",
    "iso:country":"LA",
    "name:lao_x_preferred":[
        "Ban Don-Gnang"
    ],
    "wof:name":"Ban Don-Gnang",
    "wof:placetype":"locality"
},
  "geometry": {"coordinates":[105.85535,14.13737],"type":"Point"}
}