{
  "type": "Feature",
  "properties": {
    "gn:admin1_code":"20.0",
    "gn:asciiname":"Ban Lambou",
    "gn:country_code":"LA",
    "gn:dem":152,
    "gn:feature_class":"P",
    "gn:feature_code":"PPL",
    "gn:name":"Ban Lambou",
    "gn:population":0,
    "gn:timezone":"Asia/Vientiane",
    "iso:country":"LA",
    "name:lao_x_preferred":[
        "Ban Lambou"
    ],
    "wof:name":"Ban Lambou",
    "wof:placetype":"locality"
},
  "geometry": {"coordinates":[105.43322000000001,16.38425],"type":"Point"}
}