{
  "type": "Feature",
  "properties": {
    "gn:admin1_code":"17.0",
    "gn:asciiname":"Ban Samang",
    "gn:country_code":"LA",
    "gn:dem":432,
    "gn:feature_class":"P",
    "gn:feature_code":"PPL",
    "gn:name":"Ban Samang",
    "gn:population":0,
    "gn:timezone":"Asia/Vientiane",
    "iso:country":"LA",
    "name:lao_x_preferred":[
        "Ban Samang"
    ],
    "wof:name":"Ban Samang",
    "wof:placetype":"locality"
},
  "geometry": {"coordinates":[102.59772,19.7151],"type":"Point"}
}