{
  "type": "Feature",
  "properties": {
    "gn:admin1_code":"13.0",
    "gn:asciiname":"Ban Houaykha",
    "gn:country_code":"LA",
    "gn:dem":476,
    "gn:feature_class":"P",
    "gn:feature_code":"PPL",
    "gn:name":"Ban Houaykha",
    "gn:population":0,
    "gn:timezone":"Asia/Vientiane",
    "iso:country":"LA",
    "name:lao_x_preferred":[
        "Ban Houaykha"
    ],
    "wof:name":"Ban Houaykha",
    "wof:placetype":"locality"
},
  "geometry": {"coordinates":[101.27742000000001,17.81717],"type":"Point"}
}