{
  "type": "Feature",
  "properties": {
    "gn:admin1_code":"16.0",
    "gn:asciiname":"Muang Nale",
    "gn:country_code":"LA",
    "gn:dem":482,
    "gn:feature_class":"P",
    "gn:feature_code":"PPLA2",
    "gn:name":"Muang Nal\u00e8",
    "gn:population":0,
    "gn:timezone":"Asia/Vientiane",
    "iso:country":"LA",
    "name:lao_x_preferred":[
        "Muang Nal\u00e8"
    ],
    "wof:name":"Muang Nale",
    "wof:placetype":"locality"
},
  "geometry": {"coordinates":[101.44678,20.53212000000001],"type":"Point"}
}