{
  "type": "Feature",
  "properties": {
    "gn:admin1_code":"23.0",
    "gn:asciiname":"Ban Sivilai",
    "gn:country_code":"LA",
    "gn:dem":160,
    "gn:feature_class":"P",
    "gn:feature_code":"PPL",
    "gn:name":"Ban Sivilai",
    "gn:population":0,
    "gn:timezone":"Asia/Vientiane",
    "iso:country":"LA",
    "name:und_x_variant":[
        "Ban Si Wi Lai"
    ],
    "wof:name":"Ban Sivilai",
    "wof:placetype":"locality"
},
  "geometry": {"coordinates":[103.66413,18.40356],"type":"Point"}
}