{
  "type": "Feature",
  "properties": {
    "gn:admin1_code":"3.0",
    "gn:asciiname":"Ban Soppit",
    "gn:country_code":"LA",
    "gn:dem":241,
    "gn:feature_class":"P",
    "gn:feature_code":"PPL",
    "gn:name":"Ban S\u00f4ppit",
    "gn:population":0,
    "gn:timezone":"Asia/Vientiane",
    "iso:country":"LA",
    "name:und_x_variant":[
        "Sap Pit",
        "Sop Pit",
        "Ban S\u00f4ppit"
    ],
    "wof:name":"Ban Soppit",
    "wof:placetype":"locality"
},
  "geometry": {"coordinates":[104.22893000000001,20.76684],"type":"Point"}
}