{
  "type": "Feature",
  "properties": {
    "gn:admin1_code":"20.0",
    "gn:asciiname":"Ban Nanokkhian",
    "gn:country_code":"LA",
    "gn:dem":164,
    "gn:feature_class":"P",
    "gn:feature_code":"PPL",
    "gn:name":"Ban Nan\u00f4kkhian",
    "gn:population":0,
    "gn:timezone":"Asia/Vientiane",
    "iso:country":"LA",
    "name:und_x_variant":[
        "Ban Nok Khien",
        "Ban Nan\u00f4kkhian"
    ],
    "wof:name":"Ban Nanokkhian",
    "wof:placetype":"locality"
},
  "geometry": {"coordinates":[105.09049,16.55213],"type":"Point"}
}