{
  "type": "Feature",
  "properties": {
    "gn:admin1_code":"24.0",
    "gn:asciiname":"Ban Natan",
    "gn:country_code":"LA",
    "gn:dem":195,
    "gn:feature_class":"P",
    "gn:feature_code":"PPL",
    "gn:name":"Ban Natan",
    "gn:population":0,
    "gn:timezone":"Asia/Vientiane",
    "iso:country":"LA",
    "name:lao_x_preferred":[
        "Ban Natan"
    ],
    "wof:name":"Ban Natan",
    "wof:placetype":"locality"
},
  "geometry": {"coordinates":[102.22301,18.30437],"type":"Point"}
}