{
  "type": "Feature",
  "properties": {
    "gn:country":"LA",
    "gn:fcode":"PPL",
    "gn:pop":404,
    "iso:country":"LA",
    "name:rus_x_preferred":[
        "\u0414\u043e\u043d-\u0414\u0435\u0442-\u0422\u043e\u043a"
    ],
    "qs:name":"Don Det Tok",
    "qs:photos_9r":0,
    "qs:photos_sr":0,
    "qs:pop_sr":"2",
    "wof:name":"Don Det Tok",
    "wof:placetype":"locality",
    "wof:population":404
},
  "geometry": {"coordinates":[105.91475,13.98529],"type":"Point"}
}