{
  "type": "Feature",
  "properties": {
    "gn:admin1_code":"20.0",
    "gn:asciiname":"Ban Douan",
    "gn:cc2":"LA",
    "gn:country_code":"LA",
    "gn:dem":224,
    "gn:feature_class":"P",
    "gn:feature_code":"PPL",
    "gn:name":"Ban Douan",
    "gn:population":0,
    "gn:timezone":"Asia/Vientiane",
    "iso:country":"LA",
    "name:und_x_variant":[
        "Ban Doan",
        "Ban Douan"
    ],
    "wof:name":"Ban Douan",
    "wof:placetype":"locality"
},
  "geometry": {"coordinates":[106.21666999999999,16.26667],"type":"Point"}
}