{
  "type": "Feature",
  "properties": {
    "gn:admin1_code":"2.0",
    "gn:asciiname":"Ban Phanouan-Gnai",
    "gn:country_code":"LA",
    "gn:dem":1041,
    "gn:feature_class":"P",
    "gn:feature_code":"PPL",
    "gn:name":"Ban Phanouan-Gnai",
    "gn:population":0,
    "gn:timezone":"Asia/Vientiane",
    "iso:country":"LA",
    "name:lao_x_preferred":[
        "Ban Phanouan-Gnai"
    ],
    "name:und_x_variant":[
        "Ban Phankouan Gnai",
        "Ban Phan Ouan Nhay"
    ],
    "wof:name":"Ban Phanouan-Gnai",
    "wof:placetype":"locality"
},
  "geometry": {"coordinates":[106.38516,15.0571],"type":"Point"}
}