{
  "type": "Feature",
  "properties": {
    "gn:admin1_code":"19.0",
    "gn:asciiname":"Ban Lang",
    "gn:country_code":"LA",
    "gn:dem":628,
    "gn:feature_class":"P",
    "gn:feature_code":"PPL",
    "gn:name":"Ban Lang",
    "gn:population":0,
    "gn:timezone":"Asia/Vientiane",
    "iso:country":"LA",
    "name:lao_x_preferred":[
        "Ban Lang"
    ],
    "name:und_x_variant":[
        "A Rang"
    ],
    "wof:name":"Ban Lang",
    "wof:placetype":"locality"
},
  "geometry": {"coordinates":[106.71401000000002,16.04125],"type":"Point"}
}