{
  "type": "Feature",
  "properties": {
    "gn:admin1_code":"20.0",
    "gn:asciiname":"Ban Nonsomboum",
    "gn:country_code":"LA",
    "gn:dem":177,
    "gn:feature_class":"P",
    "gn:feature_code":"PPL",
    "gn:name":"Ban N\u00f4ns\u00f4mboum",
    "gn:population":0,
    "gn:timezone":"Asia/Vientiane",
    "iso:country":"LA",
    "name:lao_x_preferred":[
        "Ban N\u00f4ns\u00f4mboum"
    ],
    "wof:name":"Ban Nonsomboum",
    "wof:placetype":"locality"
},
  "geometry": {"coordinates":[105.17028000000001,16.24845],"type":"Point"}
}