{
  "type": "Feature",
  "properties": {
    "gn:admin1_code":"7.0",
    "gn:asciiname":"Ban Nale",
    "gn:country_code":"LA",
    "gn:dem":646,
    "gn:feature_class":"P",
    "gn:feature_code":"PPL",
    "gn:name":"Ban Nal\u00e8",
    "gn:population":0,
    "gn:timezone":"Asia/Vientiane",
    "iso:country":"LA",
    "name:und_x_variant":[
        "Nale",
        "Ban Nal\u00e8"
    ],
    "wof:name":"Ban Nale",
    "wof:placetype":"locality"
},
  "geometry": {"coordinates":[101.96737,20.67214],"type":"Point"}
}