{
  "type": "Feature",
  "properties": {
    "gn:admin1_code":"20.0",
    "gn:asciiname":"Ban Maloua",
    "gn:country_code":"LA",
    "gn:dem":247,
    "gn:feature_class":"P",
    "gn:feature_code":"PPL",
    "gn:name":"Ban Maloua",
    "gn:population":0,
    "gn:timezone":"Asia/Vientiane",
    "iso:country":"LA",
    "name:und_x_variant":[
        "Ban Malua",
        "Ban Maloua"
    ],
    "wof:name":"Ban Maloua",
    "wof:placetype":"locality"
},
  "geometry": {"coordinates":[106.04007,16.62991],"type":"Point"}
}