{
  "type": "Feature",
  "properties": {
    "gn:admin1_code":"14.0",
    "gn:asciiname":"Ban Xon",
    "gn:cc2":"LA",
    "gn:country_code":"LA",
    "gn:dem":1141,
    "gn:feature_class":"P",
    "gn:feature_code":"PPL",
    "gn:name":"Ban Xon",
    "gn:population":0,
    "gn:timezone":"Asia/Vientiane",
    "iso:country":"LA",
    "name:und_x_variant":[
        "Ban Xionn",
        "Ban Xienn",
        "Ban Xon"
    ],
    "wof:name":"Ban Xon",
    "wof:placetype":"locality"
},
  "geometry": {"coordinates":[102.93333,19.48333],"type":"Point"}
}