{
  "type": "Feature",
  "properties": {
    "gn:admin1_code":"20.0",
    "gn:asciiname":"Ban Nonkoung",
    "gn:country_code":"LA",
    "gn:dem":184,
    "gn:feature_class":"P",
    "gn:feature_code":"PPL",
    "gn:name":"Ban N\u00f4nkoung",
    "gn:population":0,
    "gn:timezone":"Asia/Vientiane",
    "iso:country":"LA",
    "name:und_x_variant":[
        "Ban None Keung",
        "Ban N\u00f4nkoung"
    ],
    "wof:name":"Ban Nonkoung",
    "wof:placetype":"locality"
},
  "geometry": {"coordinates":[105.06961,16.62179],"type":"Point"}
}