{
  "type": "Feature",
  "properties": {
    "gn:admin1_code":"19.0",
    "gn:asciiname":"Ban Lammana-Tai",
    "gn:country_code":"LA",
    "gn:dem":680,
    "gn:feature_class":"P",
    "gn:feature_code":"PPL",
    "gn:name":"Ban Lammana-Tai",
    "gn:population":0,
    "gn:timezone":"Asia/Vientiane",
    "iso:country":"LA",
    "name:lao_x_preferred":[
        "Ban Lammana-Tai"
    ],
    "wof:name":"Ban Lammana-Tai",
    "wof:placetype":"locality"
},
  "geometry": {"coordinates":[106.52836000000001,15.98206],"type":"Point"}
}