{
  "type": "Feature",
  "properties": {
    "gn:admin1_code":"14.0",
    "gn:asciiname":"Ban Sanhiang",
    "gn:country_code":"LA",
    "gn:dem":1372,
    "gn:feature_class":"P",
    "gn:feature_code":"PPL",
    "gn:name":"Ban Sanhiang",
    "gn:population":0,
    "gn:timezone":"Asia/Vientiane",
    "iso:country":"LA",
    "name:lao_x_preferred":[
        "Ban Sanhiang"
    ],
    "wof:name":"Ban Sanhiang",
    "wof:placetype":"locality"
},
  "geometry": {"coordinates":[103.71845999999999,19.86349],"type":"Point"}
}