{
  "type": "Feature",
  "properties": {
    "gn:admin1_code":"27.0",
    "gn:asciiname":"Ban Khonkeo",
    "gn:country_code":"LA",
    "gn:dem":217,
    "gn:feature_class":"P",
    "gn:feature_code":"PPL",
    "gn:name":"Ban Khonkeo",
    "gn:population":0,
    "gn:timezone":"Asia/Vientiane",
    "iso:country":"LA",
    "name:lao_x_preferred":[
        "Ban Khonkeo"
    ],
    "wof:name":"Ban Khonkeo",
    "wof:placetype":"locality"
},
  "geometry": {"coordinates":[102.3338,18.55021],"type":"Point"}
}