{
  "type": "Feature",
  "properties": {
    "gn:admin1_code":"7.0",
    "gn:asciiname":"Ban Sakho Noy",
    "gn:country_code":"LA",
    "gn:dem":654,
    "gn:feature_class":"P",
    "gn:feature_code":"PPL",
    "gn:name":"Ban Sakho Noy",
    "gn:population":0,
    "gn:timezone":"Asia/Vientiane",
    "iso:country":"LA",
    "name:und_x_variant":[
        "So Ko Noi",
        "Ban So Ko Noi",
        "Ban Sa Khoua No\u00ef",
        "Ban Sakho Noy"
    ],
    "wof:name":"Ban Sakho Noy",
    "wof:placetype":"locality"
},
  "geometry": {"coordinates":[101.53333000000001,20.71667],"type":"Point"}
}