{
  "type": "Feature",
  "properties": {
    "gn:admin1_code":"22.0",
    "gn:asciiname":"Ban Pak-Hao-Nua",
    "gn:country_code":"LA",
    "gn:dem":361,
    "gn:feature_class":"P",
    "gn:feature_code":"PPL",
    "gn:name":"Ban Pak-Hao-Nua",
    "gn:population":0,
    "gn:timezone":"Asia/Vientiane",
    "iso:country":"LA",
    "name:lao_x_preferred":[
        "Ban Pak-Hao-Nua"
    ],
    "wof:name":"Ban Pak-Hao-Nua",
    "wof:placetype":"locality"
},
  "geometry": {"coordinates":[100.44584999999999,20.25244],"type":"Point"}
}