{
  "type": "Feature",
  "properties": {
    "gn:admin1_code":"13.0",
    "gn:asciiname":"Ban Houaykhoay",
    "gn:country_code":"LA",
    "gn:dem":373,
    "gn:feature_class":"P",
    "gn:feature_code":"PPL",
    "gn:name":"Ban Houaykhoay",
    "gn:population":0,
    "gn:timezone":"Asia/Vientiane",
    "iso:country":"LA",
    "name:lao_x_preferred":[
        "Ban Houaykhoay"
    ],
    "wof:name":"Ban Houaykhoay",
    "wof:placetype":"locality"
},
  "geometry": {"coordinates":[101.21982,18.20179],"type":"Point"}
}