{
  "type": "Feature",
  "properties": {
    "gn:admin1_code":"17.0",
    "gn:asciiname":"Ban Namthouam",
    "gn:country_code":"LA",
    "gn:dem":391,
    "gn:feature_class":"P",
    "gn:feature_code":"PPL",
    "gn:name":"Ban Namthouam",
    "gn:population":0,
    "gn:timezone":"Asia/Vientiane",
    "iso:country":"LA",
    "name:lao_x_preferred":[
        "Ban Namthouam"
    ],
    "wof:name":"Ban Namthouam",
    "wof:placetype":"locality"
},
  "geometry": {"coordinates":[102.36163999999999,20.49401],"type":"Point"}
}