{
  "type": "Feature",
  "properties": {
    "gn:admin1_code":"27.0",
    "gn:asciiname":"Ban Houaytakeo",
    "gn:country_code":"LA",
    "gn:dem":330,
    "gn:feature_class":"P",
    "gn:feature_code":"PPL",
    "gn:name":"Ban Houaytak\u00e8o",
    "gn:population":0,
    "gn:timezone":"Asia/Vientiane",
    "iso:country":"LA",
    "wof:name":"Ban Houaytakeo",
    "wof:placetype":"locality"
},
  "geometry": {"coordinates":[101.41667,18.11667000000001],"type":"Point"}
}