{
  "type": "Feature",
  "properties": {
    "gn:admin1_code":"17.0",
    "gn:asciiname":"Ban Pouakhoay",
    "gn:country_code":"LA",
    "gn:dem":632,
    "gn:feature_class":"P",
    "gn:feature_code":"PPL",
    "gn:name":"Ban Pouakhoay",
    "gn:population":0,
    "gn:timezone":"Asia/Vientiane",
    "iso:country":"LA",
    "name:lao_x_preferred":[
        "Ban Pouakhoay"
    ],
    "wof:name":"Ban Pouakhoay",
    "wof:placetype":"locality"
},
  "geometry": {"coordinates":[103.06511999999999,20.40017000000001],"type":"Point"}
}