{
  "type": "Feature",
  "properties": {
    "gn:admin1_code":"19.0",
    "gn:asciiname":"Ban Phoudaocheng-Noy",
    "gn:country_code":"LA",
    "gn:dem":161,
    "gn:feature_class":"P",
    "gn:feature_code":"PPL",
    "gn:name":"Ban Phoudaoch\u00e8ng-Noy",
    "gn:population":0,
    "gn:timezone":"Asia/Vientiane",
    "iso:country":"LA",
    "name:lao_x_preferred":[
        "Ban Phoudaoch\u00e8ng-Noy"
    ],
    "name:und_x_variant":[
        "Ban Phou Daotieng Noi"
    ],
    "wof:name":"Ban Phoudaocheng-Noy",
    "wof:placetype":"locality"
},
  "geometry": {"coordinates":[105.73482,15.76205],"type":"Point"}
}