{
  "type": "Feature",
  "properties": {
    "gn:admin1_code":"14.0",
    "gn:asciiname":"Ban Thamkhoay",
    "gn:country_code":"LA",
    "gn:dem":1091,
    "gn:feature_class":"P",
    "gn:feature_code":"PPL",
    "gn:name":"Ban Thamkhoay",
    "gn:population":0,
    "gn:timezone":"Asia/Vientiane",
    "iso:country":"LA",
    "name:lao_x_preferred":[
        "Ban Thamkhoay"
    ],
    "wof:name":"Ban Thamkhoay",
    "wof:placetype":"locality"
},
  "geometry": {"coordinates":[103.71577000000001,19.41332],"type":"Point"}
}