{
  "type": "Feature",
  "properties": {
    "gn:admin1_code":"26.0",
    "gn:asciiname":"Ban Dakleun",
    "gn:country_code":"LA",
    "gn:dem":1374,
    "gn:feature_class":"P",
    "gn:feature_code":"PPL",
    "gn:name":"Ban Dakleun",
    "gn:population":0,
    "gn:timezone":"Asia/Vientiane",
    "iso:country":"LA",
    "name:lao_x_preferred":[
        "Ban Dakleun"
    ],
    "name:und_x_variant":[
        "Ban Dakreun",
        "Reuni",
        "Reun"
    ],
    "wof:name":"Ban Dakleun",
    "wof:placetype":"locality"
},
  "geometry": {"coordinates":[107.19729,15.46385],"type":"Point"}
}