{
  "type": "Feature",
  "properties": {
    "gn:admin1_code":"7.0",
    "gn:asciiname":"Ban Mokchak-Kang",
    "gn:country_code":"LA",
    "gn:dem":1018,
    "gn:feature_class":"P",
    "gn:feature_code":"PPL",
    "gn:name":"Ban M\u00f4kchak-Kang",
    "gn:population":0,
    "gn:timezone":"Asia/Vientiane",
    "iso:country":"LA",
    "name:lao_x_preferred":[
        "Ban M\u00f4kchak-Kang"
    ],
    "wof:name":"Ban Mokchak-Kang",
    "wof:placetype":"locality"
},
  "geometry": {"coordinates":[101.80777999999999,20.58993],"type":"Point"}
}