{
  "type": "Feature",
  "properties": {
    "gn:admin1_code":"20.0",
    "gn:asciiname":"Ban Miyiam",
    "gn:country_code":"LA",
    "gn:dem":139,
    "gn:feature_class":"P",
    "gn:feature_code":"PPL",
    "gn:name":"Ban Miyiam",
    "gn:population":0,
    "gn:timezone":"Asia/Vientiane",
    "iso:country":"LA",
    "name:und_x_variant":[
        "Ban Nhyem",
        "Ban Mi Yem",
        "Ban Mi Vem",
        "Ban Miyiam",
        "Ban Myiam"
    ],
    "wof:name":"Ban Miyiam",
    "wof:placetype":"locality"
},
  "geometry": {"coordinates":[105.32953000000001,16.08793],"type":"Point"}
}