{
  "type": "Feature",
  "properties": {
    "gn:admin1_code":"17.0",
    "gn:asciiname":"Ban Ham",
    "gn:country_code":"LA",
    "gn:dem":469,
    "gn:feature_class":"P",
    "gn:feature_code":"PPL",
    "gn:name":"Ban Ham",
    "gn:population":0,
    "gn:timezone":"Asia/Vientiane",
    "iso:country":"LA",
    "name:lao_x_preferred":[
        "Ban Ham"
    ],
    "wof:name":"Ban Ham",
    "wof:placetype":"locality"
},
  "geometry": {"coordinates":[102.41955,19.80632],"type":"Point"}
}