{
  "type": "Feature",
  "properties": {
    "gn:admin1_code":"24.0",
    "gn:asciiname":"Ban Hongngoua",
    "gn:country_code":"LA",
    "gn:dem":170,
    "gn:feature_class":"P",
    "gn:feature_code":"PPL",
    "gn:name":"Ban Hongngoua",
    "gn:population":0,
    "gn:timezone":"Asia/Vientiane",
    "iso:country":"LA",
    "name:lao_x_preferred":[
        "Ban Hongngoua"
    ],
    "wof:name":"Ban Hongngoua",
    "wof:placetype":"locality"
},
  "geometry": {"coordinates":[102.51445,18.21505],"type":"Point"}
}