{
  "type": "Feature",
  "properties": {
    "gn:admin1_code":"15.0",
    "gn:asciiname":"Ban Kouankhagnom",
    "gn:country_code":"LA",
    "gn:dem":186,
    "gn:feature_class":"P",
    "gn:feature_code":"PPL",
    "gn:name":"Ban Kouankhagn\u00f4m",
    "gn:population":0,
    "gn:timezone":"Asia/Vientiane",
    "iso:country":"LA",
    "name:und_x_variant":[
        "Ban Kha Niom",
        "Ban Khouan Kha Nhom",
        "Ban Kouan Kha Nhom",
        "Ban Kouankhagn\u00f4m"
    ],
    "wof:name":"Ban Kouankhagnom",
    "wof:placetype":"locality"
},
  "geometry": {"coordinates":[105.79107,17.38877],"type":"Point"}
}