{
  "type": "Feature",
  "properties": {
    "gn:admin1_code":"20.0",
    "gn:asciiname":"Ban Phanxi",
    "gn:country_code":"LA",
    "gn:dem":201,
    "gn:feature_class":"P",
    "gn:feature_code":"PPL",
    "gn:name":"Ban Phanxi",
    "gn:population":0,
    "gn:timezone":"Asia/Vientiane",
    "iso:country":"LA",
    "name:und_x_variant":[
        "Ban Phan Si",
        "Ban Phanxi"
    ],
    "wof:name":"Ban Phanxi",
    "wof:placetype":"locality"
},
  "geometry": {"coordinates":[105.78032,15.97628],"type":"Point"}
}