{
  "type": "Feature",
  "properties": {
    "gn:admin1_code":"20.0",
    "gn:asciiname":"Ban Kengkabao",
    "gn:country_code":"LA",
    "gn:dem":146,
    "gn:feature_class":"P",
    "gn:feature_code":"PPL",
    "gn:name":"Ban K\u00e8ngkabao",
    "gn:population":0,
    "gn:timezone":"Asia/Bangkok",
    "iso:country":"LA",
    "name:und_x_variant":[
        "Keng Kabao",
        "Ban K\u00e8ngkabao"
    ],
    "wof:name":"Ban Kengkabao",
    "wof:placetype":"locality"
},
  "geometry": {"coordinates":[104.74694,16.81112000000001],"type":"Point"}
}