{
  "type": "Feature",
  "properties": {
    "gn:admin1_code":"20.0",
    "gn:asciiname":"Ban Tang-Alaiphoamat",
    "gn:country_code":"LA",
    "gn:dem":280,
    "gn:feature_class":"P",
    "gn:feature_code":"PPL",
    "gn:name":"Ban Tang-Alaiphoamat",
    "gn:population":0,
    "gn:timezone":"Asia/Vientiane",
    "iso:country":"LA",
    "name:lao_x_preferred":[
        "Ban Tang-Alaiphoamat"
    ],
    "name:und_x_variant":[
        "Tang A Lai Pa A Mang",
        "Ban Tang-Alai-Phoamang"
    ],
    "wof:name":"Ban Tang-Alaiphoamat",
    "wof:placetype":"locality"
},
  "geometry": {"coordinates":[106.51602,16.32115],"type":"Point"}
}