{
  "type": "Feature",
  "properties": {
    "gn:admin1_code":"3.0",
    "gn:asciiname":"Ban Sop Man",
    "gn:country_code":"LA",
    "gn:dem":1025,
    "gn:feature_class":"P",
    "gn:feature_code":"PPL",
    "gn:name":"Ban Sop Man",
    "gn:population":0,
    "gn:timezone":"Asia/Vientiane",
    "iso:country":"LA",
    "wof:name":"Ban Sop Man",
    "wof:placetype":"locality"
},
  "geometry": {"coordinates":[103.33333,19.91667],"type":"Point"}
}