{
  "type": "Feature",
  "properties": {
    "gn:admin1_code":"27.0",
    "gn:asciiname":"Ban Danpasat",
    "gn:country_code":"LA",
    "gn:dem":187,
    "gn:feature_class":"P",
    "gn:feature_code":"PPL",
    "gn:name":"Ban Danpasat",
    "gn:population":0,
    "gn:timezone":"Asia/Vientiane",
    "iso:country":"LA",
    "name:lao_x_preferred":[
        "Ban Danpasat"
    ],
    "wof:name":"Ban Danpasat",
    "wof:placetype":"locality"
},
  "geometry": {"coordinates":[102.37886,18.45962],"type":"Point"}
}