{
  "type": "Feature",
  "properties": {
    "gn:admin1_code":"16.0",
    "gn:asciiname":"Ban Khanungphet",
    "gn:country_code":"LA",
    "gn:dem":997,
    "gn:feature_class":"P",
    "gn:feature_code":"PPL",
    "gn:name":"Ban Khanungph\u00e8t",
    "gn:population":0,
    "gn:timezone":"Asia/Vientiane",
    "iso:country":"LA",
    "name:lao_x_preferred":[
        "Ban Khanungph\u00e8t"
    ],
    "wof:name":"Ban Khanungphet",
    "wof:placetype":"locality"
},
  "geometry": {"coordinates":[101.17312,20.44275],"type":"Point"}
}