{
  "type": "Feature",
  "properties": {
    "gn:admin1_code":"19.0",
    "gn:asciiname":"Ban Sangthong-Gnai",
    "gn:country_code":"LA",
    "gn:dem":574,
    "gn:feature_class":"P",
    "gn:feature_code":"PPL",
    "gn:name":"Ban Sangthong-Gnai",
    "gn:population":0,
    "gn:timezone":"Asia/Vientiane",
    "iso:country":"LA",
    "name:lao_x_preferred":[
        "Ban Sangthong-Gnai"
    ],
    "name:und_x_variant":[
        "Ban Tam\u00e9-Sangthong"
    ],
    "wof:name":"Ban Sangthong-Gnai",
    "wof:placetype":"locality"
},
  "geometry": {"coordinates":[106.19038999999999,15.46793],"type":"Point"}
}