{
  "type": "Feature",
  "properties": {
    "gn:admin1_code":"15.0",
    "gn:asciiname":"Ban Khok-Het",
    "gn:country_code":"LA",
    "gn:dem":154,
    "gn:feature_class":"P",
    "gn:feature_code":"PPL",
    "gn:name":"Ban Kh\u00f4k-H\u00e8t",
    "gn:population":0,
    "gn:timezone":"Asia/Vientiane",
    "iso:country":"LA",
    "name:lao_x_preferred":[
        "Ban Kh\u00f4k-H\u00e8t"
    ],
    "wof:name":"Ban Khok-Het",
    "wof:placetype":"locality"
},
  "geometry": {"coordinates":[104.89135,17.31696],"type":"Point"}
}