{
  "type": "Feature",
  "properties": {
    "gn:admin1_code":"18.0",
    "gn:asciiname":"Ban Nadanglouang",
    "gn:country_code":"LA",
    "gn:dem":738,
    "gn:feature_class":"P",
    "gn:feature_code":"PPL",
    "gn:name":"Ban Nadanglouang",
    "gn:population":0,
    "gn:timezone":"Asia/Vientiane",
    "iso:country":"LA",
    "name:lao_x_preferred":[
        "Ban Nadanglouang"
    ],
    "wof:name":"Ban Nadanglouang",
    "wof:placetype":"locality"
},
  "geometry": {"coordinates":[101.73454,22.19046],"type":"Point"}
}