{
  "type": "Feature",
  "properties": {
    "gn:admin1_code":"15.0",
    "gn:asciiname":"Ban Paksimang",
    "gn:country_code":"LA",
    "gn:dem":143,
    "gn:feature_class":"P",
    "gn:feature_code":"PPL",
    "gn:name":"Ban Paksimang",
    "gn:population":0,
    "gn:timezone":"Asia/Vientiane",
    "iso:country":"LA",
    "name:lao_x_preferred":[
        "Ban Paksimang"
    ],
    "name:lao_x_variant":[
        "Ban Dantio"
    ],
    "wof:name":"Ban Paksimang",
    "wof:placetype":"locality"
},
  "geometry": {"coordinates":[104.81139,17.35996],"type":"Point"}
}