{
  "type": "Feature",
  "properties": {
    "gn:admin1_code":"13.0",
    "gn:asciiname":"Ban Khoksavan",
    "gn:country_code":"LA",
    "gn:dem":411,
    "gn:feature_class":"P",
    "gn:feature_code":"PPL",
    "gn:name":"Ban Kh\u00f4ksavan",
    "gn:population":0,
    "gn:timezone":"Asia/Vientiane",
    "iso:country":"LA",
    "name:lao_x_preferred":[
        "Ban Kh\u00f4ksavan"
    ],
    "name:und_x_variant":[
        "Ban Kok"
    ],
    "wof:name":"Ban Khoksavan",
    "wof:placetype":"locality"
},
  "geometry": {"coordinates":[101.39104,18.36043],"type":"Point"}
}