{
  "type": "Feature",
  "properties": {
    "gn:admin1_code":"7.0",
    "gn:asciiname":"Ban Pangdou",
    "gn:country_code":"LA",
    "gn:dem":615,
    "gn:feature_class":"P",
    "gn:feature_code":"PPL",
    "gn:name":"Ban Pangdou",
    "gn:population":0,
    "gn:timezone":"Asia/Vientiane",
    "iso:country":"LA",
    "name:lao_x_preferred":[
        "Ban Pangdou"
    ],
    "wof:name":"Ban Pangdou",
    "wof:placetype":"locality"
},
  "geometry": {"coordinates":[101.76166000000001,20.90588],"type":"Point"}
}