{
  "type": "Feature",
  "properties": {
    "gn:admin1_code":"20.0",
    "gn:asciiname":"Ban Navangkhen",
    "gn:country_code":"LA",
    "gn:dem":148,
    "gn:feature_class":"P",
    "gn:feature_code":"PPL",
    "gn:name":"Ban Navangkh\u00e8n",
    "gn:population":0,
    "gn:timezone":"Asia/Vientiane",
    "iso:country":"LA",
    "name:lao_x_preferred":[
        "Ban Navangkh\u00e8n"
    ],
    "wof:name":"Ban Navangkhen",
    "wof:placetype":"locality"
},
  "geometry": {"coordinates":[105.57966999999999,16.24141],"type":"Point"}
}