{
  "type": "Feature",
  "properties": {
    "gn:admin1_code":"7.0",
    "gn:asciiname":"Ban Namvun-Nua",
    "gn:country_code":"LA",
    "gn:dem":643,
    "gn:feature_class":"P",
    "gn:feature_code":"PPL",
    "gn:name":"Ban Namvun-Nua",
    "gn:population":0,
    "gn:timezone":"Asia/Vientiane",
    "iso:country":"LA",
    "name:lao_x_preferred":[
        "Ban Namvun-Nua"
    ],
    "wof:name":"Ban Namvun-Nua",
    "wof:placetype":"locality"
},
  "geometry": {"coordinates":[101.80840000000001,20.88274],"type":"Point"}
}