{
  "type": "Feature",
  "properties": {
    "gn:admin1_code":"19.0",
    "gn:asciiname":"Ban Beng",
    "gn:country_code":"LA",
    "gn:dem":323,
    "gn:feature_class":"P",
    "gn:feature_code":"PPL",
    "gn:name":"Ban B\u00e8ng",
    "gn:population":0,
    "gn:timezone":"Asia/Vientiane",
    "iso:country":"LA",
    "name:lao_x_preferred":[
        "Ban B\u00e8ng"
    ],
    "wof:name":"Ban Beng",
    "wof:placetype":"locality"
},
  "geometry": {"coordinates":[106.2962,15.57094],"type":"Point"}
}