{
  "type": "Feature",
  "properties": {
    "gn:admin1_code":"17.0",
    "gn:asciiname":"Ban Phasanin-Gnai",
    "gn:country_code":"LA",
    "gn:dem":1137,
    "gn:feature_class":"P",
    "gn:feature_code":"PPL",
    "gn:name":"Ban Phasanin-Gnai",
    "gn:population":0,
    "gn:timezone":"Asia/Vientiane",
    "iso:country":"LA",
    "name:lao_x_preferred":[
        "Ban Phasanin-Gnai"
    ],
    "wof:name":"Ban Phasanin-Gnai",
    "wof:placetype":"locality"
},
  "geometry": {"coordinates":[102.31762000000001,19.59642],"type":"Point"}
}