{
  "type": "Feature",
  "properties": {
    "gn:admin1_code":"27.0",
    "gn:asciiname":"Ban Phonbok",
    "gn:country_code":"LA",
    "gn:dem":191,
    "gn:feature_class":"P",
    "gn:feature_code":"PPL",
    "gn:name":"Ban Ph\u00f4nb\u00f4k",
    "gn:population":0,
    "gn:timezone":"Asia/Vientiane",
    "iso:country":"LA",
    "name:lao_x_preferred":[
        "Ban Ph\u00f4nb\u00f4k"
    ],
    "wof:name":"Ban Phonbok",
    "wof:placetype":"locality"
},
  "geometry": {"coordinates":[102.40112000000001,18.54655],"type":"Point"}
}