{
  "type": "Feature",
  "properties": {
    "gn:admin1_code":"23.0",
    "gn:asciiname":"Ban Phahon",
    "gn:country_code":"LA",
    "gn:dem":816,
    "gn:feature_class":"P",
    "gn:feature_code":"PPL",
    "gn:name":"Ban Phahon",
    "gn:population":0,
    "gn:timezone":"Asia/Vientiane",
    "iso:country":"LA",
    "name:lao_x_preferred":[
        "Ban Phahon"
    ],
    "wof:name":"Ban Phahon",
    "wof:placetype":"locality"
},
  "geometry": {"coordinates":[104.44671,18.77431],"type":"Point"}
}