{
  "type": "Feature",
  "properties": {
    "gn:admin1_code":"19.0",
    "gn:asciiname":"Ban Bouttaphan",
    "gn:country_code":"LA",
    "gn:dem":160,
    "gn:feature_class":"P",
    "gn:feature_code":"PPL",
    "gn:name":"Ban Bouttaphan",
    "gn:population":0,
    "gn:timezone":"Asia/Vientiane",
    "iso:country":"LA",
    "name:und_x_variant":[
        "Ban Kout Taphan",
        "Ban Bouttaphan"
    ],
    "wof:name":"Ban Bouttaphan",
    "wof:placetype":"locality"
},
  "geometry": {"coordinates":[105.77215,15.69827],"type":"Point"}
}