{
  "type": "Feature",
  "properties": {
    "gn:admin1_code":"13.0",
    "gn:asciiname":"Ban Houaydok",
    "gn:country_code":"LA",
    "gn:dem":322,
    "gn:feature_class":"P",
    "gn:feature_code":"PPL",
    "gn:name":"Ban Houayd\u00f4k",
    "gn:population":0,
    "gn:timezone":"Asia/Vientiane",
    "iso:country":"LA",
    "name:lao_x_preferred":[
        "Ban Houayd\u00f4k"
    ],
    "wof:name":"Ban Houaydok",
    "wof:placetype":"locality"
},
  "geometry": {"coordinates":[101.71346,19.1766],"type":"Point"}
}