{
  "type": "Feature",
  "properties": {
    "gn:admin1_code":"15.0",
    "gn:asciiname":"Ban Phonsavang",
    "gn:country_code":"LA",
    "gn:dem":159,
    "gn:feature_class":"P",
    "gn:feature_code":"PPL",
    "gn:name":"Ban Ph\u00f4nsavang",
    "gn:population":0,
    "gn:timezone":"Asia/Vientiane",
    "iso:country":"LA",
    "name:lao_x_preferred":[
        "Ban Ph\u00f4nsavang"
    ],
    "wof:name":"Ban Phonsavang",
    "wof:placetype":"locality"
},
  "geometry": {"coordinates":[104.68522,17.56449],"type":"Point"}
}