{
  "type": "Feature",
  "properties": {
    "gn:admin1_code":"27.0",
    "gn:asciiname":"Ban Phakhiling",
    "gn:country_code":"LA",
    "gn:dem":406,
    "gn:feature_class":"P",
    "gn:feature_code":"PPL",
    "gn:name":"Ban Phakhiling",
    "gn:population":0,
    "gn:timezone":"Asia/Vientiane",
    "iso:country":"LA",
    "name:lao_x_preferred":[
        "Ban Phakhiling"
    ],
    "wof:name":"Ban Phakhiling",
    "wof:placetype":"locality"
},
  "geometry": {"coordinates":[102.16678,19.12289],"type":"Point"}
}