{
  "type": "Feature",
  "properties": {
    "gn:admin1_code":"17.0",
    "gn:asciiname":"Ban Paklouang",
    "gn:country_code":"LA",
    "gn:dem":378,
    "gn:feature_class":"P",
    "gn:feature_code":"PPL",
    "gn:name":"Ban Paklouang",
    "gn:population":0,
    "gn:timezone":"Asia/Vientiane",
    "iso:country":"LA",
    "name:und_x_variant":[
        "Pak Luong"
    ],
    "wof:name":"Ban Paklouang",
    "wof:placetype":"locality"
},
  "geometry": {"coordinates":[102.75763000000001,20.94241],"type":"Point"}
}