{
  "type": "Feature",
  "properties": {
    "gn:admin1_code":"13.0",
    "gn:asciiname":"Ban Thanoun",
    "gn:country_code":"LA",
    "gn:dem":343,
    "gn:feature_class":"P",
    "gn:feature_code":"PPL",
    "gn:name":"Ban Thanoun",
    "gn:population":0,
    "gn:timezone":"Asia/Vientiane",
    "iso:country":"LA",
    "name:und_x_variant":[
        "Ban Tanoun",
        "Ban Tha Nun",
        "Ban Thanoun"
    ],
    "wof:name":"Ban Thanoun",
    "wof:placetype":"locality"
},
  "geometry": {"coordinates":[101.48269999999999,19.82532],"type":"Point"}
}