{
  "type": "Feature",
  "properties": {
    "gn:admin1_code":"26.0",
    "gn:asciiname":"Ban Tangyeuy",
    "gn:country_code":"LA",
    "gn:dem":1418,
    "gn:feature_class":"P",
    "gn:feature_code":"PPL",
    "gn:name":"Ban Tangyeuy",
    "gn:population":0,
    "gn:timezone":"Asia/Vientiane",
    "iso:country":"LA",
    "name:lao_x_preferred":[
        "Ban Tangyeuy"
    ],
    "wof:name":"Ban Tangyeuy",
    "wof:placetype":"locality"
},
  "geometry": {"coordinates":[107.21865,15.66434],"type":"Point"}
}