{
  "type": "Feature",
  "properties": {
    "gn:admin1_code":"15.0",
    "gn:asciiname":"Ban Nongping-Nua",
    "gn:country_code":"LA",
    "gn:dem":171,
    "gn:feature_class":"P",
    "gn:feature_code":"PPL",
    "gn:name":"Ban Nongping-Nua",
    "gn:population":0,
    "gn:timezone":"Asia/Vientiane",
    "iso:country":"LA",
    "name:lao_x_preferred":[
        "Ban Nongping-Nua"
    ],
    "name:und_x_variant":[
        "Ban Nongping"
    ],
    "wof:name":"Ban Nongping-Nua",
    "wof:placetype":"locality"
},
  "geometry": {"coordinates":[105.1849,17.59761],"type":"Point"}
}