{
  "type": "Feature",
  "properties": {
    "gn:admin1_code":"20.0",
    "gn:asciiname":"Ban Saat-Nua",
    "gn:country_code":"LA",
    "gn:dem":152,
    "gn:feature_class":"P",
    "gn:feature_code":"PPL",
    "gn:name":"Ban Saat-Nua",
    "gn:population":0,
    "gn:timezone":"Asia/Vientiane",
    "iso:country":"LA",
    "name:lao_x_preferred":[
        "Ban Saat-Nua"
    ],
    "name:und_x_variant":[
        "Ban Saat"
    ],
    "wof:name":"Ban Saat-Nua",
    "wof:placetype":"locality"
},
  "geometry": {"coordinates":[105.28152,16.57777999999999],"type":"Point"}
}