{
  "type": "Feature",
  "properties": {
    "gn:country":"LA",
    "gn:fcode":"ADMD",
    "gn:pop":80883,
    "iso:country":"LA",
    "name:unk_x_variant":[
        "Muang Sekong"
    ],
    "qs:name":"Muang X\u00e9kong",
    "qs:photos_9r":0,
    "qs:photos_sr":0,
    "qs:pop_sr":"8",
    "wof:name":"Muang X\u00e9kong",
    "wof:placetype":"localadmin",
    "wof:population":80883
},
  "geometry": {"coordinates":[106.97846,15.32084],"type":"Point"}
}