{
  "type": "Feature",
  "properties": {
    "gn:admin1_code":"14.0",
    "gn:asciiname":"Ban Nakoang",
    "gn:cc2":"LA",
    "gn:country_code":"LA",
    "gn:dem":1187,
    "gn:feature_class":"P",
    "gn:feature_code":"PPL",
    "gn:name":"Ban Nakoang",
    "gn:population":0,
    "gn:timezone":"Asia/Vientiane",
    "iso:country":"LA",
    "name:und_x_variant":[
        "Ban Na Khoang",
        "Ban Nakoang"
    ],
    "wof:name":"Ban Nakoang",
    "wof:placetype":"locality"
},
  "geometry": {"coordinates":[103.08333,19.28333],"type":"Point"}
}