{
  "type": "Feature",
  "properties": {
    "gn:admin1_code":"20.0",
    "gn:asciiname":"Ban Pene",
    "gn:country_code":"LA",
    "gn:dem":375,
    "gn:feature_class":"P",
    "gn:feature_code":"PPL",
    "gn:name":"Ban P\u00e9n\u00e9",
    "gn:population":0,
    "gn:timezone":"Asia/Vientiane",
    "iso:country":"LA",
    "wof:name":"Ban Pene",
    "wof:placetype":"locality"
},
  "geometry": {"coordinates":[106.63333,16.21667],"type":"Point"}
}