{
  "type": "Feature",
  "properties": {
    "gn:admin1_code":"27.0",
    "gn:asciiname":"Ban Kokten",
    "gn:country_code":"LA",
    "gn:dem":206,
    "gn:feature_class":"P",
    "gn:feature_code":"PPL",
    "gn:name":"Ban K\u00f4kt\u00e9n",
    "gn:population":0,
    "gn:timezone":"Asia/Vientiane",
    "iso:country":"LA",
    "name:lao_x_preferred":[
        "Ban K\u00f4kt\u00e9n"
    ],
    "wof:name":"Ban Kokten",
    "wof:placetype":"locality"
},
  "geometry": {"coordinates":[102.39379,18.50525],"type":"Point"}
}