{
  "type": "Feature",
  "properties": {
    "gn:admin1_code":"19.0",
    "gn:asciiname":"Ban Apia",
    "gn:country_code":"LA",
    "gn:dem":206,
    "gn:feature_class":"P",
    "gn:feature_code":"PPL",
    "gn:name":"Ban Apia",
    "gn:population":0,
    "gn:timezone":"Asia/Vientiane",
    "iso:country":"LA",
    "name:lao_x_preferred":[
        "Ban Apia"
    ],
    "wof:name":"Ban Apia",
    "wof:placetype":"locality"
},
  "geometry": {"coordinates":[106.19880000000001,16.06583],"type":"Point"}
}