{
  "type": "Feature",
  "properties": {
    "gn:admin1_code":"15.0",
    "gn:asciiname":"Ban Vanghin",
    "gn:country_code":"LA",
    "gn:dem":205,
    "gn:feature_class":"P",
    "gn:feature_code":"PPL",
    "gn:name":"Ban Vanghin",
    "gn:population":0,
    "gn:timezone":"Asia/Vientiane",
    "iso:country":"LA",
    "name:lao_x_preferred":[
        "Ban Vanghin"
    ],
    "wof:name":"Ban Vanghin",
    "wof:placetype":"locality"
},
  "geometry": {"coordinates":[104.91094,17.78183],"type":"Point"}
}