{
  "type": "Feature",
  "properties": {
    "gn:admin1_code":"19.0",
    "gn:asciiname":"Ban Toumli-Thong",
    "gn:country_code":"LA",
    "gn:dem":364,
    "gn:feature_class":"P",
    "gn:feature_code":"PPL",
    "gn:name":"Ban Toumli-Th\u00f4ng",
    "gn:population":0,
    "gn:timezone":"Asia/Vientiane",
    "iso:country":"LA",
    "name:lao_x_preferred":[
        "Ban Toumli-Th\u00f4ng"
    ],
    "wof:name":"Ban Toumli-Thong",
    "wof:placetype":"locality"
},
  "geometry": {"coordinates":[106.61022,16.15295],"type":"Point"}
}