{
  "type": "Feature",
  "properties": {
    "gn:admin1_code":"22.0",
    "gn:asciiname":"Ban Nalouang",
    "gn:country_code":"LA",
    "gn:dem":519,
    "gn:feature_class":"P",
    "gn:feature_code":"PPL",
    "gn:name":"Ban Nalouang",
    "gn:population":0,
    "gn:timezone":"Asia/Vientiane",
    "iso:country":"LA",
    "name:lao_x_preferred":[
        "Ban Nalouang"
    ],
    "wof:name":"Ban Nalouang",
    "wof:placetype":"locality"
},
  "geometry": {"coordinates":[100.70341000000001,20.36281],"type":"Point"}
}