{
  "type": "Feature",
  "properties": {
    "gn:admin1_code":"26.0",
    "gn:asciiname":"Ban Louang",
    "gn:country_code":"LA",
    "gn:dem":220,
    "gn:feature_class":"P",
    "gn:feature_code":"PPL",
    "gn:name":"Ban Louang",
    "gn:population":0,
    "gn:timezone":"Asia/Vientiane",
    "iso:country":"LA",
    "name:lao_x_preferred":[
        "Ban Louang"
    ],
    "name:und_x_variant":[
        "Ban Long"
    ],
    "wof:name":"Ban Louang",
    "wof:placetype":"locality"
},
  "geometry": {"coordinates":[106.76936000000001,15.84151],"type":"Point"}
}