{
  "type": "Feature",
  "properties": {
    "gn:admin1_code":"20.0",
    "gn:asciiname":"Ban Alao",
    "gn:country_code":"LA",
    "gn:dem":304,
    "gn:feature_class":"P",
    "gn:feature_code":"PPL",
    "gn:name":"Ban Alao",
    "gn:population":0,
    "gn:timezone":"Asia/Vientiane",
    "iso:country":"LA",
    "name:lao_x_preferred":[
        "Ban Alao"
    ],
    "wof:name":"Ban Alao",
    "wof:placetype":"locality"
},
  "geometry": {"coordinates":[106.07671000000001,16.01483],"type":"Point"}
}