{
  "type": "Feature",
  "properties": {
    "gn:admin1_code":"23.0",
    "gn:asciiname":"Ban Pakthoay",
    "gn:country_code":"LA",
    "gn:dem":161,
    "gn:feature_class":"P",
    "gn:feature_code":"PPL",
    "gn:name":"Ban Pakthoay",
    "gn:population":0,
    "gn:timezone":"Asia/Vientiane",
    "iso:country":"LA",
    "name:und_x_variant":[
        "Ban Pak Thouei",
        "Ban Pakthouay",
        "Ban Pakthoay"
    ],
    "wof:name":"Ban Pakthoay",
    "wof:placetype":"locality"
},
  "geometry": {"coordinates":[103.43934,18.44125],"type":"Point"}
}