{
  "type": "Feature",
  "properties": {
    "gn:admin1_code":"27.0",
    "gn:asciiname":"Ban Pakha",
    "gn:country_code":"LA",
    "gn:dem":504,
    "gn:feature_class":"P",
    "gn:feature_code":"PPL",
    "gn:name":"Ban Pakha",
    "gn:population":0,
    "gn:timezone":"Asia/Vientiane",
    "iso:country":"LA",
    "name:lao_x_preferred":[
        "Ban Pakha"
    ],
    "name:pol_x_preferred":[
        "Ban Pakha"
    ],
    "wof:name":"Ban Pakha",
    "wof:placetype":"locality"
},
  "geometry": {"coordinates":[102.26542000000001,19.12895],"type":"Point"}
}