{
  "type": "Feature",
  "properties": {
    "gn:admin1_code":"20.0",
    "gn:asciiname":"Ban Navatai",
    "gn:country_code":"LA",
    "gn:dem":179,
    "gn:feature_class":"P",
    "gn:feature_code":"PPL",
    "gn:name":"Ban Navatai",
    "gn:population":0,
    "gn:timezone":"Asia/Vientiane",
    "iso:country":"LA",
    "name:lao_x_preferred":[
        "Ban Navatai"
    ],
    "wof:name":"Ban Navatai",
    "wof:placetype":"locality"
},
  "geometry": {"coordinates":[105.52651000000002,16.34105],"type":"Point"}
}