{
  "type": "Feature",
  "properties": {
    "gn:admin1_code":"20.0",
    "gn:asciiname":"Ban Deng",
    "gn:country_code":"LA",
    "gn:dem":149,
    "gn:feature_class":"P",
    "gn:feature_code":"PPL",
    "gn:name":"Ban D\u00e8ng",
    "gn:population":0,
    "gn:timezone":"Asia/Vientiane",
    "iso:country":"LA",
    "name:lao_x_preferred":[
        "Ban D\u00e8ng"
    ],
    "wof:name":"Ban Deng",
    "wof:placetype":"locality"
},
  "geometry": {"coordinates":[105.04283,16.35878],"type":"Point"}
}