{
  "type": "Feature",
  "properties": {
    "gn:admin1_code":"17.0",
    "gn:asciiname":"Ban Houaychok",
    "gn:country_code":"LA",
    "gn:dem":437,
    "gn:feature_class":"P",
    "gn:feature_code":"PPL",
    "gn:name":"Ban Houaych\u00f4k",
    "gn:population":0,
    "gn:timezone":"Asia/Vientiane",
    "iso:country":"LA",
    "name:lao_x_preferred":[
        "Ban Houaych\u00f4k"
    ],
    "wof:name":"Ban Houaychok",
    "wof:placetype":"locality"
},
  "geometry": {"coordinates":[102.14088,20.03702],"type":"Point"}
}