{
  "type": "Feature",
  "properties": {
    "gn:admin1_code":"17.0",
    "gn:asciiname":"Ban Phakhok-Noy",
    "gn:country_code":"LA",
    "gn:dem":1043,
    "gn:feature_class":"P",
    "gn:feature_code":"PPL",
    "gn:name":"Ban Phakh\u00f4k-Noy",
    "gn:population":0,
    "gn:timezone":"Asia/Vientiane",
    "iso:country":"LA",
    "name:lao_x_preferred":[
        "Ban Phakh\u00f4k-Noy"
    ],
    "wof:name":"Ban Phakhok-Noy",
    "wof:placetype":"locality"
},
  "geometry": {"coordinates":[102.35732,19.63123],"type":"Point"}
}