{
  "type": "Feature",
  "properties": {
    "gn:admin1_code":"7.0",
    "gn:asciiname":"Ban Houaylak",
    "gn:country_code":"LA",
    "gn:dem":809,
    "gn:feature_class":"P",
    "gn:feature_code":"PPL",
    "gn:name":"Ban Houaylak",
    "gn:population":0,
    "gn:timezone":"Asia/Vientiane",
    "iso:country":"LA",
    "name:und_x_variant":[
        "Houei Lak",
        "Ban Houei Lak",
        "Ban Houaylak"
    ],
    "wof:name":"Ban Houaylak",
    "wof:placetype":"locality"
},
  "geometry": {"coordinates":[101.87913,21.04404],"type":"Point"}
}