{
  "type": "Feature",
  "properties": {
    "gn:admin1_code":"17.0",
    "gn:asciiname":"Ban Phalakhon",
    "gn:country_code":"LA",
    "gn:dem":569,
    "gn:feature_class":"P",
    "gn:feature_code":"PPL",
    "gn:name":"Ban Phalakhon",
    "gn:population":0,
    "gn:timezone":"Asia/Vientiane",
    "iso:country":"LA",
    "name:lao_x_preferred":[
        "Ban Phalakhon"
    ],
    "wof:name":"Ban Phalakhon",
    "wof:placetype":"locality"
},
  "geometry": {"coordinates":[101.96768,19.38802],"type":"Point"}
}