{
  "type": "Feature",
  "properties": {
    "gn:admin1_code":"2.0",
    "gn:asciiname":"Ban Nonghin",
    "gn:country_code":"LA",
    "gn:dem":876,
    "gn:feature_class":"P",
    "gn:feature_code":"PPL",
    "gn:name":"Ban Nonghin",
    "gn:population":0,
    "gn:timezone":"Asia/Vientiane",
    "iso:country":"LA",
    "name:und_x_variant":[
        "Ban Nong Hine",
        "Ban Nonghin"
    ],
    "wof:name":"Ban Nonghin",
    "wof:placetype":"locality"
},
  "geometry": {"coordinates":[106.55397000000001,15.15852],"type":"Point"}
}