{
  "type": "Feature",
  "properties": {
    "gn:admin1_code":"20.0",
    "gn:asciiname":"Ban Nongdeng",
    "gn:country_code":"LA",
    "gn:dem":191,
    "gn:feature_class":"P",
    "gn:feature_code":"PPL",
    "gn:name":"Ban Nongd\u00e8ng",
    "gn:population":0,
    "gn:timezone":"Asia/Vientiane",
    "iso:country":"LA",
    "name:lao_x_preferred":[
        "Ban Nongd\u00e8ng"
    ],
    "wof:name":"Ban Nongdeng",
    "wof:placetype":"locality"
},
  "geometry": {"coordinates":[105.67177,17.10765],"type":"Point"}
}