{
  "type": "Feature",
  "properties": {
    "gn:admin1_code":"3.0",
    "gn:asciiname":"Ban Nanom",
    "gn:country_code":"LA",
    "gn:dem":747,
    "gn:feature_class":"P",
    "gn:feature_code":"PPL",
    "gn:name":"Ban Nanom",
    "gn:population":0,
    "gn:timezone":"Asia/Vientiane",
    "iso:country":"LA",
    "name:lao_x_preferred":[
        "Ban Nanom"
    ],
    "wof:name":"Ban Nanom",
    "wof:placetype":"locality"
},
  "geometry": {"coordinates":[103.3501,20.44343],"type":"Point"}
}