{
  "type": "Feature",
  "properties": {
    "gn:admin1_code":"27.0",
    "gn:asciiname":"Ban Pakpo",
    "gn:country_code":"LA",
    "gn:dem":256,
    "gn:feature_class":"P",
    "gn:feature_code":"PPL",
    "gn:name":"Ban Pakpo",
    "gn:population":0,
    "gn:timezone":"Asia/Vientiane",
    "iso:country":"LA",
    "wof:name":"Ban Pakpo",
    "wof:placetype":"locality"
},
  "geometry": {"coordinates":[102.45003,18.97376],"type":"Point"}
}