{
  "type": "Feature",
  "properties": {
    "gn:admin1_code":"17.0",
    "gn:asciiname":"Ban Hat Kho",
    "gn:country_code":"LA",
    "gn:dem":338,
    "gn:feature_class":"P",
    "gn:feature_code":"PPL",
    "gn:name":"Ban Hat Kho",
    "gn:population":0,
    "gn:timezone":"Asia/Vientiane",
    "iso:country":"LA",
    "wof:name":"Ban Hat Kho",
    "wof:placetype":"locality"
},
  "geometry": {"coordinates":[102.36667,20.25],"type":"Point"}
}