{
  "type": "Feature",
  "properties": {
    "gn:admin1_code":"23.0",
    "gn:asciiname":"Ban Phabo",
    "gn:country_code":"LA",
    "gn:dem":1304,
    "gn:feature_class":"P",
    "gn:feature_code":"PPL",
    "gn:name":"Ban Phabo",
    "gn:population":0,
    "gn:timezone":"Asia/Vientiane",
    "iso:country":"LA",
    "name:lao_x_preferred":[
        "Ban Phabo"
    ],
    "wof:name":"Ban Phabo",
    "wof:placetype":"locality"
},
  "geometry": {"coordinates":[104.61614,18.65078],"type":"Point"}
}