{
  "type": "Feature",
  "properties": {
    "gn:admin1_code":"16.0",
    "gn:asciiname":"Ban Cha-Oup",
    "gn:country_code":"LA",
    "gn:dem":771,
    "gn:feature_class":"P",
    "gn:feature_code":"PPL",
    "gn:name":"Ban Cha-Oup",
    "gn:population":0,
    "gn:timezone":"Asia/Vientiane",
    "iso:country":"LA",
    "name:lao_x_preferred":[
        "Ban Cha-Oup"
    ],
    "wof:name":"Ban Cha-Oup",
    "wof:placetype":"locality"
},
  "geometry": {"coordinates":[101.03570000000001,21.41003],"type":"Point"}
}