{
  "type": "Feature",
  "properties": {
    "gn:admin1_code":"18.0",
    "gn:asciiname":"Ban Sopxou",
    "gn:country_code":"LA",
    "gn:dem":666,
    "gn:feature_class":"P",
    "gn:feature_code":"PPL",
    "gn:name":"Ban S\u00f4pxou",
    "gn:population":0,
    "gn:timezone":"Asia/Vientiane",
    "iso:country":"LA",
    "name:lao_x_preferred":[
        "Ban S\u00f4pxou"
    ],
    "wof:name":"Ban Sopxou",
    "wof:placetype":"locality"
},
  "geometry": {"coordinates":[101.8711,22.00217],"type":"Point"}
}