{
  "type": "Feature",
  "properties": {
    "gn:admin1_code":"24.0",
    "gn:asciiname":"Ban Naxaythong",
    "gn:cc2":"LA",
    "gn:country_code":"LA",
    "gn:dem":179,
    "gn:feature_class":"P",
    "gn:feature_code":"PPL",
    "gn:name":"Ban Naxaythong",
    "gn:population":0,
    "gn:timezone":"Asia/Vientiane",
    "iso:country":"LA",
    "name:und_x_variant":[
        "Muang Naxay Thong",
        "Ban Naxaythong"
    ],
    "wof:name":"Ban Naxaythong",
    "wof:placetype":"locality"
},
  "geometry": {"coordinates":[102.53028,18.07806],"type":"Point"}
}