{
  "type": "Feature",
  "properties": {
    "gn:admin1_code":"14.0",
    "gn:asciiname":"Ban Kouay",
    "gn:cc2":"LA",
    "gn:country_code":"LA",
    "gn:dem":1108,
    "gn:feature_class":"P",
    "gn:feature_code":"PPL",
    "gn:name":"Ban Kouay",
    "gn:population":0,
    "gn:timezone":"Asia/Vientiane",
    "iso:country":"LA",
    "name:und_x_variant":[
        "Ban Kouei",
        "Ban Kouay"
    ],
    "wof:name":"Ban Kouay",
    "wof:placetype":"locality"
},
  "geometry": {"coordinates":[103.16667,19.38333],"type":"Point"}
}