{
  "type": "Feature",
  "properties": {
    "gn:admin1_code":"7.0",
    "gn:asciiname":"Ban Bo",
    "gn:country_code":"LA",
    "gn:dem":325,
    "gn:feature_class":"P",
    "gn:feature_code":"PPL",
    "gn:name":"Ban Bo",
    "gn:population":0,
    "gn:timezone":"Asia/Vientiane",
    "iso:country":"LA",
    "name:lao_x_preferred":[
        "Ban Bo"
    ],
    "name:und_x_variant":[
        "Ban Xieng Bo",
        "Ban Xiangbo"
    ],
    "wof:name":"Ban Bo",
    "wof:placetype":"locality"
},
  "geometry": {"coordinates":[101.64382999999999,19.87914],"type":"Point"}
}