{
  "type": "Feature",
  "properties": {
    "gn:admin1_code":"23.0",
    "gn:asciiname":"Ban Namsun",
    "gn:country_code":"LA",
    "gn:dem":166,
    "gn:feature_class":"P",
    "gn:feature_code":"PPL",
    "gn:name":"Ban Namsun",
    "gn:population":0,
    "gn:timezone":"Asia/Vientiane",
    "iso:country":"LA",
    "name:lao_x_preferred":[
        "Ban Namsun"
    ],
    "wof:name":"Ban Namsun",
    "wof:placetype":"locality"
},
  "geometry": {"coordinates":[104.03825000000001,18.38992],"type":"Point"}
}