{
  "type": "Feature",
  "properties": {
    "gn:admin1_code":"20.0",
    "gn:asciiname":"Ban Nanongdeun",
    "gn:country_code":"LA",
    "gn:dem":172,
    "gn:feature_class":"P",
    "gn:feature_code":"PPL",
    "gn:name":"Ban Nanongdeun",
    "gn:population":0,
    "gn:timezone":"Asia/Vientiane",
    "iso:country":"LA",
    "name:lao_x_preferred":[
        "Ban Nanongdeun"
    ],
    "wof:name":"Ban Nanongdeun",
    "wof:placetype":"locality"
},
  "geometry": {"coordinates":[105.37036000000001,16.80527],"type":"Point"}
}