{
  "type": "Feature",
  "properties": {
    "gn:admin1_code":"28.0",
    "gn:asciiname":"Ban Kengsang",
    "gn:country_code":"LA",
    "gn:dem":227,
    "gn:feature_class":"P",
    "gn:feature_code":"PPL",
    "gn:name":"Ban Kengsang",
    "gn:population":0,
    "gn:timezone":"Asia/Vientiane",
    "iso:country":"LA",
    "name:lao_x_preferred":[
        "Ban Kengsang"
    ],
    "wof:name":"Ban Kengsang",
    "wof:placetype":"locality"
},
  "geometry": {"coordinates":[102.95014,18.53691],"type":"Point"}
}