{
  "type": "Feature",
  "properties": {
    "gn:admin1_code":"19.0",
    "gn:asciiname":"Ban Nongseng",
    "gn:country_code":"LA",
    "gn:dem":143,
    "gn:feature_class":"P",
    "gn:feature_code":"PPL",
    "gn:name":"Ban Nongs\u00e8ng",
    "gn:population":0,
    "gn:timezone":"Asia/Vientiane",
    "iso:country":"LA",
    "name:lao_x_preferred":[
        "Ban Nongs\u00e8ng"
    ],
    "name:lao_x_variant":[
        "Ban Nong Seng"
    ],
    "wof:name":"Ban Nongseng",
    "wof:placetype":"locality"
},
  "geometry": {"coordinates":[105.42511,15.89373],"type":"Point"}
}