{
  "type": "Feature",
  "properties": {
    "gn:admin1_code":"17.0",
    "gn:asciiname":"Ban Vangmat",
    "gn:country_code":"LA",
    "gn:dem":541,
    "gn:feature_class":"P",
    "gn:feature_code":"PPL",
    "gn:name":"Ban Vangmat",
    "gn:population":0,
    "gn:timezone":"Asia/Vientiane",
    "iso:country":"LA",
    "name:lao_x_preferred":[
        "Ban Vangmat"
    ],
    "wof:name":"Ban Vangmat",
    "wof:placetype":"locality"
},
  "geometry": {"coordinates":[103.06932,20.36389],"type":"Point"}
}