{
  "type": "Feature",
  "properties": {
    "gn:admin1_code":"2.0",
    "gn:asciiname":"Ban Songkhon",
    "gn:country_code":"LA",
    "gn:dem":188,
    "gn:feature_class":"P",
    "gn:feature_code":"PPL",
    "gn:name":"Ban Songkhon",
    "gn:population":0,
    "gn:timezone":"Asia/Vientiane",
    "iso:country":"LA",
    "name:lao_x_preferred":[
        "Ban Songkhon"
    ],
    "name:und_x_variant":[
        "Ban Song Khone",
        "Ban Thong Sone",
        "Ban Th\u00f4ngson"
    ],
    "wof:name":"Ban Songkhon",
    "wof:placetype":"locality"
},
  "geometry": {"coordinates":[105.90873000000001,15.33607],"type":"Point"}
}