{
  "type": "Feature",
  "properties": {
    "gn:admin1_code":"20.0",
    "gn:asciiname":"Ban Kaison",
    "gn:country_code":"LA",
    "gn:dem":235,
    "gn:feature_class":"P",
    "gn:feature_code":"PPL",
    "gn:name":"Ban Kaison",
    "gn:population":0,
    "gn:timezone":"Asia/Vientiane",
    "iso:country":"LA",
    "name:lao_x_preferred":[
        "Ban Kaison"
    ],
    "wof:name":"Ban Kaison",
    "wof:placetype":"locality"
},
  "geometry": {"coordinates":[106.40227,16.42104],"type":"Point"}
}