{
  "type": "Feature",
  "properties": {
    "gn:admin1_code":"18.0",
    "gn:asciiname":"Ban Sen-In",
    "gn:country_code":"LA",
    "gn:dem":868,
    "gn:feature_class":"P",
    "gn:feature_code":"PPL",
    "gn:name":"Ban S\u00e8n-In",
    "gn:population":0,
    "gn:timezone":"Asia/Vientiane",
    "iso:country":"LA",
    "name:lao_x_preferred":[
        "Ban S\u00e8n-In"
    ],
    "wof:name":"Ban Sen-In",
    "wof:placetype":"locality"
},
  "geometry": {"coordinates":[102.65000999999999,21.09469],"type":"Point"}
}