{
  "type": "Feature",
  "properties": {
    "gn:admin1_code":"20.0",
    "gn:asciiname":"Ban Naphek-Noy",
    "gn:country_code":"LA",
    "gn:dem":169,
    "gn:feature_class":"P",
    "gn:feature_code":"PPL",
    "gn:name":"Ban Naph\u00e8k-Noy",
    "gn:population":0,
    "gn:timezone":"Asia/Vientiane",
    "iso:country":"LA",
    "name:lao_x_preferred":[
        "Ban Naph\u00e8k-Noy"
    ],
    "wof:name":"Ban Naphek-Noy",
    "wof:placetype":"locality"
},
  "geometry": {"coordinates":[105.24109,16.79631],"type":"Point"}
}