{
  "type": "Feature",
  "properties": {
    "gn:admin1_code":"17.0",
    "gn:asciiname":"Ban Babaluay",
    "gn:country_code":"LA",
    "gn:dem":1038,
    "gn:feature_class":"P",
    "gn:feature_code":"PPL",
    "gn:name":"Ban Babaluay",
    "gn:population":0,
    "gn:timezone":"Asia/Vientiane",
    "iso:country":"LA",
    "name:und_x_variant":[
        "Ban Ba Bluey",
        "Ban Babaluay"
    ],
    "wof:name":"Ban Babaluay",
    "wof:placetype":"locality"
},
  "geometry": {"coordinates":[102.40322999999999,19.866],"type":"Point"}
}