{
  "type": "Feature",
  "properties": {
    "gn:admin1_code":"20.0",
    "gn:asciiname":"Ban Nongsithouan",
    "gn:country_code":"LA",
    "gn:dem":148,
    "gn:feature_class":"P",
    "gn:feature_code":"PPL",
    "gn:name":"Ban Nongsithouan",
    "gn:population":0,
    "gn:timezone":"Asia/Vientiane",
    "iso:country":"LA",
    "name:lao_x_preferred":[
        "Ban Nongsithouan"
    ],
    "wof:name":"Ban Nongsithouan",
    "wof:placetype":"locality"
},
  "geometry": {"coordinates":[105.19110000000001,16.49503],"type":"Point"}
}