{
  "type": "Feature",
  "properties": {
    "gn:admin1_code":"18.0",
    "gn:asciiname":"Ban Namlong-Mai",
    "gn:country_code":"LA",
    "gn:dem":1051,
    "gn:feature_class":"P",
    "gn:feature_code":"PPL",
    "gn:name":"Ban Namlong-Mai",
    "gn:population":0,
    "gn:timezone":"Asia/Vientiane",
    "iso:country":"LA",
    "name:lao_x_preferred":[
        "Ban Namlong-Mai"
    ],
    "wof:name":"Ban Namlong-Mai",
    "wof:placetype":"locality"
},
  "geometry": {"coordinates":[102.00624000000001,21.62498],"type":"Point"}
}