{
  "type": "Feature",
  "properties": {
    "gn:admin1_code":"20.0",
    "gn:asciiname":"Ban Nabong",
    "gn:country_code":"LA",
    "gn:dem":181,
    "gn:feature_class":"P",
    "gn:feature_code":"PPL",
    "gn:name":"Ban Nab\u00f4ng",
    "gn:population":0,
    "gn:timezone":"Asia/Vientiane",
    "iso:country":"LA",
    "name:lao_x_preferred":[
        "Ban Nab\u00f4ng"
    ],
    "wof:name":"Ban Nabong",
    "wof:placetype":"locality"
},
  "geometry": {"coordinates":[105.73521,16.1817],"type":"Point"}
}