{
  "type": "Feature",
  "properties": {
    "gn:admin1_code":"7.0",
    "gn:asciiname":"Ban Houayhok",
    "gn:country_code":"LA",
    "gn:dem":570,
    "gn:feature_class":"P",
    "gn:feature_code":"PPL",
    "gn:name":"Ban Houayh\u00f4k",
    "gn:population":0,
    "gn:timezone":"Asia/Vientiane",
    "iso:country":"LA",
    "name:lao_x_preferred":[
        "Ban Houayh\u00f4k"
    ],
    "wof:name":"Ban Houayhok",
    "wof:placetype":"locality"
},
  "geometry": {"coordinates":[102.02777,20.91971],"type":"Point"}
}