{
  "type": "Feature",
  "properties": {
    "gn:admin1_code":"18.0",
    "gn:asciiname":"A Ta Chai",
    "gn:country_code":"LA",
    "gn:dem":1188,
    "gn:feature_class":"P",
    "gn:feature_code":"PPL",
    "gn:name":"A Ta Chai",
    "gn:population":0,
    "gn:timezone":"Asia/Vientiane",
    "iso:country":"LA",
    "wof:name":"A Ta Chai",
    "wof:placetype":"locality"
},
  "geometry": {"coordinates":[102.13333,21.41667],"type":"Point"}
}