{
  "type": "Feature",
  "properties": {
    "gn:admin1_code":"20.0",
    "gn:asciiname":"Ban Panai",
    "gn:country_code":"LA",
    "gn:dem":368,
    "gn:feature_class":"P",
    "gn:feature_code":"PPL",
    "gn:name":"Ban Panai",
    "gn:population":0,
    "gn:timezone":"Asia/Vientiane",
    "iso:country":"LA",
    "name:lao_x_preferred":[
        "Ban Panai"
    ],
    "wof:name":"Ban Panai",
    "wof:placetype":"locality"
},
  "geometry": {"coordinates":[106.42413000000001,16.75136],"type":"Point"}
}