{
  "type": "Feature",
  "properties": {
    "gn:admin1_code":"2.0",
    "gn:asciiname":"Ban Houadonhi-Noy",
    "gn:country_code":"LA",
    "gn:dem":93,
    "gn:feature_class":"P",
    "gn:feature_code":"PPL",
    "gn:name":"Ban Houadonhi-Noy",
    "gn:population":0,
    "gn:timezone":"Asia/Vientiane",
    "iso:country":"LA",
    "name:lao_x_preferred":[
        "Ban Houadonhi-Noy"
    ],
    "name:und_x_variant":[
        "Ban Houa Donchi"
    ],
    "wof:name":"Ban Houadonhi-Noy",
    "wof:placetype":"locality"
},
  "geometry": {"coordinates":[105.81119,14.0541],"type":"Point"}
}