{
  "type": "Feature",
  "properties": {
    "gn:admin1_code":"15.0",
    "gn:asciiname":"Ban Thap-Mai",
    "gn:country_code":"LA",
    "gn:dem":176,
    "gn:feature_class":"P",
    "gn:feature_code":"PPL",
    "gn:name":"Ban Thap-Mai",
    "gn:population":0,
    "gn:timezone":"Asia/Vientiane",
    "iso:country":"LA",
    "name:lao_x_preferred":[
        "Ban Thap-Mai"
    ],
    "wof:name":"Ban Thap-Mai",
    "wof:placetype":"locality"
},
  "geometry": {"coordinates":[105.23526,17.15346],"type":"Point"}
}