{
  "type": "Feature",
  "properties": {
    "gn:admin1_code":"15.0",
    "gn:asciiname":"Ban Kenggnang",
    "gn:country_code":"LA",
    "gn:dem":164,
    "gn:feature_class":"P",
    "gn:feature_code":"PPL",
    "gn:name":"Ban K\u00e8nggnang",
    "gn:population":0,
    "gn:timezone":"Asia/Vientiane",
    "iso:country":"LA",
    "name:lao_x_preferred":[
        "Ban K\u00e8nggnang"
    ],
    "wof:name":"Ban Kenggnang",
    "wof:placetype":"locality"
},
  "geometry": {"coordinates":[104.74329,17.52697],"type":"Point"}
}