{
  "type": "Feature",
  "properties": {
    "gn:admin1_code":"2.0",
    "gn:asciiname":"Ban Xiangvang",
    "gn:country_code":"LA",
    "gn:dem":103,
    "gn:feature_class":"P",
    "gn:feature_code":"PPL",
    "gn:name":"Ban Xiangvang",
    "gn:population":0,
    "gn:timezone":"Asia/Vientiane",
    "iso:country":"LA",
    "name:und_x_variant":[
        "Ban Sieng Vang",
        "Ban Xiangvang"
    ],
    "wof:name":"Ban Xiangvang",
    "wof:placetype":"locality"
},
  "geometry": {"coordinates":[105.88975000000001,14.86055],"type":"Point"}
}