{
  "type": "Feature",
  "properties": {
    "gn:admin1_code":"19.0",
    "gn:asciiname":"Muang Taoy",
    "gn:country_code":"LA",
    "gn:dem":418,
    "gn:feature_class":"P",
    "gn:feature_code":"PPL",
    "gn:name":"Muang Ta\u00f4y",
    "gn:population":0,
    "gn:timezone":"Asia/Vientiane",
    "iso:country":"LA",
    "name:lao_x_preferred":[
        "Muang Ta\u00f4y"
    ],
    "wof:name":"Muang Taoy",
    "wof:placetype":"locality"
},
  "geometry": {"coordinates":[106.58157,16.05862999999999],"type":"Point"}
}