{
  "type": "Feature",
  "properties": {
    "gn:admin1_code":"18.0",
    "gn:asciiname":"Ban Phicheu-Mai",
    "gn:country_code":"LA",
    "gn:dem":508,
    "gn:feature_class":"P",
    "gn:feature_code":"PPL",
    "gn:name":"Ban Phicheu-Mai",
    "gn:population":0,
    "gn:timezone":"Asia/Vientiane",
    "iso:country":"LA",
    "name:und_x_variant":[
        "Ban Phiou",
        "Ban Phieu",
        "Ban Phicheu-Mai"
    ],
    "wof:name":"Ban Phicheu-Mai",
    "wof:placetype":"locality"
},
  "geometry": {"coordinates":[102.12560000000001,21.12646],"type":"Point"}
}