{
  "type": "Feature",
  "properties": {
    "gn:admin1_code":"27.0",
    "gn:asciiname":"Ban Khok Khaodo",
    "gn:country_code":"LA",
    "gn:dem":338,
    "gn:feature_class":"P",
    "gn:feature_code":"PPL",
    "gn:name":"Ban Kh\u00f4k Khaodo",
    "gn:population":0,
    "gn:timezone":"Asia/Vientiane",
    "iso:country":"LA",
    "wof:name":"Ban Khok Khaodo",
    "wof:placetype":"locality"
},
  "geometry": {"coordinates":[101.55,18.33333],"type":"Point"}
}