{
  "type": "Feature",
  "properties": {
    "gn:admin1_code":"14.0",
    "gn:asciiname":"Ban Pakka",
    "gn:country_code":"LA",
    "gn:dem":1497,
    "gn:feature_class":"P",
    "gn:feature_code":"PPL",
    "gn:name":"Ban Pakka",
    "gn:population":0,
    "gn:timezone":"Asia/Vientiane",
    "iso:country":"LA",
    "name:lao_x_preferred":[
        "Ban Pakka"
    ],
    "wof:name":"Ban Pakka",
    "wof:placetype":"locality"
},
  "geometry": {"coordinates":[104.02463,19.49345],"type":"Point"}
}