{
  "type": "Feature",
  "properties": {
    "gn:admin1_code":"13.0",
    "gn:asciiname":"Ban Thamixay",
    "gn:country_code":"LA",
    "gn:dem":392,
    "gn:feature_class":"P",
    "gn:feature_code":"PPL",
    "gn:name":"Ban Thamixay",
    "gn:population":0,
    "gn:timezone":"Asia/Vientiane",
    "iso:country":"LA",
    "name:lao_x_preferred":[
        "Ban Thamixay"
    ],
    "wof:name":"Ban Thamixay",
    "wof:placetype":"locality"
},
  "geometry": {"coordinates":[101.35277000000001,18.32686],"type":"Point"}
}