{
  "type": "Feature",
  "properties": {
    "gn:admin1_code":"3.0",
    "gn:asciiname":"Ban Nahin",
    "gn:country_code":"LA",
    "gn:dem":405,
    "gn:feature_class":"P",
    "gn:feature_code":"PPL",
    "gn:name":"Ban Nahin",
    "gn:population":0,
    "gn:timezone":"Asia/Vientiane",
    "iso:country":"LA",
    "name:lao_x_preferred":[
        "Ban Nahin"
    ],
    "wof:name":"Ban Nahin",
    "wof:placetype":"locality"
},
  "geometry": {"coordinates":[104.41704,20.40817],"type":"Point"}
}