{
  "type": "Feature",
  "properties": {
    "gn:admin1_code":"13.0",
    "gn:asciiname":"Ban Houaydou",
    "gn:country_code":"LA",
    "gn:dem":426,
    "gn:feature_class":"P",
    "gn:feature_code":"PPL",
    "gn:name":"Ban Houaydou",
    "gn:population":0,
    "gn:timezone":"Asia/Vientiane",
    "iso:country":"LA",
    "name:lao_x_preferred":[
        "Ban Houaydou"
    ],
    "wof:name":"Ban Houaydou",
    "wof:placetype":"locality"
},
  "geometry": {"coordinates":[101.50472000000001,19.79669],"type":"Point"}
}