{
  "type": "Feature",
  "properties": {
    "gn:admin1_code":"17.0",
    "gn:asciiname":"Ban Namting",
    "gn:country_code":"LA",
    "gn:dem":1087,
    "gn:feature_class":"P",
    "gn:feature_code":"PPL",
    "gn:name":"Ban Namting",
    "gn:population":0,
    "gn:timezone":"Asia/Vientiane",
    "iso:country":"LA",
    "name:lao_x_preferred":[
        "Ban Namting"
    ],
    "wof:name":"Ban Namting",
    "wof:placetype":"locality"
},
  "geometry": {"coordinates":[102.60688,19.32938],"type":"Point"}
}