{
  "type": "Feature",
  "properties": {
    "gn:admin1_code":"20.0",
    "gn:asciiname":"Ban Hatkhamdi",
    "gn:country_code":"LA",
    "gn:dem":150,
    "gn:feature_class":"P",
    "gn:feature_code":"PPL",
    "gn:name":"Ban Hatkhamdi",
    "gn:population":0,
    "gn:timezone":"Asia/Vientiane",
    "iso:country":"LA",
    "name:lao_x_preferred":[
        "Ban Hatkhamdi"
    ],
    "wof:name":"Ban Hatkhamdi",
    "wof:placetype":"locality"
},
  "geometry": {"coordinates":[104.93168,17.08972],"type":"Point"}
}