{
  "type": "Feature",
  "properties": {
    "gn:admin1_code":"14.0",
    "gn:asciiname":"Ban Xouan",
    "gn:country_code":"LA",
    "gn:dem":1314,
    "gn:feature_class":"P",
    "gn:feature_code":"PPL",
    "gn:name":"Ban Xouan",
    "gn:population":0,
    "gn:timezone":"Asia/Vientiane",
    "iso:country":"LA",
    "name:lao_x_preferred":[
        "Ban Xouan"
    ],
    "wof:name":"Ban Xouan",
    "wof:placetype":"locality"
},
  "geometry": {"coordinates":[103.35428,19.62319],"type":"Point"}
}