{
  "type": "Feature",
  "properties": {
    "gn:admin1_code":"23.0",
    "gn:asciiname":"Ban Xu-Kdum",
    "gn:country_code":"LA",
    "gn:dem":1118,
    "gn:feature_class":"P",
    "gn:feature_code":"PPL",
    "gn:name":"Ban Xu-Kdum",
    "gn:population":0,
    "gn:timezone":"Asia/Vientiane",
    "iso:country":"LA",
    "name:lao_x_preferred":[
        "Ban Xu-Kdum"
    ],
    "name:und_x_variant":[
        "Ban Xu Kdum",
        "Ban Xu Koum"
    ],
    "wof:name":"Ban Xu-Kdum",
    "wof:placetype":"locality"
},
  "geometry": {"coordinates":[104.99222,18.49501],"type":"Point"}
}