{
  "type": "Feature",
  "properties": {
    "gn:admin1_code":"2.0",
    "gn:asciiname":"Ban Lek Pet",
    "gn:country_code":"LA",
    "gn:dem":269,
    "gn:feature_class":"P",
    "gn:feature_code":"PPL",
    "gn:name":"Ban Lek P\u00e8t",
    "gn:population":0,
    "gn:timezone":"Asia/Vientiane",
    "iso:country":"LA",
    "name:lao_x_preferred":[
        "Ban Lek P\u00e8t"
    ],
    "wof:name":"Ban Lek Pet",
    "wof:placetype":"locality"
},
  "geometry": {"coordinates":[105.89654,15.20579],"type":"Point"}
}