{
  "type": "Feature",
  "properties": {
    "gn:admin1_code":"19.0",
    "gn:asciiname":"Ban Tongxouay",
    "gn:country_code":"LA",
    "gn:dem":187,
    "gn:feature_class":"P",
    "gn:feature_code":"PPL",
    "gn:name":"Ban T\u00f4ngxouay",
    "gn:population":0,
    "gn:timezone":"Asia/Vientiane",
    "iso:country":"LA",
    "name:lao_x_preferred":[
        "Ban T\u00f4ngxouay"
    ],
    "wof:name":"Ban Tongxouay",
    "wof:placetype":"locality"
},
  "geometry": {"coordinates":[106.34687,15.83676],"type":"Point"}
}