{
  "type": "Feature",
  "properties": {
    "gn:admin1_code":"1.0",
    "gn:asciiname":"Ban Salatintok",
    "gn:country_code":"LA",
    "gn:dem":226,
    "gn:feature_class":"P",
    "gn:feature_code":"PPL",
    "gn:name":"Ban Salatint\u00f4k",
    "gn:population":0,
    "gn:timezone":"Asia/Vientiane",
    "iso:country":"LA",
    "name:und_x_variant":[
        "Salatint\u00f4k",
        "Sala Tin Toc",
        "Sa La Sin Toc",
        "Ban Salatint\u00f4k"
    ],
    "wof:name":"Ban Salatintok",
    "wof:placetype":"locality"
},
  "geometry": {"coordinates":[107.08484,15.00732],"type":"Point"}
}