{
  "type": "Feature",
  "properties": {
    "gn:admin1_code":"19.0",
    "gn:asciiname":"Ban Sano-Noy",
    "gn:country_code":"LA",
    "gn:dem":232,
    "gn:feature_class":"P",
    "gn:feature_code":"PPL",
    "gn:name":"Ban San\u00f4-Noy",
    "gn:population":0,
    "gn:timezone":"Asia/Vientiane",
    "iso:country":"LA",
    "name:lao_x_preferred":[
        "Ban San\u00f4-Noy"
    ],
    "wof:name":"Ban Sano-Noy",
    "wof:placetype":"locality"
},
  "geometry": {"coordinates":[106.16754,16.11574],"type":"Point"}
}