{
  "type": "Feature",
  "properties": {
    "gn:admin1_code":"20.0",
    "gn:asciiname":"Ban Houaymao",
    "gn:country_code":"LA",
    "gn:dem":168,
    "gn:feature_class":"P",
    "gn:feature_code":"PPL",
    "gn:name":"Ban Houaymao",
    "gn:population":0,
    "gn:timezone":"Asia/Vientiane",
    "iso:country":"LA",
    "name:und_x_variant":[
        "Ban Houei Mao",
        "Ban Houaymao"
    ],
    "wof:name":"Ban Houaymao",
    "wof:placetype":"locality"
},
  "geometry": {"coordinates":[105.06755,16.63929],"type":"Point"}
}