{
  "type": "Feature",
  "properties": {
    "gn:admin1_code":"18.0",
    "gn:asciiname":"Nok Peng",
    "gn:country_code":"LA",
    "gn:dem":601,
    "gn:feature_class":"P",
    "gn:feature_code":"PPL",
    "gn:name":"Nok Peng",
    "gn:population":0,
    "gn:timezone":"Asia/Vientiane",
    "iso:country":"LA",
    "wof:name":"Nok Peng",
    "wof:placetype":"locality"
},
  "geometry": {"coordinates":[102.59999999999999,21.05],"type":"Point"}
}