{
  "type": "Feature",
  "properties": {
    "gn:admin1_code":"20.0",
    "gn:asciiname":"Ban Vang",
    "gn:country_code":"LA",
    "gn:dem":407,
    "gn:feature_class":"P",
    "gn:feature_code":"PPL",
    "gn:name":"Ban Vang",
    "gn:population":0,
    "gn:timezone":"Asia/Vientiane",
    "iso:country":"LA",
    "name:lao_x_preferred":[
        "Ban Vang"
    ],
    "wof:name":"Ban Vang",
    "wof:placetype":"locality"
},
  "geometry": {"coordinates":[106.42983999999998,16.34012],"type":"Point"}
}