{
  "type": "Feature",
  "properties": {
    "gn:admin1_code":"17.0",
    "gn:asciiname":"Ban Houaykha",
    "gn:country_code":"LA",
    "gn:dem":752,
    "gn:feature_class":"P",
    "gn:feature_code":"PPL",
    "gn:name":"Ban Houaykha",
    "gn:population":0,
    "gn:timezone":"Asia/Vientiane",
    "iso:country":"LA",
    "name:und_x_variant":[
        "Ban Houei Khe",
        "Ban Houay Kh\u00e9",
        "Ban Houaykha"
    ],
    "wof:name":"Ban Houaykha",
    "wof:placetype":"locality"
},
  "geometry": {"coordinates":[102.27002,20.16951],"type":"Point"}
}