{
  "type": "Feature",
  "properties": {
    "gn:admin1_code":"22.0",
    "gn:asciiname":"Ban Mai-Viangphoukha",
    "gn:country_code":"LA",
    "gn:dem":451,
    "gn:feature_class":"P",
    "gn:feature_code":"PPL",
    "gn:name":"Ban Mai-Viangphoukha",
    "gn:population":0,
    "gn:timezone":"Asia/Vientiane",
    "iso:country":"LA",
    "name:lao_x_preferred":[
        "Ban Mai-Viangphoukha"
    ],
    "wof:name":"Ban Mai-Viangphoukha",
    "wof:placetype":"locality"
},
  "geometry": {"coordinates":[100.44279,20.27753],"type":"Point"}
}