{
  "type": "Feature",
  "properties": {
    "gn:admin1_code":"20.0",
    "gn:asciiname":"Ban Pa-Ok",
    "gn:country_code":"LA",
    "gn:dem":190,
    "gn:feature_class":"P",
    "gn:feature_code":"PPL",
    "gn:name":"Ban Pa-\u00d4k",
    "gn:population":0,
    "gn:timezone":"Asia/Vientiane",
    "iso:country":"LA",
    "name:lao_x_preferred":[
        "Ban Pa-\u00d4k"
    ],
    "name:und_x_variant":[
        "Ban Pook",
        "Ban Pa-\u00d4k (1)"
    ],
    "wof:name":"Ban Pa-Ok",
    "wof:placetype":"locality"
},
  "geometry": {"coordinates":[106.19484,16.28635],"type":"Point"}
}