{
  "type": "Feature",
  "properties": {
    "gn:admin1_code":"1.0",
    "gn:asciiname":"Ban Dakmaluk-Kang",
    "gn:country_code":"LA",
    "gn:dem":514,
    "gn:feature_class":"P",
    "gn:feature_code":"PPL",
    "gn:name":"Ban Dakmaluk-Kang",
    "gn:population":0,
    "gn:timezone":"Asia/Vientiane",
    "iso:country":"LA",
    "name:lao_x_preferred":[
        "Ban Dakmaluk-Kang"
    ],
    "wof:name":"Ban Dakmaluk-Kang",
    "wof:placetype":"locality"
},
  "geometry": {"coordinates":[107.29952,15.15815],"type":"Point"}
}