{
  "type": "Feature",
  "properties": {
    "gn:admin1_code":"20.0",
    "gn:asciiname":"Ban Vangkhen",
    "gn:cc2":"LA",
    "gn:country_code":"LA",
    "gn:dem":176,
    "gn:feature_class":"P",
    "gn:feature_code":"PPL",
    "gn:name":"Ban Vangkh\u00e8n",
    "gn:population":0,
    "gn:timezone":"Asia/Vientiane",
    "iso:country":"LA",
    "name:und_x_variant":[
        "Ban Vang Khene",
        "Ban Vangkh\u00e8n"
    ],
    "wof:name":"Ban Vangkhen",
    "wof:placetype":"locality"
},
  "geometry": {"coordinates":[105.13333,16.73333],"type":"Point"}
}