{
  "type": "Feature",
  "properties": {
    "gn:admin1_code":"13.0",
    "gn:asciiname":"Ban Hoygnok",
    "gn:country_code":"LA",
    "gn:dem":636,
    "gn:feature_class":"P",
    "gn:feature_code":"PPL",
    "gn:name":"Ban Hoygnok",
    "gn:population":0,
    "gn:timezone":"Asia/Vientiane",
    "iso:country":"LA",
    "name:lao_x_preferred":[
        "Ban Hoygnok"
    ],
    "wof:name":"Ban Hoygnok",
    "wof:placetype":"locality"
},
  "geometry": {"coordinates":[100.94123999999999,19.66323],"type":"Point"}
}