{
  "type": "Feature",
  "properties": {
    "gn:admin1_code":"13.0",
    "gn:asciiname":"Ban Mouang",
    "gn:country_code":"LA",
    "gn:dem":418,
    "gn:feature_class":"P",
    "gn:feature_code":"PPL",
    "gn:name":"Ban Mouang",
    "gn:population":0,
    "gn:timezone":"Asia/Vientiane",
    "iso:country":"LA",
    "name:und_x_variant":[
        "Muang Khop",
        "Ban Mouang"
    ],
    "wof:name":"Ban Mouang",
    "wof:placetype":"locality"
},
  "geometry": {"coordinates":[100.51166000000001,19.67596],"type":"Point"}
}