{
  "type": "Feature",
  "properties": {
    "gn:admin1_code":"17.0",
    "gn:asciiname":"Ban Chanve",
    "gn:country_code":"LA",
    "gn:dem":988,
    "gn:feature_class":"P",
    "gn:feature_code":"PPL",
    "gn:name":"Ban Chanv\u00e8",
    "gn:population":0,
    "gn:timezone":"Asia/Vientiane",
    "iso:country":"LA",
    "name:lao_x_preferred":[
        "Ban Chanv\u00e8"
    ],
    "wof:name":"Ban Chanve",
    "wof:placetype":"locality"
},
  "geometry": {"coordinates":[102.52395,19.74129],"type":"Point"}
}