{
  "type": "Feature",
  "properties": {
    "gn:admin1_code":"14.0",
    "gn:asciiname":"Ban Dendin",
    "gn:country_code":"LA",
    "gn:dem":1306,
    "gn:feature_class":"P",
    "gn:feature_code":"PPL",
    "gn:name":"Ban D\u00e8ndin",
    "gn:population":0,
    "gn:timezone":"Asia/Vientiane",
    "iso:country":"LA",
    "name:lao_x_preferred":[
        "Ban D\u00e8ndin"
    ],
    "wof:name":"Ban Dendin",
    "wof:placetype":"locality"
},
  "geometry": {"coordinates":[104.06758000000001,19.44971],"type":"Point"}
}