{
  "type": "Feature",
  "properties": {
    "gn:admin1_code":"15.0",
    "gn:asciiname":"Ban Tong",
    "gn:country_code":"LA",
    "gn:dem":261,
    "gn:feature_class":"P",
    "gn:feature_code":"PPL",
    "gn:name":"Ban Tong",
    "gn:population":0,
    "gn:timezone":"Asia/Vientiane",
    "iso:country":"LA",
    "name:lao_x_preferred":[
        "Ban Tong"
    ],
    "wof:name":"Ban Tong",
    "wof:placetype":"locality"
},
  "geometry": {"coordinates":[106.03149999999999,17.22294],"type":"Point"}
}