{
  "type": "Feature",
  "properties": {
    "gn:admin1_code":"7.0",
    "gn:asciiname":"Ban Namphao",
    "gn:country_code":"LA",
    "gn:dem":941,
    "gn:feature_class":"P",
    "gn:feature_code":"PPL",
    "gn:name":"Ban Namphao",
    "gn:population":0,
    "gn:timezone":"Asia/Vientiane",
    "iso:country":"LA",
    "name:lao_x_preferred":[
        "Ban Namphao"
    ],
    "wof:name":"Ban Namphao",
    "wof:placetype":"locality"
},
  "geometry": {"coordinates":[101.79248,20.50507],"type":"Point"}
}