{
  "type": "Feature",
  "properties": {
    "gn:admin1_code":"20.0",
    "gn:asciiname":"Ban Nathalang",
    "gn:country_code":"LA",
    "gn:dem":192,
    "gn:feature_class":"P",
    "gn:feature_code":"PPL",
    "gn:name":"Ban Nathalang",
    "gn:population":0,
    "gn:timezone":"Asia/Vientiane",
    "iso:country":"LA",
    "name:lao_x_preferred":[
        "Ban Nathalang"
    ],
    "wof:name":"Ban Nathalang",
    "wof:placetype":"locality"
},
  "geometry": {"coordinates":[106.05607000000001,16.53894],"type":"Point"}
}