{
  "type": "Feature",
  "properties": {
    "gn:admin1_code":"26.0",
    "gn:asciiname":"Ban Thongnai-Mai",
    "gn:country_code":"LA",
    "gn:dem":371,
    "gn:feature_class":"P",
    "gn:feature_code":"PPL",
    "gn:name":"Ban Th\u00f4ngnai-Mai",
    "gn:population":0,
    "gn:timezone":"Asia/Vientiane",
    "iso:country":"LA",
    "name:lao_x_preferred":[
        "Ban Th\u00f4ngnai-Mai"
    ],
    "wof:name":"Ban Thongnai-Mai",
    "wof:placetype":"locality"
},
  "geometry": {"coordinates":[106.62152,15.37903],"type":"Point"}
}