{
  "type": "Feature",
  "properties": {
    "gn:admin1_code":"3.0",
    "gn:asciiname":"Ban Then Thong",
    "gn:country_code":"LA",
    "gn:dem":1248,
    "gn:feature_class":"P",
    "gn:feature_code":"PPL",
    "gn:name":"Ban Then Thong",
    "gn:population":0,
    "gn:timezone":"Asia/Vientiane",
    "iso:country":"LA",
    "wof:name":"Ban Then Thong",
    "wof:placetype":"locality"
},
  "geometry": {"coordinates":[103.90000000000001,20.35],"type":"Point"}
}