{
  "type": "Feature",
  "properties": {
    "gn:admin1_code":"22.0",
    "gn:asciiname":"Ban Khanungphet (1)",
    "gn:country_code":"LA",
    "gn:dem":942,
    "gn:feature_class":"P",
    "gn:feature_code":"PPL",
    "gn:name":"Ban Khanungph\u00e8t (1)",
    "gn:population":0,
    "gn:timezone":"Asia/Vientiane",
    "iso:country":"LA",
    "name:und_x_variant":[
        "Ban Khanungph\u00e8t",
        "Ban Khanungph\u00e8t (1)"
    ],
    "wof:name":"Ban Khanungphet (1)",
    "wof:placetype":"locality"
},
  "geometry": {"coordinates":[101.01817,20.25825],"type":"Point"}
}