{
  "type": "Feature",
  "properties": {
    "gn:admin1_code":"20.0",
    "gn:asciiname":"Ban Takhong",
    "gn:country_code":"LA",
    "gn:dem":191,
    "gn:feature_class":"P",
    "gn:feature_code":"PPL",
    "gn:name":"Ban T\u00e1kh\u00f4ng",
    "gn:population":0,
    "gn:timezone":"Asia/Vientiane",
    "iso:country":"LA",
    "name:lao_x_preferred":[
        "Ban T\u00e1kh\u00f4ng"
    ],
    "wof:name":"Ban Takhong",
    "wof:placetype":"locality"
},
  "geometry": {"coordinates":[106.10007,16.50315],"type":"Point"}
}