{
  "type": "Feature",
  "properties": {
    "gn:admin1_code":"14.0",
    "gn:asciiname":"Ban Yiam",
    "gn:country_code":"LA",
    "gn:dem":1479,
    "gn:feature_class":"P",
    "gn:feature_code":"PPL",
    "gn:name":"Ban Yiam",
    "gn:population":0,
    "gn:timezone":"Asia/Vientiane",
    "iso:country":"LA",
    "name:lao_x_preferred":[
        "Ban Yiam"
    ],
    "wof:name":"Ban Yiam",
    "wof:placetype":"locality"
},
  "geometry": {"coordinates":[103.68582000000001,19.17867],"type":"Point"}
}