{
  "type": "Feature",
  "properties": {
    "gn:admin1_code":"19.0",
    "gn:asciiname":"Ban Nongkoxong",
    "gn:country_code":"LA",
    "gn:dem":140,
    "gn:feature_class":"P",
    "gn:feature_code":"PPL",
    "gn:name":"Ban Nongkoxong",
    "gn:population":0,
    "gn:timezone":"Asia/Vientiane",
    "iso:country":"LA",
    "name:lao_x_preferred":[
        "Ban Nongkoxong"
    ],
    "name:und_x_variant":[
        "Ban Nong Ko Song",
        "Ban Nongoxong"
    ],
    "wof:name":"Ban Nongkoxong",
    "wof:placetype":"locality"
},
  "geometry": {"coordinates":[105.80145,15.54705],"type":"Point"}
}