{
  "type": "Feature",
  "properties": {
    "gn:admin1_code":"20.0",
    "gn:asciiname":"Ban Dong-Nabo",
    "gn:country_code":"LA",
    "gn:dem":187,
    "gn:feature_class":"P",
    "gn:feature_code":"PPL",
    "gn:name":"Ban D\u00f4ng-Nabo",
    "gn:population":0,
    "gn:timezone":"Asia/Vientiane",
    "iso:country":"LA",
    "name:lao_x_preferred":[
        "Ban D\u00f4ng-Nabo"
    ],
    "wof:name":"Ban Dong-Nabo",
    "wof:placetype":"locality"
},
  "geometry": {"coordinates":[105.37354000000001,16.89323],"type":"Point"}
}