{
  "type": "Feature",
  "properties": {
    "gn:admin1_code":"1.0",
    "gn:asciiname":"Ban Daknek",
    "gn:country_code":"LA",
    "gn:dem":1133,
    "gn:feature_class":"P",
    "gn:feature_code":"PPL",
    "gn:name":"Ban Dakn\u00e9k",
    "gn:population":0,
    "gn:timezone":"Asia/Vientiane",
    "iso:country":"LA",
    "name:lao_x_preferred":[
        "Ban Dakn\u00e9k"
    ],
    "wof:name":"Ban Daknek",
    "wof:placetype":"locality"
},
  "geometry": {"coordinates":[107.09697,15.25132],"type":"Point"}
}