{
  "type": "Feature",
  "properties": {
    "gn:admin1_code":"20.0",
    "gn:asciiname":"Ban Saloy-Gnai",
    "gn:country_code":"LA",
    "gn:dem":252,
    "gn:feature_class":"P",
    "gn:feature_code":"PPL",
    "gn:name":"Ban Saloy-Gnai",
    "gn:population":0,
    "gn:timezone":"Asia/Vientiane",
    "iso:country":"LA",
    "name:und_x_variant":[
        "Ban Saloy (1)",
        "Ban Sa Loi",
        "Ban Saloy-Gnai"
    ],
    "wof:name":"Ban Saloy-Gnai",
    "wof:placetype":"locality"
},
  "geometry": {"coordinates":[106.04404,16.62127000000001],"type":"Point"}
}