{
  "type": "Feature",
  "properties": {
    "gn:admin1_code":"13.0",
    "gn:asciiname":"Ban Houakhoua",
    "gn:country_code":"LA",
    "gn:dem":510,
    "gn:feature_class":"P",
    "gn:feature_code":"PPL",
    "gn:name":"Ban Houakhoua",
    "gn:population":0,
    "gn:timezone":"Asia/Vientiane",
    "iso:country":"LA",
    "name:lao_x_preferred":[
        "Ban Houakhoua"
    ],
    "wof:name":"Ban Houakhoua",
    "wof:placetype":"locality"
},
  "geometry": {"coordinates":[101.26281,17.84392],"type":"Point"}
}