{
  "type": "Feature",
  "properties": {
    "gn:admin1_code":"17.0",
    "gn:asciiname":"Ban Houayfa",
    "gn:country_code":"LA",
    "gn:dem":876,
    "gn:feature_class":"P",
    "gn:feature_code":"PPL",
    "gn:name":"Ban Houayfa",
    "gn:population":0,
    "gn:timezone":"Asia/Vientiane",
    "iso:country":"LA",
    "name:und_x_variant":[
        "Ban Houei Pha Kha",
        "Ban Houay Pha Kha",
        "Ban Houayfa"
    ],
    "wof:name":"Ban Houayfa",
    "wof:placetype":"locality"
},
  "geometry": {"coordinates":[102.34783,20.59868],"type":"Point"}
}