{
  "type": "Feature",
  "properties": {
    "gn:admin1_code":"20.0",
    "gn:asciiname":"Ban Sopsaloung",
    "gn:country_code":"LA",
    "gn:dem":257,
    "gn:feature_class":"P",
    "gn:feature_code":"PPL",
    "gn:name":"Ban S\u00f4psaloung",
    "gn:population":0,
    "gn:timezone":"Asia/Vientiane",
    "iso:country":"LA",
    "name:lao_x_preferred":[
        "Ban S\u00f4psaloung"
    ],
    "wof:name":"Ban Sopsaloung",
    "wof:placetype":"locality"
},
  "geometry": {"coordinates":[106.16013,16.96268],"type":"Point"}
}