{
  "type": "Feature",
  "properties": {
    "gn:admin1_code":"17.0",
    "gn:asciiname":"Ban Houapha",
    "gn:country_code":"LA",
    "gn:dem":1198,
    "gn:feature_class":"P",
    "gn:feature_code":"PPL",
    "gn:name":"Ban Houapha",
    "gn:population":0,
    "gn:timezone":"Asia/Vientiane",
    "iso:country":"LA",
    "name:lao_x_preferred":[
        "Ban Houapha"
    ],
    "wof:name":"Ban Houapha",
    "wof:placetype":"locality"
},
  "geometry": {"coordinates":[102.36618,19.92379],"type":"Point"}
}