{
  "type": "Feature",
  "properties": {
    "gn:admin1_code":"22.0",
    "gn:asciiname":"Ban Takhen",
    "gn:country_code":"LA",
    "gn:dem":880,
    "gn:feature_class":"P",
    "gn:feature_code":"PPL",
    "gn:name":"Ban Takh\u00e8n",
    "gn:population":0,
    "gn:timezone":"Asia/Vientiane",
    "iso:country":"LA",
    "name:lao_x_preferred":[
        "Ban Takh\u00e8n"
    ],
    "wof:name":"Ban Takhen",
    "wof:placetype":"locality"
},
  "geometry": {"coordinates":[101.07044,20.24097],"type":"Point"}
}