{
  "type": "Feature",
  "properties": {
    "gn:admin1_code":"3.0",
    "gn:asciiname":"Ban Sang Thao",
    "gn:country_code":"LA",
    "gn:dem":934,
    "gn:feature_class":"P",
    "gn:feature_code":"PPL",
    "gn:name":"Ban Sang Thao",
    "gn:population":0,
    "gn:timezone":"Asia/Vientiane",
    "iso:country":"LA",
    "wof:name":"Ban Sang Thao",
    "wof:placetype":"locality"
},
  "geometry": {"coordinates":[104.09999999999999,20.35],"type":"Point"}
}