{
  "type": "Feature",
  "properties": {
    "gn:admin1_code":"13.0",
    "gn:asciiname":"Ban Kouay",
    "gn:country_code":"LA",
    "gn:dem":535,
    "gn:feature_class":"P",
    "gn:feature_code":"PPL",
    "gn:name":"Ban Kouay",
    "gn:population":0,
    "gn:timezone":"Asia/Vientiane",
    "iso:country":"LA",
    "name:lao_x_preferred":[
        "Ban Kouay"
    ],
    "wof:name":"Ban Kouay",
    "wof:placetype":"locality"
},
  "geometry": {"coordinates":[100.52575,19.56652],"type":"Point"}
}