{
  "type": "Feature",
  "properties": {
    "gn:admin1_code":"16.0",
    "gn:asciiname":"Ban Taphai",
    "gn:country_code":"LA",
    "gn:dem":883,
    "gn:feature_class":"P",
    "gn:feature_code":"PPL",
    "gn:name":"Ban Taphai",
    "gn:population":0,
    "gn:timezone":"Asia/Vientiane",
    "iso:country":"LA",
    "name:lao_x_preferred":[
        "Ban Taphai"
    ],
    "wof:name":"Ban Taphai",
    "wof:placetype":"locality"
},
  "geometry": {"coordinates":[100.65177,21.02374],"type":"Point"}
}