{
  "type": "Feature",
  "properties": {
    "gn:admin1_code":"17.0",
    "gn:asciiname":"Ban Nakok",
    "gn:country_code":"LA",
    "gn:dem":386,
    "gn:feature_class":"P",
    "gn:feature_code":"PPL",
    "gn:name":"Ban Nakok",
    "gn:population":0,
    "gn:timezone":"Asia/Vientiane",
    "iso:country":"LA",
    "name:lao_x_preferred":[
        "Ban Nakok"
    ],
    "wof:name":"Ban Nakok",
    "wof:placetype":"locality"
},
  "geometry": {"coordinates":[102.39885,20.56018],"type":"Point"}
}