{
  "type": "Feature",
  "properties": {
    "gn:admin1_code":"20.0",
    "gn:asciiname":"Ban Nachalit",
    "gn:country_code":"LA",
    "gn:dem":177,
    "gn:feature_class":"P",
    "gn:feature_code":"PPL",
    "gn:name":"Ban Nachalit",
    "gn:population":0,
    "gn:timezone":"Asia/Vientiane",
    "iso:country":"LA",
    "name:und_x_variant":[
        "Ban Chalit",
        "Ban Nachalit"
    ],
    "wof:name":"Ban Nachalit",
    "wof:placetype":"locality"
},
  "geometry": {"coordinates":[104.90703999999999,16.67577],"type":"Point"}
}