{
  "type": "Feature",
  "properties": {
    "gn:admin1_code":"23.0",
    "gn:asciiname":"Ban Sopxay",
    "gn:country_code":"LA",
    "gn:dem":269,
    "gn:feature_class":"P",
    "gn:feature_code":"PPL",
    "gn:name":"Ban S\u00f4pxay",
    "gn:population":0,
    "gn:timezone":"Asia/Vientiane",
    "iso:country":"LA",
    "name:und_x_variant":[
        "Ban Sop Say",
        "Ban S\u00f4pxay"
    ],
    "wof:name":"Ban Sopxay",
    "wof:placetype":"locality"
},
  "geometry": {"coordinates":[104.34523,18.46154],"type":"Point"}
}