{
  "type": "Feature",
  "properties": {
    "gn:admin1_code":"7.0",
    "gn:asciiname":"Ban Sakhan",
    "gn:country_code":"LA",
    "gn:dem":760,
    "gn:feature_class":"P",
    "gn:feature_code":"PPL",
    "gn:name":"Ban Sakhan",
    "gn:population":0,
    "gn:timezone":"Asia/Vientiane",
    "iso:country":"LA",
    "name:lao_x_preferred":[
        "Ban Sakhan"
    ],
    "wof:name":"Ban Sakhan",
    "wof:placetype":"locality"
},
  "geometry": {"coordinates":[101.66352999999999,20.67915],"type":"Point"}
}