{
  "type": "Feature",
  "properties": {
    "gn:admin1_code":"15.0",
    "gn:admin2_code":"1201.0",
    "gn:asciiname":"Ban Lak Si",
    "gn:country_code":"LA",
    "gn:dem":166,
    "gn:feature_class":"P",
    "gn:feature_code":"PPL",
    "gn:name":"Ban Lak Si",
    "gn:population":0,
    "gn:timezone":"Asia/Vientiane",
    "iso:country":"LA",
    "name:lao_x_preferred":[
        "Ban Lak Si"
    ],
    "wof:name":"Ban Lak Si",
    "wof:placetype":"locality"
},
  "geometry": {"coordinates":[104.82877999999999,17.40891],"type":"Point"}
}