{
  "type": "Feature",
  "properties": {
    "gn:admin1_code":"15.0",
    "gn:asciiname":"Nonggnama",
    "gn:country_code":"LA",
    "gn:dem":521,
    "gn:feature_class":"P",
    "gn:feature_code":"PPL",
    "gn:name":"Nonggnama",
    "gn:population":0,
    "gn:timezone":"Asia/Vientiane",
    "iso:country":"LA",
    "name:lao_x_preferred":[
        "Nonggnama"
    ],
    "wof:name":"Nonggnama",
    "wof:placetype":"locality"
},
  "geometry": {"coordinates":[106.12486,17.24845],"type":"Point"}
}