{
  "type": "Feature",
  "properties": {
    "gn:admin1_code":"17.0",
    "gn:asciiname":"Ban Kioukhan",
    "gn:country_code":"LA",
    "gn:dem":732,
    "gn:feature_class":"P",
    "gn:feature_code":"PPL",
    "gn:name":"Ban Kioukhan",
    "gn:population":0,
    "gn:timezone":"Asia/Vientiane",
    "iso:country":"LA",
    "name:und_x_variant":[
        "Kiou Kan",
        "Ban Kioukhan"
    ],
    "wof:name":"Ban Kioukhan",
    "wof:placetype":"locality"
},
  "geometry": {"coordinates":[102.70936,20.75019],"type":"Point"}
}