{
  "type": "Feature",
  "properties": {
    "gn:admin1_code":"23.0",
    "gn:asciiname":"Ban Kongphat",
    "gn:country_code":"LA",
    "gn:dem":532,
    "gn:feature_class":"P",
    "gn:feature_code":"PPL",
    "gn:name":"Ban K\u00f4ngphat",
    "gn:population":0,
    "gn:timezone":"Asia/Vientiane",
    "iso:country":"LA",
    "name:lao_x_preferred":[
        "Ban K\u00f4ngphat"
    ],
    "wof:name":"Ban Kongphat",
    "wof:placetype":"locality"
},
  "geometry": {"coordinates":[104.96906,18.27374],"type":"Point"}
}