{
  "type": "Feature",
  "properties": {
    "gn:admin1_code":"24.0",
    "gn:asciiname":"Ban Nikhom-N Si",
    "gn:country_code":"LA",
    "gn:dem":179,
    "gn:feature_class":"P",
    "gn:feature_code":"PPL",
    "gn:name":"Ban Nikh\u00f4m-N Si",
    "gn:population":0,
    "gn:timezone":"Asia/Vientiane",
    "iso:country":"LA",
    "name:lao_x_preferred":[
        "Ban Nikh\u00f4m-N Si"
    ],
    "wof:name":"Ban Nikhom-N Si",
    "wof:placetype":"locality"
},
  "geometry": {"coordinates":[102.48922,18.26529],"type":"Point"}
}