{
  "type": "Feature",
  "properties": {
    "gn:admin1_code":"13.0",
    "gn:asciiname":"Ban Nathom",
    "gn:country_code":"LA",
    "gn:dem":532,
    "gn:feature_class":"P",
    "gn:feature_code":"PPL",
    "gn:name":"Ban Nath\u00f4m",
    "gn:population":0,
    "gn:timezone":"Asia/Vientiane",
    "iso:country":"LA",
    "name:lao_x_preferred":[
        "Ban Nath\u00f4m"
    ],
    "wof:name":"Ban Nathom",
    "wof:placetype":"locality"
},
  "geometry": {"coordinates":[100.57429999999999,19.55627],"type":"Point"}
}