{
  "type": "Feature",
  "properties": {
    "gn:admin1_code":"7.0",
    "gn:asciiname":"Ban Kontang",
    "gn:country_code":"LA",
    "gn:dem":649,
    "gn:feature_class":"P",
    "gn:feature_code":"PPL",
    "gn:name":"Ban Kontang",
    "gn:population":0,
    "gn:timezone":"Asia/Vientiane",
    "iso:country":"LA",
    "name:lao_x_preferred":[
        "Ban Kontang"
    ],
    "wof:name":"Ban Kontang",
    "wof:placetype":"locality"
},
  "geometry": {"coordinates":[101.55861,19.98171],"type":"Point"}
}