{
  "type": "Feature",
  "properties": {
    "gn:admin1_code":"19.0",
    "gn:asciiname":"Ban Lalaideo",
    "gn:country_code":"LA",
    "gn:dem":617,
    "gn:feature_class":"P",
    "gn:feature_code":"PPL",
    "gn:name":"Ban Lalaid\u00e8o",
    "gn:population":0,
    "gn:timezone":"Asia/Vientiane",
    "iso:country":"LA",
    "name:lao_x_preferred":[
        "Ban Lalaid\u00e8o"
    ],
    "name:und_x_variant":[
        "La Lay Deo",
        "Lalai D\u00e8o"
    ],
    "wof:name":"Ban Lalaideo",
    "wof:placetype":"locality"
},
  "geometry": {"coordinates":[106.94644,16.3127],"type":"Point"}
}