{
  "type": "Feature",
  "properties": {
    "gn:admin1_code":"17.0",
    "gn:asciiname":"Ban Phia",
    "gn:country_code":"LA",
    "gn:dem":1052,
    "gn:feature_class":"P",
    "gn:feature_code":"PPL",
    "gn:name":"Ban Phia",
    "gn:population":0,
    "gn:timezone":"Asia/Vientiane",
    "iso:country":"LA",
    "name:lao_x_preferred":[
        "Ban Phia"
    ],
    "wof:name":"Ban Phia",
    "wof:placetype":"locality"
},
  "geometry": {"coordinates":[102.89097,20.32861],"type":"Point"}
}