{
  "type": "Feature",
  "properties": {
    "gn:admin1_code":"13.0",
    "gn:asciiname":"Ban Tintok",
    "gn:country_code":"LA",
    "gn:dem":980,
    "gn:feature_class":"P",
    "gn:feature_code":"PPL",
    "gn:name":"Ban Tintok",
    "gn:population":0,
    "gn:timezone":"Asia/Vientiane",
    "iso:country":"LA",
    "name:lao_x_preferred":[
        "Ban Tintok"
    ],
    "wof:name":"Ban Tintok",
    "wof:placetype":"locality"
},
  "geometry": {"coordinates":[101.0427,19.79192],"type":"Point"}
}