{
  "type": "Feature",
  "properties": {
    "gn:admin1_code":"23.0",
    "gn:asciiname":"Ban Namsading",
    "gn:country_code":"LA",
    "gn:dem":937,
    "gn:feature_class":"P",
    "gn:feature_code":"PPL",
    "gn:name":"Ban Namsading",
    "gn:population":0,
    "gn:timezone":"Asia/Vientiane",
    "iso:country":"LA",
    "name:lao_x_preferred":[
        "Ban Namsading"
    ],
    "wof:name":"Ban Namsading",
    "wof:placetype":"locality"
},
  "geometry": {"coordinates":[104.61909,18.42897],"type":"Point"}
}