{
  "type": "Feature",
  "properties": {
    "gn:admin1_code":"22.0",
    "gn:asciiname":"Ban Mokkha-Theung",
    "gn:country_code":"LA",
    "gn:dem":758,
    "gn:feature_class":"P",
    "gn:feature_code":"PPL",
    "gn:name":"Ban M\u00f4kkha-Theung",
    "gn:population":0,
    "gn:timezone":"Asia/Vientiane",
    "iso:country":"LA",
    "name:lao_x_preferred":[
        "Ban M\u00f4kkha-Thoung"
    ],
    "name:lao_x_variant":[
        "Ban M\u00f4kkha-Theung"
    ],
    "wof:name":"Ban Mokkha-Theung",
    "wof:placetype":"locality"
},
  "geometry": {"coordinates":[100.92534999999999,20.07536],"type":"Point"}
}