{
  "type": "Feature",
  "properties": {
    "gn:admin1_code":"7.0",
    "gn:asciiname":"Ban Khon",
    "gn:country_code":"LA",
    "gn:dem":887,
    "gn:feature_class":"P",
    "gn:feature_code":"PPL",
    "gn:name":"Ban Khon",
    "gn:population":0,
    "gn:timezone":"Asia/Vientiane",
    "iso:country":"LA",
    "name:lao_x_preferred":[
        "Ban Khon"
    ],
    "wof:name":"Ban Khon",
    "wof:placetype":"locality"
},
  "geometry": {"coordinates":[101.50859,20.33763],"type":"Point"}
}