{
  "type": "Feature",
  "properties": {
    "gn:admin1_code":"20.0",
    "gn:asciiname":"Ban Kado",
    "gn:country_code":"LA",
    "gn:dem":281,
    "gn:feature_class":"P",
    "gn:feature_code":"PPL",
    "gn:name":"Ban Kad\u00f4",
    "gn:population":0,
    "gn:timezone":"Asia/Vientiane",
    "iso:country":"LA",
    "name:lao_x_preferred":[
        "Ban Kad\u00f4"
    ],
    "wof:name":"Ban Kado",
    "wof:placetype":"locality"
},
  "geometry": {"coordinates":[106.35055,16.89349],"type":"Point"}
}