{
  "type": "Feature",
  "properties": {
    "gn:admin1_code":"3.0",
    "gn:asciiname":"Ban Pounghai",
    "gn:country_code":"LA",
    "gn:dem":671,
    "gn:feature_class":"P",
    "gn:feature_code":"PPL",
    "gn:name":"Ban Pounghai",
    "gn:population":0,
    "gn:timezone":"Asia/Vientiane",
    "iso:country":"LA",
    "name:lao_x_preferred":[
        "Ban Pounghai"
    ],
    "wof:name":"Ban Pounghai",
    "wof:placetype":"locality"
},
  "geometry": {"coordinates":[103.35487000000001,20.04116],"type":"Point"}
}