{
  "type": "Feature",
  "properties": {
    "gn:admin1_code":"14.0",
    "gn:asciiname":"Ban Phan",
    "gn:country_code":"LA",
    "gn:dem":1110,
    "gn:feature_class":"P",
    "gn:feature_code":"PPL",
    "gn:name":"Ban Phan",
    "gn:population":0,
    "gn:timezone":"Asia/Vientiane",
    "iso:country":"LA",
    "name:und_x_variant":[
        "Ban Van"
    ],
    "wof:name":"Ban Phan",
    "wof:placetype":"locality"
},
  "geometry": {"coordinates":[103.04201,19.39967],"type":"Point"}
}