{
  "type": "Feature",
  "properties": {
    "gn:admin1_code":"19.0",
    "gn:asciiname":"Ban Nongveng",
    "gn:country_code":"LA",
    "gn:dem":187,
    "gn:feature_class":"P",
    "gn:feature_code":"PPL",
    "gn:name":"Ban Nongv\u00e8ng",
    "gn:population":0,
    "gn:timezone":"Asia/Vientiane",
    "iso:country":"LA",
    "name:lao_x_preferred":[
        "Ban Nongv\u00e8ng"
    ],
    "name:und_x_variant":[
        "Ban Nong Vang",
        "Ban Nong Veng (1)",
        "Ban Nong Veng"
    ],
    "wof:name":"Ban Nongveng",
    "wof:placetype":"locality"
},
  "geometry": {"coordinates":[105.65356,15.85834],"type":"Point"}
}