{
  "type": "Feature",
  "properties": {
    "gn:admin1_code":"7.0",
    "gn:asciiname":"Ban Phoukeu",
    "gn:country_code":"LA",
    "gn:dem":1138,
    "gn:feature_class":"P",
    "gn:feature_code":"PPL",
    "gn:name":"Ban Phoukeu",
    "gn:population":0,
    "gn:timezone":"Asia/Vientiane",
    "iso:country":"LA",
    "name:lao_x_preferred":[
        "Ban Phoukeu"
    ],
    "wof:name":"Ban Phoukeu",
    "wof:placetype":"locality"
},
  "geometry": {"coordinates":[101.98348,20.21948],"type":"Point"}
}