{
  "type": "Feature",
  "properties": {
    "gn:admin1_code":"14.0",
    "gn:asciiname":"Ban Manxom",
    "gn:country_code":"LA",
    "gn:dem":1182,
    "gn:feature_class":"P",
    "gn:feature_code":"PPL",
    "gn:name":"Ban Manx\u00f4m",
    "gn:population":0,
    "gn:timezone":"Asia/Vientiane",
    "iso:country":"LA",
    "name:lao_x_preferred":[
        "Ban Manx\u00f4m"
    ],
    "wof:name":"Ban Manxom",
    "wof:placetype":"locality"
},
  "geometry": {"coordinates":[103.28270999999999,19.56217],"type":"Point"}
}