{
  "type": "Feature",
  "properties": {
    "gn:admin1_code":"27.0",
    "gn:asciiname":"Ban Non",
    "gn:country_code":"LA",
    "gn:dem":173,
    "gn:feature_class":"P",
    "gn:feature_code":"PPL",
    "gn:name":"Ban N\u00f4n",
    "gn:population":0,
    "gn:timezone":"Asia/Vientiane",
    "iso:country":"LA",
    "wof:name":"Ban Non",
    "wof:placetype":"locality"
},
  "geometry": {"coordinates":[102.46722,18.30944],"type":"Point"}
}