{
  "type": "Feature",
  "properties": {
    "gn:admin1_code":"19.0",
    "gn:asciiname":"Ban Nabak",
    "gn:country_code":"LA",
    "gn:dem":186,
    "gn:feature_class":"P",
    "gn:feature_code":"PPL",
    "gn:name":"Ban Nabak",
    "gn:population":0,
    "gn:timezone":"Asia/Vientiane",
    "iso:country":"LA",
    "name:lao_x_preferred":[
        "Ban Nabak"
    ],
    "wof:name":"Ban Nabak",
    "wof:placetype":"locality"
},
  "geometry": {"coordinates":[106.41670000000001,15.73929],"type":"Point"}
}