{
  "type": "Feature",
  "properties": {
    "gn:admin1_code":"17.0",
    "gn:asciiname":"Ban Nongpa",
    "gn:country_code":"LA",
    "gn:dem":1059,
    "gn:feature_class":"P",
    "gn:feature_code":"PPL",
    "gn:name":"Ban Nongpa",
    "gn:population":0,
    "gn:timezone":"Asia/Vientiane",
    "iso:country":"LA",
    "name:lao_x_preferred":[
        "Ban Nongpa"
    ],
    "wof:name":"Ban Nongpa",
    "wof:placetype":"locality"
},
  "geometry": {"coordinates":[102.09635,19.59457],"type":"Point"}
}