{
  "type": "Feature",
  "properties": {
    "gn:admin1_code":"26.0",
    "gn:asciiname":"Ban Gnokthong",
    "gn:country_code":"LA",
    "gn:dem":445,
    "gn:feature_class":"P",
    "gn:feature_code":"PPL",
    "gn:name":"Ban Gnokth\u00f4ng",
    "gn:population":0,
    "gn:timezone":"Asia/Vientiane",
    "iso:country":"LA",
    "name:lao_x_preferred":[
        "Ban Gnokth\u00f4ng"
    ],
    "name:und_x_variant":[
        "Ban Nhok Thung"
    ],
    "wof:name":"Ban Gnokthong",
    "wof:placetype":"locality"
},
  "geometry": {"coordinates":[106.57228000000001,15.47368],"type":"Point"}
}