{
  "type": "Feature",
  "properties": {
    "gn:admin1_code":"19.0",
    "gn:asciiname":"Ban Kaman",
    "gn:country_code":"LA",
    "gn:dem":558,
    "gn:feature_class":"P",
    "gn:feature_code":"PPL",
    "gn:name":"Ban Kaman",
    "gn:population":0,
    "gn:timezone":"Asia/Vientiane",
    "iso:country":"LA",
    "name:lao_x_preferred":[
        "Ban Kaman"
    ],
    "wof:name":"Ban Kaman",
    "wof:placetype":"locality"
},
  "geometry": {"coordinates":[106.84238999999999,16.16419],"type":"Point"}
}