{
  "type": "Feature",
  "properties": {
    "gn:admin1_code":"16.0",
    "gn:asciiname":"Ban Donpoy",
    "gn:country_code":"LA",
    "gn:dem":487,
    "gn:feature_class":"P",
    "gn:feature_code":"PPL",
    "gn:name":"Ban Donpoy",
    "gn:population":0,
    "gn:timezone":"Asia/Vientiane",
    "iso:country":"LA",
    "name:lao_x_preferred":[
        "Ban Donpoy"
    ],
    "wof:name":"Ban Donpoy",
    "wof:placetype":"locality"
},
  "geometry": {"coordinates":[100.79648,20.96164],"type":"Point"}
}