{
  "type": "Feature",
  "properties": {
    "gn:admin1_code":"7.0",
    "gn:asciiname":"Ban Bong-Nua",
    "gn:country_code":"LA",
    "gn:dem":772,
    "gn:feature_class":"P",
    "gn:feature_code":"PPL",
    "gn:name":"Ban B\u00f4ng-Nua",
    "gn:population":0,
    "gn:timezone":"Asia/Vientiane",
    "iso:country":"LA",
    "name:lao_x_preferred":[
        "Ban B\u00f4ng-Nua"
    ],
    "wof:name":"Ban Bong-Nua",
    "wof:placetype":"locality"
},
  "geometry": {"coordinates":[101.64303,20.46062],"type":"Point"}
}