{
  "type": "Feature",
  "properties": {
    "gn:admin1_code":"15.0",
    "gn:asciiname":"Ban Phonsangphai",
    "gn:country_code":"LA",
    "gn:dem":177,
    "gn:feature_class":"P",
    "gn:feature_code":"PPL",
    "gn:name":"Ban Ph\u00f4nsangphai",
    "gn:population":0,
    "gn:timezone":"Asia/Vientiane",
    "iso:country":"LA",
    "name:und_x_variant":[
        "Ban Phon Sang Phay",
        "Ban Phon Seng Phay",
        "Ban Phon Phay",
        "Ban Ph\u00f4nsangphai"
    ],
    "wof:name":"Ban Phonsangphai",
    "wof:placetype":"locality"
},
  "geometry": {"coordinates":[105.66119,17.42946],"type":"Point"}
}