{
  "type": "Feature",
  "properties": {
    "gn:admin1_code":"3.0",
    "gn:asciiname":"Ban Naka",
    "gn:country_code":"LA",
    "gn:dem":1066,
    "gn:feature_class":"P",
    "gn:feature_code":"PPL",
    "gn:name":"Ban Naka",
    "gn:population":0,
    "gn:timezone":"Asia/Vientiane",
    "iso:country":"LA",
    "name:lao_x_preferred":[
        "Ban Naka"
    ],
    "name:und_x_variant":[
        "Ban Na Ke",
        "Ban La Ka"
    ],
    "wof:name":"Ban Naka",
    "wof:placetype":"locality"
},
  "geometry": {"coordinates":[104.351,20.22481],"type":"Point"}
}