{
  "type": "Feature",
  "properties": {
    "gn:admin1_code":"20.0",
    "gn:asciiname":"Ban Theum-Gnai",
    "gn:country_code":"LA",
    "gn:dem":173,
    "gn:feature_class":"P",
    "gn:feature_code":"PPL",
    "gn:name":"Ban Theum-Gnai",
    "gn:population":0,
    "gn:timezone":"Asia/Vientiane",
    "iso:country":"LA",
    "name:lao_x_preferred":[
        "Ban Theum-Gnai"
    ],
    "name:und_x_variant":[
        "Ban Teum"
    ],
    "wof:name":"Ban Theum-Gnai",
    "wof:placetype":"locality"
},
  "geometry": {"coordinates":[105.60766,16.70159],"type":"Point"}
}