{
  "type": "Feature",
  "properties": {
    "gn:admin1_code":"20.0",
    "gn:asciiname":"Ban Bak Gnai",
    "gn:country_code":"LA",
    "gn:dem":173,
    "gn:feature_class":"P",
    "gn:feature_code":"PPL",
    "gn:name":"Ban Bak Gnai",
    "gn:population":0,
    "gn:timezone":"Asia/Vientiane",
    "iso:country":"LA",
    "name:lao_x_preferred":[
        "Ban Bak"
    ],
    "wof:name":"Ban Bak Gnai",
    "wof:placetype":"locality"
},
  "geometry": {"coordinates":[105.14362,16.44052000000001],"type":"Point"}
}