{
  "type": "Feature",
  "properties": {
    "gn:admin1_code":"20.0",
    "gn:asciiname":"Ban Tomouang",
    "gn:country_code":"LA",
    "gn:dem":145,
    "gn:feature_class":"P",
    "gn:feature_code":"PPL",
    "gn:name":"Ban Tomouang",
    "gn:population":0,
    "gn:timezone":"Asia/Vientiane",
    "iso:country":"LA",
    "name:lao_x_preferred":[
        "Ban Tomouang"
    ],
    "wof:name":"Ban Tomouang",
    "wof:placetype":"locality"
},
  "geometry": {"coordinates":[104.77164,16.90443],"type":"Point"}
}