{
  "type": "Feature",
  "properties": {
    "gn:admin1_code":"22.0",
    "gn:asciiname":"Ban Houay-Et",
    "gn:country_code":"LA",
    "gn:dem":594,
    "gn:feature_class":"P",
    "gn:feature_code":"PPL",
    "gn:name":"Ban Houay-\u00c8t",
    "gn:population":0,
    "gn:timezone":"Asia/Vientiane",
    "iso:country":"LA",
    "name:lao_x_preferred":[
        "Ban Houay-\u00c8t"
    ],
    "wof:name":"Ban Houay-Et",
    "wof:placetype":"locality"
},
  "geometry": {"coordinates":[100.73845,19.8719],"type":"Point"}
}