{
  "type": "Feature",
  "properties": {
    "gn:admin1_code":"15.0",
    "gn:asciiname":"Ban Nasaykham",
    "gn:country_code":"LA",
    "gn:dem":163,
    "gn:feature_class":"P",
    "gn:feature_code":"PPL",
    "gn:name":"Ban Nasaykham",
    "gn:population":0,
    "gn:timezone":"Asia/Vientiane",
    "iso:country":"LA",
    "name:lao_x_preferred":[
        "Ban Nasaykham"
    ],
    "wof:name":"Ban Nasaykham",
    "wof:placetype":"locality"
},
  "geometry": {"coordinates":[104.57925,18.07704],"type":"Point"}
}