{
  "type": "Feature",
  "properties": {
    "gn:admin1_code":"20.0",
    "gn:asciiname":"Ban Houalouang",
    "gn:country_code":"LA",
    "gn:dem":167,
    "gn:feature_class":"P",
    "gn:feature_code":"PPL",
    "gn:name":"Ban Houalouang",
    "gn:population":0,
    "gn:timezone":"Asia/Vientiane",
    "iso:country":"LA",
    "name:lao_x_preferred":[
        "Ban Houalouang"
    ],
    "wof:name":"Ban Houalouang",
    "wof:placetype":"locality"
},
  "geometry": {"coordinates":[105.78379,16.27519],"type":"Point"}
}