{
  "type": "Feature",
  "properties": {
    "gn:admin1_code":"3.0",
    "gn:asciiname":"Ban Nakhang",
    "gn:country_code":"LA",
    "gn:dem":776,
    "gn:feature_class":"P",
    "gn:feature_code":"PPL",
    "gn:name":"Ban Nakhang",
    "gn:population":0,
    "gn:timezone":"Asia/Vientiane",
    "iso:country":"LA",
    "name:und_x_variant":[
        "Na Can"
    ],
    "wof:name":"Ban Nakhang",
    "wof:placetype":"locality"
},
  "geometry": {"coordinates":[104.22677,20.89487],"type":"Point"}
}