{
  "type": "Feature",
  "properties": {
    "gn:admin1_code":"23.0",
    "gn:asciiname":"Ban Namchale",
    "gn:country_code":"LA",
    "gn:dem":1035,
    "gn:feature_class":"P",
    "gn:feature_code":"PPL",
    "gn:name":"Ban Namchal\u00e8",
    "gn:population":0,
    "gn:timezone":"Asia/Vientiane",
    "iso:country":"LA",
    "name:lao_x_preferred":[
        "Ban Namchal\u00e8"
    ],
    "wof:name":"Ban Namchale",
    "wof:placetype":"locality"
},
  "geometry": {"coordinates":[104.64608,18.54684],"type":"Point"}
}