{
  "type": "Feature",
  "properties": {
    "gn:admin1_code":"17.0",
    "gn:asciiname":"Ban Houay-En-Noy",
    "gn:country_code":"LA",
    "gn:dem":399,
    "gn:feature_class":"P",
    "gn:feature_code":"PPL",
    "gn:name":"Ban Houay-En-Noy",
    "gn:population":0,
    "gn:timezone":"Asia/Vientiane",
    "iso:country":"LA",
    "name:lao_x_preferred":[
        "Ban Houay-En-Noy"
    ],
    "wof:name":"Ban Houay-En-Noy",
    "wof:placetype":"locality"
},
  "geometry": {"coordinates":[102.61873,20.47462],"type":"Point"}
}