{
  "type": "Feature",
  "properties": {
    "gn:admin1_code":"20.0",
    "gn:asciiname":"Ban Thahouaxang",
    "gn:country_code":"LA",
    "gn:dem":148,
    "gn:feature_class":"P",
    "gn:feature_code":"PPL",
    "gn:name":"Ban Thahouaxang",
    "gn:population":0,
    "gn:timezone":"Asia/Vientiane",
    "iso:country":"LA",
    "name:und_x_variant":[
        "Ban Houei Houa Sang",
        "Ban Houa Sang",
        "Ban Houayhousaxang",
        "Ban Houayhouaxang",
        "Ban Thahouaxang"
    ],
    "wof:name":"Ban Thahouaxang",
    "wof:placetype":"locality"
},
  "geometry": {"coordinates":[104.77169000000001,16.73589],"type":"Point"}
}