{
  "type": "Feature",
  "properties": {
    "gn:country":"LA",
    "gn:fcode":"PPLA",
    "gn:pop":21967,
    "iso:country":"LA",
    "name:ara_x_preferred":[
        "\u0628\u0627\u0643\u0633\u0627\u0646"
    ],
    "name:ben_x_preferred":[
        "\u09aa\u09be\u0995\u09cd\u09b8\u09be\u09a8"
    ],
    "name:chi_x_preferred":[
        "\u5317\u6c55"
    ],
    "name:dan_x_preferred":[
        "Pakxan"
    ],
    "name:dut_x_preferred":[
        "Paksan"
    ],
    "name:eng_x_preferred":[
        "Pakxan"
    ],
    "name:epo_x_preferred":[
        "Paksan"
    ],
    "name:fin_x_preferred":[
        "Pakxan"
    ],
    "name:fre_x_preferred":[
        "Paksane"
    ],
    "name:geo_x_preferred":[
        "\u10de\u10d0\u10e5\u10e1\u10d0\u10dc\u10d8"
    ],
    "name:ger_x_preferred":[
        "Pakxan"
    ],
    "name:gre_x_preferred":[
        "\u03a0\u03b1\u03ba\u03c3\u03ac\u03bd"
    ],
    "name:guj_x_preferred":[
        "\u0aaa\u0a95\u0acd\u0ab8\u0abe\u0aa8"
    ],
    "name:hin_x_preferred":[
        "\u092a\u0915\u094d\u0938\u093e\u0928"
    ],
    "name:ind_x_preferred":[
        "Pakxan"
    ],
    "name:ita_x_preferred":[
        "Pakxan"
    ],
    "name:jpn_x_preferred":[
        "\u30d1\u30fc\u30af\u30b5\u30f3\u90e1"
    ],
    "name:kan_x_preferred":[
        "\u0caa\u0cbe\u0c95\u0ccd\u0c95\u0ccd\u0cb8\u0cbe\u0ca8\u0ccd"
    ],
    "name:kor_x_preferred":[
        "\ud30d\uc0b0"
    ],
    "name:lav_x_preferred":[
        "Paksana"
    ],
    "name:lit_x_preferred":[
        "Pakchanas"
    ],
    "name:mar_x_preferred":[
        "\u092a\u0915\u094d\u0938\u093e\u0928"
    ],
    "name:may_x_preferred":[
        "Pakxan"
    ],
    "name:nob_x_preferred":[
        "Pakxan"
    ],
    "name:per_x_preferred":[
        "\u067e\u0627\u06a9\u0634\u0646"
    ],
    "name:pol_x_preferred":[
        "Pakxan"
    ],
    "name:por_x_preferred":[
        "Muang Pakxan"
    ],
    "name:rus_x_preferred":[
        "\u041f\u0430\u043a\u0441\u0430\u043d"
    ],
    "name:sin_x_preferred":[
        "\u0db4\u0dd0\u0d9a\u0dca\u0dc3\u0db1\u0dca"
    ],
    "name:spa_x_preferred":[
        "Pakxan"
    ],
    "name:swe_x_preferred":[
        "Pakxan"
    ],
    "name:tam_x_preferred":[
        "\u0baa\u0bbe\u0b95\u0bcd\u0b9a\u0bbe\u0ba9\u0bcd"
    ],
    "name:tel_x_preferred":[
        "\u0c2a\u0c3e\u0c15\u0c4d\u0c38\u0c28\u0c4d"
    ],
    "name:tha_x_preferred":[
        "\u0e1b\u0e32\u0e01\u0e0b\u0e31\u0e19"
    ],
    "name:tur_x_preferred":[
        "Pakxan"
    ],
    "name:ukr_x_preferred":[
        "\u041f\u0430\u043a\u0441\u0430\u043d"
    ],
    "name:unk_x_variant":[
        "Paksane"
    ],
    "name:urd_x_preferred":[
        "\u067e\u0627\u06a9\u0633\u0627\u0646"
    ],
    "name:vie_x_preferred":[
        "Pakxane"
    ],
    "name:war_x_preferred":[
        "Paksan"
    ],
    "qs:name":"Muang Pakxan",
    "qs:photos_9r":0,
    "qs:photos_sr":0,
    "qs:pop_sr":"7",
    "wof:name":"Muang Pakxan",
    "wof:placetype":"locality",
    "wof:population":21967
},
  "geometry": {"coordinates":[103.65857,18.38261],"type":"Point"}
}