{
  "type": "Feature",
  "properties": {
    "gn:admin1_code":"19.0",
    "gn:asciiname":"Ban Touk-Louk",
    "gn:country_code":"LA",
    "gn:dem":570,
    "gn:feature_class":"P",
    "gn:feature_code":"PPL",
    "gn:name":"Ban Touk-Louk",
    "gn:population":0,
    "gn:timezone":"Asia/Vientiane",
    "iso:country":"LA",
    "name:und_x_variant":[
        "Ban Tok Lok",
        "Ban Touk-Louk"
    ],
    "wof:name":"Ban Touk-Louk",
    "wof:placetype":"locality"
},
  "geometry": {"coordinates":[106.10254,15.3904],"type":"Point"}
}