{
  "type": "Feature",
  "properties": {
    "gn:admin1_code":"2.0",
    "gn:asciiname":"Ban Nao",
    "gn:country_code":"LA",
    "gn:dem":113,
    "gn:feature_class":"P",
    "gn:feature_code":"PPL",
    "gn:name":"Ban Na\u00f4",
    "gn:population":0,
    "gn:timezone":"Asia/Vientiane",
    "iso:country":"LA",
    "name:lao_x_preferred":[
        "Ban Na\u00f4"
    ],
    "wof:name":"Ban Nao",
    "wof:placetype":"locality"
},
  "geometry": {"coordinates":[105.81131999999999,15.26432],"type":"Point"}
}