{
  "type": "Feature",
  "properties": {
    "gn:admin1_code":"26.0",
    "gn:asciiname":"Ban Dakpok-Nua",
    "gn:country_code":"LA",
    "gn:dem":1160,
    "gn:feature_class":"P",
    "gn:feature_code":"PPL",
    "gn:name":"Ban Dakpok-Nua",
    "gn:population":0,
    "gn:timezone":"Asia/Vientiane",
    "iso:country":"LA",
    "name:lao_x_preferred":[
        "Ban Dakpok-Nua"
    ],
    "wof:name":"Ban Dakpok-Nua",
    "wof:placetype":"locality"
},
  "geometry": {"coordinates":[107.06207000000001,15.27096],"type":"Point"}
}