{
  "type": "Feature",
  "properties": {
    "gn:admin1_code":"27.0",
    "gn:asciiname":"Ban Houay-Youak",
    "gn:country_code":"LA",
    "gn:dem":920,
    "gn:feature_class":"P",
    "gn:feature_code":"PPL",
    "gn:name":"Ban Houay-Youak",
    "gn:population":0,
    "gn:timezone":"Asia/Vientiane",
    "iso:country":"LA",
    "name:lao_x_preferred":[
        "Ban Houay-Youak"
    ],
    "wof:name":"Ban Houay-Youak",
    "wof:placetype":"locality"
},
  "geometry": {"coordinates":[101.97859,18.81457],"type":"Point"}
}