{
  "type": "Feature",
  "properties": {
    "gn:admin1_code":"20.0",
    "gn:asciiname":"Ban Nongboua-Nua",
    "gn:country_code":"LA",
    "gn:dem":146,
    "gn:feature_class":"P",
    "gn:feature_code":"PPL",
    "gn:name":"Ban Nongboua-Nua",
    "gn:population":0,
    "gn:timezone":"Asia/Vientiane",
    "iso:country":"LA",
    "name:lao_x_preferred":[
        "Ban Nongboua-Nua"
    ],
    "wof:name":"Ban Nongboua-Nua",
    "wof:placetype":"locality"
},
  "geometry": {"coordinates":[105.39023,16.28419],"type":"Point"}
}