{
  "type": "Feature",
  "properties": {
    "gn:admin1_code":"20.0",
    "gn:asciiname":"Ban Napho-Khok",
    "gn:country_code":"LA",
    "gn:dem":168,
    "gn:feature_class":"P",
    "gn:feature_code":"PPL",
    "gn:name":"Ban Naph\u00f4-Kh\u00f4k",
    "gn:population":0,
    "gn:timezone":"Asia/Vientiane",
    "iso:country":"LA",
    "name:lao_x_preferred":[
        "Ban Naph\u00f4-Kh\u00f4k"
    ],
    "name:und_x_variant":[
        "Ban Naph\u00f4",
        "Ban Napha"
    ],
    "wof:name":"Ban Napho-Khok",
    "wof:placetype":"locality"
},
  "geometry": {"coordinates":[105.60120999999999,16.62036],"type":"Point"}
}