{
  "type": "Feature",
  "properties": {
    "gn:admin1_code":"14.0",
    "gn:asciiname":"Ban Pakkha",
    "gn:country_code":"LA",
    "gn:dem":1364,
    "gn:feature_class":"P",
    "gn:feature_code":"PPL",
    "gn:name":"Ban Pakkha",
    "gn:population":0,
    "gn:timezone":"Asia/Vientiane",
    "iso:country":"LA",
    "name:und_x_variant":[
        "Pha Kha",
        "Ban Pakha",
        "Ban Pakkha"
    ],
    "wof:name":"Ban Pakkha",
    "wof:placetype":"locality"
},
  "geometry": {"coordinates":[103.54349999999999,19.41091],"type":"Point"}
}