{
  "type": "Feature",
  "properties": {
    "gn:admin1_code":"20.0",
    "gn:asciiname":"Ban Phouthai",
    "gn:country_code":"LA",
    "gn:dem":235,
    "gn:feature_class":"P",
    "gn:feature_code":"PPL",
    "gn:name":"Ban Phouthai",
    "gn:population":0,
    "gn:timezone":"Asia/Vientiane",
    "iso:country":"LA",
    "name:und_x_variant":[
        "Ban Pouthai",
        "Ban Phouthai"
    ],
    "wof:name":"Ban Phouthai",
    "wof:placetype":"locality"
},
  "geometry": {"coordinates":[106.36841,16.44686],"type":"Point"}
}