{
  "type": "Feature",
  "properties": {
    "gn:admin1_code":"14.0",
    "gn:asciiname":"Ban Phichi",
    "gn:cc2":"LA",
    "gn:country_code":"LA",
    "gn:dem":1115,
    "gn:feature_class":"P",
    "gn:feature_code":"PPL",
    "gn:name":"Ban Phichi",
    "gn:population":0,
    "gn:timezone":"Asia/Vientiane",
    "iso:country":"LA",
    "name:und_x_variant":[
        "Tham Lom",
        "Tham Lam",
        "Ban Phichi"
    ],
    "wof:name":"Ban Phichi",
    "wof:placetype":"locality"
},
  "geometry": {"coordinates":[103.81667,19.35],"type":"Point"}
}