{
  "type": "Feature",
  "properties": {
    "gn:admin1_code":"14.0",
    "gn:asciiname":"Ban Xay",
    "gn:country_code":"LA",
    "gn:dem":1091,
    "gn:feature_class":"P",
    "gn:feature_code":"PPL",
    "gn:name":"Ban Xay",
    "gn:population":0,
    "gn:timezone":"Asia/Vientiane",
    "iso:country":"LA",
    "name:und_x_variant":[
        "Ban Sai",
        "Ban Xai",
        "Ban Xay"
    ],
    "wof:name":"Ban Xay",
    "wof:placetype":"locality"
},
  "geometry": {"coordinates":[103.00391999999999,19.521],"type":"Point"}
}