{
  "type": "Feature",
  "properties": {
    "gn:admin1_code":"23.0",
    "gn:asciiname":"Ban Sophoy",
    "gn:country_code":"LA",
    "gn:dem":515,
    "gn:feature_class":"P",
    "gn:feature_code":"PPL",
    "gn:name":"Ban S\u00f4phoy",
    "gn:population":0,
    "gn:timezone":"Asia/Vientiane",
    "iso:country":"LA",
    "name:und_x_variant":[
        "Ban Namhoy",
        "Ban Nam Hoi",
        "Ban S\u00f4phoy"
    ],
    "wof:name":"Ban Sophoy",
    "wof:placetype":"locality"
},
  "geometry": {"coordinates":[104.91406000000001,18.14851],"type":"Point"}
}