{
  "type": "Feature",
  "properties": {
    "gn:admin1_code":"19.0",
    "gn:asciiname":"Ban Sabongphoham",
    "gn:country_code":"LA",
    "gn:dem":615,
    "gn:feature_class":"P",
    "gn:feature_code":"PPL",
    "gn:name":"Ban Sab\u00f4ngphoham",
    "gn:population":0,
    "gn:timezone":"Asia/Vientiane",
    "iso:country":"LA",
    "name:lao_x_preferred":[
        "Ban Sab\u00f4ngphoham"
    ],
    "wof:name":"Ban Sabongphoham",
    "wof:placetype":"locality"
},
  "geometry": {"coordinates":[106.65809,16.02364],"type":"Point"}
}