{
  "type": "Feature",
  "properties": {
    "gn:admin1_code":"22.0",
    "gn:asciiname":"Ban Pong",
    "gn:country_code":"LA",
    "gn:dem":463,
    "gn:feature_class":"P",
    "gn:feature_code":"PPL",
    "gn:name":"Ban Pong",
    "gn:population":0,
    "gn:timezone":"Asia/Vientiane",
    "iso:country":"LA",
    "name:lao_x_preferred":[
        "Ban Pong"
    ],
    "wof:name":"Ban Pong",
    "wof:placetype":"locality"
},
  "geometry": {"coordinates":[100.53211,20.42382000000001],"type":"Point"}
}