{
  "type": "Feature",
  "properties": {
    "gn:admin1_code":"2.0",
    "gn:asciiname":"Ban Nongkhe",
    "gn:country_code":"LA",
    "gn:dem":102,
    "gn:feature_class":"P",
    "gn:feature_code":"PPL",
    "gn:name":"Ban Nongkh\u00e8",
    "gn:population":0,
    "gn:timezone":"Asia/Vientiane",
    "iso:country":"LA",
    "name:und_x_variant":[
        "Ban Nong K\u00e8",
        "Ban Nongkh\u00e8"
    ],
    "wof:name":"Ban Nongkhe",
    "wof:placetype":"locality"
},
  "geometry": {"coordinates":[105.94880999999999,14.7919],"type":"Point"}
}