{
  "type": "Feature",
  "properties": {
    "gn:admin1_code":"3.0",
    "gn:asciiname":"Ban Poungban",
    "gn:country_code":"LA",
    "gn:dem":1213,
    "gn:feature_class":"P",
    "gn:feature_code":"PPL",
    "gn:name":"Ban Poungban",
    "gn:population":0,
    "gn:timezone":"Asia/Vientiane",
    "iso:country":"LA",
    "name:lao_x_preferred":[
        "Ban Poungban"
    ],
    "wof:name":"Ban Poungban",
    "wof:placetype":"locality"
},
  "geometry": {"coordinates":[104.21317999999999,19.94771],"type":"Point"}
}