{
  "type": "Feature",
  "properties": {
    "gn:admin1_code":"17.0",
    "gn:asciiname":"Ban Houaytamang",
    "gn:country_code":"LA",
    "gn:dem":1153,
    "gn:feature_class":"P",
    "gn:feature_code":"PPL",
    "gn:name":"Ban Houaytamang",
    "gn:population":0,
    "gn:timezone":"Asia/Vientiane",
    "iso:country":"LA",
    "name:lao_x_preferred":[
        "Ban Houaytamang"
    ],
    "wof:name":"Ban Houaytamang",
    "wof:placetype":"locality"
},
  "geometry": {"coordinates":[102.7193,20.02344],"type":"Point"}
}