{
  "type": "Feature",
  "properties": {
    "gn:admin1_code":"16.0",
    "gn:asciiname":"Ban Viang-Nua",
    "gn:country_code":"LA",
    "gn:dem":554,
    "gn:feature_class":"P",
    "gn:feature_code":"PPL",
    "gn:name":"Ban Viang-Nua",
    "gn:population":0,
    "gn:timezone":"Asia/Vientiane",
    "iso:country":"LA",
    "name:lao_x_preferred":[
        "Ban Viang-Nua"
    ],
    "wof:name":"Ban Viang-Nua",
    "wof:placetype":"locality"
},
  "geometry": {"coordinates":[101.40282999999999,20.97096],"type":"Point"}
}