{
  "type": "Feature",
  "properties": {
    "gn:admin1_code":"28.0",
    "gn:asciiname":"Muang Xao",
    "gn:country_code":"LA",
    "gn:dem":594,
    "gn:feature_class":"P",
    "gn:feature_code":"PPL",
    "gn:name":"Muang Xao",
    "gn:population":0,
    "gn:timezone":"Asia/Vientiane",
    "iso:country":"LA",
    "name:und_x_variant":[
        "Muong Xao",
        "Muang Xao"
    ],
    "wof:name":"Muang Xao",
    "wof:placetype":"locality"
},
  "geometry": {"coordinates":[102.59999999999999,19.03333],"type":"Point"}
}