{
  "type": "Feature",
  "properties": {
    "gn:admin1_code":"18.0",
    "gn:asciiname":"Ban Phouhak",
    "gn:country_code":"LA",
    "gn:dem":978,
    "gn:feature_class":"P",
    "gn:feature_code":"PPL",
    "gn:name":"Ban Phouhak",
    "gn:population":0,
    "gn:timezone":"Asia/Vientiane",
    "iso:country":"LA",
    "name:lao_x_preferred":[
        "Ban Phouhak"
    ],
    "name:und_x_variant":[
        "Pou Hao",
        "Pou Hac",
        "Phou Hac"
    ],
    "wof:name":"Ban Phouhak",
    "wof:placetype":"locality"
},
  "geometry": {"coordinates":[101.88252,21.58715],"type":"Point"}
}