{
  "type": "Feature",
  "properties": {
    "gn:admin1_code":"2.0",
    "gn:asciiname":"Ban Donkhamao",
    "gn:country_code":"LA",
    "gn:dem":96,
    "gn:feature_class":"P",
    "gn:feature_code":"PPL",
    "gn:name":"Ban Donkhamao",
    "gn:population":0,
    "gn:timezone":"Asia/Vientiane",
    "iso:country":"LA",
    "name:und_x_variant":[
        "Ban Done Khamao",
        "Ban Donkhamao"
    ],
    "wof:name":"Ban Donkhamao",
    "wof:placetype":"locality"
},
  "geometry": {"coordinates":[105.86405000000001,14.44691],"type":"Point"}
}