{
  "type": "Feature",
  "properties": {
    "gn:admin1_code":"18.0",
    "gn:asciiname":"Sen Luong Chang",
    "gn:cc2":"LA",
    "gn:country_code":"LA",
    "gn:dem":977,
    "gn:feature_class":"P",
    "gn:feature_code":"PPL",
    "gn:name":"Sen Luong Chang",
    "gn:population":0,
    "gn:timezone":"Asia/Vientiane",
    "iso:country":"LA",
    "name:und_x_variant":[
        "Sen Luong",
        "Sen Luong Chang"
    ],
    "wof:name":"Sen Luong Chang",
    "wof:placetype":"locality"
},
  "geometry": {"coordinates":[101.86667,21.68333],"type":"Point"}
}