{
  "type": "Feature",
  "properties": {
    "gn:admin1_code":"18.0",
    "gn:asciiname":"Ban Choningon",
    "gn:country_code":"LA",
    "gn:dem":775,
    "gn:feature_class":"P",
    "gn:feature_code":"PPL",
    "gn:name":"Ban Choningon",
    "gn:population":0,
    "gn:timezone":"Asia/Vientiane",
    "iso:country":"LA",
    "name:lao_x_preferred":[
        "Ban Choningon"
    ],
    "wof:name":"Ban Choningon",
    "wof:placetype":"locality"
},
  "geometry": {"coordinates":[102.35485,21.12473],"type":"Point"}
}