{
  "type": "Feature",
  "properties": {
    "gn:admin1_code":"23.0",
    "gn:asciiname":"Ban Nongkhoay",
    "gn:country_code":"LA",
    "gn:dem":1044,
    "gn:feature_class":"P",
    "gn:feature_code":"PPL",
    "gn:name":"Ban Nongkhoay",
    "gn:population":0,
    "gn:timezone":"Asia/Vientiane",
    "iso:country":"LA",
    "name:lao_x_preferred":[
        "Ban Nongkhoay"
    ],
    "wof:name":"Ban Nongkhoay",
    "wof:placetype":"locality"
},
  "geometry": {"coordinates":[105.00943999999998,18.48433],"type":"Point"}
}