{
  "type": "Feature",
  "properties": {
    "gn:admin1_code":"19.0",
    "gn:asciiname":"Ban Xicheng-Tai",
    "gn:country_code":"LA",
    "gn:dem":429,
    "gn:feature_class":"P",
    "gn:feature_code":"PPL",
    "gn:name":"Ban Xich\u00e8ng-Tai",
    "gn:population":0,
    "gn:timezone":"Asia/Vientiane",
    "iso:country":"LA",
    "name:lao_x_preferred":[
        "Ban Xich\u00e8ng-Tai"
    ],
    "wof:name":"Ban Xicheng-Tai",
    "wof:placetype":"locality"
},
  "geometry": {"coordinates":[106.71196,16.16047],"type":"Point"}
}