{
  "type": "Feature",
  "properties": {
    "gn:admin1_code":"20.0",
    "gn:asciiname":"Ban Kangpa-Noy",
    "gn:country_code":"LA",
    "gn:dem":146,
    "gn:feature_class":"P",
    "gn:feature_code":"PPL",
    "gn:name":"Ban Kangpa-Noy",
    "gn:population":0,
    "gn:timezone":"Asia/Vientiane",
    "iso:country":"LA",
    "name:lao_x_preferred":[
        "Ban Kangpa-Noy"
    ],
    "wof:name":"Ban Kangpa-Noy",
    "wof:placetype":"locality"
},
  "geometry": {"coordinates":[104.851,17.04792],"type":"Point"}
}