{
  "type": "Feature",
  "properties": {
    "gn:admin1_code":"15.0",
    "gn:asciiname":"Ban Phonset",
    "gn:country_code":"LA",
    "gn:dem":165,
    "gn:feature_class":"P",
    "gn:feature_code":"PPL",
    "gn:name":"Ban Ph\u00f4ns\u00e8t",
    "gn:population":0,
    "gn:timezone":"Asia/Vientiane",
    "iso:country":"LA",
    "name:lao_x_preferred":[
        "Ban Ph\u00f4ns\u00e8t"
    ],
    "wof:name":"Ban Phonset",
    "wof:placetype":"locality"
},
  "geometry": {"coordinates":[105.2608,17.51172],"type":"Point"}
}