{
  "type": "Feature",
  "properties": {
    "gn:admin1_code":"18.0",
    "gn:asciiname":"Ban Kounglit",
    "gn:country_code":"LA",
    "gn:dem":1074,
    "gn:feature_class":"P",
    "gn:feature_code":"PPL",
    "gn:name":"Ban Kounglit",
    "gn:population":0,
    "gn:timezone":"Asia/Vientiane",
    "iso:country":"LA",
    "name:und_x_variant":[
        "Kong Rip",
        "Ban Kounglit"
    ],
    "wof:name":"Ban Kounglit",
    "wof:placetype":"locality"
},
  "geometry": {"coordinates":[102.52073,20.95035],"type":"Point"}
}