{
  "type": "Feature",
  "properties": {
    "gn:admin1_code":"15.0",
    "gn:asciiname":"Ban Xot",
    "gn:country_code":"LA",
    "gn:dem":538,
    "gn:feature_class":"P",
    "gn:feature_code":"PPL",
    "gn:name":"Ban Xot",
    "gn:population":0,
    "gn:timezone":"Asia/Vientiane",
    "iso:country":"LA",
    "name:lao_x_preferred":[
        "Ban Xot"
    ],
    "wof:name":"Ban Xot",
    "wof:placetype":"locality"
},
  "geometry": {"coordinates":[105.22602999999999,17.72307],"type":"Point"}
}