{
  "type": "Feature",
  "properties": {
    "gn:admin1_code":"13.0",
    "gn:asciiname":"Ban Khmou",
    "gn:country_code":"LA",
    "gn:dem":797,
    "gn:feature_class":"P",
    "gn:feature_code":"PPL",
    "gn:name":"Ban Khmou",
    "gn:population":0,
    "gn:timezone":"Asia/Vientiane",
    "iso:country":"LA",
    "wof:name":"Ban Khmou",
    "wof:placetype":"locality"
},
  "geometry": {"coordinates":[100.93333,19.76667],"type":"Point"}
}