{
  "type": "Feature",
  "properties": {
    "gn:admin1_code":"20.0",
    "gn:asciiname":"Ban Houayhoy-Nua",
    "gn:country_code":"LA",
    "gn:dem":182,
    "gn:feature_class":"P",
    "gn:feature_code":"PPL",
    "gn:name":"Ban Houayhoy-Nua",
    "gn:population":0,
    "gn:timezone":"Asia/Vientiane",
    "iso:country":"LA",
    "name:lao_x_preferred":[
        "Ban Houayhoy-Nua"
    ],
    "wof:name":"Ban Houayhoy-Nua",
    "wof:placetype":"locality"
},
  "geometry": {"coordinates":[106.15747,16.42103],"type":"Point"}
}