{
  "type": "Feature",
  "properties": {
    "gn:admin1_code":"16.0",
    "gn:asciiname":"Ban Phouxe",
    "gn:country_code":"LA",
    "gn:dem":543,
    "gn:feature_class":"P",
    "gn:feature_code":"PPL",
    "gn:name":"Ban Phoux\u00e8",
    "gn:population":0,
    "gn:timezone":"Asia/Vientiane",
    "iso:country":"LA",
    "name:lao_x_preferred":[
        "Ban Phoux\u00e8"
    ],
    "wof:name":"Ban Phouxe",
    "wof:placetype":"locality"
},
  "geometry": {"coordinates":[101.52555,20.57485],"type":"Point"}
}