{
  "type": "Feature",
  "properties": {
    "gn:admin1_code":"15.0",
    "gn:asciiname":"Ban Nakachan-Thong",
    "gn:country_code":"LA",
    "gn:dem":185,
    "gn:feature_class":"P",
    "gn:feature_code":"PPL",
    "gn:name":"Ban Nakachan-Thong",
    "gn:population":0,
    "gn:timezone":"Asia/Vientiane",
    "iso:country":"LA",
    "name:lao_x_preferred":[
        "Ban Nakachan-Thong"
    ],
    "name:und_x_variant":[
        "Ban Nakachan"
    ],
    "wof:name":"Ban Nakachan-Thong",
    "wof:placetype":"locality"
},
  "geometry": {"coordinates":[105.70631000000002,17.32053],"type":"Point"}
}