{
  "type": "Feature",
  "properties": {
    "gn:admin1_code":"18.0",
    "gn:asciiname":"Ban Houayphouk",
    "gn:country_code":"LA",
    "gn:dem":388,
    "gn:feature_class":"P",
    "gn:feature_code":"PPL",
    "gn:name":"Ban Houayphouk",
    "gn:population":0,
    "gn:timezone":"Asia/Vientiane",
    "iso:country":"LA",
    "name:lao_x_preferred":[
        "Ban Houayphouk"
    ],
    "wof:name":"Ban Houayphouk",
    "wof:placetype":"locality"
},
  "geometry": {"coordinates":[102.46259000000001,21.22673],"type":"Point"}
}