{
  "type": "Feature",
  "properties": {
    "gn:admin1_code":"17.0",
    "gn:asciiname":"Ban Nakang",
    "gn:country_code":"LA",
    "gn:dem":547,
    "gn:feature_class":"P",
    "gn:feature_code":"PPL",
    "gn:name":"Ban Nakang",
    "gn:population":0,
    "gn:timezone":"Asia/Vientiane",
    "iso:country":"LA",
    "name:lao_x_preferred":[
        "Ban Nakang"
    ],
    "wof:name":"Ban Nakang",
    "wof:placetype":"locality"
},
  "geometry": {"coordinates":[103.07187,20.61481],"type":"Point"}
}