{
  "type": "Feature",
  "properties": {
    "gn:admin1_code":"16.0",
    "gn:asciiname":"Ban Panghouayhok",
    "gn:country_code":"LA",
    "gn:dem":552,
    "gn:feature_class":"P",
    "gn:feature_code":"PPL",
    "gn:name":"Ban Panghouayh\u00f4k",
    "gn:population":0,
    "gn:timezone":"Asia/Vientiane",
    "iso:country":"LA",
    "name:lao_x_preferred":[
        "Ban Panghouayh\u00f4k"
    ],
    "wof:name":"Ban Panghouayhok",
    "wof:placetype":"locality"
},
  "geometry": {"coordinates":[101.43577000000001,20.95897],"type":"Point"}
}