{
  "type": "Feature",
  "properties": {
    "gn:admin1_code":"13.0",
    "gn:asciiname":"Ban Phougnaykha",
    "gn:country_code":"LA",
    "gn:dem":383,
    "gn:feature_class":"P",
    "gn:feature_code":"PPL",
    "gn:name":"Ban Phougnaykha",
    "gn:population":0,
    "gn:timezone":"Asia/Vientiane",
    "iso:country":"LA",
    "name:lao_x_preferred":[
        "Ban Phougnaykha"
    ],
    "wof:name":"Ban Phougnaykha",
    "wof:placetype":"locality"
},
  "geometry": {"coordinates":[101.05002,19.8236],"type":"Point"}
}