{
  "type": "Feature",
  "properties": {
    "gn:admin1_code":"2.0",
    "gn:asciiname":"Ban Mai",
    "gn:country_code":"LA",
    "gn:dem":127,
    "gn:feature_class":"P",
    "gn:feature_code":"PPL",
    "gn:name":"Ban Mai",
    "gn:population":0,
    "gn:timezone":"Asia/Vientiane",
    "iso:country":"LA",
    "name:lao_x_preferred":[
        "Ban Mai"
    ],
    "wof:name":"Ban Mai",
    "wof:placetype":"locality"
},
  "geometry": {"coordinates":[105.61296000000002,15.18695],"type":"Point"}
}