{
  "type": "Feature",
  "properties": {
    "gn:admin1_code":"3.0",
    "gn:asciiname":"Ban Houay Ouang",
    "gn:cc2":"LA",
    "gn:country_code":"LA",
    "gn:dem":1219,
    "gn:feature_class":"P",
    "gn:feature_code":"PPL",
    "gn:name":"Ban Houay Ouang",
    "gn:population":0,
    "gn:timezone":"Asia/Vientiane",
    "iso:country":"LA",
    "name:und_x_variant":[
        "Ban Houei Quang",
        "Ban Houei Ouang",
        "Ban Houay Ouang"
    ],
    "wof:name":"Ban Houay Ouang",
    "wof:placetype":"locality"
},
  "geometry": {"coordinates":[104.05,20.46667],"type":"Point"}
}