{
  "type": "Feature",
  "properties": {
    "gn:admin1_code":"14.0",
    "gn:asciiname":"Ban Nanoy",
    "gn:cc2":"LA",
    "gn:country_code":"LA",
    "gn:dem":1286,
    "gn:feature_class":"P",
    "gn:feature_code":"PPL",
    "gn:name":"Ban Nanoy",
    "gn:population":0,
    "gn:timezone":"Asia/Vientiane",
    "iso:country":"LA",
    "name:und_x_variant":[
        "Ban Na Noi",
        "Ban Nanoy"
    ],
    "wof:name":"Ban Nanoy",
    "wof:placetype":"locality"
},
  "geometry": {"coordinates":[103.28333000000001,19.63333],"type":"Point"}
}