{
  "type": "Feature",
  "properties": {
    "gn:admin1_code":"27.0",
    "gn:asciiname":"Ban Tangkham",
    "gn:country_code":"LA",
    "gn:dem":206,
    "gn:feature_class":"P",
    "gn:feature_code":"PPL",
    "gn:name":"Ban Tangkham",
    "gn:population":0,
    "gn:timezone":"Asia/Vientiane",
    "iso:country":"LA",
    "name:lao_x_preferred":[
        "Ban Tangkham"
    ],
    "wof:name":"Ban Tangkham",
    "wof:placetype":"locality"
},
  "geometry": {"coordinates":[102.28605,18.66511],"type":"Point"}
}