{
  "type": "Feature",
  "properties": {
    "gn:admin1_code":"15.0",
    "gn:asciiname":"Ban Donmounkhoay",
    "gn:country_code":"LA",
    "gn:dem":152,
    "gn:feature_class":"P",
    "gn:feature_code":"PPL",
    "gn:name":"Ban Donmounkhoay",
    "gn:population":0,
    "gn:timezone":"Asia/Vientiane",
    "iso:country":"LA",
    "name:lao_x_preferred":[
        "Ban Donmounkhoay"
    ],
    "wof:name":"Ban Donmounkhoay",
    "wof:placetype":"locality"
},
  "geometry": {"coordinates":[104.81999,17.20954],"type":"Point"}
}