{
  "type": "Feature",
  "properties": {
    "gn:admin1_code":"24.0",
    "gn:asciiname":"Ban Namon",
    "gn:country_code":"LA",
    "gn:dem":172,
    "gn:feature_class":"P",
    "gn:feature_code":"PPL",
    "gn:name":"Ban Nam\u00f4n",
    "gn:population":0,
    "gn:timezone":"Asia/Vientiane",
    "iso:country":"LA",
    "name:und_x_variant":[
        "Ban Na Monh",
        "Ban Nam\u00f4n"
    ],
    "wof:name":"Ban Namon",
    "wof:placetype":"locality"
},
  "geometry": {"coordinates":[102.75057,18.10605],"type":"Point"}
}