{
  "type": "Feature",
  "properties": {
    "gn:admin1_code":"1.0",
    "gn:asciiname":"Ban Daktout",
    "gn:country_code":"LA",
    "gn:dem":1101,
    "gn:feature_class":"P",
    "gn:feature_code":"PPL",
    "gn:name":"Ban Daktout",
    "gn:population":0,
    "gn:timezone":"Asia/Vientiane",
    "iso:country":"LA",
    "name:und_x_variant":[
        "Nhot",
        "Ban Daktout"
    ],
    "wof:name":"Ban Daktout",
    "wof:placetype":"locality"
},
  "geometry": {"coordinates":[107.16579,15.26768],"type":"Point"}
}