{
  "type": "Feature",
  "properties": {
    "gn:admin1_code":"17.0",
    "gn:asciiname":"Ban Sanok",
    "gn:country_code":"LA",
    "gn:dem":303,
    "gn:feature_class":"P",
    "gn:feature_code":"PPL",
    "gn:name":"Ban San\u00f4k",
    "gn:population":0,
    "gn:timezone":"Asia/Vientiane",
    "iso:country":"LA",
    "name:lao_x_preferred":[
        "Ban San\u00f4k"
    ],
    "wof:name":"Ban Sanok",
    "wof:placetype":"locality"
},
  "geometry": {"coordinates":[102.20941000000001,19.93904],"type":"Point"}
}