{
  "type": "Feature",
  "properties": {
    "gn:admin1_code":"27.0",
    "gn:asciiname":"Ban Xam-Nadi",
    "gn:country_code":"LA",
    "gn:dem":246,
    "gn:feature_class":"P",
    "gn:feature_code":"PPL",
    "gn:name":"Ban Xam-Nadi",
    "gn:population":0,
    "gn:timezone":"Asia/Vientiane",
    "iso:country":"LA",
    "name:lao_x_preferred":[
        "Ban Xam-Nadi"
    ],
    "wof:name":"Ban Xam-Nadi",
    "wof:placetype":"locality"
},
  "geometry": {"coordinates":[101.71850999999999,18.14171],"type":"Point"}
}