{
  "type": "Feature",
  "properties": {
    "gn:admin1_code":"23.0",
    "gn:asciiname":"Ban Bong",
    "gn:country_code":"LA",
    "gn:dem":162,
    "gn:feature_class":"P",
    "gn:feature_code":"PPL",
    "gn:name":"Ban B\u00f4ng",
    "gn:population":0,
    "gn:timezone":"Asia/Vientiane",
    "iso:country":"LA",
    "name:lao_x_preferred":[
        "Lan-Gnao"
    ],
    "name:und_x_variant":[
        "Ban Ph\u00f4n-Ngam",
        "Ban Lau Jai",
        "Ban Lan-Gnao",
        "Ban B\u00f4ng"
    ],
    "wof:name":"Ban Bong",
    "wof:placetype":"locality"
},
  "geometry": {"coordinates":[103.88052,18.38815],"type":"Point"}
}