{
  "type": "Feature",
  "properties": {
    "gn:admin1_code":"14.0",
    "gn:asciiname":"Ban Gnotpiang",
    "gn:country_code":"LA",
    "gn:dem":1183,
    "gn:feature_class":"P",
    "gn:feature_code":"PPL",
    "gn:name":"Ban Gnotpiang",
    "gn:population":0,
    "gn:timezone":"Asia/Vientiane",
    "iso:country":"LA",
    "name:und_x_variant":[
        "Ban Gnolpiang"
    ],
    "wof:name":"Ban Gnotpiang",
    "wof:placetype":"locality"
},
  "geometry": {"coordinates":[103.28464,19.64882],"type":"Point"}
}