{
  "type": "Feature",
  "properties": {
    "gn:admin1_code":"16.0",
    "gn:asciiname":"Ban Suadeng",
    "gn:country_code":"LA",
    "gn:dem":1178,
    "gn:feature_class":"P",
    "gn:feature_code":"PPL",
    "gn:name":"Ban Suad\u00e8ng",
    "gn:population":0,
    "gn:timezone":"Asia/Vientiane",
    "iso:country":"LA",
    "name:lao_x_preferred":[
        "Ban Suad\u00e8ng"
    ],
    "wof:name":"Ban Suadeng",
    "wof:placetype":"locality"
},
  "geometry": {"coordinates":[101.02643999999999,21.29875],"type":"Point"}
}