{
  "type": "Feature",
  "properties": {
    "gn:admin1_code":"3.0",
    "gn:asciiname":"Ban Phonthong",
    "gn:country_code":"LA",
    "gn:dem":618,
    "gn:feature_class":"P",
    "gn:feature_code":"PPL",
    "gn:name":"Ban Ph\u00f4nthong",
    "gn:population":0,
    "gn:timezone":"Asia/Vientiane",
    "iso:country":"LA",
    "name:lao_x_preferred":[
        "Ban Ph\u00f4nthong"
    ],
    "name:und_x_variant":[
        "Xieng K\u00e8ne"
    ],
    "wof:name":"Ban Phonthong",
    "wof:placetype":"locality"
},
  "geometry": {"coordinates":[104.29649999999999,20.47379],"type":"Point"}
}