{
  "type": "Feature",
  "properties": {
    "gn:admin1_code":"28.0",
    "gn:asciiname":"Ban Lak Xao-Si",
    "gn:country_code":"LA",
    "gn:dem":395,
    "gn:feature_class":"P",
    "gn:feature_code":"PPL",
    "gn:name":"Ban Lak Xao-Si",
    "gn:population":0,
    "gn:timezone":"Asia/Vientiane",
    "iso:country":"LA",
    "name:lao_x_preferred":[
        "Ban Lak Xao-Si"
    ],
    "wof:name":"Ban Lak Xao-Si",
    "wof:placetype":"locality"
},
  "geometry": {"coordinates":[102.64521999999999,18.8104],"type":"Point"}
}