{
  "type": "Feature",
  "properties": {
    "gn:admin1_code":"22.0",
    "gn:asciiname":"Ban Phangoua",
    "gn:country_code":"LA",
    "gn:dem":719,
    "gn:feature_class":"P",
    "gn:feature_code":"PPL",
    "gn:name":"Ban Phangoua",
    "gn:population":0,
    "gn:timezone":"Asia/Vientiane",
    "iso:country":"LA",
    "name:lao_x_preferred":[
        "Ban Phangoua"
    ],
    "wof:name":"Ban Phangoua",
    "wof:placetype":"locality"
},
  "geometry": {"coordinates":[100.48289,20.75727],"type":"Point"}
}