{
  "type": "Feature",
  "properties": {
    "gn:admin1_code":"15.0",
    "gn:asciiname":"Ban Phonnadi",
    "gn:country_code":"LA",
    "gn:dem":171,
    "gn:feature_class":"P",
    "gn:feature_code":"PPL",
    "gn:name":"Ban Ph\u00f4nnadi",
    "gn:population":0,
    "gn:timezone":"Asia/Vientiane",
    "iso:country":"LA",
    "name:lao_x_preferred":[
        "Ban Ph\u00f4nnadi"
    ],
    "wof:name":"Ban Phonnadi",
    "wof:placetype":"locality"
},
  "geometry": {"coordinates":[105.0487,17.45556],"type":"Point"}
}