{
  "type": "Feature",
  "properties": {
    "gn:admin1_code":"15.0",
    "gn:asciiname":"Ban Phonsavan",
    "gn:country_code":"LA",
    "gn:dem":182,
    "gn:feature_class":"P",
    "gn:feature_code":"PPL",
    "gn:name":"Ban Ph\u00f4nsavan",
    "gn:population":0,
    "gn:timezone":"Asia/Vientiane",
    "iso:country":"LA",
    "name:und_x_variant":[
        "Ban Phon",
        "Ban Phong Savane",
        "Ban Ph\u00f4nsavan"
    ],
    "wof:name":"Ban Phonsavan",
    "wof:placetype":"locality"
},
  "geometry": {"coordinates":[105.20577,17.62288],"type":"Point"}
}