{
  "type": "Feature",
  "properties": {
    "gn:admin1_code":"20.0",
    "gn:asciiname":"Ban Muang-Angkham",
    "gn:country_code":"LA",
    "gn:dem":245,
    "gn:feature_class":"P",
    "gn:feature_code":"PPL",
    "gn:name":"Ban Muang-Angkham",
    "gn:population":0,
    "gn:timezone":"Asia/Vientiane",
    "iso:country":"LA",
    "name:und_x_variant":[
        "Ban Ang Kham",
        "Ban Muong Ang Kham",
        "Ang Kham",
        "Ban Muang-Angkham"
    ],
    "wof:name":"Ban Muang-Angkham",
    "wof:placetype":"locality"
},
  "geometry": {"coordinates":[106.12116,16.96589],"type":"Point"}
}