{
  "type": "Feature",
  "properties": {
    "gn:admin1_code":"3.0",
    "gn:asciiname":"Ban Nam Seu",
    "gn:country_code":"LA",
    "gn:dem":1136,
    "gn:feature_class":"P",
    "gn:feature_code":"PPL",
    "gn:name":"Ban Nam Seu",
    "gn:population":0,
    "gn:timezone":"Asia/Vientiane",
    "iso:country":"LA",
    "wof:name":"Ban Nam Seu",
    "wof:placetype":"locality"
},
  "geometry": {"coordinates":[103.93333,20.63333],"type":"Point"}
}