{
  "type": "Feature",
  "properties": {
    "gn:admin1_code":"17.0",
    "gn:asciiname":"Ban Hatngo",
    "gn:country_code":"LA",
    "gn:dem":470,
    "gn:feature_class":"P",
    "gn:feature_code":"PPL",
    "gn:name":"Ban Hatngo",
    "gn:population":0,
    "gn:timezone":"Asia/Vientiane",
    "iso:country":"LA",
    "name:lao_x_preferred":[
        "Ban Hatngo"
    ],
    "wof:name":"Ban Hatngo",
    "wof:placetype":"locality"
},
  "geometry": {"coordinates":[103.02665,20.61625],"type":"Point"}
}