{
  "type": "Feature",
  "properties": {
    "gn:admin1_code":"20.0",
    "gn:asciiname":"Ban Thakhamlian",
    "gn:country_code":"LA",
    "gn:dem":144,
    "gn:feature_class":"P",
    "gn:feature_code":"PPL",
    "gn:name":"Ban Thakhamlian",
    "gn:population":0,
    "gn:timezone":"Asia/Vientiane",
    "iso:country":"LA",
    "name:lao_x_preferred":[
        "Ban Thakhamlian"
    ],
    "wof:name":"Ban Thakhamlian",
    "wof:placetype":"locality"
},
  "geometry": {"coordinates":[105.27003999999999,16.26569],"type":"Point"}
}