{
  "type": "Feature",
  "properties": {
    "gn:admin1_code":"18.0",
    "gn:asciiname":"Ban Omkok",
    "gn:country_code":"LA",
    "gn:dem":1013,
    "gn:feature_class":"P",
    "gn:feature_code":"PPL",
    "gn:name":"Ban \u00d4mk\u00f4k",
    "gn:population":0,
    "gn:timezone":"Asia/Vientiane",
    "iso:country":"LA",
    "name:und_x_variant":[
        "Om Kok",
        "Ban \u00d4mk\u00f4k",
        "Ham Kok"
    ],
    "wof:name":"Ban Omkok",
    "wof:placetype":"locality"
},
  "geometry": {"coordinates":[102.58644,21.00694],"type":"Point"}
}