{
  "type": "Feature",
  "properties": {
    "gn:admin1_code":"14.0",
    "gn:asciiname":"Ban Phiangkhop",
    "gn:country_code":"LA",
    "gn:dem":702,
    "gn:feature_class":"P",
    "gn:feature_code":"PPL",
    "gn:name":"Ban Phiangkh\u00f4p",
    "gn:population":0,
    "gn:timezone":"Asia/Vientiane",
    "iso:country":"LA",
    "name:lao_x_preferred":[
        "Ban Phiangkh\u00f4p"
    ],
    "wof:name":"Ban Phiangkhop",
    "wof:placetype":"locality"
},
  "geometry": {"coordinates":[103.51869000000001,19.68375],"type":"Point"}
}