{
  "type": "Feature",
  "properties": {
    "gn:admin1_code":"26.0",
    "gn:asciiname":"Ban Youn-Tai",
    "gn:country_code":"LA",
    "gn:dem":1066,
    "gn:feature_class":"P",
    "gn:feature_code":"PPL",
    "gn:name":"Ban Youn-Tai",
    "gn:population":0,
    "gn:timezone":"Asia/Vientiane",
    "iso:country":"LA",
    "name:lao_x_preferred":[
        "Ban Youn-Tai"
    ],
    "wof:name":"Ban Youn-Tai",
    "wof:placetype":"locality"
},
  "geometry": {"coordinates":[107.29575,15.25373],"type":"Point"}
}