{
  "type": "Feature",
  "properties": {
    "gn:admin1_code":"17.0",
    "gn:asciiname":"Ban Lek Sip",
    "gn:country_code":"LA",
    "gn:dem":418,
    "gn:feature_class":"P",
    "gn:feature_code":"PPL",
    "gn:name":"Ban L\u00e9k Sip",
    "gn:population":0,
    "gn:timezone":"Asia/Vientiane",
    "iso:country":"LA",
    "name:lao_x_preferred":[
        "Ban L\u00e9k Sip"
    ],
    "wof:name":"Ban Lek Sip",
    "wof:placetype":"locality"
},
  "geometry": {"coordinates":[102.09739999999999,19.6577],"type":"Point"}
}