{
  "type": "Feature",
  "properties": {
    "gn:admin1_code":"13.0",
    "gn:asciiname":"Ban Namsok",
    "gn:country_code":"LA",
    "gn:dem":324,
    "gn:feature_class":"P",
    "gn:feature_code":"PPL",
    "gn:name":"Ban Nams\u00f4k",
    "gn:population":0,
    "gn:timezone":"Asia/Vientiane",
    "iso:country":"LA",
    "name:lao_x_preferred":[
        "Ban Nams\u00f4k"
    ],
    "wof:name":"Ban Namsok",
    "wof:placetype":"locality"
},
  "geometry": {"coordinates":[101.58288,18.54502],"type":"Point"}
}