{
  "type": "Feature",
  "properties": {
    "gn:admin1_code":"3.0",
    "gn:asciiname":"Ban Bo Bon",
    "gn:country_code":"LA",
    "gn:dem":1035,
    "gn:feature_class":"P",
    "gn:feature_code":"PPL",
    "gn:name":"Ban Bo Bon",
    "gn:population":0,
    "gn:timezone":"Asia/Vientiane",
    "iso:country":"LA",
    "wof:name":"Ban Bo Bon",
    "wof:placetype":"locality"
},
  "geometry": {"coordinates":[104.08333,20.93333],"type":"Point"}
}