{
  "type": "Feature",
  "properties": {
    "gn:admin1_code":"27.0",
    "gn:asciiname":"Ban Phonkham-Nua",
    "gn:country_code":"LA",
    "gn:dem":209,
    "gn:feature_class":"P",
    "gn:feature_code":"PPL",
    "gn:name":"Ban Ph\u00f4nkham-Nua",
    "gn:population":0,
    "gn:timezone":"Asia/Vientiane",
    "iso:country":"LA",
    "name:lao_x_preferred":[
        "Ban Ph\u00f4nkham-Nua"
    ],
    "wof:name":"Ban Phonkham-Nua",
    "wof:placetype":"locality"
},
  "geometry": {"coordinates":[102.33074999999999,18.55363],"type":"Point"}
}