{
  "type": "Feature",
  "properties": {
    "gn:admin1_code":"13.0",
    "gn:asciiname":"Ban Khamkang",
    "gn:country_code":"LA",
    "gn:dem":233,
    "gn:feature_class":"P",
    "gn:feature_code":"PPL",
    "gn:name":"Ban Khamkang",
    "gn:population":0,
    "gn:timezone":"Asia/Vientiane",
    "iso:country":"LA",
    "name:lao_x_preferred":[
        "Ban Khamkang"
    ],
    "wof:name":"Ban Khamkang",
    "wof:placetype":"locality"
},
  "geometry": {"coordinates":[101.37273,18.11379],"type":"Point"}
}