{
  "type": "Feature",
  "properties": {
    "gn:admin1_code":"14.0",
    "gn:asciiname":"Ban Gnotkha-Kao",
    "gn:country_code":"LA",
    "gn:dem":1251,
    "gn:feature_class":"P",
    "gn:feature_code":"PPL",
    "gn:name":"Ban Gnotkha-Kao",
    "gn:population":0,
    "gn:timezone":"Asia/Vientiane",
    "iso:country":"LA",
    "name:lao_x_preferred":[
        "Ban Gnotkha-Kao"
    ],
    "wof:name":"Ban Gnotkha-Kao",
    "wof:placetype":"locality"
},
  "geometry": {"coordinates":[103.80834,19.52353],"type":"Point"}
}