{
  "type": "Feature",
  "properties": {
    "gn:admin1_code":"26.0",
    "gn:asciiname":"Ban Sen-Nua",
    "gn:country_code":"LA",
    "gn:dem":744,
    "gn:feature_class":"P",
    "gn:feature_code":"PPL",
    "gn:name":"Ban S\u00e8n-Nua",
    "gn:population":0,
    "gn:timezone":"Asia/Vientiane",
    "iso:country":"LA",
    "name:lao_x_preferred":[
        "Ban S\u00e8n-Nua"
    ],
    "wof:name":"Ban Sen-Nua",
    "wof:placetype":"locality"
},
  "geometry": {"coordinates":[106.42515,15.47674],"type":"Point"}
}