{
  "type": "Feature",
  "properties": {
    "gn:admin1_code":"26.0",
    "gn:asciiname":"Ban Thongnai-Kao",
    "gn:country_code":"LA",
    "gn:dem":382,
    "gn:feature_class":"P",
    "gn:feature_code":"PPL",
    "gn:name":"Ban Th\u00f4ngnai-Kao",
    "gn:population":0,
    "gn:timezone":"Asia/Vientiane",
    "iso:country":"LA",
    "name:lao_x_preferred":[
        "Ban Th\u00f4ngnai-Kao"
    ],
    "wof:name":"Ban Thongnai-Kao",
    "wof:placetype":"locality"
},
  "geometry": {"coordinates":[106.6093,15.38585],"type":"Point"}
}