{
  "type": "Feature",
  "properties": {
    "gn:admin1_code":"0.0",
    "gn:asciiname":"Ban Na Yeung",
    "gn:country_code":"LA",
    "gn:dem":1262,
    "gn:feature_class":"P",
    "gn:feature_code":"PPL",
    "gn:name":"Ban Na Yeung",
    "gn:population":0,
    "gn:timezone":"Asia/Vientiane",
    "iso:country":"LA",
    "name:vie_x_preferred":[
        "Ban Na Yeung"
    ],
    "wof:name":"Ban Na Yeung",
    "wof:placetype":"locality"
},
  "geometry": {"coordinates":[104.05343999999999,20.29582000000001],"type":"Point"}
}