{
  "type": "Feature",
  "properties": {
    "gn:admin1_code":"15.0",
    "gn:asciiname":"Ban Viang",
    "gn:country_code":"LA",
    "gn:dem":160,
    "gn:feature_class":"P",
    "gn:feature_code":"PPL",
    "gn:name":"Ban Viang",
    "gn:population":0,
    "gn:timezone":"Asia/Vientiane",
    "iso:country":"LA",
    "name:lao_x_preferred":[
        "Ban Viang"
    ],
    "wof:name":"Ban Viang",
    "wof:placetype":"locality"
},
  "geometry": {"coordinates":[104.6664,18.01933],"type":"Point"}
}