{
  "type": "Feature",
  "properties": {
    "gn:admin1_code":"19.0",
    "gn:asciiname":"Ban Phakkha",
    "gn:cc2":"LA",
    "gn:country_code":"LA",
    "gn:dem":185,
    "gn:feature_class":"P",
    "gn:feature_code":"PPL",
    "gn:name":"Ban Phakkha",
    "gn:population":0,
    "gn:timezone":"Asia/Vientiane",
    "iso:country":"LA",
    "name:und_x_variant":[
        "Ban Pha Kha",
        "Ban Phakkha"
    ],
    "wof:name":"Ban Phakkha",
    "wof:placetype":"locality"
},
  "geometry": {"coordinates":[106.48333,15.71667],"type":"Point"}
}