{
  "type": "Feature",
  "properties": {
    "gn:admin1_code":"17.0",
    "gn:asciiname":"Ban Phopaou",
    "gn:country_code":"LA",
    "gn:dem":630,
    "gn:feature_class":"P",
    "gn:feature_code":"PPL",
    "gn:name":"Ban Phopaou",
    "gn:population":0,
    "gn:timezone":"Asia/Vientiane",
    "iso:country":"LA",
    "name:lao_x_preferred":[
        "Ban Phopaou"
    ],
    "wof:name":"Ban Phopaou",
    "wof:placetype":"locality"
},
  "geometry": {"coordinates":[102.38599000000001,19.88607],"type":"Point"}
}