{
  "type": "Feature",
  "properties": {
    "gn:admin1_code":"13.0",
    "gn:asciiname":"Ban Nadokmai",
    "gn:country_code":"LA",
    "gn:dem":660,
    "gn:feature_class":"P",
    "gn:feature_code":"PPL",
    "gn:name":"Ban Nadokmai",
    "gn:population":0,
    "gn:timezone":"Asia/Vientiane",
    "iso:country":"LA",
    "name:lao_x_preferred":[
        "Ban Nadokmai"
    ],
    "wof:name":"Ban Nadokmai",
    "wof:placetype":"locality"
},
  "geometry": {"coordinates":[101.23096,17.95763999999999],"type":"Point"}
}