{
  "type": "Feature",
  "properties": {
    "gn:admin1_code":"17.0",
    "gn:asciiname":"Ban Houaykou",
    "gn:country_code":"LA",
    "gn:dem":1016,
    "gn:feature_class":"P",
    "gn:feature_code":"PPL",
    "gn:name":"Ban Houaykou",
    "gn:population":0,
    "gn:timezone":"Asia/Vientiane",
    "iso:country":"LA",
    "name:lao_x_preferred":[
        "Ban Houaykou"
    ],
    "wof:name":"Ban Houaykou",
    "wof:placetype":"locality"
},
  "geometry": {"coordinates":[102.98792,20.40596],"type":"Point"}
}