{
  "type": "Feature",
  "properties": {
    "gn:admin1_code":"23.0",
    "gn:asciiname":"Ban Hinlekfai",
    "gn:country_code":"LA",
    "gn:dem":766,
    "gn:feature_class":"P",
    "gn:feature_code":"PPL",
    "gn:name":"Ban Hinl\u00e9kfai",
    "gn:population":0,
    "gn:timezone":"Asia/Vientiane",
    "iso:country":"LA",
    "name:lao_x_preferred":[
        "Ban Hinl\u00e9kfai"
    ],
    "wof:name":"Ban Hinlekfai",
    "wof:placetype":"locality"
},
  "geometry": {"coordinates":[104.27025,18.63612],"type":"Point"}
}