{
  "type": "Feature",
  "properties": {
    "gn:admin1_code":"18.0",
    "gn:asciiname":"Ban Laoxe",
    "gn:country_code":"LA",
    "gn:dem":1152,
    "gn:feature_class":"P",
    "gn:feature_code":"PPL",
    "gn:name":"Ban Laox\u00e8",
    "gn:population":0,
    "gn:timezone":"Asia/Vientiane",
    "iso:country":"LA",
    "name:lao_x_preferred":[
        "Ban Laox\u00e8"
    ],
    "wof:name":"Ban Laoxe",
    "wof:placetype":"locality"
},
  "geometry": {"coordinates":[102.07152000000001,21.981],"type":"Point"}
}