{
  "type": "Feature",
  "properties": {
    "iso:country":"LA",
    "name:pol_x_preferred":[
        "Ban Pakha"
    ],
    "name:unk_x_variant":[
        "Ban Pac Kha"
    ],
    "qs:gn_country":"LA",
    "qs:gn_fcode":"PPL",
    "qs:gn_pop":0,
    "qs:name":"Ban Pakha",
    "qs:name_adm0":"Laos",
    "qs:name_adm1":"Bolikhamxai",
    "qs:photos":34,
    "qs:photos_1k":7,
    "qs:photos_9k":1,
    "qs:photos_9r":2,
    "qs:photos_all":34,
    "qs:photos_sr":2,
    "qs:placetype":"Town",
    "qs:pop_sr":"4",
    "qs:woe_adm0":23424872,
    "wd:wordcount":33,
    "wof:name":"Ban Pakha",
    "wof:placetype":"locality"
},
  "geometry": {"coordinates":[104.68939,18.24319],"type":"Point"}
}