{
  "type": "Feature",
  "properties": {
    "gn:admin1_code":"7.0",
    "gn:asciiname":"Ban Chomxang-Dong",
    "gn:country_code":"LA",
    "gn:dem":915,
    "gn:feature_class":"P",
    "gn:feature_code":"PPL",
    "gn:name":"Ban Chomxang-D\u00f4ng",
    "gn:population":0,
    "gn:timezone":"Asia/Vientiane",
    "iso:country":"LA",
    "name:lao_x_preferred":[
        "Ban Chomxang-D\u00f4ng"
    ],
    "wof:name":"Ban Chomxang-Dong",
    "wof:placetype":"locality"
},
  "geometry": {"coordinates":[101.07057,19.95249],"type":"Point"}
}