{
  "type": "Feature",
  "properties": {
    "gn:admin1_code":"17.0",
    "gn:asciiname":"Ban Navet",
    "gn:country_code":"LA",
    "gn:dem":1222,
    "gn:feature_class":"P",
    "gn:feature_code":"PPL",
    "gn:name":"Ban Nav\u00e8t",
    "gn:population":0,
    "gn:timezone":"Asia/Vientiane",
    "iso:country":"LA",
    "name:lao_x_preferred":[
        "Ban Nav\u00e8t"
    ],
    "wof:name":"Ban Navet",
    "wof:placetype":"locality"
},
  "geometry": {"coordinates":[103.19117,20.54404],"type":"Point"}
}