{
  "type": "Feature",
  "properties": {
    "gn:admin1_code":"3.0",
    "gn:asciiname":"Ban Talat",
    "gn:country_code":"LA",
    "gn:dem":450,
    "gn:feature_class":"P",
    "gn:feature_code":"PPL",
    "gn:name":"Ban Talat",
    "gn:population":0,
    "gn:timezone":"Asia/Vientiane",
    "iso:country":"LA",
    "wof:name":"Ban Talat",
    "wof:placetype":"locality"
},
  "geometry": {"coordinates":[104.28888999999999,20.87833],"type":"Point"}
}