{
  "type": "Feature",
  "properties": {
    "gn:admin1_code":"3.0",
    "gn:asciiname":"Kham So",
    "gn:country_code":"LA",
    "gn:dem":1114,
    "gn:feature_class":"P",
    "gn:feature_code":"PPL",
    "gn:name":"Kham S\u00f4",
    "gn:population":0,
    "gn:timezone":"Asia/Vientiane",
    "iso:country":"LA",
    "wof:name":"Kham So",
    "wof:placetype":"locality"
},
  "geometry": {"coordinates":[104.25,20.65],"type":"Point"}
}