{
  "type": "Feature",
  "properties": {
    "gn:admin1_code":"18.0",
    "gn:asciiname":"Ban Chande",
    "gn:country_code":"LA",
    "gn:dem":721,
    "gn:feature_class":"P",
    "gn:feature_code":"PPL",
    "gn:name":"Ban Chand\u00e9",
    "gn:population":0,
    "gn:timezone":"Asia/Vientiane",
    "iso:country":"LA",
    "name:lao_x_preferred":[
        "Ban Chand\u00e9"
    ],
    "wof:name":"Ban Chande",
    "wof:placetype":"locality"
},
  "geometry": {"coordinates":[102.49532000000001,20.9058],"type":"Point"}
}