{
  "type": "Feature",
  "properties": {
    "gn:admin1_code":"16.0",
    "gn:asciiname":"Ban Thongdi-Mai",
    "gn:country_code":"LA",
    "gn:dem":564,
    "gn:feature_class":"P",
    "gn:feature_code":"PPL",
    "gn:name":"Ban Th\u00f4ngdi-Mai",
    "gn:population":0,
    "gn:timezone":"Asia/Vientiane",
    "iso:country":"LA",
    "name:lao_x_preferred":[
        "Ban Th\u00f4ngdi-Mai"
    ],
    "wof:name":"Ban Thongdi-Mai",
    "wof:placetype":"locality"
},
  "geometry": {"coordinates":[101.42937000000001,20.99017000000001],"type":"Point"}
}