{
  "type": "Feature",
  "properties": {
    "gn:admin1_code":"20.0",
    "gn:asciiname":"Ban Kokphok",
    "gn:country_code":"LA",
    "gn:dem":145,
    "gn:feature_class":"P",
    "gn:feature_code":"PPL",
    "gn:name":"Ban K\u00f4kphok",
    "gn:population":0,
    "gn:timezone":"Asia/Vientiane",
    "iso:country":"LA",
    "name:lao_x_preferred":[
        "Ban K\u00f4kphok"
    ],
    "wof:name":"Ban Kokphok",
    "wof:placetype":"locality"
},
  "geometry": {"coordinates":[105.26373,16.26057999999999],"type":"Point"}
}