{
  "type": "Feature",
  "properties": {
    "gn:admin1_code":"18.0",
    "gn:asciiname":"Ban Chavang-Noy",
    "gn:country_code":"LA",
    "gn:dem":1006,
    "gn:feature_class":"P",
    "gn:feature_code":"PPL",
    "gn:name":"Ban Chavang-Noy",
    "gn:population":0,
    "gn:timezone":"Asia/Vientiane",
    "iso:country":"LA",
    "name:lao_x_preferred":[
        "Ban Chavang-Noy"
    ],
    "wof:name":"Ban Chavang-Noy",
    "wof:placetype":"locality"
},
  "geometry": {"coordinates":[101.88563000000001,21.20714],"type":"Point"}
}