{
  "type": "Feature",
  "properties": {
    "gn:admin1_code":"26.0",
    "gn:asciiname":"Ban Houaypahe",
    "gn:country_code":"LA",
    "gn:dem":707,
    "gn:feature_class":"P",
    "gn:feature_code":"PPL",
    "gn:name":"Ban Houaypahe",
    "gn:population":0,
    "gn:timezone":"Asia/Vientiane",
    "iso:country":"LA",
    "name:lao_x_preferred":[
        "Ban Houaypahe"
    ],
    "wof:name":"Ban Houaypahe",
    "wof:placetype":"locality"
},
  "geometry": {"coordinates":[106.86469,15.98179],"type":"Point"}
}