{
  "type": "Feature",
  "properties": {
    "gn:admin1_code":"22.0",
    "gn:asciiname":"Ban Padong",
    "gn:country_code":"LA",
    "gn:dem":836,
    "gn:feature_class":"P",
    "gn:feature_code":"PPL",
    "gn:name":"Ban Pad\u00f4ng",
    "gn:population":0,
    "gn:timezone":"Asia/Vientiane",
    "iso:country":"LA",
    "name:lao_x_preferred":[
        "Ban Pad\u00f4ng"
    ],
    "wof:name":"Ban Padong",
    "wof:placetype":"locality"
},
  "geometry": {"coordinates":[100.64982999999999,19.8707],"type":"Point"}
}