{
  "type": "Feature",
  "properties": {
    "gn:admin1_code":"19.0",
    "gn:asciiname":"Ban Khoumkeo",
    "gn:country_code":"LA",
    "gn:dem":142,
    "gn:feature_class":"P",
    "gn:feature_code":"PPL",
    "gn:name":"Ban Khoumk\u00e8o",
    "gn:population":0,
    "gn:timezone":"Asia/Vientiane",
    "iso:country":"LA",
    "name:lao_x_preferred":[
        "Ban Khoumk\u00e8o"
    ],
    "wof:name":"Ban Khoumkeo",
    "wof:placetype":"locality"
},
  "geometry": {"coordinates":[105.84378999999998,15.65104],"type":"Point"}
}