{
  "type": "Feature",
  "properties": {
    "gn:admin1_code":"17.0",
    "gn:asciiname":"Ban Phonxai",
    "gn:country_code":"LA",
    "gn:dem":1027,
    "gn:feature_class":"P",
    "gn:feature_code":"PPL",
    "gn:name":"Ban Ph\u00f4nxai",
    "gn:population":0,
    "gn:timezone":"Asia/Vientiane",
    "iso:country":"LA",
    "name:lao_x_preferred":[
        "Ban Ph\u00f4nxai"
    ],
    "wof:name":"Ban Phonxai",
    "wof:placetype":"locality"
},
  "geometry": {"coordinates":[102.97295,20.16409],"type":"Point"}
}