{
  "type": "Feature",
  "properties": {
    "gn:admin1_code":"2.0",
    "gn:asciiname":"Ban Katup Theung",
    "gn:cc2":"LA",
    "gn:country_code":"LA",
    "gn:dem":106,
    "gn:feature_class":"P",
    "gn:feature_code":"PPL",
    "gn:name":"Ban Katup Theung",
    "gn:population":0,
    "gn:timezone":"Asia/Vientiane",
    "iso:country":"LA",
    "name:und_x_variant":[
        "Sangmakyang",
        "Ban Katsup Theung",
        "Ban Katup Theung"
    ],
    "wof:name":"Ban Katup Theung",
    "wof:placetype":"locality"
},
  "geometry": {"coordinates":[105.83333,14.81667],"type":"Point"}
}