{
  "type": "Feature",
  "properties": {
    "gn:admin1_code":"20.0",
    "gn:asciiname":"Ban Khonken",
    "gn:country_code":"LA",
    "gn:dem":164,
    "gn:feature_class":"P",
    "gn:feature_code":"PPL",
    "gn:name":"Ban Khonk\u00e8n",
    "gn:population":0,
    "gn:timezone":"Asia/Vientiane",
    "iso:country":"LA",
    "name:und_x_variant":[
        "Ban Khone Kene",
        "Ban Khonk\u00e8n"
    ],
    "wof:name":"Ban Khonken",
    "wof:placetype":"locality"
},
  "geometry": {"coordinates":[104.88526,16.71654],"type":"Point"}
}