{
  "type": "Feature",
  "properties": {
    "gn:admin1_code":"18.0",
    "gn:asciiname":"Lao Sieu",
    "gn:country_code":"LA",
    "gn:dem":1140,
    "gn:feature_class":"P",
    "gn:feature_code":"PPL",
    "gn:name":"Lao Sieu",
    "gn:population":0,
    "gn:timezone":"Asia/Vientiane",
    "iso:country":"LA",
    "wof:name":"Lao Sieu",
    "wof:placetype":"locality"
},
  "geometry": {"coordinates":[102.05,22.01667],"type":"Point"}
}