{
  "type": "Feature",
  "properties": {
    "gn:admin1_code":"3.0",
    "gn:asciiname":"Ban Xamthong",
    "gn:country_code":"LA",
    "gn:dem":337,
    "gn:feature_class":"P",
    "gn:feature_code":"PPL",
    "gn:name":"Ban Xamthong",
    "gn:population":0,
    "gn:timezone":"Asia/Vientiane",
    "iso:country":"LA",
    "name:lao_x_preferred":[
        "Ban Xamthong"
    ],
    "wof:name":"Ban Xamthong",
    "wof:placetype":"locality"
},
  "geometry": {"coordinates":[104.63954,19.99094],"type":"Point"}
}