{
  "type": "Feature",
  "properties": {
    "gn:admin1_code":"2.0",
    "gn:asciiname":"Ban Pak-Houaybangliang",
    "gn:country_code":"LA",
    "gn:dem":101,
    "gn:feature_class":"P",
    "gn:feature_code":"PPL",
    "gn:name":"Ban Pak-Houaybangliang",
    "gn:population":0,
    "gn:timezone":"Asia/Vientiane",
    "iso:country":"LA",
    "name:lao_x_preferred":[
        "Ban Pak-Houaybangliang"
    ],
    "name:und_x_variant":[
        "Ban Pak Houei",
        "Ban Pak Houay"
    ],
    "wof:name":"Ban Pak-Houaybangliang",
    "wof:placetype":"locality"
},
  "geometry": {"coordinates":[105.90496,14.96036],"type":"Point"}
}