{
  "type": "Feature",
  "properties": {
    "gn:admin1_code":"17.0",
    "gn:asciiname":"Ban Phoupot",
    "gn:country_code":"LA",
    "gn:dem":642,
    "gn:feature_class":"P",
    "gn:feature_code":"PPL",
    "gn:name":"Ban Phoupot",
    "gn:population":0,
    "gn:timezone":"Asia/Vientiane",
    "iso:country":"LA",
    "name:lao_x_preferred":[
        "Ban Phoupot"
    ],
    "wof:name":"Ban Phoupot",
    "wof:placetype":"locality"
},
  "geometry": {"coordinates":[101.83172999999999,19.71364],"type":"Point"}
}