{
  "type": "Feature",
  "properties": {
    "gn:admin1_code":"26.0",
    "gn:asciiname":"Ban Bu",
    "gn:country_code":"LA",
    "gn:dem":1248,
    "gn:feature_class":"P",
    "gn:feature_code":"PPL",
    "gn:name":"Ban Bu",
    "gn:population":0,
    "gn:timezone":"Asia/Vientiane",
    "iso:country":"LA",
    "name:lao_x_preferred":[
        "Ban Bu"
    ],
    "name:und_x_variant":[
        "Bou",
        "Ban Bou"
    ],
    "wof:name":"Ban Bu",
    "wof:placetype":"locality"
},
  "geometry": {"coordinates":[107.28149999999999,15.51205],"type":"Point"}
}