{
  "type": "Feature",
  "properties": {
    "gn:admin1_code":"17.0",
    "gn:asciiname":"Ban Vay",
    "gn:country_code":"LA",
    "gn:dem":1286,
    "gn:feature_class":"P",
    "gn:feature_code":"PPL",
    "gn:name":"Ban Vay",
    "gn:population":0,
    "gn:timezone":"Asia/Vientiane",
    "iso:country":"LA",
    "name:lao_x_preferred":[
        "Ban Vay"
    ],
    "wof:name":"Ban Vay",
    "wof:placetype":"locality"
},
  "geometry": {"coordinates":[102.31749000000001,19.53259],"type":"Point"}
}