{
  "type": "Feature",
  "properties": {
    "gn:admin1_code":"24.0",
    "gn:asciiname":"Ban Ang",
    "gn:country_code":"LA",
    "gn:dem":181,
    "gn:feature_class":"P",
    "gn:feature_code":"PPL",
    "gn:name":"Ban Ang",
    "gn:population":0,
    "gn:timezone":"Asia/Vientiane",
    "iso:country":"LA",
    "name:und_x_variant":[
        "Ban Ang Gnai",
        "Ban Ang"
    ],
    "wof:name":"Ban Ang",
    "wof:placetype":"locality"
},
  "geometry": {"coordinates":[102.39463000000001,18.01706],"type":"Point"}
}