{
  "type": "Feature",
  "properties": {
    "gn:admin1_code":"17.0",
    "gn:asciiname":"Ban Phonia",
    "gn:country_code":"LA",
    "gn:dem":505,
    "gn:feature_class":"P",
    "gn:feature_code":"PPL",
    "gn:name":"Ban Phonia",
    "gn:population":0,
    "gn:timezone":"Asia/Vientiane",
    "iso:country":"LA",
    "name:und_x_variant":[
        "Ban Pho Niai",
        "Ban Phonia"
    ],
    "wof:name":"Ban Phonia",
    "wof:placetype":"locality"
},
  "geometry": {"coordinates":[102.35286000000001,19.83704],"type":"Point"}
}