{
  "type": "Feature",
  "properties": {
    "gn:admin1_code":"7.0",
    "gn:asciiname":"Ban Houaycha",
    "gn:country_code":"LA",
    "gn:dem":746,
    "gn:feature_class":"P",
    "gn:feature_code":"PPL",
    "gn:name":"Ban Houaycha",
    "gn:population":0,
    "gn:timezone":"Asia/Vientiane",
    "iso:country":"LA",
    "name:lao_x_preferred":[
        "Ban Houaycha"
    ],
    "wof:name":"Ban Houaycha",
    "wof:placetype":"locality"
},
  "geometry": {"coordinates":[101.94723,20.61638],"type":"Point"}
}