{
  "type": "Feature",
  "properties": {
    "gn:admin1_code":"27.0",
    "gn:asciiname":"Ban Nampat-Nua",
    "gn:country_code":"LA",
    "gn:dem":229,
    "gn:feature_class":"P",
    "gn:feature_code":"PPL",
    "gn:name":"Ban Nampat-Nua",
    "gn:population":0,
    "gn:timezone":"Asia/Vientiane",
    "iso:country":"LA",
    "name:lao_x_preferred":[
        "Ban Nampat-Nua"
    ],
    "wof:name":"Ban Nampat-Nua",
    "wof:placetype":"locality"
},
  "geometry": {"coordinates":[102.54473,18.79962],"type":"Point"}
}