{
  "type": "Feature",
  "properties": {
    "gn:admin1_code":"15.0",
    "gn:asciiname":"Ban Dongkhouang",
    "gn:country_code":"LA",
    "gn:dem":162,
    "gn:feature_class":"P",
    "gn:feature_code":"PPL",
    "gn:name":"Ban D\u00f4ngkhouang",
    "gn:population":0,
    "gn:timezone":"Asia/Vientiane",
    "iso:country":"LA",
    "name:lao_x_preferred":[
        "Ban D\u00f4ngkhouang"
    ],
    "wof:name":"Ban Dongkhouang",
    "wof:placetype":"locality"
},
  "geometry": {"coordinates":[104.79895,17.09624],"type":"Point"}
}