{
  "type": "Feature",
  "properties": {
    "gn:admin1_code":"2.0",
    "gn:asciiname":"Ban Pak-Houaylai",
    "gn:country_code":"LA",
    "gn:dem":88,
    "gn:feature_class":"P",
    "gn:feature_code":"PPL",
    "gn:name":"Ban Pak-Houaylai",
    "gn:population":0,
    "gn:timezone":"Asia/Vientiane",
    "iso:country":"LA",
    "wof:name":"Ban Pak-Houaylai",
    "wof:placetype":"locality"
},
  "geometry": {"coordinates":[105.88333,14.81667],"type":"Point"}
}