{
  "type": "Feature",
  "properties": {
    "gn:admin1_code":"27.0",
    "gn:asciiname":"Ban Muangkhi",
    "gn:country_code":"LA",
    "gn:dem":251,
    "gn:feature_class":"P",
    "gn:feature_code":"PPL",
    "gn:name":"Ban Muangkhi",
    "gn:population":0,
    "gn:timezone":"Asia/Vientiane",
    "iso:country":"LA",
    "name:lao_x_preferred":[
        "Ban Muangkhi"
    ],
    "name:und_x_variant":[
        "Muong Ki",
        "Muang Gi",
        "Muong Ky",
        "Muang Ki",
        "Muang Khi"
    ],
    "wof:name":"Ban Muangkhi",
    "wof:placetype":"locality"
},
  "geometry": {"coordinates":[101.76138,18.44857],"type":"Point"}
}