{
  "type": "Feature",
  "properties": {
    "gn:admin1_code":"24.0",
    "gn:asciiname":"Ban Lakxao-Pet",
    "gn:country_code":"LA",
    "gn:dem":178,
    "gn:feature_class":"P",
    "gn:feature_code":"PPL",
    "gn:name":"Ban Lakxao-P\u00e8t",
    "gn:population":0,
    "gn:timezone":"Asia/Vientiane",
    "iso:country":"LA",
    "name:lao_x_preferred":[
        "Ban Lakxao-P\u00e8t"
    ],
    "wof:name":"Ban Lakxao-Pet",
    "wof:placetype":"locality"
},
  "geometry": {"coordinates":[102.80607999999999,18.06109],"type":"Point"}
}