{
  "type": "Feature",
  "properties": {
    "gn:admin1_code":"1.0",
    "gn:asciiname":"Ban Dakying-Gnai",
    "gn:country_code":"LA",
    "gn:dem":1115,
    "gn:feature_class":"P",
    "gn:feature_code":"PPL",
    "gn:name":"Ban Dakying-Gnai",
    "gn:population":0,
    "gn:timezone":"Asia/Vientiane",
    "iso:country":"LA",
    "name:lao_x_preferred":[
        "Ban Dakying-Gnai"
    ],
    "wof:name":"Ban Dakying-Gnai",
    "wof:placetype":"locality"
},
  "geometry": {"coordinates":[107.20475,15.26325],"type":"Point"}
}