{
  "type": "Feature",
  "properties": {
    "gn:admin1_code":"20.0",
    "gn:asciiname":"Ban Konghin",
    "gn:country_code":"LA",
    "gn:dem":226,
    "gn:feature_class":"P",
    "gn:feature_code":"PPL",
    "gn:name":"Ban Konghin",
    "gn:population":0,
    "gn:timezone":"Asia/Vientiane",
    "iso:country":"LA",
    "name:lao_x_preferred":[
        "Ban Konghin"
    ],
    "wof:name":"Ban Konghin",
    "wof:placetype":"locality"
},
  "geometry": {"coordinates":[106.1153,16.66165],"type":"Point"}
}