{
  "type": "Feature",
  "properties": {
    "gn:admin1_code":"28.0",
    "gn:asciiname":"Ban Pou",
    "gn:country_code":"LA",
    "gn:dem":324,
    "gn:feature_class":"P",
    "gn:feature_code":"PPL",
    "gn:name":"Ban Pou",
    "gn:population":0,
    "gn:timezone":"Asia/Vientiane",
    "iso:country":"LA",
    "name:lao_x_preferred":[
        "Ban Pou"
    ],
    "wof:name":"Ban Pou",
    "wof:placetype":"locality"
},
  "geometry": {"coordinates":[103.45444999999999,19.01895],"type":"Point"}
}