{
  "type": "Feature",
  "properties": {
    "gn:admin1_code":"15.0",
    "gn:asciiname":"Ban Songkhon",
    "gn:country_code":"LA",
    "gn:dem":554,
    "gn:feature_class":"P",
    "gn:feature_code":"PPL",
    "gn:name":"Ban Songkhon",
    "gn:population":0,
    "gn:timezone":"Asia/Vientiane",
    "iso:country":"LA",
    "name:lao_x_preferred":[
        "Ban Songkhon"
    ],
    "wof:name":"Ban Songkhon",
    "wof:placetype":"locality"
},
  "geometry": {"coordinates":[105.18143000000001,18.00027],"type":"Point"}
}