{
  "type": "Feature",
  "properties": {
    "gn:admin1_code":"23.0",
    "gn:asciiname":"Ban Nachia",
    "gn:country_code":"LA",
    "gn:dem":530,
    "gn:feature_class":"P",
    "gn:feature_code":"PPL",
    "gn:name":"Ban Nachia",
    "gn:population":0,
    "gn:timezone":"Asia/Vientiane",
    "iso:country":"LA",
    "name:lao_x_preferred":[
        "Ban Nachia"
    ],
    "wof:name":"Ban Nachia",
    "wof:placetype":"locality"
},
  "geometry": {"coordinates":[105.07809,18.31681],"type":"Point"}
}