{
  "type": "Feature",
  "properties": {
    "gn:admin1_code":"3.0",
    "gn:asciiname":"Ban Kongiou",
    "gn:country_code":"LA",
    "gn:dem":540,
    "gn:feature_class":"P",
    "gn:feature_code":"PPL",
    "gn:name":"Ban Kongiou",
    "gn:population":0,
    "gn:timezone":"Asia/Vientiane",
    "iso:country":"LA",
    "name:lao_x_preferred":[
        "Ban Kongiou"
    ],
    "wof:name":"Ban Kongiou",
    "wof:placetype":"locality"
},
  "geometry": {"coordinates":[104.18178,20.84993],"type":"Point"}
}