{
  "type": "Feature",
  "properties": {
    "gn:admin1_code":"17.0",
    "gn:asciiname":"Ban Phan-Tai",
    "gn:country_code":"LA",
    "gn:dem":988,
    "gn:feature_class":"P",
    "gn:feature_code":"PPL",
    "gn:name":"Ban Phan-Tai",
    "gn:population":0,
    "gn:timezone":"Asia/Vientiane",
    "iso:country":"LA",
    "name:lao_x_preferred":[
        "Ban Phan-Tai"
    ],
    "wof:name":"Ban Phan-Tai",
    "wof:placetype":"locality"
},
  "geometry": {"coordinates":[102.85469999999999,20.09746],"type":"Point"}
}