{
  "type": "Feature",
  "properties": {
    "gn:admin1_code":"17.0",
    "gn:asciiname":"Ban Le",
    "gn:country_code":"LA",
    "gn:dem":336,
    "gn:feature_class":"P",
    "gn:feature_code":"PPL",
    "gn:name":"Ban L\u00e8",
    "gn:population":0,
    "gn:timezone":"Asia/Vientiane",
    "iso:country":"LA",
    "name:und_x_variant":[
        "Ban Kho Le",
        "Ban L\u00e8"
    ],
    "wof:name":"Ban Le",
    "wof:placetype":"locality"
},
  "geometry": {"coordinates":[101.93334,20.00695],"type":"Point"}
}