{
  "type": "Feature",
  "properties": {
    "gn:admin1_code":"3.0",
    "gn:asciiname":"Ban Muangpoua",
    "gn:country_code":"LA",
    "gn:dem":633,
    "gn:feature_class":"P",
    "gn:feature_code":"PPL",
    "gn:name":"Ban Muangpoua",
    "gn:population":0,
    "gn:timezone":"Asia/Vientiane",
    "iso:country":"LA",
    "name:und_x_variant":[
        "Muang Poua",
        "Muong Poua",
        "Ban Muangpoua"
    ],
    "wof:name":"Ban Muangpoua",
    "wof:placetype":"locality"
},
  "geometry": {"coordinates":[104.25273,20.48102],"type":"Point"}
}