{
  "type": "Feature",
  "properties": {
    "gn:admin1_code":"19.0",
    "gn:asciiname":"Ban Bouay",
    "gn:country_code":"LA",
    "gn:dem":687,
    "gn:feature_class":"P",
    "gn:feature_code":"PPL",
    "gn:name":"Ban Bouay",
    "gn:population":0,
    "gn:timezone":"Asia/Vientiane",
    "iso:country":"LA",
    "name:und_x_variant":[
        "Tam Boai",
        "Ban Bouay"
    ],
    "wof:name":"Ban Bouay",
    "wof:placetype":"locality"
},
  "geometry": {"coordinates":[106.9444,16.35517999999999],"type":"Point"}
}