{
  "type": "Feature",
  "properties": {
    "gn:admin1_code":"19.0",
    "gn:asciiname":"Ban Saoven",
    "gn:country_code":"LA",
    "gn:dem":155,
    "gn:feature_class":"P",
    "gn:feature_code":"PPL",
    "gn:name":"Ban Saov\u00e8n",
    "gn:population":0,
    "gn:timezone":"Asia/Vientiane",
    "iso:country":"LA",
    "name:und_x_variant":[
        "Ban Sao Vene",
        "Ban Saov\u00e8n"
    ],
    "wof:name":"Ban Saoven",
    "wof:placetype":"locality"
},
  "geometry": {"coordinates":[105.81905,15.73519],"type":"Point"}
}