{
  "type": "Feature",
  "properties": {
    "gn:admin1_code":"20.0",
    "gn:asciiname":"Ban Koai",
    "gn:country_code":"LA",
    "gn:dem":324,
    "gn:feature_class":"P",
    "gn:feature_code":"PPL",
    "gn:name":"Ban Koai",
    "gn:population":0,
    "gn:timezone":"Asia/Vientiane",
    "iso:country":"LA",
    "wof:name":"Ban Koai",
    "wof:placetype":"locality"
},
  "geometry": {"coordinates":[106.38333,16.75],"type":"Point"}
}