{
  "type": "Feature",
  "properties": {
    "gn:admin1_code":"15.0",
    "gn:asciiname":"Ban Gnang",
    "gn:country_code":"LA",
    "gn:dem":185,
    "gn:feature_class":"P",
    "gn:feature_code":"PPL",
    "gn:name":"Ban Gnang",
    "gn:population":0,
    "gn:timezone":"Asia/Vientiane",
    "iso:country":"LA",
    "name:und_x_variant":[
        "Ban Nhang",
        "Ban Gnang"
    ],
    "wof:name":"Ban Gnang",
    "wof:placetype":"locality"
},
  "geometry": {"coordinates":[105.53789,17.10748],"type":"Point"}
}