{
  "type": "Feature",
  "properties": {
    "gn:admin1_code":"27.0",
    "gn:asciiname":"Ban Houaykhong",
    "gn:country_code":"LA",
    "gn:dem":181,
    "gn:feature_class":"P",
    "gn:feature_code":"PPL",
    "gn:name":"Ban Houaykh\u00f4ng",
    "gn:population":0,
    "gn:timezone":"Asia/Vientiane",
    "iso:country":"LA",
    "name:lao_x_preferred":[
        "Ban Houaykh\u00f4ng"
    ],
    "wof:name":"Ban Houaykhong",
    "wof:placetype":"locality"
},
  "geometry": {"coordinates":[102.57044999999999,18.45122000000001],"type":"Point"}
}