{
  "type": "Feature",
  "properties": {
    "gn:admin1_code":"7.0",
    "gn:asciiname":"Ban Mokmun",
    "gn:country_code":"LA",
    "gn:dem":426,
    "gn:feature_class":"P",
    "gn:feature_code":"PPL",
    "gn:name":"Ban M\u00f4kmun",
    "gn:population":0,
    "gn:timezone":"Asia/Vientiane",
    "iso:country":"LA",
    "name:und_x_variant":[
        "Ban Mok Mheun",
        "Ban M\u00f4kmun"
    ],
    "wof:name":"Ban Mokmun",
    "wof:placetype":"locality"
},
  "geometry": {"coordinates":[102.10330999999999,20.10492],"type":"Point"}
}