{
  "type": "Feature",
  "properties": {
    "gn:admin1_code":"2.0",
    "gn:asciiname":"Ban Houadonhi",
    "gn:country_code":"LA",
    "gn:dem":96,
    "gn:feature_class":"P",
    "gn:feature_code":"PPL",
    "gn:name":"Ban Houadonhi",
    "gn:population":0,
    "gn:timezone":"Asia/Vientiane",
    "iso:country":"LA",
    "name:lao_x_preferred":[
        "Ban Houadonhi"
    ],
    "name:und_x_variant":[
        "Don Hi",
        "Ban Done Hi",
        "Ban Don-Hi"
    ],
    "wof:name":"Ban Houadonhi",
    "wof:placetype":"locality"
},
  "geometry": {"coordinates":[105.78668,14.19105],"type":"Point"}
}