{
  "type": "Feature",
  "properties": {
    "gn:admin1_code":"17.0",
    "gn:asciiname":"Ban Xiansen",
    "gn:country_code":"LA",
    "gn:dem":1174,
    "gn:feature_class":"P",
    "gn:feature_code":"PPL",
    "gn:name":"Ban Xians\u00e9n",
    "gn:population":0,
    "gn:timezone":"Asia/Vientiane",
    "iso:country":"LA",
    "name:lao_x_preferred":[
        "Ban Xians\u00e9n"
    ],
    "wof:name":"Ban Xiansen",
    "wof:placetype":"locality"
},
  "geometry": {"coordinates":[103.18062,20.56211],"type":"Point"}
}