{
  "type": "Feature",
  "properties": {
    "gn:admin1_code":"17.0",
    "gn:asciiname":"Ban Taovang",
    "gn:cc2":"LA",
    "gn:country_code":"LA",
    "gn:dem":423,
    "gn:feature_class":"P",
    "gn:feature_code":"PPL",
    "gn:name":"Ban Taovang",
    "gn:population":0,
    "gn:timezone":"Asia/Vientiane",
    "iso:country":"LA",
    "name:und_x_variant":[
        "Ban Taou Vang",
        "Ban Taovang"
    ],
    "wof:name":"Ban Taovang",
    "wof:placetype":"locality"
},
  "geometry": {"coordinates":[102.23333,19.83333],"type":"Point"}
}