{
  "type": "Feature",
  "properties": {
    "gn:admin1_code":"2.0",
    "gn:asciiname":"Ban Tom",
    "gn:country_code":"LA",
    "gn:dem":1202,
    "gn:feature_class":"P",
    "gn:feature_code":"PPL",
    "gn:name":"Ban T\u00f4m",
    "gn:population":0,
    "gn:timezone":"Asia/Vientiane",
    "iso:country":"LA",
    "name:und_x_variant":[
        "Ban Tome",
        "Ban T\u00f4m"
    ],
    "wof:name":"Ban Tom",
    "wof:placetype":"locality"
},
  "geometry": {"coordinates":[106.36667,15.18333],"type":"Point"}
}