{
  "type": "Feature",
  "properties": {
    "gn:admin1_code":"16.0",
    "gn:asciiname":"Ban Namchang",
    "gn:country_code":"LA",
    "gn:dem":577,
    "gn:feature_class":"P",
    "gn:feature_code":"PPL",
    "gn:name":"Ban Namchang",
    "gn:population":0,
    "gn:timezone":"Asia/Vientiane",
    "iso:country":"LA",
    "name:lao_x_preferred":[
        "Ban Namchang"
    ],
    "wof:name":"Ban Namchang",
    "wof:placetype":"locality"
},
  "geometry": {"coordinates":[101.3964,20.99842],"type":"Point"}
}