{
  "type": "Feature",
  "properties": {
    "gn:admin1_code":"14.0",
    "gn:asciiname":"Ban Poung (1)",
    "gn:cc2":"LA",
    "gn:country_code":"LA",
    "gn:dem":1132,
    "gn:feature_class":"P",
    "gn:feature_code":"PPL",
    "gn:name":"Ban Poung (1)",
    "gn:population":0,
    "gn:timezone":"Asia/Vientiane",
    "iso:country":"LA",
    "name:und_x_variant":[
        "Ban Pouh",
        "Ban Poung (1)"
    ],
    "wof:name":"Ban Poung (1)",
    "wof:placetype":"locality"
},
  "geometry": {"coordinates":[103.21666999999999,19.55],"type":"Point"}
}