{
  "type": "Feature",
  "properties": {
    "gn:admin1_code":"17.0",
    "gn:asciiname":"Ban Houay Mac",
    "gn:country_code":"LA",
    "gn:dem":513,
    "gn:feature_class":"P",
    "gn:feature_code":"PPL",
    "gn:name":"Ban Houay Mac",
    "gn:population":0,
    "gn:timezone":"Asia/Vientiane",
    "iso:country":"LA",
    "wof:name":"Ban Houay Mac",
    "wof:placetype":"locality"
},
  "geometry": {"coordinates":[102.34999999999999,20.33333],"type":"Point"}
}