{
  "type": "Feature",
  "properties": {
    "gn:admin1_code":"17.0",
    "gn:asciiname":"Ban Phakalangha",
    "gn:country_code":"LA",
    "gn:dem":449,
    "gn:feature_class":"P",
    "gn:feature_code":"PPL",
    "gn:name":"Ban Phakalangha",
    "gn:population":0,
    "gn:timezone":"Asia/Vientiane",
    "iso:country":"LA",
    "name:lao_x_preferred":[
        "Ban Phakalangha"
    ],
    "wof:name":"Ban Phakalangha",
    "wof:placetype":"locality"
},
  "geometry": {"coordinates":[102.35762,20.40761],"type":"Point"}
}