{
  "type": "Feature",
  "properties": {
    "gn:admin1_code":"17.0",
    "gn:asciiname":"Ban Xiangkeo",
    "gn:country_code":"LA",
    "gn:dem":303,
    "gn:feature_class":"P",
    "gn:feature_code":"PPL",
    "gn:name":"Ban Xiangk\u00e8o",
    "gn:population":0,
    "gn:timezone":"Asia/Vientiane",
    "iso:country":"LA",
    "name:und_x_variant":[
        "Ban Sieng Keo",
        "Ban Sieng K\u00e8ou",
        "Ban Xiangk\u00e8o"
    ],
    "wof:name":"Ban Xiangkeo",
    "wof:placetype":"locality"
},
  "geometry": {"coordinates":[102.11821,19.86417],"type":"Point"}
}