{
  "type": "Feature",
  "properties": {
    "gn:admin1_code":"7.0",
    "gn:asciiname":"Ban Nangoua",
    "gn:country_code":"LA",
    "gn:dem":553,
    "gn:feature_class":"P",
    "gn:feature_code":"PPL",
    "gn:name":"Ban Nangoua",
    "gn:population":0,
    "gn:timezone":"Asia/Vientiane",
    "iso:country":"LA",
    "name:lao_x_preferred":[
        "Ban Nangoua"
    ],
    "wof:name":"Ban Nangoua",
    "wof:placetype":"locality"
},
  "geometry": {"coordinates":[101.67789999999999,20.38173],"type":"Point"}
}