{
  "type": "Feature",
  "properties": {
    "gn:admin1_code":"20.0",
    "gn:asciiname":"Ban Nachan",
    "gn:country_code":"LA",
    "gn:dem":170,
    "gn:feature_class":"P",
    "gn:feature_code":"PPL",
    "gn:name":"Ban Nachan",
    "gn:population":0,
    "gn:timezone":"Asia/Vientiane",
    "iso:country":"LA",
    "name:und_x_variant":[
        "Ban Nachane",
        "Ban Nachan"
    ],
    "wof:name":"Ban Nachan",
    "wof:placetype":"locality"
},
  "geometry": {"coordinates":[105.21727,16.7885],"type":"Point"}
}