{
  "type": "Feature",
  "properties": {
    "gn:admin1_code":"18.0",
    "gn:asciiname":"Ban Kenglouang",
    "gn:country_code":"LA",
    "gn:dem":560,
    "gn:feature_class":"P",
    "gn:feature_code":"PPL",
    "gn:name":"Ban K\u00e8nglouang",
    "gn:population":0,
    "gn:timezone":"Asia/Vientiane",
    "iso:country":"LA",
    "wof:name":"Ban Kenglouang",
    "wof:placetype":"locality"
},
  "geometry": {"coordinates":[102.23333,21.03333],"type":"Point"}
}