{
  "type": "Feature",
  "properties": {
    "gn:admin1_code":"20.0",
    "gn:asciiname":"Pe Riang",
    "gn:country_code":"LA",
    "gn:dem":521,
    "gn:feature_class":"P",
    "gn:feature_code":"PPL",
    "gn:name":"Pe Riang",
    "gn:population":0,
    "gn:timezone":"Asia/Vientiane",
    "iso:country":"LA",
    "wof:name":"Pe Riang",
    "wof:placetype":"locality"
},
  "geometry": {"coordinates":[106.59999999999999,16.41667],"type":"Point"}
}