{
  "type": "Feature",
  "properties": {
    "gn:admin1_code":"20.0",
    "gn:asciiname":"Ban Nonsavang",
    "gn:country_code":"LA",
    "gn:dem":149,
    "gn:feature_class":"P",
    "gn:feature_code":"PPL",
    "gn:name":"Ban N\u00f4nsavang",
    "gn:population":0,
    "gn:timezone":"Asia/Vientiane",
    "iso:country":"LA",
    "name:lao_x_preferred":[
        "Ban N\u00f4nsavang"
    ],
    "wof:name":"Ban Nonsavang",
    "wof:placetype":"locality"
},
  "geometry": {"coordinates":[105.3027,16.18384],"type":"Point"}
}