{
  "type": "Feature",
  "properties": {
    "gn:admin1_code":"17.0",
    "gn:asciiname":"Ban Louk",
    "gn:country_code":"LA",
    "gn:dem":1056,
    "gn:feature_class":"P",
    "gn:feature_code":"PPL",
    "gn:name":"Ban Louk",
    "gn:population":0,
    "gn:timezone":"Asia/Vientiane",
    "iso:country":"LA",
    "name:lao_x_preferred":[
        "Ban Louk"
    ],
    "wof:name":"Ban Louk",
    "wof:placetype":"locality"
},
  "geometry": {"coordinates":[102.28859,20.6272],"type":"Point"}
}