{
  "type": "Feature",
  "properties": {
    "gn:admin1_code":"3.0",
    "gn:asciiname":"Xiengdi",
    "gn:country_code":"LA",
    "gn:dem":567,
    "gn:feature_class":"P",
    "gn:feature_code":"PPL",
    "gn:name":"Xiengdi",
    "gn:population":0,
    "gn:timezone":"Asia/Vientiane",
    "iso:country":"LA",
    "name:und_x_variant":[
        "Ban Xieng Di",
        "Xiengdi"
    ],
    "wof:name":"Xiengdi",
    "wof:placetype":"locality"
},
  "geometry": {"coordinates":[103.73333,20.03333],"type":"Point"}
}