{
  "type": "Feature",
  "properties": {
    "gn:admin1_code":"13.0",
    "gn:asciiname":"Ban Moy",
    "gn:country_code":"LA",
    "gn:dem":771,
    "gn:feature_class":"P",
    "gn:feature_code":"PPL",
    "gn:name":"Ban Moy",
    "gn:population":0,
    "gn:timezone":"Asia/Vientiane",
    "iso:country":"LA",
    "name:lao_x_preferred":[
        "Ban Moy"
    ],
    "wof:name":"Ban Moy",
    "wof:placetype":"locality"
},
  "geometry": {"coordinates":[100.96921,19.67233],"type":"Point"}
}