{
  "type": "Feature",
  "properties": {
    "gn:admin1_code":"20.0",
    "gn:asciiname":"Ban Sen",
    "gn:country_code":"LA",
    "gn:dem":405,
    "gn:feature_class":"P",
    "gn:feature_code":"PPL",
    "gn:name":"Ban S\u00e8n",
    "gn:population":0,
    "gn:timezone":"Asia/Vientiane",
    "iso:country":"LA",
    "name:lao_x_preferred":[
        "Ban S\u00e8n"
    ],
    "name:und_x_variant":[
        "L\u00e0ng Sen"
    ],
    "wof:name":"Ban Sen",
    "wof:placetype":"locality"
},
  "geometry": {"coordinates":[106.56044,16.52124],"type":"Point"}
}