{
  "type": "Feature",
  "properties": {
    "gn:admin1_code":"23.0",
    "gn:asciiname":"Ban Kaan",
    "gn:country_code":"LA",
    "gn:dem":437,
    "gn:feature_class":"P",
    "gn:feature_code":"PPL",
    "gn:name":"Ban Kaan",
    "gn:population":0,
    "gn:timezone":"Asia/Vientiane",
    "iso:country":"LA",
    "name:und_x_variant":[
        "Ban Ca An",
        "Ban Kaan"
    ],
    "wof:name":"Ban Kaan",
    "wof:placetype":"locality"
},
  "geometry": {"coordinates":[104.83468999999999,18.29127],"type":"Point"}
}