{
  "type": "Feature",
  "properties": {
    "gn:admin1_code":"14.0",
    "gn:asciiname":"Ban Na-O",
    "gn:country_code":"LA",
    "gn:dem":1122,
    "gn:feature_class":"P",
    "gn:feature_code":"PPL",
    "gn:name":"Ban Na-O",
    "gn:population":0,
    "gn:timezone":"Asia/Vientiane",
    "iso:country":"LA",
    "name:lao_x_preferred":[
        "Ban Na-O"
    ],
    "wof:name":"Ban Na-O",
    "wof:placetype":"locality"
},
  "geometry": {"coordinates":[103.18120999999999,19.42204],"type":"Point"}
}