{
  "type": "Feature",
  "properties": {
    "gn:admin1_code":"17.0",
    "gn:asciiname":"Ban Phakleng",
    "gn:country_code":"LA",
    "gn:dem":869,
    "gn:feature_class":"P",
    "gn:feature_code":"PPL",
    "gn:name":"Ban Phakl\u00e8ng",
    "gn:population":0,
    "gn:timezone":"Asia/Vientiane",
    "iso:country":"LA",
    "name:lao_x_preferred":[
        "Ban Phakl\u00e8ng"
    ],
    "wof:name":"Ban Phakleng",
    "wof:placetype":"locality"
},
  "geometry": {"coordinates":[102.53152,19.656],"type":"Point"}
}