{
  "type": "Feature",
  "properties": {
    "gn:admin1_code":"3.0",
    "gn:asciiname":"Ban Sop-Kat",
    "gn:country_code":"LA",
    "gn:dem":548,
    "gn:feature_class":"P",
    "gn:feature_code":"PPL",
    "gn:name":"Ban S\u00f4p-Kat",
    "gn:population":0,
    "gn:timezone":"Asia/Vientiane",
    "iso:country":"LA",
    "name:lao_x_preferred":[
        "Ban S\u00f4p-Kat"
    ],
    "name:und_x_variant":[
        "Sop Nath",
        "S\u00f4pnat"
    ],
    "wof:name":"Ban Sop-Kat",
    "wof:placetype":"locality"
},
  "geometry": {"coordinates":[103.66775,20.04444],"type":"Point"}
}