{
  "type": "Feature",
  "properties": {
    "gn:admin1_code":"20.0",
    "gn:asciiname":"Ban Naphilang",
    "gn:country_code":"LA",
    "gn:dem":209,
    "gn:feature_class":"P",
    "gn:feature_code":"PPL",
    "gn:name":"Ban Naphilang",
    "gn:population":0,
    "gn:timezone":"Asia/Vientiane",
    "iso:country":"LA",
    "name:und_x_variant":[
        "Ban Nafilang",
        "Ban Naphilang"
    ],
    "wof:name":"Ban Naphilang",
    "wof:placetype":"locality"
},
  "geometry": {"coordinates":[105.86613,16.83705],"type":"Point"}
}