{
  "type": "Feature",
  "properties": {
    "gn:admin1_code":"19.0",
    "gn:asciiname":"Ban Vanggnau",
    "gn:country_code":"LA",
    "gn:dem":930,
    "gn:feature_class":"P",
    "gn:feature_code":"PPL",
    "gn:name":"Ban Vanggnau",
    "gn:population":0,
    "gn:timezone":"Asia/Vientiane",
    "iso:country":"LA",
    "name:lao_x_preferred":[
        "Ban Vanggnau"
    ],
    "name:und_x_variant":[
        "Ban Kang Nbao",
        "Ban Kang Nhao"
    ],
    "wof:name":"Ban Vanggnau",
    "wof:placetype":"locality"
},
  "geometry": {"coordinates":[106.20282,15.35014],"type":"Point"}
}