{
  "type": "Feature",
  "properties": {
    "gn:admin1_code":"17.0",
    "gn:asciiname":"Ban Pong-Tai",
    "gn:country_code":"LA",
    "gn:dem":762,
    "gn:feature_class":"P",
    "gn:feature_code":"PPL",
    "gn:name":"Ban Pong-Tai",
    "gn:population":0,
    "gn:timezone":"Asia/Vientiane",
    "iso:country":"LA",
    "name:lao_x_preferred":[
        "Ban Pong-Tai"
    ],
    "wof:name":"Ban Pong-Tai",
    "wof:placetype":"locality"
},
  "geometry": {"coordinates":[102.267,20.4107],"type":"Point"}
}