{
  "type": "Feature",
  "properties": {
    "gn:admin1_code":"20.0",
    "gn:asciiname":"Ban Khanmek",
    "gn:country_code":"LA",
    "gn:dem":185,
    "gn:feature_class":"P",
    "gn:feature_code":"PPL",
    "gn:name":"Ban Khanm\u00e8k",
    "gn:population":0,
    "gn:timezone":"Asia/Vientiane",
    "iso:country":"LA",
    "name:lao_x_preferred":[
        "Ban Khanm\u00e8k"
    ],
    "name:und_x_variant":[
        "Ban Kham Meck",
        "Kham Meck",
        "Khamm\u00e9k",
        "Ban Khamm\u00e9k"
    ],
    "wof:name":"Ban Khanmek",
    "wof:placetype":"locality"
},
  "geometry": {"coordinates":[105.53923,16.84737],"type":"Point"}
}