{
  "type": "Feature",
  "properties": {
    "gn:admin1_code":"3.0",
    "gn:asciiname":"Ban Son",
    "gn:country_code":"LA",
    "gn:dem":485,
    "gn:feature_class":"P",
    "gn:feature_code":"PPL",
    "gn:name":"Ban Son",
    "gn:population":0,
    "gn:timezone":"Asia/Vientiane",
    "iso:country":"LA",
    "wof:name":"Ban Son",
    "wof:placetype":"locality"
},
  "geometry": {"coordinates":[104.46666999999999,20.53333],"type":"Point"}
}