{
  "type": "Feature",
  "properties": {
    "gn:admin1_code":"19.0",
    "gn:asciiname":"Ban Tahouak",
    "gn:country_code":"LA",
    "gn:dem":404,
    "gn:feature_class":"P",
    "gn:feature_code":"PPL",
    "gn:name":"Ban Tahouak",
    "gn:population":0,
    "gn:timezone":"Asia/Vientiane",
    "iso:country":"LA",
    "name:lao_x_preferred":[
        "Ban Tahouak"
    ],
    "name:und_x_variant":[
        "Tavouac (3)",
        "Tavouac"
    ],
    "wof:name":"Ban Tahouak",
    "wof:placetype":"locality"
},
  "geometry": {"coordinates":[106.75841,16.26263],"type":"Point"}
}