{
  "type": "Feature",
  "properties": {
    "gn:admin1_code":"20.0",
    "gn:asciiname":"Ban Naphokhen",
    "gn:country_code":"LA",
    "gn:dem":183,
    "gn:feature_class":"P",
    "gn:feature_code":"PPL",
    "gn:name":"Ban Naph\u00f4kh\u00e8n",
    "gn:population":0,
    "gn:timezone":"Asia/Vientiane",
    "iso:country":"LA",
    "name:und_x_variant":[
        "Ban Napho",
        "Ban Napho Khene",
        "Ban Naph\u00f4kh\u00e8n"
    ],
    "wof:name":"Ban Naphokhen",
    "wof:placetype":"locality"
},
  "geometry": {"coordinates":[105.05464000000001,16.82935],"type":"Point"}
}