{
  "type": "Feature",
  "properties": {
    "gn:admin1_code":"18.0",
    "gn:asciiname":"Ban Choungloung",
    "gn:country_code":"LA",
    "gn:dem":819,
    "gn:feature_class":"P",
    "gn:feature_code":"PPL",
    "gn:name":"Ban Choungloung",
    "gn:population":0,
    "gn:timezone":"Asia/Vientiane",
    "iso:country":"LA",
    "name:lao_x_preferred":[
        "Ban Choungloung"
    ],
    "wof:name":"Ban Choungloung",
    "wof:placetype":"locality"
},
  "geometry": {"coordinates":[102.49952999999999,20.91628],"type":"Point"}
}