{
  "type": "Feature",
  "properties": {
    "gn:admin1_code":"3.0",
    "gn:asciiname":"Ban Houaykouan",
    "gn:country_code":"LA",
    "gn:dem":1020,
    "gn:feature_class":"P",
    "gn:feature_code":"PPL",
    "gn:name":"Ban Houaykouan",
    "gn:population":0,
    "gn:timezone":"Asia/Vientiane",
    "iso:country":"LA",
    "name:lao_x_preferred":[
        "Ban Houaykouan"
    ],
    "wof:name":"Ban Houaykouan",
    "wof:placetype":"locality"
},
  "geometry": {"coordinates":[104.33472,20.22747],"type":"Point"}
}