{
  "type": "Feature",
  "properties": {
    "gn:admin1_code":"16.0",
    "gn:asciiname":"Ban Tongmang",
    "gn:country_code":"LA",
    "gn:dem":1407,
    "gn:feature_class":"P",
    "gn:feature_code":"PPL",
    "gn:name":"Ban T\u00f4ngmang",
    "gn:population":0,
    "gn:timezone":"Asia/Vientiane",
    "iso:country":"LA",
    "name:lao_x_preferred":[
        "Ban T\u00f4ngmang"
    ],
    "wof:name":"Ban Tongmang",
    "wof:placetype":"locality"
},
  "geometry": {"coordinates":[101.03946000000001,20.35586],"type":"Point"}
}