{
  "type": "Feature",
  "properties": {
    "gn:admin1_code":"18.0",
    "gn:asciiname":"Ban Phiaachen-Noy",
    "gn:country_code":"LA",
    "gn:dem":916,
    "gn:feature_class":"P",
    "gn:feature_code":"PPL",
    "gn:name":"Ban Phiaach\u00e8n-Noy",
    "gn:population":0,
    "gn:timezone":"Asia/Vientiane",
    "iso:country":"LA",
    "name:lao_x_preferred":[
        "Ban Phiaach\u00e8n-Noy"
    ],
    "wof:name":"Ban Phiaachen-Noy",
    "wof:placetype":"locality"
},
  "geometry": {"coordinates":[101.78281,21.47194],"type":"Point"}
}