{
  "type": "Feature",
  "properties": {
    "gn:admin1_code":"20.0",
    "gn:asciiname":"Ban Koutthep",
    "gn:country_code":"LA",
    "gn:dem":178,
    "gn:feature_class":"P",
    "gn:feature_code":"PPL",
    "gn:name":"Ban Koutth\u00e9p",
    "gn:population":0,
    "gn:timezone":"Asia/Vientiane",
    "iso:country":"LA",
    "name:und_x_variant":[
        "Ban Song Peui",
        "Ban Koutth\u00e9p"
    ],
    "wof:name":"Ban Koutthep",
    "wof:placetype":"locality"
},
  "geometry": {"coordinates":[105.25852999999999,16.88585],"type":"Point"}
}