{
  "type": "Feature",
  "properties": {
    "gn:admin1_code":"13.0",
    "gn:asciiname":"Ban Laoli",
    "gn:country_code":"LA",
    "gn:dem":1681,
    "gn:feature_class":"P",
    "gn:feature_code":"PPL",
    "gn:name":"Ban Laoli",
    "gn:population":0,
    "gn:timezone":"Asia/Vientiane",
    "iso:country":"LA",
    "name:und_x_variant":[
        "Ban Lua Lai",
        "Ban Laoli"
    ],
    "wof:name":"Ban Laoli",
    "wof:placetype":"locality"
},
  "geometry": {"coordinates":[101.24002,19.35353],"type":"Point"}
}