{
  "type": "Feature",
  "properties": {
    "gn:admin1_code":"16.0",
    "gn:asciiname":"Sop Tialeng",
    "gn:country_code":"LA",
    "gn:dem":463,
    "gn:feature_class":"P",
    "gn:feature_code":"PPL",
    "gn:name":"Sop Tialeng",
    "gn:population":0,
    "gn:timezone":"Asia/Vientiane",
    "iso:country":"LA",
    "wof:name":"Sop Tialeng",
    "wof:placetype":"locality"
},
  "geometry": {"coordinates":[101.45,20.53333],"type":"Point"}
}