{
  "type": "Feature",
  "properties": {
    "gn:admin1_code":"3.0",
    "gn:asciiname":"Ban Houayngeum",
    "gn:country_code":"LA",
    "gn:dem":584,
    "gn:feature_class":"P",
    "gn:feature_code":"PPL",
    "gn:name":"Ban Houayngeum",
    "gn:population":0,
    "gn:timezone":"Asia/Vientiane",
    "iso:country":"LA",
    "name:lao_x_preferred":[
        "Ban Houayngeum"
    ],
    "name:und_x_variant":[
        "Ban Huoi Ngeum"
    ],
    "wof:name":"Ban Houayngeum",
    "wof:placetype":"locality"
},
  "geometry": {"coordinates":[104.41213999999999,20.74216],"type":"Point"}
}