{
  "type": "Feature",
  "properties": {
    "gn:admin1_code":"20.0",
    "gn:asciiname":"Ban Xethamouak",
    "gn:country_code":"LA",
    "gn:dem":161,
    "gn:feature_class":"P",
    "gn:feature_code":"PPL",
    "gn:name":"Ban X\u00e8thamouak",
    "gn:population":0,
    "gn:timezone":"Asia/Vientiane",
    "iso:country":"LA",
    "name:lao_x_preferred":[
        "Ban X\u00e8thamouak"
    ],
    "wof:name":"Ban Xethamouak",
    "wof:placetype":"locality"
},
  "geometry": {"coordinates":[105.6875,16.43254],"type":"Point"}
}