{
  "type": "Feature",
  "properties": {
    "gn:admin1_code":"2.0",
    "gn:asciiname":"Ban Salao",
    "gn:country_code":"LA",
    "gn:dem":105,
    "gn:feature_class":"P",
    "gn:feature_code":"PPL",
    "gn:name":"Ban Salao",
    "gn:population":0,
    "gn:timezone":"Asia/Vientiane",
    "iso:country":"LA",
    "name:und_x_variant":[
        "Ban Salaou",
        "Ban Salao"
    ],
    "wof:name":"Ban Salao",
    "wof:placetype":"locality"
},
  "geometry": {"coordinates":[105.82411,15.07343],"type":"Point"}
}