{
  "type": "Feature",
  "properties": {
    "gn:admin1_code":"7.0",
    "gn:asciiname":"Ban Chanmai",
    "gn:country_code":"LA",
    "gn:dem":683,
    "gn:feature_class":"P",
    "gn:feature_code":"PPL",
    "gn:name":"Ban Chanmai",
    "gn:population":0,
    "gn:timezone":"Asia/Vientiane",
    "iso:country":"LA",
    "name:lao_x_preferred":[
        "Ban Chanmai"
    ],
    "wof:name":"Ban Chanmai",
    "wof:placetype":"locality"
},
  "geometry": {"coordinates":[101.30732,20.31403],"type":"Point"}
}