{
  "type": "Feature",
  "properties": {
    "gn:admin1_code":"13.0",
    "gn:asciiname":"Ban Khum",
    "gn:country_code":"LA",
    "gn:dem":572,
    "gn:feature_class":"P",
    "gn:feature_code":"PPL",
    "gn:name":"Ban Khum",
    "gn:population":0,
    "gn:timezone":"Asia/Vientiane",
    "iso:country":"LA",
    "name:lao_x_preferred":[
        "Ban Khum"
    ],
    "wof:name":"Ban Khum",
    "wof:placetype":"locality"
},
  "geometry": {"coordinates":[101.11045,17.74892000000001],"type":"Point"}
}