{
  "type": "Feature",
  "properties": {
    "gn:admin1_code":"27.0",
    "gn:asciiname":"Ban Naman Noy",
    "gn:country_code":"LA",
    "gn:dem":436,
    "gn:feature_class":"P",
    "gn:feature_code":"PPL",
    "gn:name":"Ban Naman Noy",
    "gn:population":0,
    "gn:timezone":"Asia/Vientiane",
    "iso:country":"LA",
    "name:und_x_variant":[
        "Ban Na Mon Noi",
        "Ban Naman Noy"
    ],
    "wof:name":"Ban Naman Noy",
    "wof:placetype":"locality"
},
  "geometry": {"coordinates":[102.28333000000001,19.25],"type":"Point"}
}