{
  "type": "Feature",
  "properties": {
    "gn:admin1_code":"13.0",
    "gn:asciiname":"Ban Namthouan",
    "gn:country_code":"LA",
    "gn:dem":1054,
    "gn:feature_class":"P",
    "gn:feature_code":"PPL",
    "gn:name":"Ban Namthouan",
    "gn:population":0,
    "gn:timezone":"Asia/Vientiane",
    "iso:country":"LA",
    "name:lao_x_preferred":[
        "Ban Namthouan"
    ],
    "wof:name":"Ban Namthouan",
    "wof:placetype":"locality"
},
  "geometry": {"coordinates":[101.03446,19.79138],"type":"Point"}
}