{
  "type": "Feature",
  "properties": {
    "gn:admin1_code":"15.0",
    "gn:asciiname":"Ban Thanamkeo",
    "gn:country_code":"LA",
    "gn:dem":160,
    "gn:feature_class":"P",
    "gn:feature_code":"PPL",
    "gn:name":"Ban Thanamk\u00e8o",
    "gn:population":0,
    "gn:timezone":"Asia/Vientiane",
    "iso:country":"LA",
    "name:lao_x_preferred":[
        "Ban Thanamk\u00e8o"
    ],
    "wof:name":"Ban Thanamkeo",
    "wof:placetype":"locality"
},
  "geometry": {"coordinates":[104.46468,17.70658],"type":"Point"}
}