{
  "type": "Feature",
  "properties": {
    "gn:admin1_code":"13.0",
    "gn:asciiname":"Ban Napho",
    "gn:country_code":"LA",
    "gn:dem":282,
    "gn:feature_class":"P",
    "gn:feature_code":"PPL",
    "gn:name":"Ban Naph\u00f4",
    "gn:population":0,
    "gn:timezone":"Asia/Vientiane",
    "iso:country":"LA",
    "name:lao_x_preferred":[
        "Ban Naph\u00f4"
    ],
    "wof:name":"Ban Napho",
    "wof:placetype":"locality"
},
  "geometry": {"coordinates":[101.55087,18.46913],"type":"Point"}
}