{
  "type": "Feature",
  "properties": {
    "gn:admin1_code":"1.0",
    "gn:asciiname":"Ban Pliat",
    "gn:country_code":"LA",
    "gn:dem":1020,
    "gn:feature_class":"P",
    "gn:feature_code":"PPL",
    "gn:name":"Ban Pliat",
    "gn:population":0,
    "gn:timezone":"Asia/Vientiane",
    "iso:country":"LA",
    "name:und_x_variant":[
        "Ban Priet",
        "Ban Priat",
        "Ban Pliat"
    ],
    "wof:name":"Ban Pliat",
    "wof:placetype":"locality"
},
  "geometry": {"coordinates":[107.11332,15.23579],"type":"Point"}
}