{
  "type": "Feature",
  "properties": {
    "gn:admin1_code":"20.0",
    "gn:asciiname":"Ban Houahat-Gnai",
    "gn:country_code":"LA",
    "gn:dem":145,
    "gn:feature_class":"P",
    "gn:feature_code":"PPL",
    "gn:name":"Ban Houahat-Gnai",
    "gn:population":0,
    "gn:timezone":"Asia/Vientiane",
    "iso:country":"LA",
    "name:lao_x_preferred":[
        "Ban Houahat-Gnai"
    ],
    "wof:name":"Ban Houahat-Gnai",
    "wof:placetype":"locality"
},
  "geometry": {"coordinates":[104.88924,16.37844],"type":"Point"}
}