{
  "type": "Feature",
  "properties": {
    "gn:admin1_code":"22.0",
    "gn:asciiname":"Ban Panna",
    "gn:country_code":"LA",
    "gn:dem":674,
    "gn:feature_class":"P",
    "gn:feature_code":"PPL",
    "gn:name":"Ban Panna",
    "gn:population":0,
    "gn:timezone":"Asia/Vientiane",
    "iso:country":"LA",
    "name:lao_x_preferred":[
        "Ban Panna"
    ],
    "wof:name":"Ban Panna",
    "wof:placetype":"locality"
},
  "geometry": {"coordinates":[100.39673000000001,20.47979],"type":"Point"}
}