{
  "type": "Feature",
  "properties": {
    "gn:admin1_code":"3.0",
    "gn:asciiname":"Ban Thamla-Nua",
    "gn:country_code":"LA",
    "gn:dem":1275,
    "gn:feature_class":"P",
    "gn:feature_code":"PPL",
    "gn:name":"Ban Thamla-Nua",
    "gn:population":0,
    "gn:timezone":"Asia/Vientiane",
    "iso:country":"LA",
    "name:und_x_variant":[
        "Tam La",
        "Thamla",
        "Ban Thamla-Nua"
    ],
    "wof:name":"Ban Thamla-Nua",
    "wof:placetype":"locality"
},
  "geometry": {"coordinates":[103.44455000000001,19.92763],"type":"Point"}
}