{
  "type": "Feature",
  "properties": {
    "gn:admin1_code":"14.0",
    "gn:asciiname":"Ban Kaliang-Noi",
    "gn:country_code":"LA",
    "gn:dem":1351,
    "gn:feature_class":"P",
    "gn:feature_code":"PPL",
    "gn:name":"Ban Kaliang-Noi",
    "gn:population":0,
    "gn:timezone":"Asia/Vientiane",
    "iso:country":"LA",
    "name:lao_x_preferred":[
        "Ban Kaliang-Noi"
    ],
    "wof:name":"Ban Kaliang-Noi",
    "wof:placetype":"locality"
},
  "geometry": {"coordinates":[103.39541,19.47113],"type":"Point"}
}