{
  "type": "Feature",
  "properties": {
    "gn:admin1_code":"20.0",
    "gn:asciiname":"Ban Kalouk-Mai",
    "gn:country_code":"LA",
    "gn:dem":230,
    "gn:feature_class":"P",
    "gn:feature_code":"PPL",
    "gn:name":"Ban Kalouk-Mai",
    "gn:population":0,
    "gn:timezone":"Asia/Vientiane",
    "iso:country":"LA",
    "name:lao_x_preferred":[
        "Ban Kalouk-Mai"
    ],
    "wof:name":"Ban Kalouk-Mai",
    "wof:placetype":"locality"
},
  "geometry": {"coordinates":[106.31507999999999,16.69329],"type":"Point"}
}