{
  "type": "Feature",
  "properties": {
    "gn:admin1_code":"7.0",
    "gn:asciiname":"Ban Kioulom",
    "gn:country_code":"LA",
    "gn:dem":467,
    "gn:feature_class":"P",
    "gn:feature_code":"PPL",
    "gn:name":"Ban Kioul\u00f4m",
    "gn:population":0,
    "gn:timezone":"Asia/Vientiane",
    "iso:country":"LA",
    "name:lao_x_preferred":[
        "Ban Kioul\u00f4m"
    ],
    "wof:name":"Ban Kioulom",
    "wof:placetype":"locality"
},
  "geometry": {"coordinates":[102.13643,20.8397],"type":"Point"}
}