{
  "type": "Feature",
  "properties": {
    "gn:admin1_code":"2.0",
    "gn:asciiname":"Champi Noy",
    "gn:country_code":"LA",
    "gn:dem":1174,
    "gn:feature_class":"P",
    "gn:feature_code":"PPL",
    "gn:name":"Champi Noy",
    "gn:population":0,
    "gn:timezone":"Asia/Vientiane",
    "iso:country":"LA",
    "name:und_x_variant":[
        "Ban Champi Noi",
        "Champi Noi",
        "Champi Noy"
    ],
    "wof:name":"Champi Noy",
    "wof:placetype":"locality"
},
  "geometry": {"coordinates":[106.34999999999999,15.08333],"type":"Point"}
}