{
  "type": "Feature",
  "properties": {
    "gn:admin1_code":"3.0",
    "gn:asciiname":"Ban Peu",
    "gn:country_code":"LA",
    "gn:dem":630,
    "gn:feature_class":"P",
    "gn:feature_code":"PPL",
    "gn:name":"Ban Peu",
    "gn:population":0,
    "gn:timezone":"Asia/Vientiane",
    "iso:country":"LA",
    "name:und_x_variant":[
        "Muong Peu",
        "Muang Peu",
        "Ban Peu"
    ],
    "wof:name":"Ban Peu",
    "wof:placetype":"locality"
},
  "geometry": {"coordinates":[103.40204,20.72032],"type":"Point"}
}