{
  "type": "Feature",
  "properties": {
    "gn:admin1_code":"3.0",
    "gn:asciiname":"Ban Houaykhai",
    "gn:country_code":"LA",
    "gn:dem":1092,
    "gn:feature_class":"P",
    "gn:feature_code":"PPL",
    "gn:name":"Ban Houaykhai",
    "gn:population":0,
    "gn:timezone":"Asia/Vientiane",
    "iso:country":"LA",
    "name:und_x_variant":[
        "Ban Houei Khai",
        "Ban Houaykhai"
    ],
    "wof:name":"Ban Houaykhai",
    "wof:placetype":"locality"
},
  "geometry": {"coordinates":[103.96696,20.42683],"type":"Point"}
}