{
  "type": "Feature",
  "properties": {
    "gn:admin1_code":"27.0",
    "gn:asciiname":"Ban Phouphong",
    "gn:country_code":"LA",
    "gn:dem":450,
    "gn:feature_class":"P",
    "gn:feature_code":"PPL",
    "gn:name":"Ban Phouph\u00f4ng",
    "gn:population":0,
    "gn:timezone":"Asia/Vientiane",
    "iso:country":"LA",
    "name:lao_x_preferred":[
        "Ban Phouph\u00f4ng"
    ],
    "wof:name":"Ban Phouphong",
    "wof:placetype":"locality"
},
  "geometry": {"coordinates":[102.44349,19.05702],"type":"Point"}
}