{
  "type": "Feature",
  "properties": {
    "gn:admin1_code":"24.0",
    "gn:asciiname":"Ban Phonmouang",
    "gn:country_code":"LA",
    "gn:dem":178,
    "gn:feature_class":"P",
    "gn:feature_code":"PPL",
    "gn:name":"Ban Ph\u00f4nmouang",
    "gn:population":0,
    "gn:timezone":"Asia/Vientiane",
    "iso:country":"LA",
    "name:und_x_variant":[
        "Ban Ph\u00f4nmouang",
        "Ban Ph\u00f4n Muang"
    ],
    "wof:name":"Ban Phonmouang",
    "wof:placetype":"locality"
},
  "geometry": {"coordinates":[102.4988,18.21394],"type":"Point"}
}