{
  "type": "Feature",
  "properties": {
    "gn:admin1_code":"26.0",
    "gn:asciiname":"Ban Tanang",
    "gn:country_code":"LA",
    "gn:dem":557,
    "gn:feature_class":"P",
    "gn:feature_code":"PPL",
    "gn:name":"Ban Tanang",
    "gn:population":0,
    "gn:timezone":"Asia/Vientiane",
    "iso:country":"LA",
    "name:lao_x_preferred":[
        "Ban Tanang"
    ],
    "wof:name":"Ban Tanang",
    "wof:placetype":"locality"
},
  "geometry": {"coordinates":[107.05049,15.89903],"type":"Point"}
}