{
  "type": "Feature",
  "properties": {
    "gn:admin1_code":"16.0",
    "gn:asciiname":"Ban Texa",
    "gn:country_code":"LA",
    "gn:dem":645,
    "gn:feature_class":"P",
    "gn:feature_code":"PPL",
    "gn:name":"Ban T\u00e8xa",
    "gn:population":0,
    "gn:timezone":"Asia/Vientiane",
    "iso:country":"LA",
    "name:lao_x_preferred":[
        "Ban T\u00e8xa"
    ],
    "wof:name":"Ban Texa",
    "wof:placetype":"locality"
},
  "geometry": {"coordinates":[101.01993,21.05846],"type":"Point"}
}