{
  "type": "Feature",
  "properties": {
    "gn:admin1_code":"16.0",
    "gn:asciiname":"Ban Mokkha",
    "gn:country_code":"LA",
    "gn:dem":827,
    "gn:feature_class":"P",
    "gn:feature_code":"PPL",
    "gn:name":"Ban M\u00f4kkha",
    "gn:population":0,
    "gn:timezone":"Asia/Vientiane",
    "iso:country":"LA",
    "name:lao_x_preferred":[
        "Ban M\u00f4kkha"
    ],
    "wof:name":"Ban Mokkha",
    "wof:placetype":"locality"
},
  "geometry": {"coordinates":[101.38619,20.45621],"type":"Point"}
}