{
  "type": "Feature",
  "properties": {
    "gn:admin1_code":"7.0",
    "gn:asciiname":"Ban Mokplai",
    "gn:country_code":"LA",
    "gn:dem":735,
    "gn:feature_class":"P",
    "gn:feature_code":"PPL",
    "gn:name":"Ban M\u00f4kplai",
    "gn:population":0,
    "gn:timezone":"Asia/Vientiane",
    "iso:country":"LA",
    "name:lao_x_preferred":[
        "Ban M\u00f4kplai"
    ],
    "name:und_x_variant":[
        "Ban M\u00f4kprai"
    ],
    "wof:name":"Ban Mokplai",
    "wof:placetype":"locality"
},
  "geometry": {"coordinates":[102.15170999999999,20.12702],"type":"Point"}
}