{
  "type": "Feature",
  "properties": {
    "gn:admin1_code":"2.0",
    "gn:asciiname":"Ban Ke",
    "gn:country_code":"LA",
    "gn:dem":103,
    "gn:feature_class":"P",
    "gn:feature_code":"PPL",
    "gn:name":"Ban K\u00e8",
    "gn:population":0,
    "gn:timezone":"Asia/Vientiane",
    "iso:country":"LA",
    "name:lao_x_preferred":[
        "Ban K\u00e8"
    ],
    "wof:name":"Ban Ke",
    "wof:placetype":"locality"
},
  "geometry": {"coordinates":[105.81289,15.12556],"type":"Point"}
}