{
  "type": "Feature",
  "properties": {
    "gn:admin1_code":"17.0",
    "gn:asciiname":"Ban Lang-Uat",
    "gn:country_code":"LA",
    "gn:dem":699,
    "gn:feature_class":"P",
    "gn:feature_code":"PPL",
    "gn:name":"Ban Lang-Uat",
    "gn:population":0,
    "gn:timezone":"Asia/Vientiane",
    "iso:country":"LA",
    "name:lao_x_preferred":[
        "Ban Lang-Uat"
    ],
    "wof:name":"Ban Lang-Uat",
    "wof:placetype":"locality"
},
  "geometry": {"coordinates":[102.70292999999999,20.89306],"type":"Point"}
}