{
  "type": "Feature",
  "properties": {
    "gn:admin1_code":"18.0",
    "gn:asciiname":"Ban Houayngeun",
    "gn:country_code":"LA",
    "gn:dem":632,
    "gn:feature_class":"P",
    "gn:feature_code":"PPL",
    "gn:name":"Ban Houayngeun",
    "gn:population":0,
    "gn:timezone":"Asia/Vientiane",
    "iso:country":"LA",
    "name:lao_x_preferred":[
        "Ban Houayngeun"
    ],
    "wof:name":"Ban Houayngeun",
    "wof:placetype":"locality"
},
  "geometry": {"coordinates":[102.89362,21.5999],"type":"Point"}
}