{
  "type": "Feature",
  "properties": {
    "gn:admin1_code":"16.0",
    "gn:asciiname":"Ban Yao",
    "gn:country_code":"LA",
    "gn:dem":1065,
    "gn:feature_class":"P",
    "gn:feature_code":"PPL",
    "gn:name":"Ban Yao",
    "gn:population":0,
    "gn:timezone":"Asia/Vientiane",
    "iso:country":"LA",
    "name:lao_x_preferred":[
        "Ban Yao"
    ],
    "wof:name":"Ban Yao",
    "wof:placetype":"locality"
},
  "geometry": {"coordinates":[100.99226,21.07845],"type":"Point"}
}