{
  "type": "Feature",
  "properties": {
    "gn:admin1_code":"20.0",
    "gn:asciiname":"Ban Manilat",
    "gn:country_code":"LA",
    "gn:dem":163,
    "gn:feature_class":"P",
    "gn:feature_code":"PPL",
    "gn:name":"Ban Manilat",
    "gn:population":0,
    "gn:timezone":"Asia/Vientiane",
    "iso:country":"LA",
    "name:lao_x_preferred":[
        "Ban Manilat"
    ],
    "wof:name":"Ban Manilat",
    "wof:placetype":"locality"
},
  "geometry": {"coordinates":[104.98818,17.07126],"type":"Point"}
}