{
  "type": "Feature",
  "properties": {
    "gn:admin1_code":"14.0",
    "gn:asciiname":"Ban Nabong",
    "gn:country_code":"LA",
    "gn:dem":1238,
    "gn:feature_class":"P",
    "gn:feature_code":"PPL",
    "gn:name":"Ban Nab\u00f4ng",
    "gn:population":0,
    "gn:timezone":"Asia/Vientiane",
    "iso:country":"LA",
    "name:und_x_variant":[
        "Ban Nab\u00f4ng",
        "Ban Nalong"
    ],
    "wof:name":"Ban Nabong",
    "wof:placetype":"locality"
},
  "geometry": {"coordinates":[103.62567,19.26723],"type":"Point"}
}