{
  "type": "Feature",
  "properties": {
    "gn:admin1_code":"22.0",
    "gn:asciiname":"Ban Pamaignang",
    "gn:country_code":"LA",
    "gn:dem":422,
    "gn:feature_class":"P",
    "gn:feature_code":"PPL",
    "gn:name":"Ban Pamaignang",
    "gn:population":0,
    "gn:timezone":"Asia/Vientiane",
    "iso:country":"LA",
    "name:lao_x_preferred":[
        "Ban Pamaignang"
    ],
    "wof:name":"Ban Pamaignang",
    "wof:placetype":"locality"
},
  "geometry": {"coordinates":[100.51246,20.29927],"type":"Point"}
}