{
  "type": "Feature",
  "properties": {
    "gn:admin1_code":"18.0",
    "gn:asciiname":"Mok Troi",
    "gn:country_code":"LA",
    "gn:dem":643,
    "gn:feature_class":"P",
    "gn:feature_code":"PPL",
    "gn:name":"Mok Troi",
    "gn:population":0,
    "gn:timezone":"Asia/Vientiane",
    "iso:country":"LA",
    "wof:name":"Mok Troi",
    "wof:placetype":"locality"
},
  "geometry": {"coordinates":[102.40000000000001,21.06667],"type":"Point"}
}