{
  "type": "Feature",
  "properties": {
    "gn:admin1_code":"17.0",
    "gn:asciiname":"Ban Houaysaliang",
    "gn:country_code":"LA",
    "gn:dem":1130,
    "gn:feature_class":"P",
    "gn:feature_code":"PPL",
    "gn:name":"Ban Houaysaliang",
    "gn:population":0,
    "gn:timezone":"Asia/Vientiane",
    "iso:country":"LA",
    "name:lao_x_preferred":[
        "Ban Houaysaliang"
    ],
    "wof:name":"Ban Houaysaliang",
    "wof:placetype":"locality"
},
  "geometry": {"coordinates":[102.84756,20.28249],"type":"Point"}
}