{
  "type": "Feature",
  "properties": {
    "gn:admin1_code":"27.0",
    "gn:asciiname":"Ban Longyen",
    "gn:country_code":"LA",
    "gn:dem":1137,
    "gn:feature_class":"P",
    "gn:feature_code":"PPL",
    "gn:name":"Ban Longy\u00e8n",
    "gn:population":0,
    "gn:timezone":"Asia/Vientiane",
    "iso:country":"LA",
    "name:lao_x_preferred":[
        "Ban Longy\u00e8n"
    ],
    "wof:name":"Ban Longyen",
    "wof:placetype":"locality"
},
  "geometry": {"coordinates":[102.4012,19.23506],"type":"Point"}
}