{
  "type": "Feature",
  "properties": {
    "gn:admin1_code":"1.0",
    "gn:asciiname":"Ban Dakke",
    "gn:country_code":"LA",
    "gn:dem":1063,
    "gn:feature_class":"P",
    "gn:feature_code":"PPL",
    "gn:name":"Ban Dakk\u00e8",
    "gn:population":0,
    "gn:timezone":"Asia/Vientiane",
    "iso:country":"LA",
    "name:und_x_variant":[
        "Ban Khe",
        "Ban Dakk\u00e8"
    ],
    "wof:name":"Ban Dakke",
    "wof:placetype":"locality"
},
  "geometry": {"coordinates":[107.11324999999999,15.23093],"type":"Point"}
}