{
  "type": "Feature",
  "properties": {
    "gn:admin1_code":"16.0",
    "gn:asciiname":"Ban Houn",
    "gn:country_code":"LA",
    "gn:dem":459,
    "gn:feature_class":"P",
    "gn:feature_code":"PPL",
    "gn:name":"Ban Houn",
    "gn:population":0,
    "gn:timezone":"Asia/Vientiane",
    "iso:country":"LA",
    "name:lao_x_preferred":[
        "Ban Houn"
    ],
    "wof:name":"Ban Houn",
    "wof:placetype":"locality"
},
  "geometry": {"coordinates":[101.34187,20.43551],"type":"Point"}
}