{
  "type": "Feature",
  "properties": {
    "gn:admin1_code":"16.0",
    "gn:asciiname":"Ban Namloung",
    "gn:country_code":"LA",
    "gn:dem":1115,
    "gn:feature_class":"P",
    "gn:feature_code":"PPL",
    "gn:name":"Ban Namloung",
    "gn:population":0,
    "gn:timezone":"Asia/Vientiane",
    "iso:country":"LA",
    "name:lao_x_preferred":[
        "Ban Namloung"
    ],
    "wof:name":"Ban Namloung",
    "wof:placetype":"locality"
},
  "geometry": {"coordinates":[101.28989,20.57446],"type":"Point"}
}