{
  "type": "Feature",
  "properties": {
    "gn:admin1_code":"3.0",
    "gn:asciiname":"Ban Ngouam",
    "gn:country_code":"LA",
    "gn:dem":337,
    "gn:feature_class":"P",
    "gn:feature_code":"PPL",
    "gn:name":"Ban Ngouam",
    "gn:population":0,
    "gn:timezone":"Asia/Vientiane",
    "iso:country":"LA",
    "name:und_x_variant":[
        "Ban Na Noua",
        "Ban Na Ngua",
        "Ban Na Ngoa",
        "Ban Ngouam"
    ],
    "wof:name":"Ban Ngouam",
    "wof:placetype":"locality"
},
  "geometry": {"coordinates":[104.12938,20.76129],"type":"Point"}
}