{
  "type": "Feature",
  "properties": {
    "gn:admin1_code":"3.0",
    "gn:asciiname":"Ban Homthong",
    "gn:country_code":"LA",
    "gn:dem":644,
    "gn:feature_class":"P",
    "gn:feature_code":"PPL",
    "gn:name":"Ban H\u00f4mthong",
    "gn:population":0,
    "gn:timezone":"Asia/Vientiane",
    "iso:country":"LA",
    "name:lao_x_preferred":[
        "Ban H\u00f4mthong"
    ],
    "wof:name":"Ban Homthong",
    "wof:placetype":"locality"
},
  "geometry": {"coordinates":[103.60514000000001,20.04375],"type":"Point"}
}