{
  "type": "Feature",
  "properties": {
    "gn:admin1_code":"26.0",
    "gn:asciiname":"Ban Katlup",
    "gn:country_code":"LA",
    "gn:dem":747,
    "gn:feature_class":"P",
    "gn:feature_code":"PPL",
    "gn:name":"Ban Katlup",
    "gn:population":0,
    "gn:timezone":"Asia/Vientiane",
    "iso:country":"LA",
    "name:lao_x_preferred":[
        "Ban Katlup"
    ],
    "name:und_x_variant":[
        "Ban Katrup"
    ],
    "wof:name":"Ban Katlup",
    "wof:placetype":"locality"
},
  "geometry": {"coordinates":[107.02231,15.89262],"type":"Point"}
}