{
  "type": "Feature",
  "properties": {
    "gn:admin1_code":"3.0",
    "gn:asciiname":"Ban Mon",
    "gn:country_code":"LA",
    "gn:dem":1058,
    "gn:feature_class":"P",
    "gn:feature_code":"PPL",
    "gn:name":"Ban Mon",
    "gn:population":0,
    "gn:timezone":"Asia/Vientiane",
    "iso:country":"LA",
    "name:und_x_variant":[
        "Ban Mone",
        "Ban Mon"
    ],
    "wof:name":"Ban Mon",
    "wof:placetype":"locality"
},
  "geometry": {"coordinates":[103.94259,19.8262],"type":"Point"}
}