{
  "type": "Feature",
  "properties": {
    "gn:admin1_code":"14.0",
    "gn:asciiname":"Ban Houayxaykhao",
    "gn:cc2":"LA",
    "gn:country_code":"LA",
    "gn:dem":1199,
    "gn:feature_class":"P",
    "gn:feature_code":"PPL",
    "gn:name":"Ban Houayxaykhao",
    "gn:population":0,
    "gn:timezone":"Asia/Vientiane",
    "iso:country":"LA",
    "name:und_x_variant":[
        "Ban Houei Xai Khao",
        "Ban Houayxaykhao"
    ],
    "wof:name":"Ban Houayxaykhao",
    "wof:placetype":"locality"
},
  "geometry": {"coordinates":[103.84999999999999,19.23333],"type":"Point"}
}