{
  "type": "Feature",
  "properties": {
    "gn:admin1_code":"14.0",
    "gn:asciiname":"Ban Nada",
    "gn:country_code":"LA",
    "gn:dem":522,
    "gn:feature_class":"P",
    "gn:feature_code":"PPL",
    "gn:name":"Ban Nada",
    "gn:population":0,
    "gn:timezone":"Asia/Vientiane",
    "iso:country":"LA",
    "name:lao_x_preferred":[
        "Ban Nada"
    ],
    "wof:name":"Ban Nada",
    "wof:placetype":"locality"
},
  "geometry": {"coordinates":[103.68773,19.59879],"type":"Point"}
}