{
  "type": "Feature",
  "properties": {
    "gn:admin1_code":"14.0",
    "gn:asciiname":"Ban Thang",
    "gn:cc2":"LA",
    "gn:country_code":"LA",
    "gn:dem":1056,
    "gn:feature_class":"P",
    "gn:feature_code":"PPL",
    "gn:name":"Ban Thang",
    "gn:population":0,
    "gn:timezone":"Asia/Vientiane",
    "iso:country":"LA",
    "name:und_x_variant":[
        "Ban Tha",
        "Ban Thang"
    ],
    "wof:name":"Ban Thang",
    "wof:placetype":"locality"
},
  "geometry": {"coordinates":[103.41667,19.55],"type":"Point"}
}