{
  "type": "Feature",
  "properties": {
    "gn:admin1_code":"24.0",
    "gn:asciiname":"Ban Gnangxoum",
    "gn:country_code":"LA",
    "gn:dem":170,
    "gn:feature_class":"P",
    "gn:feature_code":"PPL",
    "gn:name":"Ban Gnangxoum",
    "gn:population":0,
    "gn:timezone":"Asia/Vientiane",
    "iso:country":"LA",
    "name:lao_x_preferred":[
        "Ban Gnangxoum"
    ],
    "wof:name":"Ban Gnangxoum",
    "wof:placetype":"locality"
},
  "geometry": {"coordinates":[102.64991000000001,18.01742],"type":"Point"}
}