{
  "type": "Feature",
  "properties": {
    "gn:admin1_code":"17.0",
    "gn:asciiname":"Ban Hat-Houay",
    "gn:country_code":"LA",
    "gn:dem":331,
    "gn:feature_class":"P",
    "gn:feature_code":"PPL",
    "gn:name":"Ban Hat-Houay",
    "gn:population":0,
    "gn:timezone":"Asia/Vientiane",
    "iso:country":"LA",
    "name:lao_x_preferred":[
        "Ban Hat-Houay"
    ],
    "name:und_x_variant":[
        "Ban Houei Tong",
        "Ban Houay Tong",
        "Ban Hat Houai"
    ],
    "wof:name":"Ban Hat-Houay",
    "wof:placetype":"locality"
},
  "geometry": {"coordinates":[102.41656,20.09519],"type":"Point"}
}