{
  "type": "Feature",
  "properties": {
    "gn:admin1_code":"20.0",
    "gn:asciiname":"Ban Pongchik",
    "gn:cc2":"LA",
    "gn:country_code":"LA",
    "gn:dem":868,
    "gn:feature_class":"P",
    "gn:feature_code":"PPL",
    "gn:name":"Ban Pongchik",
    "gn:population":0,
    "gn:timezone":"Asia/Vientiane",
    "iso:country":"LA",
    "name:und_x_variant":[
        "Ban Tek",
        "Ban Pongchik"
    ],
    "wof:name":"Ban Pongchik",
    "wof:placetype":"locality"
},
  "geometry": {"coordinates":[106.28333000000001,16.93333],"type":"Point"}
}