{
  "type": "Feature",
  "properties": {
    "gn:admin1_code":"14.0",
    "gn:asciiname":"Ban Thoum",
    "gn:country_code":"LA",
    "gn:dem":1166,
    "gn:feature_class":"P",
    "gn:feature_code":"PPL",
    "gn:name":"Ban Thoum",
    "gn:population":0,
    "gn:timezone":"Asia/Vientiane",
    "iso:country":"LA",
    "name:lao_x_preferred":[
        "Ban Thoum"
    ],
    "wof:name":"Ban Thoum",
    "wof:placetype":"locality"
},
  "geometry": {"coordinates":[103.21558,19.20911],"type":"Point"}
}