{
  "type": "Feature",
  "properties": {
    "gn:admin1_code":"7.0",
    "gn:asciiname":"Ban Longya",
    "gn:country_code":"LA",
    "gn:dem":506,
    "gn:feature_class":"P",
    "gn:feature_code":"PPL",
    "gn:name":"Ban Longya",
    "gn:population":0,
    "gn:timezone":"Asia/Vientiane",
    "iso:country":"LA",
    "name:und_x_variant":[
        "Longya",
        "Lang Ya",
        "Ban Longya"
    ],
    "wof:name":"Ban Longya",
    "wof:placetype":"locality"
},
  "geometry": {"coordinates":[102.12332000000001,20.80834],"type":"Point"}
}