{
  "type": "Feature",
  "properties": {
    "gn:admin1_code":"2.0",
    "gn:asciiname":"Ban Naxon",
    "gn:country_code":"LA",
    "gn:dem":112,
    "gn:feature_class":"P",
    "gn:feature_code":"PPL",
    "gn:name":"Ban Naxon",
    "gn:population":0,
    "gn:timezone":"Asia/Vientiane",
    "iso:country":"LA",
    "name:und_x_variant":[
        "Ban Nas\u00f4ne",
        "Ban Naxon"
    ],
    "wof:name":"Ban Naxon",
    "wof:placetype":"locality"
},
  "geometry": {"coordinates":[105.75003,15.23415],"type":"Point"}
}