{
  "type": "Feature",
  "properties": {
    "gn:admin1_code":"20.0",
    "gn:asciiname":"Ban Kengleng",
    "gn:country_code":"LA",
    "gn:dem":150,
    "gn:feature_class":"P",
    "gn:feature_code":"PPL",
    "gn:name":"Ban K\u00e8ngl\u00e8ng",
    "gn:population":0,
    "gn:timezone":"Asia/Vientiane",
    "iso:country":"LA",
    "name:und_x_variant":[
        "Ban Keng Heng",
        "Ban K\u00e8ngl\u00e8ng"
    ],
    "wof:name":"Ban Kengleng",
    "wof:placetype":"locality"
},
  "geometry": {"coordinates":[105.07126,17.06694],"type":"Point"}
}