{
  "type": "Feature",
  "properties": {
    "gn:admin1_code":"20.0",
    "gn:asciiname":"Ban Phoxai-Mai",
    "gn:country_code":"LA",
    "gn:dem":197,
    "gn:feature_class":"P",
    "gn:feature_code":"PPL",
    "gn:name":"Ban Ph\u00f4xai-Mai",
    "gn:population":0,
    "gn:timezone":"Asia/Vientiane",
    "iso:country":"LA",
    "name:lao_x_preferred":[
        "Ban Ph\u00f4xai-Mai"
    ],
    "name:und_x_variant":[
        "Ban Phosay",
        "Ban Ph\u00f4xai"
    ],
    "wof:name":"Ban Phoxai-Mai",
    "wof:placetype":"locality"
},
  "geometry": {"coordinates":[105.01406,16.46501],"type":"Point"}
}