{
  "type": "Feature",
  "properties": {
    "gn:admin1_code":"3.0",
    "gn:asciiname":"Ban Bong",
    "gn:country_code":"LA",
    "gn:dem":733,
    "gn:feature_class":"P",
    "gn:feature_code":"PPL",
    "gn:name":"Ban B\u00f4ng",
    "gn:population":0,
    "gn:timezone":"Asia/Vientiane",
    "iso:country":"LA",
    "name:lao_x_preferred":[
        "Ban B\u00f4ng"
    ],
    "wof:name":"Ban Bong",
    "wof:placetype":"locality"
},
  "geometry": {"coordinates":[103.49472,20.69265],"type":"Point"}
}