{
  "type": "Feature",
  "properties": {
    "gn:admin1_code":"3.0",
    "gn:asciiname":"Ban Longlao",
    "gn:country_code":"LA",
    "gn:dem":734,
    "gn:feature_class":"P",
    "gn:feature_code":"PPL",
    "gn:name":"Ban Longlao",
    "gn:population":0,
    "gn:timezone":"Asia/Vientiane",
    "iso:country":"LA",
    "name:lao_x_preferred":[
        "Ban Longlao"
    ],
    "wof:name":"Ban Longlao",
    "wof:placetype":"locality"
},
  "geometry": {"coordinates":[104.34844,20.40293],"type":"Point"}
}