{
  "type": "Feature",
  "properties": {
    "gn:admin1_code":"7.0",
    "gn:asciiname":"Ban Kanong",
    "gn:country_code":"LA",
    "gn:dem":936,
    "gn:feature_class":"P",
    "gn:feature_code":"PPL",
    "gn:name":"Ban Kan\u00f4ng",
    "gn:population":0,
    "gn:timezone":"Asia/Vientiane",
    "iso:country":"LA",
    "name:lao_x_preferred":[
        "Ban Kan\u00f4ng"
    ],
    "wof:name":"Ban Kanong",
    "wof:placetype":"locality"
},
  "geometry": {"coordinates":[101.77303000000001,20.58717],"type":"Point"}
}