{
  "type": "Feature",
  "properties": {
    "gn:admin1_code":"20.0",
    "gn:asciiname":"Ban Nao-Nua",
    "gn:country_code":"LA",
    "gn:dem":157,
    "gn:feature_class":"P",
    "gn:feature_code":"PPL",
    "gn:name":"Ban Nao-Nua",
    "gn:population":0,
    "gn:timezone":"Asia/Vientiane",
    "iso:country":"LA",
    "name:lao_x_preferred":[
        "Ban Nao-Nua"
    ],
    "name:und_x_variant":[
        "Ban Mak Naoneua",
        "Ban Nao Neua"
    ],
    "wof:name":"Ban Nao-Nua",
    "wof:placetype":"locality"
},
  "geometry": {"coordinates":[104.88883,16.98309],"type":"Point"}
}