{
  "type": "Feature",
  "properties": {
    "gn:admin1_code":"20.0",
    "gn:asciiname":"Ban Kokdeng",
    "gn:country_code":"LA",
    "gn:dem":182,
    "gn:feature_class":"P",
    "gn:feature_code":"PPL",
    "gn:name":"Ban K\u00f4kd\u00e8ng",
    "gn:population":0,
    "gn:timezone":"Asia/Vientiane",
    "iso:country":"LA",
    "name:lao_x_preferred":[
        "Ban K\u00f4kd\u00e8ng"
    ],
    "wof:name":"Ban Kokdeng",
    "wof:placetype":"locality"
},
  "geometry": {"coordinates":[105.24782999999999,16.91997000000001],"type":"Point"}
}