{
  "type": "Feature",
  "properties": {
    "gn:admin1_code":"18.0",
    "gn:asciiname":"Ban Houanga",
    "gn:country_code":"LA",
    "gn:dem":774,
    "gn:feature_class":"P",
    "gn:feature_code":"PPL",
    "gn:name":"Ban Houanga",
    "gn:population":0,
    "gn:timezone":"Asia/Vientiane",
    "iso:country":"LA",
    "name:lao_x_preferred":[
        "Ban Houanga"
    ],
    "wof:name":"Ban Houanga",
    "wof:placetype":"locality"
},
  "geometry": {"coordinates":[102.66491000000001,21.25062],"type":"Point"}
}