{
  "type": "Feature",
  "properties": {
    "gn:admin1_code":"28.0",
    "gn:asciiname":"Ban Phouthat",
    "gn:country_code":"LA",
    "gn:dem":1322,
    "gn:feature_class":"P",
    "gn:feature_code":"PPL",
    "gn:name":"Ban Phouthat",
    "gn:population":0,
    "gn:timezone":"Asia/Vientiane",
    "iso:country":"LA",
    "wof:name":"Ban Phouthat",
    "wof:placetype":"locality"
},
  "geometry": {"coordinates":[103.23333,18.78333],"type":"Point"}
}