{
  "type": "Feature",
  "properties": {
    "gn:admin1_code":"2.0",
    "gn:asciiname":"Ban Sala",
    "gn:country_code":"LA",
    "gn:dem":92,
    "gn:feature_class":"P",
    "gn:feature_code":"PPL",
    "gn:name":"Ban Sala",
    "gn:population":0,
    "gn:timezone":"Asia/Vientiane",
    "iso:country":"LA",
    "name:lao_x_preferred":[
        "Ban Sala"
    ],
    "wof:name":"Ban Sala",
    "wof:placetype":"locality"
},
  "geometry": {"coordinates":[105.86702,14.06816],"type":"Point"}
}