{
  "type": "Feature",
  "properties": {
    "gn:admin1_code":"14.0",
    "gn:asciiname":"Ban Haihin",
    "gn:country_code":"LA",
    "gn:dem":989,
    "gn:feature_class":"P",
    "gn:feature_code":"PPL",
    "gn:name":"Ban Haihin",
    "gn:population":0,
    "gn:timezone":"Asia/Vientiane",
    "iso:country":"LA",
    "name:lao_x_preferred":[
        "Ban Haihin"
    ],
    "wof:name":"Ban Haihin",
    "wof:placetype":"locality"
},
  "geometry": {"coordinates":[103.44811,19.523],"type":"Point"}
}