{
  "type": "Feature",
  "properties": {
    "gn:admin1_code":"17.0",
    "gn:asciiname":"Ban Nambak",
    "gn:country_code":"LA",
    "gn:dem":354,
    "gn:feature_class":"P",
    "gn:feature_code":"PPL",
    "gn:name":"Ban Nambak",
    "gn:population":0,
    "gn:timezone":"Asia/Vientiane",
    "iso:country":"LA",
    "name:und_x_variant":[
        "Nam Bac",
        "Ban Nam Bac",
        "Muang Namba",
        "Muang Nambak",
        "Ban Nambak"
    ],
    "wof:name":"Ban Nambak",
    "wof:placetype":"locality"
},
  "geometry": {"coordinates":[102.45255,20.62666],"type":"Point"}
}