{
  "type": "Feature",
  "properties": {
    "gn:admin1_code":"17.0",
    "gn:asciiname":"Ban Chomchiang-Kang",
    "gn:country_code":"LA",
    "gn:dem":812,
    "gn:feature_class":"P",
    "gn:feature_code":"PPL",
    "gn:name":"Ban Chomchiang-Kang",
    "gn:population":0,
    "gn:timezone":"Asia/Vientiane",
    "iso:country":"LA",
    "name:lao_x_preferred":[
        "Ban Chomchiang-Kang"
    ],
    "name:und_x_variant":[
        "Tiom Tieng Khang"
    ],
    "wof:name":"Ban Chomchiang-Kang",
    "wof:placetype":"locality"
},
  "geometry": {"coordinates":[102.77887,21.00793],"type":"Point"}
}