{
  "type": "Feature",
  "properties": {
    "gn:admin1_code":"20.0",
    "gn:asciiname":"Ban Nakangxe",
    "gn:country_code":"LA",
    "gn:dem":162,
    "gn:feature_class":"P",
    "gn:feature_code":"PPL",
    "gn:name":"Ban Nakangx\u00e8",
    "gn:population":0,
    "gn:timezone":"Asia/Vientiane",
    "iso:country":"LA",
    "name:lao_x_preferred":[
        "Ban Nakangx\u00e8"
    ],
    "name:und_x_variant":[
        "Ban Na Kang"
    ],
    "wof:name":"Ban Nakangxe",
    "wof:placetype":"locality"
},
  "geometry": {"coordinates":[105.57391,16.60081],"type":"Point"}
}