{
  "type": "Feature",
  "properties": {
    "gn:admin1_code":"20.0",
    "gn:asciiname":"Ban Pongxe",
    "gn:country_code":"LA",
    "gn:dem":154,
    "gn:feature_class":"P",
    "gn:feature_code":"PPL",
    "gn:name":"Ban P\u00f4ngx\u00e9",
    "gn:population":0,
    "gn:timezone":"Asia/Vientiane",
    "iso:country":"LA",
    "name:lao_x_preferred":[
        "Ban P\u00f4ngx\u00e9"
    ],
    "wof:name":"Ban Pongxe",
    "wof:placetype":"locality"
},
  "geometry": {"coordinates":[105.51972000000001,16.49658],"type":"Point"}
}