{
  "type": "Feature",
  "properties": {
    "gn:admin1_code":"27.0",
    "gn:asciiname":"Ban Muang-Kao",
    "gn:country_code":"LA",
    "gn:dem":179,
    "gn:feature_class":"P",
    "gn:feature_code":"PPL",
    "gn:name":"Ban Muang-Kao",
    "gn:population":0,
    "gn:timezone":"Asia/Vientiane",
    "iso:country":"LA",
    "name:lao_x_preferred":[
        "Ban Muang-Kao"
    ],
    "name:und_x_variant":[
        "Muang Kao"
    ],
    "wof:name":"Ban Muang-Kao",
    "wof:placetype":"locality"
},
  "geometry": {"coordinates":[102.53686,18.42936],"type":"Point"}
}