{
  "type": "Feature",
  "properties": {
    "gn:admin1_code":"26.0",
    "gn:asciiname":"Ban Tangyoun",
    "gn:country_code":"LA",
    "gn:dem":1207,
    "gn:feature_class":"P",
    "gn:feature_code":"PPL",
    "gn:name":"Ban Tangyoun",
    "gn:population":0,
    "gn:timezone":"Asia/Vientiane",
    "iso:country":"LA",
    "name:lao_x_preferred":[
        "Ban Tangyoun"
    ],
    "wof:name":"Ban Tangyoun",
    "wof:placetype":"locality"
},
  "geometry": {"coordinates":[107.21107000000001,15.63637],"type":"Point"}
}