{
  "type": "Feature",
  "properties": {
    "gn:admin1_code":"17.0",
    "gn:asciiname":"Ban Kiouklim",
    "gn:country_code":"LA",
    "gn:dem":761,
    "gn:feature_class":"P",
    "gn:feature_code":"PPL",
    "gn:name":"Ban Kiouklim",
    "gn:population":0,
    "gn:timezone":"Asia/Vientiane",
    "iso:country":"LA",
    "name:lao_x_preferred":[
        "Ban Kiouklim"
    ],
    "wof:name":"Ban Kiouklim",
    "wof:placetype":"locality"
},
  "geometry": {"coordinates":[102.58301,20.93682],"type":"Point"}
}