{
  "type": "Feature",
  "properties": {
    "gn:admin1_code":"7.0",
    "gn:asciiname":"Ban Namkhong",
    "gn:country_code":"LA",
    "gn:dem":827,
    "gn:feature_class":"P",
    "gn:feature_code":"PPL",
    "gn:name":"Ban Namkhong",
    "gn:population":0,
    "gn:timezone":"Asia/Vientiane",
    "iso:country":"LA",
    "name:lao_x_preferred":[
        "Ban Namkhong"
    ],
    "wof:name":"Ban Namkhong",
    "wof:placetype":"locality"
},
  "geometry": {"coordinates":[101.56519,20.3237],"type":"Point"}
}