{
  "type": "Feature",
  "properties": {
    "gn:admin1_code":"7.0",
    "gn:asciiname":"Ban Pakko",
    "gn:country_code":"LA",
    "gn:dem":453,
    "gn:feature_class":"P",
    "gn:feature_code":"PPL",
    "gn:name":"Ban Pakko",
    "gn:population":0,
    "gn:timezone":"Asia/Vientiane",
    "iso:country":"LA",
    "name:lao_x_preferred":[
        "Ban Pakko"
    ],
    "wof:name":"Ban Pakko",
    "wof:placetype":"locality"
},
  "geometry": {"coordinates":[102.1409,20.87166],"type":"Point"}
}