{
  "type": "Feature",
  "properties": {
    "gn:admin1_code":"17.0",
    "gn:asciiname":"Ban Moktao",
    "gn:country_code":"LA",
    "gn:dem":485,
    "gn:feature_class":"P",
    "gn:feature_code":"PPL",
    "gn:name":"Ban Moktao",
    "gn:population":0,
    "gn:timezone":"Asia/Vientiane",
    "iso:country":"LA",
    "name:lao_x_preferred":[
        "Ban Moktao"
    ],
    "wof:name":"Ban Moktao",
    "wof:placetype":"locality"
},
  "geometry": {"coordinates":[102.53415,20.14742],"type":"Point"}
}