{
  "type": "Feature",
  "properties": {
    "gn:admin1_code":"20.0",
    "gn:asciiname":"Ban Loko",
    "gn:country_code":"LA",
    "gn:dem":229,
    "gn:feature_class":"P",
    "gn:feature_code":"PPL",
    "gn:name":"Ban Loko",
    "gn:population":0,
    "gn:timezone":"Asia/Vientiane",
    "iso:country":"LA",
    "name:lao_x_preferred":[
        "Ban Loko"
    ],
    "name:und_x_variant":[
        "Po Lo Co",
        "P\u00e9 Lo Co"
    ],
    "wof:name":"Ban Loko",
    "wof:placetype":"locality"
},
  "geometry": {"coordinates":[106.68392,16.45594],"type":"Point"}
}