{
  "type": "Feature",
  "properties": {
    "gn:admin1_code":"17.0",
    "gn:asciiname":"Ban Som",
    "gn:country_code":"LA",
    "gn:dem":388,
    "gn:feature_class":"P",
    "gn:feature_code":"PPL",
    "gn:name":"Ban S\u00f4m",
    "gn:population":0,
    "gn:timezone":"Asia/Vientiane",
    "iso:country":"LA",
    "name:lao_x_preferred":[
        "Ban S\u00f4m"
    ],
    "wof:name":"Ban Som",
    "wof:placetype":"locality"
},
  "geometry": {"coordinates":[102.12560000000001,19.97492],"type":"Point"}
}