{
  "type": "Feature",
  "properties": {
    "gn:admin1_code":"2.0",
    "gn:asciiname":"Ban Xonphak",
    "gn:country_code":"LA",
    "gn:dem":122,
    "gn:feature_class":"P",
    "gn:feature_code":"PPL",
    "gn:name":"Ban Xonphak",
    "gn:population":0,
    "gn:timezone":"Asia/Vientiane",
    "iso:country":"LA",
    "name:lao_x_preferred":[
        "Ban Xonphak"
    ],
    "name:und_x_variant":[
        "Ban Sone Pak",
        "Ban S\u00f4np\u00e8k"
    ],
    "wof:name":"Ban Xonphak",
    "wof:placetype":"locality"
},
  "geometry": {"coordinates":[105.74329,15.29932],"type":"Point"}
}