{
  "type": "Feature",
  "properties": {
    "gn:admin1_code":"18.0",
    "gn:asciiname":"Ban Laha",
    "gn:country_code":"LA",
    "gn:dem":1339,
    "gn:feature_class":"P",
    "gn:feature_code":"PPL",
    "gn:name":"Ban Laha",
    "gn:population":0,
    "gn:timezone":"Asia/Vientiane",
    "iso:country":"LA",
    "name:lao_x_preferred":[
        "Ban Laha"
    ],
    "wof:name":"Ban Laha",
    "wof:placetype":"locality"
},
  "geometry": {"coordinates":[102.12819,21.69943],"type":"Point"}
}