{
  "type": "Feature",
  "properties": {
    "gn:admin1_code":"20.0",
    "gn:asciiname":"Ban Padong",
    "gn:country_code":"LA",
    "gn:dem":161,
    "gn:feature_class":"P",
    "gn:feature_code":"PPL",
    "gn:name":"Ban Pad\u00f4ng",
    "gn:population":0,
    "gn:timezone":"Asia/Vientiane",
    "iso:country":"LA",
    "name:lao_x_preferred":[
        "Ban Pad\u00f4ng"
    ],
    "wof:name":"Ban Padong",
    "wof:placetype":"locality"
},
  "geometry": {"coordinates":[105.60141000000002,16.25587],"type":"Point"}
}