{
  "type": "Feature",
  "properties": {
    "gn:admin1_code":"20.0",
    "gn:asciiname":"Ban Vangthong",
    "gn:country_code":"LA",
    "gn:dem":198,
    "gn:feature_class":"P",
    "gn:feature_code":"PPL",
    "gn:name":"Ban Vangth\u00f4ng",
    "gn:population":0,
    "gn:timezone":"Asia/Vientiane",
    "iso:country":"LA",
    "name:und_x_variant":[
        "Ban Na Semou",
        "Ban Vangth\u00f4ng"
    ],
    "wof:name":"Ban Vangthong",
    "wof:placetype":"locality"
},
  "geometry": {"coordinates":[106.28503000000001,16.67112],"type":"Point"}
}