{
  "type": "Feature",
  "properties": {
    "gn:admin1_code":"19.0",
    "gn:asciiname":"Ban Naphontan",
    "gn:country_code":"LA",
    "gn:dem":143,
    "gn:feature_class":"P",
    "gn:feature_code":"PPL",
    "gn:name":"Ban Naph\u00f4ntan",
    "gn:population":0,
    "gn:timezone":"Asia/Vientiane",
    "iso:country":"LA",
    "name:und_x_variant":[
        "Ban Na Phone Tane",
        "Ban Na Phone Tan",
        "Ban Naph\u00f4ntan"
    ],
    "wof:name":"Ban Naphontan",
    "wof:placetype":"locality"
},
  "geometry": {"coordinates":[105.97239999999999,15.72454],"type":"Point"}
}