{
  "type": "Feature",
  "properties": {
    "gn:admin1_code":"17.0",
    "gn:asciiname":"Ban Phonle",
    "gn:country_code":"LA",
    "gn:dem":387,
    "gn:feature_class":"P",
    "gn:feature_code":"PPL",
    "gn:name":"Ban Ph\u00f4nl\u00e8",
    "gn:population":0,
    "gn:timezone":"Asia/Vientiane",
    "iso:country":"LA",
    "name:lao_x_preferred":[
        "Ban Ph\u00f4nl\u00e8"
    ],
    "wof:name":"Ban Phonle",
    "wof:placetype":"locality"
},
  "geometry": {"coordinates":[102.38682,20.54627],"type":"Point"}
}