{
  "type": "Feature",
  "properties": {
    "gn:admin1_code":"17.0",
    "gn:asciiname":"Ban Mouan",
    "gn:country_code":"LA",
    "gn:dem":763,
    "gn:feature_class":"P",
    "gn:feature_code":"PPL",
    "gn:name":"Ban Mouan",
    "gn:population":0,
    "gn:timezone":"Asia/Vientiane",
    "iso:country":"LA",
    "name:lao_x_preferred":[
        "Ban Mouan"
    ],
    "wof:name":"Ban Mouan",
    "wof:placetype":"locality"
},
  "geometry": {"coordinates":[102.24902,20.43675],"type":"Point"}
}