{
  "type": "Feature",
  "properties": {
    "gn:admin1_code":"13.0",
    "gn:asciiname":"Ban Viangxai",
    "gn:country_code":"LA",
    "gn:dem":367,
    "gn:feature_class":"P",
    "gn:feature_code":"PPL",
    "gn:name":"Ban Viangxai",
    "gn:population":0,
    "gn:timezone":"Asia/Vientiane",
    "iso:country":"LA",
    "name:lao_x_preferred":[
        "Ban Viangxai"
    ],
    "wof:name":"Ban Viangxai",
    "wof:placetype":"locality"
},
  "geometry": {"coordinates":[101.49163,18.89935],"type":"Point"}
}