{
  "type": "Feature",
  "properties": {
    "gn:admin1_code":"17.0",
    "gn:asciiname":"Ban Nonthong",
    "gn:country_code":"LA",
    "gn:dem":435,
    "gn:feature_class":"P",
    "gn:feature_code":"PPL",
    "gn:name":"Ban N\u00f4nthong",
    "gn:population":0,
    "gn:timezone":"Asia/Vientiane",
    "iso:country":"LA",
    "name:lao_x_preferred":[
        "Ban N\u00f4nthong"
    ],
    "wof:name":"Ban Nonthong",
    "wof:placetype":"locality"
},
  "geometry": {"coordinates":[102.6532,20.18203],"type":"Point"}
}