{
  "type": "Feature",
  "properties": {
    "gn:admin1_code":"19.0",
    "gn:asciiname":"Ban Nalancha",
    "gn:country_code":"LA",
    "gn:dem":177,
    "gn:feature_class":"P",
    "gn:feature_code":"PPL",
    "gn:name":"Ban Nalancha",
    "gn:population":0,
    "gn:timezone":"Asia/Vientiane",
    "iso:country":"LA",
    "name:und_x_variant":[
        "Ban Nalane Cha",
        "Ban Nalancha"
    ],
    "wof:name":"Ban Nalancha",
    "wof:placetype":"locality"
},
  "geometry": {"coordinates":[105.88333,15.53333],"type":"Point"}
}