{
  "type": "Feature",
  "properties": {
    "gn:admin1_code":"15.0",
    "gn:asciiname":"Ban Nang",
    "gn:country_code":"LA",
    "gn:dem":159,
    "gn:feature_class":"P",
    "gn:feature_code":"PPL",
    "gn:name":"Ban Nang",
    "gn:population":0,
    "gn:timezone":"Asia/Vientiane",
    "iso:country":"LA",
    "name:und_x_variant":[
        "Ban Na Ngou",
        "Ban Nang"
    ],
    "wof:name":"Ban Nang",
    "wof:placetype":"locality"
},
  "geometry": {"coordinates":[104.68588,17.56447],"type":"Point"}
}