{
  "type": "Feature",
  "properties": {
    "gn:admin1_code":"3.0",
    "gn:asciiname":"Ban Sopka",
    "gn:country_code":"LA",
    "gn:dem":483,
    "gn:feature_class":"P",
    "gn:feature_code":"PPL",
    "gn:name":"Ban S\u00f4pka",
    "gn:population":0,
    "gn:timezone":"Asia/Vientiane",
    "iso:country":"LA",
    "name:und_x_variant":[
        "S\u00f4pka",
        "Ban S\u00f4pka"
    ],
    "wof:name":"Ban Sopka",
    "wof:placetype":"locality"
},
  "geometry": {"coordinates":[103.67511,20.48107000000001],"type":"Point"}
}