{
  "type": "Feature",
  "properties": {
    "gn:admin1_code":"19.0",
    "gn:asciiname":"Ban Muang-Kao",
    "gn:country_code":"LA",
    "gn:dem":137,
    "gn:feature_class":"P",
    "gn:feature_code":"PPL",
    "gn:name":"Ban Muang-Kao",
    "gn:population":0,
    "gn:timezone":"Asia/Vientiane",
    "iso:country":"LA",
    "name:lao_x_preferred":[
        "Ban Muang-Kao"
    ],
    "name:und_x_variant":[
        "Ban Muong K\u2019ao"
    ],
    "wof:name":"Ban Muang-Kao",
    "wof:placetype":"locality"
},
  "geometry": {"coordinates":[105.78149999999999,15.52712],"type":"Point"}
}