{
  "type": "Feature",
  "properties": {
    "gn:admin1_code":"7.0",
    "gn:asciiname":"Ban Phousoung",
    "gn:country_code":"LA",
    "gn:dem":1071,
    "gn:feature_class":"P",
    "gn:feature_code":"PPL",
    "gn:name":"Ban Phousoung",
    "gn:population":0,
    "gn:timezone":"Asia/Vientiane",
    "iso:country":"LA",
    "name:lao_x_preferred":[
        "Ban Phousoung"
    ],
    "wof:name":"Ban Phousoung",
    "wof:placetype":"locality"
},
  "geometry": {"coordinates":[101.17773,19.98582],"type":"Point"}
}