{
  "type": "Feature",
  "properties": {
    "gn:admin1_code":"2.0",
    "gn:asciiname":"Ban Vangtao-Gnai",
    "gn:country_code":"LA",
    "gn:dem":133,
    "gn:feature_class":"P",
    "gn:feature_code":"PPL",
    "gn:name":"Ban Vangtao-Gnai",
    "gn:population":0,
    "gn:timezone":"Asia/Vientiane",
    "iso:country":"LA",
    "name:lao_x_preferred":[
        "Ban Vangtao-Gnai"
    ],
    "name:und_x_variant":[
        "Vang Taou",
        "Ban Vang Taou",
        "Ban Vangtao Nai"
    ],
    "wof:name":"Ban Vangtao-Gnai",
    "wof:placetype":"locality"
},
  "geometry": {"coordinates":[105.51132,15.1639],"type":"Point"}
}