{
  "type": "Feature",
  "properties": {
    "gn:admin1_code":"15.0",
    "gn:asciiname":"Ban Mouangkhai",
    "gn:country_code":"LA",
    "gn:dem":172,
    "gn:feature_class":"P",
    "gn:feature_code":"PPL",
    "gn:name":"Ban Mouangkhai",
    "gn:population":0,
    "gn:timezone":"Asia/Vientiane",
    "iso:country":"LA",
    "name:lao_x_preferred":[
        "Ban Mouangkhai"
    ],
    "wof:name":"Ban Mouangkhai",
    "wof:placetype":"locality"
},
  "geometry": {"coordinates":[104.5977,17.89979],"type":"Point"}
}