{
  "type": "Feature",
  "properties": {
    "gn:admin1_code":"23.0",
    "gn:asciiname":"Ban Khambon",
    "gn:country_code":"LA",
    "gn:dem":169,
    "gn:feature_class":"P",
    "gn:feature_code":"PPL",
    "gn:name":"Ban Khambon",
    "gn:population":0,
    "gn:timezone":"Asia/Vientiane",
    "iso:country":"LA",
    "name:und_x_variant":[
        "Ban Kham Bona",
        "Ban Kham B\u00f4ne",
        "Ban Khambon"
    ],
    "wof:name":"Ban Khambon",
    "wof:placetype":"locality"
},
  "geometry": {"coordinates":[103.84502999999999,18.4755],"type":"Point"}
}