{
  "type": "Feature",
  "properties": {
    "gn:admin1_code":"27.0",
    "gn:asciiname":"Ban Phonmouang",
    "gn:country_code":"LA",
    "gn:dem":180,
    "gn:feature_class":"P",
    "gn:feature_code":"PPL",
    "gn:name":"Ban Ph\u00f4nmouang",
    "gn:population":0,
    "gn:timezone":"Asia/Vientiane",
    "iso:country":"LA",
    "name:lao_x_preferred":[
        "Ban Ph\u00f4nmouang"
    ],
    "wof:name":"Ban Phonmouang",
    "wof:placetype":"locality"
},
  "geometry": {"coordinates":[102.67831,18.33174],"type":"Point"}
}