{
  "type": "Feature",
  "properties": {
    "gn:admin1_code":"19.0",
    "gn:asciiname":"Ban Napheng-Noy",
    "gn:country_code":"LA",
    "gn:dem":180,
    "gn:feature_class":"P",
    "gn:feature_code":"PPL",
    "gn:name":"Ban Napheng-Noy",
    "gn:population":0,
    "gn:timezone":"Asia/Vientiane",
    "iso:country":"LA",
    "name:lao_x_preferred":[
        "Ban Napheng-Noy"
    ],
    "wof:name":"Ban Napheng-Noy",
    "wof:placetype":"locality"
},
  "geometry": {"coordinates":[106.31131000000001,15.74268],"type":"Point"}
}