{
  "type": "Feature",
  "properties": {
    "gn:admin1_code":"3.0",
    "gn:asciiname":"Ban Piat",
    "gn:country_code":"LA",
    "gn:dem":1269,
    "gn:feature_class":"P",
    "gn:feature_code":"PPL",
    "gn:name":"Ban Piat",
    "gn:population":0,
    "gn:timezone":"Asia/Vientiane",
    "iso:country":"LA",
    "name:lao_x_preferred":[
        "Ban Piat"
    ],
    "wof:name":"Ban Piat",
    "wof:placetype":"locality"
},
  "geometry": {"coordinates":[103.96507,20.29842],"type":"Point"}
}