{
  "type": "Feature",
  "properties": {
    "gn:admin1_code":"23.0",
    "gn:asciiname":"Ban Phayat",
    "gn:country_code":"LA",
    "gn:dem":866,
    "gn:feature_class":"P",
    "gn:feature_code":"PPL",
    "gn:name":"Ban Phayat",
    "gn:population":0,
    "gn:timezone":"Asia/Vientiane",
    "iso:country":"LA",
    "name:lao_x_preferred":[
        "Ban Phayat"
    ],
    "wof:name":"Ban Phayat",
    "wof:placetype":"locality"
},
  "geometry": {"coordinates":[104.59536,18.54667],"type":"Point"}
}