{
  "type": "Feature",
  "properties": {
    "gn:admin1_code":"3.0",
    "gn:asciiname":"Ban Houayveui",
    "gn:country_code":"LA",
    "gn:dem":974,
    "gn:feature_class":"P",
    "gn:feature_code":"PPL",
    "gn:name":"Ban Houayveui",
    "gn:population":0,
    "gn:timezone":"Asia/Vientiane",
    "iso:country":"LA",
    "name:lao_x_preferred":[
        "Ban Houayveui"
    ],
    "wof:name":"Ban Houayveui",
    "wof:placetype":"locality"
},
  "geometry": {"coordinates":[104.45896,19.79397],"type":"Point"}
}