{
  "type": "Feature",
  "properties": {
    "gn:admin1_code":"17.0",
    "gn:asciiname":"Ban That",
    "gn:country_code":"LA",
    "gn:dem":316,
    "gn:feature_class":"P",
    "gn:feature_code":"PPL",
    "gn:name":"Ban That",
    "gn:population":0,
    "gn:timezone":"Asia/Vientiane",
    "iso:country":"LA",
    "wof:name":"Ban That",
    "wof:placetype":"locality"
},
  "geometry": {"coordinates":[101.86750000000001,19.49278],"type":"Point"}
}