{
  "type": "Feature",
  "properties": {
    "gn:admin1_code":"15.0",
    "gn:asciiname":"Ban Nabon",
    "gn:country_code":"LA",
    "gn:dem":186,
    "gn:feature_class":"P",
    "gn:feature_code":"PPL",
    "gn:name":"Ban Nabon",
    "gn:population":0,
    "gn:timezone":"Asia/Vientiane",
    "iso:country":"LA",
    "name:und_x_variant":[
        "Ban Na Phung",
        "Ban Na Phun",
        "Ban Nabon"
    ],
    "wof:name":"Ban Nabon",
    "wof:placetype":"locality"
},
  "geometry": {"coordinates":[104.84016,17.91962000000001],"type":"Point"}
}