{
  "type": "Feature",
  "properties": {
    "gn:admin1_code":"17.0",
    "gn:asciiname":"Ban Phoutongngong",
    "gn:country_code":"LA",
    "gn:dem":1262,
    "gn:feature_class":"P",
    "gn:feature_code":"PPL",
    "gn:name":"Ban Phoutongngong",
    "gn:population":0,
    "gn:timezone":"Asia/Vientiane",
    "iso:country":"LA",
    "name:lao_x_preferred":[
        "Ban Phoutongngong"
    ],
    "wof:name":"Ban Phoutongngong",
    "wof:placetype":"locality"
},
  "geometry": {"coordinates":[102.74808,20.0393],"type":"Point"}
}