{
  "type": "Feature",
  "properties": {
    "gn:admin1_code":"3.0",
    "gn:asciiname":"Ban Don",
    "gn:country_code":"LA",
    "gn:dem":1154,
    "gn:feature_class":"P",
    "gn:feature_code":"PPL",
    "gn:name":"Ban Don",
    "gn:population":0,
    "gn:timezone":"Asia/Vientiane",
    "iso:country":"LA",
    "name:lao_x_preferred":[
        "Ban Don"
    ],
    "wof:name":"Ban Don",
    "wof:placetype":"locality"
},
  "geometry": {"coordinates":[104.72295,19.78129],"type":"Point"}
}