{
  "type": "Feature",
  "properties": {
    "gn:admin1_code":"28.0",
    "gn:asciiname":"Ban Vang-An",
    "gn:country_code":"LA",
    "gn:dem":221,
    "gn:feature_class":"P",
    "gn:feature_code":"PPL",
    "gn:name":"Ban Vang-An",
    "gn:population":0,
    "gn:timezone":"Asia/Vientiane",
    "iso:country":"LA",
    "name:lao_x_preferred":[
        "Ban Vang-An"
    ],
    "wof:name":"Ban Vang-An",
    "wof:placetype":"locality"
},
  "geometry": {"coordinates":[103.68231,18.93665],"type":"Point"}
}