{
  "type": "Feature",
  "properties": {
    "gn:admin1_code":"20.0",
    "gn:asciiname":"Ban Bungphano",
    "gn:country_code":"LA",
    "gn:dem":171,
    "gn:feature_class":"P",
    "gn:feature_code":"PPL",
    "gn:name":"Ban Bungphano",
    "gn:population":0,
    "gn:timezone":"Asia/Vientiane",
    "iso:country":"LA",
    "name:und_x_variant":[
        "Ban Bung Pho No",
        "Ban Bung",
        "Ban Bungphano",
        "Ban Bungphang"
    ],
    "wof:name":"Ban Bungphano",
    "wof:placetype":"locality"
},
  "geometry": {"coordinates":[105.45595,16.89294],"type":"Point"}
}