{
  "type": "Feature",
  "properties": {
    "gn:admin1_code":"2.0",
    "gn:asciiname":"Ban Khamao Tiak",
    "gn:country_code":"LA",
    "gn:dem":92,
    "gn:feature_class":"P",
    "gn:feature_code":"PPL",
    "gn:name":"Ban Khamao Tiak",
    "gn:population":0,
    "gn:timezone":"Asia/Vientiane",
    "iso:country":"LA",
    "name:und_x_variant":[
        "Ban Kamaou Tech",
        "Ban Khamao Tiak"
    ],
    "wof:name":"Ban Khamao Tiak",
    "wof:placetype":"locality"
},
  "geometry": {"coordinates":[105.78333000000001,14.08333],"type":"Point"}
}