{
  "type": "Feature",
  "properties": {
    "gn:admin1_code":"1.0",
    "gn:asciiname":"Ban Tonglek",
    "gn:country_code":"LA",
    "gn:dem":88,
    "gn:feature_class":"P",
    "gn:feature_code":"PPL",
    "gn:name":"Ban Tongl\u00e9k",
    "gn:population":0,
    "gn:timezone":"Asia/Vientiane",
    "iso:country":"LA",
    "name:lao_x_preferred":[
        "Ban Tongl\u00e9k"
    ],
    "wof:name":"Ban Tonglek",
    "wof:placetype":"locality"
},
  "geometry": {"coordinates":[106.5189,14.75278],"type":"Point"}
}