{
  "type": "Feature",
  "properties": {
    "gn:admin1_code":"18.0",
    "gn:asciiname":"Ban Hatcha",
    "gn:country_code":"LA",
    "gn:dem":688,
    "gn:feature_class":"P",
    "gn:feature_code":"PPL",
    "gn:name":"Ban Hatcha",
    "gn:population":0,
    "gn:timezone":"Asia/Vientiane",
    "iso:country":"LA",
    "name:lao_x_preferred":[
        "Ban Hatcha"
    ],
    "wof:name":"Ban Hatcha",
    "wof:placetype":"locality"
},
  "geometry": {"coordinates":[102.74348000000001,21.03834],"type":"Point"}
}