{
  "type": "Feature",
  "properties": {
    "gn:admin1_code":"2.0",
    "gn:asciiname":"Ban Donsanban-Noy",
    "gn:country_code":"LA",
    "gn:dem":101,
    "gn:feature_class":"P",
    "gn:feature_code":"PPL",
    "gn:name":"Ban Donsanban-Noy",
    "gn:population":0,
    "gn:timezone":"Asia/Vientiane",
    "iso:country":"LA",
    "name:lao_x_preferred":[
        "Ban Donsanban-Noy"
    ],
    "name:und_x_variant":[
        "Done Sane Bam Noi",
        "Done Sane Ban Noi",
        "Ban Donsan-Ban Noy"
    ],
    "wof:name":"Ban Donsanban-Noy",
    "wof:placetype":"locality"
},
  "geometry": {"coordinates":[105.85424999999999,14.27032],"type":"Point"}
}