{
  "type": "Feature",
  "properties": {
    "gn:admin1_code":"14.0",
    "gn:asciiname":"Ban Phiangchan",
    "gn:country_code":"LA",
    "gn:dem":536,
    "gn:feature_class":"P",
    "gn:feature_code":"PPL",
    "gn:name":"Ban Phiangchan",
    "gn:population":0,
    "gn:timezone":"Asia/Vientiane",
    "iso:country":"LA",
    "name:und_x_variant":[
        "Ban Sieng Mi",
        "Ban Phiangdi",
        "Ban Phiangchan"
    ],
    "wof:name":"Ban Phiangchan",
    "wof:placetype":"locality"
},
  "geometry": {"coordinates":[103.65284,19.59027],"type":"Point"}
}