{
  "type": "Feature",
  "properties": {
    "gn:admin1_code":"13.0",
    "gn:asciiname":"Ban Laoli",
    "gn:country_code":"LA",
    "gn:dem":888,
    "gn:feature_class":"P",
    "gn:feature_code":"PPL",
    "gn:name":"Ban Laoli",
    "gn:population":0,
    "gn:timezone":"Asia/Vientiane",
    "iso:country":"LA",
    "name:lao_x_preferred":[
        "Ban Laoli"
    ],
    "wof:name":"Ban Laoli",
    "wof:placetype":"locality"
},
  "geometry": {"coordinates":[100.78925,19.77033],"type":"Point"}
}