{
  "type": "Feature",
  "properties": {
    "gn:admin1_code":"17.0",
    "gn:asciiname":"Ban Sophoun",
    "gn:country_code":"LA",
    "gn:dem":353,
    "gn:feature_class":"P",
    "gn:feature_code":"PPL",
    "gn:name":"Ban S\u00f4phoun",
    "gn:population":0,
    "gn:timezone":"Asia/Vientiane",
    "iso:country":"LA",
    "name:lao_x_preferred":[
        "Ban S\u00f4phoun"
    ],
    "wof:name":"Ban Sophoun",
    "wof:placetype":"locality"
},
  "geometry": {"coordinates":[102.61709,20.56856],"type":"Point"}
}