{
  "type": "Feature",
  "properties": {
    "gn:admin1_code":"2.0",
    "gn:asciiname":"Ban Singsamphan",
    "gn:country_code":"LA",
    "gn:dem":111,
    "gn:feature_class":"P",
    "gn:feature_code":"PPL",
    "gn:name":"Ban Singsamphan",
    "gn:population":0,
    "gn:timezone":"Asia/Vientiane",
    "iso:country":"LA",
    "name:lao_x_preferred":[
        "Ban Singsamphan"
    ],
    "wof:name":"Ban Singsamphan",
    "wof:placetype":"locality"
},
  "geometry": {"coordinates":[105.51182,15.32643],"type":"Point"}
}