{
  "type": "Feature",
  "properties": {
    "gn:admin1_code":"19.0",
    "gn:asciiname":"Ban Napho-Noy",
    "gn:country_code":"LA",
    "gn:dem":188,
    "gn:feature_class":"P",
    "gn:feature_code":"PPL",
    "gn:name":"Ban Naph\u00f4-Noy",
    "gn:population":0,
    "gn:timezone":"Asia/Vientiane",
    "iso:country":"LA",
    "name:lao_x_preferred":[
        "Ban Naph\u00f4-Noy"
    ],
    "name:und_x_variant":[
        "Ban Naph\u00f4 Noy"
    ],
    "wof:name":"Ban Napho-Noy",
    "wof:placetype":"locality"
},
  "geometry": {"coordinates":[106.25424,15.91675],"type":"Point"}
}