{
  "type": "Feature",
  "properties": {
    "gn:admin1_code":"20.0",
    "gn:asciiname":"Ban Loy",
    "gn:country_code":"LA",
    "gn:dem":243,
    "gn:feature_class":"P",
    "gn:feature_code":"PPL",
    "gn:name":"Ban Loy",
    "gn:population":0,
    "gn:timezone":"Asia/Vientiane",
    "iso:country":"LA",
    "name:lao_x_preferred":[
        "Ban Loy"
    ],
    "wof:name":"Ban Loy",
    "wof:placetype":"locality"
},
  "geometry": {"coordinates":[106.35061,16.40784],"type":"Point"}
}