{
  "type": "Feature",
  "properties": {
    "gn:admin1_code":"17.0",
    "gn:asciiname":"Ban Lek Nung",
    "gn:country_code":"LA",
    "gn:dem":1330,
    "gn:feature_class":"P",
    "gn:feature_code":"PPL",
    "gn:name":"Ban Lek Nung",
    "gn:population":0,
    "gn:timezone":"Asia/Vientiane",
    "iso:country":"LA",
    "name:lao_x_preferred":[
        "Ban Lek Nung"
    ],
    "wof:name":"Ban Lek Nung",
    "wof:placetype":"locality"
},
  "geometry": {"coordinates":[102.76777,19.98885],"type":"Point"}
}