{
  "type": "Feature",
  "properties": {
    "gn:admin1_code":"15.0",
    "gn:asciiname":"Ban Khai",
    "gn:country_code":"LA",
    "gn:dem":321,
    "gn:feature_class":"P",
    "gn:feature_code":"PPL",
    "gn:name":"Ban Khai",
    "gn:population":0,
    "gn:timezone":"Asia/Vientiane",
    "iso:country":"LA",
    "name:lao_x_preferred":[
        "Ban Khai"
    ],
    "wof:name":"Ban Khai",
    "wof:placetype":"locality"
},
  "geometry": {"coordinates":[105.82059,17.15629],"type":"Point"}
}