{
  "type": "Feature",
  "properties": {
    "gn:admin1_code":"23.0",
    "gn:asciiname":"Ban Kang",
    "gn:country_code":"LA",
    "gn:dem":501,
    "gn:feature_class":"P",
    "gn:feature_code":"PPL",
    "gn:name":"Ban Kang",
    "gn:population":0,
    "gn:timezone":"Asia/Vientiane",
    "iso:country":"LA",
    "name:lao_x_preferred":[
        "Ban Kang"
    ],
    "wof:name":"Ban Kang",
    "wof:placetype":"locality"
},
  "geometry": {"coordinates":[104.90412000000001,18.15043],"type":"Point"}
}