{
  "type": "Feature",
  "properties": {
    "gn:admin1_code":"3.0",
    "gn:asciiname":"Ban Houaytiang",
    "gn:country_code":"LA",
    "gn:dem":573,
    "gn:feature_class":"P",
    "gn:feature_code":"PPL",
    "gn:name":"Ban Houaytiang",
    "gn:population":0,
    "gn:timezone":"Asia/Vientiane",
    "iso:country":"LA",
    "name:lao_x_preferred":[
        "Ban Houaytiang"
    ],
    "wof:name":"Ban Houaytiang",
    "wof:placetype":"locality"
},
  "geometry": {"coordinates":[104.36174,20.53783],"type":"Point"}
}