{
  "type": "Feature",
  "properties": {
    "gn:admin1_code":"23.0",
    "gn:asciiname":"Ban Khambon",
    "gn:country_code":"LA",
    "gn:dem":163,
    "gn:feature_class":"P",
    "gn:feature_code":"PPL",
    "gn:name":"Ban Khambon",
    "gn:population":0,
    "gn:timezone":"Asia/Vientiane",
    "iso:country":"LA",
    "name:lao_x_preferred":[
        "Ban Khambon"
    ],
    "wof:name":"Ban Khambon",
    "wof:placetype":"locality"
},
  "geometry": {"coordinates":[103.81914,18.37316],"type":"Point"}
}