{
  "type": "Feature",
  "properties": {
    "gn:admin1_code":"15.0",
    "gn:asciiname":"Ban Nakhangxang",
    "gn:country_code":"LA",
    "gn:dem":159,
    "gn:feature_class":"P",
    "gn:feature_code":"PPL",
    "gn:name":"Ban Nakhangxang",
    "gn:population":0,
    "gn:timezone":"Asia/Vientiane",
    "iso:country":"LA",
    "name:lao_x_preferred":[
        "Ban Nakhangxang"
    ],
    "wof:name":"Ban Nakhangxang",
    "wof:placetype":"locality"
},
  "geometry": {"coordinates":[104.86924999999999,17.47731],"type":"Point"}
}