{
  "type": "Feature",
  "properties": {
    "gn:admin1_code":"3.0",
    "gn:asciiname":"Ban Bouak",
    "gn:country_code":"LA",
    "gn:dem":1411,
    "gn:feature_class":"P",
    "gn:feature_code":"PPL",
    "gn:name":"Ban Bouak",
    "gn:population":0,
    "gn:timezone":"Asia/Vientiane",
    "iso:country":"LA",
    "name:und_x_variant":[
        "Ban Buoc",
        "Ban Bouok",
        "Ban Bouak"
    ],
    "wof:name":"Ban Bouak",
    "wof:placetype":"locality"
},
  "geometry": {"coordinates":[104.35996,19.95603],"type":"Point"}
}