{
  "type": "Feature",
  "properties": {
    "gn:admin1_code":"18.0",
    "gn:asciiname":"Ban Chabu-Tai",
    "gn:country_code":"LA",
    "gn:dem":519,
    "gn:feature_class":"P",
    "gn:feature_code":"PPL",
    "gn:name":"Ban Chabu-Tai",
    "gn:population":0,
    "gn:timezone":"Asia/Vientiane",
    "iso:country":"LA",
    "name:lao_x_preferred":[
        "Ban Chabu-Tai"
    ],
    "name:und_x_variant":[
        "Tiaheu Tay"
    ],
    "wof:name":"Ban Chabu-Tai",
    "wof:placetype":"locality"
},
  "geometry": {"coordinates":[102.58886,21.28984],"type":"Point"}
}