{
  "type": "Feature",
  "properties": {
    "gn:admin1_code":"15.0",
    "gn:asciiname":"Ban Phahang",
    "gn:country_code":"LA",
    "gn:dem":158,
    "gn:feature_class":"P",
    "gn:feature_code":"PPL",
    "gn:name":"Ban Phahang",
    "gn:population":0,
    "gn:timezone":"Asia/Vientiane",
    "iso:country":"LA",
    "name:lao_x_preferred":[
        "Ban Phahang"
    ],
    "wof:name":"Ban Phahang",
    "wof:placetype":"locality"
},
  "geometry": {"coordinates":[104.43722,17.96544],"type":"Point"}
}