{
  "type": "Feature",
  "properties": {
    "gn:admin1_code":"17.0",
    "gn:asciiname":"Ban Taiphakhao",
    "gn:country_code":"LA",
    "gn:dem":1471,
    "gn:feature_class":"P",
    "gn:feature_code":"PPL",
    "gn:name":"Ban Taiphakhao",
    "gn:population":0,
    "gn:timezone":"Asia/Vientiane",
    "iso:country":"LA",
    "name:lao_x_preferred":[
        "Ban Taiphakhao"
    ],
    "wof:name":"Ban Taiphakhao",
    "wof:placetype":"locality"
},
  "geometry": {"coordinates":[102.36281,19.58553],"type":"Point"}
}