{
  "type": "Feature",
  "properties": {
    "gn:admin1_code":"2.0",
    "gn:asciiname":"Houaygnang-Gnai",
    "gn:country_code":"LA",
    "gn:dem":109,
    "gn:feature_class":"P",
    "gn:feature_code":"PPL",
    "gn:name":"Houaygnang-Gnai",
    "gn:population":0,
    "gn:timezone":"Asia/Vientiane",
    "iso:country":"LA",
    "name:lao_x_preferred":[
        "Houaygnang-Gnai"
    ],
    "name:und_x_variant":[
        "Ban Nhang",
        "Ban Gnang"
    ],
    "wof:name":"Houaygnang-Gnai",
    "wof:placetype":"locality"
},
  "geometry": {"coordinates":[105.66771,15.23275],"type":"Point"}
}