{
  "type": "Feature",
  "properties": {
    "gn:admin1_code":"19.0",
    "gn:asciiname":"Ban Chennomuang",
    "gn:country_code":"LA",
    "gn:dem":590,
    "gn:feature_class":"P",
    "gn:feature_code":"PPL",
    "gn:name":"Ban Ch\u00e9nnomuang",
    "gn:population":0,
    "gn:timezone":"Asia/Vientiane",
    "iso:country":"LA",
    "name:und_x_variant":[
        "Chen Na Muong",
        "Ban Ch\u00e9nnomuang"
    ],
    "wof:name":"Ban Chennomuang",
    "wof:placetype":"locality"
},
  "geometry": {"coordinates":[106.53592999999999,16.05697],"type":"Point"}
}