{
  "type": "Feature",
  "properties": {
    "gn:admin1_code":"3.0",
    "gn:asciiname":"Ban Houaytha",
    "gn:country_code":"LA",
    "gn:dem":1279,
    "gn:feature_class":"P",
    "gn:feature_code":"PPL",
    "gn:name":"Ban Houaytha",
    "gn:population":0,
    "gn:timezone":"Asia/Vientiane",
    "iso:country":"LA",
    "name:lao_x_preferred":[
        "Ban Houaytha"
    ],
    "wof:name":"Ban Houaytha",
    "wof:placetype":"locality"
},
  "geometry": {"coordinates":[104.30105,19.79042],"type":"Point"}
}