{
  "type": "Feature",
  "properties": {
    "gn:admin1_code":"15.0",
    "gn:asciiname":"Ban Haithongxom",
    "gn:country_code":"LA",
    "gn:dem":177,
    "gn:feature_class":"P",
    "gn:feature_code":"PPL",
    "gn:name":"Ban Haith\u00f4ngx\u00f4m",
    "gn:population":0,
    "gn:timezone":"Asia/Vientiane",
    "iso:country":"LA",
    "name:und_x_variant":[
        "Ban Hay Thong Som",
        "Ban Haith\u00f4ngx\u00f4m"
    ],
    "wof:name":"Ban Haithongxom",
    "wof:placetype":"locality"
},
  "geometry": {"coordinates":[105.58728000000001,17.35138],"type":"Point"}
}