{
  "type": "Feature",
  "properties": {
    "gn:admin1_code":"7.0",
    "gn:asciiname":"Ban Longyong",
    "gn:country_code":"LA",
    "gn:dem":742,
    "gn:feature_class":"P",
    "gn:feature_code":"PPL",
    "gn:name":"Ban Longyong",
    "gn:population":0,
    "gn:timezone":"Asia/Vientiane",
    "iso:country":"LA",
    "name:lao_x_preferred":[
        "Ban Longyong"
    ],
    "wof:name":"Ban Longyong",
    "wof:placetype":"locality"
},
  "geometry": {"coordinates":[100.96279,19.99662],"type":"Point"}
}