{
  "type": "Feature",
  "properties": {
    "gn:admin1_code":"18.0",
    "gn:asciiname":"Ban Sen-In",
    "gn:country_code":"LA",
    "gn:dem":1147,
    "gn:feature_class":"P",
    "gn:feature_code":"PPL",
    "gn:name":"Ban S\u00e8n-In",
    "gn:population":0,
    "gn:timezone":"Asia/Vientiane",
    "iso:country":"LA",
    "name:und_x_variant":[
        "Sen In",
        "Ban S\u00e8n-In"
    ],
    "wof:name":"Ban Sen-In",
    "wof:placetype":"locality"
},
  "geometry": {"coordinates":[102.13885000000001,21.49503],"type":"Point"}
}