{
  "type": "Feature",
  "properties": {
    "gn:admin1_code":"3.0",
    "gn:asciiname":"Ban Houayhak",
    "gn:country_code":"LA",
    "gn:dem":1184,
    "gn:feature_class":"P",
    "gn:feature_code":"PPL",
    "gn:name":"Ban Houayhak",
    "gn:population":0,
    "gn:timezone":"Asia/Vientiane",
    "iso:country":"LA",
    "name:und_x_variant":[
        "Ban Houay Hao",
        "Ban Houei Hao",
        "Ban Houei Hac",
        "Ban Houayhak"
    ],
    "wof:name":"Ban Houayhak",
    "wof:placetype":"locality"
},
  "geometry": {"coordinates":[104.03846,20.25615],"type":"Point"}
}