{
  "type": "Feature",
  "properties": {
    "gn:admin1_code":"15.0",
    "gn:asciiname":"Ban Houaysanap",
    "gn:cc2":"LA",
    "gn:country_code":"LA",
    "gn:dem":544,
    "gn:feature_class":"P",
    "gn:feature_code":"PPL",
    "gn:name":"Ban Houaysanap",
    "gn:population":0,
    "gn:timezone":"Asia/Vientiane",
    "iso:country":"LA",
    "name:und_x_variant":[
        "Ban Hovei Sa Nap",
        "Ban Houei Sa Nap",
        "Ban Houaysanap"
    ],
    "wof:name":"Ban Houaysanap",
    "wof:placetype":"locality"
},
  "geometry": {"coordinates":[105.23333,17.78333],"type":"Point"}
}