{
  "type": "Feature",
  "properties": {
    "gn:admin1_code":"3.0",
    "gn:asciiname":"Ban Naxai",
    "gn:country_code":"LA",
    "gn:dem":446,
    "gn:feature_class":"P",
    "gn:feature_code":"PPL",
    "gn:name":"Ban Naxai",
    "gn:population":0,
    "gn:timezone":"Asia/Vientiane",
    "iso:country":"LA",
    "name:lao_x_preferred":[
        "Ban Naxai"
    ],
    "wof:name":"Ban Naxai",
    "wof:placetype":"locality"
},
  "geometry": {"coordinates":[104.15237,20.73068],"type":"Point"}
}