{
  "type": "Feature",
  "properties": {
    "gn:admin1_code":"19.0",
    "gn:asciiname":"Ban Taleo",
    "gn:country_code":"LA",
    "gn:dem":201,
    "gn:feature_class":"P",
    "gn:feature_code":"PPL",
    "gn:name":"Ban Tal\u00eao",
    "gn:population":0,
    "gn:timezone":"Asia/Vientiane",
    "iso:country":"LA",
    "name:lao_x_preferred":[
        "Ban Tal\u00eao"
    ],
    "wof:name":"Ban Taleo",
    "wof:placetype":"locality"
},
  "geometry": {"coordinates":[106.38569,15.84461],"type":"Point"}
}