{
  "type": "Feature",
  "properties": {
    "gn:admin1_code":"17.0",
    "gn:asciiname":"Ban Nammouang-Noy",
    "gn:country_code":"LA",
    "gn:dem":1067,
    "gn:feature_class":"P",
    "gn:feature_code":"PPL",
    "gn:name":"Ban Nammouang-Noy",
    "gn:population":0,
    "gn:timezone":"Asia/Vientiane",
    "iso:country":"LA",
    "name:lao_x_preferred":[
        "Ban Nammouang-Noy"
    ],
    "wof:name":"Ban Nammouang-Noy",
    "wof:placetype":"locality"
},
  "geometry": {"coordinates":[102.23894,19.53561],"type":"Point"}
}