{
  "type": "Feature",
  "properties": {
    "gn:admin1_code":"24.0",
    "gn:asciiname":"Ban Kongsam",
    "gn:country_code":"LA",
    "gn:dem":173,
    "gn:feature_class":"P",
    "gn:feature_code":"PPL",
    "gn:name":"Ban Kongsam",
    "gn:population":0,
    "gn:timezone":"Asia/Vientiane",
    "iso:country":"LA",
    "name:lao_x_preferred":[
        "Ban Kongsam"
    ],
    "wof:name":"Ban Kongsam",
    "wof:placetype":"locality"
},
  "geometry": {"coordinates":[102.49511,18.25454],"type":"Point"}
}