{
  "type": "Feature",
  "properties": {
    "gn:admin1_code":"17.0",
    "gn:asciiname":"Ban Houayhan",
    "gn:country_code":"LA",
    "gn:dem":463,
    "gn:feature_class":"P",
    "gn:feature_code":"PPL",
    "gn:name":"Ban Houayhan",
    "gn:population":0,
    "gn:timezone":"Asia/Vientiane",
    "iso:country":"LA",
    "name:lao_x_preferred":[
        "Ban Houayhan"
    ],
    "wof:name":"Ban Houayhan",
    "wof:placetype":"locality"
},
  "geometry": {"coordinates":[101.90255999999999,19.66929],"type":"Point"}
}