{
  "type": "Feature",
  "properties": {
    "gn:admin1_code":"19.0",
    "gn:asciiname":"Ban Phakpheoxet",
    "gn:country_code":"LA",
    "gn:dem":189,
    "gn:feature_class":"P",
    "gn:feature_code":"PPL",
    "gn:name":"Ban Phakph\u00e8ox\u00e9t",
    "gn:population":0,
    "gn:timezone":"Asia/Vientiane",
    "iso:country":"LA",
    "name:lao_x_preferred":[
        "Ban Phakph\u00e8ox\u00e9t"
    ],
    "wof:name":"Ban Phakpheoxet",
    "wof:placetype":"locality"
},
  "geometry": {"coordinates":[106.24624,15.68942],"type":"Point"}
}