{
  "type": "Feature",
  "properties": {
    "gn:admin1_code":"20.0",
    "gn:asciiname":"Ban Dong-Noy",
    "gn:country_code":"LA",
    "gn:dem":183,
    "gn:feature_class":"P",
    "gn:feature_code":"PPL",
    "gn:name":"Ban D\u00f4ng-Noy",
    "gn:population":0,
    "gn:timezone":"Asia/Vientiane",
    "iso:country":"LA",
    "name:lao_x_preferred":[
        "Ban D\u00f4ng-Noy"
    ],
    "name:und_x_variant":[
        "Ban Dong Noi"
    ],
    "wof:name":"Ban Dong-Noy",
    "wof:placetype":"locality"
},
  "geometry": {"coordinates":[105.09912,16.6077],"type":"Point"}
}