{
  "type": "Feature",
  "properties": {
    "gn:admin1_code":"14.0",
    "gn:asciiname":"Muang Mok",
    "gn:country_code":"LA",
    "gn:dem":920,
    "gn:feature_class":"P",
    "gn:feature_code":"PPLA2",
    "gn:name":"Muang Mok",
    "gn:population":0,
    "gn:timezone":"Asia/Vientiane",
    "iso:country":"LA",
    "name:und_x_variant":[
        "Muang Moc",
        "Muong Moc",
        "Muang Mok"
    ],
    "wof:name":"Muang Mok",
    "wof:placetype":"locality"
},
  "geometry": {"coordinates":[104.00626,18.90997],"type":"Point"}
}