{
  "type": "Feature",
  "properties": {
    "gn:admin1_code":"3.0",
    "gn:asciiname":"Ban Khoun",
    "gn:country_code":"LA",
    "gn:dem":752,
    "gn:feature_class":"P",
    "gn:feature_code":"PPL",
    "gn:name":"Ban Khoun",
    "gn:population":0,
    "gn:timezone":"Asia/Vientiane",
    "iso:country":"LA",
    "name:lao_x_preferred":[
        "Ban Khoun"
    ],
    "wof:name":"Ban Khoun",
    "wof:placetype":"locality"
},
  "geometry": {"coordinates":[104.19622,20.23068],"type":"Point"}
}