{
  "type": "Feature",
  "properties": {
    "gn:admin1_code":"26.0",
    "gn:asciiname":"Ban Paleng Nua",
    "gn:country_code":"LA",
    "gn:dem":827,
    "gn:feature_class":"P",
    "gn:feature_code":"PPL",
    "gn:name":"Ban Pal\u00e8ng Nua",
    "gn:population":0,
    "gn:timezone":"Asia/Vientiane",
    "iso:country":"LA",
    "name:und_x_variant":[
        "Ban Pal\u00e8ng Nua",
        "Ban Pal\u00e8ng Nua (2)"
    ],
    "wof:name":"Ban Paleng Nua",
    "wof:placetype":"locality"
},
  "geometry": {"coordinates":[106.34999999999999,15.45],"type":"Point"}
}