{
  "type": "Feature",
  "properties": {
    "gn:admin1_code":"2.0",
    "gn:asciiname":"Ban Donkho",
    "gn:country_code":"LA",
    "gn:dem":107,
    "gn:feature_class":"P",
    "gn:feature_code":"PPL",
    "gn:name":"Ban Donkh\u00f4",
    "gn:population":0,
    "gn:timezone":"Asia/Vientiane",
    "iso:country":"LA",
    "name:und_x_variant":[
        "Ban Donekho",
        "Ban Donkh\u00f4"
    ],
    "wof:name":"Ban Donkho",
    "wof:placetype":"locality"
},
  "geometry": {"coordinates":[105.74669,15.15483],"type":"Point"}
}