{
  "type": "Feature",
  "properties": {
    "gn:admin1_code":"26.0",
    "gn:asciiname":"Ban Adeut-Tai",
    "gn:country_code":"LA",
    "gn:dem":615,
    "gn:feature_class":"P",
    "gn:feature_code":"PPL",
    "gn:name":"Ban Adeut-Tai",
    "gn:population":0,
    "gn:timezone":"Asia/Vientiane",
    "iso:country":"LA",
    "name:lao_x_preferred":[
        "Ban Adeut-Tai"
    ],
    "wof:name":"Ban Adeut-Tai",
    "wof:placetype":"locality"
},
  "geometry": {"coordinates":[107.20928000000001,16.01629],"type":"Point"}
}