{
  "type": "Feature",
  "properties": {
    "gn:admin1_code":"14.0",
    "gn:asciiname":"Ban Phiangxai",
    "gn:country_code":"LA",
    "gn:dem":563,
    "gn:feature_class":"P",
    "gn:feature_code":"PPL",
    "gn:name":"Ban Phiangxai",
    "gn:population":0,
    "gn:timezone":"Asia/Vientiane",
    "iso:country":"LA",
    "name:und_x_variant":[
        "Ban Phiangxai (1)"
    ],
    "wof:name":"Ban Phiangxai",
    "wof:placetype":"locality"
},
  "geometry": {"coordinates":[103.59859,19.63618],"type":"Point"}
}