{
  "type": "Feature",
  "properties": {
    "gn:admin1_code":"28.0",
    "gn:asciiname":"Ban Longsouay",
    "gn:country_code":"LA",
    "gn:dem":1118,
    "gn:feature_class":"P",
    "gn:feature_code":"PPL",
    "gn:name":"Ban Longsouay",
    "gn:population":0,
    "gn:timezone":"Asia/Vientiane",
    "iso:country":"LA",
    "name:lao_x_preferred":[
        "Ban Longsouay"
    ],
    "wof:name":"Ban Longsouay",
    "wof:placetype":"locality"
},
  "geometry": {"coordinates":[102.86381,19.14705],"type":"Point"}
}