{
  "type": "Feature",
  "properties": {
    "gn:admin1_code":"2.0",
    "gn:asciiname":"Ban Noy",
    "gn:country_code":"LA",
    "gn:dem":1057,
    "gn:feature_class":"P",
    "gn:feature_code":"PPL",
    "gn:name":"Ban Noy",
    "gn:population":0,
    "gn:timezone":"Asia/Vientiane",
    "iso:country":"LA",
    "name:lao_x_preferred":[
        "Ban Noy"
    ],
    "wof:name":"Ban Noy",
    "wof:placetype":"locality"
},
  "geometry": {"coordinates":[106.33517000000001,15.33363],"type":"Point"}
}