{
  "type": "Feature",
  "properties": {
    "gn:admin1_code":"13.0",
    "gn:asciiname":"Ban Namthang",
    "gn:country_code":"LA",
    "gn:dem":381,
    "gn:feature_class":"P",
    "gn:feature_code":"PPL",
    "gn:name":"Ban Namthang",
    "gn:population":0,
    "gn:timezone":"Asia/Vientiane",
    "iso:country":"LA",
    "name:lao_x_preferred":[
        "Ban Namthang"
    ],
    "wof:name":"Ban Namthang",
    "wof:placetype":"locality"
},
  "geometry": {"coordinates":[101.62737,19.07436],"type":"Point"}
}