{
  "type": "Feature",
  "properties": {
    "gn:admin1_code":"7.0",
    "gn:asciiname":"Ban Longlou",
    "gn:country_code":"LA",
    "gn:dem":1144,
    "gn:feature_class":"P",
    "gn:feature_code":"PPL",
    "gn:name":"Ban Longlou",
    "gn:population":0,
    "gn:timezone":"Asia/Vientiane",
    "iso:country":"LA",
    "name:lao_x_preferred":[
        "Ban Longlou"
    ],
    "wof:name":"Ban Longlou",
    "wof:placetype":"locality"
},
  "geometry": {"coordinates":[101.25771,20.10629],"type":"Point"}
}