{
  "type": "Feature",
  "properties": {
    "gn:admin1_code":"7.0",
    "gn:asciiname":"Ban Konlouang",
    "gn:country_code":"LA",
    "gn:dem":1004,
    "gn:feature_class":"P",
    "gn:feature_code":"PPL",
    "gn:name":"Ban Konlouang",
    "gn:population":0,
    "gn:timezone":"Asia/Vientiane",
    "iso:country":"LA",
    "name:und_x_variant":[
        "Ban Con Luong",
        "Ban Konlouang"
    ],
    "wof:name":"Ban Konlouang",
    "wof:placetype":"locality"
},
  "geometry": {"coordinates":[101.86667,20.85],"type":"Point"}
}