{
  "type": "Feature",
  "properties": {
    "gn:admin1_code":"16.0",
    "gn:asciiname":"Ban Namngeun",
    "gn:country_code":"LA",
    "gn:dem":682,
    "gn:feature_class":"P",
    "gn:feature_code":"PPL",
    "gn:name":"Ban Namngeun",
    "gn:population":0,
    "gn:timezone":"Asia/Vientiane",
    "iso:country":"LA",
    "name:lao_x_preferred":[
        "Ban Namngeun"
    ],
    "name:und_x_variant":[
        "Muong Ngeun",
        "Muang Ngeun"
    ],
    "wof:name":"Ban Namngeun",
    "wof:placetype":"locality"
},
  "geometry": {"coordinates":[101.05936,20.59317],"type":"Point"}
}