{
  "type": "Feature",
  "properties": {
    "gn:admin1_code":"13.0",
    "gn:asciiname":"Ban Taling",
    "gn:country_code":"LA",
    "gn:dem":357,
    "gn:feature_class":"P",
    "gn:feature_code":"PPL",
    "gn:name":"Ban Taling",
    "gn:population":0,
    "gn:timezone":"Asia/Vientiane",
    "iso:country":"LA",
    "name:lao_x_preferred":[
        "Ban Taling"
    ],
    "wof:name":"Ban Taling",
    "wof:placetype":"locality"
},
  "geometry": {"coordinates":[101.17061,17.78426],"type":"Point"}
}