{
  "type": "Feature",
  "properties": {
    "gn:admin1_code":"3.0",
    "gn:asciiname":"Ban Pao",
    "gn:country_code":"LA",
    "gn:dem":275,
    "gn:feature_class":"P",
    "gn:feature_code":"PPL",
    "gn:name":"Ban Pao",
    "gn:population":0,
    "gn:timezone":"Asia/Vientiane",
    "iso:country":"LA",
    "name:und_x_variant":[
        "Muong Pao",
        "Muang Pao",
        "Ban Pao"
    ],
    "wof:name":"Ban Pao",
    "wof:placetype":"locality"
},
  "geometry": {"coordinates":[104.81527,20.1244],"type":"Point"}
}