{
  "type": "Feature",
  "properties": {
    "gn:admin1_code":"19.0",
    "gn:asciiname":"Ban Nongtom",
    "gn:country_code":"LA",
    "gn:dem":866,
    "gn:feature_class":"P",
    "gn:feature_code":"PPL",
    "gn:name":"Ban Nongt\u00f4m",
    "gn:population":0,
    "gn:timezone":"Asia/Vientiane",
    "iso:country":"LA",
    "name:lao_x_preferred":[
        "Ban Nongt\u00f4m"
    ],
    "wof:name":"Ban Nongtom",
    "wof:placetype":"locality"
},
  "geometry": {"coordinates":[106.23688,15.372],"type":"Point"}
}