{
  "type": "Feature",
  "properties": {
    "iso:country":"LA",
    "name:und_x_variant":[
        "Ban Houei Pa Mome"
    ],
    "qs:gn_country":"LA",
    "qs:gn_fcode":"PPL",
    "qs:gn_pop":0,
    "qs:name":"Ban Houay Pamon",
    "qs:name_adm0":"Laos",
    "qs:name_adm1":"Viangchan",
    "qs:photos":119,
    "qs:photos_1k":24,
    "qs:photos_9k":1,
    "qs:photos_9r":3,
    "qs:photos_all":119,
    "qs:photos_sr":3,
    "qs:placetype":"Town",
    "qs:pop_sr":"4",
    "qs:woe_adm0":23424872,
    "wof:name":"Ban Houay Pamon",
    "wof:placetype":"locality"
},
  "geometry": {"coordinates":[102.49702000000001,18.79212],"type":"Point"}
}