{
  "type": "Feature",
  "properties": {
    "gn:admin1_code":"17.0",
    "gn:asciiname":"Ban Mokdou",
    "gn:country_code":"LA",
    "gn:dem":404,
    "gn:feature_class":"P",
    "gn:feature_code":"PPL",
    "gn:name":"Ban Mokdou",
    "gn:population":0,
    "gn:timezone":"Asia/Vientiane",
    "iso:country":"LA",
    "name:lao_x_preferred":[
        "Ban Mokdou"
    ],
    "wof:name":"Ban Mokdou",
    "wof:placetype":"locality"
},
  "geometry": {"coordinates":[102.71341,20.61653],"type":"Point"}
}