{
  "type": "Feature",
  "properties": {
    "gn:admin1_code":"26.0",
    "gn:asciiname":"Ban Dak-Lam",
    "gn:country_code":"LA",
    "gn:dem":1136,
    "gn:feature_class":"P",
    "gn:feature_code":"PPL",
    "gn:name":"Ban Dak-Lam",
    "gn:population":0,
    "gn:timezone":"Asia/Vientiane",
    "iso:country":"LA",
    "name:und_x_variant":[
        "Lam",
        "Ban Dak-Lam"
    ],
    "wof:name":"Ban Dak-Lam",
    "wof:placetype":"locality"
},
  "geometry": {"coordinates":[107.03333000000001,15.35],"type":"Point"}
}