{
  "type": "Feature",
  "properties": {
    "gn:admin1_code":"20.0",
    "gn:asciiname":"Ban Mouangkhai",
    "gn:country_code":"LA",
    "gn:dem":173,
    "gn:feature_class":"P",
    "gn:feature_code":"PPL",
    "gn:name":"Ban Mouangkhai",
    "gn:population":0,
    "gn:timezone":"Asia/Vientiane",
    "iso:country":"LA",
    "name:und_x_variant":[
        "Ban Monkay",
        "Ban Mouangkhai"
    ],
    "wof:name":"Ban Mouangkhai",
    "wof:placetype":"locality"
},
  "geometry": {"coordinates":[105.00014,16.38878],"type":"Point"}
}