{
  "type": "Feature",
  "properties": {
    "gn:admin1_code":"2.0",
    "gn:asciiname":"Ban Donthangkhoay",
    "gn:country_code":"LA",
    "gn:dem":104,
    "gn:feature_class":"P",
    "gn:feature_code":"PPL",
    "gn:name":"Ban Donthangkhoay",
    "gn:population":0,
    "gn:timezone":"Asia/Vientiane",
    "iso:country":"LA",
    "name:lao_x_preferred":[
        "Ban Donthangkhoay"
    ],
    "wof:name":"Ban Donthangkhoay",
    "wof:placetype":"locality"
},
  "geometry": {"coordinates":[105.85283,14.83118],"type":"Point"}
}