{
  "type": "Feature",
  "properties": {
    "gn:admin1_code":"3.0",
    "gn:asciiname":"Ban Tat",
    "gn:country_code":"LA",
    "gn:dem":854,
    "gn:feature_class":"P",
    "gn:feature_code":"PPL",
    "gn:name":"Ban Tat",
    "gn:population":0,
    "gn:timezone":"Asia/Vientiane",
    "iso:country":"LA",
    "name:lao_x_preferred":[
        "Ban Tat"
    ],
    "wof:name":"Ban Tat",
    "wof:placetype":"locality"
},
  "geometry": {"coordinates":[103.90701,19.89938],"type":"Point"}
}