{
  "type": "Feature",
  "properties": {
    "gn:admin1_code":"7.0",
    "gn:asciiname":"Ban Tangya",
    "gn:country_code":"LA",
    "gn:dem":1073,
    "gn:feature_class":"P",
    "gn:feature_code":"PPL",
    "gn:name":"Ban Tangya",
    "gn:population":0,
    "gn:timezone":"Asia/Vientiane",
    "iso:country":"LA",
    "name:lao_x_preferred":[
        "Ban Tangya"
    ],
    "wof:name":"Ban Tangya",
    "wof:placetype":"locality"
},
  "geometry": {"coordinates":[101.25681,20.09208],"type":"Point"}
}