{
  "type": "Feature",
  "properties": {
    "gn:admin1_code":"20.0",
    "gn:asciiname":"Ban Khamthao",
    "gn:country_code":"LA",
    "gn:dem":151,
    "gn:feature_class":"P",
    "gn:feature_code":"PPL",
    "gn:name":"Ban Khamthao",
    "gn:population":0,
    "gn:timezone":"Asia/Vientiane",
    "iso:country":"LA",
    "name:und_x_variant":[
        "Ban Kam Thao",
        "Ban Khamthao"
    ],
    "wof:name":"Ban Khamthao",
    "wof:placetype":"locality"
},
  "geometry": {"coordinates":[105.12618000000001,16.51632],"type":"Point"}
}