{
  "type": "Feature",
  "properties": {
    "gn:admin1_code":"7.0",
    "gn:asciiname":"Ban Lan",
    "gn:country_code":"LA",
    "gn:dem":990,
    "gn:feature_class":"P",
    "gn:feature_code":"PPL",
    "gn:name":"Ban Lan",
    "gn:population":0,
    "gn:timezone":"Asia/Vientiane",
    "iso:country":"LA",
    "wof:name":"Ban Lan",
    "wof:placetype":"locality"
},
  "geometry": {"coordinates":[102.03333000000001,20.78333],"type":"Point"}
}