{
  "type": "Feature",
  "properties": {
    "gn:admin1_code":"2.0",
    "gn:asciiname":"Ban Non-Oudom",
    "gn:country_code":"LA",
    "gn:dem":485,
    "gn:feature_class":"P",
    "gn:feature_code":"PPL",
    "gn:name":"Ban N\u00f4n-Oud\u00f4m",
    "gn:population":0,
    "gn:timezone":"Asia/Vientiane",
    "iso:country":"LA",
    "name:lao_x_preferred":[
        "Ban N\u00f4n-Oud\u00f4m"
    ],
    "wof:name":"Ban Non-Oudom",
    "wof:placetype":"locality"
},
  "geometry": {"coordinates":[106.0766,15.39984],"type":"Point"}
}