{
  "type": "Feature",
  "properties": {
    "gn:admin1_code":"17.0",
    "gn:asciiname":"Ban Tanlolom",
    "gn:country_code":"LA",
    "gn:dem":680,
    "gn:feature_class":"P",
    "gn:feature_code":"PPL",
    "gn:name":"Ban Tanl\u00f4l\u00f4m",
    "gn:population":0,
    "gn:timezone":"Asia/Vientiane",
    "iso:country":"LA",
    "name:lao_x_preferred":[
        "Ban Tanl\u00f4l\u00f4m"
    ],
    "wof:name":"Ban Tanlolom",
    "wof:placetype":"locality"
},
  "geometry": {"coordinates":[102.3571,20.91883],"type":"Point"}
}