{
  "type": "Feature",
  "properties": {
    "gn:admin1_code":"7.0",
    "gn:asciiname":"Ban Lak",
    "gn:country_code":"LA",
    "gn:dem":829,
    "gn:feature_class":"P",
    "gn:feature_code":"PPL",
    "gn:name":"Ban Lak",
    "gn:population":0,
    "gn:timezone":"Asia/Vientiane",
    "iso:country":"LA",
    "name:lao_x_preferred":[
        "Ban Lak"
    ],
    "wof:name":"Ban Lak",
    "wof:placetype":"locality"
},
  "geometry": {"coordinates":[102.15506999999999,20.5692],"type":"Point"}
}