{
  "type": "Feature",
  "properties": {
    "gn:admin1_code":"26.0",
    "gn:asciiname":"Ban Pa-O",
    "gn:country_code":"LA",
    "gn:dem":337,
    "gn:feature_class":"P",
    "gn:feature_code":"PPL",
    "gn:name":"Ban Pa-O",
    "gn:population":0,
    "gn:timezone":"Asia/Vientiane",
    "iso:country":"LA",
    "wof:name":"Ban Pa-O",
    "wof:placetype":"locality"
},
  "geometry": {"coordinates":[106.96666999999999,15.33333],"type":"Point"}
}