{
  "type": "Feature",
  "properties": {
    "gn:admin1_code":"2.0",
    "gn:asciiname":"Ban Kengmai",
    "gn:country_code":"LA",
    "gn:dem":138,
    "gn:feature_class":"P",
    "gn:feature_code":"PPL",
    "gn:name":"Ban K\u00e8ngmai",
    "gn:population":0,
    "gn:timezone":"Asia/Vientiane",
    "iso:country":"LA",
    "name:und_x_variant":[
        "Ban Keng May",
        "Ban K\u00e8ngmai"
    ],
    "wof:name":"Ban Kengmai",
    "wof:placetype":"locality"
},
  "geometry": {"coordinates":[105.86439,15.38797],"type":"Point"}
}