{
  "type": "Feature",
  "properties": {
    "gn:admin1_code":"3.0",
    "gn:asciiname":"Ban Houay Kasao",
    "gn:cc2":"LA",
    "gn:country_code":"LA",
    "gn:dem":1001,
    "gn:feature_class":"P",
    "gn:feature_code":"PPL",
    "gn:name":"Ban Houay Kasao",
    "gn:population":0,
    "gn:timezone":"Asia/Vientiane",
    "iso:country":"LA",
    "name:und_x_variant":[
        "Ban Houei Kasao",
        "Ban Houay Kasao"
    ],
    "wof:name":"Ban Houay Kasao",
    "wof:placetype":"locality"
},
  "geometry": {"coordinates":[104.01667,20.33333],"type":"Point"}
}