{
  "type": "Feature",
  "properties": {
    "gn:admin1_code":"3.0",
    "gn:asciiname":"Ban Gnot-In",
    "gn:country_code":"LA",
    "gn:dem":1297,
    "gn:feature_class":"P",
    "gn:feature_code":"PPL",
    "gn:name":"Ban Gnot-In",
    "gn:population":0,
    "gn:timezone":"Asia/Vientiane",
    "iso:country":"LA",
    "name:lao_x_preferred":[
        "Ban Gnot-In"
    ],
    "wof:name":"Ban Gnot-In",
    "wof:placetype":"locality"
},
  "geometry": {"coordinates":[104.53721,19.91907],"type":"Point"}
}