{
  "type": "Feature",
  "properties": {
    "gn:admin1_code":"2.0",
    "gn:asciiname":"Ban Veun",
    "gn:country_code":"LA",
    "gn:dem":95,
    "gn:feature_class":"P",
    "gn:feature_code":"PPL",
    "gn:name":"Ban Veun",
    "gn:population":0,
    "gn:timezone":"Asia/Vientiane",
    "iso:country":"LA",
    "name:und_x_variant":[
        "Ban Veune",
        "Ban Veun"
    ],
    "wof:name":"Ban Veun",
    "wof:placetype":"locality"
},
  "geometry": {"coordinates":[105.75133,14.1587],"type":"Point"}
}