{
  "type": "Feature",
  "properties": {
    "gn:admin1_code":"15.0",
    "gn:asciiname":"Ban Nadon",
    "gn:country_code":"LA",
    "gn:dem":157,
    "gn:feature_class":"P",
    "gn:feature_code":"PPL",
    "gn:name":"Ban Nad\u00f4n",
    "gn:population":0,
    "gn:timezone":"Asia/Vientiane",
    "iso:country":"LA",
    "name:und_x_variant":[
        "Ban May",
        "Ban Na Done",
        "Ban Nad\u00f4n"
    ],
    "wof:name":"Ban Nadon",
    "wof:placetype":"locality"
},
  "geometry": {"coordinates":[104.90115,17.33487],"type":"Point"}
}