{
  "type": "Feature",
  "properties": {
    "gn:admin1_code":"20.0",
    "gn:asciiname":"Ban Tan-A",
    "gn:country_code":"LA",
    "gn:dem":621,
    "gn:feature_class":"P",
    "gn:feature_code":"PPL",
    "gn:name":"Ban Tan-A",
    "gn:population":0,
    "gn:timezone":"Asia/Vientiane",
    "iso:country":"LA",
    "name:lao_x_preferred":[
        "Ban Tan-A"
    ],
    "name:und_x_variant":[
        "Tang A",
        "Ban Tang A"
    ],
    "wof:name":"Ban Tan-A",
    "wof:placetype":"locality"
},
  "geometry": {"coordinates":[106.50982999999999,16.85538],"type":"Point"}
}