{
  "type": "Feature",
  "properties": {
    "gn:admin1_code":"20.0",
    "gn:asciiname":"Ban Phakhok",
    "gn:country_code":"LA",
    "gn:dem":196,
    "gn:feature_class":"P",
    "gn:feature_code":"PPL",
    "gn:name":"Ban Phakhok",
    "gn:population":0,
    "gn:timezone":"Asia/Vientiane",
    "iso:country":"LA",
    "name:lao_x_preferred":[
        "Ban Phakhok"
    ],
    "wof:name":"Ban Phakhok",
    "wof:placetype":"locality"
},
  "geometry": {"coordinates":[105.70650999999999,16.97893],"type":"Point"}
}