{
  "type": "Feature",
  "properties": {
    "gn:admin1_code":"19.0",
    "gn:asciiname":"Ban Kenghouat",
    "gn:country_code":"LA",
    "gn:dem":136,
    "gn:feature_class":"P",
    "gn:feature_code":"PPL",
    "gn:name":"Ban K\u00e8nghouat",
    "gn:population":0,
    "gn:timezone":"Asia/Vientiane",
    "iso:country":"LA",
    "name:lao_x_preferred":[
        "Ban K\u00e8nghouat"
    ],
    "wof:name":"Ban Kenghouat",
    "wof:placetype":"locality"
},
  "geometry": {"coordinates":[105.77325999999999,15.4661],"type":"Point"}
}