{
  "type": "Feature",
  "properties": {
    "gn:admin1_code":"3.0",
    "gn:asciiname":"Ban Hatsou",
    "gn:country_code":"LA",
    "gn:dem":283,
    "gn:feature_class":"P",
    "gn:feature_code":"PPL",
    "gn:name":"Ban Hatsou",
    "gn:population":0,
    "gn:timezone":"Asia/Vientiane",
    "iso:country":"LA",
    "name:und_x_variant":[
        "Ban Hat Cu",
        "Ban Hatsou"
    ],
    "wof:name":"Ban Hatsou",
    "wof:placetype":"locality"
},
  "geometry": {"coordinates":[103.9777,20.89071],"type":"Point"}
}