{
  "type": "Feature",
  "properties": {
    "gn:admin1_code":"17.0",
    "gn:asciiname":"Ban Nangvang",
    "gn:country_code":"LA",
    "gn:dem":550,
    "gn:feature_class":"P",
    "gn:feature_code":"PPL",
    "gn:name":"Ban Nangvang",
    "gn:population":0,
    "gn:timezone":"Asia/Vientiane",
    "iso:country":"LA",
    "name:lao_x_preferred":[
        "Ban Nanvang"
    ],
    "name:lao_x_variant":[
        "Ban Nangvang"
    ],
    "wof:name":"Ban Nangvang",
    "wof:placetype":"locality"
},
  "geometry": {"coordinates":[101.88943999999999,19.86831],"type":"Point"}
}