{
  "type": "Feature",
  "properties": {
    "gn:admin1_code":"19.0",
    "gn:asciiname":"Ban Kengkavao",
    "gn:country_code":"LA",
    "gn:dem":226,
    "gn:feature_class":"P",
    "gn:feature_code":"PPL",
    "gn:name":"Ban K\u00e8ngkavao",
    "gn:population":0,
    "gn:timezone":"Asia/Vientiane",
    "iso:country":"LA",
    "name:lao_x_preferred":[
        "Ban K\u00e8ngkavao"
    ],
    "wof:name":"Ban Kengkavao",
    "wof:placetype":"locality"
},
  "geometry": {"coordinates":[106.26128,15.63583],"type":"Point"}
}