{
  "type": "Feature",
  "properties": {
    "gn:admin1_code":"16.0",
    "gn:asciiname":"Ban Mokkhamtun",
    "gn:country_code":"LA",
    "gn:dem":736,
    "gn:feature_class":"P",
    "gn:feature_code":"PPL",
    "gn:name":"Ban M\u00f4kkhamtun",
    "gn:population":0,
    "gn:timezone":"Asia/Vientiane",
    "iso:country":"LA",
    "name:lao_x_preferred":[
        "Ban M\u00f4kkhamtun"
    ],
    "wof:name":"Ban Mokkhamtun",
    "wof:placetype":"locality"
},
  "geometry": {"coordinates":[101.37833999999999,20.47778],"type":"Point"}
}