{
  "type": "Feature",
  "properties": {
    "gn:admin1_code":"19.0",
    "gn:asciiname":"Ban Donglouang",
    "gn:country_code":"LA",
    "gn:dem":389,
    "gn:feature_class":"P",
    "gn:feature_code":"PPL",
    "gn:name":"Ban D\u00f4nglouang",
    "gn:population":0,
    "gn:timezone":"Asia/Vientiane",
    "iso:country":"LA",
    "name:lao_x_preferred":[
        "Ban D\u00f4nglouang"
    ],
    "wof:name":"Ban Donglouang",
    "wof:placetype":"locality"
},
  "geometry": {"coordinates":[106.1035,15.51479],"type":"Point"}
}