{
  "type": "Feature",
  "properties": {
    "gn:admin1_code":"16.0",
    "gn:asciiname":"Ban Phoukho",
    "gn:country_code":"LA",
    "gn:dem":814,
    "gn:feature_class":"P",
    "gn:feature_code":"PPL",
    "gn:name":"Ban Phoukho",
    "gn:population":0,
    "gn:timezone":"Asia/Vientiane",
    "iso:country":"LA",
    "name:lao_x_preferred":[
        "Ban Phoukho"
    ],
    "wof:name":"Ban Phoukho",
    "wof:placetype":"locality"
},
  "geometry": {"coordinates":[101.238,20.34076],"type":"Point"}
}