{
  "type": "Feature",
  "properties": {
    "gn:admin1_code":"7.0",
    "gn:asciiname":"Ban Lat-En",
    "gn:country_code":"LA",
    "gn:dem":298,
    "gn:feature_class":"P",
    "gn:feature_code":"PPL",
    "gn:name":"Ban Lat-En",
    "gn:population":0,
    "gn:timezone":"Asia/Vientiane",
    "iso:country":"LA",
    "name:lao_x_preferred":[
        "Ban Lat-En"
    ],
    "wof:name":"Ban Lat-En",
    "wof:placetype":"locality"
},
  "geometry": {"coordinates":[101.93142,20.01288],"type":"Point"}
}