{
  "type": "Feature",
  "properties": {
    "gn:admin1_code":"1.0",
    "gn:asciiname":"Ban Donngiou",
    "gn:country_code":"LA",
    "gn:dem":113,
    "gn:feature_class":"P",
    "gn:feature_code":"PPL",
    "gn:name":"Ban Donngiou",
    "gn:population":0,
    "gn:timezone":"Asia/Vientiane",
    "iso:country":"LA",
    "name:lao_x_preferred":[
        "Ban Donngiou"
    ],
    "wof:name":"Ban Donngiou",
    "wof:placetype":"locality"
},
  "geometry": {"coordinates":[106.95289,14.74607],"type":"Point"}
}