{
  "type": "Feature",
  "properties": {
    "gn:admin1_code":"17.0",
    "gn:asciiname":"Ban Houaykouan",
    "gn:country_code":"LA",
    "gn:dem":650,
    "gn:feature_class":"P",
    "gn:feature_code":"PPL",
    "gn:name":"Ban Houaykouan",
    "gn:population":0,
    "gn:timezone":"Asia/Vientiane",
    "iso:country":"LA",
    "name:und_x_variant":[
        "Ban Houaykouan (1)"
    ],
    "wof:name":"Ban Houaykouan",
    "wof:placetype":"locality"
},
  "geometry": {"coordinates":[101.98641000000001,19.70872],"type":"Point"}
}