{
  "type": "Feature",
  "properties": {
    "gn:admin1_code":"13.0",
    "gn:asciiname":"Nam Pouy",
    "gn:country_code":"LA",
    "gn:dem":342,
    "gn:feature_class":"P",
    "gn:feature_code":"PPL",
    "gn:name":"Nam Pouy",
    "gn:population":0,
    "gn:timezone":"Asia/Vientiane",
    "iso:country":"LA",
    "wof:name":"Nam Pouy",
    "wof:placetype":"locality"
},
  "geometry": {"coordinates":[101.51599,18.91977],"type":"Point"}
}