{
  "type": "Feature",
  "properties": {
    "gn:admin1_code":"20.0",
    "gn:asciiname":"Ban Phou",
    "gn:country_code":"LA",
    "gn:dem":183,
    "gn:feature_class":"P",
    "gn:feature_code":"PPL",
    "gn:name":"Ban Phou",
    "gn:population":0,
    "gn:timezone":"Asia/Vientiane",
    "iso:country":"LA",
    "name:lao_x_preferred":[
        "Ban Phou"
    ],
    "wof:name":"Ban Phou",
    "wof:placetype":"locality"
},
  "geometry": {"coordinates":[105.13171,17.0601],"type":"Point"}
}