{
  "type": "Feature",
  "properties": {
    "gn:admin1_code":"3.0",
    "gn:asciiname":"Ban Nasamong",
    "gn:country_code":"LA",
    "gn:dem":1254,
    "gn:feature_class":"P",
    "gn:feature_code":"PPL",
    "gn:name":"Ban Nasam\u00f4ng",
    "gn:population":0,
    "gn:timezone":"Asia/Vientiane",
    "iso:country":"LA",
    "name:lao_x_preferred":[
        "Ban Nasam\u00f4ng"
    ],
    "wof:name":"Ban Nasamong",
    "wof:placetype":"locality"
},
  "geometry": {"coordinates":[104.01767,20.15756],"type":"Point"}
}