{
  "type": "Feature",
  "properties": {
    "gn:admin1_code":"22.0",
    "gn:asciiname":"Ban Sibounhuang",
    "gn:country_code":"LA",
    "gn:dem":623,
    "gn:feature_class":"P",
    "gn:feature_code":"PPL",
    "gn:name":"Ban Sibounhuang",
    "gn:population":0,
    "gn:timezone":"Asia/Vientiane",
    "iso:country":"LA",
    "name:lao_x_preferred":[
        "Ban Sibounhuang"
    ],
    "wof:name":"Ban Sibounhuang",
    "wof:placetype":"locality"
},
  "geometry": {"coordinates":[100.96322000000001,20.47102000000001],"type":"Point"}
}