{
  "type": "Feature",
  "properties": {
    "gn:admin1_code":"3.0",
    "gn:asciiname":"Ban Xiang",
    "gn:country_code":"LA",
    "gn:dem":435,
    "gn:feature_class":"P",
    "gn:feature_code":"PPL",
    "gn:name":"Ban Xiang",
    "gn:population":0,
    "gn:timezone":"Asia/Vientiane",
    "iso:country":"LA",
    "name:lao_x_preferred":[
        "Ban Xiang"
    ],
    "wof:name":"Ban Xiang",
    "wof:placetype":"locality"
},
  "geometry": {"coordinates":[104.54886999999999,20.32],"type":"Point"}
}