{
  "type": "Feature",
  "properties": {
    "gn:admin1_code":"17.0",
    "gn:asciiname":"Ban Sanam Hay",
    "gn:country_code":"LA",
    "gn:dem":1088,
    "gn:feature_class":"P",
    "gn:feature_code":"PPL",
    "gn:name":"Ban Sanam Hay",
    "gn:population":0,
    "gn:timezone":"Asia/Vientiane",
    "iso:country":"LA",
    "wof:name":"Ban Sanam Hay",
    "wof:placetype":"locality"
},
  "geometry": {"coordinates":[102.58333,19.35],"type":"Point"}
}