{
  "type": "Feature",
  "properties": {
    "gn:admin1_code":"20.0",
    "gn:asciiname":"Ban Kengpho",
    "gn:country_code":"LA",
    "gn:dem":175,
    "gn:feature_class":"P",
    "gn:feature_code":"PPL",
    "gn:name":"Ban K\u00e8ngph\u00f4",
    "gn:population":0,
    "gn:timezone":"Asia/Vientiane",
    "iso:country":"LA",
    "wof:name":"Ban Kengpho",
    "wof:placetype":"locality"
},
  "geometry": {"coordinates":[105.91667,16.61667000000001],"type":"Point"}
}