{
  "type": "Feature",
  "properties": {
    "gn:admin1_code":"28.0",
    "gn:asciiname":"Ban Thaviang",
    "gn:country_code":"LA",
    "gn:dem":326,
    "gn:feature_class":"P",
    "gn:feature_code":"PPL",
    "gn:name":"Ban Thaviang",
    "gn:population":0,
    "gn:timezone":"Asia/Vientiane",
    "iso:country":"LA",
    "name:und_x_variant":[
        "Ban Ta Viang",
        "Ban Thaviang"
    ],
    "wof:name":"Ban Thaviang",
    "wof:placetype":"locality"
},
  "geometry": {"coordinates":[103.39951000000001,19.03912],"type":"Point"}
}