{
  "type": "Feature",
  "properties": {
    "gn:admin1_code":"23.0",
    "gn:asciiname":"Ban Nathomkouang",
    "gn:country_code":"LA",
    "gn:dem":511,
    "gn:feature_class":"P",
    "gn:feature_code":"PPL",
    "gn:name":"Ban Nath\u00f4mkouang",
    "gn:population":0,
    "gn:timezone":"Asia/Vientiane",
    "iso:country":"LA",
    "name:lao_x_preferred":[
        "Ban Nath\u00f4mkouang"
    ],
    "wof:name":"Ban Nathomkouang",
    "wof:placetype":"locality"
},
  "geometry": {"coordinates":[104.91591,18.16065],"type":"Point"}
}