{
  "type": "Feature",
  "properties": {
    "gn:admin1_code":"13.0",
    "gn:asciiname":"Ban Houaysin",
    "gn:country_code":"LA",
    "gn:dem":430,
    "gn:feature_class":"P",
    "gn:feature_code":"PPL",
    "gn:name":"Ban Houaysin",
    "gn:population":0,
    "gn:timezone":"Asia/Vientiane",
    "iso:country":"LA",
    "name:lao_x_preferred":[
        "Ban Houaysin"
    ],
    "wof:name":"Ban Houaysin",
    "wof:placetype":"locality"
},
  "geometry": {"coordinates":[101.44074999999999,18.96497],"type":"Point"}
}