{
  "type": "Feature",
  "properties": {
    "gn:admin1_code":"18.0",
    "gn:asciiname":"Ban Houaylo-Nua",
    "gn:country_code":"LA",
    "gn:dem":1226,
    "gn:feature_class":"P",
    "gn:feature_code":"PPL",
    "gn:name":"Ban Houayl\u00f4-Nua",
    "gn:population":0,
    "gn:timezone":"Asia/Vientiane",
    "iso:country":"LA",
    "name:lao_x_preferred":[
        "Ban Houayl\u00f4-Nua"
    ],
    "wof:name":"Ban Houaylo-Nua",
    "wof:placetype":"locality"
},
  "geometry": {"coordinates":[101.94859,21.62538],"type":"Point"}
}