{
  "type": "Feature",
  "properties": {
    "gn:admin1_code":"14.0",
    "gn:asciiname":"Ban Naxay",
    "gn:cc2":"LA",
    "gn:country_code":"LA",
    "gn:dem":1109,
    "gn:feature_class":"P",
    "gn:feature_code":"PPL",
    "gn:name":"Ban Naxay",
    "gn:population":0,
    "gn:timezone":"Asia/Vientiane",
    "iso:country":"LA",
    "name:und_x_variant":[
        "Ban Na Sai",
        "Ban Naxay"
    ],
    "wof:name":"Ban Naxay",
    "wof:placetype":"locality"
},
  "geometry": {"coordinates":[103.06667,19.36667000000001],"type":"Point"}
}