{
  "type": "Feature",
  "properties": {
    "gn:admin1_code":"20.0",
    "gn:asciiname":"Ban Nasongkhon",
    "gn:country_code":"LA",
    "gn:dem":184,
    "gn:feature_class":"P",
    "gn:feature_code":"PPL",
    "gn:name":"Ban Nasongkhon",
    "gn:population":0,
    "gn:timezone":"Asia/Vientiane",
    "iso:country":"LA",
    "name:und_x_variant":[
        "Ban Song Khone",
        "Ban Na Song Khone",
        "Ban Nasongkhon"
    ],
    "wof:name":"Ban Nasongkhon",
    "wof:placetype":"locality"
},
  "geometry": {"coordinates":[105.27724000000001,16.9464],"type":"Point"}
}