{
  "type": "Feature",
  "properties": {
    "gn:admin1_code":"14.0",
    "gn:asciiname":"Ban Louang",
    "gn:cc2":"LA",
    "gn:country_code":"LA",
    "gn:dem":1182,
    "gn:feature_class":"P",
    "gn:feature_code":"PPL",
    "gn:name":"Ban Louang",
    "gn:population":0,
    "gn:timezone":"Asia/Vientiane",
    "iso:country":"LA",
    "name:und_x_variant":[
        "Ban Luang",
        "Ban Louang"
    ],
    "wof:name":"Ban Louang",
    "wof:placetype":"locality"
},
  "geometry": {"coordinates":[103.21666999999999,19.53333],"type":"Point"}
}