{
  "type": "Feature",
  "properties": {
    "gn:admin1_code":"3.0",
    "gn:asciiname":"Ban Bo-Sam",
    "gn:country_code":"LA",
    "gn:dem":398,
    "gn:feature_class":"P",
    "gn:feature_code":"PPL",
    "gn:name":"Ban Bo-Sam",
    "gn:population":0,
    "gn:timezone":"Asia/Vientiane",
    "iso:country":"LA",
    "name:und_x_variant":[
        "Ban Bo",
        "Ban Bo-Sam"
    ],
    "wof:name":"Ban Bo-Sam",
    "wof:placetype":"locality"
},
  "geometry": {"coordinates":[104.42597000000001,20.40409],"type":"Point"}
}