{
  "type": "Feature",
  "properties": {
    "gn:admin1_code":"2.0",
    "gn:asciiname":"Ban Thopsok",
    "gn:country_code":"LA",
    "gn:dem":177,
    "gn:feature_class":"P",
    "gn:feature_code":"PPL",
    "gn:name":"Ban Th\u00f4psok",
    "gn:population":0,
    "gn:timezone":"Asia/Vientiane",
    "iso:country":"LA",
    "name:lao_x_preferred":[
        "Ban Th\u00f4psok"
    ],
    "name:und_x_variant":[
        "Ban Thop Sok",
        "Ban Thapsok"
    ],
    "wof:name":"Ban Thopsok",
    "wof:placetype":"locality"
},
  "geometry": {"coordinates":[106.03865999999999,14.79073],"type":"Point"}
}