{
  "type": "Feature",
  "properties": {
    "gn:admin1_code":"15.0",
    "gn:asciiname":"Ban Bonongxun",
    "gn:country_code":"LA",
    "gn:dem":210,
    "gn:feature_class":"P",
    "gn:feature_code":"PPL",
    "gn:name":"Ban Bonongxun",
    "gn:population":0,
    "gn:timezone":"Asia/Vientiane",
    "iso:country":"LA",
    "name:lao_x_preferred":[
        "Ban Bonongxun"
    ],
    "wof:name":"Ban Bonongxun",
    "wof:placetype":"locality"
},
  "geometry": {"coordinates":[104.51654000000001,17.94382000000001],"type":"Point"}
}