{
  "type": "Feature",
  "properties": {
    "gn:admin1_code":"7.0",
    "gn:asciiname":"Ban Tao",
    "gn:country_code":"LA",
    "gn:dem":692,
    "gn:feature_class":"P",
    "gn:feature_code":"PPL",
    "gn:name":"Ban Tao",
    "gn:population":0,
    "gn:timezone":"Asia/Vientiane",
    "iso:country":"LA",
    "name:lao_x_preferred":[
        "Ban Tao"
    ],
    "wof:name":"Ban Tao",
    "wof:placetype":"locality"
},
  "geometry": {"coordinates":[101.54862,20.7031],"type":"Point"}
}