{
  "type": "Feature",
  "properties": {
    "gn:admin1_code":"13.0",
    "gn:asciiname":"Ban Samphan",
    "gn:country_code":"LA",
    "gn:dem":539,
    "gn:feature_class":"P",
    "gn:feature_code":"PPL",
    "gn:name":"Ban Samphan",
    "gn:population":0,
    "gn:timezone":"Asia/Vientiane",
    "iso:country":"LA",
    "name:lao_x_preferred":[
        "Ban Samphan"
    ],
    "wof:name":"Ban Samphan",
    "wof:placetype":"locality"
},
  "geometry": {"coordinates":[101.73896000000001,19.70286],"type":"Point"}
}