{
  "type": "Feature",
  "properties": {
    "gn:admin1_code":"20.0",
    "gn:asciiname":"Ban Latdeng",
    "gn:country_code":"LA",
    "gn:dem":250,
    "gn:feature_class":"P",
    "gn:feature_code":"PPL",
    "gn:name":"Ban Latd\u00e8ng",
    "gn:population":0,
    "gn:timezone":"Asia/Vientiane",
    "iso:country":"LA",
    "name:lao_x_preferred":[
        "Ban Latd\u00e8ng"
    ],
    "wof:name":"Ban Latdeng",
    "wof:placetype":"locality"
},
  "geometry": {"coordinates":[105.89706,16.98079],"type":"Point"}
}