{
  "type": "Feature",
  "properties": {
    "gn:admin1_code":"15.0",
    "gn:asciiname":"Ban Phon-Gneng",
    "gn:country_code":"LA",
    "gn:dem":167,
    "gn:feature_class":"P",
    "gn:feature_code":"PPL",
    "gn:name":"Ban Ph\u00f4n-Gn\u00e8ng",
    "gn:population":0,
    "gn:timezone":"Asia/Vientiane",
    "iso:country":"LA",
    "name:lao_x_preferred":[
        "Ban Ph\u00f4n-Gn\u00e8ng"
    ],
    "wof:name":"Ban Phon-Gneng",
    "wof:placetype":"locality"
},
  "geometry": {"coordinates":[104.69219,18.00686],"type":"Point"}
}