{
  "type": "Feature",
  "properties": {
    "gn:admin1_code":"7.0",
    "gn:asciiname":"Ban Tamklok",
    "gn:country_code":"LA",
    "gn:dem":627,
    "gn:feature_class":"P",
    "gn:feature_code":"PPL",
    "gn:name":"Ban Tamkl\u00f4k",
    "gn:population":0,
    "gn:timezone":"Asia/Vientiane",
    "iso:country":"LA",
    "name:lao_x_preferred":[
        "Ban Tamkl\u00f4k"
    ],
    "wof:name":"Ban Tamklok",
    "wof:placetype":"locality"
},
  "geometry": {"coordinates":[101.99871,20.91883],"type":"Point"}
}