{
  "type": "Feature",
  "properties": {
    "gn:admin1_code":"17.0",
    "gn:asciiname":"Ban Souan",
    "gn:country_code":"LA",
    "gn:dem":315,
    "gn:feature_class":"P",
    "gn:feature_code":"PPL",
    "gn:name":"Ban Souan",
    "gn:population":0,
    "gn:timezone":"Asia/Vientiane",
    "iso:country":"LA",
    "name:und_x_variant":[
        "Ban Son",
        "Ban Xon",
        "Ban Souan"
    ],
    "wof:name":"Ban Souan",
    "wof:placetype":"locality"
},
  "geometry": {"coordinates":[102.21029,19.82039],"type":"Point"}
}