{
  "type": "Feature",
  "properties": {
    "gn:admin1_code":"16.0",
    "gn:asciiname":"Ban Lacha",
    "gn:country_code":"LA",
    "gn:dem":1199,
    "gn:feature_class":"P",
    "gn:feature_code":"PPL",
    "gn:name":"Ban Lacha",
    "gn:population":0,
    "gn:timezone":"Asia/Vientiane",
    "iso:country":"LA",
    "wof:name":"Ban Lacha",
    "wof:placetype":"locality"
},
  "geometry": {"coordinates":[101.16667,21.11667000000001],"type":"Point"}
}