{
  "type": "Feature",
  "properties": {
    "gn:admin1_code":"17.0",
    "gn:asciiname":"Ban Sophuang",
    "gn:country_code":"LA",
    "gn:dem":464,
    "gn:feature_class":"P",
    "gn:feature_code":"PPL",
    "gn:name":"Ban S\u00f4phuang",
    "gn:population":0,
    "gn:timezone":"Asia/Vientiane",
    "iso:country":"LA",
    "name:und_x_variant":[
        "Ban S\u00f4phuang",
        "Ban S\u00f4phuang (2)"
    ],
    "wof:name":"Ban Sophuang",
    "wof:placetype":"locality"
},
  "geometry": {"coordinates":[103.04978,20.21123],"type":"Point"}
}