{
  "type": "Feature",
  "properties": {
    "gn:admin1_code":"22.0",
    "gn:asciiname":"Ban Houaytheung",
    "gn:country_code":"LA",
    "gn:dem":460,
    "gn:feature_class":"P",
    "gn:feature_code":"PPL",
    "gn:name":"Ban Houaytheung",
    "gn:population":0,
    "gn:timezone":"Asia/Vientiane",
    "iso:country":"LA",
    "name:lao_x_preferred":[
        "Ban Houaytheung"
    ],
    "wof:name":"Ban Houaytheung",
    "wof:placetype":"locality"
},
  "geometry": {"coordinates":[100.60784,19.85904],"type":"Point"}
}