{
  "type": "Feature",
  "properties": {
    "gn:admin1_code":"13.0",
    "gn:asciiname":"Ban Muangmo",
    "gn:country_code":"LA",
    "gn:dem":250,
    "gn:feature_class":"P",
    "gn:feature_code":"PPL",
    "gn:name":"Ban Muangmo",
    "gn:population":0,
    "gn:timezone":"Asia/Vientiane",
    "iso:country":"LA",
    "name:und_x_variant":[
        "Muang Mo",
        "Ban Moung Mo",
        "Ban Muangmo"
    ],
    "wof:name":"Ban Muangmo",
    "wof:placetype":"locality"
},
  "geometry": {"coordinates":[101.37633,17.68987000000001],"type":"Point"}
}