{
  "type": "Feature",
  "properties": {
    "gn:admin1_code":"17.0",
    "gn:asciiname":"Ban Nagnang",
    "gn:country_code":"LA",
    "gn:dem":426,
    "gn:feature_class":"P",
    "gn:feature_code":"PPL",
    "gn:name":"Ban Nagnang",
    "gn:population":0,
    "gn:timezone":"Asia/Vientiane",
    "iso:country":"LA",
    "name:lao_x_preferred":[
        "Ban Nagnang"
    ],
    "wof:name":"Ban Nagnang",
    "wof:placetype":"locality"
},
  "geometry": {"coordinates":[102.52793,20.65194],"type":"Point"}
}