{
  "type": "Feature",
  "properties": {
    "gn:admin1_code":"17.0",
    "gn:asciiname":"Ban Houaykhan",
    "gn:country_code":"LA",
    "gn:dem":453,
    "gn:feature_class":"P",
    "gn:feature_code":"PPL",
    "gn:name":"Ban Houaykhan",
    "gn:population":0,
    "gn:timezone":"Asia/Vientiane",
    "iso:country":"LA",
    "name:lao_x_preferred":[
        "Ban Houaykhan"
    ],
    "wof:name":"Ban Houaykhan",
    "wof:placetype":"locality"
},
  "geometry": {"coordinates":[101.90539,19.83463],"type":"Point"}
}