{
  "type": "Feature",
  "properties": {
    "gn:admin1_code":"23.0",
    "gn:asciiname":"Ban Namouangkhai",
    "gn:country_code":"LA",
    "gn:dem":158,
    "gn:feature_class":"P",
    "gn:feature_code":"PPL",
    "gn:name":"Ban Namouangkhai",
    "gn:population":0,
    "gn:timezone":"Asia/Vientiane",
    "iso:country":"LA",
    "name:und_x_variant":[
        "Ban Namouangkahi",
        "Ban Namouangkhai"
    ],
    "wof:name":"Ban Namouangkhai",
    "wof:placetype":"locality"
},
  "geometry": {"coordinates":[104.11667,18.31667],"type":"Point"}
}