{
  "type": "Feature",
  "properties": {
    "gn:admin1_code":"22.0",
    "gn:asciiname":"Ban Phoulo",
    "gn:country_code":"LA",
    "gn:dem":627,
    "gn:feature_class":"P",
    "gn:feature_code":"PPL",
    "gn:name":"Ban Phoulo",
    "gn:population":0,
    "gn:timezone":"Asia/Vientiane",
    "iso:country":"LA",
    "name:lao_x_preferred":[
        "Ban Phoulo"
    ],
    "wof:name":"Ban Phoulo",
    "wof:placetype":"locality"
},
  "geometry": {"coordinates":[101.08275,20.19645],"type":"Point"}
}