{
  "type": "Feature",
  "properties": {
    "gn:admin1_code":"17.0",
    "gn:asciiname":"Ban Hai",
    "gn:country_code":"LA",
    "gn:dem":1135,
    "gn:feature_class":"P",
    "gn:feature_code":"PPL",
    "gn:name":"Ban Hai",
    "gn:population":0,
    "gn:timezone":"Asia/Vientiane",
    "iso:country":"LA",
    "name:lao_x_preferred":[
        "Ban Hai"
    ],
    "wof:name":"Ban Hai",
    "wof:placetype":"locality"
},
  "geometry": {"coordinates":[102.47677,20.83986],"type":"Point"}
}