{
  "type": "Feature",
  "properties": {
    "gn:admin1_code":"3.0",
    "gn:asciiname":"Ban Soy",
    "gn:country_code":"LA",
    "gn:dem":411,
    "gn:feature_class":"P",
    "gn:feature_code":"PPL",
    "gn:name":"Ban S\u00f4y",
    "gn:population":0,
    "gn:timezone":"Asia/Vientiane",
    "iso:country":"LA",
    "name:und_x_variant":[
        "Muang Soi",
        "Muang S\u00f4y",
        "Ban S\u00f4y"
    ],
    "wof:name":"Ban Soy",
    "wof:placetype":"locality"
},
  "geometry": {"coordinates":[104.53775,20.27207000000001],"type":"Point"}
}