{
  "type": "Feature",
  "properties": {
    "gn:admin1_code":"7.0",
    "gn:asciiname":"Ban Houayha",
    "gn:country_code":"LA",
    "gn:dem":546,
    "gn:feature_class":"P",
    "gn:feature_code":"PPL",
    "gn:name":"Ban Houayha",
    "gn:population":0,
    "gn:timezone":"Asia/Vientiane",
    "iso:country":"LA",
    "name:lao_x_preferred":[
        "Ban Houayha"
    ],
    "wof:name":"Ban Houayha",
    "wof:placetype":"locality"
},
  "geometry": {"coordinates":[101.5784,20.78619],"type":"Point"}
}