{
  "type": "Feature",
  "properties": {
    "gn:admin1_code":"26.0",
    "gn:asciiname":"Sekong",
    "gn:country_code":"LA",
    "gn:dem":148,
    "gn:feature_class":"P",
    "gn:feature_code":"PPL",
    "gn:name":"Sekong",
    "gn:population":0,
    "gn:timezone":"Asia/Vientiane",
    "iso:country":"LA",
    "wof:name":"Sekong",
    "wof:placetype":"locality"
},
  "geometry": {"coordinates":[106.72368,15.34582],"type":"Point"}
}