{
  "type": "Feature",
  "properties": {
    "gn:admin1_code":"26.0",
    "gn:asciiname":"Sekong",
    "gn:country_code":"LA",
    "gn:dem":148,
    "gn:feature_class":"P",
    "gn:feature_code":"PPL",
    "gn:name":"Sekong",
    "gn:population":0,
    "gn:timezone":"Asia/Vientiane",
    "iso:country":"LA",
    "name:fas_x_preferred":[
        "\u0633\u06cc\u06a9\u0648\u0646\u06af"
    ],
    "name:fra_x_preferred":[
        "S\u00e9kong"
    ],
    "name:nld_x_preferred":[
        "Ban Phone"
    ],
    "name:pol_x_preferred":[
        "Ban Phone"
    ],
    "name:rus_x_preferred":[
        "\u041b\u0430\u043c\u0430\u043c"
    ],
    "name:tha_x_preferred":[
        "\u0e40\u0e0b\u0e01\u0e2d\u0e07"
    ],
    "name:urd_x_preferred":[
        "\u0633\u06cc\u06a9\u0648\u0646\u06af"
    ],
    "wof:name":"Sekong",
    "wof:placetype":"locality"
},
  "geometry": {"coordinates":[106.72368,15.34582],"type":"Point"}
}