{
  "type": "Feature",
  "properties": {
    "gn:admin1_code":"26.0",
    "gn:asciiname":"Ban Thongvay",
    "gn:country_code":"LA",
    "gn:dem":806,
    "gn:feature_class":"P",
    "gn:feature_code":"PPL",
    "gn:name":"Ban Thongvay",
    "gn:population":0,
    "gn:timezone":"Asia/Vientiane",
    "iso:country":"LA",
    "name:lao_x_preferred":[
        "Ban Thongvay"
    ],
    "wof:name":"Ban Thongvay",
    "wof:placetype":"locality"
},
  "geometry": {"coordinates":[106.48229000000001,15.362],"type":"Point"}
}