{
  "type": "Feature",
  "properties": {
    "gn:admin1_code":"14.0",
    "gn:asciiname":"Ban Leng",
    "gn:country_code":"LA",
    "gn:dem":579,
    "gn:feature_class":"P",
    "gn:feature_code":"PPL",
    "gn:name":"Ban L\u00e8ng",
    "gn:population":0,
    "gn:timezone":"Asia/Vientiane",
    "iso:country":"LA",
    "name:lao_x_preferred":[
        "Ban L\u00e8ng"
    ],
    "name:und_x_variant":[
        "Ban L\u00e8"
    ],
    "wof:name":"Ban Leng",
    "wof:placetype":"locality"
},
  "geometry": {"coordinates":[103.61233,19.64832],"type":"Point"}
}