{
  "type": "Feature",
  "properties": {
    "gn:admin1_code":"17.0",
    "gn:asciiname":"Ban Houaythong",
    "gn:country_code":"LA",
    "gn:dem":785,
    "gn:feature_class":"P",
    "gn:feature_code":"PPL",
    "gn:name":"Ban Houaythong",
    "gn:population":0,
    "gn:timezone":"Asia/Vientiane",
    "iso:country":"LA",
    "name:lao_x_preferred":[
        "Ban Houaythong"
    ],
    "name:und_x_variant":[
        "Ban Thong"
    ],
    "wof:name":"Ban Houaythong",
    "wof:placetype":"locality"
},
  "geometry": {"coordinates":[102.27607,20.41268],"type":"Point"}
}