{
  "type": "Feature",
  "properties": {
    "gn:admin1_code":"14.0",
    "gn:asciiname":"Ban Khokmou",
    "gn:country_code":"LA",
    "gn:dem":1105,
    "gn:feature_class":"P",
    "gn:feature_code":"PPL",
    "gn:name":"Ban Khokmou",
    "gn:population":0,
    "gn:timezone":"Asia/Vientiane",
    "iso:country":"LA",
    "name:und_x_variant":[
        "Ban Khok Mou Nhay",
        "Ban Khokmou Gnai",
        "Ban Khok Mon Nhoy",
        "Ban Khokmou"
    ],
    "wof:name":"Ban Khokmou",
    "wof:placetype":"locality"
},
  "geometry": {"coordinates":[103.78158000000001,19.48495],"type":"Point"}
}