{
  "type": "Feature",
  "properties": {
    "gn:admin1_code":"22.0",
    "gn:asciiname":"Ban Phimonsin",
    "gn:country_code":"LA",
    "gn:dem":415,
    "gn:feature_class":"P",
    "gn:feature_code":"PPL",
    "gn:name":"Ban Phim\u00f4nsin",
    "gn:population":0,
    "gn:timezone":"Asia/Vientiane",
    "iso:country":"LA",
    "name:lao_x_preferred":[
        "Ban Phim\u00f4nsin"
    ],
    "wof:name":"Ban Phimonsin",
    "wof:placetype":"locality"
},
  "geometry": {"coordinates":[100.57671999999999,20.38182],"type":"Point"}
}