{
  "type": "Feature",
  "properties": {
    "gn:admin1_code":"18.0",
    "gn:asciiname":"Ban Lang-Ne",
    "gn:country_code":"LA",
    "gn:dem":1042,
    "gn:feature_class":"P",
    "gn:feature_code":"PPL",
    "gn:name":"Ban Lang-N\u00e8",
    "gn:population":0,
    "gn:timezone":"Asia/Vientiane",
    "iso:country":"LA",
    "name:lao_x_preferred":[
        "Ban Lang-N\u00e8"
    ],
    "name:und_x_variant":[
        "Lang Ne"
    ],
    "wof:name":"Ban Lang-Ne",
    "wof:placetype":"locality"
},
  "geometry": {"coordinates":[102.05958,21.52007],"type":"Point"}
}