{
  "type": "Feature",
  "properties": {
    "gn:admin1_code":"28.0",
    "gn:asciiname":"Ban Phak-Lan",
    "gn:country_code":"LA",
    "gn:dem":455,
    "gn:feature_class":"P",
    "gn:feature_code":"PPL",
    "gn:name":"Ban Phak-Lan",
    "gn:population":0,
    "gn:timezone":"Asia/Vientiane",
    "iso:country":"LA",
    "name:und_x_variant":[
        "Phak-Lan",
        "Pak Lane",
        "Ban Phak-Lan"
    ],
    "wof:name":"Ban Phak-Lan",
    "wof:placetype":"locality"
},
  "geometry": {"coordinates":[103.53333000000001,19.03333],"type":"Point"}
}