{
  "type": "Feature",
  "properties": {
    "gn:admin1_code":"19.0",
    "gn:asciiname":"Ban Taliap-Aho",
    "gn:country_code":"LA",
    "gn:dem":366,
    "gn:feature_class":"P",
    "gn:feature_code":"PPL",
    "gn:name":"Ban Taliap-Aho",
    "gn:population":0,
    "gn:timezone":"Asia/Vientiane",
    "iso:country":"LA",
    "name:lao_x_preferred":[
        "Ban Taliap-Aho"
    ],
    "wof:name":"Ban Taliap-Aho",
    "wof:placetype":"locality"
},
  "geometry": {"coordinates":[106.83262999999999,16.51276],"type":"Point"}
}