{
  "type": "Feature",
  "properties": {
    "gn:admin1_code":"2.0",
    "gn:asciiname":"Ban Senlam",
    "gn:country_code":"LA",
    "gn:dem":85,
    "gn:feature_class":"P",
    "gn:feature_code":"PPL",
    "gn:name":"Ban S\u00e8nlam",
    "gn:population":0,
    "gn:timezone":"Asia/Vientiane",
    "iso:country":"LA",
    "name:lao_x_preferred":[
        "Ban S\u00e8nlam"
    ],
    "wof:name":"Ban Senlam",
    "wof:placetype":"locality"
},
  "geometry": {"coordinates":[105.83902,14.21199],"type":"Point"}
}