{
  "type": "Feature",
  "properties": {
    "gn:admin1_code":"19.0",
    "gn:asciiname":"Ban Leunthon",
    "gn:country_code":"LA",
    "gn:dem":259,
    "gn:feature_class":"P",
    "gn:feature_code":"PPL",
    "gn:name":"Ban Leunth\u00f4n",
    "gn:population":0,
    "gn:timezone":"Asia/Vientiane",
    "iso:country":"LA",
    "name:lao_x_preferred":[
        "Ban Leunth\u00f4n"
    ],
    "wof:name":"Ban Leunthon",
    "wof:placetype":"locality"
},
  "geometry": {"coordinates":[106.28574,15.60221],"type":"Point"}
}