{
  "type": "Feature",
  "properties": {
    "gn:admin1_code":"3.0",
    "gn:asciiname":"Ban Nom",
    "gn:country_code":"LA",
    "gn:dem":773,
    "gn:feature_class":"P",
    "gn:feature_code":"PPL",
    "gn:name":"Ban Nom",
    "gn:population":0,
    "gn:timezone":"Asia/Vientiane",
    "iso:country":"LA",
    "name:lao_x_preferred":[
        "Ban Nom"
    ],
    "wof:name":"Ban Nom",
    "wof:placetype":"locality"
},
  "geometry": {"coordinates":[103.32129,20.52907],"type":"Point"}
}