{
  "type": "Feature",
  "properties": {
    "gn:admin1_code":"17.0",
    "gn:asciiname":"Ban Pholai",
    "gn:country_code":"LA",
    "gn:dem":1139,
    "gn:feature_class":"P",
    "gn:feature_code":"PPL",
    "gn:name":"Ban Pholai",
    "gn:population":0,
    "gn:timezone":"Asia/Vientiane",
    "iso:country":"LA",
    "name:lao_x_preferred":[
        "Ban Pholai"
    ],
    "wof:name":"Ban Pholai",
    "wof:placetype":"locality"
},
  "geometry": {"coordinates":[102.55662,19.63306],"type":"Point"}
}