{
  "type": "Feature",
  "properties": {
    "gn:admin1_code":"20.0",
    "gn:asciiname":"Ban Nakoung",
    "gn:country_code":"LA",
    "gn:dem":301,
    "gn:feature_class":"P",
    "gn:feature_code":"PPL",
    "gn:name":"Ban Nakoung",
    "gn:population":0,
    "gn:timezone":"Asia/Vientiane",
    "iso:country":"LA",
    "name:lao_x_preferred":[
        "Ban Nakoung"
    ],
    "wof:name":"Ban Nakoung",
    "wof:placetype":"locality"
},
  "geometry": {"coordinates":[106.00758999999999,16.02993],"type":"Point"}
}