{
  "type": "Feature",
  "properties": {
    "gn:admin1_code":"20.0",
    "gn:asciiname":"Ban Klong-Kang",
    "gn:country_code":"LA",
    "gn:dem":172,
    "gn:feature_class":"P",
    "gn:feature_code":"PPL",
    "gn:name":"Ban Klong-Kang",
    "gn:population":0,
    "gn:timezone":"Asia/Vientiane",
    "iso:country":"LA",
    "name:lao_x_preferred":[
        "Ban Klong-Kang"
    ],
    "wof:name":"Ban Klong-Kang",
    "wof:placetype":"locality"
},
  "geometry": {"coordinates":[105.52972,16.63604],"type":"Point"}
}