{
  "type": "Feature",
  "properties": {
    "gn:admin1_code":"1.0",
    "gn:asciiname":"Ban Mixai",
    "gn:country_code":"LA",
    "gn:dem":115,
    "gn:feature_class":"P",
    "gn:feature_code":"PPL",
    "gn:name":"Ban Mixai",
    "gn:population":0,
    "gn:timezone":"Asia/Vientiane",
    "iso:country":"LA",
    "name:lao_x_preferred":[
        "Ban Mixai"
    ],
    "name:und_x_variant":[
        "Ban Koniac",
        "Ban Kaniac",
        "Ban Kaniak",
        "Ban Kagnak"
    ],
    "wof:name":"Ban Mixai",
    "wof:placetype":"locality"
},
  "geometry": {"coordinates":[106.84238999999999,15.08106],"type":"Point"}
}