{
  "type": "Feature",
  "properties": {
    "gn:admin1_code":"27.0",
    "gn:asciiname":"Ban Mun",
    "gn:country_code":"LA",
    "gn:dem":447,
    "gn:feature_class":"P",
    "gn:feature_code":"PPL",
    "gn:name":"Ban Mun",
    "gn:population":0,
    "gn:timezone":"Asia/Vientiane",
    "iso:country":"LA",
    "name:und_x_variant":[
        "Ban Mum",
        "Ban Mun"
    ],
    "wof:name":"Ban Mun",
    "wof:placetype":"locality"
},
  "geometry": {"coordinates":[102.27757,19.19864],"type":"Point"}
}