{
  "type": "Feature",
  "properties": {
    "gn:admin1_code":"19.0",
    "gn:asciiname":"Ban Natanxe",
    "gn:country_code":"LA",
    "gn:dem":134,
    "gn:feature_class":"P",
    "gn:feature_code":"PPL",
    "gn:name":"Ban Natanx\u00e9",
    "gn:population":0,
    "gn:timezone":"Asia/Vientiane",
    "iso:country":"LA",
    "name:und_x_variant":[
        "Ban Na Tan",
        "Ban Natanx\u00e9"
    ],
    "wof:name":"Ban Natanxe",
    "wof:placetype":"locality"
},
  "geometry": {"coordinates":[105.79528999999999,15.44522],"type":"Point"}
}