{
  "type": "Feature",
  "properties": {
    "gn:admin1_code":"17.0",
    "gn:asciiname":"Ban Houaythoum",
    "gn:country_code":"LA",
    "gn:dem":378,
    "gn:feature_class":"P",
    "gn:feature_code":"PPL",
    "gn:name":"Ban Houaythoum",
    "gn:population":0,
    "gn:timezone":"Asia/Vientiane",
    "iso:country":"LA",
    "name:und_x_variant":[
        "Ban Houay Toum",
        "Ban Houei Toum",
        "Ban Houaythoum"
    ],
    "wof:name":"Ban Houaythoum",
    "wof:placetype":"locality"
},
  "geometry": {"coordinates":[102.37602,20.18889],"type":"Point"}
}