{
  "type": "Feature",
  "properties": {
    "gn:admin1_code":"19.0",
    "gn:asciiname":"Ban Pongphanay",
    "gn:country_code":"LA",
    "gn:dem":254,
    "gn:feature_class":"P",
    "gn:feature_code":"PPL",
    "gn:name":"Ban P\u00f4ngphanay",
    "gn:population":0,
    "gn:timezone":"Asia/Vientiane",
    "iso:country":"LA",
    "name:und_x_variant":[
        "Ban Pong Panay",
        "Ban P\u00f4ngphanay"
    ],
    "wof:name":"Ban Pongphanay",
    "wof:placetype":"locality"
},
  "geometry": {"coordinates":[106.10773,15.61364],"type":"Point"}
}