{
  "type": "Feature",
  "properties": {
    "gn:admin1_code":"18.0",
    "gn:asciiname":"Ban Khamkhoun",
    "gn:country_code":"LA",
    "gn:dem":1094,
    "gn:feature_class":"P",
    "gn:feature_code":"PPL",
    "gn:name":"Ban Khamkhoun",
    "gn:population":0,
    "gn:timezone":"Asia/Vientiane",
    "iso:country":"LA",
    "name:lao_x_preferred":[
        "Ban Khamkhoun"
    ],
    "wof:name":"Ban Khamkhoun",
    "wof:placetype":"locality"
},
  "geometry": {"coordinates":[102.15519,21.53082],"type":"Point"}
}