{
  "type": "Feature",
  "properties": {
    "gn:admin1_code":"22.0",
    "gn:asciiname":"Ban Sanouk",
    "gn:country_code":"LA",
    "gn:dem":431,
    "gn:feature_class":"P",
    "gn:feature_code":"PPL",
    "gn:name":"Ban Sanouk",
    "gn:population":0,
    "gn:timezone":"Asia/Vientiane",
    "iso:country":"LA",
    "name:und_x_variant":[
        "Ban Se Nouk",
        "Ban Sanouk"
    ],
    "wof:name":"Ban Sanouk",
    "wof:placetype":"locality"
},
  "geometry": {"coordinates":[101.21366999999999,20.30537],"type":"Point"}
}