{
  "type": "Feature",
  "properties": {
    "gn:admin1_code":"7.0",
    "gn:asciiname":"Ban Moksouk",
    "gn:country_code":"LA",
    "gn:dem":974,
    "gn:feature_class":"P",
    "gn:feature_code":"PPL",
    "gn:name":"Ban M\u00f4ksouk",
    "gn:population":0,
    "gn:timezone":"Asia/Vientiane",
    "iso:country":"LA",
    "name:lao_x_preferred":[
        "Ban M\u00f4ksouk"
    ],
    "name:und_x_variant":[
        "Ban M\u00f4ksouk (1)"
    ],
    "wof:name":"Ban Moksouk",
    "wof:placetype":"locality"
},
  "geometry": {"coordinates":[101.96898,20.06922],"type":"Point"}
}