{
  "type": "Feature",
  "properties": {
    "gn:admin1_code":"17.0",
    "gn:asciiname":"Ban Phia Chan",
    "gn:country_code":"LA",
    "gn:dem":737,
    "gn:feature_class":"P",
    "gn:feature_code":"PPL",
    "gn:name":"Ban Phia Chan",
    "gn:population":0,
    "gn:timezone":"Asia/Vientiane",
    "iso:country":"LA",
    "wof:name":"Ban Phia Chan",
    "wof:placetype":"locality"
},
  "geometry": {"coordinates":[102.91667,20.33333],"type":"Point"}
}