{
  "type": "Feature",
  "properties": {
    "gn:admin1_code":"20.0",
    "gn:asciiname":"Ban Naxuak",
    "gn:country_code":"LA",
    "gn:dem":179,
    "gn:feature_class":"P",
    "gn:feature_code":"PPL",
    "gn:name":"Ban Naxuak",
    "gn:population":0,
    "gn:timezone":"Asia/Vientiane",
    "iso:country":"LA",
    "name:und_x_variant":[
        "Ban Na Seuk",
        "Ban Naxuak"
    ],
    "wof:name":"Ban Naxuak",
    "wof:placetype":"locality"
},
  "geometry": {"coordinates":[105.66893,16.01744],"type":"Point"}
}