{
  "type": "Feature",
  "properties": {
    "gn:admin1_code":"7.0",
    "gn:asciiname":"Ban Ay",
    "gn:country_code":"LA",
    "gn:dem":785,
    "gn:feature_class":"P",
    "gn:feature_code":"PPL",
    "gn:name":"Ban Ay",
    "gn:population":0,
    "gn:timezone":"Asia/Vientiane",
    "iso:country":"LA",
    "name:lao_x_preferred":[
        "Ban Ay"
    ],
    "name:und_x_variant":[
        "Muang Ay",
        "Muong Hai",
        "Muang Hai",
        "Muang Hay"
    ],
    "wof:name":"Ban Ay",
    "wof:placetype":"locality"
},
  "geometry": {"coordinates":[101.81215,21.04968],"type":"Point"}
}