{
  "type": "Feature",
  "properties": {
    "gn:admin1_code":"26.0",
    "gn:asciiname":"Ban Halong",
    "gn:country_code":"LA",
    "gn:dem":630,
    "gn:feature_class":"P",
    "gn:feature_code":"PPL",
    "gn:name":"Ban Halong",
    "gn:population":0,
    "gn:timezone":"Asia/Vientiane",
    "iso:country":"LA",
    "name:lao_x_preferred":[
        "Ban Halong"
    ],
    "wof:name":"Ban Halong",
    "wof:placetype":"locality"
},
  "geometry": {"coordinates":[106.85472,15.47238],"type":"Point"}
}