{
  "type": "Feature",
  "properties": {
    "gn:admin1_code":"20.0",
    "gn:asciiname":"Thong Louang",
    "gn:cc2":"LA",
    "gn:country_code":"LA",
    "gn:dem":240,
    "gn:feature_class":"P",
    "gn:feature_code":"PPL",
    "gn:name":"Thong Louang",
    "gn:population":0,
    "gn:timezone":"Asia/Vientiane",
    "iso:country":"LA",
    "name:und_x_variant":[
        "Ban Th\u00f4nglouang",
        "Thong Louang"
    ],
    "wof:name":"Thong Louang",
    "wof:placetype":"locality"
},
  "geometry": {"coordinates":[106.10389000000001,17.04167],"type":"Point"}
}