{
  "type": "Feature",
  "properties": {
    "gn:admin1_code":"15.0",
    "gn:asciiname":"Ban Nagnavay",
    "gn:country_code":"LA",
    "gn:dem":159,
    "gn:feature_class":"P",
    "gn:feature_code":"PPL",
    "gn:name":"Ban Nagnavay",
    "gn:population":0,
    "gn:timezone":"Asia/Vientiane",
    "iso:country":"LA",
    "name:und_x_variant":[
        "Ban Na Nha Vay",
        "Ban Nagnavay"
    ],
    "wof:name":"Ban Nagnavay",
    "wof:placetype":"locality"
},
  "geometry": {"coordinates":[104.79521,17.44544],"type":"Point"}
}