{
  "type": "Feature",
  "properties": {
    "gn:admin1_code":"19.0",
    "gn:asciiname":"Ban Houaykhen",
    "gn:country_code":"LA",
    "gn:dem":162,
    "gn:feature_class":"P",
    "gn:feature_code":"PPL",
    "gn:name":"Ban Houaykh\u00e8n",
    "gn:population":0,
    "gn:timezone":"Asia/Vientiane",
    "iso:country":"LA",
    "name:lao_x_preferred":[
        "Ban Houaykh\u00e8n"
    ],
    "wof:name":"Ban Houaykhen",
    "wof:placetype":"locality"
},
  "geometry": {"coordinates":[105.77726,15.68982],"type":"Point"}
}