{
  "type": "Feature",
  "properties": {
    "gn:admin1_code":"13.0",
    "gn:asciiname":"Ban Namouang",
    "gn:country_code":"LA",
    "gn:dem":586,
    "gn:feature_class":"P",
    "gn:feature_code":"PPL",
    "gn:name":"Ban Namouang",
    "gn:population":0,
    "gn:timezone":"Asia/Vientiane",
    "iso:country":"LA",
    "name:lao_x_preferred":[
        "Ban Namouang"
    ],
    "name:und_x_variant":[
        "Ban Mouong",
        "Ban Moung"
    ],
    "wof:name":"Ban Namouang",
    "wof:placetype":"locality"
},
  "geometry": {"coordinates":[101.1922,18.37978],"type":"Point"}
}