{
  "type": "Feature",
  "properties": {
    "gn:admin1_code":"27.0",
    "gn:asciiname":"Ban Naxom",
    "gn:country_code":"LA",
    "gn:dem":192,
    "gn:feature_class":"P",
    "gn:feature_code":"PPL",
    "gn:name":"Ban Naxom",
    "gn:population":0,
    "gn:timezone":"Asia/Vientiane",
    "iso:country":"LA",
    "name:und_x_variant":[
        "Ban Na Some"
    ],
    "wof:name":"Ban Naxom",
    "wof:placetype":"locality"
},
  "geometry": {"coordinates":[102.42109000000001,18.55175],"type":"Point"}
}