{
  "type": "Feature",
  "properties": {
    "gn:admin1_code":"17.0",
    "gn:asciiname":"Ban Phoudam",
    "gn:country_code":"LA",
    "gn:dem":979,
    "gn:feature_class":"P",
    "gn:feature_code":"PPL",
    "gn:name":"Ban Phoudam",
    "gn:population":0,
    "gn:timezone":"Asia/Vientiane",
    "iso:country":"LA",
    "name:lao_x_preferred":[
        "Ban Phoudam"
    ],
    "wof:name":"Ban Phoudam",
    "wof:placetype":"locality"
},
  "geometry": {"coordinates":[102.11895,20.0254],"type":"Point"}
}