{
  "type": "Feature",
  "properties": {
    "gn:admin1_code":"16.0",
    "gn:asciiname":"Ban Houadoy",
    "gn:country_code":"LA",
    "gn:dem":649,
    "gn:feature_class":"P",
    "gn:feature_code":"PPL",
    "gn:name":"Ban Houadoy",
    "gn:population":0,
    "gn:timezone":"Asia/Vientiane",
    "iso:country":"LA",
    "name:lao_x_preferred":[
        "Ban Houadoy"
    ],
    "wof:name":"Ban Houadoy",
    "wof:placetype":"locality"
},
  "geometry": {"coordinates":[100.7332,20.93113],"type":"Point"}
}