{
  "type": "Feature",
  "properties": {
    "gn:admin1_code":"19.0",
    "gn:asciiname":"Ban Khonsay",
    "gn:country_code":"LA",
    "gn:dem":149,
    "gn:feature_class":"P",
    "gn:feature_code":"PPL",
    "gn:name":"Ban Khonsay",
    "gn:population":0,
    "gn:timezone":"Asia/Vientiane",
    "iso:country":"LA",
    "name:und_x_variant":[
        "Ban Khone Say",
        "Ban Khonsay"
    ],
    "wof:name":"Ban Khonsay",
    "wof:placetype":"locality"
},
  "geometry": {"coordinates":[105.90575,15.69427],"type":"Point"}
}