{
  "type": "Feature",
  "properties": {
    "gn:admin1_code":"2.0",
    "gn:asciiname":"Ban Khamyat",
    "gn:country_code":"LA",
    "gn:dem":132,
    "gn:feature_class":"P",
    "gn:feature_code":"PPL",
    "gn:name":"Ban Khamyat",
    "gn:population":0,
    "gn:timezone":"Asia/Vientiane",
    "iso:country":"LA",
    "name:und_x_variant":[
        "Ban Khan Vat",
        "Ban Khamyat"
    ],
    "wof:name":"Ban Khamyat",
    "wof:placetype":"locality"
},
  "geometry": {"coordinates":[105.82384,15.4021],"type":"Point"}
}