{
  "type": "Feature",
  "properties": {
    "gn:admin1_code":"14.0",
    "gn:asciiname":"Ban Tasseng",
    "gn:country_code":"LA",
    "gn:dem":1230,
    "gn:feature_class":"P",
    "gn:feature_code":"PPL",
    "gn:name":"Ban Tasseng",
    "gn:population":0,
    "gn:timezone":"Asia/Vientiane",
    "iso:country":"LA",
    "wof:name":"Ban Tasseng",
    "wof:placetype":"locality"
},
  "geometry": {"coordinates":[103.88333,19.11667000000001],"type":"Point"}
}