{
  "type": "Feature",
  "properties": {
    "gn:admin1_code":"15.0",
    "gn:asciiname":"Ban Xiangven",
    "gn:country_code":"LA",
    "gn:dem":154,
    "gn:feature_class":"P",
    "gn:feature_code":"PPL",
    "gn:name":"Ban Xiangv\u00e8n",
    "gn:population":0,
    "gn:timezone":"Asia/Vientiane",
    "iso:country":"LA",
    "name:und_x_variant":[
        "Ban Xieng V\u00e8ne",
        "Ban Xiangv\u00e8n"
    ],
    "wof:name":"Ban Xiangven",
    "wof:placetype":"locality"
},
  "geometry": {"coordinates":[104.86609,17.42683],"type":"Point"}
}