{
  "type": "Feature",
  "properties": {
    "gn:admin1_code":"23.0",
    "gn:asciiname":"Ban Pakouay",
    "gn:country_code":"LA",
    "gn:dem":307,
    "gn:feature_class":"P",
    "gn:feature_code":"PPL",
    "gn:name":"Ban Pakouay",
    "gn:population":0,
    "gn:timezone":"Asia/Vientiane",
    "iso:country":"LA",
    "name:lao_x_preferred":[
        "Ban Pakouay"
    ],
    "wof:name":"Ban Pakouay",
    "wof:placetype":"locality"
},
  "geometry": {"coordinates":[104.22286,18.69046],"type":"Point"}
}