{
  "type": "Feature",
  "properties": {
    "gn:admin1_code":"2.0",
    "gn:asciiname":"Ban Dua-Nua",
    "gn:country_code":"LA",
    "gn:dem":108,
    "gn:feature_class":"P",
    "gn:feature_code":"PPL",
    "gn:name":"Ban Dua-Nua",
    "gn:population":0,
    "gn:timezone":"Asia/Vientiane",
    "iso:country":"LA",
    "name:lao_x_preferred":[
        "Ban Dua-Nua"
    ],
    "wof:name":"Ban Dua-Nua",
    "wof:placetype":"locality"
},
  "geometry": {"coordinates":[105.79931000000001,15.25036],"type":"Point"}
}