{
  "type": "Feature",
  "properties": {
    "gn:admin1_code":"20.0",
    "gn:asciiname":"Ban Dongkum",
    "gn:country_code":"LA",
    "gn:dem":164,
    "gn:feature_class":"P",
    "gn:feature_code":"PPL",
    "gn:name":"Ban D\u00f4ngkum",
    "gn:population":0,
    "gn:timezone":"Asia/Vientiane",
    "iso:country":"LA",
    "name:lao_x_preferred":[
        "Ban D\u00f4ngkum"
    ],
    "name:und_x_variant":[
        "Dong Kum"
    ],
    "wof:name":"Ban Dongkum",
    "wof:placetype":"locality"
},
  "geometry": {"coordinates":[105.32187999999999,16.77432],"type":"Point"}
}