{
  "type": "Feature",
  "properties": {
    "gn:admin1_code":"3.0",
    "gn:asciiname":"Ban Houayhok",
    "gn:cc2":"LA",
    "gn:country_code":"LA",
    "gn:dem":1420,
    "gn:feature_class":"P",
    "gn:feature_code":"PPL",
    "gn:name":"Ban Houayh\u00f4k",
    "gn:population":0,
    "gn:timezone":"Asia/Vientiane",
    "iso:country":"LA",
    "name:und_x_variant":[
        "Ban Houei Hok",
        "Ban Houayh\u00f4k"
    ],
    "wof:name":"Ban Houayhok",
    "wof:placetype":"locality"
},
  "geometry": {"coordinates":[104.55,19.63333],"type":"Point"}
}