{
  "type": "Feature",
  "properties": {
    "gn:admin1_code":"7.0",
    "gn:asciiname":"Ban Kat",
    "gn:country_code":"LA",
    "gn:dem":605,
    "gn:feature_class":"P",
    "gn:feature_code":"PPL",
    "gn:name":"Ban Kat",
    "gn:population":0,
    "gn:timezone":"Asia/Vientiane",
    "iso:country":"LA",
    "name:lao_x_preferred":[
        "Ban Kat"
    ],
    "wof:name":"Ban Kat",
    "wof:placetype":"locality"
},
  "geometry": {"coordinates":[102.08792,20.752],"type":"Point"}
}