{
  "type": "Feature",
  "properties": {
    "gn:admin1_code":"7.0",
    "gn:asciiname":"Ban Houaykhagnay-Nua",
    "gn:country_code":"LA",
    "gn:dem":380,
    "gn:feature_class":"P",
    "gn:feature_code":"PPL",
    "gn:name":"Ban Houaykhagnay-Nua",
    "gn:population":0,
    "gn:timezone":"Asia/Vientiane",
    "iso:country":"LA",
    "name:und_x_variant":[
        "Ban Kha Niai Nieou",
        "Ban Khok Mai",
        "Ban Houaykhagnay-Nua"
    ],
    "wof:name":"Ban Houaykhagnay-Nua",
    "wof:placetype":"locality"
},
  "geometry": {"coordinates":[102.14336,20.14767],"type":"Point"}
}