{
  "type": "Feature",
  "properties": {
    "gn:admin1_code":"24.0",
    "gn:asciiname":"Ban Nalom",
    "gn:country_code":"LA",
    "gn:dem":181,
    "gn:feature_class":"P",
    "gn:feature_code":"PPL",
    "gn:name":"Ban Nalom",
    "gn:population":0,
    "gn:timezone":"Asia/Vientiane",
    "iso:country":"LA",
    "name:lao_x_preferred":[
        "Ban Nalom"
    ],
    "wof:name":"Ban Nalom",
    "wof:placetype":"locality"
},
  "geometry": {"coordinates":[102.72898000000001,18.07904],"type":"Point"}
}