{
  "type": "Feature",
  "properties": {
    "gn:admin1_code":"26.0",
    "gn:asciiname":"Ban Dakchapa",
    "gn:country_code":"LA",
    "gn:dem":1156,
    "gn:feature_class":"P",
    "gn:feature_code":"PPL",
    "gn:name":"Ban Dakchapa",
    "gn:population":0,
    "gn:timezone":"Asia/Vientiane",
    "iso:country":"LA",
    "name:lao_x_preferred":[
        "Ban Dakchapa"
    ],
    "wof:name":"Ban Dakchapa",
    "wof:placetype":"locality"
},
  "geometry": {"coordinates":[107.21467,15.27325],"type":"Point"}
}