{
  "type": "Feature",
  "properties": {
    "gn:admin1_code":"3.0",
    "gn:asciiname":"Ban Phiangkhoun",
    "gn:country_code":"LA",
    "gn:dem":304,
    "gn:feature_class":"P",
    "gn:feature_code":"PPL",
    "gn:name":"Ban Phiangkhoun",
    "gn:population":0,
    "gn:timezone":"Asia/Vientiane",
    "iso:country":"LA",
    "name:lao_x_preferred":[
        "Ban Phiangkhoun"
    ],
    "wof:name":"Ban Phiangkhoun",
    "wof:placetype":"locality"
},
  "geometry": {"coordinates":[104.7525,19.88836],"type":"Point"}
}