{
  "type": "Feature",
  "properties": {
    "gn:admin1_code":"3.0",
    "gn:asciiname":"Ban Vek",
    "gn:country_code":"LA",
    "gn:dem":1121,
    "gn:feature_class":"P",
    "gn:feature_code":"PPL",
    "gn:name":"Ban V\u00e8k",
    "gn:population":0,
    "gn:timezone":"Asia/Vientiane",
    "iso:country":"LA",
    "wof:name":"Ban Vek",
    "wof:placetype":"locality"
},
  "geometry": {"coordinates":[103.89917,20.18944],"type":"Point"}
}