{
  "type": "Feature",
  "properties": {
    "gn:admin1_code":"2.0",
    "gn:asciiname":"Ban Donhi",
    "gn:country_code":"LA",
    "gn:dem":106,
    "gn:feature_class":"P",
    "gn:feature_code":"PPL",
    "gn:name":"Ban Donhi",
    "gn:population":0,
    "gn:timezone":"Asia/Vientiane",
    "iso:country":"LA",
    "name:lao_x_preferred":[
        "Ban Donhi"
    ],
    "wof:name":"Ban Donhi",
    "wof:placetype":"locality"
},
  "geometry": {"coordinates":[105.87688,14.74527],"type":"Point"}
}