{
  "type": "Feature",
  "properties": {
    "gn:admin1_code":"19.0",
    "gn:asciiname":"Ta Riep A Shao",
    "gn:country_code":"LA",
    "gn:dem":345,
    "gn:feature_class":"P",
    "gn:feature_code":"PPL",
    "gn:name":"Ta Riep A Shao",
    "gn:population":0,
    "gn:timezone":"Asia/Vientiane",
    "iso:country":"LA",
    "wof:name":"Ta Riep A Shao",
    "wof:placetype":"locality"
},
  "geometry": {"coordinates":[106.83333,16.48333],"type":"Point"}
}