{
  "type": "Feature",
  "properties": {
    "gn:admin1_code":"14.0",
    "gn:asciiname":"Ban Phiangphang",
    "gn:country_code":"LA",
    "gn:dem":434,
    "gn:feature_class":"P",
    "gn:feature_code":"PPL",
    "gn:name":"Ban Phiangphang",
    "gn:population":0,
    "gn:timezone":"Asia/Vientiane",
    "iso:country":"LA",
    "name:lao_x_preferred":[
        "Ban Phiangphang"
    ],
    "wof:name":"Ban Phiangphang",
    "wof:placetype":"locality"
},
  "geometry": {"coordinates":[103.87211000000001,19.94694],"type":"Point"}
}