{
  "type": "Feature",
  "properties": {
    "gn:admin1_code":"2.0",
    "gn:asciiname":"Ban Xaymoun",
    "gn:country_code":"LA",
    "gn:dem":105,
    "gn:feature_class":"P",
    "gn:feature_code":"PPL",
    "gn:name":"Ban Xaymoun",
    "gn:population":0,
    "gn:timezone":"Asia/Vientiane",
    "iso:country":"LA",
    "name:und_x_variant":[
        "Ban Sai Moun",
        "Ban Xaymoun"
    ],
    "wof:name":"Ban Xaymoun",
    "wof:placetype":"locality"
},
  "geometry": {"coordinates":[105.71939,15.19787],"type":"Point"}
}