{
  "type": "Feature",
  "properties": {
    "gn:admin1_code":"17.0",
    "gn:asciiname":"Ban Houaythong-Tai",
    "gn:country_code":"LA",
    "gn:dem":900,
    "gn:feature_class":"P",
    "gn:feature_code":"PPL",
    "gn:name":"Ban Houaythong-Tai",
    "gn:population":0,
    "gn:timezone":"Asia/Vientiane",
    "iso:country":"LA",
    "name:lao_x_preferred":[
        "Ban Houaythong-Tai"
    ],
    "wof:name":"Ban Houaythong-Tai",
    "wof:placetype":"locality"
},
  "geometry": {"coordinates":[102.92561000000001,20.36868],"type":"Point"}
}