{
  "type": "Feature",
  "properties": {
    "gn:admin1_code":"19.0",
    "gn:asciiname":"Ban Chong-Gnai",
    "gn:country_code":"LA",
    "gn:dem":254,
    "gn:feature_class":"P",
    "gn:feature_code":"PPL",
    "gn:name":"Ban Ch\u00f4ng-Gnai",
    "gn:population":0,
    "gn:timezone":"Asia/Vientiane",
    "iso:country":"LA",
    "name:lao_x_preferred":[
        "Ban Ch\u00f4ng-Gnai"
    ],
    "name:und_x_variant":[
        "Ban Chong Nhao"
    ],
    "wof:name":"Ban Chong-Gnai",
    "wof:placetype":"locality"
},
  "geometry": {"coordinates":[106.29083,15.61441],"type":"Point"}
}