{
  "type": "Feature",
  "properties": {
    "gn:admin1_code":"7.0",
    "gn:asciiname":"Ban Xenoy",
    "gn:country_code":"LA",
    "gn:dem":646,
    "gn:feature_class":"P",
    "gn:feature_code":"PPL",
    "gn:name":"Ban X\u00e9noy",
    "gn:population":0,
    "gn:timezone":"Asia/Vientiane",
    "iso:country":"LA",
    "name:und_x_variant":[
        "Senoy",
        "Ban X\u00e9noy"
    ],
    "wof:name":"Ban Xenoy",
    "wof:placetype":"locality"
},
  "geometry": {"coordinates":[102.18333,20.81667],"type":"Point"}
}