{
  "type": "Feature",
  "properties": {
    "gn:admin1_code":"20.0",
    "gn:asciiname":"Ban Xiangxoum",
    "gn:country_code":"LA",
    "gn:dem":156,
    "gn:feature_class":"P",
    "gn:feature_code":"PPL",
    "gn:name":"Ban Xiangxoum",
    "gn:population":0,
    "gn:timezone":"Asia/Vientiane",
    "iso:country":"LA",
    "name:und_x_variant":[
        "Ban Sieng Soum",
        "Ban Xiangxoum"
    ],
    "wof:name":"Ban Xiangxoum",
    "wof:placetype":"locality"
},
  "geometry": {"coordinates":[105.24466,16.46306],"type":"Point"}
}