{
  "type": "Feature",
  "properties": {
    "gn:admin1_code":"7.0",
    "gn:asciiname":"Ban Nahom",
    "gn:country_code":"LA",
    "gn:dem":887,
    "gn:feature_class":"P",
    "gn:feature_code":"PPL",
    "gn:name":"Ban Nah\u00f4m",
    "gn:population":0,
    "gn:timezone":"Asia/Vientiane",
    "iso:country":"LA",
    "name:lao_x_preferred":[
        "Ban Nah\u00f4m"
    ],
    "wof:name":"Ban Nahom",
    "wof:placetype":"locality"
},
  "geometry": {"coordinates":[101.67055999999999,20.19656],"type":"Point"}
}