{
  "type": "Feature",
  "properties": {
    "gn:admin1_code":"2.0",
    "gn:asciiname":"Ban Khamao-Kang",
    "gn:country_code":"LA",
    "gn:dem":83,
    "gn:feature_class":"P",
    "gn:feature_code":"PPL",
    "gn:name":"Ban Khamao-Kang",
    "gn:population":0,
    "gn:timezone":"Asia/Vientiane",
    "iso:country":"LA",
    "name:lao_x_preferred":[
        "Ban Khamao-Kang"
    ],
    "name:und_x_variant":[
        "Ban Kamaou Khan",
        "Ban Khamao Kang"
    ],
    "wof:name":"Ban Khamao-Kang",
    "wof:placetype":"locality"
},
  "geometry": {"coordinates":[105.76304,14.09208],"type":"Point"}
}