{
  "type": "Feature",
  "properties": {
    "gn:admin1_code":"16.0",
    "gn:asciiname":"Ban Eula",
    "gn:country_code":"LA",
    "gn:dem":972,
    "gn:feature_class":"P",
    "gn:feature_code":"PPL",
    "gn:name":"Ban Eula",
    "gn:population":0,
    "gn:timezone":"Asia/Vientiane",
    "iso:country":"LA",
    "name:lao_x_preferred":[
        "Ban Eula"
    ],
    "wof:name":"Ban Eula",
    "wof:placetype":"locality"
},
  "geometry": {"coordinates":[100.96732,21.36527],"type":"Point"}
}