{
  "type": "Feature",
  "properties": {
    "gn:admin1_code":"13.0",
    "gn:asciiname":"Ban Pakpa",
    "gn:country_code":"LA",
    "gn:dem":264,
    "gn:feature_class":"P",
    "gn:feature_code":"PPL",
    "gn:name":"Ban Pakpa",
    "gn:population":0,
    "gn:timezone":"Asia/Vientiane",
    "iso:country":"LA",
    "name:lao_x_preferred":[
        "Ban Pakpa"
    ],
    "wof:name":"Ban Pakpa",
    "wof:placetype":"locality"
},
  "geometry": {"coordinates":[101.81332,19.14614],"type":"Point"}
}