{
  "type": "Feature",
  "properties": {
    "gn:admin1_code":"14.0",
    "gn:asciiname":"Ban Hai",
    "gn:country_code":"LA",
    "gn:dem":1119,
    "gn:feature_class":"P",
    "gn:feature_code":"PPL",
    "gn:name":"Ban Hai",
    "gn:population":0,
    "gn:timezone":"Asia/Vientiane",
    "iso:country":"LA",
    "name:und_x_variant":[
        "Ban Suon Hay",
        "Ban Souanhai",
        "Ban Hai"
    ],
    "wof:name":"Ban Hai",
    "wof:placetype":"locality"
},
  "geometry": {"coordinates":[103.1279,19.26866],"type":"Point"}
}