{
  "type": "Feature",
  "properties": {
    "gn:admin1_code":"17.0",
    "gn:asciiname":"Ban Hatkeo",
    "gn:country_code":"LA",
    "gn:dem":383,
    "gn:feature_class":"P",
    "gn:feature_code":"PPL",
    "gn:name":"Ban Hatk\u00e8o",
    "gn:population":0,
    "gn:timezone":"Asia/Vientiane",
    "iso:country":"LA",
    "name:lao_x_preferred":[
        "Ban Hatk\u00e8o"
    ],
    "wof:name":"Ban Hatkeo",
    "wof:placetype":"locality"
},
  "geometry": {"coordinates":[102.75776,20.31872000000001],"type":"Point"}
}