{
  "type": "Feature",
  "properties": {
    "gn:admin1_code":"17.0",
    "gn:asciiname":"Ban Khok",
    "gn:country_code":"LA",
    "gn:dem":308,
    "gn:feature_class":"P",
    "gn:feature_code":"PPL",
    "gn:name":"Ban Kh\u00f4k",
    "gn:population":0,
    "gn:timezone":"Asia/Vientiane",
    "iso:country":"LA",
    "name:lao_x_preferred":[
        "Ban Kh\u00f4k"
    ],
    "wof:name":"Ban Khok",
    "wof:placetype":"locality"
},
  "geometry": {"coordinates":[102.20779,20.05834],"type":"Point"}
}