{
  "type": "Feature",
  "properties": {
    "gn:admin1_code":"14.0",
    "gn:asciiname":"Phonsavan",
    "gn:country_code":"LA",
    "gn:dem":1107,
    "gn:feature_class":"P",
    "gn:feature_code":"PPL",
    "gn:name":"Phonsavan",
    "gn:population":0,
    "gn:timezone":"Asia/Vientiane",
    "iso:country":"LA",
    "name:ceb_x_preferred":[
        "Phonsavan"
    ],
    "name:ces_x_preferred":[
        "Phonsavan"
    ],
    "name:deu_x_preferred":[
        "Phonsavan"
    ],
    "name:eng_x_preferred":[
        "Phonsavan"
    ],
    "name:epo_x_preferred":[
        "Phonsavan"
    ],
    "name:fas_x_preferred":[
        "\u0641\u0648\u0646\u0633\u0627\u0648\u0627\u0646"
    ],
    "name:fra_x_preferred":[
        "Phonsavan"
    ],
    "name:ita_x_preferred":[
        "Phonsavan"
    ],
    "name:jpn_x_preferred":[
        "\u30dd\u30fc\u30f3\u30b5\u30ef\u30f3\u90e1"
    ],
    "name:lao_x_preferred":[
        "\u0ec2\u0e9e\u0e99\u0eaa\u0eb0\u0eab\u0ea7\u0eb1\u0e99"
    ],
    "name:lit_x_preferred":[
        "Ponsavanas"
    ],
    "name:nld_x_preferred":[
        "Phonsavan"
    ],
    "name:pol_x_preferred":[
        "Phonsavan"
    ],
    "name:rus_x_preferred":[
        "\u041f\u0445\u043e\u043d\u0441\u0430\u0432\u0430\u043d"
    ],
    "name:spa_x_preferred":[
        "Phonsavan"
    ],
    "name:swe_x_preferred":[
        "Phonsavan"
    ],
    "name:tha_x_preferred":[
        "\u0e42\u0e1e\u0e19\u0e2a\u0e27\u0e23\u0e23\u0e04\u0e4c"
    ],
    "name:tha_x_variant":[
        "\u0e42\u0e1e\u0e19\u0e2a\u0e30\u0e2b\u0e27\u0e31\u0e19"
    ],
    "name:urd_x_preferred":[
        "\u0641\u0648\u0646\u0633\u0627\u0648\u0627\u0646"
    ],
    "name:vie_x_preferred":[
        "Ph\u00f4n Xa V\u1eb3n"
    ],
    "name:vie_x_variant":[
        "Phonsavan"
    ],
    "name:war_x_preferred":[
        "Phonsavan"
    ],
    "name:zho_x_preferred":[
        "\u8c50\u6c99\u7063"
    ],
    "wof:name":"Phonsavan",
    "wof:placetype":"locality"
},
  "geometry": {"coordinates":[103.18804,19.45011],"type":"Point"}
}