{
  "type": "Feature",
  "properties": {
    "gn:admin1_code":"27.0",
    "gn:asciiname":"Ban Nakhom",
    "gn:country_code":"LA",
    "gn:dem":403,
    "gn:feature_class":"P",
    "gn:feature_code":"PPL",
    "gn:name":"Ban Nakh\u00f4m",
    "gn:population":0,
    "gn:timezone":"Asia/Vientiane",
    "iso:country":"LA",
    "name:lao_x_preferred":[
        "Ban Nakh\u00f4m"
    ],
    "wof:name":"Ban Nakhom",
    "wof:placetype":"locality"
},
  "geometry": {"coordinates":[102.22601,19.17139],"type":"Point"}
}