{
  "type": "Feature",
  "properties": {
    "gn:admin1_code":"7.0",
    "gn:asciiname":"Ban Kongtha",
    "gn:country_code":"LA",
    "gn:dem":1084,
    "gn:feature_class":"P",
    "gn:feature_code":"PPL",
    "gn:name":"Ban K\u00f4ngtha",
    "gn:population":0,
    "gn:timezone":"Asia/Vientiane",
    "iso:country":"LA",
    "name:lao_x_preferred":[
        "Ban K\u00f4ngtha"
    ],
    "wof:name":"Ban Kongtha",
    "wof:placetype":"locality"
},
  "geometry": {"coordinates":[101.93028,20.97348],"type":"Point"}
}