{
  "type": "Feature",
  "properties": {
    "gn:admin1_code":"7.0",
    "gn:asciiname":"Ban Phoulouang",
    "gn:country_code":"LA",
    "gn:dem":1339,
    "gn:feature_class":"P",
    "gn:feature_code":"PPL",
    "gn:name":"Ban Phoulouang",
    "gn:population":0,
    "gn:timezone":"Asia/Vientiane",
    "iso:country":"LA",
    "name:lao_x_preferred":[
        "Ban Phoulouang"
    ],
    "wof:name":"Ban Phoulouang",
    "wof:placetype":"locality"
},
  "geometry": {"coordinates":[100.99384000000001,19.98109],"type":"Point"}
}