{
  "type": "Feature",
  "properties": {
    "gn:admin1_code":"20.0",
    "gn:asciiname":"Ban Samsaat",
    "gn:country_code":"LA",
    "gn:dem":176,
    "gn:feature_class":"P",
    "gn:feature_code":"PPL",
    "gn:name":"Ban Samsaat",
    "gn:population":0,
    "gn:timezone":"Asia/Vientiane",
    "iso:country":"LA",
    "name:lao_x_preferred":[
        "Ban Samsaat"
    ],
    "wof:name":"Ban Samsaat",
    "wof:placetype":"locality"
},
  "geometry": {"coordinates":[104.95147,16.79828],"type":"Point"}
}