{
  "type": "Feature",
  "properties": {
    "gn:admin1_code":"17.0",
    "gn:asciiname":"Ban Phoutit-Buang",
    "gn:country_code":"LA",
    "gn:dem":1206,
    "gn:feature_class":"P",
    "gn:feature_code":"PPL",
    "gn:name":"Ban Phoutit-Buang",
    "gn:population":0,
    "gn:timezone":"Asia/Vientiane",
    "iso:country":"LA",
    "name:lao_x_preferred":[
        "Ban Phoutit-Buang"
    ],
    "wof:name":"Ban Phoutit-Buang",
    "wof:placetype":"locality"
},
  "geometry": {"coordinates":[102.78568,20.51755],"type":"Point"}
}