{
  "type": "Feature",
  "properties": {
    "gn:admin1_code":"23.0",
    "gn:asciiname":"Ban Thongnami",
    "gn:country_code":"LA",
    "gn:dem":163,
    "gn:feature_class":"P",
    "gn:feature_code":"PPL",
    "gn:name":"Ban Th\u00f4ngnami",
    "gn:population":0,
    "gn:timezone":"Asia/Vientiane",
    "iso:country":"LA",
    "name:lao_x_preferred":[
        "Ban Th\u00f4ngnami"
    ],
    "wof:name":"Ban Thongnami",
    "wof:placetype":"locality"
},
  "geometry": {"coordinates":[104.23466000000001,18.17343],"type":"Point"}
}