{
  "type": "Feature",
  "properties": {
    "gn:admin1_code":"3.0",
    "gn:asciiname":"Ban Cong Meo",
    "gn:country_code":"LA",
    "gn:dem":633,
    "gn:feature_class":"P",
    "gn:feature_code":"PPL",
    "gn:name":"Ban Cong Meo",
    "gn:population":0,
    "gn:timezone":"Asia/Vientiane",
    "iso:country":"LA",
    "wof:name":"Ban Cong Meo",
    "wof:placetype":"locality"
},
  "geometry": {"coordinates":[104.15000000000001,20.71667],"type":"Point"}
}