{
  "type": "Feature",
  "properties": {
    "gn:admin1_code":"2.0",
    "gn:asciiname":"Ban Hangkhonsadam",
    "gn:country_code":"LA",
    "gn:dem":71,
    "gn:feature_class":"P",
    "gn:feature_code":"PPL",
    "gn:name":"Ban Hangkhonsadam",
    "gn:population":0,
    "gn:timezone":"Asia/Vientiane",
    "iso:country":"LA",
    "name:lao_x_preferred":[
        "Ban Hangkhonsadam"
    ],
    "name:und_x_variant":[
        "Ban Dan Sdam",
        "Ban Dan Sadam",
        "Ban Donsadam"
    ],
    "wof:name":"Ban Hangkhonsadam",
    "wof:placetype":"locality"
},
  "geometry": {"coordinates":[105.96044000000001,13.93811],"type":"Point"}
}