{
  "type": "Feature",
  "properties": {
    "gn:admin1_code":"20.0",
    "gn:asciiname":"Ban Nongdindeng",
    "gn:country_code":"LA",
    "gn:dem":138,
    "gn:feature_class":"P",
    "gn:feature_code":"PPL",
    "gn:name":"Ban Nongdind\u00e8ng",
    "gn:population":0,
    "gn:timezone":"Asia/Vientiane",
    "iso:country":"LA",
    "name:und_x_variant":[
        "Ban Dinh Deng",
        "Ban Nongdind\u00e8ng"
    ],
    "wof:name":"Ban Nongdindeng",
    "wof:placetype":"locality"
},
  "geometry": {"coordinates":[105.39483,16.36556],"type":"Point"}
}