{
  "type": "Feature",
  "properties": {
    "gn:admin1_code":"27.0",
    "gn:asciiname":"Ban Nakhong",
    "gn:country_code":"LA",
    "gn:dem":179,
    "gn:feature_class":"P",
    "gn:feature_code":"PPL",
    "gn:name":"Ban Nakhong",
    "gn:population":0,
    "gn:timezone":"Asia/Vientiane",
    "iso:country":"LA",
    "name:und_x_variant":[
        "Ban Na Thong",
        "Ban Nakhong"
    ],
    "wof:name":"Ban Nakhong",
    "wof:placetype":"locality"
},
  "geometry": {"coordinates":[102.57657,18.3235],"type":"Point"}
}