{
  "type": "Feature",
  "properties": {
    "gn:admin1_code":"20.0",
    "gn:asciiname":"Ban Naxakhou",
    "gn:country_code":"LA",
    "gn:dem":173,
    "gn:feature_class":"P",
    "gn:feature_code":"PPL",
    "gn:name":"Ban Naxakhou",
    "gn:population":0,
    "gn:timezone":"Asia/Vientiane",
    "iso:country":"LA",
    "name:und_x_variant":[
        "Ban Sa Cou",
        "Ban Na Sa Khou",
        "Ban Naxakhou"
    ],
    "wof:name":"Ban Naxakhou",
    "wof:placetype":"locality"
},
  "geometry": {"coordinates":[105.56086000000001,16.7276],"type":"Point"}
}