{
  "type": "Feature",
  "properties": {
    "gn:admin1_code":"17.0",
    "gn:asciiname":"Ban Sen-Nua",
    "gn:country_code":"LA",
    "gn:dem":1152,
    "gn:feature_class":"P",
    "gn:feature_code":"PPL",
    "gn:name":"Ban S\u00e8n-Nua",
    "gn:population":0,
    "gn:timezone":"Asia/Vientiane",
    "iso:country":"LA",
    "name:lao_x_preferred":[
        "Ban S\u00e8n-Nua"
    ],
    "wof:name":"Ban Sen-Nua",
    "wof:placetype":"locality"
},
  "geometry": {"coordinates":[102.25095,20.55187],"type":"Point"}
}