{
  "type": "Feature",
  "properties": {
    "gn:admin1_code":"15.0",
    "gn:asciiname":"Ban Kenglek",
    "gn:country_code":"LA",
    "gn:dem":168,
    "gn:feature_class":"P",
    "gn:feature_code":"PPL",
    "gn:name":"Ban K\u00e8ngl\u00e9k",
    "gn:population":0,
    "gn:timezone":"Asia/Vientiane",
    "iso:country":"LA",
    "name:und_x_variant":[
        "Ban Keng Leck",
        "Ban K\u00e8ngl\u00e9k"
    ],
    "wof:name":"Ban Kenglek",
    "wof:placetype":"locality"
},
  "geometry": {"coordinates":[105.20705,17.60385],"type":"Point"}
}