{
  "type": "Feature",
  "properties": {
    "gn:admin1_code":"15.0",
    "gn:asciiname":"Ban Nongkaching",
    "gn:country_code":"LA",
    "gn:dem":174,
    "gn:feature_class":"P",
    "gn:feature_code":"PPL",
    "gn:name":"Ban Nongkaching",
    "gn:population":0,
    "gn:timezone":"Asia/Vientiane",
    "iso:country":"LA",
    "name:und_x_variant":[
        "Ban Ka Ching",
        "Ban Nang Xa Ching",
        "Ban Nongkaching"
    ],
    "wof:name":"Ban Nongkaching",
    "wof:placetype":"locality"
},
  "geometry": {"coordinates":[105.18449,17.62279],"type":"Point"}
}