{
  "type": "Feature",
  "properties": {
    "gn:admin1_code":"20.0",
    "gn:asciiname":"Ban Taluay",
    "gn:country_code":"LA",
    "gn:dem":199,
    "gn:feature_class":"P",
    "gn:feature_code":"PPL",
    "gn:name":"Ban Taluay",
    "gn:population":0,
    "gn:timezone":"Asia/Vientiane",
    "iso:country":"LA",
    "name:lao_x_preferred":[
        "Ban Taluay"
    ],
    "wof:name":"Ban Taluay",
    "wof:placetype":"locality"
},
  "geometry": {"coordinates":[106.14297000000001,16.26712],"type":"Point"}
}