{
  "type": "Feature",
  "properties": {
    "gn:admin1_code":"14.0",
    "gn:asciiname":"Ban Phon-Ngam",
    "gn:country_code":"LA",
    "gn:dem":659,
    "gn:feature_class":"P",
    "gn:feature_code":"PPL",
    "gn:name":"Ban Ph\u00f4n-Ngam",
    "gn:population":0,
    "gn:timezone":"Asia/Vientiane",
    "iso:country":"LA",
    "name:lao_x_preferred":[
        "Ban Ph\u00f4n-Ngam"
    ],
    "wof:name":"Ban Phon-Ngam",
    "wof:placetype":"locality"
},
  "geometry": {"coordinates":[103.52598,19.65989],"type":"Point"}
}