{
  "type": "Feature",
  "properties": {
    "gn:admin1_code":"23.0",
    "gn:asciiname":"Ban Thoay-Gnai",
    "gn:country_code":"LA",
    "gn:dem":166,
    "gn:feature_class":"P",
    "gn:feature_code":"PPL",
    "gn:name":"Ban Thoay-Gnai",
    "gn:population":0,
    "gn:timezone":"Asia/Vientiane",
    "iso:country":"LA",
    "name:lao_x_preferred":[
        "Ban Thoay-Gnai"
    ],
    "name:und_x_variant":[
        "Ban Thoue",
        "Ban Thouei",
        "Ban Toay",
        "Ban Thouay-gnai",
        "Ban Thon",
        "Ban Thoay"
    ],
    "wof:name":"Ban Thoay-Gnai",
    "wof:placetype":"locality"
},
  "geometry": {"coordinates":[103.21348999999999,18.27937],"type":"Point"}
}