{
  "type": "Feature",
  "properties": {
    "gn:admin1_code":"20.0",
    "gn:asciiname":"Ban Phakkhagna-Tai",
    "gn:country_code":"LA",
    "gn:dem":182,
    "gn:feature_class":"P",
    "gn:feature_code":"PPL",
    "gn:name":"Ban Phakkhagna-Tai",
    "gn:population":0,
    "gn:timezone":"Asia/Vientiane",
    "iso:country":"LA",
    "name:lao_x_preferred":[
        "Ban Phakkhagna-Tai"
    ],
    "wof:name":"Ban Phakkhagna-Tai",
    "wof:placetype":"locality"
},
  "geometry": {"coordinates":[104.82356,16.72161],"type":"Point"}
}