{
  "type": "Feature",
  "properties": {
    "gn:admin1_code":"2.0",
    "gn:asciiname":"Ban Latsasin",
    "gn:country_code":"LA",
    "gn:dem":753,
    "gn:feature_class":"P",
    "gn:feature_code":"PPL",
    "gn:name":"Ban Latsasin",
    "gn:population":0,
    "gn:timezone":"Asia/Vientiane",
    "iso:country":"LA",
    "name:und_x_variant":[
        "Ban Latasin",
        "Ban Latassasine",
        "Ban Latsasin"
    ],
    "wof:name":"Ban Latsasin",
    "wof:placetype":"locality"
},
  "geometry": {"coordinates":[106.60189,15.05447],"type":"Point"}
}