{
  "type": "Feature",
  "properties": {
    "gn:admin1_code":"17.0",
    "gn:asciiname":"Ban Sen Nam Hai",
    "gn:cc2":"LA",
    "gn:country_code":"LA",
    "gn:dem":991,
    "gn:feature_class":"P",
    "gn:feature_code":"PPL",
    "gn:name":"Ban S\u00e8n Nam Hai",
    "gn:population":0,
    "gn:timezone":"Asia/Vientiane",
    "iso:country":"LA",
    "name:und_x_variant":[
        "Ban Ben Nan Hai",
        "Ban S\u00e8n Nam Hai"
    ],
    "wof:name":"Ban Sen Nam Hai",
    "wof:placetype":"locality"
},
  "geometry": {"coordinates":[102.56667,19.76667],"type":"Point"}
}