{
  "type": "Feature",
  "properties": {
    "gn:admin1_code":"18.0",
    "gn:asciiname":"Mok Phek",
    "gn:country_code":"LA",
    "gn:dem":949,
    "gn:feature_class":"P",
    "gn:feature_code":"PPL",
    "gn:name":"Mok Phek",
    "gn:population":0,
    "gn:timezone":"Asia/Vientiane",
    "iso:country":"LA",
    "wof:name":"Mok Phek",
    "wof:placetype":"locality"
},
  "geometry": {"coordinates":[102.48333,20.88333],"type":"Point"}
}