{
  "type": "Feature",
  "properties": {
    "gn:admin1_code":"23.0",
    "gn:asciiname":"Ban Namyang",
    "gn:country_code":"LA",
    "gn:dem":351,
    "gn:feature_class":"P",
    "gn:feature_code":"PPL",
    "gn:name":"Ban Namyang",
    "gn:population":0,
    "gn:timezone":"Asia/Vientiane",
    "iso:country":"LA",
    "name:lao_x_preferred":[
        "Ban Namyang"
    ],
    "name:und_x_variant":[
        "Ban Nam Giang"
    ],
    "wof:name":"Ban Namyang",
    "wof:placetype":"locality"
},
  "geometry": {"coordinates":[104.49204,18.53205],"type":"Point"}
}