{
  "type": "Feature",
  "properties": {
    "gn:admin1_code":"7.0",
    "gn:asciiname":"Ban Phimho",
    "gn:country_code":"LA",
    "gn:dem":1549,
    "gn:feature_class":"P",
    "gn:feature_code":"PPL",
    "gn:name":"Ban Phimho",
    "gn:population":0,
    "gn:timezone":"Asia/Vientiane",
    "iso:country":"LA",
    "name:lao_x_preferred":[
        "Ban Phimho"
    ],
    "wof:name":"Ban Phimho",
    "wof:placetype":"locality"
},
  "geometry": {"coordinates":[101.43098000000001,19.93587],"type":"Point"}
}