{
  "type": "Feature",
  "properties": {
    "gn:admin1_code":"26.0",
    "gn:asciiname":"Ban Xu-Ang",
    "gn:country_code":"LA",
    "gn:dem":1270,
    "gn:feature_class":"P",
    "gn:feature_code":"PPL",
    "gn:name":"Ban Xu-Ang",
    "gn:population":0,
    "gn:timezone":"Asia/Vientiane",
    "iso:country":"LA",
    "name:lao_x_preferred":[
        "Ban Xu-Ang"
    ],
    "name:und_x_variant":[
        "Xouang",
        "Ban Dakxouang"
    ],
    "wof:name":"Ban Xu-Ang",
    "wof:placetype":"locality"
},
  "geometry": {"coordinates":[107.25776999999999,15.52506],"type":"Point"}
}