{
  "type": "Feature",
  "properties": {
    "gn:admin1_code":"13.0",
    "gn:asciiname":"Ban Namon",
    "gn:country_code":"LA",
    "gn:dem":580,
    "gn:feature_class":"P",
    "gn:feature_code":"PPL",
    "gn:name":"Ban Nam\u00f4n",
    "gn:population":0,
    "gn:timezone":"Asia/Vientiane",
    "iso:country":"LA",
    "name:lao_x_preferred":[
        "Ban Nam\u00f4n"
    ],
    "wof:name":"Ban Namon",
    "wof:placetype":"locality"
},
  "geometry": {"coordinates":[101.19253,18.40604],"type":"Point"}
}