{
  "type": "Feature",
  "properties": {
    "gn:admin1_code":"22.0",
    "gn:asciiname":"Ban Phoutho",
    "gn:country_code":"LA",
    "gn:dem":456,
    "gn:feature_class":"P",
    "gn:feature_code":"PPL",
    "gn:name":"Ban Phouth\u00f4",
    "gn:population":0,
    "gn:timezone":"Asia/Vientiane",
    "iso:country":"LA",
    "name:lao_x_preferred":[
        "Ban Phouth\u00f4"
    ],
    "wof:name":"Ban Phoutho",
    "wof:placetype":"locality"
},
  "geometry": {"coordinates":[100.72611999999999,20.05861],"type":"Point"}
}