{
  "type": "Feature",
  "properties": {
    "gn:admin1_code":"20.0",
    "gn:asciiname":"Ban Namkham",
    "gn:country_code":"LA",
    "gn:dem":157,
    "gn:feature_class":"P",
    "gn:feature_code":"PPL",
    "gn:name":"Ban Namkham",
    "gn:population":0,
    "gn:timezone":"Asia/Vientiane",
    "iso:country":"LA",
    "name:lao_x_preferred":[
        "Ban Namkham"
    ],
    "wof:name":"Ban Namkham",
    "wof:placetype":"locality"
},
  "geometry": {"coordinates":[105.18758,16.32992999999999],"type":"Point"}
}