{
  "type": "Feature",
  "properties": {
    "gn:admin1_code":"2.0",
    "gn:asciiname":"Ban Outhoum-Kao",
    "gn:country_code":"LA",
    "gn:dem":96,
    "gn:feature_class":"P",
    "gn:feature_code":"PPL",
    "gn:name":"Ban Outhoum-Kao",
    "gn:population":0,
    "gn:timezone":"Asia/Vientiane",
    "iso:country":"LA",
    "name:lao_x_preferred":[
        "Ban Outhoum-Kao"
    ],
    "name:und_x_variant":[
        "Ban Outhoum",
        "Ban Outthoum Kau"
    ],
    "wof:name":"Ban Outhoum-Kao",
    "wof:placetype":"locality"
},
  "geometry": {"coordinates":[105.82153999999998,14.51726],"type":"Point"}
}