{
  "type": "Feature",
  "properties": {
    "gn:admin1_code":"13.0",
    "gn:asciiname":"Ban Nakhok",
    "gn:country_code":"LA",
    "gn:dem":367,
    "gn:feature_class":"P",
    "gn:feature_code":"PPL",
    "gn:name":"Ban Nakh\u00f4k",
    "gn:population":0,
    "gn:timezone":"Asia/Vientiane",
    "iso:country":"LA",
    "name:lao_x_preferred":[
        "Ban Nakh\u00f4k"
    ],
    "wof:name":"Ban Nakhok",
    "wof:placetype":"locality"
},
  "geometry": {"coordinates":[101.56635,18.70329],"type":"Point"}
}