{
  "type": "Feature",
  "properties": {
    "gn:admin1_code":"2.0",
    "gn:asciiname":"Ban Nakasang",
    "gn:country_code":"LA",
    "gn:dem":86,
    "gn:feature_class":"P",
    "gn:feature_code":"PPL",
    "gn:name":"Ban Nakasang",
    "gn:population":0,
    "gn:timezone":"Asia/Vientiane",
    "iso:country":"LA",
    "name:und_x_variant":[
        "Ban Nakasong",
        "Nakasong"
    ],
    "wof:name":"Ban Nakasang",
    "wof:placetype":"locality"
},
  "geometry": {"coordinates":[105.92253999999998,14.00378],"type":"Point"}
}