{
  "type": "Feature",
  "properties": {
    "gn:admin1_code":"20.0",
    "gn:asciiname":"Ban Houayngoua-Tai",
    "gn:country_code":"LA",
    "gn:dem":187,
    "gn:feature_class":"P",
    "gn:feature_code":"PPL",
    "gn:name":"Ban Houayngoua-Tai",
    "gn:population":0,
    "gn:timezone":"Asia/Vientiane",
    "iso:country":"LA",
    "name:lao_x_preferred":[
        "Ban Houayngoua-Tai"
    ],
    "name:und_x_variant":[
        "Ban Houei Ngoua Tay"
    ],
    "wof:name":"Ban Houayngoua-Tai",
    "wof:placetype":"locality"
},
  "geometry": {"coordinates":[105.54349999999999,16.84844],"type":"Point"}
}