{
  "type": "Feature",
  "properties": {
    "gn:admin1_code":"18.0",
    "gn:asciiname":"Ban Houayleng",
    "gn:country_code":"LA",
    "gn:dem":597,
    "gn:feature_class":"P",
    "gn:feature_code":"PPL",
    "gn:name":"Ban Houayl\u00e8ng",
    "gn:population":0,
    "gn:timezone":"Asia/Vientiane",
    "iso:country":"LA",
    "name:lao_x_preferred":[
        "Ban Houayl\u00e8ng"
    ],
    "wof:name":"Ban Houayleng",
    "wof:placetype":"locality"
},
  "geometry": {"coordinates":[102.5316,21.18215],"type":"Point"}
}