{
  "type": "Feature",
  "properties": {
    "gn:admin1_code":"13.0",
    "gn:asciiname":"Ban Phonsak",
    "gn:country_code":"LA",
    "gn:dem":289,
    "gn:feature_class":"P",
    "gn:feature_code":"PPL",
    "gn:name":"Ban Ph\u00f4nsak",
    "gn:population":0,
    "gn:timezone":"Asia/Vientiane",
    "iso:country":"LA",
    "name:und_x_variant":[
        "Sala",
        "Ban Ph\u00f4nsak"
    ],
    "wof:name":"Ban Phonsak",
    "wof:placetype":"locality"
},
  "geometry": {"coordinates":[101.47068,18.5791],"type":"Point"}
}