{
  "type": "Feature",
  "properties": {
    "gn:admin1_code":"20.0",
    "gn:asciiname":"Ban Nabo-Tai",
    "gn:country_code":"LA",
    "gn:dem":179,
    "gn:feature_class":"P",
    "gn:feature_code":"PPL",
    "gn:name":"Ban Nabo-Tai",
    "gn:population":0,
    "gn:timezone":"Asia/Vientiane",
    "iso:country":"LA",
    "name:lao_x_preferred":[
        "Ban Nabo-Tai"
    ],
    "name:und_x_variant":[
        "Ban Na Bo"
    ],
    "wof:name":"Ban Nabo-Tai",
    "wof:placetype":"locality"
},
  "geometry": {"coordinates":[105.63713,16.74326],"type":"Point"}
}