{
  "type": "Feature",
  "properties": {
    "gn:admin1_code":"13.0",
    "gn:asciiname":"Ban Nafay",
    "gn:country_code":"LA",
    "gn:dem":603,
    "gn:feature_class":"P",
    "gn:feature_code":"PPL",
    "gn:name":"Ban Nafay",
    "gn:population":0,
    "gn:timezone":"Asia/Vientiane",
    "iso:country":"LA",
    "name:und_x_variant":[
        "Ban Na Fai",
        "Ban Nafay"
    ],
    "wof:name":"Ban Nafay",
    "wof:placetype":"locality"
},
  "geometry": {"coordinates":[101.15828999999999,18.35605],"type":"Point"}
}