{
  "type": "Feature",
  "properties": {
    "gn:admin1_code":"17.0",
    "gn:asciiname":"Ban Houaylek",
    "gn:country_code":"LA",
    "gn:dem":399,
    "gn:feature_class":"P",
    "gn:feature_code":"PPL",
    "gn:name":"Ban Houayl\u00e8k",
    "gn:population":0,
    "gn:timezone":"Asia/Vientiane",
    "iso:country":"LA",
    "name:lao_x_preferred":[
        "Ban Houayl\u00e8k"
    ],
    "wof:name":"Ban Houaylek",
    "wof:placetype":"locality"
},
  "geometry": {"coordinates":[102.67045,20.53424],"type":"Point"}
}