{
  "type": "Feature",
  "properties": {
    "gn:admin1_code":"17.0",
    "gn:asciiname":"Ban Pakpha",
    "gn:country_code":"LA",
    "gn:dem":458,
    "gn:feature_class":"P",
    "gn:feature_code":"PPL",
    "gn:name":"Ban Pakpha",
    "gn:population":0,
    "gn:timezone":"Asia/Vientiane",
    "iso:country":"LA",
    "name:lao_x_preferred":[
        "Ban Pakpha"
    ],
    "wof:name":"Ban Pakpha",
    "wof:placetype":"locality"
},
  "geometry": {"coordinates":[102.73495,19.77794],"type":"Point"}
}