{
  "type": "Feature",
  "properties": {
    "gn:admin1_code":"14.0",
    "gn:asciiname":"Ban Naxeng",
    "gn:country_code":"LA",
    "gn:dem":1251,
    "gn:feature_class":"P",
    "gn:feature_code":"PPL",
    "gn:name":"Ban Nax\u00e9ng",
    "gn:population":0,
    "gn:timezone":"Asia/Vientiane",
    "iso:country":"LA",
    "name:lao_x_preferred":[
        "Ban Nax\u00e9ng"
    ],
    "wof:name":"Ban Naxeng",
    "wof:placetype":"locality"
},
  "geometry": {"coordinates":[103.59233,19.43839],"type":"Point"}
}