{
  "type": "Feature",
  "properties": {
    "gn:admin1_code":"14.0",
    "gn:asciiname":"Ban Sancho",
    "gn:country_code":"LA",
    "gn:dem":1361,
    "gn:feature_class":"P",
    "gn:feature_code":"PPL",
    "gn:name":"Ban Sancho",
    "gn:population":0,
    "gn:timezone":"Asia/Vientiane",
    "iso:country":"LA",
    "name:und_x_variant":[
        "San Tiau",
        "Ban Sancho"
    ],
    "wof:name":"Ban Sancho",
    "wof:placetype":"locality"
},
  "geometry": {"coordinates":[103.52849000000001,19.48828],"type":"Point"}
}