{
  "type": "Feature",
  "properties": {
    "gn:admin1_code":"18.0",
    "gn:asciiname":"Ban Hatxeuy",
    "gn:country_code":"LA",
    "gn:dem":404,
    "gn:feature_class":"P",
    "gn:feature_code":"PPL",
    "gn:name":"Ban Hatxeuy",
    "gn:population":0,
    "gn:timezone":"Asia/Vientiane",
    "iso:country":"LA",
    "name:lao_x_preferred":[
        "Ban Hatxeuy"
    ],
    "wof:name":"Ban Hatxeuy",
    "wof:placetype":"locality"
},
  "geometry": {"coordinates":[102.34347,21.08671],"type":"Point"}
}