{
  "type": "Feature",
  "properties": {
    "gn:admin1_code":"13.0",
    "gn:asciiname":"Ban Houaylao",
    "gn:country_code":"LA",
    "gn:dem":423,
    "gn:feature_class":"P",
    "gn:feature_code":"PPL",
    "gn:name":"Ban Houaylao",
    "gn:population":0,
    "gn:timezone":"Asia/Vientiane",
    "iso:country":"LA",
    "name:und_x_variant":[
        "Ban Houei Lao",
        "Ban Houaylao"
    ],
    "wof:name":"Ban Houaylao",
    "wof:placetype":"locality"
},
  "geometry": {"coordinates":[100.50982999999999,19.76484],"type":"Point"}
}