{
  "type": "Feature",
  "properties": {
    "gn:admin1_code":"16.0",
    "gn:asciiname":"Ban Tongkatang",
    "gn:country_code":"LA",
    "gn:dem":827,
    "gn:feature_class":"P",
    "gn:feature_code":"PPL",
    "gn:name":"Ban T\u00f4ngkatang",
    "gn:population":0,
    "gn:timezone":"Asia/Vientiane",
    "iso:country":"LA",
    "name:lao_x_preferred":[
        "Ban T\u00f4ngkatang"
    ],
    "wof:name":"Ban Tongkatang",
    "wof:placetype":"locality"
},
  "geometry": {"coordinates":[101.34911,20.45272000000001],"type":"Point"}
}