{
  "type": "Feature",
  "properties": {
    "gn:admin1_code":"2.0",
    "gn:asciiname":"Ban Namtiang-Loum",
    "gn:country_code":"LA",
    "gn:dem":772,
    "gn:feature_class":"P",
    "gn:feature_code":"PPL",
    "gn:name":"Ban Namtiang-Loum",
    "gn:population":0,
    "gn:timezone":"Asia/Vientiane",
    "iso:country":"LA",
    "name:lao_x_preferred":[
        "Ban Namtiang-Loum"
    ],
    "wof:name":"Ban Namtiang-Loum",
    "wof:placetype":"locality"
},
  "geometry": {"coordinates":[106.64525,15.03315],"type":"Point"}
}