{
  "type": "Feature",
  "properties": {
    "gn:admin1_code":"2.0",
    "gn:asciiname":"Ban Nalan",
    "gn:country_code":"LA",
    "gn:dem":92,
    "gn:feature_class":"P",
    "gn:feature_code":"PPL",
    "gn:name":"Ban Nalan",
    "gn:population":0,
    "gn:timezone":"Asia/Vientiane",
    "iso:country":"LA",
    "name:und_x_variant":[
        "Ban Nalane",
        "Ban Nalan"
    ],
    "wof:name":"Ban Nalan",
    "wof:placetype":"locality"
},
  "geometry": {"coordinates":[105.8514,14.22393],"type":"Point"}
}