{
  "type": "Feature",
  "properties": {
    "gn:admin1_code":"15.0",
    "gn:asciiname":"Ban Na Phao",
    "gn:cc2":"LA",
    "gn:country_code":"LA",
    "gn:dem":193,
    "gn:feature_class":"P",
    "gn:feature_code":"PPL",
    "gn:name":"Ban Na Phao",
    "gn:population":0,
    "gn:timezone":"Asia/Vientiane",
    "iso:country":"LA",
    "name:und_x_variant":[
        "Na Phao",
        "Ban Na Phao"
    ],
    "wof:name":"Ban Na Phao",
    "wof:placetype":"locality"
},
  "geometry": {"coordinates":[105.73333,17.58333],"type":"Point"}
}