{
  "type": "Feature",
  "properties": {
    "gn:admin1_code":"15.0",
    "gn:asciiname":"Ban Doy",
    "gn:country_code":"LA",
    "gn:dem":157,
    "gn:feature_class":"P",
    "gn:feature_code":"PPL",
    "gn:name":"Ban Doy",
    "gn:population":0,
    "gn:timezone":"Asia/Vientiane",
    "iso:country":"LA",
    "name:und_x_variant":[
        "Ban Doi",
        "Ban Doy"
    ],
    "wof:name":"Ban Doy",
    "wof:placetype":"locality"
},
  "geometry": {"coordinates":[104.82514999999999,17.55753],"type":"Point"}
}