{
  "type": "Feature",
  "properties": {
    "gn:admin1_code":"3.0",
    "gn:asciiname":"Ban Poun-Mai",
    "gn:country_code":"LA",
    "gn:dem":436,
    "gn:feature_class":"P",
    "gn:feature_code":"PPL",
    "gn:name":"Ban Poun-Mai",
    "gn:population":0,
    "gn:timezone":"Asia/Vientiane",
    "iso:country":"LA",
    "name:lao_x_preferred":[
        "Ban Poun-Mai"
    ],
    "wof:name":"Ban Poun-Mai",
    "wof:placetype":"locality"
},
  "geometry": {"coordinates":[104.54622000000001,20.32097000000001],"type":"Point"}
}