{
  "type": "Feature",
  "properties": {
    "gn:admin1_code":"3.0",
    "gn:asciiname":"Ban Hinkhoun",
    "gn:country_code":"LA",
    "gn:dem":305,
    "gn:feature_class":"P",
    "gn:feature_code":"PPL",
    "gn:name":"Ban Hinkhoun",
    "gn:population":0,
    "gn:timezone":"Asia/Vientiane",
    "iso:country":"LA",
    "name:und_x_variant":[
        "Ban Him Kum",
        "Ban Hinkhoun"
    ],
    "wof:name":"Ban Hinkhoun",
    "wof:placetype":"locality"
},
  "geometry": {"coordinates":[103.96478999999999,20.82785],"type":"Point"}
}