{
  "type": "Feature",
  "properties": {
    "gn:admin1_code":"23.0",
    "gn:asciiname":"Ban Soptong",
    "gn:country_code":"LA",
    "gn:dem":440,
    "gn:feature_class":"P",
    "gn:feature_code":"PPL",
    "gn:name":"Ban S\u00f4ptong",
    "gn:population":0,
    "gn:timezone":"Asia/Vientiane",
    "iso:country":"LA",
    "name:und_x_variant":[
        "Ban Sop Tung",
        "Ban S\u00f4ptong"
    ],
    "wof:name":"Ban Soptong",
    "wof:placetype":"locality"
},
  "geometry": {"coordinates":[104.92349,18.33993],"type":"Point"}
}