{
  "type": "Feature",
  "properties": {
    "gn:admin1_code":"22.0",
    "gn:asciiname":"Ban Namthoung",
    "gn:country_code":"LA",
    "gn:dem":413,
    "gn:feature_class":"P",
    "gn:feature_code":"PPL",
    "gn:name":"Ban Namthoung",
    "gn:population":0,
    "gn:timezone":"Asia/Vientiane",
    "iso:country":"LA",
    "name:lao_x_preferred":[
        "Ban Namthoung"
    ],
    "wof:name":"Ban Namthoung",
    "wof:placetype":"locality"
},
  "geometry": {"coordinates":[100.58207,20.4291],"type":"Point"}
}