{
  "type": "Feature",
  "properties": {
    "gn:admin1_code":"20.0",
    "gn:asciiname":"Ban Khouaxe",
    "gn:country_code":"LA",
    "gn:dem":159,
    "gn:feature_class":"P",
    "gn:feature_code":"PPL",
    "gn:name":"Ban Khouax\u00e9",
    "gn:population":0,
    "gn:timezone":"Asia/Vientiane",
    "iso:country":"LA",
    "name:lao_x_preferred":[
        "Ban Khouax\u00e9"
    ],
    "wof:name":"Ban Khouaxe",
    "wof:placetype":"locality"
},
  "geometry": {"coordinates":[104.98318,17.08053],"type":"Point"}
}