{
  "type": "Feature",
  "properties": {
    "gn:admin1_code":"3.0",
    "gn:asciiname":"Ban Phapat",
    "gn:country_code":"LA",
    "gn:dem":1204,
    "gn:feature_class":"P",
    "gn:feature_code":"PPL",
    "gn:name":"Ban Phapat",
    "gn:population":0,
    "gn:timezone":"Asia/Vientiane",
    "iso:country":"LA",
    "name:lao_x_preferred":[
        "Ban Phapat"
    ],
    "wof:name":"Ban Phapat",
    "wof:placetype":"locality"
},
  "geometry": {"coordinates":[104.10096,20.37419],"type":"Point"}
}