{
  "type": "Feature",
  "properties": {
    "iso:country":"LA",
    "name:lao_x_preferred":[
        "Ban Thanal\u00e8ng"
    ],
    "qs:gn_country":"LA",
    "qs:gn_fcode":"PPL",
    "qs:gn_pop":0,
    "qs:name":"Ban Thanal\u00e8ng",
    "qs:name_adm0":"Laos",
    "qs:name_adm1":"Viangchan",
    "qs:photos":963,
    "qs:photos_1k":195,
    "qs:photos_9k":4,
    "qs:photos_9r":6,
    "qs:photos_all":963,
    "qs:photos_sr":10,
    "qs:placetype":"Town",
    "qs:pop_sr":"0",
    "qs:woe_adm0":23424872,
    "wof:name":"Ban Thanal\u00e8ng",
    "wof:placetype":"locality"
},
  "geometry": {"coordinates":[102.73582,17.88944],"type":"Point"}
}