{
  "type": "Feature",
  "properties": {
    "gn:admin1_code":"18.0",
    "gn:asciiname":"Ban Hatden",
    "gn:country_code":"LA",
    "gn:dem":379,
    "gn:feature_class":"P",
    "gn:feature_code":"PPL",
    "gn:name":"Ban Hatd\u00e9n",
    "gn:population":0,
    "gn:timezone":"Asia/Vientiane",
    "iso:country":"LA",
    "name:und_x_variant":[
        "Houei Den",
        "Ban Hatd\u00e9n",
        "Houay Den"
    ],
    "wof:name":"Ban Hatden",
    "wof:placetype":"locality"
},
  "geometry": {"coordinates":[102.60714,21.06403],"type":"Point"}
}