{
  "type": "Feature",
  "properties": {
    "gn:admin1_code":"15.0",
    "gn:asciiname":"Ban Thapachon",
    "gn:country_code":"LA",
    "gn:dem":200,
    "gn:feature_class":"P",
    "gn:feature_code":"PPL",
    "gn:name":"Ban Thapach\u00f4n",
    "gn:population":0,
    "gn:timezone":"Asia/Vientiane",
    "iso:country":"LA",
    "name:und_x_variant":[
        "Ban Thapchon",
        "Ban Tha Pha Chon",
        "Ban Thapach\u00f4n"
    ],
    "wof:name":"Ban Thapachon",
    "wof:placetype":"locality"
},
  "geometry": {"coordinates":[105.82076000000001,17.2352],"type":"Point"}
}