{
  "type": "Feature",
  "properties": {
    "gn:admin1_code":"16.0",
    "gn:asciiname":"Ban Thongkang",
    "gn:country_code":"LA",
    "gn:dem":560,
    "gn:feature_class":"P",
    "gn:feature_code":"PPL",
    "gn:name":"Ban Th\u00f4ngkang",
    "gn:population":0,
    "gn:timezone":"Asia/Vientiane",
    "iso:country":"LA",
    "name:lao_x_preferred":[
        "Ban Th\u00f4ngkang"
    ],
    "wof:name":"Ban Thongkang",
    "wof:placetype":"locality"
},
  "geometry": {"coordinates":[101.37862,20.97041],"type":"Point"}
}