{
  "type": "Feature",
  "properties": {
    "gn:admin1_code":"17.0",
    "gn:asciiname":"Na Mi",
    "gn:country_code":"LA",
    "gn:dem":595,
    "gn:feature_class":"P",
    "gn:feature_code":"PPL",
    "gn:name":"Na Mi",
    "gn:population":0,
    "gn:timezone":"Asia/Vientiane",
    "iso:country":"LA",
    "wof:name":"Na Mi",
    "wof:placetype":"locality"
},
  "geometry": {"coordinates":[102.91667,20.66667],"type":"Point"}
}