{
  "type": "Feature",
  "properties": {
    "gn:admin1_code":"17.0",
    "gn:asciiname":"Ban Latkhok",
    "gn:country_code":"LA",
    "gn:dem":311,
    "gn:feature_class":"P",
    "gn:feature_code":"PPL",
    "gn:name":"Ban Latkh\u00f4k",
    "gn:population":0,
    "gn:timezone":"Asia/Vientiane",
    "iso:country":"LA",
    "name:lao_x_preferred":[
        "Ban Latkh\u00f4k"
    ],
    "wof:name":"Ban Latkhok",
    "wof:placetype":"locality"
},
  "geometry": {"coordinates":[102.09699000000001,19.89728],"type":"Point"}
}