{
  "type": "Feature",
  "properties": {
    "gn:admin1_code":"2.0",
    "gn:asciiname":"Ban Thongset",
    "gn:country_code":"LA",
    "gn:dem":1261,
    "gn:feature_class":"P",
    "gn:feature_code":"PPL",
    "gn:name":"Ban Th\u00f4ngs\u00e9t",
    "gn:population":0,
    "gn:timezone":"Asia/Vientiane",
    "iso:country":"LA",
    "name:lao_x_preferred":[
        "Ban Th\u00f4ngs\u00e9t"
    ],
    "wof:name":"Ban Thongset",
    "wof:placetype":"locality"
},
  "geometry": {"coordinates":[106.30356999999999,15.21407],"type":"Point"}
}