{
  "type": "Feature",
  "properties": {
    "gn:admin1_code":"15.0",
    "gn:asciiname":"Ban Bunghouana-Kang",
    "gn:country_code":"LA",
    "gn:dem":161,
    "gn:feature_class":"P",
    "gn:feature_code":"PPL",
    "gn:name":"Ban Bunghouana-Kang",
    "gn:population":0,
    "gn:timezone":"Asia/Vientiane",
    "iso:country":"LA",
    "name:lao_x_preferred":[
        "Ban Bunghouana-Kang"
    ],
    "wof:name":"Ban Bunghouana-Kang",
    "wof:placetype":"locality"
},
  "geometry": {"coordinates":[104.98412999999999,17.14062],"type":"Point"}
}