{
  "type": "Feature",
  "properties": {
    "gn:admin1_code":"19.0",
    "gn:asciiname":"Ban Phakkha",
    "gn:country_code":"LA",
    "gn:dem":140,
    "gn:feature_class":"P",
    "gn:feature_code":"PPL",
    "gn:name":"Ban Phakkha",
    "gn:population":0,
    "gn:timezone":"Asia/Vientiane",
    "iso:country":"LA",
    "name:und_x_variant":[
        "Ban Phakha",
        "Ban Phakkha"
    ],
    "wof:name":"Ban Phakkha",
    "wof:placetype":"locality"
},
  "geometry": {"coordinates":[105.96210000000001,15.68187],"type":"Point"}
}