{
  "type": "Feature",
  "properties": {
    "gn:admin1_code":"19.0",
    "gn:asciiname":"Ban Namtheng",
    "gn:country_code":"LA",
    "gn:dem":138,
    "gn:feature_class":"P",
    "gn:feature_code":"PPL",
    "gn:name":"Ban Namth\u00e8ng",
    "gn:population":0,
    "gn:timezone":"Asia/Vientiane",
    "iso:country":"LA",
    "name:und_x_variant":[
        "Ban Nam Ten",
        "Ban Namth\u00e8ng"
    ],
    "wof:name":"Ban Namtheng",
    "wof:placetype":"locality"
},
  "geometry": {"coordinates":[105.81583000000001,15.45197],"type":"Point"}
}