{
  "type": "Feature",
  "properties": {
    "gn:admin1_code":"18.0",
    "gn:asciiname":"Ban Bo May",
    "gn:country_code":"LA",
    "gn:dem":883,
    "gn:feature_class":"P",
    "gn:feature_code":"PPL",
    "gn:name":"Ban Bo May",
    "gn:population":0,
    "gn:timezone":"Asia/Vientiane",
    "iso:country":"LA",
    "name:lao_x_preferred":[
        "Ban Bo May"
    ],
    "wof:name":"Ban Bo May",
    "wof:placetype":"locality"
},
  "geometry": {"coordinates":[101.76667,22.33333],"type":"Point"}
}