{
  "type": "Feature",
  "properties": {
    "gn:admin1_code":"13.0",
    "gn:asciiname":"Ban Khokngiou",
    "gn:country_code":"LA",
    "gn:dem":234,
    "gn:feature_class":"P",
    "gn:feature_code":"PPL",
    "gn:name":"Ban Kh\u00f4kngiou",
    "gn:population":0,
    "gn:timezone":"Asia/Vientiane",
    "iso:country":"LA",
    "name:lao_x_preferred":[
        "Ban Kh\u00f4kngiou"
    ],
    "wof:name":"Ban Khokngiou",
    "wof:placetype":"locality"
},
  "geometry": {"coordinates":[101.43971999999999,18.25449],"type":"Point"}
}