{
  "type": "Feature",
  "properties": {
    "gn:admin1_code":"26.0",
    "gn:asciiname":"Ban Taoun",
    "gn:country_code":"LA",
    "gn:dem":760,
    "gn:feature_class":"P",
    "gn:feature_code":"PPL",
    "gn:name":"Ban Taoun",
    "gn:population":0,
    "gn:timezone":"Asia/Vientiane",
    "iso:country":"LA",
    "name:lao_x_preferred":[
        "Ban Taoun"
    ],
    "wof:name":"Ban Taoun",
    "wof:placetype":"locality"
},
  "geometry": {"coordinates":[106.94538,15.46701],"type":"Point"}
}