{
  "type": "Feature",
  "properties": {
    "gn:admin1_code":"15.0",
    "gn:asciiname":"Ban Naveng",
    "gn:country_code":"LA",
    "gn:dem":163,
    "gn:feature_class":"P",
    "gn:feature_code":"PPL",
    "gn:name":"Ban Nav\u00e8ng",
    "gn:population":0,
    "gn:timezone":"Asia/Vientiane",
    "iso:country":"LA",
    "name:lao_x_preferred":[
        "Ban Nav\u00e8ng"
    ],
    "wof:name":"Ban Naveng",
    "wof:placetype":"locality"
},
  "geometry": {"coordinates":[105.246,17.54805],"type":"Point"}
}