{
  "type": "Feature",
  "properties": {
    "gn:admin1_code":"15.0",
    "gn:asciiname":"Ban Vangle",
    "gn:cc2":"LA",
    "gn:country_code":"LA",
    "gn:dem":664,
    "gn:feature_class":"P",
    "gn:feature_code":"PPL",
    "gn:name":"Ban Vangl\u00e8",
    "gn:population":0,
    "gn:timezone":"Asia/Vientiane",
    "iso:country":"LA",
    "name:und_x_variant":[
        "Ban K\u00e8ng Lai",
        "Ban Vangl\u00e8"
    ],
    "wof:name":"Ban Vangle",
    "wof:placetype":"locality"
},
  "geometry": {"coordinates":[105.46666999999999,17.85],"type":"Point"}
}