{
  "type": "Feature",
  "properties": {
    "gn:admin1_code":"23.0",
    "gn:asciiname":"Ban Naphong",
    "gn:country_code":"LA",
    "gn:dem":568,
    "gn:feature_class":"P",
    "gn:feature_code":"PPL",
    "gn:name":"Ban Naphong",
    "gn:population":0,
    "gn:timezone":"Asia/Vientiane",
    "iso:country":"LA",
    "name:lao_x_preferred":[
        "Ban Naphong"
    ],
    "wof:name":"Ban Naphong",
    "wof:placetype":"locality"
},
  "geometry": {"coordinates":[105.08999,18.30612],"type":"Point"}
}