{
  "type": "Feature",
  "properties": {
    "gn:admin1_code":"26.0",
    "gn:asciiname":"Ban Tongmup",
    "gn:country_code":"LA",
    "gn:dem":1223,
    "gn:feature_class":"P",
    "gn:feature_code":"PPL",
    "gn:name":"Ban Tongmup",
    "gn:population":0,
    "gn:timezone":"Asia/Vientiane",
    "iso:country":"LA",
    "name:lao_x_preferred":[
        "Ban Tongmup"
    ],
    "wof:name":"Ban Tongmup",
    "wof:placetype":"locality"
},
  "geometry": {"coordinates":[107.25972,15.42185],"type":"Point"}
}