{
  "type": "Feature",
  "properties": {
    "gn:admin1_code":"17.0",
    "gn:asciiname":"Ban Loko",
    "gn:country_code":"LA",
    "gn:dem":592,
    "gn:feature_class":"P",
    "gn:feature_code":"PPL",
    "gn:name":"Ban L\u00f4ko",
    "gn:population":0,
    "gn:timezone":"Asia/Vientiane",
    "iso:country":"LA",
    "wof:name":"Ban Loko",
    "wof:placetype":"locality"
},
  "geometry": {"coordinates":[102.23333,20.21667],"type":"Point"}
}