{
  "type": "Feature",
  "properties": {
    "gn:admin1_code":"17.0",
    "gn:asciiname":"Ban Pakhok",
    "gn:country_code":"LA",
    "gn:dem":1030,
    "gn:feature_class":"P",
    "gn:feature_code":"PPL",
    "gn:name":"Ban Pakhok",
    "gn:population":0,
    "gn:timezone":"Asia/Vientiane",
    "iso:country":"LA",
    "name:lao_x_preferred":[
        "Ban Pakhok"
    ],
    "wof:name":"Ban Pakhok",
    "wof:placetype":"locality"
},
  "geometry": {"coordinates":[102.39373000000001,19.6137],"type":"Point"}
}