{
  "type": "Feature",
  "properties": {
    "gn:admin1_code":"28.0",
    "gn:asciiname":"Ban Pomom-Noi",
    "gn:country_code":"LA",
    "gn:dem":381,
    "gn:feature_class":"P",
    "gn:feature_code":"PPL",
    "gn:name":"Ban Pomom-Noi",
    "gn:population":0,
    "gn:timezone":"Asia/Vientiane",
    "iso:country":"LA",
    "name:lao_x_preferred":[
        "Ban Pomom-Noi"
    ],
    "name:und_x_variant":[
        "Ban Pomome"
    ],
    "wof:name":"Ban Pomom-Noi",
    "wof:placetype":"locality"
},
  "geometry": {"coordinates":[103.42868,18.68436],"type":"Point"}
}