{
  "type": "Feature",
  "properties": {
    "gn:admin1_code":"20.0",
    "gn:asciiname":"Ban Dong-Gnai",
    "gn:country_code":"LA",
    "gn:dem":202,
    "gn:feature_class":"P",
    "gn:feature_code":"PPL",
    "gn:name":"Ban D\u00f4ng-Gnai",
    "gn:population":0,
    "gn:timezone":"Asia/Vientiane",
    "iso:country":"LA",
    "name:und_x_variant":[
        "Ban Dong Nay",
        "Ban D\u00f4ng-Nai",
        "Ban D\u00f4ng-Gnai"
    ],
    "wof:name":"Ban Dong-Gnai",
    "wof:placetype":"locality"
},
  "geometry": {"coordinates":[105.07338,16.86993],"type":"Point"}
}