{
  "type": "Feature",
  "properties": {
    "gn:admin1_code":"19.0",
    "gn:asciiname":"Ban Lahen",
    "gn:country_code":"LA",
    "gn:dem":414,
    "gn:feature_class":"P",
    "gn:feature_code":"PPL",
    "gn:name":"Ban Lah\u00e9n",
    "gn:population":0,
    "gn:timezone":"Asia/Vientiane",
    "iso:country":"LA",
    "name:lao_x_preferred":[
        "Ban Lah\u00e9n"
    ],
    "wof:name":"Ban Lahen",
    "wof:placetype":"locality"
},
  "geometry": {"coordinates":[106.66005,16.29981],"type":"Point"}
}