{
  "type": "Feature",
  "properties": {
    "gn:admin1_code":"17.0",
    "gn:asciiname":"Ban Thaoui",
    "gn:country_code":"LA",
    "gn:dem":348,
    "gn:feature_class":"P",
    "gn:feature_code":"PPL",
    "gn:name":"Ban Thaoui",
    "gn:population":0,
    "gn:timezone":"Asia/Vientiane",
    "iso:country":"LA",
    "name:und_x_variant":[
        "Ban Tha Ouei",
        "Ban Thaoui"
    ],
    "wof:name":"Ban Thaoui",
    "wof:placetype":"locality"
},
  "geometry": {"coordinates":[102.34305000000001,19.98047],"type":"Point"}
}