{
  "type": "Feature",
  "properties": {
    "gn:admin1_code":"18.0",
    "gn:asciiname":"Ban Houaychik-Nua",
    "gn:country_code":"LA",
    "gn:dem":446,
    "gn:feature_class":"P",
    "gn:feature_code":"PPL",
    "gn:name":"Ban Houaychik-Nua",
    "gn:population":0,
    "gn:timezone":"Asia/Vientiane",
    "iso:country":"LA",
    "name:lao_x_preferred":[
        "Ban Houaychik-Nua"
    ],
    "name:und_x_variant":[
        "Houay Chik"
    ],
    "wof:name":"Ban Houaychik-Nua",
    "wof:placetype":"locality"
},
  "geometry": {"coordinates":[102.73565000000001,21.17502],"type":"Point"}
}