{
  "type": "Feature",
  "properties": {
    "gn:admin1_code":"3.0",
    "gn:asciiname":"Ban Phoulao",
    "gn:country_code":"LA",
    "gn:dem":1119,
    "gn:feature_class":"P",
    "gn:feature_code":"PPL",
    "gn:name":"Ban Phoulao",
    "gn:population":0,
    "gn:timezone":"Asia/Vientiane",
    "iso:country":"LA",
    "wof:name":"Ban Phoulao",
    "wof:placetype":"locality"
},
  "geometry": {"coordinates":[103.73624,20.08005],"type":"Point"}
}