{
  "type": "Feature",
  "properties": {
    "gn:admin1_code":"20.0",
    "gn:asciiname":"Ban Kangtiou",
    "gn:country_code":"LA",
    "gn:dem":171,
    "gn:feature_class":"P",
    "gn:feature_code":"PPL",
    "gn:name":"Ban Kangtiou",
    "gn:population":0,
    "gn:timezone":"Asia/Vientiane",
    "iso:country":"LA",
    "name:lao_x_preferred":[
        "Ban Kangtiou"
    ],
    "wof:name":"Ban Kangtiou",
    "wof:placetype":"locality"
},
  "geometry": {"coordinates":[105.16312000000001,17.04209],"type":"Point"}
}