{
  "type": "Feature",
  "properties": {
    "gn:admin1_code":"2.0",
    "gn:asciiname":"Ban Lomphat",
    "gn:country_code":"LA",
    "gn:dem":98,
    "gn:feature_class":"P",
    "gn:feature_code":"PPL",
    "gn:name":"Ban L\u00f4mphat",
    "gn:population":0,
    "gn:timezone":"Asia/Vientiane",
    "iso:country":"LA",
    "name:lao_x_preferred":[
        "Ban L\u00f4mphat"
    ],
    "wof:name":"Ban Lomphat",
    "wof:placetype":"locality"
},
  "geometry": {"coordinates":[105.86893000000001,14.26264],"type":"Point"}
}