{
  "type": "Feature",
  "properties": {
    "gn:admin1_code":"23.0",
    "gn:asciiname":"Ban Nabon",
    "gn:country_code":"LA",
    "gn:dem":160,
    "gn:feature_class":"P",
    "gn:feature_code":"PPL",
    "gn:name":"Ban Nabon",
    "gn:population":0,
    "gn:timezone":"Asia/Vientiane",
    "iso:country":"LA",
    "name:lao_x_preferred":[
        "Ban Nabon"
    ],
    "wof:name":"Ban Nabon",
    "wof:placetype":"locality"
},
  "geometry": {"coordinates":[103.92610000000001,18.38995],"type":"Point"}
}