{
  "type": "Feature",
  "properties": {
    "gn:admin1_code":"22.0",
    "gn:asciiname":"Ban Houaynam",
    "gn:country_code":"LA",
    "gn:dem":398,
    "gn:feature_class":"P",
    "gn:feature_code":"PPL",
    "gn:name":"Ban Houaynam",
    "gn:population":0,
    "gn:timezone":"Asia/Vientiane",
    "iso:country":"LA",
    "name:und_x_variant":[
        "Ban Huai Nam",
        "Ban Houei Nam",
        "Ban Houaynam",
        "Ban Hat Nam"
    ],
    "wof:name":"Ban Houaynam",
    "wof:placetype":"locality"
},
  "geometry": {"coordinates":[100.79652,20.27174],"type":"Point"}
}