{
  "type": "Feature",
  "properties": {
    "gn:admin1_code":"7.0",
    "gn:asciiname":"Ban Kon-Gnong",
    "gn:country_code":"LA",
    "gn:dem":1036,
    "gn:feature_class":"P",
    "gn:feature_code":"PPL",
    "gn:name":"Ban Kon-Gnong",
    "gn:population":0,
    "gn:timezone":"Asia/Vientiane",
    "iso:country":"LA",
    "name:lao_x_preferred":[
        "Ban Kon-Gnong"
    ],
    "wof:name":"Ban Kon-Gnong",
    "wof:placetype":"locality"
},
  "geometry": {"coordinates":[101.29602,20.23914],"type":"Point"}
}