{
  "type": "Feature",
  "properties": {
    "gn:admin1_code":"14.0",
    "gn:asciiname":"Ban Man",
    "gn:country_code":"LA",
    "gn:dem":1119,
    "gn:feature_class":"P",
    "gn:feature_code":"PPL",
    "gn:name":"Ban Man",
    "gn:population":0,
    "gn:timezone":"Asia/Vientiane",
    "iso:country":"LA",
    "name:lao_x_preferred":[
        "Ban Man"
    ],
    "wof:name":"Ban Man",
    "wof:placetype":"locality"
},
  "geometry": {"coordinates":[103.20316,19.6877],"type":"Point"}
}