{
  "type": "Feature",
  "properties": {
    "gn:admin1_code":"3.0",
    "gn:asciiname":"Ban Tonghou",
    "gn:country_code":"LA",
    "gn:dem":1268,
    "gn:feature_class":"P",
    "gn:feature_code":"PPL",
    "gn:name":"Ban Tonghou",
    "gn:population":0,
    "gn:timezone":"Asia/Vientiane",
    "iso:country":"LA",
    "wof:name":"Ban Tonghou",
    "wof:placetype":"locality"
},
  "geometry": {"coordinates":[104.66667,19.73333],"type":"Point"}
}