{
  "type": "Feature",
  "properties": {
    "gn:admin1_code":"22.0",
    "gn:asciiname":"Ban Houayliang",
    "gn:country_code":"LA",
    "gn:dem":414,
    "gn:feature_class":"P",
    "gn:feature_code":"PPL",
    "gn:name":"Ban Houayliang",
    "gn:population":0,
    "gn:timezone":"Asia/Vientiane",
    "iso:country":"LA",
    "name:lao_x_preferred":[
        "Ban Houayliang"
    ],
    "wof:name":"Ban Houayliang",
    "wof:placetype":"locality"
},
  "geometry": {"coordinates":[100.80994,20.0684],"type":"Point"}
}