{
  "type": "Feature",
  "properties": {
    "gn:admin1_code":"17.0",
    "gn:asciiname":"Ban Paksanan",
    "gn:country_code":"LA",
    "gn:dem":396,
    "gn:feature_class":"P",
    "gn:feature_code":"PPL",
    "gn:name":"Ban Paksanan",
    "gn:population":0,
    "gn:timezone":"Asia/Vientiane",
    "iso:country":"LA",
    "name:lao_x_preferred":[
        "Ban Paksanan"
    ],
    "name:und_x_variant":[
        "Pa Sa Nam"
    ],
    "wof:name":"Ban Paksanan",
    "wof:placetype":"locality"
},
  "geometry": {"coordinates":[102.14363,19.60725],"type":"Point"}
}