{
  "type": "Feature",
  "properties": {
    "gn:admin1_code":"3.0",
    "gn:asciiname":"Ban Leng",
    "gn:country_code":"LA",
    "gn:dem":562,
    "gn:feature_class":"P",
    "gn:feature_code":"PPL",
    "gn:name":"Ban L\u00e8ng",
    "gn:population":0,
    "gn:timezone":"Asia/Vientiane",
    "iso:country":"LA",
    "name:lao_x_preferred":[
        "Ban L\u00e8ng"
    ],
    "wof:name":"Ban Leng",
    "wof:placetype":"locality"
},
  "geometry": {"coordinates":[103.50554,20.64875],"type":"Point"}
}