{
  "type": "Feature",
  "properties": {
    "gn:admin1_code":"17.0",
    "gn:asciiname":"Ban Namphak",
    "gn:country_code":"LA",
    "gn:dem":1072,
    "gn:feature_class":"P",
    "gn:feature_code":"PPL",
    "gn:name":"Ban Namphak",
    "gn:population":0,
    "gn:timezone":"Asia/Vientiane",
    "iso:country":"LA",
    "name:lao_x_preferred":[
        "Ban Namphak"
    ],
    "wof:name":"Ban Namphak",
    "wof:placetype":"locality"
},
  "geometry": {"coordinates":[102.23117999999999,19.52629],"type":"Point"}
}