{
  "type": "Feature",
  "properties": {
    "iso:country":"LA",
    "name:und_x_variant":[
        "Ban Nhik"
    ],
    "qs:gn_country":"LA",
    "qs:gn_fcode":"PPL",
    "qs:gn_pop":0,
    "qs:name":"Ban Gnik",
    "qs:name_adm0":"Laos",
    "qs:name_adm1":"Champasak",
    "qs:photos":90,
    "qs:photos_1k":18,
    "qs:photos_9k":1,
    "qs:photos_9r":3,
    "qs:photos_all":90,
    "qs:photos_sr":3,
    "qs:placetype":"Town",
    "qs:pop_sr":"4",
    "qs:woe_adm0":23424872,
    "wof:name":"Ban Gnik",
    "wof:placetype":"locality"
},
  "geometry": {"coordinates":[106.06667,15.16667],"type":"Point"}
}