{
  "type": "Feature",
  "properties": {
    "gn:admin1_code":"20.0",
    "gn:asciiname":"Ban Bloy",
    "gn:country_code":"LA",
    "gn:dem":334,
    "gn:feature_class":"P",
    "gn:feature_code":"PPL",
    "gn:name":"Ban Bloy",
    "gn:population":0,
    "gn:timezone":"Asia/Vientiane",
    "iso:country":"LA",
    "name:lao_x_preferred":[
        "Ban Bloy"
    ],
    "wof:name":"Ban Bloy",
    "wof:placetype":"locality"
},
  "geometry": {"coordinates":[106.50378000000001,16.24244],"type":"Point"}
}