{
  "type": "Feature",
  "properties": {
    "gn:admin1_code":"18.0",
    "gn:asciiname":"Ban Lo Pha",
    "gn:country_code":"LA",
    "gn:dem":1001,
    "gn:feature_class":"P",
    "gn:feature_code":"PPL",
    "gn:name":"Ban Lo Pha",
    "gn:population":0,
    "gn:timezone":"Asia/Vientiane",
    "iso:country":"LA",
    "wof:name":"Ban Lo Pha",
    "wof:placetype":"locality"
},
  "geometry": {"coordinates":[101.68333,22.15],"type":"Point"}
}