{
  "type": "Feature",
  "properties": {
    "gn:admin1_code":"17.0",
    "gn:asciiname":"Ban Viangsamai",
    "gn:country_code":"LA",
    "gn:dem":489,
    "gn:feature_class":"P",
    "gn:feature_code":"PPL",
    "gn:name":"Ban Viangsamai",
    "gn:population":0,
    "gn:timezone":"Asia/Vientiane",
    "iso:country":"LA",
    "name:lao_x_preferred":[
        "Ban Viangsamai"
    ],
    "wof:name":"Ban Viangsamai",
    "wof:placetype":"locality"
},
  "geometry": {"coordinates":[102.64702,19.63077],"type":"Point"}
}