{
  "type": "Feature",
  "properties": {
    "gn:admin1_code":"18.0",
    "gn:asciiname":"Ban Khounsouklouang",
    "gn:country_code":"LA",
    "gn:dem":1247,
    "gn:feature_class":"P",
    "gn:feature_code":"PPL",
    "gn:name":"Ban Khounsouklouang",
    "gn:population":0,
    "gn:timezone":"Asia/Vientiane",
    "iso:country":"LA",
    "name:lao_x_preferred":[
        "Ban Khounsouklouang"
    ],
    "name:und_x_variant":[
        "Khun Suc"
    ],
    "wof:name":"Ban Khounsouklouang",
    "wof:placetype":"locality"
},
  "geometry": {"coordinates":[102.12203,21.72722000000001],"type":"Point"}
}