{
  "type": "Feature",
  "properties": {
    "gn:admin1_code":"15.0",
    "gn:asciiname":"Ban Nasakong",
    "gn:country_code":"LA",
    "gn:dem":171,
    "gn:feature_class":"P",
    "gn:feature_code":"PPL",
    "gn:name":"Ban Nasakong",
    "gn:population":0,
    "gn:timezone":"Asia/Vientiane",
    "iso:country":"LA",
    "name:und_x_variant":[
        "Ban Na Xa Kong",
        "Ban Nasakong"
    ],
    "wof:name":"Ban Nasakong",
    "wof:placetype":"locality"
},
  "geometry": {"coordinates":[104.4879,18.10171],"type":"Point"}
}