{
  "type": "Feature",
  "properties": {
    "gn:admin1_code":"26.0",
    "gn:asciiname":"Ban Alim",
    "gn:country_code":"LA",
    "gn:dem":909,
    "gn:feature_class":"P",
    "gn:feature_code":"PPL",
    "gn:name":"Ban Alim",
    "gn:population":0,
    "gn:timezone":"Asia/Vientiane",
    "iso:country":"LA",
    "name:lao_x_preferred":[
        "Ban Alim"
    ],
    "name:und_x_variant":[
        "A Lim"
    ],
    "wof:name":"Ban Alim",
    "wof:placetype":"locality"
},
  "geometry": {"coordinates":[107.29893,15.90698],"type":"Point"}
}