{
  "type": "Feature",
  "properties": {
    "gn:admin1_code":"14.0",
    "gn:asciiname":"Ban Gnotkho",
    "gn:country_code":"LA",
    "gn:dem":1304,
    "gn:feature_class":"P",
    "gn:feature_code":"PPL",
    "gn:name":"Ban Gnotkho",
    "gn:population":0,
    "gn:timezone":"Asia/Vientiane",
    "iso:country":"LA",
    "name:lao_x_preferred":[
        "Ban Gnotkho"
    ],
    "wof:name":"Ban Gnotkho",
    "wof:placetype":"locality"
},
  "geometry": {"coordinates":[103.84162000000001,19.6045],"type":"Point"}
}