{
  "type": "Feature",
  "properties": {
    "gn:admin1_code":"19.0",
    "gn:asciiname":"Ban Vangli",
    "gn:country_code":"LA",
    "gn:dem":276,
    "gn:feature_class":"P",
    "gn:feature_code":"PPL",
    "gn:name":"Ban Vangli",
    "gn:population":0,
    "gn:timezone":"Asia/Vientiane",
    "iso:country":"LA",
    "name:lao_x_preferred":[
        "Ban Vangli"
    ],
    "wof:name":"Ban Vangli",
    "wof:placetype":"locality"
},
  "geometry": {"coordinates":[106.33284,16.13524],"type":"Point"}
}