{
  "type": "Feature",
  "properties": {
    "gn:admin1_code":"26.0",
    "gn:asciiname":"Ban Avon",
    "gn:country_code":"LA",
    "gn:dem":840,
    "gn:feature_class":"P",
    "gn:feature_code":"PPL",
    "gn:name":"Ban Av\u00f4n",
    "gn:population":0,
    "gn:timezone":"Asia/Vientiane",
    "iso:country":"LA",
    "name:lao_x_preferred":[
        "Ban Av\u00f4n"
    ],
    "wof:name":"Ban Avon",
    "wof:placetype":"locality"
},
  "geometry": {"coordinates":[107.06386999999999,15.88044],"type":"Point"}
}