{
  "type": "Feature",
  "properties": {
    "gn:admin1_code":"20.0",
    "gn:asciiname":"Ban Dongvay",
    "gn:country_code":"LA",
    "gn:dem":145,
    "gn:feature_class":"P",
    "gn:feature_code":"PPL",
    "gn:name":"Ban D\u00f4ngvay",
    "gn:population":0,
    "gn:timezone":"Asia/Vientiane",
    "iso:country":"LA",
    "name:und_x_variant":[
        "Ban Dong Vai",
        "Ban D\u00f4ngvay"
    ],
    "wof:name":"Ban Dongvay",
    "wof:placetype":"locality"
},
  "geometry": {"coordinates":[105.38514000000001,16.36025],"type":"Point"}
}