{
  "type": "Feature",
  "properties": {
    "gn:admin1_code":"20.0",
    "gn:asciiname":"Ban Klongnachan",
    "gn:country_code":"LA",
    "gn:dem":176,
    "gn:feature_class":"P",
    "gn:feature_code":"PPL",
    "gn:name":"Ban Klongnachan",
    "gn:population":0,
    "gn:timezone":"Asia/Vientiane",
    "iso:country":"LA",
    "name:lao_x_preferred":[
        "Ban Klongnachan"
    ],
    "wof:name":"Ban Klongnachan",
    "wof:placetype":"locality"
},
  "geometry": {"coordinates":[105.53131999999999,16.65045],"type":"Point"}
}