{
  "type": "Feature",
  "properties": {
    "gn:admin1_code":"17.0",
    "gn:asciiname":"Ban Xiangmouak",
    "gn:country_code":"LA",
    "gn:dem":558,
    "gn:feature_class":"P",
    "gn:feature_code":"PPL",
    "gn:name":"Ban Xiangmouak",
    "gn:population":0,
    "gn:timezone":"Asia/Vientiane",
    "iso:country":"LA",
    "name:und_x_variant":[
        "Xieng Mouok",
        "Ban Xiang-Nouak",
        "Ban Xiangmouak"
    ],
    "wof:name":"Ban Xiangmouak",
    "wof:placetype":"locality"
},
  "geometry": {"coordinates":[102.10602,19.81546],"type":"Point"}
}