{
  "type": "Feature",
  "properties": {
    "gn:admin1_code":"7.0",
    "gn:asciiname":"Ban Namhem",
    "gn:country_code":"LA",
    "gn:dem":870,
    "gn:feature_class":"P",
    "gn:feature_code":"PPL",
    "gn:name":"Ban Namh\u00e9m",
    "gn:population":0,
    "gn:timezone":"Asia/Vientiane",
    "iso:country":"LA",
    "name:lao_x_preferred":[
        "Ban Namh\u00e9m"
    ],
    "wof:name":"Ban Namhem",
    "wof:placetype":"locality"
},
  "geometry": {"coordinates":[101.53925,20.03384],"type":"Point"}
}