{
  "type": "Feature",
  "properties": {
    "gn:admin1_code":"1.0",
    "gn:asciiname":"Ban Dakbung",
    "gn:country_code":"LA",
    "gn:dem":876,
    "gn:feature_class":"P",
    "gn:feature_code":"PPL",
    "gn:name":"Ban Dakbung",
    "gn:population":0,
    "gn:timezone":"Asia/Vientiane",
    "iso:country":"LA",
    "name:lao_x_preferred":[
        "Ban Dakbung"
    ],
    "wof:name":"Ban Dakbung",
    "wof:placetype":"locality"
},
  "geometry": {"coordinates":[107.15076999999999,15.16277],"type":"Point"}
}