{
  "type": "Feature",
  "properties": {
    "gn:admin1_code":"19.0",
    "gn:asciiname":"Ban Adu",
    "gn:country_code":"LA",
    "gn:dem":455,
    "gn:feature_class":"P",
    "gn:feature_code":"PPL",
    "gn:name":"Ban Adu",
    "gn:population":0,
    "gn:timezone":"Asia/Vientiane",
    "iso:country":"LA",
    "name:lao_x_preferred":[
        "Ban Adu"
    ],
    "wof:name":"Ban Adu",
    "wof:placetype":"locality"
},
  "geometry": {"coordinates":[106.83627,16.20886],"type":"Point"}
}