{
  "type": "Feature",
  "properties": {
    "gn:admin1_code":"20.0",
    "gn:asciiname":"Ban Laobouakhok",
    "gn:country_code":"LA",
    "gn:dem":325,
    "gn:feature_class":"P",
    "gn:feature_code":"PPL",
    "gn:name":"Ban Laobouakh\u00f4k",
    "gn:population":0,
    "gn:timezone":"Asia/Vientiane",
    "iso:country":"LA",
    "name:lao_x_preferred":[
        "Ban Laobouakh\u00f4k"
    ],
    "wof:name":"Ban Laobouakhok",
    "wof:placetype":"locality"
},
  "geometry": {"coordinates":[106.29286999999999,16.47399],"type":"Point"}
}