{
  "type": "Feature",
  "properties": {
    "gn:admin1_code":"14.0",
    "gn:asciiname":"Ban Nong-Hon",
    "gn:cc2":"LA",
    "gn:country_code":"LA",
    "gn:dem":1089,
    "gn:feature_class":"P",
    "gn:feature_code":"PPL",
    "gn:name":"Ban Nong-Hon",
    "gn:population":0,
    "gn:timezone":"Asia/Vientiane",
    "iso:country":"LA",
    "name:und_x_variant":[
        "Ban Non Hon",
        "Ban Nong-Hon"
    ],
    "wof:name":"Ban Nong-Hon",
    "wof:placetype":"locality"
},
  "geometry": {"coordinates":[103.11667,19.43333],"type":"Point"}
}