{
  "type": "Feature",
  "properties": {
    "gn:admin1_code":"19.0",
    "gn:asciiname":"Ban Taloung-Noy",
    "gn:country_code":"LA",
    "gn:dem":362,
    "gn:feature_class":"P",
    "gn:feature_code":"PPL",
    "gn:name":"Ban Taloung-Noy",
    "gn:population":0,
    "gn:timezone":"Asia/Vientiane",
    "iso:country":"LA",
    "name:lao_x_preferred":[
        "Ban Taloung-Noy"
    ],
    "wof:name":"Ban Taloung-Noy",
    "wof:placetype":"locality"
},
  "geometry": {"coordinates":[106.60281000000001,16.13019],"type":"Point"}
}