{
  "type": "Feature",
  "properties": {
    "gn:admin1_code":"27.0",
    "gn:asciiname":"Ban Namouang",
    "gn:country_code":"LA",
    "gn:dem":185,
    "gn:feature_class":"P",
    "gn:feature_code":"PPL",
    "gn:name":"Ban Namouang",
    "gn:population":0,
    "gn:timezone":"Asia/Vientiane",
    "iso:country":"LA",
    "name:lao_x_preferred":[
        "Ban Namouang"
    ],
    "wof:name":"Ban Namouang",
    "wof:placetype":"locality"
},
  "geometry": {"coordinates":[102.42676,18.5361],"type":"Point"}
}