{
  "type": "Feature",
  "properties": {
    "gn:admin1_code":"17.0",
    "gn:asciiname":"Ban Lantica",
    "gn:country_code":"LA",
    "gn:dem":876,
    "gn:feature_class":"P",
    "gn:feature_code":"PPL",
    "gn:name":"Ban Lantica",
    "gn:population":0,
    "gn:timezone":"Asia/Vientiane",
    "iso:country":"LA",
    "wof:name":"Ban Lantica",
    "wof:placetype":"locality"
},
  "geometry": {"coordinates":[102.51667,20.06667],"type":"Point"}
}