{
  "type": "Feature",
  "properties": {
    "gn:admin1_code":"3.0",
    "gn:asciiname":"Ban Muanggnut",
    "gn:country_code":"LA",
    "gn:dem":676,
    "gn:feature_class":"P",
    "gn:feature_code":"PPL",
    "gn:name":"Ban Muanggnut",
    "gn:population":0,
    "gn:timezone":"Asia/Vientiane",
    "iso:country":"LA",
    "name:und_x_variant":[
        "Moung Yut",
        "Muong Iute",
        "Muong Yut",
        "Muang Yut",
        "Ban Muanggnut"
    ],
    "wof:name":"Ban Muanggnut",
    "wof:placetype":"locality"
},
  "geometry": {"coordinates":[103.75377,20.4031],"type":"Point"}
}