{
  "type": "Feature",
  "properties": {
    "gn:admin1_code":"20.0",
    "gn:asciiname":"Ban Dongpakhon",
    "gn:country_code":"LA",
    "gn:dem":150,
    "gn:feature_class":"P",
    "gn:feature_code":"PPL",
    "gn:name":"Ban D\u00f4ngpakh\u00f4n",
    "gn:population":0,
    "gn:timezone":"Asia/Vientiane",
    "iso:country":"LA",
    "name:lao_x_preferred":[
        "Ban D\u00f4ngpakh\u00f4n"
    ],
    "name:und_x_variant":[
        "Ban Pa Khone",
        "Ban Pakh\u00f4n"
    ],
    "wof:name":"Ban Dongpakhon",
    "wof:placetype":"locality"
},
  "geometry": {"coordinates":[105.24326000000001,16.47402],"type":"Point"}
}