{
  "type": "Feature",
  "properties": {
    "gn:admin1_code":"13.0",
    "gn:asciiname":"Ban May",
    "gn:country_code":"LA",
    "gn:dem":612,
    "gn:feature_class":"P",
    "gn:feature_code":"PPL",
    "gn:name":"Ban May",
    "gn:population":0,
    "gn:timezone":"Asia/Vientiane",
    "iso:country":"LA",
    "name:und_x_variant":[
        "Ban Mai",
        "Ban May"
    ],
    "wof:name":"Ban May",
    "wof:placetype":"locality"
},
  "geometry": {"coordinates":[101.13578,18.36192],"type":"Point"}
}