{
  "type": "Feature",
  "properties": {
    "gn:admin1_code":"15.0",
    "gn:asciiname":"Ban Nauat",
    "gn:country_code":"LA",
    "gn:dem":185,
    "gn:feature_class":"P",
    "gn:feature_code":"PPL",
    "gn:name":"Ban Nauat",
    "gn:population":0,
    "gn:timezone":"Asia/Vientiane",
    "iso:country":"LA",
    "name:lao_x_preferred":[
        "Ban Nauat"
    ],
    "name:und_x_variant":[
        "Ban Na Euat",
        "Ban Na Eut"
    ],
    "wof:name":"Ban Nauat",
    "wof:placetype":"locality"
},
  "geometry": {"coordinates":[105.29224000000001,17.1351],"type":"Point"}
}