{
  "type": "Feature",
  "properties": {
    "gn:admin1_code":"17.0",
    "gn:asciiname":"Ban Menon",
    "gn:country_code":"LA",
    "gn:dem":509,
    "gn:feature_class":"P",
    "gn:feature_code":"PPL",
    "gn:name":"Ban M\u00e8non",
    "gn:population":0,
    "gn:timezone":"Asia/Vientiane",
    "iso:country":"LA",
    "wof:name":"Ban Menon",
    "wof:placetype":"locality"
},
  "geometry": {"coordinates":[102.65000000000001,19.63333],"type":"Point"}
}