{
  "type": "Feature",
  "properties": {
    "gn:admin1_code":"7.0",
    "gn:asciiname":"Ban Phoulang",
    "gn:country_code":"LA",
    "gn:dem":805,
    "gn:feature_class":"P",
    "gn:feature_code":"PPL",
    "gn:name":"Ban Phoulang",
    "gn:population":0,
    "gn:timezone":"Asia/Vientiane",
    "iso:country":"LA",
    "name:lao_x_preferred":[
        "Ban Phoulang"
    ],
    "wof:name":"Ban Phoulang",
    "wof:placetype":"locality"
},
  "geometry": {"coordinates":[101.11296,19.93513],"type":"Point"}
}