{
  "type": "Feature",
  "properties": {
    "gn:admin1_code":"3.0",
    "gn:asciiname":"Ban Houayxang",
    "gn:country_code":"LA",
    "gn:dem":264,
    "gn:feature_class":"P",
    "gn:feature_code":"PPL",
    "gn:name":"Ban Houayxang",
    "gn:population":0,
    "gn:timezone":"Asia/Vientiane",
    "iso:country":"LA",
    "name:lao_x_preferred":[
        "Ban Houayxang"
    ],
    "name:und_x_variant":[
        "Na Sane",
        "Ban Na Sang"
    ],
    "wof:name":"Ban Houayxang",
    "wof:placetype":"locality"
},
  "geometry": {"coordinates":[104.41414,20.54068],"type":"Point"}
}