{
  "type": "Feature",
  "properties": {
    "gn:admin1_code":"20.0",
    "gn:asciiname":"Ban Tamli",
    "gn:country_code":"LA",
    "gn:dem":148,
    "gn:feature_class":"P",
    "gn:feature_code":"PPL",
    "gn:name":"Ban Tamli",
    "gn:population":0,
    "gn:timezone":"Asia/Vientiane",
    "iso:country":"LA",
    "name:und_x_variant":[
        "Ban Tamly",
        "Ban Tamli"
    ],
    "wof:name":"Ban Tamli",
    "wof:placetype":"locality"
},
  "geometry": {"coordinates":[105.62130000000001,16.26838],"type":"Point"}
}