{
  "type": "Feature",
  "properties": {
    "gn:admin1_code":"7.0",
    "gn:asciiname":"Ban Houayka",
    "gn:country_code":"LA",
    "gn:dem":436,
    "gn:feature_class":"P",
    "gn:feature_code":"PPL",
    "gn:name":"Ban Houayka",
    "gn:population":0,
    "gn:timezone":"Asia/Vientiane",
    "iso:country":"LA",
    "name:lao_x_preferred":[
        "Ban Houayka"
    ],
    "wof:name":"Ban Houayka",
    "wof:placetype":"locality"
},
  "geometry": {"coordinates":[101.1014,19.92083],"type":"Point"}
}