{
  "type": "Feature",
  "properties": {
    "gn:admin1_code":"2.0",
    "gn:asciiname":"Ban Nonghoy",
    "gn:country_code":"LA",
    "gn:dem":98,
    "gn:feature_class":"P",
    "gn:feature_code":"PPL",
    "gn:name":"Ban Nonghoy",
    "gn:population":0,
    "gn:timezone":"Asia/Vientiane",
    "iso:country":"LA",
    "name:lao_x_preferred":[
        "Ban Nonghoy"
    ],
    "name:und_x_variant":[
        "Ban Dong Hoi",
        "Ban D\u00f4nghoy"
    ],
    "wof:name":"Ban Nonghoy",
    "wof:placetype":"locality"
},
  "geometry": {"coordinates":[105.82496999999999,14.24718],"type":"Point"}
}