{
  "type": "Feature",
  "properties": {
    "gn:admin1_code":"17.0",
    "gn:asciiname":"Ban Ka Teng Xieng",
    "gn:country_code":"LA",
    "gn:dem":1116,
    "gn:feature_class":"P",
    "gn:feature_code":"PPL",
    "gn:name":"Ban Ka Teng Xieng",
    "gn:population":0,
    "gn:timezone":"Asia/Vientiane",
    "iso:country":"LA",
    "wof:name":"Ban Ka Teng Xieng",
    "wof:placetype":"locality"
},
  "geometry": {"coordinates":[102.68333,20.36667000000001],"type":"Point"}
}