{
  "type": "Feature",
  "properties": {
    "gn:admin1_code":"19.0",
    "gn:asciiname":"Ban Pako",
    "gn:country_code":"LA",
    "gn:dem":395,
    "gn:feature_class":"P",
    "gn:feature_code":"PPL",
    "gn:name":"Ban Pako",
    "gn:population":0,
    "gn:timezone":"Asia/Vientiane",
    "iso:country":"LA",
    "name:lao_x_preferred":[
        "Ban Pako"
    ],
    "name:und_x_variant":[
        "Pa Ko"
    ],
    "wof:name":"Ban Pako",
    "wof:placetype":"locality"
},
  "geometry": {"coordinates":[106.53581,16.14083],"type":"Point"}
}