{
  "type": "Feature",
  "properties": {
    "gn:admin1_code":"26.0",
    "gn:asciiname":"Ban Chavik",
    "gn:country_code":"LA",
    "gn:dem":184,
    "gn:feature_class":"P",
    "gn:feature_code":"PPL",
    "gn:name":"Ban Chavik",
    "gn:population":0,
    "gn:timezone":"Asia/Vientiane",
    "iso:country":"LA",
    "name:lao_x_preferred":[
        "Ban Chavik"
    ],
    "wof:name":"Ban Chavik",
    "wof:placetype":"locality"
},
  "geometry": {"coordinates":[106.81731000000001,15.41374],"type":"Point"}
}