{
  "type": "Feature",
  "properties": {
    "gn:admin1_code":"20.0",
    "gn:asciiname":"Ban Ala",
    "gn:country_code":"LA",
    "gn:dem":290,
    "gn:feature_class":"P",
    "gn:feature_code":"PPL",
    "gn:name":"Ban Ala",
    "gn:population":0,
    "gn:timezone":"Asia/Vientiane",
    "iso:country":"LA",
    "name:lao_x_preferred":[
        "Ban Ala"
    ],
    "wof:name":"Ban Ala",
    "wof:placetype":"locality"
},
  "geometry": {"coordinates":[106.51549,16.28569],"type":"Point"}
}