{
  "type": "Feature",
  "properties": {
    "gn:admin1_code":"18.0",
    "gn:asciiname":"Ban Tanha",
    "gn:country_code":"LA",
    "gn:dem":798,
    "gn:feature_class":"P",
    "gn:feature_code":"PPL",
    "gn:name":"Ban Tanha",
    "gn:population":0,
    "gn:timezone":"Asia/Vientiane",
    "iso:country":"LA",
    "wof:name":"Ban Tanha",
    "wof:placetype":"locality"
},
  "geometry": {"coordinates":[102.61528,21.04167],"type":"Point"}
}