{
  "type": "Feature",
  "properties": {
    "gn:admin1_code":"18.0",
    "gn:asciiname":"Ban Houaypoung",
    "gn:country_code":"LA",
    "gn:dem":905,
    "gn:feature_class":"P",
    "gn:feature_code":"PPL",
    "gn:name":"Ban Houaypoung",
    "gn:population":0,
    "gn:timezone":"Asia/Vientiane",
    "iso:country":"LA",
    "name:lao_x_preferred":[
        "Ban Houaypoung"
    ],
    "wof:name":"Ban Houaypoung",
    "wof:placetype":"locality"
},
  "geometry": {"coordinates":[102.39903,20.99846],"type":"Point"}
}