{
  "type": "Feature",
  "properties": {
    "gn:admin1_code":"20.0",
    "gn:asciiname":"Ban Na-Noy",
    "gn:country_code":"LA",
    "gn:dem":177,
    "gn:feature_class":"P",
    "gn:feature_code":"PPL",
    "gn:name":"Ban Na-Noy",
    "gn:population":0,
    "gn:timezone":"Asia/Vientiane",
    "iso:country":"LA",
    "name:lao_x_preferred":[
        "Ban Na-Noy"
    ],
    "wof:name":"Ban Na-Noy",
    "wof:placetype":"locality"
},
  "geometry": {"coordinates":[105.23277,17.03639],"type":"Point"}
}