{
  "type": "Feature",
  "properties": {
    "gn:admin1_code":"20.0",
    "gn:asciiname":"Ban Songkhe",
    "gn:country_code":"LA",
    "gn:dem":200,
    "gn:feature_class":"P",
    "gn:feature_code":"PPL",
    "gn:name":"Ban Songkh\u00e8",
    "gn:population":0,
    "gn:timezone":"Asia/Vientiane",
    "iso:country":"LA",
    "name:und_x_variant":[
        "Ban Song Qu\u00e9",
        "Ban Songkh\u00e8"
    ],
    "wof:name":"Ban Songkhe",
    "wof:placetype":"locality"
},
  "geometry": {"coordinates":[106.10075000000001,16.82265],"type":"Point"}
}