{
  "type": "Feature",
  "properties": {
    "gn:admin1_code":"2.0",
    "gn:asciiname":"Ban Khonthout",
    "gn:country_code":"LA",
    "gn:dem":161,
    "gn:feature_class":"P",
    "gn:feature_code":"PPL",
    "gn:name":"Ban Khonthout",
    "gn:population":0,
    "gn:timezone":"Asia/Vientiane",
    "iso:country":"LA",
    "name:lao_x_preferred":[
        "Ban Khonthout"
    ],
    "name:und_x_variant":[
        "Ban Kaut Hou",
        "Ban Khout-Hout"
    ],
    "wof:name":"Ban Khonthout",
    "wof:placetype":"locality"
},
  "geometry": {"coordinates":[106.17185000000001,14.73089],"type":"Point"}
}