{
  "type": "Feature",
  "properties": {
    "gn:admin1_code":"15.0",
    "gn:asciiname":"Ban Houaynamkham",
    "gn:country_code":"LA",
    "gn:dem":153,
    "gn:feature_class":"P",
    "gn:feature_code":"PPL",
    "gn:name":"Ban Houaynamkham",
    "gn:population":0,
    "gn:timezone":"Asia/Vientiane",
    "iso:country":"LA",
    "name:lao_x_preferred":[
        "Ban Houaynamkham"
    ],
    "wof:name":"Ban Houaynamkham",
    "wof:placetype":"locality"
},
  "geometry": {"coordinates":[105.0689,17.17256],"type":"Point"}
}