{
  "type": "Feature",
  "properties": {
    "gn:admin1_code":"2.0",
    "gn:asciiname":"Ban Houadon",
    "gn:country_code":"LA",
    "gn:dem":100,
    "gn:feature_class":"P",
    "gn:feature_code":"PPL",
    "gn:name":"Ban Houadon",
    "gn:population":0,
    "gn:timezone":"Asia/Vientiane",
    "iso:country":"LA",
    "name:und_x_variant":[
        "Ban Houa Done",
        "Ban Houadon"
    ],
    "wof:name":"Ban Houadon",
    "wof:placetype":"locality"
},
  "geometry": {"coordinates":[105.84974,14.43081],"type":"Point"}
}