{
  "type": "Feature",
  "properties": {
    "gn:admin1_code":"3.0",
    "gn:asciiname":"Ban Muangpeun",
    "gn:country_code":"LA",
    "gn:dem":1136,
    "gn:feature_class":"P",
    "gn:feature_code":"PPL",
    "gn:name":"Ban Muangpeun",
    "gn:population":0,
    "gn:timezone":"Asia/Vientiane",
    "iso:country":"LA",
    "name:und_x_variant":[
        "Muong Peun",
        "Muang Peun",
        "Ban Muangpeun"
    ],
    "wof:name":"Ban Muangpeun",
    "wof:placetype":"locality"
},
  "geometry": {"coordinates":[103.86897999999999,20.21281],"type":"Point"}
}