{
  "type": "Feature",
  "properties": {
    "gn:admin1_code":"23.0",
    "gn:asciiname":"Ban Nasommo",
    "gn:country_code":"LA",
    "gn:dem":165,
    "gn:feature_class":"P",
    "gn:feature_code":"PPL",
    "gn:name":"Ban Nas\u00f4mmo",
    "gn:population":0,
    "gn:timezone":"Asia/Vientiane",
    "iso:country":"LA",
    "name:lao_x_preferred":[
        "Ban Nas\u00f4mmo"
    ],
    "wof:name":"Ban Nasommo",
    "wof:placetype":"locality"
},
  "geometry": {"coordinates":[103.73062,18.37713],"type":"Point"}
}