{
  "type": "Feature",
  "properties": {
    "gn:admin1_code":"24.0",
    "gn:asciiname":"Ban Pakpeng",
    "gn:country_code":"LA",
    "gn:dem":170,
    "gn:feature_class":"P",
    "gn:feature_code":"PPL",
    "gn:name":"Ban Pakp\u00e9ng",
    "gn:population":0,
    "gn:timezone":"Asia/Vientiane",
    "iso:country":"LA",
    "name:lao_x_preferred":[
        "Ban Pakp\u00e9ng"
    ],
    "wof:name":"Ban Pakpeng",
    "wof:placetype":"locality"
},
  "geometry": {"coordinates":[102.79697,17.94187999999999],"type":"Point"}
}