{
  "type": "Feature",
  "properties": {
    "gn:admin1_code":"19.0",
    "gn:asciiname":"Ban Donkha",
    "gn:country_code":"LA",
    "gn:dem":152,
    "gn:feature_class":"P",
    "gn:feature_code":"PPL",
    "gn:name":"Ban Donkha",
    "gn:population":0,
    "gn:timezone":"Asia/Vientiane",
    "iso:country":"LA",
    "name:und_x_variant":[
        "Ban Done Kha",
        "Ban Donkha"
    ],
    "wof:name":"Ban Donkha",
    "wof:placetype":"locality"
},
  "geometry": {"coordinates":[105.88409,15.68647],"type":"Point"}
}