{
  "type": "Feature",
  "properties": {
    "gn:admin1_code":"24.0",
    "gn:asciiname":"Ban Donnoun",
    "gn:country_code":"LA",
    "gn:dem":174,
    "gn:feature_class":"P",
    "gn:feature_code":"PPL",
    "gn:name":"Ban Donnoun",
    "gn:population":0,
    "gn:timezone":"Asia/Vientiane",
    "iso:country":"LA",
    "name:und_x_variant":[
        "Don Noun",
        "Ban Donnoun"
    ],
    "wof:name":"Ban Donnoun",
    "wof:placetype":"locality"
},
  "geometry": {"coordinates":[102.6615,18.04929],"type":"Point"}
}