{
  "type": "Feature",
  "properties": {
    "gn:admin1_code":"3.0",
    "gn:asciiname":"Ban Houaytia",
    "gn:country_code":"LA",
    "gn:dem":353,
    "gn:feature_class":"P",
    "gn:feature_code":"PPL",
    "gn:name":"Ban Houaytia",
    "gn:population":0,
    "gn:timezone":"Asia/Vientiane",
    "iso:country":"LA",
    "name:lao_x_preferred":[
        "Ban Houaytia"
    ],
    "wof:name":"Ban Houaytia",
    "wof:placetype":"locality"
},
  "geometry": {"coordinates":[104.05968,20.88563],"type":"Point"}
}