{
  "type": "Feature",
  "properties": {
    "gn:admin1_code":"20.0",
    "gn:asciiname":"Ban Laikatha",
    "gn:country_code":"LA",
    "gn:dem":152,
    "gn:feature_class":"P",
    "gn:feature_code":"PPL",
    "gn:name":"Ban Laikatha",
    "gn:population":0,
    "gn:timezone":"Asia/Vientiane",
    "iso:country":"LA",
    "name:und_x_variant":[
        "Ban Lai Khatha",
        "Ban Laikatha"
    ],
    "wof:name":"Ban Laikatha",
    "wof:placetype":"locality"
},
  "geometry": {"coordinates":[105.28881,16.60014],"type":"Point"}
}