{
  "type": "Feature",
  "properties": {
    "gn:admin1_code":"20.0",
    "gn:asciiname":"Ban Nachik",
    "gn:country_code":"LA",
    "gn:dem":157,
    "gn:feature_class":"P",
    "gn:feature_code":"PPL",
    "gn:name":"Ban Nachik",
    "gn:population":0,
    "gn:timezone":"Asia/Vientiane",
    "iso:country":"LA",
    "name:und_x_variant":[
        "Ban Na Khak",
        "Ban Nachik"
    ],
    "wof:name":"Ban Nachik",
    "wof:placetype":"locality"
},
  "geometry": {"coordinates":[105.01385999999999,16.32466],"type":"Point"}
}