{
  "type": "Feature",
  "properties": {
    "gn:admin1_code":"17.0",
    "gn:asciiname":"Ban Houaysaou",
    "gn:country_code":"LA",
    "gn:dem":1287,
    "gn:feature_class":"P",
    "gn:feature_code":"PPL",
    "gn:name":"Ban Houaysaou",
    "gn:population":0,
    "gn:timezone":"Asia/Vientiane",
    "iso:country":"LA",
    "wof:name":"Ban Houaysaou",
    "wof:placetype":"locality"
},
  "geometry": {"coordinates":[102.69583,20.0875],"type":"Point"}
}