{
  "type": "Feature",
  "properties": {
    "gn:admin1_code":"17.0",
    "gn:asciiname":"Ban Nakham",
    "gn:country_code":"LA",
    "gn:dem":465,
    "gn:feature_class":"P",
    "gn:feature_code":"PPL",
    "gn:name":"Ban Nakham",
    "gn:population":0,
    "gn:timezone":"Asia/Vientiane",
    "iso:country":"LA",
    "name:lao_x_preferred":[
        "Ban Nakham"
    ],
    "wof:name":"Ban Nakham",
    "wof:placetype":"locality"
},
  "geometry": {"coordinates":[102.01123,19.93495],"type":"Point"}
}