{
  "type": "Feature",
  "properties": {
    "gn:admin1_code":"17.0",
    "gn:asciiname":"Ban Phonthong",
    "gn:country_code":"LA",
    "gn:dem":1055,
    "gn:feature_class":"P",
    "gn:feature_code":"PPL",
    "gn:name":"Ban Ph\u00f4nthong",
    "gn:population":0,
    "gn:timezone":"Asia/Vientiane",
    "iso:country":"LA",
    "name:lao_x_preferred":[
        "Ban Ph\u00f4nthong"
    ],
    "wof:name":"Ban Phonthong",
    "wof:placetype":"locality"
},
  "geometry": {"coordinates":[102.40924,20.90787000000001],"type":"Point"}
}