{
  "type": "Feature",
  "properties": {
    "gn:admin1_code":"20.0",
    "gn:asciiname":"Ban Palang",
    "gn:country_code":"LA",
    "gn:dem":207,
    "gn:feature_class":"P",
    "gn:feature_code":"PPL",
    "gn:name":"Ban Palang",
    "gn:population":0,
    "gn:timezone":"Asia/Vientiane",
    "iso:country":"LA",
    "name:lao_x_preferred":[
        "Ban Palang"
    ],
    "wof:name":"Ban Palang",
    "wof:placetype":"locality"
},
  "geometry": {"coordinates":[106.17202,16.23335],"type":"Point"}
}