{
  "type": "Feature",
  "properties": {
    "gn:admin1_code":"28.0",
    "gn:asciiname":"Ban Dongmo",
    "gn:country_code":"LA",
    "gn:dem":231,
    "gn:feature_class":"P",
    "gn:feature_code":"PPL",
    "gn:name":"Ban D\u00f4ngmo",
    "gn:population":0,
    "gn:timezone":"Asia/Vientiane",
    "iso:country":"LA",
    "name:lao_x_preferred":[
        "Ban D\u00f4ngmo"
    ],
    "wof:name":"Ban Dongmo",
    "wof:placetype":"locality"
},
  "geometry": {"coordinates":[103.62645000000001,18.96904],"type":"Point"}
}