{
  "type": "Feature",
  "properties": {
    "gn:admin1_code":"20.0",
    "gn:asciiname":"Ban Phan",
    "gn:country_code":"LA",
    "gn:dem":175,
    "gn:feature_class":"P",
    "gn:feature_code":"PPL",
    "gn:name":"Ban Phan",
    "gn:population":0,
    "gn:timezone":"Asia/Vientiane",
    "iso:country":"LA",
    "name:lao_x_preferred":[
        "Ban Phan"
    ],
    "wof:name":"Ban Phan",
    "wof:placetype":"locality"
},
  "geometry": {"coordinates":[106.0825,16.28611],"type":"Point"}
}