{
  "type": "Feature",
  "properties": {
    "gn:admin1_code":"26.0",
    "gn:asciiname":"Ban Hong-Nua",
    "gn:country_code":"LA",
    "gn:dem":862,
    "gn:feature_class":"P",
    "gn:feature_code":"PPL",
    "gn:name":"Ban H\u00f4ng-Nua",
    "gn:population":0,
    "gn:timezone":"Asia/Vientiane",
    "iso:country":"LA",
    "name:lao_x_preferred":[
        "Ban H\u00f4ng-Nua"
    ],
    "wof:name":"Ban Hong-Nua",
    "wof:placetype":"locality"
},
  "geometry": {"coordinates":[107.03062,15.79496],"type":"Point"}
}