{
  "type": "Feature",
  "properties": {
    "gn:admin1_code":"7.0",
    "gn:asciiname":"Ban Tang-Ong",
    "gn:country_code":"LA",
    "gn:dem":668,
    "gn:feature_class":"P",
    "gn:feature_code":"PPL",
    "gn:name":"Ban Tang-Ong",
    "gn:population":0,
    "gn:timezone":"Asia/Vientiane",
    "iso:country":"LA",
    "name:lao_x_preferred":[
        "Ban Tang-Ong"
    ],
    "wof:name":"Ban Tang-Ong",
    "wof:placetype":"locality"
},
  "geometry": {"coordinates":[101.89899,20.0027],"type":"Point"}
}