{
  "type": "Feature",
  "properties": {
    "gn:admin1_code":"20.0",
    "gn:asciiname":"Ban Kapa-Noy",
    "gn:country_code":"LA",
    "gn:dem":324,
    "gn:feature_class":"P",
    "gn:feature_code":"PPL",
    "gn:name":"Ban Kapa-Noy",
    "gn:population":0,
    "gn:timezone":"Asia/Vientiane",
    "iso:country":"LA",
    "name:lao_x_preferred":[
        "Ban Kapa-Noy"
    ],
    "wof:name":"Ban Kapa-Noy",
    "wof:placetype":"locality"
},
  "geometry": {"coordinates":[106.47273,16.30495],"type":"Point"}
}