{
  "type": "Feature",
  "properties": {
    "gn:admin1_code":"20.0",
    "gn:asciiname":"Ban Nong-I-Gno",
    "gn:country_code":"LA",
    "gn:dem":143,
    "gn:feature_class":"P",
    "gn:feature_code":"PPL",
    "gn:name":"Ban Nong-I-Gno",
    "gn:population":0,
    "gn:timezone":"Asia/Vientiane",
    "iso:country":"LA",
    "name:lao_x_preferred":[
        "Ban Nong-I-Gno"
    ],
    "wof:name":"Ban Nong-I-Gno",
    "wof:placetype":"locality"
},
  "geometry": {"coordinates":[105.10759,16.10131],"type":"Point"}
}