{
  "type": "Feature",
  "properties": {
    "gn:admin1_code":"1.0",
    "gn:asciiname":"Ban Makkhua",
    "gn:country_code":"LA",
    "gn:dem":114,
    "gn:feature_class":"P",
    "gn:feature_code":"PPL",
    "gn:name":"Ban Makkhua",
    "gn:population":0,
    "gn:timezone":"Asia/Vientiane",
    "iso:country":"LA",
    "name:lao_x_preferred":[
        "Ban Makkhua"
    ],
    "wof:name":"Ban Makkhua",
    "wof:placetype":"locality"
},
  "geometry": {"coordinates":[106.97024999999999,14.73854],"type":"Point"}
}