{
  "type": "Feature",
  "properties": {
    "gn:admin1_code":"15.0",
    "gn:asciiname":"Ban Houaysout",
    "gn:cc2":"LA",
    "gn:country_code":"LA",
    "gn:dem":281,
    "gn:feature_class":"P",
    "gn:feature_code":"PPL",
    "gn:name":"Ban Houaysout",
    "gn:population":0,
    "gn:timezone":"Asia/Vientiane",
    "iso:country":"LA",
    "name:und_x_variant":[
        "Ban Houei Sout",
        "Ban Houaysout"
    ],
    "wof:name":"Ban Houaysout",
    "wof:placetype":"locality"
},
  "geometry": {"coordinates":[106.09999999999999,17.06667],"type":"Point"}
}