{
  "type": "Feature",
  "properties": {
    "gn:admin1_code":"14.0",
    "gn:asciiname":"Ban Mang",
    "gn:country_code":"LA",
    "gn:dem":1262,
    "gn:feature_class":"P",
    "gn:feature_code":"PPL",
    "gn:name":"Ban Mang",
    "gn:population":0,
    "gn:timezone":"Asia/Vientiane",
    "iso:country":"LA",
    "name:lao_x_preferred":[
        "Ban Mang"
    ],
    "wof:name":"Ban Mang",
    "wof:placetype":"locality"
},
  "geometry": {"coordinates":[103.64113,19.25173],"type":"Point"}
}