{
  "type": "Feature",
  "properties": {
    "gn:admin1_code":"7.0",
    "gn:asciiname":"Ban Kioutlou",
    "gn:country_code":"LA",
    "gn:dem":892,
    "gn:feature_class":"P",
    "gn:feature_code":"PPL",
    "gn:name":"Ban Kioutlou",
    "gn:population":0,
    "gn:timezone":"Asia/Vientiane",
    "iso:country":"LA",
    "name:lao_x_preferred":[
        "Ban Kioutlou"
    ],
    "wof:name":"Ban Kioutlou",
    "wof:placetype":"locality"
},
  "geometry": {"coordinates":[101.36957,19.97281],"type":"Point"}
}