{
  "type": "Feature",
  "properties": {
    "gn:admin1_code":"1.0",
    "gn:asciiname":"Ban Kong-Na-Gnai",
    "gn:country_code":"LA",
    "gn:dem":868,
    "gn:feature_class":"P",
    "gn:feature_code":"PPL",
    "gn:name":"Ban Kong-Na-Gnai",
    "gn:population":0,
    "gn:timezone":"Asia/Vientiane",
    "iso:country":"LA",
    "name:und_x_variant":[
        "Noi",
        "Ban Kong-na Moy",
        "Ban Cong Na Noi",
        "Ban Kong-Na Noy",
        "Ban Cong Na Nhai",
        "Ban Kong Na",
        "Ban Kong-Na-Gnai"
    ],
    "wof:name":"Ban Kong-Na-Gnai",
    "wof:placetype":"locality"
},
  "geometry": {"coordinates":[107.13796000000001,15.12057],"type":"Point"}
}