{
  "type": "Feature",
  "properties": {
    "gn:admin1_code":"20.0",
    "gn:asciiname":"Ban Khok-Gnai",
    "gn:country_code":"LA",
    "gn:dem":170,
    "gn:feature_class":"P",
    "gn:feature_code":"PPL",
    "gn:name":"Ban Kh\u00f4k-Gnai",
    "gn:population":0,
    "gn:timezone":"Asia/Vientiane",
    "iso:country":"LA",
    "name:lao_x_preferred":[
        "Ban Kh\u00f4k-Gnai"
    ],
    "name:und_x_variant":[
        "Ban Coc",
        "Ban Kh\u00f4k"
    ],
    "wof:name":"Ban Khok-Gnai",
    "wof:placetype":"locality"
},
  "geometry": {"coordinates":[104.98587999999999,16.60564],"type":"Point"}
}