{
  "type": "Feature",
  "properties": {
    "gn:admin1_code":"3.0",
    "gn:asciiname":"Ban Sopkoy",
    "gn:country_code":"LA",
    "gn:dem":237,
    "gn:feature_class":"P",
    "gn:feature_code":"PPL",
    "gn:name":"Ban S\u00f4pkoy",
    "gn:population":0,
    "gn:timezone":"Asia/Vientiane",
    "iso:country":"LA",
    "name:lao_x_preferred":[
        "Ban S\u00f4pkoy"
    ],
    "wof:name":"Ban Sopkoy",
    "wof:placetype":"locality"
},
  "geometry": {"coordinates":[104.28426,20.7596],"type":"Point"}
}