{
  "type": "Feature",
  "properties": {
    "gn:admin1_code":"7.0",
    "gn:asciiname":"Ban Katangkoang",
    "gn:country_code":"LA",
    "gn:dem":778,
    "gn:feature_class":"P",
    "gn:feature_code":"PPL",
    "gn:name":"Ban Katangkoang",
    "gn:population":0,
    "gn:timezone":"Asia/Vientiane",
    "iso:country":"LA",
    "name:und_x_variant":[
        "Ban Ka Lang Kouang",
        "Ban Ka Lang Khouang",
        "Ban Katangkoang"
    ],
    "wof:name":"Ban Katangkoang",
    "wof:placetype":"locality"
},
  "geometry": {"coordinates":[101.75,20.71667],"type":"Point"}
}