{
  "type": "Feature",
  "properties": {
    "gn:admin1_code":"3.0",
    "gn:asciiname":"Ban Kangmuang",
    "gn:country_code":"LA",
    "gn:dem":657,
    "gn:feature_class":"P",
    "gn:feature_code":"PPL",
    "gn:name":"Ban Kangmuang",
    "gn:population":0,
    "gn:timezone":"Asia/Vientiane",
    "iso:country":"LA",
    "name:und_x_variant":[
        "Kang Muong",
        "Kang Muang",
        "Ban Kangmuang"
    ],
    "wof:name":"Ban Kangmuang",
    "wof:placetype":"locality"
},
  "geometry": {"coordinates":[104.38409,20.33236],"type":"Point"}
}