{
  "type": "Feature",
  "properties": {
    "gn:admin1_code":"19.0",
    "gn:asciiname":"Ban Napholeun",
    "gn:country_code":"LA",
    "gn:dem":178,
    "gn:feature_class":"P",
    "gn:feature_code":"PPL",
    "gn:name":"Ban Naph\u00f4leun",
    "gn:population":0,
    "gn:timezone":"Asia/Vientiane",
    "iso:country":"LA",
    "name:lao_x_preferred":[
        "Ban Naph\u00f4leun"
    ],
    "wof:name":"Ban Napholeun",
    "wof:placetype":"locality"
},
  "geometry": {"coordinates":[106.24769000000001,15.7675],"type":"Point"}
}