{
  "type": "Feature",
  "properties": {
    "gn:admin1_code":"23.0",
    "gn:asciiname":"Ban Bothun",
    "gn:country_code":"LA",
    "gn:dem":162,
    "gn:feature_class":"P",
    "gn:feature_code":"PPL",
    "gn:name":"Ban Bothun",
    "gn:population":0,
    "gn:timezone":"Asia/Vientiane",
    "iso:country":"LA",
    "name:lao_x_preferred":[
        "Ban Bothun"
    ],
    "wof:name":"Ban Bothun",
    "wof:placetype":"locality"
},
  "geometry": {"coordinates":[103.89610999999999,18.42349],"type":"Point"}
}