{
  "type": "Feature",
  "properties": {
    "gn:admin1_code":"18.0",
    "gn:asciiname":"Ban Souamnay",
    "gn:country_code":"LA",
    "gn:dem":689,
    "gn:feature_class":"P",
    "gn:feature_code":"PPL",
    "gn:name":"Ban Souamnay",
    "gn:population":0,
    "gn:timezone":"Asia/Vientiane",
    "iso:country":"LA",
    "name:lao_x_preferred":[
        "Ban Souamnay"
    ],
    "wof:name":"Ban Souamnay",
    "wof:placetype":"locality"
},
  "geometry": {"coordinates":[102.72165,21.38698],"type":"Point"}
}