{
  "type": "Feature",
  "properties": {
    "gn:admin1_code":"20.0",
    "gn:asciiname":"Ban Nalao",
    "gn:country_code":"LA",
    "gn:dem":202,
    "gn:feature_class":"P",
    "gn:feature_code":"PPL",
    "gn:name":"Ban Nalao",
    "gn:population":0,
    "gn:timezone":"Asia/Vientiane",
    "iso:country":"LA",
    "name:und_x_variant":[
        "Ban Lao",
        "Ban Nalao"
    ],
    "wof:name":"Ban Nalao",
    "wof:placetype":"locality"
},
  "geometry": {"coordinates":[105.79015,17.06359],"type":"Point"}
}