{
  "type": "Feature",
  "properties": {
    "gn:admin1_code":"17.0",
    "gn:asciiname":"Ban Hat-Houng",
    "gn:country_code":"LA",
    "gn:dem":443,
    "gn:feature_class":"P",
    "gn:feature_code":"PPL",
    "gn:name":"Ban Hat-Houng",
    "gn:population":0,
    "gn:timezone":"Asia/Vientiane",
    "iso:country":"LA",
    "name:lao_x_preferred":[
        "Ban Hat-Houng"
    ],
    "wof:name":"Ban Hat-Houng",
    "wof:placetype":"locality"
},
  "geometry": {"coordinates":[102.91670999999999,20.49755],"type":"Point"}
}