{
  "type": "Feature",
  "properties": {
    "gn:admin1_code":"7.0",
    "gn:asciiname":"Ban Sala",
    "gn:country_code":"LA",
    "gn:dem":949,
    "gn:feature_class":"P",
    "gn:feature_code":"PPL",
    "gn:name":"Ban Sala",
    "gn:population":0,
    "gn:timezone":"Asia/Vientiane",
    "iso:country":"LA",
    "name:und_x_variant":[
        "Sala",
        "Ban Sala"
    ],
    "wof:name":"Ban Sala",
    "wof:placetype":"locality"
},
  "geometry": {"coordinates":[102.05,20.93333],"type":"Point"}
}