{
  "type": "Feature",
  "properties": {
    "gn:admin1_code":"23.0",
    "gn:asciiname":"Ban Nong-O",
    "gn:country_code":"LA",
    "gn:dem":522,
    "gn:feature_class":"P",
    "gn:feature_code":"PPL",
    "gn:name":"Ban Nong-O",
    "gn:population":0,
    "gn:timezone":"Asia/Vientiane",
    "iso:country":"LA",
    "name:lao_x_preferred":[
        "Ban Nong-O"
    ],
    "wof:name":"Ban Nong-O",
    "wof:placetype":"locality"
},
  "geometry": {"coordinates":[105.07449,18.28912],"type":"Point"}
}