{
  "type": "Feature",
  "properties": {
    "gn:admin1_code":"20.0",
    "gn:asciiname":"Ban Niang-Noy",
    "gn:country_code":"LA",
    "gn:dem":231,
    "gn:feature_class":"P",
    "gn:feature_code":"PPL",
    "gn:name":"Ban Niang-Noy",
    "gn:population":0,
    "gn:timezone":"Asia/Vientiane",
    "iso:country":"LA",
    "name:lao_x_preferred":[
        "Ban Niang-Noy"
    ],
    "wof:name":"Ban Niang-Noy",
    "wof:placetype":"locality"
},
  "geometry": {"coordinates":[106.2715,16.7454],"type":"Point"}
}