{
  "type": "Feature",
  "properties": {
    "gn:admin1_code":"3.0",
    "gn:asciiname":"Ban Phua",
    "gn:country_code":"LA",
    "gn:dem":256,
    "gn:feature_class":"P",
    "gn:feature_code":"PPL",
    "gn:name":"Ban Phua",
    "gn:population":0,
    "gn:timezone":"Asia/Vientiane",
    "iso:country":"LA",
    "name:und_x_variant":[
        "Sop Phua"
    ],
    "wof:name":"Ban Phua",
    "wof:placetype":"locality"
},
  "geometry": {"coordinates":[104.83958,20.12872],"type":"Point"}
}