{
  "type": "Feature",
  "properties": {
    "gn:admin1_code":"3.0",
    "gn:asciiname":"Ban Naxeng",
    "gn:country_code":"LA",
    "gn:dem":931,
    "gn:feature_class":"P",
    "gn:feature_code":"PPL",
    "gn:name":"Ban Nax\u00e9ng",
    "gn:population":0,
    "gn:timezone":"Asia/Vientiane",
    "iso:country":"LA",
    "name:und_x_variant":[
        "Ban Na S\u00e9ng",
        "Ban Nax\u00e9ng"
    ],
    "wof:name":"Ban Naxeng",
    "wof:placetype":"locality"
},
  "geometry": {"coordinates":[104.08481999999999,20.5459],"type":"Point"}
}