{
  "type": "Feature",
  "properties": {
    "gn:admin1_code":"16.0",
    "gn:asciiname":"Ban Namluang",
    "gn:country_code":"LA",
    "gn:dem":937,
    "gn:feature_class":"P",
    "gn:feature_code":"PPL",
    "gn:name":"Ban Namluang",
    "gn:population":0,
    "gn:timezone":"Asia/Vientiane",
    "iso:country":"LA",
    "name:lao_x_preferred":[
        "Ban Namluang"
    ],
    "wof:name":"Ban Namluang",
    "wof:placetype":"locality"
},
  "geometry": {"coordinates":[101.23797999999999,20.94364],"type":"Point"}
}