{
  "type": "Feature",
  "properties": {
    "gn:admin1_code":"23.0",
    "gn:asciiname":"Ban Kenglat",
    "gn:country_code":"LA",
    "gn:dem":411,
    "gn:feature_class":"P",
    "gn:feature_code":"PPL",
    "gn:name":"Ban K\u00e8nglat",
    "gn:population":0,
    "gn:timezone":"Asia/Vientiane",
    "iso:country":"LA",
    "name:lao_x_preferred":[
        "Ban K\u00e8nglat"
    ],
    "wof:name":"Ban Kenglat",
    "wof:placetype":"locality"
},
  "geometry": {"coordinates":[104.59923000000001,18.2516],"type":"Point"}
}