{
  "type": "Feature",
  "properties": {
    "gn:admin1_code":"14.0",
    "gn:asciiname":"Ban Poungveng",
    "gn:country_code":"LA",
    "gn:dem":1104,
    "gn:feature_class":"P",
    "gn:feature_code":"PPL",
    "gn:name":"Ban Poungv\u00e8ng",
    "gn:population":0,
    "gn:timezone":"Asia/Vientiane",
    "iso:country":"LA",
    "name:lao_x_preferred":[
        "Ban Poungv\u00e8ng"
    ],
    "wof:name":"Ban Poungveng",
    "wof:placetype":"locality"
},
  "geometry": {"coordinates":[103.03167999999999,19.42578],"type":"Point"}
}