{
  "type": "Feature",
  "properties": {
    "gn:admin1_code":"20.0",
    "gn:asciiname":"Ban Tampong",
    "gn:country_code":"LA",
    "gn:dem":158,
    "gn:feature_class":"P",
    "gn:feature_code":"PPL",
    "gn:name":"Ban Tamp\u00f4ng",
    "gn:population":0,
    "gn:timezone":"Asia/Vientiane",
    "iso:country":"LA",
    "name:lao_x_preferred":[
        "Ban Tamp\u00f4ng"
    ],
    "name:und_x_variant":[
        "Ban Tampong Kh\u00f4k"
    ],
    "wof:name":"Ban Tampong",
    "wof:placetype":"locality"
},
  "geometry": {"coordinates":[105.5198,16.51972],"type":"Point"}
}