{
  "type": "Feature",
  "properties": {
    "gn:admin1_code":"2.0",
    "gn:asciiname":"Ban Donnam",
    "gn:country_code":"LA",
    "gn:dem":115,
    "gn:feature_class":"P",
    "gn:feature_code":"PPL",
    "gn:name":"Ban Donnam",
    "gn:population":0,
    "gn:timezone":"Asia/Vientiane",
    "iso:country":"LA",
    "name:und_x_variant":[
        "Done Nha Ma",
        "Ban Donnam"
    ],
    "wof:name":"Ban Donnam",
    "wof:placetype":"locality"
},
  "geometry": {"coordinates":[105.68783999999999,15.10767],"type":"Point"}
}