{
  "type": "Feature",
  "properties": {
    "gn:admin1_code":"20.0",
    "gn:asciiname":"Ban Houay",
    "gn:country_code":"LA",
    "gn:dem":173,
    "gn:feature_class":"P",
    "gn:feature_code":"PPL",
    "gn:name":"Ban Houay",
    "gn:population":0,
    "gn:timezone":"Asia/Vientiane",
    "iso:country":"LA",
    "name:und_x_variant":[
        "Ban Houei",
        "Ban Houay"
    ],
    "wof:name":"Ban Houay",
    "wof:placetype":"locality"
},
  "geometry": {"coordinates":[105.20193,16.80449],"type":"Point"}
}