{
  "type": "Feature",
  "properties": {
    "gn:admin1_code":"7.0",
    "gn:asciiname":"Ban Houaynampa",
    "gn:country_code":"LA",
    "gn:dem":688,
    "gn:feature_class":"P",
    "gn:feature_code":"PPL",
    "gn:name":"Ban Houaynampa",
    "gn:population":0,
    "gn:timezone":"Asia/Vientiane",
    "iso:country":"LA",
    "name:lao_x_preferred":[
        "Ban Houaynampa"
    ],
    "wof:name":"Ban Houaynampa",
    "wof:placetype":"locality"
},
  "geometry": {"coordinates":[101.19070000000001,19.9306],"type":"Point"}
}