{
  "type": "Feature",
  "properties": {
    "gn:admin1_code":"15.0",
    "gn:asciiname":"Ban Veunxe Mai",
    "gn:country_code":"LA",
    "gn:dem":155,
    "gn:feature_class":"P",
    "gn:feature_code":"PPL",
    "gn:name":"Ban Veunx\u00e9 Mai",
    "gn:population":0,
    "gn:timezone":"Asia/Vientiane",
    "iso:country":"LA",
    "name:lao_x_preferred":[
        "Ban Veunx\u00e9 Mai"
    ],
    "wof:name":"Ban Veunxe Mai",
    "wof:placetype":"locality"
},
  "geometry": {"coordinates":[105.06574000000001,17.16235],"type":"Point"}
}