{
  "type": "Feature",
  "properties": {
    "gn:admin1_code":"17.0",
    "gn:asciiname":"Ban Khingkang",
    "gn:country_code":"LA",
    "gn:dem":446,
    "gn:feature_class":"P",
    "gn:feature_code":"PPL",
    "gn:name":"Ban Khingkang",
    "gn:population":0,
    "gn:timezone":"Asia/Vientiane",
    "iso:country":"LA",
    "name:lao_x_preferred":[
        "Ban Khingkang"
    ],
    "name:und_x_variant":[
        "Nam Khing Nua"
    ],
    "wof:name":"Ban Khingkang",
    "wof:placetype":"locality"
},
  "geometry": {"coordinates":[102.57093,20.84506],"type":"Point"}
}