{
  "type": "Feature",
  "properties": {
    "gn:admin1_code":"17.0",
    "gn:asciiname":"Ban Pho Nek",
    "gn:country_code":"LA",
    "gn:dem":578,
    "gn:feature_class":"P",
    "gn:feature_code":"PPL",
    "gn:name":"Ban Pho N\u00eak",
    "gn:population":0,
    "gn:timezone":"Asia/Vientiane",
    "iso:country":"LA",
    "wof:name":"Ban Pho Nek",
    "wof:placetype":"locality"
},
  "geometry": {"coordinates":[102.26667,20.21667],"type":"Point"}
}