{
  "type": "Feature",
  "properties": {
    "gn:admin1_code":"3.0",
    "gn:asciiname":"Ban Houaypit",
    "gn:country_code":"LA",
    "gn:dem":397,
    "gn:feature_class":"P",
    "gn:feature_code":"PPL",
    "gn:name":"Ban Houaypit",
    "gn:population":0,
    "gn:timezone":"Asia/Vientiane",
    "iso:country":"LA",
    "name:lao_x_preferred":[
        "Ban Houaypit"
    ],
    "wof:name":"Ban Houaypit",
    "wof:placetype":"locality"
},
  "geometry": {"coordinates":[104.22597,20.80517],"type":"Point"}
}