{
  "type": "Feature",
  "properties": {
    "gn:admin1_code":"19.0",
    "gn:asciiname":"Ban Toumli-Khao",
    "gn:country_code":"LA",
    "gn:dem":355,
    "gn:feature_class":"P",
    "gn:feature_code":"PPL",
    "gn:name":"Ban Toumli-Khao",
    "gn:population":0,
    "gn:timezone":"Asia/Vientiane",
    "iso:country":"LA",
    "name:lao_x_preferred":[
        "Ban Toumli-Khao"
    ],
    "wof:name":"Ban Toumli-Khao",
    "wof:placetype":"locality"
},
  "geometry": {"coordinates":[106.65585,16.19995],"type":"Point"}
}