{
  "type": "Feature",
  "properties": {
    "gn:admin1_code":"2.0",
    "gn:asciiname":"Ban Boung",
    "gn:country_code":"LA",
    "gn:dem":95,
    "gn:feature_class":"P",
    "gn:feature_code":"PPL",
    "gn:name":"Ban Boung",
    "gn:population":0,
    "gn:timezone":"Asia/Vientiane",
    "iso:country":"LA",
    "name:lao_x_preferred":[
        "Ban Boung"
    ],
    "wof:name":"Ban Boung",
    "wof:placetype":"locality"
},
  "geometry": {"coordinates":[105.8728,14.15408],"type":"Point"}
}