{
  "type": "Feature",
  "properties": {
    "gn:admin1_code":"20.0",
    "gn:asciiname":"Ban Naphonthan",
    "gn:country_code":"LA",
    "gn:dem":169,
    "gn:feature_class":"P",
    "gn:feature_code":"PPL",
    "gn:name":"Ban Naph\u00f4nthan",
    "gn:population":0,
    "gn:timezone":"Asia/Vientiane",
    "iso:country":"LA",
    "name:lao_x_preferred":[
        "Ban Naph\u00f4nthan"
    ],
    "name:und_x_variant":[
        "Ban Naph\u00f4 Thanh",
        "Ban Ph\u00f4nthan"
    ],
    "wof:name":"Ban Naphonthan",
    "wof:placetype":"locality"
},
  "geometry": {"coordinates":[104.99164,16.81649],"type":"Point"}
}