{
  "type": "Feature",
  "properties": {
    "gn:admin1_code":"16.0",
    "gn:asciiname":"Ban Chavadi",
    "gn:country_code":"LA",
    "gn:dem":1083,
    "gn:feature_class":"P",
    "gn:feature_code":"PPL",
    "gn:name":"Ban Chavadi",
    "gn:population":0,
    "gn:timezone":"Asia/Vientiane",
    "iso:country":"LA",
    "name:lao_x_preferred":[
        "Ban Chavadi"
    ],
    "wof:name":"Ban Chavadi",
    "wof:placetype":"locality"
},
  "geometry": {"coordinates":[100.81317,20.75736],"type":"Point"}
}