{
  "type": "Feature",
  "properties": {
    "gn:admin1_code":"20.0",
    "gn:asciiname":"Ban Vangsaloang",
    "gn:cc2":"LA",
    "gn:country_code":"LA",
    "gn:dem":228,
    "gn:feature_class":"P",
    "gn:feature_code":"PPL",
    "gn:name":"Ban Vangsaloang",
    "gn:population":0,
    "gn:timezone":"Asia/Vientiane",
    "iso:country":"LA",
    "name:und_x_variant":[
        "Ban Vang Salonang",
        "Ban Vangsaloang"
    ],
    "wof:name":"Ban Vangsaloang",
    "wof:placetype":"locality"
},
  "geometry": {"coordinates":[106.08333,16.91667],"type":"Point"}
}