{
  "type": "Feature",
  "properties": {
    "gn:admin1_code":"2.0",
    "gn:asciiname":"Ban Xong",
    "gn:country_code":"LA",
    "gn:dem":105,
    "gn:feature_class":"P",
    "gn:feature_code":"PPL",
    "gn:name":"Ban X\u00f4ng",
    "gn:population":0,
    "gn:timezone":"Asia/Vientiane",
    "iso:country":"LA",
    "name:und_x_variant":[
        "Ban Soun",
        "Ban X\u00f4ng"
    ],
    "wof:name":"Ban Xong",
    "wof:placetype":"locality"
},
  "geometry": {"coordinates":[105.80228,15.16782],"type":"Point"}
}