{
  "type": "Feature",
  "properties": {
    "gn:admin1_code":"20.0",
    "gn:asciiname":"Ban Sano",
    "gn:country_code":"LA",
    "gn:dem":207,
    "gn:feature_class":"P",
    "gn:feature_code":"PPL",
    "gn:name":"Ban San\u00f4",
    "gn:population":0,
    "gn:timezone":"Asia/Vientiane",
    "iso:country":"LA",
    "name:lao_x_preferred":[
        "Ban San\u00f4"
    ],
    "wof:name":"Ban Sano",
    "wof:placetype":"locality"
},
  "geometry": {"coordinates":[106.10503,16.13269],"type":"Point"}
}