{
  "type": "Feature",
  "properties": {
    "gn:admin1_code":"20.0",
    "gn:asciiname":"Ban Houaypoun",
    "gn:country_code":"LA",
    "gn:dem":210,
    "gn:feature_class":"P",
    "gn:feature_code":"PPL",
    "gn:name":"Ban Houaypoun",
    "gn:population":0,
    "gn:timezone":"Asia/Vientiane",
    "iso:country":"LA",
    "name:und_x_variant":[
        "Ban Houei Poune",
        "Ban Houaypoun"
    ],
    "wof:name":"Ban Houaypoun",
    "wof:placetype":"locality"
},
  "geometry": {"coordinates":[105.58614,16.86334],"type":"Point"}
}