{
  "type": "Feature",
  "properties": {
    "gn:admin1_code":"17.0",
    "gn:asciiname":"Pong Cha",
    "gn:country_code":"LA",
    "gn:dem":822,
    "gn:feature_class":"P",
    "gn:feature_code":"PPL",
    "gn:name":"Pong Cha",
    "gn:population":0,
    "gn:timezone":"Asia/Vientiane",
    "iso:country":"LA",
    "wof:name":"Pong Cha",
    "wof:placetype":"locality"
},
  "geometry": {"coordinates":[102.76667,20.75],"type":"Point"}
}