{
  "type": "Feature",
  "properties": {
    "gn:admin1_code":"14.0",
    "gn:asciiname":"Ban Bon",
    "gn:country_code":"LA",
    "gn:dem":1120,
    "gn:feature_class":"P",
    "gn:feature_code":"PPL",
    "gn:name":"Ban Bon",
    "gn:population":0,
    "gn:timezone":"Asia/Vientiane",
    "iso:country":"LA",
    "name:lao_x_preferred":[
        "Ban Bon"
    ],
    "wof:name":"Ban Bon",
    "wof:placetype":"locality"
},
  "geometry": {"coordinates":[103.14427000000001,19.68303],"type":"Point"}
}