{
  "type": "Feature",
  "properties": {
    "gn:admin1_code":"22.0",
    "gn:asciiname":"Ban Namkeung-Kao",
    "gn:country_code":"LA",
    "gn:dem":369,
    "gn:feature_class":"P",
    "gn:feature_code":"PPL",
    "gn:name":"Ban Namkeung-Kao",
    "gn:population":0,
    "gn:timezone":"Asia/Vientiane",
    "iso:country":"LA",
    "name:und_x_variant":[
        "Ban Nam Kueng",
        "Ban Nam Kueung",
        "Ban Namkeung-Kao"
    ],
    "wof:name":"Ban Namkeung-Kao",
    "wof:placetype":"locality"
},
  "geometry": {"coordinates":[100.25870999999999,20.40296],"type":"Point"}
}