{
  "type": "Feature",
  "properties": {
    "gn:admin1_code":"18.0",
    "gn:asciiname":"Ban Houaphimo",
    "gn:country_code":"LA",
    "gn:dem":1194,
    "gn:feature_class":"P",
    "gn:feature_code":"PPL",
    "gn:name":"Ban Houaphimo",
    "gn:population":0,
    "gn:timezone":"Asia/Vientiane",
    "iso:country":"LA",
    "name:und_x_variant":[
        "Hoa Phi Mo",
        "Ban Houaphimo"
    ],
    "wof:name":"Ban Houaphimo",
    "wof:placetype":"locality"
},
  "geometry": {"coordinates":[101.72811,22.01086],"type":"Point"}
}