{
  "type": "Feature",
  "properties": {
    "gn:admin1_code":"19.0",
    "gn:asciiname":"Ban Taopoun",
    "gn:country_code":"LA",
    "gn:dem":187,
    "gn:feature_class":"P",
    "gn:feature_code":"PPL",
    "gn:name":"Ban Taopoun",
    "gn:population":0,
    "gn:timezone":"Asia/Vientiane",
    "iso:country":"LA",
    "name:lao_x_preferred":[
        "Ban Taopoun"
    ],
    "wof:name":"Ban Taopoun",
    "wof:placetype":"locality"
},
  "geometry": {"coordinates":[106.43257,15.7195],"type":"Point"}
}