{
  "type": "Feature",
  "properties": {
    "gn:admin1_code":"17.0",
    "gn:asciiname":"Ban Houana",
    "gn:country_code":"LA",
    "gn:dem":378,
    "gn:feature_class":"P",
    "gn:feature_code":"PPL",
    "gn:name":"Ban Houana",
    "gn:population":0,
    "gn:timezone":"Asia/Vientiane",
    "iso:country":"LA",
    "name:lao_x_preferred":[
        "Ban Houana"
    ],
    "name:und_x_variant":[
        "Ban Hua Na"
    ],
    "wof:name":"Ban Houana",
    "wof:placetype":"locality"
},
  "geometry": {"coordinates":[102.33360999999999,20.45972],"type":"Point"}
}