{
  "type": "Feature",
  "properties": {
    "gn:admin1_code":"2.0",
    "gn:asciiname":"Ban Donggnang",
    "gn:country_code":"LA",
    "gn:dem":103,
    "gn:feature_class":"P",
    "gn:feature_code":"PPL",
    "gn:name":"Ban D\u00f4nggnang",
    "gn:population":0,
    "gn:timezone":"Asia/Vientiane",
    "iso:country":"LA",
    "name:und_x_variant":[
        "Ban D\u00f4ng Nhang",
        "Ban D\u00f4nggnang"
    ],
    "wof:name":"Ban Donggnang",
    "wof:placetype":"locality"
},
  "geometry": {"coordinates":[105.82795,14.60994],"type":"Point"}
}