{
  "type": "Feature",
  "properties": {
    "gn:admin1_code":"14.0",
    "gn:asciiname":"Ban Om",
    "gn:country_code":"LA",
    "gn:dem":1212,
    "gn:feature_class":"P",
    "gn:feature_code":"PPL",
    "gn:name":"Ban \u00d4m",
    "gn:population":0,
    "gn:timezone":"Asia/Vientiane",
    "iso:country":"LA",
    "name:und_x_variant":[
        "Ban Hom",
        "Ban \u00d4m"
    ],
    "wof:name":"Ban Om",
    "wof:placetype":"locality"
},
  "geometry": {"coordinates":[103.55476,19.29063],"type":"Point"}
}