{
  "type": "Feature",
  "properties": {
    "gn:admin1_code":"20.0",
    "gn:asciiname":"Ban Nalai Khok",
    "gn:country_code":"LA",
    "gn:dem":163,
    "gn:feature_class":"P",
    "gn:feature_code":"PPL",
    "gn:name":"Ban Nalai Kh\u00f4k",
    "gn:population":0,
    "gn:timezone":"Asia/Vientiane",
    "iso:country":"LA",
    "name:und_x_variant":[
        "Nalai Khok",
        "Ban Nalai Kh\u00f4k"
    ],
    "wof:name":"Ban Nalai Khok",
    "wof:placetype":"locality"
},
  "geometry": {"coordinates":[105.34206,16.73775],"type":"Point"}
}