{
  "type": "Feature",
  "properties": {
    "gn:admin1_code":"20.0",
    "gn:asciiname":"Ban Keng-Nokkhao",
    "gn:country_code":"LA",
    "gn:dem":164,
    "gn:feature_class":"P",
    "gn:feature_code":"PPL",
    "gn:name":"Ban K\u00e9ng-N\u00f4kkhao",
    "gn:population":0,
    "gn:timezone":"Asia/Vientiane",
    "iso:country":"LA",
    "name:lao_x_preferred":[
        "Ban K\u00e9ng-N\u00f4kkhao"
    ],
    "wof:name":"Ban Keng-Nokkhao",
    "wof:placetype":"locality"
},
  "geometry": {"coordinates":[105.1867,16.12889],"type":"Point"}
}