{
  "type": "Feature",
  "properties": {
    "gn:admin1_code":"2.0",
    "gn:asciiname":"Ban Kha",
    "gn:country_code":"LA",
    "gn:dem":107,
    "gn:feature_class":"P",
    "gn:feature_code":"PPL",
    "gn:name":"Ban Kha",
    "gn:population":0,
    "gn:timezone":"Asia/Vientiane",
    "iso:country":"LA",
    "name:lao_x_preferred":[
        "Ban Kha"
    ],
    "name:und_x_variant":[
        "Ban Kha (1)"
    ],
    "wof:name":"Ban Kha",
    "wof:placetype":"locality"
},
  "geometry": {"coordinates":[105.65405,14.71345],"type":"Point"}
}