{
  "type": "Feature",
  "properties": {
    "gn:admin1_code":"14.0",
    "gn:asciiname":"Ban Choum",
    "gn:cc2":"LA",
    "gn:country_code":"LA",
    "gn:dem":1169,
    "gn:feature_class":"P",
    "gn:feature_code":"PPL",
    "gn:name":"Ban Choum",
    "gn:population":0,
    "gn:timezone":"Asia/Vientiane",
    "iso:country":"LA",
    "name:und_x_variant":[
        "Ban Chom",
        "Ban Choum"
    ],
    "wof:name":"Ban Choum",
    "wof:placetype":"locality"
},
  "geometry": {"coordinates":[103.25,19.45],"type":"Point"}
}