{
  "type": "Feature",
  "properties": {
    "gn:admin1_code":"22.0",
    "gn:asciiname":"Ban Moksamok",
    "gn:country_code":"LA",
    "gn:dem":960,
    "gn:feature_class":"P",
    "gn:feature_code":"PPL",
    "gn:name":"Ban M\u00f4ksam\u00f4k",
    "gn:population":0,
    "gn:timezone":"Asia/Vientiane",
    "iso:country":"LA",
    "name:lao_x_preferred":[
        "Ban M\u00f4ksam\u00f4k"
    ],
    "wof:name":"Ban Moksamok",
    "wof:placetype":"locality"
},
  "geometry": {"coordinates":[100.94717,20.42519],"type":"Point"}
}