{
  "type": "Feature",
  "properties": {
    "gn:admin1_code":"3.0",
    "gn:asciiname":"Ban Namuang",
    "gn:country_code":"LA",
    "gn:dem":987,
    "gn:feature_class":"P",
    "gn:feature_code":"PPL",
    "gn:name":"Ban Namuang",
    "gn:population":0,
    "gn:timezone":"Asia/Vientiane",
    "iso:country":"LA",
    "name:und_x_variant":[
        "Ban Na Muong",
        "Ban Namuang"
    ],
    "wof:name":"Ban Namuang",
    "wof:placetype":"locality"
},
  "geometry": {"coordinates":[104.01194,20.31371],"type":"Point"}
}