{
  "type": "Feature",
  "properties": {
    "gn:admin1_code":"7.0",
    "gn:asciiname":"Ban Mokkok",
    "gn:country_code":"LA",
    "gn:dem":767,
    "gn:feature_class":"P",
    "gn:feature_code":"PPL",
    "gn:name":"Ban M\u00f4kk\u00f4k",
    "gn:population":0,
    "gn:timezone":"Asia/Vientiane",
    "iso:country":"LA",
    "name:lao_x_preferred":[
        "Ban M\u00f4kk\u00f4k"
    ],
    "wof:name":"Ban Mokkok",
    "wof:placetype":"locality"
},
  "geometry": {"coordinates":[101.58291,20.34537000000001],"type":"Point"}
}