{
  "type": "Feature",
  "properties": {
    "gn:admin1_code":"17.0",
    "gn:asciiname":"Ban Phonngam",
    "gn:country_code":"LA",
    "gn:dem":301,
    "gn:feature_class":"P",
    "gn:feature_code":"PPL",
    "gn:name":"Ban Ph\u00f4nngam",
    "gn:population":0,
    "gn:timezone":"Asia/Vientiane",
    "iso:country":"LA",
    "name:lao_x_preferred":[
        "Ban Ph\u00f4nngam"
    ],
    "wof:name":"Ban Phonngam",
    "wof:placetype":"locality"
},
  "geometry": {"coordinates":[102.25978000000001,19.96185],"type":"Point"}
}