{
  "type": "Feature",
  "properties": {
    "gn:admin1_code":"17.0",
    "gn:asciiname":"Ban Houayhao",
    "gn:country_code":"LA",
    "gn:dem":1404,
    "gn:feature_class":"P",
    "gn:feature_code":"PPL",
    "gn:name":"Ban Houayhao",
    "gn:population":0,
    "gn:timezone":"Asia/Vientiane",
    "iso:country":"LA",
    "name:lao_x_preferred":[
        "Ban Houayhao"
    ],
    "wof:name":"Ban Houayhao",
    "wof:placetype":"locality"
},
  "geometry": {"coordinates":[102.22623,19.56573],"type":"Point"}
}