{
  "type": "Feature",
  "properties": {
    "gn:admin1_code":"2.0",
    "gn:asciiname":"Ban Hanglong",
    "gn:country_code":"LA",
    "gn:dem":90,
    "gn:feature_class":"P",
    "gn:feature_code":"PPL",
    "gn:name":"Ban Hangl\u00f4ng",
    "gn:population":0,
    "gn:timezone":"Asia/Vientiane",
    "iso:country":"LA",
    "name:lao_x_preferred":[
        "Ban Hangl\u00f4ng"
    ],
    "wof:name":"Ban Hanglong",
    "wof:placetype":"locality"
},
  "geometry": {"coordinates":[105.80309,14.02152],"type":"Point"}
}