{
  "type": "Feature",
  "properties": {
    "gn:admin1_code":"26.0",
    "gn:asciiname":"Ban Palong-Gnai",
    "gn:country_code":"LA",
    "gn:dem":798,
    "gn:feature_class":"P",
    "gn:feature_code":"PPL",
    "gn:name":"Ban Palong-Gnai",
    "gn:population":0,
    "gn:timezone":"Asia/Vientiane",
    "iso:country":"LA",
    "name:lao_x_preferred":[
        "Ban Palong-Gnai"
    ],
    "wof:name":"Ban Palong-Gnai",
    "wof:placetype":"locality"
},
  "geometry": {"coordinates":[107.46290999999999,15.28218],"type":"Point"}
}