{
  "type": "Feature",
  "properties": {
    "gn:admin1_code":"1.0",
    "gn:asciiname":"Ban Nong Kham",
    "gn:country_code":"LA",
    "gn:dem":95,
    "gn:feature_class":"P",
    "gn:feature_code":"PPL",
    "gn:name":"Ban Nong Kham",
    "gn:population":0,
    "gn:timezone":"Asia/Vientiane",
    "iso:country":"LA",
    "name:und_x_variant":[
        "Nong Kham",
        "Ban Nong Kham"
    ],
    "wof:name":"Ban Nong Kham",
    "wof:placetype":"locality"
},
  "geometry": {"coordinates":[106.45,14.55],"type":"Point"}
}