{
  "type": "Feature",
  "properties": {
    "gn:admin1_code":"17.0",
    "gn:asciiname":"Ban Sen Viset",
    "gn:country_code":"LA",
    "gn:dem":1036,
    "gn:feature_class":"P",
    "gn:feature_code":"PPL",
    "gn:name":"Ban S\u00e8n Viset",
    "gn:population":0,
    "gn:timezone":"Asia/Vientiane",
    "iso:country":"LA",
    "wof:name":"Ban Sen Viset",
    "wof:placetype":"locality"
},
  "geometry": {"coordinates":[102.53333000000001,19.73333],"type":"Point"}
}