{
  "type": "Feature",
  "properties": {
    "gn:admin1_code":"3.0",
    "gn:asciiname":"Ban Co Lang",
    "gn:country_code":"LA",
    "gn:dem":469,
    "gn:feature_class":"P",
    "gn:feature_code":"PPL",
    "gn:name":"Ban Co Lang",
    "gn:population":0,
    "gn:timezone":"Asia/Vientiane",
    "iso:country":"LA",
    "wof:name":"Ban Co Lang",
    "wof:placetype":"locality"
},
  "geometry": {"coordinates":[104.48333,20.63333],"type":"Point"}
}