{
  "type": "Feature",
  "properties": {
    "gn:admin1_code":"20.0",
    "gn:asciiname":"Ban Palai",
    "gn:country_code":"LA",
    "gn:dem":205,
    "gn:feature_class":"P",
    "gn:feature_code":"PPL",
    "gn:name":"Ban Palai",
    "gn:population":0,
    "gn:timezone":"Asia/Vientiane",
    "iso:country":"LA",
    "name:und_x_variant":[
        "Ban Pra Lai",
        "Ban Palai"
    ],
    "wof:name":"Ban Palai",
    "wof:placetype":"locality"
},
  "geometry": {"coordinates":[106.43875,16.60666],"type":"Point"}
}