{
  "type": "Feature",
  "properties": {
    "gn:admin1_code":"1.0",
    "gn:asciiname":"Ban Moun",
    "gn:country_code":"LA",
    "gn:dem":841,
    "gn:feature_class":"P",
    "gn:feature_code":"PPL",
    "gn:name":"Ban Moun",
    "gn:population":0,
    "gn:timezone":"Asia/Vientiane",
    "iso:country":"LA",
    "name:lao_x_preferred":[
        "Ban Moun"
    ],
    "wof:name":"Ban Moun",
    "wof:placetype":"locality"
},
  "geometry": {"coordinates":[106.97016000000001,15.18649],"type":"Point"}
}