{
  "type": "Feature",
  "properties": {
    "gn:admin1_code":"3.0",
    "gn:asciiname":"Ban Houayxai",
    "gn:country_code":"LA",
    "gn:dem":1264,
    "gn:feature_class":"P",
    "gn:feature_code":"PPL",
    "gn:name":"Ban Houayxai",
    "gn:population":0,
    "gn:timezone":"Asia/Vientiane",
    "iso:country":"LA",
    "name:lao_x_preferred":[
        "Ban Houayxai"
    ],
    "wof:name":"Ban Houayxai",
    "wof:placetype":"locality"
},
  "geometry": {"coordinates":[103.25091,20.52362],"type":"Point"}
}