{
  "type": "Feature",
  "properties": {
    "gn:admin1_code":"1.0",
    "gn:asciiname":"Ban Vangtat",
    "gn:country_code":"LA",
    "gn:dem":830,
    "gn:feature_class":"P",
    "gn:feature_code":"PPL",
    "gn:name":"Ban Vangtat",
    "gn:population":0,
    "gn:timezone":"Asia/Vientiane",
    "iso:country":"LA",
    "name:lao_x_preferred":[
        "Ban Vangtat"
    ],
    "wof:name":"Ban Vangtat",
    "wof:placetype":"locality"
},
  "geometry": {"coordinates":[107.39537,15.03179],"type":"Point"}
}