{
  "type": "Feature",
  "properties": {
    "gn:admin1_code":"20.0",
    "gn:asciiname":"Ban Tanonkham",
    "gn:country_code":"LA",
    "gn:dem":156,
    "gn:feature_class":"P",
    "gn:feature_code":"PPL",
    "gn:name":"Ban Tan\u00f4nkham",
    "gn:population":0,
    "gn:timezone":"Asia/Vientiane",
    "iso:country":"LA",
    "name:lao_x_preferred":[
        "Ban Tan\u00f4nkham"
    ],
    "wof:name":"Ban Tanonkham",
    "wof:placetype":"locality"
},
  "geometry": {"coordinates":[105.51322,16.50633],"type":"Point"}
}