{
  "type": "Feature",
  "properties": {
    "gn:admin1_code":"3.0",
    "gn:asciiname":"Ban Sanamhai",
    "gn:country_code":"LA",
    "gn:dem":913,
    "gn:feature_class":"P",
    "gn:feature_code":"PPL",
    "gn:name":"Ban Sanamhai",
    "gn:population":0,
    "gn:timezone":"Asia/Vientiane",
    "iso:country":"LA",
    "name:lao_x_preferred":[
        "Ban Sanamhai"
    ],
    "wof:name":"Ban Sanamhai",
    "wof:placetype":"locality"
},
  "geometry": {"coordinates":[103.67389,19.98749],"type":"Point"}
}