{
  "type": "Feature",
  "properties": {
    "gn:admin1_code":"2.0",
    "gn:asciiname":"Ban Kiatngong",
    "gn:country_code":"LA",
    "gn:dem":171,
    "gn:feature_class":"P",
    "gn:feature_code":"PPL",
    "gn:name":"Ban Kiatng\u00f4ng",
    "gn:population":0,
    "gn:timezone":"Asia/Vientiane",
    "iso:country":"LA",
    "name:und_x_variant":[
        "Ban Kiatng\u00f4ng",
        "Ban Ki\u00ean Ng\u00f4ng",
        "Ban Kian-Ng\u00f4ng"
    ],
    "wof:name":"Ban Kiatngong",
    "wof:placetype":"locality"
},
  "geometry": {"coordinates":[106.03785000000001,14.77069],"type":"Point"}
}