{
  "type": "Feature",
  "properties": {
    "gn:admin1_code":"17.0",
    "gn:asciiname":"Ban Phonsouk",
    "gn:country_code":"LA",
    "gn:dem":452,
    "gn:feature_class":"P",
    "gn:feature_code":"PPL",
    "gn:name":"Ban Ph\u00f4nsouk",
    "gn:population":0,
    "gn:timezone":"Asia/Vientiane",
    "iso:country":"LA",
    "name:lao_x_preferred":[
        "Ban Ph\u00f4nsouk"
    ],
    "wof:name":"Ban Phonsouk",
    "wof:placetype":"locality"
},
  "geometry": {"coordinates":[102.84005999999999,21.05485],"type":"Point"}
}