{
  "type": "Feature",
  "properties": {
    "gn:admin1_code":"18.0",
    "gn:asciiname":"Ban Xichachay",
    "gn:country_code":"LA",
    "gn:dem":1155,
    "gn:feature_class":"P",
    "gn:feature_code":"PPL",
    "gn:name":"Ban Xichachay",
    "gn:population":0,
    "gn:timezone":"Asia/Vientiane",
    "iso:country":"LA",
    "name:lao_x_preferred":[
        "Ban Xichachay"
    ],
    "wof:name":"Ban Xichachay",
    "wof:placetype":"locality"
},
  "geometry": {"coordinates":[101.89917,22.11868],"type":"Point"}
}