{
  "type": "Feature",
  "properties": {
    "gn:admin1_code":"14.0",
    "gn:asciiname":"Ban Koay",
    "gn:country_code":"LA",
    "gn:dem":573,
    "gn:feature_class":"P",
    "gn:feature_code":"PPL",
    "gn:name":"Ban Koay",
    "gn:population":0,
    "gn:timezone":"Asia/Vientiane",
    "iso:country":"LA",
    "name:lao_x_preferred":[
        "Ban Koay"
    ],
    "wof:name":"Ban Koay",
    "wof:placetype":"locality"
},
  "geometry": {"coordinates":[103.58172999999999,19.61941],"type":"Point"}
}