{
  "type": "Feature",
  "properties": {
    "gn:admin1_code":"19.0",
    "gn:asciiname":"Ban Nami-Noy",
    "gn:country_code":"LA",
    "gn:dem":269,
    "gn:feature_class":"P",
    "gn:feature_code":"PPL",
    "gn:name":"Ban Nami-Noy",
    "gn:population":0,
    "gn:timezone":"Asia/Vientiane",
    "iso:country":"LA",
    "name:lao_x_preferred":[
        "Ban Nami-Noy"
    ],
    "name:und_x_variant":[
        "Ban Nam Noi"
    ],
    "wof:name":"Ban Nami-Noy",
    "wof:placetype":"locality"
},
  "geometry": {"coordinates":[106.14700000000001,15.60648],"type":"Point"}
}