{
  "type": "Feature",
  "properties": {
    "gn:admin1_code":"27.0",
    "gn:asciiname":"Ban Hattha",
    "gn:country_code":"LA",
    "gn:dem":193,
    "gn:feature_class":"P",
    "gn:feature_code":"PPL",
    "gn:name":"Ban Hattha",
    "gn:population":0,
    "gn:timezone":"Asia/Vientiane",
    "iso:country":"LA",
    "name:lao_x_preferred":[
        "Ban Hattha"
    ],
    "wof:name":"Ban Hattha",
    "wof:placetype":"locality"
},
  "geometry": {"coordinates":[102.45014,18.60887],"type":"Point"}
}