{
  "type": "Feature",
  "properties": {
    "gn:admin1_code":"14.0",
    "gn:asciiname":"Ban Theun",
    "gn:country_code":"LA",
    "gn:dem":1168,
    "gn:feature_class":"P",
    "gn:feature_code":"PPL",
    "gn:name":"Ban Theun",
    "gn:population":0,
    "gn:timezone":"Asia/Vientiane",
    "iso:country":"LA",
    "name:lao_x_preferred":[
        "Ban Theun"
    ],
    "wof:name":"Ban Theun",
    "wof:placetype":"locality"
},
  "geometry": {"coordinates":[103.35102000000001,19.56186],"type":"Point"}
}