{
  "type": "Feature",
  "properties": {
    "gn:admin1_code":"2.0",
    "gn:asciiname":"Ban Houakhong-Gnai",
    "gn:country_code":"LA",
    "gn:dem":95,
    "gn:feature_class":"P",
    "gn:feature_code":"PPL",
    "gn:name":"Ban Houakh\u00f4ng-Gnai",
    "gn:population":0,
    "gn:timezone":"Asia/Vientiane",
    "iso:country":"LA",
    "name:lao_x_preferred":[
        "Ban Houakh\u00f4ng-Gnai"
    ],
    "name:und_x_variant":[
        "Houa Khong Nhai"
    ],
    "wof:name":"Ban Houakhong-Gnai",
    "wof:placetype":"locality"
},
  "geometry": {"coordinates":[105.80936,14.20239],"type":"Point"}
}