{
  "type": "Feature",
  "properties": {
    "gn:admin1_code":"27.0",
    "gn:asciiname":"Ban Khonphouk",
    "gn:country_code":"LA",
    "gn:dem":206,
    "gn:feature_class":"P",
    "gn:feature_code":"PPL",
    "gn:name":"Ban Khonphouk",
    "gn:population":0,
    "gn:timezone":"Asia/Vientiane",
    "iso:country":"LA",
    "name:lao_x_preferred":[
        "Ban Khonphouk"
    ],
    "name:und_x_variant":[
        "Ban Khonephouk",
        "Ban Khone Phuk"
    ],
    "wof:name":"Ban Khonphouk",
    "wof:placetype":"locality"
},
  "geometry": {"coordinates":[102.27468,18.62966],"type":"Point"}
}