{
  "type": "Feature",
  "properties": {
    "gn:admin1_code":"20.0",
    "gn:asciiname":"Ban Xaykha",
    "gn:cc2":"LA",
    "gn:country_code":"LA",
    "gn:dem":145,
    "gn:feature_class":"P",
    "gn:feature_code":"PPL",
    "gn:name":"Ban Xaykha",
    "gn:population":0,
    "gn:timezone":"Asia/Vientiane",
    "iso:country":"LA",
    "name:und_x_variant":[
        "Ban Saikhua",
        "Ban Xaykha"
    ],
    "wof:name":"Ban Xaykha",
    "wof:placetype":"locality"
},
  "geometry": {"coordinates":[105.13333,16.55],"type":"Point"}
}