{
  "type": "Feature",
  "properties": {
    "gn:admin1_code":"13.0",
    "gn:asciiname":"Ban Hat Kat Ke",
    "gn:country_code":"LA",
    "gn:dem":233,
    "gn:feature_class":"P",
    "gn:feature_code":"PPL",
    "gn:name":"Ban Hat Kat K\u00e9",
    "gn:population":0,
    "gn:timezone":"Asia/Vientiane",
    "iso:country":"LA",
    "wof:name":"Ban Hat Kat Ke",
    "wof:placetype":"locality"
},
  "geometry": {"coordinates":[101.53333000000001,18.38333],"type":"Point"}
}