{
  "type": "Feature",
  "properties": {
    "gn:admin1_code":"2.0",
    "gn:asciiname":"Ban Kouttaboun",
    "gn:country_code":"LA",
    "gn:dem":101,
    "gn:feature_class":"P",
    "gn:feature_code":"PPL",
    "gn:name":"Ban Kouttaboun",
    "gn:population":0,
    "gn:timezone":"Asia/Vientiane",
    "iso:country":"LA",
    "name:und_x_variant":[
        "Ban Kouttaboune",
        "Ban Kouttaboun"
    ],
    "wof:name":"Ban Kouttaboun",
    "wof:placetype":"locality"
},
  "geometry": {"coordinates":[105.79075,14.62285],"type":"Point"}
}