{
  "type": "Feature",
  "properties": {
    "gn:admin1_code":"23.0",
    "gn:asciiname":"Ban Phakhao",
    "gn:country_code":"LA",
    "gn:dem":1153,
    "gn:feature_class":"P",
    "gn:feature_code":"PPL",
    "gn:name":"Ban Phakhao",
    "gn:population":0,
    "gn:timezone":"Asia/Vientiane",
    "iso:country":"LA",
    "name:und_x_variant":[
        "Phakhao"
    ],
    "wof:name":"Ban Phakhao",
    "wof:placetype":"locality"
},
  "geometry": {"coordinates":[104.66415000000001,18.55241],"type":"Point"}
}