{
  "type": "Feature",
  "properties": {
    "gn:admin1_code":"19.0",
    "gn:asciiname":"Ban Nahong",
    "gn:country_code":"LA",
    "gn:dem":207,
    "gn:feature_class":"P",
    "gn:feature_code":"PPL",
    "gn:name":"Ban Nahong",
    "gn:population":0,
    "gn:timezone":"Asia/Vientiane",
    "iso:country":"LA",
    "name:lao_x_preferred":[
        "Ban Nahong"
    ],
    "name:und_x_variant":[
        "Ban Na Hong",
        "Ban Hahong"
    ],
    "wof:name":"Ban Nahong",
    "wof:placetype":"locality"
},
  "geometry": {"coordinates":[106.18623999999998,16.0249],"type":"Point"}
}