{
  "type": "Feature",
  "properties": {
    "gn:admin1_code":"20.0",
    "gn:asciiname":"Ban Mahak-Nua",
    "gn:country_code":"LA",
    "gn:dem":215,
    "gn:feature_class":"P",
    "gn:feature_code":"PPL",
    "gn:name":"Ban Mahak-Nua",
    "gn:population":0,
    "gn:timezone":"Asia/Vientiane",
    "iso:country":"LA",
    "name:lao_x_preferred":[
        "Ban Mahak-Nua"
    ],
    "wof:name":"Ban Mahak-Nua",
    "wof:placetype":"locality"
},
  "geometry": {"coordinates":[106.64093,16.58967],"type":"Point"}
}