{
  "type": "Feature",
  "properties": {
    "gn:admin1_code":"7.0",
    "gn:asciiname":"Ban Homxang",
    "gn:country_code":"LA",
    "gn:dem":505,
    "gn:feature_class":"P",
    "gn:feature_code":"PPL",
    "gn:name":"Ban H\u00f4mxang",
    "gn:population":0,
    "gn:timezone":"Asia/Vientiane",
    "iso:country":"LA",
    "name:lao_x_preferred":[
        "Ban H\u00f4mxang"
    ],
    "wof:name":"Ban Homxang",
    "wof:placetype":"locality"
},
  "geometry": {"coordinates":[101.54246999999999,20.21386],"type":"Point"}
}