{
  "type": "Feature",
  "properties": {
    "gn:admin1_code":"23.0",
    "gn:asciiname":"Ban Namti",
    "gn:country_code":"LA",
    "gn:dem":321,
    "gn:feature_class":"P",
    "gn:feature_code":"PPL",
    "gn:name":"Ban Namti",
    "gn:population":0,
    "gn:timezone":"Asia/Vientiane",
    "iso:country":"LA",
    "name:lao_x_preferred":[
        "Ban Namti"
    ],
    "wof:name":"Ban Namti",
    "wof:placetype":"locality"
},
  "geometry": {"coordinates":[104.29172,18.733],"type":"Point"}
}