{
  "type": "Feature",
  "properties": {
    "gn:admin1_code":"14.0",
    "gn:asciiname":"Ban Tan",
    "gn:country_code":"LA",
    "gn:dem":1257,
    "gn:feature_class":"P",
    "gn:feature_code":"PPL",
    "gn:name":"Ban Tan",
    "gn:population":0,
    "gn:timezone":"Asia/Vientiane",
    "iso:country":"LA",
    "name:und_x_variant":[
        "Ban Phan",
        "Muong Phan",
        "Muang Tan",
        "Ban Tan"
    ],
    "wof:name":"Ban Tan",
    "wof:placetype":"locality"
},
  "geometry": {"coordinates":[103.49681,19.23944],"type":"Point"}
}