{
  "type": "Feature",
  "properties": {
    "gn:admin1_code":"14.0",
    "gn:asciiname":"Ban Boua",
    "gn:country_code":"LA",
    "gn:dem":545,
    "gn:feature_class":"P",
    "gn:feature_code":"PPL",
    "gn:name":"Ban Boua",
    "gn:population":0,
    "gn:timezone":"Asia/Vientiane",
    "iso:country":"LA",
    "name:und_x_variant":[
        "Ban Bua",
        "Ban Boua"
    ],
    "wof:name":"Ban Boua",
    "wof:placetype":"locality"
},
  "geometry": {"coordinates":[103.63552,19.61557],"type":"Point"}
}