{
  "type": "Feature",
  "properties": {
    "gn:admin1_code":"23.0",
    "gn:asciiname":"Ban Nam Utlot",
    "gn:country_code":"LA",
    "gn:dem":1034,
    "gn:feature_class":"P",
    "gn:feature_code":"PPL",
    "gn:name":"Ban Nam Utlot",
    "gn:population":0,
    "gn:timezone":"Asia/Vientiane",
    "iso:country":"LA",
    "name:lao_x_preferred":[
        "Ban Nam Utlot"
    ],
    "wof:name":"Ban Nam Utlot",
    "wof:placetype":"locality"
},
  "geometry": {"coordinates":[104.55493,18.56938],"type":"Point"}
}