{
  "type": "Feature",
  "properties": {
    "gn:admin1_code":"13.0",
    "gn:asciiname":"Ban Nathang",
    "gn:country_code":"LA",
    "gn:dem":874,
    "gn:feature_class":"P",
    "gn:feature_code":"PPL",
    "gn:name":"Ban Nathang",
    "gn:population":0,
    "gn:timezone":"Asia/Vientiane",
    "iso:country":"LA",
    "name:lao_x_preferred":[
        "Ban Nathang"
    ],
    "wof:name":"Ban Nathang",
    "wof:placetype":"locality"
},
  "geometry": {"coordinates":[101.71268999999999,19.07503],"type":"Point"}
}