{
  "type": "Feature",
  "properties": {
    "gn:admin1_code":"18.0",
    "gn:asciiname":"Ban Phoukho",
    "gn:country_code":"LA",
    "gn:dem":1101,
    "gn:feature_class":"P",
    "gn:feature_code":"PPL",
    "gn:name":"Ban Phoukh\u00f4",
    "gn:population":0,
    "gn:timezone":"Asia/Vientiane",
    "iso:country":"LA",
    "name:und_x_variant":[
        "P\u2019u C\u00f4",
        "Ban Phoukh\u00f4"
    ],
    "wof:name":"Ban Phoukho",
    "wof:placetype":"locality"
},
  "geometry": {"coordinates":[102.28594,21.58765],"type":"Point"}
}