{
  "type": "Feature",
  "properties": {
    "gn:admin1_code":"13.0",
    "gn:asciiname":"Ban Na Nep",
    "gn:country_code":"LA",
    "gn:dem":268,
    "gn:feature_class":"P",
    "gn:feature_code":"PPL",
    "gn:name":"Ban Na Nep",
    "gn:population":0,
    "gn:timezone":"Asia/Vientiane",
    "iso:country":"LA",
    "wof:name":"Ban Na Nep",
    "wof:placetype":"locality"
},
  "geometry": {"coordinates":[101.36667,18.08333],"type":"Point"}
}