{
  "type": "Feature",
  "properties": {
    "gn:admin1_code":"14.0",
    "gn:asciiname":"Ban Bi",
    "gn:country_code":"LA",
    "gn:dem":1124,
    "gn:feature_class":"P",
    "gn:feature_code":"PPL",
    "gn:name":"Ban Bi",
    "gn:population":0,
    "gn:timezone":"Asia/Vientiane",
    "iso:country":"LA",
    "name:lao_x_preferred":[
        "Ban Bi"
    ],
    "wof:name":"Ban Bi",
    "wof:placetype":"locality"
},
  "geometry": {"coordinates":[103.21948999999999,19.50187],"type":"Point"}
}