{
  "type": "Feature",
  "properties": {
    "gn:admin1_code":"2.0",
    "gn:asciiname":"Ban Khamngoua",
    "gn:country_code":"LA",
    "gn:dem":156,
    "gn:feature_class":"P",
    "gn:feature_code":"PPL",
    "gn:name":"Ban Khamngoua",
    "gn:population":0,
    "gn:timezone":"Asia/Vientiane",
    "iso:country":"LA",
    "name:lao_x_preferred":[
        "Ban Khamngoua"
    ],
    "wof:name":"Ban Khamngoua",
    "wof:placetype":"locality"
},
  "geometry": {"coordinates":[105.78225,15.33914],"type":"Point"}
}