{
  "type": "Feature",
  "properties": {
    "gn:admin1_code":"18.0",
    "gn:asciiname":"Ban Boke",
    "gn:country_code":"LA",
    "gn:dem":953,
    "gn:feature_class":"P",
    "gn:feature_code":"PPL",
    "gn:name":"Ban Bok\u00e9",
    "gn:population":0,
    "gn:timezone":"Asia/Vientiane",
    "iso:country":"LA",
    "name:und_x_variant":[
        "Bo K\u00e9",
        "Ban Bok\u00e9"
    ],
    "wof:name":"Ban Boke",
    "wof:placetype":"locality"
},
  "geometry": {"coordinates":[101.80406000000001,21.92235],"type":"Point"}
}