{
  "type": "Feature",
  "properties": {
    "gn:admin1_code":"2.0",
    "gn:asciiname":"Ban Sithouan",
    "gn:country_code":"LA",
    "gn:dem":112,
    "gn:feature_class":"P",
    "gn:feature_code":"PPL",
    "gn:name":"Ban Sithouan",
    "gn:population":0,
    "gn:timezone":"Asia/Vientiane",
    "iso:country":"LA",
    "name:und_x_variant":[
        "Ban Si Thouane",
        "Ban Sithouan"
    ],
    "wof:name":"Ban Sithouan",
    "wof:placetype":"locality"
},
  "geometry": {"coordinates":[105.70896999999999,15.30646],"type":"Point"}
}