{
  "type": "Feature",
  "properties": {
    "gn:admin1_code":"19.0",
    "gn:asciiname":"Ban Tang-Un-Kang",
    "gn:country_code":"LA",
    "gn:dem":662,
    "gn:feature_class":"P",
    "gn:feature_code":"PPL",
    "gn:name":"Ban Tang-Un-Kang",
    "gn:population":0,
    "gn:timezone":"Asia/Vientiane",
    "iso:country":"LA",
    "name:lao_x_preferred":[
        "Ban Tang-Un-Kang"
    ],
    "wof:name":"Ban Tang-Un-Kang",
    "wof:placetype":"locality"
},
  "geometry": {"coordinates":[106.56180000000001,15.98871],"type":"Point"}
}