{
  "type": "Feature",
  "properties": {
    "gn:admin1_code":"26.0",
    "gn:asciiname":"Ban Ding",
    "gn:country_code":"LA",
    "gn:dem":1179,
    "gn:feature_class":"P",
    "gn:feature_code":"PPL",
    "gn:name":"Ban Ding",
    "gn:population":0,
    "gn:timezone":"Asia/Vientiane",
    "iso:country":"LA",
    "name:und_x_variant":[
        "Ding",
        "Ban Dakdin",
        "Ban Ding"
    ],
    "wof:name":"Ban Ding",
    "wof:placetype":"locality"
},
  "geometry": {"coordinates":[107.11283,15.33107],"type":"Point"}
}