{
  "type": "Feature",
  "properties": {
    "gn:admin1_code":"3.0",
    "gn:asciiname":"Ban Nalouy",
    "gn:country_code":"LA",
    "gn:dem":769,
    "gn:feature_class":"P",
    "gn:feature_code":"PPL",
    "gn:name":"Ban Nalouy",
    "gn:population":0,
    "gn:timezone":"Asia/Vientiane",
    "iso:country":"LA",
    "name:lao_x_preferred":[
        "Ban Nalouy"
    ],
    "wof:name":"Ban Nalouy",
    "wof:placetype":"locality"
},
  "geometry": {"coordinates":[104.22286,20.22292],"type":"Point"}
}