{
  "type": "Feature",
  "properties": {
    "gn:admin1_code":"14.0",
    "gn:asciiname":"Sala Ban Sout",
    "gn:cc2":"LA",
    "gn:country_code":"LA",
    "gn:dem":1064,
    "gn:feature_class":"P",
    "gn:feature_code":"PPL",
    "gn:name":"Sala Ban Sout",
    "gn:population":0,
    "gn:timezone":"Asia/Vientiane",
    "iso:country":"LA",
    "name:und_x_variant":[
        "Ban Suot",
        "Ban Sout",
        "Sala Ban Sout"
    ],
    "wof:name":"Sala Ban Sout",
    "wof:placetype":"locality"
},
  "geometry": {"coordinates":[103.13333,19.48333],"type":"Point"}
}