{
  "type": "Feature",
  "properties": {
    "gn:admin1_code":"17.0",
    "gn:asciiname":"Ban Hatngam",
    "gn:country_code":"LA",
    "gn:dem":395,
    "gn:feature_class":"P",
    "gn:feature_code":"PPL",
    "gn:name":"Ban Hatngam",
    "gn:population":0,
    "gn:timezone":"Asia/Vientiane",
    "iso:country":"LA",
    "name:lao_x_preferred":[
        "Ban Hatngam"
    ],
    "wof:name":"Ban Hatngam",
    "wof:placetype":"locality"
},
  "geometry": {"coordinates":[102.68819000000001,20.1585],"type":"Point"}
}