{
  "type": "Feature",
  "properties": {
    "gn:admin1_code":"14.0",
    "gn:asciiname":"Ban Phonsi",
    "gn:country_code":"LA",
    "gn:dem":1131,
    "gn:feature_class":"P",
    "gn:feature_code":"PPL",
    "gn:name":"Ban Ph\u00f4nsi",
    "gn:population":0,
    "gn:timezone":"Asia/Vientiane",
    "iso:country":"LA",
    "name:lao_x_preferred":[
        "Ban Ph\u00f4nsi"
    ],
    "wof:name":"Ban Phonsi",
    "wof:placetype":"locality"
},
  "geometry": {"coordinates":[103.14754000000001,19.69282],"type":"Point"}
}