{
  "type": "Feature",
  "properties": {
    "gn:admin1_code":"20.0",
    "gn:asciiname":"Ban Nasatung",
    "gn:country_code":"LA",
    "gn:dem":316,
    "gn:feature_class":"P",
    "gn:feature_code":"PPL",
    "gn:name":"Ban Nasatung",
    "gn:population":0,
    "gn:timezone":"Asia/Vientiane",
    "iso:country":"LA",
    "name:lao_x_preferred":[
        "Ban Nasatung"
    ],
    "wof:name":"Ban Nasatung",
    "wof:placetype":"locality"
},
  "geometry": {"coordinates":[106.10092,16.02489],"type":"Point"}
}