{
  "type": "Feature",
  "properties": {
    "gn:admin1_code":"7.0",
    "gn:asciiname":"Ban Nabo-Gnai",
    "gn:country_code":"LA",
    "gn:dem":630,
    "gn:feature_class":"P",
    "gn:feature_code":"PPL",
    "gn:name":"Ban Nabo-Gnai",
    "gn:population":0,
    "gn:timezone":"Asia/Vientiane",
    "iso:country":"LA",
    "name:lao_x_preferred":[
        "Ban Nabo-Gnai"
    ],
    "name:und_x_variant":[
        "Ban Bo"
    ],
    "wof:name":"Ban Nabo-Gnai",
    "wof:placetype":"locality"
},
  "geometry": {"coordinates":[102.04644999999999,20.71916],"type":"Point"}
}