{
  "type": "Feature",
  "properties": {
    "gn:admin1_code":"23.0",
    "gn:asciiname":"Ban Souansavan",
    "gn:country_code":"LA",
    "gn:dem":160,
    "gn:feature_class":"P",
    "gn:feature_code":"PPL",
    "gn:name":"Ban Souansavan",
    "gn:population":0,
    "gn:timezone":"Asia/Vientiane",
    "iso:country":"LA",
    "name:lao_x_preferred":[
        "Ban Souansavan"
    ],
    "wof:name":"Ban Souansavan",
    "wof:placetype":"locality"
},
  "geometry": {"coordinates":[103.67509,18.41318],"type":"Point"}
}