{
  "type": "Feature",
  "properties": {
    "gn:admin1_code":"1.0",
    "gn:asciiname":"Ban Khanmakong",
    "gn:country_code":"LA",
    "gn:dem":105,
    "gn:feature_class":"P",
    "gn:feature_code":"PPL",
    "gn:name":"Ban Khanmakong",
    "gn:population":0,
    "gn:timezone":"Asia/Vientiane",
    "iso:country":"LA",
    "name:lao_x_preferred":[
        "Ban Khanmakong"
    ],
    "wof:name":"Ban Khanmakong",
    "wof:placetype":"locality"
},
  "geometry": {"coordinates":[106.92833,14.80892],"type":"Point"}
}