{
  "type": "Feature",
  "properties": {
    "gn:admin1_code":"15.0",
    "gn:asciiname":"Ban Tan Theung",
    "gn:country_code":"LA",
    "gn:dem":149,
    "gn:feature_class":"P",
    "gn:feature_code":"PPL",
    "gn:name":"Ban Tan Theung",
    "gn:population":0,
    "gn:timezone":"Asia/Vientiane",
    "iso:country":"LA",
    "name:und_x_variant":[
        "Ban Ta",
        "Ban Tai",
        "Ban Tan Theung"
    ],
    "wof:name":"Ban Tan Theung",
    "wof:placetype":"locality"
},
  "geometry": {"coordinates":[104.79411,16.97782],"type":"Point"}
}