{
  "type": "Feature",
  "properties": {
    "gn:admin1_code":"2.0",
    "gn:asciiname":"Ban Kapheu",
    "gn:country_code":"LA",
    "gn:dem":480,
    "gn:feature_class":"P",
    "gn:feature_code":"PPL",
    "gn:name":"Ban Kapheu",
    "gn:population":0,
    "gn:timezone":"Asia/Vientiane",
    "iso:country":"LA",
    "name:lao_x_preferred":[
        "Ban Kapheu"
    ],
    "wof:name":"Ban Kapheu",
    "wof:placetype":"locality"
},
  "geometry": {"coordinates":[106.08438,15.41524],"type":"Point"}
}