{
  "type": "Feature",
  "properties": {
    "gn:admin1_code":"15.0",
    "gn:asciiname":"Ban Chalou",
    "gn:country_code":"LA",
    "gn:dem":247,
    "gn:feature_class":"P",
    "gn:feature_code":"PPL",
    "gn:name":"Ban Chalou",
    "gn:population":0,
    "gn:timezone":"Asia/Vientiane",
    "iso:country":"LA",
    "name:und_x_variant":[
        "Ban Salou",
        "Ban Chalou"
    ],
    "wof:name":"Ban Chalou",
    "wof:placetype":"locality"
},
  "geometry": {"coordinates":[105.95119,17.29106],"type":"Point"}
}