{
  "type": "Feature",
  "properties": {
    "gn:admin1_code":"15.0",
    "gn:asciiname":"Ban Thongmuang",
    "gn:country_code":"LA",
    "gn:dem":553,
    "gn:feature_class":"P",
    "gn:feature_code":"PPL",
    "gn:name":"Ban Th\u00f4ngmuang",
    "gn:population":0,
    "gn:timezone":"Asia/Vientiane",
    "iso:country":"LA",
    "name:lao_x_preferred":[
        "Ban Th\u00f4ngmuang"
    ],
    "wof:name":"Ban Thongmuang",
    "wof:placetype":"locality"
},
  "geometry": {"coordinates":[105.17434,17.97738],"type":"Point"}
}