{
  "type": "Feature",
  "properties": {
    "gn:admin1_code":"28.0",
    "gn:asciiname":"Ban Phoumo",
    "gn:country_code":"LA",
    "gn:dem":1115,
    "gn:feature_class":"P",
    "gn:feature_code":"PPL",
    "gn:name":"Ban Phoumo",
    "gn:population":0,
    "gn:timezone":"Asia/Vientiane",
    "iso:country":"LA",
    "name:und_x_variant":[
        "Ban Pou Mo",
        "Ban Phoumo"
    ],
    "wof:name":"Ban Phoumo",
    "wof:placetype":"locality"
},
  "geometry": {"coordinates":[103.15000000000001,18.91667],"type":"Point"}
}