{
  "type": "Feature",
  "properties": {
    "gn:admin1_code":"18.0",
    "gn:asciiname":"Ban Paicho",
    "gn:country_code":"LA",
    "gn:dem":1209,
    "gn:feature_class":"P",
    "gn:feature_code":"PPL",
    "gn:name":"Ban Paicho",
    "gn:population":0,
    "gn:timezone":"Asia/Vientiane",
    "iso:country":"LA",
    "name:und_x_variant":[
        "Pay Ch\u00f4",
        "Ban Paicho"
    ],
    "wof:name":"Ban Paicho",
    "wof:placetype":"locality"
},
  "geometry": {"coordinates":[102.1801,21.90519],"type":"Point"}
}