{
  "type": "Feature",
  "properties": {
    "gn:admin1_code":"14.0",
    "gn:asciiname":"Ban Theun",
    "gn:cc2":"LA",
    "gn:country_code":"LA",
    "gn:dem":1151,
    "gn:feature_class":"P",
    "gn:feature_code":"PPL",
    "gn:name":"Ban Theun",
    "gn:population":0,
    "gn:timezone":"Asia/Vientiane",
    "iso:country":"LA",
    "name:und_x_variant":[
        "Ban Toem",
        "Ban Theun"
    ],
    "wof:name":"Ban Theun",
    "wof:placetype":"locality"
},
  "geometry": {"coordinates":[102.84999999999999,19.48333],"type":"Point"}
}