{
  "type": "Feature",
  "properties": {
    "gn:admin1_code":"17.0",
    "gn:asciiname":"Ban Houayloung-Nua",
    "gn:country_code":"LA",
    "gn:dem":769,
    "gn:feature_class":"P",
    "gn:feature_code":"PPL",
    "gn:name":"Ban Houayloung-Nua",
    "gn:population":0,
    "gn:timezone":"Asia/Vientiane",
    "iso:country":"LA",
    "name:lao_x_preferred":[
        "Ban Houayloung-Nua"
    ],
    "wof:name":"Ban Houayloung-Nua",
    "wof:placetype":"locality"
},
  "geometry": {"coordinates":[102.60021,19.9456],"type":"Point"}
}