{
  "type": "Feature",
  "properties": {
    "gn:admin1_code":"20.0",
    "gn:asciiname":"Ban Xokvang-Nua",
    "gn:country_code":"LA",
    "gn:dem":167,
    "gn:feature_class":"P",
    "gn:feature_code":"PPL",
    "gn:name":"Ban Xokvang-Nua",
    "gn:population":0,
    "gn:timezone":"Asia/Vientiane",
    "iso:country":"LA",
    "name:lao_x_preferred":[
        "Ban Xokvang-Nua"
    ],
    "name:und_x_variant":[
        "Ban Sokvang",
        "Ban Xokvang"
    ],
    "wof:name":"Ban Xokvang-Nua",
    "wof:placetype":"locality"
},
  "geometry": {"coordinates":[104.93873000000001,16.52708],"type":"Point"}
}