{
  "type": "Feature",
  "properties": {
    "gn:admin1_code":"2.0",
    "gn:asciiname":"Ban Nonkoung",
    "gn:country_code":"LA",
    "gn:dem":134,
    "gn:feature_class":"P",
    "gn:feature_code":"PPL",
    "gn:name":"Ban N\u00f4nkoung",
    "gn:population":0,
    "gn:timezone":"Asia/Vientiane",
    "iso:country":"LA",
    "name:lao_x_preferred":[
        "Ban N\u00f4nkoung"
    ],
    "wof:name":"Ban Nonkoung",
    "wof:placetype":"locality"
},
  "geometry": {"coordinates":[105.72306,14.97747],"type":"Point"}
}