{
  "type": "Feature",
  "properties": {
    "gn:admin1_code":"16.0",
    "gn:asciiname":"Ban Vat",
    "gn:country_code":"LA",
    "gn:dem":469,
    "gn:feature_class":"P",
    "gn:feature_code":"PPL",
    "gn:name":"Ban Vat",
    "gn:population":0,
    "gn:timezone":"Asia/Vientiane",
    "iso:country":"LA",
    "name:und_x_variant":[
        "Ban Vat (2)",
        "Ban Vat"
    ],
    "wof:name":"Ban Vat",
    "wof:placetype":"locality"
},
  "geometry": {"coordinates":[101.41005,20.45661],"type":"Point"}
}