{
  "type": "Feature",
  "properties": {
    "gn:admin1_code":"13.0",
    "gn:asciiname":"Ban Nahouaxang",
    "gn:country_code":"LA",
    "gn:dem":355,
    "gn:feature_class":"P",
    "gn:feature_code":"PPL",
    "gn:name":"Ban Nahouaxang",
    "gn:population":0,
    "gn:timezone":"Asia/Vientiane",
    "iso:country":"LA",
    "name:lao_x_preferred":[
        "Ban Nahouaxang"
    ],
    "wof:name":"Ban Nahouaxang",
    "wof:placetype":"locality"
},
  "geometry": {"coordinates":[101.15895999999999,17.75992],"type":"Point"}
}