{
  "type": "Feature",
  "properties": {
    "gn:admin1_code":"17.0",
    "gn:asciiname":"Ban Nong",
    "gn:country_code":"LA",
    "gn:dem":383,
    "gn:feature_class":"P",
    "gn:feature_code":"PPL",
    "gn:name":"Ban Nong",
    "gn:population":0,
    "gn:timezone":"Asia/Vientiane",
    "iso:country":"LA",
    "name:lao_x_preferred":[
        "Ban Nong"
    ],
    "wof:name":"Ban Nong",
    "wof:placetype":"locality"
},
  "geometry": {"coordinates":[102.83113,20.14198],"type":"Point"}
}