{
  "type": "Feature",
  "properties": {
    "gn:admin1_code":"19.0",
    "gn:asciiname":"Ban Avao",
    "gn:country_code":"LA",
    "gn:dem":627,
    "gn:feature_class":"P",
    "gn:feature_code":"PPL",
    "gn:name":"Ban Avao",
    "gn:population":0,
    "gn:timezone":"Asia/Vientiane",
    "iso:country":"LA",
    "name:lao_x_preferred":[
        "Ban Avao"
    ],
    "name:und_x_variant":[
        "Avaho",
        "Ban Avah\u00f4"
    ],
    "wof:name":"Ban Avao",
    "wof:placetype":"locality"
},
  "geometry": {"coordinates":[106.90416999999999,16.34971],"type":"Point"}
}