{
  "type": "Feature",
  "properties": {
    "gn:admin1_code":"24.0",
    "gn:asciiname":"Ban Naxon",
    "gn:country_code":"LA",
    "gn:dem":180,
    "gn:feature_class":"P",
    "gn:feature_code":"PPL",
    "gn:name":"Ban Naxon",
    "gn:population":0,
    "gn:timezone":"Asia/Vientiane",
    "iso:country":"LA",
    "name:und_x_variant":[
        "Ban Na Son",
        "Ban Naxon"
    ],
    "wof:name":"Ban Naxon",
    "wof:placetype":"locality"
},
  "geometry": {"coordinates":[102.50749999999999,18.10622],"type":"Point"}
}