{
  "type": "Feature",
  "properties": {
    "gn:admin1_code":"3.0",
    "gn:asciiname":"Ban Hong-Oy",
    "gn:country_code":"LA",
    "gn:dem":1404,
    "gn:feature_class":"P",
    "gn:feature_code":"PPL",
    "gn:name":"Ban H\u00f4ng-Oy",
    "gn:population":0,
    "gn:timezone":"Asia/Vientiane",
    "iso:country":"LA",
    "name:lao_x_preferred":[
        "Ban H\u00f4ng-Oy"
    ],
    "wof:name":"Ban Hong-Oy",
    "wof:placetype":"locality"
},
  "geometry": {"coordinates":[104.06455,19.99217],"type":"Point"}
}