{
  "type": "Feature",
  "properties": {
    "gn:admin1_code":"14.0",
    "gn:asciiname":"Ban Nongkang",
    "gn:country_code":"LA",
    "gn:dem":1133,
    "gn:feature_class":"P",
    "gn:feature_code":"PPL",
    "gn:name":"Ban Nongkang",
    "gn:population":0,
    "gn:timezone":"Asia/Vientiane",
    "iso:country":"LA",
    "name:lao_x_preferred":[
        "Ban Nongkang"
    ],
    "name:und_x_variant":[
        "Ban Khang"
    ],
    "wof:name":"Ban Nongkang",
    "wof:placetype":"locality"
},
  "geometry": {"coordinates":[102.91862999999999,19.5613],"type":"Point"}
}