{
  "type": "Feature",
  "properties": {
    "gn:admin1_code":"14.0",
    "gn:asciiname":"Laota",
    "gn:cc2":"LA",
    "gn:country_code":"LA",
    "gn:dem":1308,
    "gn:feature_class":"P",
    "gn:feature_code":"PPL",
    "gn:name":"Laota",
    "gn:population":0,
    "gn:timezone":"Asia/Vientiane",
    "iso:country":"LA",
    "name:und_x_variant":[
        "Lao Tao",
        "Laota"
    ],
    "wof:name":"Laota",
    "wof:placetype":"locality"
},
  "geometry": {"coordinates":[103.28333000000001,19.28333],"type":"Point"}
}