{
  "type": "Feature",
  "properties": {
    "gn:admin1_code":"3.0",
    "gn:asciiname":"Ban Houaymoun",
    "gn:country_code":"LA",
    "gn:dem":1047,
    "gn:feature_class":"P",
    "gn:feature_code":"PPL",
    "gn:name":"Ban Houaymoun",
    "gn:population":0,
    "gn:timezone":"Asia/Vientiane",
    "iso:country":"LA",
    "name:lao_x_preferred":[
        "Ban Houaymoun"
    ],
    "wof:name":"Ban Houaymoun",
    "wof:placetype":"locality"
},
  "geometry": {"coordinates":[103.81304,20.10243],"type":"Point"}
}