{
  "type": "Feature",
  "properties": {
    "gn:admin1_code":"19.0",
    "gn:asciiname":"Ban Phialat-Mai",
    "gn:country_code":"LA",
    "gn:dem":519,
    "gn:feature_class":"P",
    "gn:feature_code":"PPL",
    "gn:name":"Ban Phialat-Mai",
    "gn:population":0,
    "gn:timezone":"Asia/Vientiane",
    "iso:country":"LA",
    "name:lao_x_preferred":[
        "Ban Phialat-Mai"
    ],
    "name:und_x_variant":[
        "Ban Phialat May"
    ],
    "wof:name":"Ban Phialat-Mai",
    "wof:placetype":"locality"
},
  "geometry": {"coordinates":[106.10406999999999,15.4407],"type":"Point"}
}