{
  "type": "Feature",
  "properties": {
    "gn:admin1_code":"15.0",
    "gn:asciiname":"Ban Xoklek",
    "gn:country_code":"LA",
    "gn:dem":571,
    "gn:feature_class":"P",
    "gn:feature_code":"PPL",
    "gn:name":"Ban Xokl\u00e8k",
    "gn:population":0,
    "gn:timezone":"Asia/Vientiane",
    "iso:country":"LA",
    "name:lao_x_preferred":[
        "Ban Xokl\u00e8k"
    ],
    "name:und_x_variant":[
        "Ban Sok L\u00e8k"
    ],
    "wof:name":"Ban Xoklek",
    "wof:placetype":"locality"
},
  "geometry": {"coordinates":[105.38822,17.92998],"type":"Point"}
}