{
  "type": "Feature",
  "properties": {
    "gn:admin1_code":"20.0",
    "gn:asciiname":"Ban Khagnong",
    "gn:country_code":"LA",
    "gn:dem":163,
    "gn:feature_class":"P",
    "gn:feature_code":"PPL",
    "gn:name":"Ban Khagnong",
    "gn:population":0,
    "gn:timezone":"Asia/Vientiane",
    "iso:country":"LA",
    "name:und_x_variant":[
        "Ban Kha Ngnong",
        "Ban Kha Ngnog",
        "Ban Khagnong"
    ],
    "wof:name":"Ban Khagnong",
    "wof:placetype":"locality"
},
  "geometry": {"coordinates":[105.05686,16.26925],"type":"Point"}
}