{
  "type": "Feature",
  "properties": {
    "gn:admin1_code":"17.0",
    "gn:asciiname":"Ban Houaythong",
    "gn:country_code":"LA",
    "gn:dem":597,
    "gn:feature_class":"P",
    "gn:feature_code":"PPL",
    "gn:name":"Ban Houaythong",
    "gn:population":0,
    "gn:timezone":"Asia/Vientiane",
    "iso:country":"LA",
    "name:lao_x_preferred":[
        "Ban Houaythong"
    ],
    "wof:name":"Ban Houaythong",
    "wof:placetype":"locality"
},
  "geometry": {"coordinates":[103.00209,20.31339],"type":"Point"}
}