{
  "type": "Feature",
  "properties": {
    "gn:admin1_code":"19.0",
    "gn:asciiname":"Ban Channonghin",
    "gn:country_code":"LA",
    "gn:dem":189,
    "gn:feature_class":"P",
    "gn:feature_code":"PPL",
    "gn:name":"Ban Channonghin",
    "gn:population":0,
    "gn:timezone":"Asia/Vientiane",
    "iso:country":"LA",
    "name:lao_x_preferred":[
        "Ban Channonghin"
    ],
    "name:und_x_variant":[
        "Ban Chane Vong Chantha",
        "Ban Channonghin Gnai"
    ],
    "wof:name":"Ban Channonghin",
    "wof:placetype":"locality"
},
  "geometry": {"coordinates":[106.19925000000001,15.69438],"type":"Point"}
}