{
  "type": "Feature",
  "properties": {
    "gn:admin1_code":"19.0",
    "gn:asciiname":"Ban Khanao",
    "gn:country_code":"LA",
    "gn:dem":194,
    "gn:feature_class":"P",
    "gn:feature_code":"PPL",
    "gn:name":"Ban Khanao",
    "gn:population":0,
    "gn:timezone":"Asia/Vientiane",
    "iso:country":"LA",
    "name:lao_x_preferred":[
        "Ban Khanao"
    ],
    "wof:name":"Ban Khanao",
    "wof:placetype":"locality"
},
  "geometry": {"coordinates":[106.00557999999999,15.63724],"type":"Point"}
}