{
  "type": "Feature",
  "properties": {
    "gn:admin1_code":"19.0",
    "gn:asciiname":"Ban Natabeng-Mai",
    "gn:country_code":"LA",
    "gn:dem":260,
    "gn:feature_class":"P",
    "gn:feature_code":"PPL",
    "gn:name":"Ban Natab\u00e8ng-Mai",
    "gn:population":0,
    "gn:timezone":"Asia/Vientiane",
    "iso:country":"LA",
    "name:lao_x_preferred":[
        "Ban Natab\u00e8ng-Mai"
    ],
    "name:und_x_variant":[
        "Ban Tabeng",
        "Ban Natab\u00e8ng"
    ],
    "wof:name":"Ban Natabeng-Mai",
    "wof:placetype":"locality"
},
  "geometry": {"coordinates":[106.04092,15.57166],"type":"Point"}
}