{
  "type": "Feature",
  "properties": {
    "gn:admin1_code":"14.0",
    "gn:asciiname":"Ban Gnotlian-Kao",
    "gn:country_code":"LA",
    "gn:dem":1278,
    "gn:feature_class":"P",
    "gn:feature_code":"PPL",
    "gn:name":"Ban Gnotlian-Kao",
    "gn:population":0,
    "gn:timezone":"Asia/Vientiane",
    "iso:country":"LA",
    "name:lao_x_preferred":[
        "Ban Gnotlian-Kao"
    ],
    "wof:name":"Ban Gnotlian-Kao",
    "wof:placetype":"locality"
},
  "geometry": {"coordinates":[103.80602,19.56924],"type":"Point"}
}