{
  "type": "Feature",
  "properties": {
    "gn:admin1_code":"20.0",
    "gn:asciiname":"Ban Dongtiou",
    "gn:country_code":"LA",
    "gn:dem":159,
    "gn:feature_class":"P",
    "gn:feature_code":"PPL",
    "gn:name":"Ban D\u00f4ngtiou",
    "gn:population":0,
    "gn:timezone":"Asia/Vientiane",
    "iso:country":"LA",
    "name:lao_x_preferred":[
        "Ban D\u00f4ngtiou"
    ],
    "name:und_x_variant":[
        "Ban Done Tiou",
        "Ban Dontiou"
    ],
    "wof:name":"Ban Dongtiou",
    "wof:placetype":"locality"
},
  "geometry": {"coordinates":[105.54468,16.54517],"type":"Point"}
}