{
  "type": "Feature",
  "properties": {
    "gn:admin1_code":"15.0",
    "gn:asciiname":"Ban Phonpheng",
    "gn:country_code":"LA",
    "gn:dem":156,
    "gn:feature_class":"P",
    "gn:feature_code":"PPL",
    "gn:name":"Ban Ph\u00f4nph\u00e8ng",
    "gn:population":0,
    "gn:timezone":"Asia/Vientiane",
    "iso:country":"LA",
    "name:lao_x_preferred":[
        "Ban Ph\u00f4nph\u00e8ng"
    ],
    "wof:name":"Ban Phonpheng",
    "wof:placetype":"locality"
},
  "geometry": {"coordinates":[104.78843999999999,17.64512999999999],"type":"Point"}
}