{
  "type": "Feature",
  "properties": {
    "gn:admin1_code":"3.0",
    "gn:asciiname":"Ban Houayhai",
    "gn:country_code":"LA",
    "gn:dem":1297,
    "gn:feature_class":"P",
    "gn:feature_code":"PPL",
    "gn:name":"Ban Houayhai",
    "gn:population":0,
    "gn:timezone":"Asia/Vientiane",
    "iso:country":"LA",
    "name:und_x_variant":[
        "Ban Houay Hay",
        "Ban Houei Hay",
        "Ban Houayhai"
    ],
    "wof:name":"Ban Houayhai",
    "wof:placetype":"locality"
},
  "geometry": {"coordinates":[104.16755000000001,20.13256],"type":"Point"}
}