{
  "type": "Feature",
  "properties": {
    "gn:admin1_code":"3.0",
    "gn:asciiname":"Ban Khan",
    "gn:country_code":"LA",
    "gn:dem":993,
    "gn:feature_class":"P",
    "gn:feature_code":"PPL",
    "gn:name":"Ban Khan",
    "gn:population":0,
    "gn:timezone":"Asia/Vientiane",
    "iso:country":"LA",
    "name:lao_x_preferred":[
        "Ban Khan"
    ],
    "wof:name":"Ban Khan",
    "wof:placetype":"locality"
},
  "geometry": {"coordinates":[103.99921000000001,20.32225],"type":"Point"}
}