{
  "type": "Feature",
  "properties": {
    "gn:admin1_code":"7.0",
    "gn:asciiname":"Ban Konthoy-Tai",
    "gn:country_code":"LA",
    "gn:dem":466,
    "gn:feature_class":"P",
    "gn:feature_code":"PPL",
    "gn:name":"Ban Konthoy-Tai",
    "gn:population":0,
    "gn:timezone":"Asia/Vientiane",
    "iso:country":"LA",
    "name:lao_x_preferred":[
        "Ban Konthoy-Tai"
    ],
    "wof:name":"Ban Konthoy-Tai",
    "wof:placetype":"locality"
},
  "geometry": {"coordinates":[101.97076,20.18503],"type":"Point"}
}