{
  "type": "Feature",
  "properties": {
    "gn:admin1_code":"16.0",
    "gn:asciiname":"Ban Namkiang",
    "gn:country_code":"LA",
    "gn:dem":718,
    "gn:feature_class":"P",
    "gn:feature_code":"PPL",
    "gn:name":"Ban Namkiang",
    "gn:population":0,
    "gn:timezone":"Asia/Vientiane",
    "iso:country":"LA",
    "name:lao_x_preferred":[
        "Ban Namkiang"
    ],
    "wof:name":"Ban Namkiang",
    "wof:placetype":"locality"
},
  "geometry": {"coordinates":[101.09874000000001,20.61813],"type":"Point"}
}