{
  "type": "Feature",
  "properties": {
    "gn:admin1_code":"13.0",
    "gn:asciiname":"Ban Dimi",
    "gn:country_code":"LA",
    "gn:dem":481,
    "gn:feature_class":"P",
    "gn:feature_code":"PPL",
    "gn:name":"Ban Dimi",
    "gn:population":0,
    "gn:timezone":"Asia/Vientiane",
    "iso:country":"LA",
    "name:lao_x_preferred":[
        "Ban Dimi"
    ],
    "wof:name":"Ban Dimi",
    "wof:placetype":"locality"
},
  "geometry": {"coordinates":[101.10428,19.66249],"type":"Point"}
}