{
  "type": "Feature",
  "properties": {
    "gn:admin1_code":"20.0",
    "gn:asciiname":"Ban Khouapian",
    "gn:country_code":"LA",
    "gn:dem":140,
    "gn:feature_class":"P",
    "gn:feature_code":"PPL",
    "gn:name":"Ban Khouapian",
    "gn:population":0,
    "gn:timezone":"Asia/Vientiane",
    "iso:country":"LA",
    "name:lao_x_preferred":[
        "Ban Khouapian"
    ],
    "wof:name":"Ban Khouapian",
    "wof:placetype":"locality"
},
  "geometry": {"coordinates":[105.43306,16.03352000000001],"type":"Point"}
}