{
  "type": "Feature",
  "properties": {
    "gn:admin1_code":"27.0",
    "gn:asciiname":"Ban Keokoang",
    "gn:country_code":"LA",
    "gn:dem":312,
    "gn:feature_class":"P",
    "gn:feature_code":"PPL",
    "gn:name":"Ban K\u00e8okoang",
    "gn:population":0,
    "gn:timezone":"Asia/Vientiane",
    "iso:country":"LA",
    "name:und_x_variant":[
        "Ban Keo Kang",
        "Ban K\u00e8okoang"
    ],
    "wof:name":"Ban Keokoang",
    "wof:placetype":"locality"
},
  "geometry": {"coordinates":[102.4525,19.11239],"type":"Point"}
}