{
  "type": "Feature",
  "properties": {
    "gn:admin1_code":"20.0",
    "gn:asciiname":"Ban Laobao",
    "gn:country_code":"LA",
    "gn:dem":322,
    "gn:feature_class":"P",
    "gn:feature_code":"PPL",
    "gn:name":"Ban Laobao",
    "gn:population":0,
    "gn:timezone":"Asia/Vientiane",
    "iso:country":"LA",
    "name:und_x_variant":[
        "Ban La Bao",
        "Ban Laobao"
    ],
    "wof:name":"Ban Laobao",
    "wof:placetype":"locality"
},
  "geometry": {"coordinates":[106.31894,16.45677],"type":"Point"}
}