{
  "type": "Feature",
  "properties": {
    "gn:admin1_code":"27.0",
    "gn:asciiname":"Ban Nate",
    "gn:country_code":"LA",
    "gn:dem":223,
    "gn:feature_class":"P",
    "gn:feature_code":"PPL",
    "gn:name":"Ban Nat\u00e9",
    "gn:population":0,
    "gn:timezone":"Asia/Vientiane",
    "iso:country":"LA",
    "name:lao_x_preferred":[
        "Ban Nat\u00e9"
    ],
    "wof:name":"Ban Nate",
    "wof:placetype":"locality"
},
  "geometry": {"coordinates":[102.57553,18.47794],"type":"Point"}
}