{
  "type": "Feature",
  "properties": {
    "gn:admin1_code":"17.0",
    "gn:asciiname":"Ban Seng-Oun",
    "gn:country_code":"LA",
    "gn:dem":749,
    "gn:feature_class":"P",
    "gn:feature_code":"PPL",
    "gn:name":"Ban S\u00e8ng-Oun",
    "gn:population":0,
    "gn:timezone":"Asia/Vientiane",
    "iso:country":"LA",
    "name:lao_x_preferred":[
        "Ban S\u00e8ng-Oun"
    ],
    "wof:name":"Ban Seng-Oun",
    "wof:placetype":"locality"
},
  "geometry": {"coordinates":[103.01896000000001,20.63848],"type":"Point"}
}