{
  "type": "Feature",
  "properties": {
    "gn:admin1_code":"7.0",
    "gn:asciiname":"Ban Donkeo",
    "gn:country_code":"LA",
    "gn:dem":531,
    "gn:feature_class":"P",
    "gn:feature_code":"PPL",
    "gn:name":"Ban Donk\u00e8o",
    "gn:population":0,
    "gn:timezone":"Asia/Vientiane",
    "iso:country":"LA",
    "name:und_x_variant":[
        "Ban Donkon",
        "Ban Don Koun",
        "Ban Donk\u00e8o"
    ],
    "wof:name":"Ban Donkeo",
    "wof:placetype":"locality"
},
  "geometry": {"coordinates":[101.65653,20.32463],"type":"Point"}
}