{
  "type": "Feature",
  "properties": {
    "gn:admin1_code":"17.0",
    "gn:asciiname":"Ban Houaychang",
    "gn:country_code":"LA",
    "gn:dem":980,
    "gn:feature_class":"P",
    "gn:feature_code":"PPL",
    "gn:name":"Ban Houaychang",
    "gn:population":0,
    "gn:timezone":"Asia/Vientiane",
    "iso:country":"LA",
    "name:lao_x_preferred":[
        "Ban Houaychang"
    ],
    "wof:name":"Ban Houaychang",
    "wof:placetype":"locality"
},
  "geometry": {"coordinates":[102.67898,19.7934],"type":"Point"}
}