{
  "type": "Feature",
  "properties": {
    "gn:admin1_code":"7.0",
    "gn:asciiname":"Phiakhampong",
    "gn:country_code":"LA",
    "gn:dem":833,
    "gn:feature_class":"P",
    "gn:feature_code":"PPL",
    "gn:name":"Phiakhampong",
    "gn:population":0,
    "gn:timezone":"Asia/Vientiane",
    "iso:country":"LA",
    "name:und_x_variant":[
        "Phya Kham Pong",
        "Phiakhampong"
    ],
    "wof:name":"Phiakhampong",
    "wof:placetype":"locality"
},
  "geometry": {"coordinates":[102.15000000000001,20.95],"type":"Point"}
}