{
  "type": "Feature",
  "properties": {
    "gn:admin1_code":"17.0",
    "gn:asciiname":"Ban Houaykhai",
    "gn:country_code":"LA",
    "gn:dem":602,
    "gn:feature_class":"P",
    "gn:feature_code":"PPL",
    "gn:name":"Ban Houaykhai",
    "gn:population":0,
    "gn:timezone":"Asia/Vientiane",
    "iso:country":"LA",
    "name:lao_x_preferred":[
        "Ban Houaykhai"
    ],
    "wof:name":"Ban Houaykhai",
    "wof:placetype":"locality"
},
  "geometry": {"coordinates":[102.72528,20.29186],"type":"Point"}
}