{
  "type": "Feature",
  "properties": {
    "gn:admin1_code":"3.0",
    "gn:asciiname":"Ban O Lai",
    "gn:country_code":"LA",
    "gn:dem":701,
    "gn:feature_class":"P",
    "gn:feature_code":"PPL",
    "gn:name":"Ban O Lai",
    "gn:population":0,
    "gn:timezone":"Asia/Vientiane",
    "iso:country":"LA",
    "wof:name":"Ban O Lai",
    "wof:placetype":"locality"
},
  "geometry": {"coordinates":[104.41667,20.35],"type":"Point"}
}