{
  "type": "Feature",
  "properties": {
    "gn:admin1_code":"23.0",
    "gn:asciiname":"Ban Phokham",
    "gn:country_code":"LA",
    "gn:dem":324,
    "gn:feature_class":"P",
    "gn:feature_code":"PPL",
    "gn:name":"Ban Ph\u00f4kham",
    "gn:population":0,
    "gn:timezone":"Asia/Vientiane",
    "iso:country":"LA",
    "name:lao_x_preferred":[
        "Ban Ph\u00f4kham"
    ],
    "wof:name":"Ban Phokham",
    "wof:placetype":"locality"
},
  "geometry": {"coordinates":[104.28258,18.6941],"type":"Point"}
}