{
  "type": "Feature",
  "properties": {
    "gn:admin1_code":"17.0",
    "gn:asciiname":"Ban Nangiou",
    "gn:country_code":"LA",
    "gn:dem":641,
    "gn:feature_class":"P",
    "gn:feature_code":"PPL",
    "gn:name":"Ban Nangiou",
    "gn:population":0,
    "gn:timezone":"Asia/Vientiane",
    "iso:country":"LA",
    "name:lao_x_preferred":[
        "Ban Nangiou"
    ],
    "wof:name":"Ban Nangiou",
    "wof:placetype":"locality"
},
  "geometry": {"coordinates":[102.91553,19.94404],"type":"Point"}
}