{
  "type": "Feature",
  "properties": {
    "gn:admin1_code":"16.0",
    "gn:asciiname":"Ban Chakheum",
    "gn:country_code":"LA",
    "gn:dem":961,
    "gn:feature_class":"P",
    "gn:feature_code":"PPL",
    "gn:name":"Ban Chakheum",
    "gn:population":0,
    "gn:timezone":"Asia/Vientiane",
    "iso:country":"LA",
    "name:lao_x_preferred":[
        "Ban Chakheum"
    ],
    "wof:name":"Ban Chakheum",
    "wof:placetype":"locality"
},
  "geometry": {"coordinates":[100.92977,21.28589],"type":"Point"}
}