{
  "type": "Feature",
  "properties": {
    "gn:admin1_code":"7.0",
    "gn:asciiname":"Ban Xiangle",
    "gn:country_code":"LA",
    "gn:dem":558,
    "gn:feature_class":"P",
    "gn:feature_code":"PPL",
    "gn:name":"Ban Xiangl\u00e8",
    "gn:population":0,
    "gn:timezone":"Asia/Vientiane",
    "iso:country":"LA",
    "name:lao_x_preferred":[
        "Ban Xiangl\u00e8"
    ],
    "wof:name":"Ban Xiangle",
    "wof:placetype":"locality"
},
  "geometry": {"coordinates":[101.68646,20.35419],"type":"Point"}
}