{
  "type": "Feature",
  "properties": {
    "gn:admin1_code":"3.0",
    "gn:asciiname":"Ban Mouang",
    "gn:country_code":"LA",
    "gn:dem":307,
    "gn:feature_class":"P",
    "gn:feature_code":"PPL",
    "gn:name":"Ban Mouang",
    "gn:population":0,
    "gn:timezone":"Asia/Vientiane",
    "iso:country":"LA",
    "name:und_x_variant":[
        "Ban Muong",
        "Ban Mouang"
    ],
    "wof:name":"Ban Mouang",
    "wof:placetype":"locality"
},
  "geometry": {"coordinates":[104.32888,20.78612],"type":"Point"}
}