{
  "type": "Feature",
  "properties": {
    "gn:admin1_code":"19.0",
    "gn:asciiname":"Ban Nadonkhoang",
    "gn:country_code":"LA",
    "gn:dem":196,
    "gn:feature_class":"P",
    "gn:feature_code":"PPL",
    "gn:name":"Ban Nadonkhoang",
    "gn:population":0,
    "gn:timezone":"Asia/Vientiane",
    "iso:country":"LA",
    "name:und_x_variant":[
        "Ban Nadon Khouang",
        "Ban Nadong Khouang",
        "Ban Nadonkhoang"
    ],
    "wof:name":"Ban Nadonkhoang",
    "wof:placetype":"locality"
},
  "geometry": {"coordinates":[106.33304,15.71172],"type":"Point"}
}