{
  "type": "Feature",
  "properties": {
    "gn:admin1_code":"3.0",
    "gn:asciiname":"Houarnuang",
    "gn:country_code":"LA",
    "gn:dem":741,
    "gn:feature_class":"P",
    "gn:feature_code":"PPL",
    "gn:name":"Houarnuang",
    "gn:population":0,
    "gn:timezone":"Asia/Vientiane",
    "iso:country":"LA",
    "wof:name":"Houarnuang",
    "wof:placetype":"locality"
},
  "geometry": {"coordinates":[103.62204,20.14246],"type":"Point"}
}