{
  "type": "Feature",
  "properties": {
    "gn:admin1_code":"17.0",
    "gn:asciiname":"Ban Pha Pho Keou",
    "gn:cc2":"LA",
    "gn:country_code":"LA",
    "gn:dem":1036,
    "gn:feature_class":"P",
    "gn:feature_code":"PPL",
    "gn:name":"Ban Pha Pho K\u00e8ou",
    "gn:population":0,
    "gn:timezone":"Asia/Vientiane",
    "iso:country":"LA",
    "name:und_x_variant":[
        "Ban Pha Pho",
        "Ban Pha Pho K\u00e8ou"
    ],
    "wof:name":"Ban Pha Pho Keou",
    "wof:placetype":"locality"
},
  "geometry": {"coordinates":[102.53333000000001,19.73333],"type":"Point"}
}