{
  "type": "Feature",
  "properties": {
    "gn:admin1_code":"17.0",
    "gn:asciiname":"Ban Nian Noy",
    "gn:country_code":"LA",
    "gn:dem":592,
    "gn:feature_class":"P",
    "gn:feature_code":"PPL",
    "gn:name":"Ban Nian Noy",
    "gn:population":0,
    "gn:timezone":"Asia/Vientiane",
    "iso:country":"LA",
    "wof:name":"Ban Nian Noy",
    "wof:placetype":"locality"
},
  "geometry": {"coordinates":[102.21666999999999,19.78333],"type":"Point"}
}