{
  "type": "Feature",
  "properties": {
    "gn:admin1_code":"2.0",
    "gn:asciiname":"Ban Bak",
    "gn:country_code":"LA",
    "gn:dem":113,
    "gn:feature_class":"P",
    "gn:feature_code":"PPL",
    "gn:name":"Ban Bak",
    "gn:population":0,
    "gn:timezone":"Asia/Vientiane",
    "iso:country":"LA",
    "name:lao_x_preferred":[
        "Ban Bak"
    ],
    "wof:name":"Ban Bak",
    "wof:placetype":"locality"
},
  "geometry": {"coordinates":[105.79447,14.70797],"type":"Point"}
}