{
  "type": "Feature",
  "properties": {
    "gn:admin1_code":"7.0",
    "gn:asciiname":"Ban Laxa",
    "gn:country_code":"LA",
    "gn:dem":1002,
    "gn:feature_class":"P",
    "gn:feature_code":"PPL",
    "gn:name":"Ban Laxa",
    "gn:population":0,
    "gn:timezone":"Asia/Vientiane",
    "iso:country":"LA",
    "name:und_x_variant":[
        "Ban La Sa",
        "Ban Laxa"
    ],
    "wof:name":"Ban Laxa",
    "wof:placetype":"locality"
},
  "geometry": {"coordinates":[102.21666999999999,20.66667],"type":"Point"}
}