{
  "type": "Feature",
  "properties": {
    "gn:admin1_code":"27.0",
    "gn:asciiname":"Ban Thahua",
    "gn:country_code":"LA",
    "gn:dem":224,
    "gn:feature_class":"P",
    "gn:feature_code":"PPL",
    "gn:name":"Ban Thahua",
    "gn:population":0,
    "gn:timezone":"Asia/Vientiane",
    "iso:country":"LA",
    "name:lao_x_preferred":[
        "Ban Thahua"
    ],
    "wof:name":"Ban Thahua",
    "wof:placetype":"locality"
},
  "geometry": {"coordinates":[102.50878,18.78052000000001],"type":"Point"}
}