{
  "type": "Feature",
  "properties": {
    "gn:admin1_code":"19.0",
    "gn:asciiname":"Ban Nonsoung",
    "gn:country_code":"LA",
    "gn:dem":158,
    "gn:feature_class":"P",
    "gn:feature_code":"PPL",
    "gn:name":"Ban N\u00f4nsoung",
    "gn:population":0,
    "gn:timezone":"Asia/Vientiane",
    "iso:country":"LA",
    "name:lao_x_preferred":[
        "Ban N\u00f4nsoung"
    ],
    "wof:name":"Ban Nonsoung",
    "wof:placetype":"locality"
},
  "geometry": {"coordinates":[105.77132,15.74156],"type":"Point"}
}