{
  "type": "Feature",
  "properties": {
    "gn:admin1_code":"1.0",
    "gn:asciiname":"Ban Noy",
    "gn:cc2":"LA",
    "gn:country_code":"LA",
    "gn:dem":103,
    "gn:feature_class":"P",
    "gn:feature_code":"PPL",
    "gn:name":"Ban Noy",
    "gn:population":0,
    "gn:timezone":"Asia/Vientiane",
    "iso:country":"LA",
    "name:und_x_variant":[
        "Ban Noi",
        "Ban Noy"
    ],
    "wof:name":"Ban Noy",
    "wof:placetype":"locality"
},
  "geometry": {"coordinates":[106.93333,14.81667],"type":"Point"}
}