{
  "type": "Feature",
  "properties": {
    "gn:admin1_code":"20.0",
    "gn:asciiname":"Ban Dontoum",
    "gn:country_code":"LA",
    "gn:dem":154,
    "gn:feature_class":"P",
    "gn:feature_code":"PPL",
    "gn:name":"Ban Dontoum",
    "gn:population":0,
    "gn:timezone":"Asia/Vientiane",
    "iso:country":"LA",
    "name:und_x_variant":[
        "Ban Done Toum",
        "Ban None Toum",
        "Ban Don Taum",
        "Ban Dontoum"
    ],
    "wof:name":"Ban Dontoum",
    "wof:placetype":"locality"
},
  "geometry": {"coordinates":[105.01861,16.38926],"type":"Point"}
}