{
  "type": "Feature",
  "properties": {
    "gn:admin1_code":"3.0",
    "gn:asciiname":"Ban Meokou",
    "gn:country_code":"LA",
    "gn:dem":415,
    "gn:feature_class":"P",
    "gn:feature_code":"PPL",
    "gn:name":"Ban M\u00e8okou",
    "gn:population":0,
    "gn:timezone":"Asia/Vientiane",
    "iso:country":"LA",
    "name:lao_x_preferred":[
        "Ban M\u00e8okou"
    ],
    "wof:name":"Ban Meokou",
    "wof:placetype":"locality"
},
  "geometry": {"coordinates":[103.91046,20.8049],"type":"Point"}
}