{
  "type": "Feature",
  "properties": {
    "gn:admin1_code":"15.0",
    "gn:asciiname":"Ban Sixiang-Mai",
    "gn:country_code":"LA",
    "gn:dem":191,
    "gn:feature_class":"P",
    "gn:feature_code":"PPL",
    "gn:name":"Ban Sixiang-Mai",
    "gn:population":0,
    "gn:timezone":"Asia/Vientiane",
    "iso:country":"LA",
    "name:lao_x_preferred":[
        "Ban Sixiang-Mai"
    ],
    "wof:name":"Ban Sixiang-Mai",
    "wof:placetype":"locality"
},
  "geometry": {"coordinates":[105.46005,17.20991],"type":"Point"}
}