{
  "type": "Feature",
  "properties": {
    "gn:admin1_code":"2.0",
    "gn:asciiname":"Ban Chik",
    "gn:country_code":"LA",
    "gn:dem":108,
    "gn:feature_class":"P",
    "gn:feature_code":"PPL",
    "gn:name":"Ban Chik",
    "gn:population":0,
    "gn:timezone":"Asia/Vientiane",
    "iso:country":"LA",
    "name:lao_x_preferred":[
        "Ban Chik"
    ],
    "name:und_x_variant":[
        "Ban Chik (2)"
    ],
    "wof:name":"Ban Chik",
    "wof:placetype":"locality"
},
  "geometry": {"coordinates":[105.66373,15.14363],"type":"Point"}
}