{
  "type": "Feature",
  "properties": {
    "gn:admin1_code":"20.0",
    "gn:asciiname":"Ban Namakmi",
    "gn:country_code":"LA",
    "gn:dem":172,
    "gn:feature_class":"P",
    "gn:feature_code":"PPL",
    "gn:name":"Ban Namakmi",
    "gn:population":0,
    "gn:timezone":"Asia/Vientiane",
    "iso:country":"LA",
    "name:lao_x_preferred":[
        "Ban Namakmi"
    ],
    "wof:name":"Ban Namakmi",
    "wof:placetype":"locality"
},
  "geometry": {"coordinates":[105.38248,16.7585],"type":"Point"}
}