{
  "type": "Feature",
  "properties": {
    "gn:admin1_code":"3.0",
    "gn:asciiname":"Ban Navit",
    "gn:country_code":"LA",
    "gn:dem":704,
    "gn:feature_class":"P",
    "gn:feature_code":"PPL",
    "gn:name":"Ban Navit",
    "gn:population":0,
    "gn:timezone":"Asia/Vientiane",
    "iso:country":"LA",
    "name:lao_x_preferred":[
        "Ban Navit"
    ],
    "name:und_x_variant":[
        "Na Vit Neua"
    ],
    "wof:name":"Ban Navit",
    "wof:placetype":"locality"
},
  "geometry": {"coordinates":[104.27181,20.37936],"type":"Point"}
}