{
  "type": "Feature",
  "properties": {
    "gn:admin1_code":"20.0",
    "gn:asciiname":"Ban Sabouxai-Tai",
    "gn:country_code":"LA",
    "gn:dem":136,
    "gn:feature_class":"P",
    "gn:feature_code":"PPL",
    "gn:name":"Ban Sabouxai-Tai",
    "gn:population":0,
    "gn:timezone":"Asia/Vientiane",
    "iso:country":"LA",
    "name:lao_x_preferred":[
        "Ban Sabouxai-Tai"
    ],
    "wof:name":"Ban Sabouxai-Tai",
    "wof:placetype":"locality"
},
  "geometry": {"coordinates":[105.16106000000001,16.07558],"type":"Point"}
}