{
  "type": "Feature",
  "properties": {
    "gn:admin1_code":"22.0",
    "gn:asciiname":"Ban Houaymakkhuagnao",
    "gn:country_code":"LA",
    "gn:dem":400,
    "gn:feature_class":"P",
    "gn:feature_code":"PPL",
    "gn:name":"Ban Houaymakkhuagnao",
    "gn:population":0,
    "gn:timezone":"Asia/Vientiane",
    "iso:country":"LA",
    "name:lao_x_preferred":[
        "Ban Houaymakkhuagnao"
    ],
    "wof:name":"Ban Houaymakkhuagnao",
    "wof:placetype":"locality"
},
  "geometry": {"coordinates":[100.18404,20.393],"type":"Point"}
}