{
  "type": "Feature",
  "properties": {
    "gn:admin1_code":"14.0",
    "gn:asciiname":"Ban Sandon",
    "gn:country_code":"LA",
    "gn:dem":1334,
    "gn:feature_class":"P",
    "gn:feature_code":"PPL",
    "gn:name":"Ban Sand\u00f4n",
    "gn:population":0,
    "gn:timezone":"Asia/Vientiane",
    "iso:country":"LA",
    "name:lao_x_preferred":[
        "Ban Sand\u00f4n"
    ],
    "wof:name":"Ban Sandon",
    "wof:placetype":"locality"
},
  "geometry": {"coordinates":[103.96113,19.57507],"type":"Point"}
}