{
  "type": "Feature",
  "properties": {
    "gn:admin1_code":"19.0",
    "gn:asciiname":"Ban Laogna",
    "gn:country_code":"LA",
    "gn:dem":1071,
    "gn:feature_class":"P",
    "gn:feature_code":"PPL",
    "gn:name":"Ban Laogna",
    "gn:population":0,
    "gn:timezone":"Asia/Vientiane",
    "iso:country":"LA",
    "name:und_x_variant":[
        "Ban Lao Nhia",
        "Ban Laogna"
    ],
    "wof:name":"Ban Laogna",
    "wof:placetype":"locality"
},
  "geometry": {"coordinates":[106.15525,15.31435],"type":"Point"}
}