{
  "type": "Feature",
  "properties": {
    "gn:admin1_code":"13.0",
    "gn:asciiname":"Ban Kokhaikham",
    "gn:country_code":"LA",
    "gn:dem":509,
    "gn:feature_class":"P",
    "gn:feature_code":"PPL",
    "gn:name":"Ban K\u00f4khaikham",
    "gn:population":0,
    "gn:timezone":"Asia/Vientiane",
    "iso:country":"LA",
    "name:lao_x_preferred":[
        "Ban K\u00f4khaikham"
    ],
    "wof:name":"Ban Kokhaikham",
    "wof:placetype":"locality"
},
  "geometry": {"coordinates":[101.26685000000001,17.84442],"type":"Point"}
}