{
  "type": "Feature",
  "properties": {
    "gn:admin1_code":"3.0",
    "gn:asciiname":"Ban Tuam",
    "gn:country_code":"LA",
    "gn:dem":688,
    "gn:feature_class":"P",
    "gn:feature_code":"PPL",
    "gn:name":"Ban Tuam",
    "gn:population":0,
    "gn:timezone":"Asia/Vientiane",
    "iso:country":"LA",
    "name:und_x_variant":[
        "Ban Teum",
        "Ban Tuam"
    ],
    "wof:name":"Ban Tuam",
    "wof:placetype":"locality"
},
  "geometry": {"coordinates":[104.29249,20.14896],"type":"Point"}
}