{
  "type": "Feature",
  "properties": {
    "gn:admin1_code":"7.0",
    "gn:asciiname":"Ban Na-Ngam",
    "gn:country_code":"LA",
    "gn:dem":703,
    "gn:feature_class":"P",
    "gn:feature_code":"PPL",
    "gn:name":"Ban Na-Ngam",
    "gn:population":0,
    "gn:timezone":"Asia/Vientiane",
    "iso:country":"LA",
    "name:lao_x_preferred":[
        "Ban Na-Ngam"
    ],
    "wof:name":"Ban Na-Ngam",
    "wof:placetype":"locality"
},
  "geometry": {"coordinates":[101.87514,20.68103],"type":"Point"}
}