{
  "type": "Feature",
  "properties": {
    "gn:admin1_code":"1.0",
    "gn:asciiname":"Ban Khemxang",
    "gn:country_code":"LA",
    "gn:dem":100,
    "gn:feature_class":"P",
    "gn:feature_code":"PPL",
    "gn:name":"Ban Kh\u00e8mxang",
    "gn:population":0,
    "gn:timezone":"Asia/Vientiane",
    "iso:country":"LA",
    "name:lao_x_preferred":[
        "Ban Kh\u00e8mxang"
    ],
    "wof:name":"Ban Khemxang",
    "wof:placetype":"locality"
},
  "geometry": {"coordinates":[106.75058,14.81182],"type":"Point"}
}