{
  "type": "Feature",
  "properties": {
    "gn:admin1_code":"7.0",
    "gn:asciiname":"Ban Ton",
    "gn:country_code":"LA",
    "gn:dem":322,
    "gn:feature_class":"P",
    "gn:feature_code":"PPL",
    "gn:name":"Ban Ton",
    "gn:population":0,
    "gn:timezone":"Asia/Vientiane",
    "iso:country":"LA",
    "name:lao_x_preferred":[
        "Ban Ton"
    ],
    "wof:name":"Ban Ton",
    "wof:placetype":"locality"
},
  "geometry": {"coordinates":[101.85821,19.95628],"type":"Point"}
}