{
  "type": "Feature",
  "properties": {
    "gn:admin1_code":"23.0",
    "gn:asciiname":"Ban Pahok",
    "gn:country_code":"LA",
    "gn:dem":426,
    "gn:feature_class":"P",
    "gn:feature_code":"PPL",
    "gn:name":"Ban Pah\u00f4k",
    "gn:population":0,
    "gn:timezone":"Asia/Vientiane",
    "iso:country":"LA",
    "name:und_x_variant":[
        "Ban Pa Hoc",
        "Ban Pah\u00f4k"
    ],
    "wof:name":"Ban Pahok",
    "wof:placetype":"locality"
},
  "geometry": {"coordinates":[104.73164,18.36001],"type":"Point"}
}