{
  "type": "Feature",
  "properties": {
    "gn:admin1_code":"15.0",
    "gn:asciiname":"Ban Kengkhot",
    "gn:country_code":"LA",
    "gn:dem":162,
    "gn:feature_class":"P",
    "gn:feature_code":"PPL",
    "gn:name":"Ban K\u00e8ngkh\u00f4t",
    "gn:population":0,
    "gn:timezone":"Asia/Vientiane",
    "iso:country":"LA",
    "name:lao_x_preferred":[
        "Ban K\u00e8ngkh\u00f4t"
    ],
    "wof:name":"Ban Kengkhot",
    "wof:placetype":"locality"
},
  "geometry": {"coordinates":[104.49069,18.0702],"type":"Point"}
}