{
  "type": "Feature",
  "properties": {
    "gn:admin1_code":"22.0",
    "gn:asciiname":"Ban Donchai",
    "gn:country_code":"LA",
    "gn:dem":539,
    "gn:feature_class":"P",
    "gn:feature_code":"PPL",
    "gn:name":"Ban Donchai",
    "gn:population":0,
    "gn:timezone":"Asia/Vientiane",
    "iso:country":"LA",
    "name:lao_x_preferred":[
        "Ban Donchai"
    ],
    "wof:name":"Ban Donchai",
    "wof:placetype":"locality"
},
  "geometry": {"coordinates":[100.84979,20.41469],"type":"Point"}
}