{
  "type": "Feature",
  "properties": {
    "gn:admin1_code":"27.0",
    "gn:asciiname":"Ban Khet-Hok",
    "gn:country_code":"LA",
    "gn:dem":208,
    "gn:feature_class":"P",
    "gn:feature_code":"PPL",
    "gn:name":"Ban Khet-H\u00f4k",
    "gn:population":0,
    "gn:timezone":"Asia/Vientiane",
    "iso:country":"LA",
    "name:lao_x_preferred":[
        "Ban Khet-H\u00f4k"
    ],
    "wof:name":"Ban Khet-Hok",
    "wof:placetype":"locality"
},
  "geometry": {"coordinates":[102.59916,18.6407],"type":"Point"}
}