{
  "type": "Feature",
  "properties": {
    "gn:admin1_code":"2.0",
    "gn:asciiname":"Ban Khiam",
    "gn:country_code":"LA",
    "gn:dem":110,
    "gn:feature_class":"P",
    "gn:feature_code":"PPL",
    "gn:name":"Ban Khiam",
    "gn:population":0,
    "gn:timezone":"Asia/Vientiane",
    "iso:country":"LA",
    "name:lao_x_preferred":[
        "Ban Khiam"
    ],
    "wof:name":"Ban Khiam",
    "wof:placetype":"locality"
},
  "geometry": {"coordinates":[105.32416000000001,14.22947],"type":"Point"}
}