{
  "type": "Feature",
  "properties": {
    "gn:admin1_code":"17.0",
    "gn:asciiname":"Ban Phia",
    "gn:country_code":"LA",
    "gn:dem":1048,
    "gn:feature_class":"P",
    "gn:feature_code":"PPL",
    "gn:name":"Ban Phia",
    "gn:population":0,
    "gn:timezone":"Asia/Vientiane",
    "iso:country":"LA",
    "name:lao_x_preferred":[
        "Ban Phia"
    ],
    "name:und_x_variant":[
        "Ban Tao Pia Lat (1)"
    ],
    "wof:name":"Ban Phia",
    "wof:placetype":"locality"
},
  "geometry": {"coordinates":[102.47627,19.71812000000001],"type":"Point"}
}