{
  "type": "Feature",
  "properties": {
    "gn:admin1_code":"17.0",
    "gn:asciiname":"Ban Nammiang",
    "gn:country_code":"LA",
    "gn:dem":1071,
    "gn:feature_class":"P",
    "gn:feature_code":"PPL",
    "gn:name":"Ban Nammiang",
    "gn:population":0,
    "gn:timezone":"Asia/Vientiane",
    "iso:country":"LA",
    "name:lao_x_preferred":[
        "Ban Nammiang"
    ],
    "name:und_x_variant":[
        "Ban Nam Mieng"
    ],
    "wof:name":"Ban Nammiang",
    "wof:placetype":"locality"
},
  "geometry": {"coordinates":[102.20622,20.57619],"type":"Point"}
}