{
  "type": "Feature",
  "properties": {
    "gn:admin1_code":"17.0",
    "gn:asciiname":"Ban Houaykok",
    "gn:country_code":"LA",
    "gn:dem":337,
    "gn:feature_class":"P",
    "gn:feature_code":"PPL",
    "gn:name":"Ban Houaykok",
    "gn:population":0,
    "gn:timezone":"Asia/Vientiane",
    "iso:country":"LA",
    "name:lao_x_preferred":[
        "Ban Houaykok"
    ],
    "wof:name":"Ban Houaykok",
    "wof:placetype":"locality"
},
  "geometry": {"coordinates":[102.29868999999999,19.76288],"type":"Point"}
}