{
  "type": "Feature",
  "properties": {
    "gn:admin1_code":"23.0",
    "gn:asciiname":"Ban Muang Mai",
    "gn:country_code":"LA",
    "gn:dem":163,
    "gn:feature_class":"P",
    "gn:feature_code":"PPL",
    "gn:name":"Ban Muang Mai",
    "gn:population":0,
    "gn:timezone":"Asia/Vientiane",
    "iso:country":"LA",
    "name:und_x_variant":[
        "Muong May",
        "Muong Mai",
        "Muang Mai",
        "Ban Muang Mai"
    ],
    "wof:name":"Ban Muang Mai",
    "wof:placetype":"locality"
},
  "geometry": {"coordinates":[103.66646,18.50096],"type":"Point"}
}