{
  "type": "Feature",
  "properties": {
    "gn:admin1_code":"23.0",
    "gn:asciiname":"Ban Na-O",
    "gn:country_code":"LA",
    "gn:dem":170,
    "gn:feature_class":"P",
    "gn:feature_code":"PPL",
    "gn:name":"Ban Na-\u00d4",
    "gn:population":0,
    "gn:timezone":"Asia/Vientiane",
    "iso:country":"LA",
    "name:lao_x_preferred":[
        "Ban Na-\u00d4"
    ],
    "wof:name":"Ban Na-O",
    "wof:placetype":"locality"
},
  "geometry": {"coordinates":[103.75817000000001,18.51962],"type":"Point"}
}