{
  "type": "Feature",
  "properties": {
    "gn:admin1_code":"2.0",
    "gn:asciiname":"Ban Houaxangphai",
    "gn:country_code":"LA",
    "gn:dem":93,
    "gn:feature_class":"P",
    "gn:feature_code":"PPL",
    "gn:name":"Ban Houaxangphai",
    "gn:population":0,
    "gn:timezone":"Asia/Vientiane",
    "iso:country":"LA",
    "name:lao_x_preferred":[
        "Ban Houaxangphai"
    ],
    "wof:name":"Ban Houaxangphai",
    "wof:placetype":"locality"
},
  "geometry": {"coordinates":[105.83593,14.05587],"type":"Point"}
}