{
  "type": "Feature",
  "properties": {
    "gn:admin1_code":"1.0",
    "gn:asciiname":"Ban Namhiang",
    "gn:country_code":"LA",
    "gn:dem":122,
    "gn:feature_class":"P",
    "gn:feature_code":"PPL",
    "gn:name":"Ban Namhiang",
    "gn:population":0,
    "gn:timezone":"Asia/Vientiane",
    "iso:country":"LA",
    "name:lao_x_preferred":[
        "Ban Namhiang"
    ],
    "name:lao_x_variant":[
        "Ban Mai"
    ],
    "wof:name":"Ban Namhiang",
    "wof:placetype":"locality"
},
  "geometry": {"coordinates":[106.81220999999999,15.16135],"type":"Point"}
}