{
  "type": "Feature",
  "properties": {
    "gn:admin1_code":"3.0",
    "gn:asciiname":"Ban Bouak",
    "gn:country_code":"LA",
    "gn:dem":960,
    "gn:feature_class":"P",
    "gn:feature_code":"PPL",
    "gn:name":"Ban Bouak",
    "gn:population":0,
    "gn:timezone":"Asia/Vientiane",
    "iso:country":"LA",
    "name:lao_x_preferred":[
        "Ban Bouak"
    ],
    "wof:name":"Ban Bouak",
    "wof:placetype":"locality"
},
  "geometry": {"coordinates":[103.42097,20.32576],"type":"Point"}
}