{
  "type": "Feature",
  "properties": {
    "gn:admin1_code":"13.0",
    "gn:asciiname":"Ban Natyang",
    "gn:country_code":"LA",
    "gn:dem":600,
    "gn:feature_class":"P",
    "gn:feature_code":"PPL",
    "gn:name":"Ban Natyang",
    "gn:population":0,
    "gn:timezone":"Asia/Vientiane",
    "iso:country":"LA",
    "name:und_x_variant":[
        "Ban Nath Yang",
        "Ban Nah Yang",
        "Ban Natyang"
    ],
    "wof:name":"Ban Natyang",
    "wof:placetype":"locality"
},
  "geometry": {"coordinates":[101.28509,19.66247000000001],"type":"Point"}
}