{
  "type": "Feature",
  "properties": {
    "gn:admin1_code":"18.0",
    "gn:asciiname":"Ban Phouthen",
    "gn:country_code":"LA",
    "gn:dem":955,
    "gn:feature_class":"P",
    "gn:feature_code":"PPL",
    "gn:name":"Ban Phouth\u00e8n",
    "gn:population":0,
    "gn:timezone":"Asia/Vientiane",
    "iso:country":"LA",
    "name:lao_x_preferred":[
        "Ban Phouth\u00e8n"
    ],
    "wof:name":"Ban Phouthen",
    "wof:placetype":"locality"
},
  "geometry": {"coordinates":[102.17594,21.01305],"type":"Point"}
}