{
  "type": "Feature",
  "properties": {
    "gn:admin1_code":"17.0",
    "gn:asciiname":"Ban Phiathongdi",
    "gn:country_code":"LA",
    "gn:dem":1098,
    "gn:feature_class":"P",
    "gn:feature_code":"PPL",
    "gn:name":"Ban Phiathongdi",
    "gn:population":0,
    "gn:timezone":"Asia/Vientiane",
    "iso:country":"LA",
    "name:lao_x_preferred":[
        "Ban Phiathongdi"
    ],
    "wof:name":"Ban Phiathongdi",
    "wof:placetype":"locality"
},
  "geometry": {"coordinates":[102.9842,20.70236],"type":"Point"}
}