{
  "type": "Feature",
  "properties": {
    "gn:admin1_code":"18.0",
    "gn:asciiname":"Ban Salaoutya",
    "gn:country_code":"LA",
    "gn:dem":1065,
    "gn:feature_class":"P",
    "gn:feature_code":"PPL",
    "gn:name":"Ban Salaoutya",
    "gn:population":0,
    "gn:timezone":"Asia/Vientiane",
    "iso:country":"LA",
    "name:und_x_variant":[
        "Selaoutya",
        "Ban Salaoutya"
    ],
    "wof:name":"Ban Salaoutya",
    "wof:placetype":"locality"
},
  "geometry": {"coordinates":[101.76296000000001,21.87703],"type":"Point"}
}