{
  "type": "Feature",
  "properties": {
    "gn:admin1_code":"18.0",
    "gn:asciiname":"Ban Omtlum",
    "gn:country_code":"LA",
    "gn:dem":806,
    "gn:feature_class":"P",
    "gn:feature_code":"PPL",
    "gn:name":"Ban \u00d4mtlum",
    "gn:population":0,
    "gn:timezone":"Asia/Vientiane",
    "iso:country":"LA",
    "name:lao_x_preferred":[
        "Ban \u00d4mtlum"
    ],
    "wof:name":"Ban Omtlum",
    "wof:placetype":"locality"
},
  "geometry": {"coordinates":[102.58197,21.25332],"type":"Point"}
}