{
  "type": "Feature",
  "properties": {
    "gn:admin1_code":"28.0",
    "gn:asciiname":"Ban Nalao",
    "gn:country_code":"LA",
    "gn:dem":364,
    "gn:feature_class":"P",
    "gn:feature_code":"PPL",
    "gn:name":"Ban Nalao",
    "gn:population":0,
    "gn:timezone":"Asia/Vientiane",
    "iso:country":"LA",
    "wof:name":"Ban Nalao",
    "wof:placetype":"locality"
},
  "geometry": {"coordinates":[103.41667,19.03333],"type":"Point"}
}