{
  "type": "Feature",
  "properties": {
    "gn:admin1_code":"7.0",
    "gn:asciiname":"Ban Palen",
    "gn:country_code":"LA",
    "gn:dem":962,
    "gn:feature_class":"P",
    "gn:feature_code":"PPL",
    "gn:name":"Ban Pal\u00e8n",
    "gn:population":0,
    "gn:timezone":"Asia/Vientiane",
    "iso:country":"LA",
    "name:lao_x_preferred":[
        "Ban Pal\u00e8n"
    ],
    "wof:name":"Ban Palen",
    "wof:placetype":"locality"
},
  "geometry": {"coordinates":[101.72759000000001,20.6257],"type":"Point"}
}