{
  "type": "Feature",
  "properties": {
    "gn:admin1_code":"20.0",
    "gn:asciiname":"Ban Khadao-Duy",
    "gn:country_code":"LA",
    "gn:dem":221,
    "gn:feature_class":"P",
    "gn:feature_code":"PPL",
    "gn:name":"Ban Khadao-Duy",
    "gn:population":0,
    "gn:timezone":"Asia/Vientiane",
    "iso:country":"LA",
    "name:lao_x_preferred":[
        "Ban Khadao-Duy"
    ],
    "name:und_x_variant":[
        "Ban Khadao-Ouy"
    ],
    "wof:name":"Ban Khadao-Duy",
    "wof:placetype":"locality"
},
  "geometry": {"coordinates":[106.48972999999999,16.63557999999999],"type":"Point"}
}