{
  "type": "Feature",
  "properties": {
    "gn:admin1_code":"23.0",
    "gn:asciiname":"Ban Patxoum",
    "gn:country_code":"LA",
    "gn:dem":163,
    "gn:feature_class":"P",
    "gn:feature_code":"PPL",
    "gn:name":"Ban Patxoum",
    "gn:population":0,
    "gn:timezone":"Asia/Vientiane",
    "iso:country":"LA",
    "name:und_x_variant":[
        "Ban Pat Choum",
        "Ban Patxoum"
    ],
    "wof:name":"Ban Patxoum",
    "wof:placetype":"locality"
},
  "geometry": {"coordinates":[103.71162,18.42908],"type":"Point"}
}