{
  "type": "Feature",
  "properties": {
    "gn:admin1_code":"17.0",
    "gn:asciiname":"Ban Khonkeung",
    "gn:country_code":"LA",
    "gn:dem":334,
    "gn:feature_class":"P",
    "gn:feature_code":"PPL",
    "gn:name":"Ban Khonkeung",
    "gn:population":0,
    "gn:timezone":"Asia/Vientiane",
    "iso:country":"LA",
    "name:lao_x_preferred":[
        "Ban Khonkeung"
    ],
    "wof:name":"Ban Khonkeung",
    "wof:placetype":"locality"
},
  "geometry": {"coordinates":[102.49405,20.42919],"type":"Point"}
}