{
  "type": "Feature",
  "properties": {
    "gn:admin1_code":"20.0",
    "gn:asciiname":"Ban Napheng",
    "gn:country_code":"LA",
    "gn:dem":156,
    "gn:feature_class":"P",
    "gn:feature_code":"PPL",
    "gn:name":"Ban Naph\u00e8ng",
    "gn:population":0,
    "gn:timezone":"Asia/Vientiane",
    "iso:country":"LA",
    "name:lao_x_preferred":[
        "Ban Naph\u00e8ng"
    ],
    "wof:name":"Ban Napheng",
    "wof:placetype":"locality"
},
  "geometry": {"coordinates":[105.50576,16.48059],"type":"Point"}
}