{
  "type": "Feature",
  "properties": {
    "gn:admin1_code":"22.0",
    "gn:asciiname":"Ban Paktha",
    "gn:country_code":"LA",
    "gn:dem":352,
    "gn:feature_class":"P",
    "gn:feature_code":"PPL",
    "gn:name":"Ban Paktha",
    "gn:population":0,
    "gn:timezone":"Asia/Vientiane",
    "iso:country":"LA",
    "name:und_x_variant":[
        "Muong Pak Ta",
        "Muang Paktha",
        "Pak Tha",
        "Muong Pak Tha",
        "Ban Paktha"
    ],
    "wof:name":"Ban Paktha",
    "wof:placetype":"locality"
},
  "geometry": {"coordinates":[100.59446,20.10722],"type":"Point"}
}