{
  "type": "Feature",
  "properties": {
    "gn:admin1_code":"14.0",
    "gn:asciiname":"Ban Kognom",
    "gn:country_code":"LA",
    "gn:dem":1107,
    "gn:feature_class":"P",
    "gn:feature_code":"PPL",
    "gn:name":"Ban Kogn\u00f4m",
    "gn:population":0,
    "gn:timezone":"Asia/Vientiane",
    "iso:country":"LA",
    "name:und_x_variant":[
        "Ban Ko Niom",
        "Ban Kogn\u00f4m"
    ],
    "wof:name":"Ban Kognom",
    "wof:placetype":"locality"
},
  "geometry": {"coordinates":[103.76927000000001,19.5854],"type":"Point"}
}