{
  "type": "Feature",
  "properties": {
    "gn:admin1_code":"14.0",
    "gn:asciiname":"Ban Nampong",
    "gn:cc2":"LA",
    "gn:country_code":"LA",
    "gn:dem":1356,
    "gn:feature_class":"P",
    "gn:feature_code":"PPL",
    "gn:name":"Ban Namp\u00f4ng",
    "gn:population":0,
    "gn:timezone":"Asia/Vientiane",
    "iso:country":"LA",
    "name:und_x_variant":[
        "Ban Nam Pang",
        "Ban Namp\u00f4ng"
    ],
    "wof:name":"Ban Nampong",
    "wof:placetype":"locality"
},
  "geometry": {"coordinates":[103.73333,19.35],"type":"Point"}
}