{
  "type": "Feature",
  "properties": {
    "gn:admin1_code":"22.0",
    "gn:asciiname":"Ban Namngiou",
    "gn:country_code":"LA",
    "gn:dem":370,
    "gn:feature_class":"P",
    "gn:feature_code":"PPL",
    "gn:name":"Ban Namngiou",
    "gn:population":0,
    "gn:timezone":"Asia/Vientiane",
    "iso:country":"LA",
    "name:und_x_variant":[
        "Ban Nam Ngao",
        "Ban Namngiou",
        "Ban N-Ngao"
    ],
    "wof:name":"Ban Namngiou",
    "wof:placetype":"locality"
},
  "geometry": {"coordinates":[100.36454000000001,20.36824],"type":"Point"}
}