{
  "type": "Feature",
  "properties": {
    "gn:admin1_code":"14.0",
    "gn:asciiname":"Ban Latkhay",
    "gn:country_code":"LA",
    "gn:dem":1110,
    "gn:feature_class":"P",
    "gn:feature_code":"PPL",
    "gn:name":"Ban Latkhay",
    "gn:population":0,
    "gn:timezone":"Asia/Vientiane",
    "iso:country":"LA",
    "name:lao_x_preferred":[
        "Ban Latkhay"
    ],
    "wof:name":"Ban Latkhay",
    "wof:placetype":"locality"
},
  "geometry": {"coordinates":[103.13571,19.29676],"type":"Point"}
}