{
  "type": "Feature",
  "properties": {
    "gn:admin1_code":"16.0",
    "gn:asciiname":"Ban Vianglao",
    "gn:country_code":"LA",
    "gn:dem":459,
    "gn:feature_class":"P",
    "gn:feature_code":"PPL",
    "gn:name":"Ban Vianglao",
    "gn:population":0,
    "gn:timezone":"Asia/Vientiane",
    "iso:country":"LA",
    "name:lao_x_preferred":[
        "Ban Vianglao"
    ],
    "wof:name":"Ban Vianglao",
    "wof:placetype":"locality"
},
  "geometry": {"coordinates":[101.41312000000001,20.49733],"type":"Point"}
}