{
  "type": "Feature",
  "properties": {
    "gn:admin1_code":"15.0",
    "gn:asciiname":"Ban Pak-Hinboun-Tai",
    "gn:country_code":"LA",
    "gn:dem":136,
    "gn:feature_class":"P",
    "gn:feature_code":"PPL",
    "gn:name":"Ban Pak-Hinboun-Tai",
    "gn:population":0,
    "gn:timezone":"Asia/Vientiane",
    "iso:country":"LA",
    "name:lao_x_preferred":[
        "Ban Pak-Hinboun-Tai"
    ],
    "wof:name":"Ban Pak-Hinboun-Tai",
    "wof:placetype":"locality"
},
  "geometry": {"coordinates":[104.61176,17.58881],"type":"Point"}
}