{
  "type": "Feature",
  "properties": {
    "gn:admin1_code":"16.0",
    "gn:asciiname":"Ban Chakeo-Tai",
    "gn:country_code":"LA",
    "gn:dem":772,
    "gn:feature_class":"P",
    "gn:feature_code":"PPL",
    "gn:name":"Ban Chak\u00e8o-Tai",
    "gn:population":0,
    "gn:timezone":"Asia/Vientiane",
    "iso:country":"LA",
    "name:lao_x_preferred":[
        "Ban Chak\u00e8o-Tai"
    ],
    "wof:name":"Ban Chakeo-Tai",
    "wof:placetype":"locality"
},
  "geometry": {"coordinates":[100.63715999999999,20.94646],"type":"Point"}
}