{
  "type": "Feature",
  "properties": {
    "gn:admin1_code":"18.0",
    "gn:asciiname":"Ban Phadeng-Noy",
    "gn:country_code":"LA",
    "gn:dem":1096,
    "gn:feature_class":"P",
    "gn:feature_code":"PPL",
    "gn:name":"Ban Phad\u00e8ng-Noy",
    "gn:population":0,
    "gn:timezone":"Asia/Vientiane",
    "iso:country":"LA",
    "name:lao_x_preferred":[
        "Ban Phad\u00e8ng-Noy"
    ],
    "wof:name":"Ban Phadeng-Noy",
    "wof:placetype":"locality"
},
  "geometry": {"coordinates":[101.77428999999999,21.85414],"type":"Point"}
}