{
  "type": "Feature",
  "properties": {
    "gn:admin1_code":"22.0",
    "gn:asciiname":"Ban Khom",
    "gn:country_code":"LA",
    "gn:dem":420,
    "gn:feature_class":"P",
    "gn:feature_code":"PPL",
    "gn:name":"Ban Kh\u00f4m",
    "gn:population":0,
    "gn:timezone":"Asia/Vientiane",
    "iso:country":"LA",
    "name:lao_x_preferred":[
        "Ban Kh\u00f4m"
    ],
    "wof:name":"Ban Khom",
    "wof:placetype":"locality"
},
  "geometry": {"coordinates":[100.83265,20.07116],"type":"Point"}
}