{
  "type": "Feature",
  "properties": {
    "gn:admin1_code":"2.0",
    "gn:asciiname":"Ban Boun",
    "gn:country_code":"LA",
    "gn:dem":101,
    "gn:feature_class":"P",
    "gn:feature_code":"PPL",
    "gn:name":"Ban Boun",
    "gn:population":0,
    "gn:timezone":"Asia/Vientiane",
    "iso:country":"LA",
    "name:lao_x_preferred":[
        "Ban Boun"
    ],
    "wof:name":"Ban Boun",
    "wof:placetype":"locality"
},
  "geometry": {"coordinates":[105.87282,14.63075],"type":"Point"}
}