{
  "type": "Feature",
  "properties": {
    "gn:admin1_code":"17.0",
    "gn:asciiname":"Ban Hatkhe",
    "gn:country_code":"LA",
    "gn:dem":325,
    "gn:feature_class":"P",
    "gn:feature_code":"PPL",
    "gn:name":"Ban Hatkh\u00e8",
    "gn:population":0,
    "gn:timezone":"Asia/Vientiane",
    "iso:country":"LA",
    "name:lao_x_preferred":[
        "Ban Hatkh\u00e8"
    ],
    "wof:name":"Ban Hatkhe",
    "wof:placetype":"locality"
},
  "geometry": {"coordinates":[102.42968999999999,20.2954],"type":"Point"}
}