{
  "type": "Feature",
  "properties": {
    "gn:admin1_code":"15.0",
    "gn:asciiname":"Ban Xam-Nua",
    "gn:country_code":"LA",
    "gn:dem":187,
    "gn:feature_class":"P",
    "gn:feature_code":"PPL",
    "gn:name":"Ban Xam-Nua",
    "gn:population":0,
    "gn:timezone":"Asia/Vientiane",
    "iso:country":"LA",
    "name:lao_x_preferred":[
        "Ban Xam-Nua"
    ],
    "name:und_x_variant":[
        "Ban Neua"
    ],
    "wof:name":"Ban Xam-Nua",
    "wof:placetype":"locality"
},
  "geometry": {"coordinates":[105.83880000000001,17.55151],"type":"Point"}
}