{
  "type": "Feature",
  "properties": {
    "gn:admin1_code":"17.0",
    "gn:asciiname":"Ban Houaymon",
    "gn:country_code":"LA",
    "gn:dem":658,
    "gn:feature_class":"P",
    "gn:feature_code":"PPL",
    "gn:name":"Ban Houaymon",
    "gn:population":0,
    "gn:timezone":"Asia/Vientiane",
    "iso:country":"LA",
    "name:lao_x_preferred":[
        "Ban Houaymon"
    ],
    "wof:name":"Ban Houaymon",
    "wof:placetype":"locality"
},
  "geometry": {"coordinates":[103.03873,20.57632000000001],"type":"Point"}
}