{
  "type": "Feature",
  "properties": {
    "gn:admin1_code":"19.0",
    "gn:asciiname":"Ban Donmouang",
    "gn:country_code":"LA",
    "gn:dem":178,
    "gn:feature_class":"P",
    "gn:feature_code":"PPL",
    "gn:name":"Ban Donmouang",
    "gn:population":0,
    "gn:timezone":"Asia/Vientiane",
    "iso:country":"LA",
    "wof:name":"Ban Donmouang",
    "wof:placetype":"locality"
},
  "geometry": {"coordinates":[106.26667,15.88333],"type":"Point"}
}