{
  "type": "Feature",
  "properties": {
    "gn:admin1_code":"15.0",
    "gn:asciiname":"Ban Thongmang-Tha",
    "gn:country_code":"LA",
    "gn:dem":174,
    "gn:feature_class":"P",
    "gn:feature_code":"PPL",
    "gn:name":"Ban Th\u00f4ngmang-Tha",
    "gn:population":0,
    "gn:timezone":"Asia/Vientiane",
    "iso:country":"LA",
    "name:lao_x_preferred":[
        "Ban Th\u00f4ngmang-Tha"
    ],
    "wof:name":"Ban Thongmang-Tha",
    "wof:placetype":"locality"
},
  "geometry": {"coordinates":[105.16098999999998,17.61074],"type":"Point"}
}