{
  "type": "Feature",
  "properties": {
    "gn:admin1_code":"14.0",
    "gn:asciiname":"Ban Namsong",
    "gn:country_code":"LA",
    "gn:dem":1547,
    "gn:feature_class":"P",
    "gn:feature_code":"PPL",
    "gn:name":"Ban Namsong",
    "gn:population":0,
    "gn:timezone":"Asia/Vientiane",
    "iso:country":"LA",
    "name:lao_x_preferred":[
        "Ban Namsong"
    ],
    "wof:name":"Ban Namsong",
    "wof:placetype":"locality"
},
  "geometry": {"coordinates":[103.81052,19.17899],"type":"Point"}
}