{
  "type": "Feature",
  "properties": {
    "gn:admin1_code":"15.0",
    "gn:asciiname":"Ban Phit",
    "gn:country_code":"LA",
    "gn:dem":167,
    "gn:feature_class":"P",
    "gn:feature_code":"PPL",
    "gn:name":"Ban Phit",
    "gn:population":0,
    "gn:timezone":"Asia/Vientiane",
    "iso:country":"LA",
    "name:lao_x_preferred":[
        "Ban Phit"
    ],
    "wof:name":"Ban Phit",
    "wof:placetype":"locality"
},
  "geometry": {"coordinates":[105.11443,17.51761],"type":"Point"}
}