{
  "type": "Feature",
  "properties": {
    "gn:admin1_code":"14.0",
    "gn:asciiname":"Ban Namthoum",
    "gn:country_code":"LA",
    "gn:dem":649,
    "gn:feature_class":"P",
    "gn:feature_code":"PPL",
    "gn:name":"Ban Namthoum",
    "gn:population":0,
    "gn:timezone":"Asia/Vientiane",
    "iso:country":"LA",
    "name:lao_x_preferred":[
        "Ban Namthoum"
    ],
    "wof:name":"Ban Namthoum",
    "wof:placetype":"locality"
},
  "geometry": {"coordinates":[103.07422,19.72978],"type":"Point"}
}