{
  "type": "Feature",
  "properties": {
    "gn:admin1_code":"23.0",
    "gn:asciiname":"Ban Nagnao",
    "gn:country_code":"LA",
    "gn:dem":160,
    "gn:feature_class":"P",
    "gn:feature_code":"PPL",
    "gn:name":"Ban Nagnao",
    "gn:population":0,
    "gn:timezone":"Asia/Vientiane",
    "iso:country":"LA",
    "name:und_x_variant":[
        "Ban Na Jao",
        "Ban Nagnao"
    ],
    "wof:name":"Ban Nagnao",
    "wof:placetype":"locality"
},
  "geometry": {"coordinates":[103.91151000000001,18.40143],"type":"Point"}
}