{
  "type": "Feature",
  "properties": {
    "gn:admin1_code":"15.0",
    "gn:asciiname":"Ban Nataphoy",
    "gn:country_code":"LA",
    "gn:dem":173,
    "gn:feature_class":"P",
    "gn:feature_code":"PPL",
    "gn:name":"Ban Nataphoy",
    "gn:population":0,
    "gn:timezone":"Asia/Vientiane",
    "iso:country":"LA",
    "name:und_x_variant":[
        "Ban Nata Pho\u00ef",
        "Ban Nataphoy"
    ],
    "wof:name":"Ban Nataphoy",
    "wof:placetype":"locality"
},
  "geometry": {"coordinates":[105.45959000000001,17.3068],"type":"Point"}
}