{
  "type": "Feature",
  "properties": {
    "gn:admin1_code":"3.0",
    "gn:asciiname":"Ban Phiangdan",
    "gn:country_code":"LA",
    "gn:dem":367,
    "gn:feature_class":"P",
    "gn:feature_code":"PPL",
    "gn:name":"Ban Phiangdan",
    "gn:population":0,
    "gn:timezone":"Asia/Vientiane",
    "iso:country":"LA",
    "name:lao_x_preferred":[
        "Ban Phiangdan"
    ],
    "wof:name":"Ban Phiangdan",
    "wof:placetype":"locality"
},
  "geometry": {"coordinates":[104.57733,20.02816],"type":"Point"}
}