{
  "type": "Feature",
  "properties": {
    "gn:admin1_code":"28.0",
    "gn:asciiname":"Ban Vangluang",
    "gn:country_code":"LA",
    "gn:dem":240,
    "gn:feature_class":"P",
    "gn:feature_code":"PPL",
    "gn:name":"Ban Vangluang",
    "gn:population":0,
    "gn:timezone":"Asia/Vientiane",
    "iso:country":"LA",
    "name:und_x_variant":[
        "Ban Van Luong",
        "Ban Vang Luong",
        "Ban Vangluang"
    ],
    "wof:name":"Ban Vangluang",
    "wof:placetype":"locality"
},
  "geometry": {"coordinates":[103.03484,18.57218],"type":"Point"}
}