{
  "type": "Feature",
  "properties": {
    "gn:admin1_code":"15.0",
    "gn:asciiname":"Ban Loboy",
    "gn:country_code":"LA",
    "gn:dem":420,
    "gn:feature_class":"P",
    "gn:feature_code":"PPL",
    "gn:name":"Ban Lob\u00f4y",
    "gn:population":0,
    "gn:timezone":"Asia/Vientiane",
    "iso:country":"LA",
    "name:und_x_variant":[
        "Ban Ta Boua La Boui",
        "Ban Laboy",
        "Ban Ta Boua",
        "Ban Lob\u00f4y"
    ],
    "wof:name":"Ban Loboy",
    "wof:placetype":"locality"
},
  "geometry": {"coordinates":[106.13333,17.21667],"type":"Point"}
}