{
  "type": "Feature",
  "properties": {
    "gn:admin1_code":"17.0",
    "gn:asciiname":"Ban Houay-Oun",
    "gn:cc2":"LA",
    "gn:country_code":"LA",
    "gn:dem":921,
    "gn:feature_class":"P",
    "gn:feature_code":"PPL",
    "gn:name":"Ban Houay-Oun",
    "gn:population":0,
    "gn:timezone":"Asia/Vientiane",
    "iso:country":"LA",
    "name:und_x_variant":[
        "Ban Houei Oun",
        "Ban Houay-Oun"
    ],
    "wof:name":"Ban Houay-Oun",
    "wof:placetype":"locality"
},
  "geometry": {"coordinates":[102.91667,20.18333],"type":"Point"}
}