{
  "type": "Feature",
  "properties": {
    "gn:admin1_code":"2.0",
    "gn:asciiname":"Ban Nongbung",
    "gn:country_code":"LA",
    "gn:dem":115,
    "gn:feature_class":"P",
    "gn:feature_code":"PPL",
    "gn:name":"Ban Nongbung",
    "gn:population":0,
    "gn:timezone":"Asia/Vientiane",
    "iso:country":"LA",
    "name:lao_x_preferred":[
        "Ban Nongbung"
    ],
    "wof:name":"Ban Nongbung",
    "wof:placetype":"locality"
},
  "geometry": {"coordinates":[105.96838,14.84228],"type":"Point"}
}